{
    "changed": "2022-11-02T20:50:18.919Z",
    "content": "Check:\n  all:\n    - comparator: ''\n      context: ''\n      date_component: year\n      name: $.xls\n      operator: date_equal_to\n      order: asc\n      ordering: --DECOD\n      prefix: 12345\n      suffix: 12345\n      target: --DECOD\n      value: ''\n      value_is_literal: true\n      within: --DECOD\nCore:\n  Id: ''\n  Version: '1'\n  Status: Draft\nDescription: ''\nMatch Datasets:\n  - Name: ALL\n    Is Relationship: true\n    Keys:\n      - --DECOD\nOperations:\n  - domain: ALL\n    group:\n      - --DECOD\n    id: $.xls\n    name: ''\n    operator: >-\n      dy\nOutcome:\n  Message: ''\n  Output Variables:\n    - $.xls\n    - $.xls\nRule Type: Record Data\nSensitivity: Record\nAuthorities:\n  - Organization: ''\n    Standards:\n      - Name: ''\n        Version: ''\n        References:\n          - Origin: ''\n            Rule Identifier:\n              Id: ''\n              Version: ''\n            Version: ''\n            Citations:\n              - Cited Guidance: ''\n                Document: ''\n                Item: ''\n                Section: ''\n      - Name: ''\n        Version: ''\n        References:\n          - Origin: ADaM Conformance Rules\n            Rule Identifier:\n              Id: ''\n            Version: '4.0'\n      - Name: ''\n        Version: ''\n        References:\n          - Origin: SDTM and SDTMIG Conformance Rules\n            Rule Identifier:\n              Id: ''\n              Version: 1 | 2 | 3\n            Version: '2.0'\n      - Name: ''\n        Version: ''\n        References:\n          - Origin: SEND Conformance Rules\n            Rule Identifier:\n              Id: ''\n            Version: '4.0'\nScope:\n  Data Structures:\n    Include: ALL\n  Datasets:\n    Exclude: All\n    Include: All\n  Domains:\n    Exclude:\n      - ALL\n    Include:\n      - ALL\n    include_split_datasets: true\n  Subclasses:\n    Exclude: ADVERSE EVENT\n    Include: ALL\n",
    "created": "2022-11-02T20:38:30.037Z",
    "creator": {
        "id": "e93e7485-8349-4001-98ff-fefb21b51b3e"
    },
    "json": {
        "Check": {
            "all": [
                {
                    "comparator": "",
                    "context": "",
                    "date_component": "year",
                    "name": "$.xls",
                    "operator": "date_equal_to",
                    "order": "asc",
                    "ordering": "--DECOD",
                    "prefix": 12345,
                    "suffix": 12345,
                    "target": "--DECOD",
                    "value": "",
                    "value_is_literal": true,
                    "within": "--DECOD"
                }
            ]
        },
        "Core": {
            "Id": "",
            "Version": "1",
            "Status": "Draft"
        },
        "Description": "",
        "Match_Datasets": [
            {
                "Name": "ALL",
                "Is_Relationship": true,
                "Keys": [
                    "--DECOD"
                ]
            }
        ],
        "Operations": [
            {
                "domain": "ALL",
                "group": [
                    "--DECOD"
                ],
                "id": "$.xls",
                "name": "",
                "operator": "dy"
            }
        ],
        "Outcome": {
            "Message": "",
            "Output_Variables": [
                "$.xls",
                "$.xls"
            ]
        },
        "Rule_Type": "Record Data",
        "Sensitivity": "Record",
        "Authorities": [
            {
                "Organization": "",
                "Standards": [
                    {
                        "Name": "",
                        "Version": "",
                        "References": [
                            {
                                "Origin": "",
                                "Rule_Identifier": {
                                    "Id": "",
                                    "Version": ""
                                },
                                "Version": "",
                                "Citations": [
                                    {
                                        "Cited_Guidance": "",
                                        "Document": "",
                                        "Item": "",
                                        "Section": ""
                                    }
                                ]
                            }
                        ]
                    },
                    {
                        "Name": "",
                        "Version": "",
                        "References": [
                            {
                                "Origin": "ADaM Conformance Rules",
                                "Rule_Identifier": {
                                    "Id": ""
                                },
                                "Version": "4.0"
                            }
                        ]
                    },
                    {
                        "Name": "",
                        "Version": "",
                        "References": [
                            {
                                "Origin": "SDTM and SDTMIG Conformance Rules",
                                "Rule_Identifier": {
                                    "Id": "",
                                    "Version": "1 | 2 | 3"
                                },
                                "Version": "2.0"
                            }
                        ]
                    },
                    {
                        "Name": "",
                        "Version": "",
                        "References": [
                            {
                                "Origin": "SEND Conformance Rules",
                                "Rule_Identifier": {
                                    "Id": ""
                                },
                                "Version": "4.0"
                            }
                        ]
                    }
                ]
            }
        ],
        "Scope": {
            "Data_Structures": {
                "Include": "ALL"
            },
            "Datasets": {
                "Exclude": "All",
                "Include": "All"
            },
            "Domains": {
                "Exclude": [
                    "ALL"
                ],
                "Include": [
                    "ALL"
                ],
                "include_split_datasets": true
            },
            "Subclasses": {
                "Exclude": "ADVERSE EVENT",
                "Include": "ALL"
            }
        }
    },
    "id": "34a19046-c758-44f9-9ec8-ec462df0f997"
}