{
    "changed": "2023-02-21T14:58:09.787Z",
    "content": "Executability: Fully Executable\r\nCheck:\r\n  all:\r\n    - name: variable_name #suitable for variable level metadatacheck, req wild card to select all charcter variable values -> way of aliasing all variables ?  this is a check across all char vars.\r\n      operator: longer_than\r\n      value: 200\r\n\r\nCore:\r\n  Id:\r\n  Version: '1'\r\n  Status: Draft\r\nDescription: Variable Value must not be greather than 200 characters long\r\nOutcome:\r\n  Message: Variable value is greather than 200 characters long\r\n  Output Variables:\r\n    - \r\nRule Type: Record Data\r\n  \r\nSensitivity: Record\r\nAuthorities:\r\n  - Organization: CDISC\r\n    Standards:\r\n      - Name:  ADaMIG\r\n        Version: '1.3'\r\n        References:\r\n          - Origin:  ADaM Conformance Rules\r\n            Rule Identifier:\r\n              Id: '17'\r\n              Version: '1'\r\n            Version: '4.0'\r\n            Citations:\r\n              - Cited Guidance: In developing naming conventions, sponsors should\r\n                  consider the requirements noted in the eCTD guidance document as\r\n                  well as the need to conform to the SAS Transport format requirements\r\n                  (e.g., the total length of the name cannot exceed 8 characters).\r\n                Document: Model v2.1\r\n                Item: '1'\r\n                Section: 4.1.2\r\n              - Cited Guidance: To ensure compliance with SAS Version 5 transport\r\n                  file format and Oracle constraints, all ADaM variable names must\r\n                  be no more than 8 characters in length, start with a letter (not\r\n                  underscore), and be composed only of letters (A-Z), underscore (_),\r\n                  and numerals (0-9). All ADaM variable labels must be no more than\r\n                  40 characters in length. All ADaM character variables must be no\r\n                  more than 200 characters in length.\r\n                Document: ADaM IG v1.3\r\n                Item: '1'\r\n                Section: 3.1.1\r\n\r\n      - Name:  ADaMIG\r\n        Version: '1.2'\r\n        References:\r\n          - Origin:  ADaM Conformance Rules\r\n            Rule Identifier:\r\n              Id: '17'\r\n              Version: '1'\r\n            Version: '4.0'\r\n            Citations:\r\n              - Cited Guidance: In developing naming conventions, sponsors should\r\n                  consider the requirements noted in the eCTD guidance document as\r\n                  well as the need to conform to the SAS Transport format requirements\r\n                  (e.g., the total length of the name cannot exceed 8 characters).\r\n                Document: Model v2.1\r\n                Item: '1'\r\n                Section: 4.1.2\r\n              - Cited Guidance: To ensure compliance with SAS Version 5 transport\r\n                  file format and Oracle constraints, all ADaM variable names must\r\n                  be no more than 8 characters in length, start with a letter (not\r\n                  underscore), and be composed only of letters (A-Z), underscore (_),\r\n                  and numerals (0-9). All ADaM variable labels must be no more than\r\n                  40 characters in length. All ADaM character variables must be no\r\n                  more than 200 characters in length.''\r\n                Document: ADaM IG v1.2\r\n                Item: '1'\r\n                Section: 3.1.1 \r\n\r\n      - Name:  ADaMIG\r\n        Version: '1.1'\r\n        References:\r\n          - Origin:  ADaM Conformance Rules\r\n            Rule Identifier:\r\n              Id: '17'\r\n              Version: '1'\r\n            Version: '4.0'\r\n            Citations:\r\n              - Cited Guidance: In developing naming conventions, sponsors should\r\n                  consider the requirements noted in the eCTD guidance document as\r\n                  well as the need to conform to the SAS Transport format requirements\r\n                  (e.g., the total length of the name cannot exceed 8 characters).\r\n                Document: Model v2.1\r\n                Item: '1'\r\n                Section: 4.1.2\r\n              - Cited Guidance: To ensure compliance with SAS Version 5 transport\r\n                  file format and Oracle constraints, all   ADaM variable names must\r\n                  be no more than 8 characters in length, start with a letter (not\r\n                  underscore), and be composed only of letters (A-Z), underscore (_),\r\n                  and numerals (0-9). All ADaM variable labels must be no more than\r\n                  40 characters in length. All ADaM character variables must be no\r\n                  more than 200 characters in length.\r\n                Document: ADaM IG v1.1\r\n                Item: '1'\r\n                Section: 3.1.1\r\n              - Cited Guidance: In developing naming conventions, sponsors should\r\n                  consider the requirements noted in the   eCTD guidance document\r\n                  as well as the need to conform to the SAS Transport format requirements\r\n                  (e.g., the total length of the name cannot exceed 8 characters).\r\n                Document: Model v2.1\r\n                Item: '1'\r\n                Section: 4.1.2\r\n\r\n      - Name:  ADaMIG\r\n        Version: '1.0'\r\n        References:\r\n          - Origin:  ADaM Conformance Rules\r\n            Rule Identifier:\r\n              Id: '17'\r\n              Version: '1'\r\n            Version: '4.0'\r\n            Citations:\r\n              - Cited Guidance: In developing naming conventions, sponsors should\r\n                  consider the requirements noted in the   eCTD guidance document\r\n                  as well as the need to conform to the SAS Transport format requirements\r\n                  (e.g., the total length of the name cannot exceed 8 characters).\r\n                Document: Model v2.1\r\n                Item: '1'\r\n                Section: 4.1.2\r\n              - Cited Guidance: To ensure compliance with SAS Transport file and Oracle\r\n                  constraints, all ADaM variable names must be no more than 8 characters\r\n                  in length, start with a letter (not underscore), and be comprised\r\n                  only of letters (A-Z), underscore (_), and numerals (0-9). All ADaM\r\n                  variable labels must be no more than 40 characters in length. All\r\n                  ADaM character variables must be no more than 200 characters in\r\n                  length\r\n                Document: ADaM IG v1.0\r\n                Item: 5 (General Variable Naming Conventions)':' ADaM IG v1.0, Section\r\n                  3, Item 5 (General Variable Naming Conventions)\r\n                Section: '3'\r\n  \r\nScope:\r\n  #Classes:\r\n    #Include:\r\n      #-  \r\n  Data Structures:\r\n    Include:\r\n       - ALL\r\n  Datasets:\r\n    Include:\r\n      - ALL\r\n  Domains:\r\n    Include:\r\n      - ALL\r\n    include_split_datasets: true \r\n  Subclasses:\r\n    Include:\r\n      - ALL\r\n    \r\n",
    "created": "2023-01-27T19:38:37.338Z",
    "creator": {
        "id": "57474fac-237e-4693-bb37-7826b02737da"
    },
    "json": {
        "Executability": "Fully Executable",
        "Check": {
            "all": [
                {
                    "name": "variable_name",
                    "operator": "longer_than",
                    "value": 200
                }
            ]
        },
        "Core": {
            "Id": null,
            "Version": "1",
            "Status": "Draft"
        },
        "Description": "Variable Value must not be greather than 200 characters long",
        "Outcome": {
            "Message": "Variable value is greather than 200 characters long",
            "Output_Variables": [
                null
            ]
        },
        "Sensitivity": "Record",
        "Authorities": [
            {
                "Organization": "CDISC",
                "Standards": [
                    {
                        "Name": "ADaMIG",
                        "Version": "1.3",
                        "References": [
                            {
                                "Origin": "ADaM Conformance Rules",
                                "Version": "4.0",
                                "Citations": [
                                    {
                                        "Document": "Model v2.1",
                                        "Item": "1",
                                        "Section": "4.1.2",
                                        "Cited_Guidance": "In developing naming conventions, sponsors should consider the requirements noted in the eCTD guidance document as well as the need to conform to the SAS Transport format requirements (e.g., the total length of the name cannot exceed 8 characters)."
                                    },
                                    {
                                        "Document": "ADaM IG v1.3",
                                        "Item": "1",
                                        "Section": "3.1.1",
                                        "Cited_Guidance": "To ensure compliance with SAS Version 5 transport file format and Oracle constraints, all ADaM variable names must be no more than 8 characters in length, start with a letter (not underscore), and be composed only of letters (A-Z), underscore (_), and numerals (0-9). All ADaM variable labels must be no more than 40 characters in length. All ADaM character variables must be no more than 200 characters in length."
                                    }
                                ],
                                "Rule_Identifier": {
                                    "Id": "17",
                                    "Version": "1"
                                }
                            }
                        ]
                    },
                    {
                        "Name": "ADaMIG",
                        "Version": "1.2",
                        "References": [
                            {
                                "Origin": "ADaM Conformance Rules",
                                "Version": "4.0",
                                "Citations": [
                                    {
                                        "Document": "Model v2.1",
                                        "Item": "1",
                                        "Section": "4.1.2",
                                        "Cited_Guidance": "In developing naming conventions, sponsors should consider the requirements noted in the eCTD guidance document as well as the need to conform to the SAS Transport format requirements (e.g., the total length of the name cannot exceed 8 characters)."
                                    },
                                    {
                                        "Document": "ADaM IG v1.2",
                                        "Item": "1",
                                        "Section": "3.1.1",
                                        "Cited_Guidance": "To ensure compliance with SAS Version 5 transport file format and Oracle constraints, all ADaM variable names must be no more than 8 characters in length, start with a letter (not underscore), and be composed only of letters (A-Z), underscore (_), and numerals (0-9). All ADaM variable labels must be no more than 40 characters in length. All ADaM character variables must be no more than 200 characters in length.''"
                                    }
                                ],
                                "Rule_Identifier": {
                                    "Id": "17",
                                    "Version": "1"
                                }
                            }
                        ]
                    },
                    {
                        "Name": "ADaMIG",
                        "Version": "1.1",
                        "References": [
                            {
                                "Origin": "ADaM Conformance Rules",
                                "Version": "4.0",
                                "Citations": [
                                    {
                                        "Document": "Model v2.1",
                                        "Item": "1",
                                        "Section": "4.1.2",
                                        "Cited_Guidance": "In developing naming conventions, sponsors should consider the requirements noted in the eCTD guidance document as well as the need to conform to the SAS Transport format requirements (e.g., the total length of the name cannot exceed 8 characters)."
                                    },
                                    {
                                        "Document": "ADaM IG v1.1",
                                        "Item": "1",
                                        "Section": "3.1.1",
                                        "Cited_Guidance": "To ensure compliance with SAS Version 5 transport file format and Oracle constraints, all   ADaM variable names must be no more than 8 characters in length, start with a letter (not underscore), and be composed only of letters (A-Z), underscore (_), and numerals (0-9). All ADaM variable labels must be no more than 40 characters in length. All ADaM character variables must be no more than 200 characters in length."
                                    },
                                    {
                                        "Document": "Model v2.1",
                                        "Item": "1",
                                        "Section": "4.1.2",
                                        "Cited_Guidance": "In developing naming conventions, sponsors should consider the requirements noted in the   eCTD guidance document as well as the need to conform to the SAS Transport format requirements (e.g., the total length of the name cannot exceed 8 characters)."
                                    }
                                ],
                                "Rule_Identifier": {
                                    "Id": "17",
                                    "Version": "1"
                                }
                            }
                        ]
                    },
                    {
                        "Name": "ADaMIG",
                        "Version": "1.0",
                        "References": [
                            {
                                "Origin": "ADaM Conformance Rules",
                                "Version": "4.0",
                                "Citations": [
                                    {
                                        "Document": "Model v2.1",
                                        "Item": "1",
                                        "Section": "4.1.2",
                                        "Cited_Guidance": "In developing naming conventions, sponsors should consider the requirements noted in the   eCTD guidance document as well as the need to conform to the SAS Transport format requirements (e.g., the total length of the name cannot exceed 8 characters)."
                                    },
                                    {
                                        "Document": "ADaM IG v1.0",
                                        "Item": "5 (General Variable Naming Conventions)':' ADaM IG v1.0, Section 3, Item 5 (General Variable Naming Conventions)",
                                        "Section": "3",
                                        "Cited_Guidance": "To ensure compliance with SAS Transport file and Oracle constraints, all ADaM variable names must be no more than 8 characters in length, start with a letter (not underscore), and be comprised only of letters (A-Z), underscore (_), and numerals (0-9). All ADaM variable labels must be no more than 40 characters in length. All ADaM character variables must be no more than 200 characters in length"
                                    }
                                ],
                                "Rule_Identifier": {
                                    "Id": "17",
                                    "Version": "1"
                                }
                            }
                        ]
                    }
                ]
            }
        ],
        "Scope": {
            "Datasets": {
                "Include": [
                    "ALL"
                ]
            },
            "Domains": {
                "Include": [
                    "ALL"
                ],
                "include_split_datasets": true
            },
            "Subclasses": {
                "Include": [
                    "ALL"
                ]
            },
            "Data_Structures": {
                "Include": [
                    "ALL"
                ]
            }
        },
        "Rule_Type": "Record Data"
    },
    "id": "1a4079d3-db1a-45a7-8915-e8f4d6ba7f28"
}