{
    "id": "6d8feb58-51b4-43ac-aed3-9a90b87bad78",
    "changed": "2023-02-09T16:58:17.460Z",
    "content": "Check:\n  all:\n    - any:\n        - name: --DOSE\n          operator: non_empty\n        - name: --DOSTOT\n          operator: non_empty\n        - name: --DOSTXT\n          operator: non_empty\n    - name: --DOSU\n      operator: empty\nCore:\n  Id: ABC\n  Version: '1'\n  Status: Draft\nDescription: Raise an error when --DOSU = null and (--DOSE ^= null or --DOSTOT\n  ^= null or --DOSTXT ^= null)\nOutcome:\n  Message: Missing value for --DOSU, when --DOSE, --DOSTXT or --DOSTOT is provided\n  Output Variables:\n    - --DOSE\n    - --DOSTXT\n    - --DOSU\nRule Type: Record Data\nSensitivity: Record\nAuthorities:\n  - Organization: CDISC\n    Standards:\n      - Name: SDTMIG\n        Version: '3.4'\n        References:\n          - Origin: SDTM and SDTMIG Conformance Rules\n            Rule Identifier:\n              Id: CG0114\n              Version: '1'\n            Version: '2.0'\n            Citations:\n              - Cited Guidance: Units for --DOSE, --DOSTOT, or --DOSTXT\n                Document: Model v2.0\n                Item: --DOSU\n                Section: Interventions\nScope:\n  Classes:\n    Include:\n      - INTERVENTIONS\n  Domains:\n    Include:\n      - ALL\n",
    "created": "2022-03-03T16:45:05Z",
    "creator": {
        "id": "e4113eae-4854-4831-a2f1-a0f1639da65a"
    },
    "json": {
        "Check": {
            "all": [
                {
                    "any": [
                        {
                            "name": "--DOSE",
                            "operator": "non_empty"
                        },
                        {
                            "name": "--DOSTOT",
                            "operator": "non_empty"
                        },
                        {
                            "name": "--DOSTXT",
                            "operator": "non_empty"
                        }
                    ]
                },
                {
                    "name": "--DOSU",
                    "operator": "empty"
                }
            ]
        },
        "Core": {
            "Id": "ABC",
            "Version": "1",
            "Status": "Draft"
        },
        "Description": "Raise an error when --DOSU = null and (--DOSE ^= null or --DOSTOT ^= null or --DOSTXT ^= null)",
        "Outcome": {
            "Message": "Missing value for --DOSU, when --DOSE, --DOSTXT or --DOSTOT is provided",
            "Output_Variables": [
                "--DOSE",
                "--DOSTXT",
                "--DOSU"
            ]
        },
        "Sensitivity": "Record",
        "Authorities": [
            {
                "Organization": "CDISC",
                "Standards": [
                    {
                        "Name": "SDTMIG",
                        "Version": "3.4",
                        "References": [
                            {
                                "Origin": "SDTM and SDTMIG Conformance Rules",
                                "Version": "2.0",
                                "Citations": [
                                    {
                                        "Document": "Model v2.0",
                                        "Item": "--DOSU",
                                        "Section": "Interventions",
                                        "Cited_Guidance": "Units for --DOSE, --DOSTOT, or --DOSTXT"
                                    }
                                ],
                                "Rule_Identifier": {
                                    "Id": "CG0114",
                                    "Version": "1"
                                }
                            }
                        ]
                    }
                ]
            }
        ],
        "Scope": {
            "Classes": {
                "Include": [
                    "INTERVENTIONS"
                ]
            },
            "Domains": {
                "Include": [
                    "ALL"
                ]
            }
        },
        "Rule_Type": "Record Data"
    }
}