{
    "changed": "2022-09-29T08:49:15.304Z",
    "content": "Check:\n  # 2022-09-29: Currently it is only checked whether the semicolon is correctly used as the separator\r\n  # TODO: values must be checked against [SPEC] codelist, which requires use of the CDISC-Library API\r\n  all:\n    - name: PPSPEC\n      operator: not_matches_regex\n      value: ^[A-Za-z\\s,]+(;[A-Za-z\\s,]+)*$\nCore:\n  Id: CDISC.SENDIG.282\n  Version: '1'\n  Status: Draft\nDescription: If multiple specimen types are used for a calculation (e.g., serum and\n  urine for creatinine clearance), then this field should be populated with values\n  from the (SPEC) Controlled Terminology codelist delimited by a semicolon.\nOutcome:\n  Message: The multiple specimens are not correctly separated by a semicolon\nRule Type: Record Data\nSensitivity: Record\nAuthorities:\n  - Organization: CDISC\n    Standards:\n      - Name: SENDIG\n        Version: '3.1'\n        References:\n          - Origin: SDTM and SENDIG Conformance Rules\n            Rule Identifier:\n              Id: '282'\n              Version: '1'\n            Version: '2.0'\n            Citations:\n              - Cited Guidance: 'PPSPEC Defines the type of specimen used for a measurement.\n                  Examples SERUM, PLASMA, URINE. If multiple specimen types are used\n                  for a calculation (e.g., serum and urine for creatinine clearance),\n                  then refer to Section 4.3.6.2 for guidance on how to populate. '\n                Document: IG v3.1\n                Section: 6.3.12\nScope:\n  Classes:\n    Include:\n      - FINDINGS\n  Domains:\n    Include:\n      - PP\n",
    "created": "2022-09-29T08:13:33.941Z",
    "creator": {
        "id": "dc8bf014-df32-4631-8684-9a09a16c5071"
    },
    "json": {
        "Check": {
            "all": [
                {
                    "name": "PPSPEC",
                    "operator": "not_matches_regex",
                    "value": "^[A-Za-z\\s,]+(;[A-Za-z\\s,]+)*$"
                }
            ]
        },
        "Core": {
            "Id": "CDISC.SENDIG.282",
            "Version": "1",
            "Status": "Draft"
        },
        "Description": "If multiple specimen types are used for a calculation (e.g., serum and urine for creatinine clearance), then this field should be populated with values from the (SPEC) Controlled Terminology codelist delimited by a semicolon.",
        "Outcome": {
            "Message": "The multiple specimens are not correctly separated by a semicolon"
        },
        "Rule_Type": "Record Data",
        "Sensitivity": "Record",
        "Authorities": [
            {
                "Organization": "CDISC",
                "Standards": [
                    {
                        "Name": "SENDIG",
                        "Version": "3.1",
                        "References": [
                            {
                                "Origin": "SDTM and SENDIG Conformance Rules",
                                "Rule_Identifier": {
                                    "Id": "282",
                                    "Version": "1"
                                },
                                "Version": "2.0",
                                "Citations": [
                                    {
                                        "Cited_Guidance": "PPSPEC Defines the type of specimen used for a measurement. Examples SERUM, PLASMA, URINE. If multiple specimen types are used for a calculation (e.g., serum and urine for creatinine clearance), then refer to Section 4.3.6.2 for guidance on how to populate. ",
                                        "Document": "IG v3.1",
                                        "Section": "6.3.12"
                                    }
                                ]
                            }
                        ]
                    }
                ]
            }
        ],
        "Scope": {
            "Classes": {
                "Include": [
                    "FINDINGS"
                ]
            },
            "Domains": {
                "Include": [
                    "PP"
                ]
            }
        }
    },
    "id": "a03b7a3c-a5f3-4f8c-a73e-b0079197dbbc"
}