{
    "changed": "2022-11-08T14:00:12.229Z",
    "content": "Check:\n  all:\n    - name: CVTESTCD\n      operator: is_not_unique_set\n      value:\n        - USUBJID\n        - CVDTC\n    - name: CVTESTCD\n      operator: is_not_unique_set\n      value:\n        - USUBJID\n        - CVDTC\n        - CVSTINT\nCore:\n  Id: CDISC.SENDIG.336\n  Version: '1'\n  Status: Draft\nDescription: Raise an error when there is more than one record present for any particular\n  cardiovascular test for a subject and measurement date/time or evaluation interval.\nOutcome:\n  Message: The cardiovascular test is not unique for this subject and measurement\n    datetime or evaluation interval.\n  Output Variables:\n    - USUBJID\n    - CVTESTCD\n    - CVDTC\nRule Type: Record Data\nSensitivity: Record\nAuthorities:\n  - Organization: CDISC\n    Standards:\n      - Name: SENDIG\n        Version: '3.1'\n        References:\n          - Origin: SDTM and SENDIG Conformance Rules\n            Rule Identifier:\n              Id: '336'\n              Version: '1'\n            Version: '2.0'\n            Citations:\n              - Cited Guidance: One record per test per observation time or evaluation\n                  interval per subject\n                Document: SENDIG v3.1\n                Section: 6.3.17\nScope:\n  Classes:\n    Include:\n      - FINDINGS\n  Domains:\n    Include:\n      - CV\n",
    "created": "2022-11-08T07:31:09.395Z",
    "creator": {
        "id": "dc8bf014-df32-4631-8684-9a09a16c5071"
    },
    "json": {
        "Check": {
            "all": [
                {
                    "name": "CVTESTCD",
                    "operator": "is_not_unique_set",
                    "value": [
                        "USUBJID",
                        "CVDTC"
                    ]
                },
                {
                    "name": "CVTESTCD",
                    "operator": "is_not_unique_set",
                    "value": [
                        "USUBJID",
                        "CVDTC",
                        "CVSTINT"
                    ]
                }
            ]
        },
        "Core": {
            "Id": "CDISC.SENDIG.336",
            "Version": "1",
            "Status": "Draft"
        },
        "Description": "Raise an error when there is more than one record present for any particular cardiovascular test for a subject and measurement date/time or evaluation interval.",
        "Outcome": {
            "Message": "The cardiovascular test is not unique for this subject and measurement datetime or evaluation interval.",
            "Output_Variables": [
                "USUBJID",
                "CVTESTCD",
                "CVDTC"
            ]
        },
        "Rule_Type": "Record Data",
        "Sensitivity": "Record",
        "Authorities": [
            {
                "Organization": "CDISC",
                "Standards": [
                    {
                        "Name": "SENDIG",
                        "Version": "3.1",
                        "References": [
                            {
                                "Origin": "SDTM and SENDIG Conformance Rules",
                                "Rule_Identifier": {
                                    "Id": "336",
                                    "Version": "1"
                                },
                                "Version": "2.0",
                                "Citations": [
                                    {
                                        "Cited_Guidance": "One record per test per observation time or evaluation interval per subject",
                                        "Document": "SENDIG v3.1",
                                        "Section": "6.3.17"
                                    }
                                ]
                            }
                        ]
                    }
                ]
            }
        ],
        "Scope": {
            "Classes": {
                "Include": [
                    "FINDINGS"
                ]
            },
            "Domains": {
                "Include": [
                    "CV"
                ]
            }
        }
    },
    "id": "90964885-02c2-4ac3-99bf-fb2e78b87ec0"
}