{
    "changed": "2022-09-15T14:24:57.984Z",
    "content": "Check:\n  all:\n    - name: AGETXT\n      operator: non_empty\n    - any:\n        - name: BRTHDTC\n          operator: non_empty\n        - name: AGE\n          operator: non_empty\nCore:\n  Id: CDISC.SENDIG.103\n  Version: '1'\n  Status: Draft\nDescription: AGETXT is used to present the age range in situations where the exact\n  birthdate is not known.  If AGETXT is included both BRTHDTC and AGE should not be\n  populated.\nOutcome:\n  Message: AGETXT is populated, so neither BRTHDTC nor AGE may be populated\n  Output Variables:\n    - USUBJID\n    - AGETXT\n    - BRTHDTC\n    - AGE\nRule Type: Record Data\nSensitivity: Study\nAuthorities:\n  - Organization: CDISC\n    Standards:\n      - Name: SENDIG\n        Version: '3.1'\n        References:\n          - Origin: SDTM and SENDIG Conformance Rules\n            Rule Identifier:\n              Id: '103'\n              Version: '1'\n            Version: '2.0'\n            Citations:\n              - Cited Guidance: AGETXT is used to present the age range in situations\n                  where the exact birthdate is not known.  If AGETXT is included both\n                  BRTHDTC and AGE should not be populated.\n                Document: IG v3.1\n                Item: Specification\n                Section: 5.1.1\nScope:\n  Classes:\n    Include:\n      - SPECIAL-PURPOSE\n  Domains:\n    Include:\n      - DM\n",
    "created": "2022-09-15T14:24:57.984Z",
    "creator": {
        "id": "dc8bf014-df32-4631-8684-9a09a16c5071"
    },
    "json": {
        "Check": {
            "all": [
                {
                    "name": "AGETXT",
                    "operator": "non_empty"
                },
                {
                    "any": [
                        {
                            "name": "BRTHDTC",
                            "operator": "non_empty"
                        },
                        {
                            "name": "AGE",
                            "operator": "non_empty"
                        }
                    ]
                }
            ]
        },
        "Core": {
            "Id": "CDISC.SENDIG.103",
            "Version": "1",
            "Status": "Draft"
        },
        "Description": "AGETXT is used to present the age range in situations where the exact birthdate is not known.  If AGETXT is included both BRTHDTC and AGE should not be populated.",
        "Outcome": {
            "Message": "AGETXT is populated, so neither BRTHDTC nor AGE may be populated",
            "Output_Variables": [
                "USUBJID",
                "AGETXT",
                "BRTHDTC",
                "AGE"
            ]
        },
        "Rule_Type": "Record Data",
        "Sensitivity": "Study",
        "Authorities": [
            {
                "Organization": "CDISC",
                "Standards": [
                    {
                        "Name": "SENDIG",
                        "Version": "3.1",
                        "References": [
                            {
                                "Origin": "SDTM and SENDIG Conformance Rules",
                                "Rule_Identifier": {
                                    "Id": "103",
                                    "Version": "1"
                                },
                                "Version": "2.0",
                                "Citations": [
                                    {
                                        "Cited_Guidance": "AGETXT is used to present the age range in situations where the exact birthdate is not known.  If AGETXT is included both BRTHDTC and AGE should not be populated.",
                                        "Document": "IG v3.1",
                                        "Item": "Specification",
                                        "Section": "5.1.1"
                                    }
                                ]
                            }
                        ]
                    }
                ]
            }
        ],
        "Scope": {
            "Classes": {
                "Include": [
                    "SPECIAL-PURPOSE"
                ]
            },
            "Domains": {
                "Include": [
                    "DM"
                ]
            }
        }
    },
    "id": "e4b976f4-5555-4d35-8ad2-28d4cdc3ed59"
}