{
    "changed": "2022-09-16T08:57:15.671Z",
    "content": "Check:\n  all:\n    - name: IDVAR\n      operator: empty\n    - name: IDVARVAL\n      operator: non_empty\nCore:\n  Id: CDISC.SENDIG.118\n  Version: '1'\n  Status: Draft\nDescription: IDVAR must be specified.\nOutcome:\n  Message: IDVARVAL may not be populated as IDVAR is null\n  Output Variables:\n    - IDVARVAL\n    - IDVAR\nRule Type: Record Data\nSensitivity: Record\nAuthorities:\n  - Organization: CDISC\n    Standards:\n      - Name: SENDIG\n        Version: '3.1'\n        References:\n          - Origin: SDTM and SENDIG Conformance Rules\n            Rule Identifier:\n              Id: '118'\n              Version: '1'\n            Version: '2.0'\n            Citations:\n              - Cited Guidance: IDVARVAL is used only when individual comments are\n                  related to domain records. Cannot be populated if IDVAR is null.\n                Document: IG v3.1\n                Item: Specification\n                Section: 5.2.2.1\nScope:\n  Classes:\n    Include:\n      - SPECIAL-PURPOSE\n  Domains:\n    Include:\n      - CO\n",
    "created": "2022-09-16T08:57:15.671Z",
    "creator": {
        "id": "dc8bf014-df32-4631-8684-9a09a16c5071"
    },
    "json": {
        "Check": {
            "all": [
                {
                    "name": "IDVAR",
                    "operator": "empty"
                },
                {
                    "name": "IDVARVAL",
                    "operator": "non_empty"
                }
            ]
        },
        "Core": {
            "Id": "CDISC.SENDIG.118",
            "Version": "1",
            "Status": "Draft"
        },
        "Description": "IDVAR must be specified.",
        "Outcome": {
            "Message": "IDVARVAL may not be populated as IDVAR is null",
            "Output_Variables": [
                "IDVARVAL",
                "IDVAR"
            ]
        },
        "Rule_Type": "Record Data",
        "Sensitivity": "Record",
        "Authorities": [
            {
                "Organization": "CDISC",
                "Standards": [
                    {
                        "Name": "SENDIG",
                        "Version": "3.1",
                        "References": [
                            {
                                "Origin": "SDTM and SENDIG Conformance Rules",
                                "Rule_Identifier": {
                                    "Id": "118",
                                    "Version": "1"
                                },
                                "Version": "2.0",
                                "Citations": [
                                    {
                                        "Cited_Guidance": "IDVARVAL is used only when individual comments are related to domain records. Cannot be populated if IDVAR is null.",
                                        "Document": "IG v3.1",
                                        "Item": "Specification",
                                        "Section": "5.2.2.1"
                                    }
                                ]
                            }
                        ]
                    }
                ]
            }
        ],
        "Scope": {
            "Classes": {
                "Include": [
                    "SPECIAL-PURPOSE"
                ]
            },
            "Domains": {
                "Include": [
                    "CO"
                ]
            }
        }
    },
    "id": "fb144c37-66ea-4d8c-bfe6-6f8906e83b59"
}