{
    "changed": "2022-09-12T13:53:52.983Z",
    "content": "Check:\n  any:\n    - name: --CAT\n      operator: non_empty\n    - all:\n        - name: --DECOD\n          operator: non_empty\n        - name: --CAT\n          operator: equal_to\n          value: --DECOD\n    - all:\n        - name: --BODSYS\n          operator: non_empty\n        - name: --CAT\n          operator: equal_to\n          value: --BODSYS\nCore:\n  Id: CDISC.SENDIG.47\n  Version: '1'\n  Status: Draft\nDescription: Trigger error when --CAT is not null and --CAT is equal to --DECOD or\n  --SCAT is equal to -BODSYS\nOutcome:\n  Message: --CAT is equal to --DECOD\n  Output Variables:\n    - --CAT\n    - --DECOD\n    - --BODSYS\nRule Type: Record Data\nSensitivity: Record\nAuthorities:\n  - Organization: CDISC\n    Standards:\n      - Name: SENDIG\n        Version: '3.1'\n        References:\n          - Origin: SDTM and SENDIG Conformance Rules\n            Rule Identifier:\n              Id: '47'\n              Version: '1'\n            Version: '2.0'\n            Citations:\n              - Cited Guidance: Values for --CAT and --SCAT should not be redundant\n                  with the domain or dictionary classification provided by --DECOD\n                  and --BODSYS.\n                Document: IG v.3.1\n                Section: 4.2.6\nScope:\n  Classes:\n    Include:\n      - ALL\n  Domains:\n    Include:\n      - ALL\n",
    "created": "2022-09-11T17:21:04.986Z",
    "creator": {
        "id": "dc8bf014-df32-4631-8684-9a09a16c5071"
    },
    "json": {
        "Check": {
            "any": [
                {
                    "name": "--CAT",
                    "operator": "non_empty"
                },
                {
                    "all": [
                        {
                            "name": "--DECOD",
                            "operator": "non_empty"
                        },
                        {
                            "name": "--CAT",
                            "operator": "equal_to",
                            "value": "--DECOD"
                        }
                    ]
                },
                {
                    "all": [
                        {
                            "name": "--BODSYS",
                            "operator": "non_empty"
                        },
                        {
                            "name": "--CAT",
                            "operator": "equal_to",
                            "value": "--BODSYS"
                        }
                    ]
                }
            ]
        },
        "Core": {
            "Id": "CDISC.SENDIG.47",
            "Version": "1",
            "Status": "Draft"
        },
        "Description": "Trigger error when --CAT is not null and --CAT is equal to --DECOD or --SCAT is equal to -BODSYS",
        "Outcome": {
            "Message": "--CAT is equal to --DECOD",
            "Output_Variables": [
                "--CAT",
                "--DECOD",
                "--BODSYS"
            ]
        },
        "Rule_Type": "Record Data",
        "Sensitivity": "Record",
        "Authorities": [
            {
                "Organization": "CDISC",
                "Standards": [
                    {
                        "Name": "SENDIG",
                        "Version": "3.1",
                        "References": [
                            {
                                "Origin": "SDTM and SENDIG Conformance Rules",
                                "Rule_Identifier": {
                                    "Id": "47",
                                    "Version": "1"
                                },
                                "Version": "2.0",
                                "Citations": [
                                    {
                                        "Cited_Guidance": "Values for --CAT and --SCAT should not be redundant with the domain or dictionary classification provided by --DECOD and --BODSYS.",
                                        "Document": "IG v.3.1",
                                        "Section": "4.2.6"
                                    }
                                ]
                            }
                        ]
                    }
                ]
            }
        ],
        "Scope": {
            "Classes": {
                "Include": [
                    "ALL"
                ]
            },
            "Domains": {
                "Include": [
                    "ALL"
                ]
            }
        }
    },
    "id": "ba4318bb-53d0-46a1-94cd-604e4e8104ac"
}