{
    "changed": "2022-09-16T11:54:46.088Z",
    "content": "Check:\n  all:\n    - name: POOLID\n      operator: non_empty\n    - name: USUBJID\n      operator: non_empty\nCore:\n  Id: CDISC.SENDIG.132\n  Version: '1'\n  Status: Draft\nDescription: Raise an error when both USUBJID and POOLID are empty\nOutcome:\n  Message: When POOLID is populated, USUBJID may not be populated\n  Output Variables:\n    - USUBJID\n    - POOLID\nRule Type: Record Data\nSensitivity: Record\nAuthorities:\n  - Organization: CDISC\n    Standards:\n      - Name: SENDIG\n        Version: '3.1'\n        References:\n          - Origin: SDTM and SENDIG Conformance Rules\n            Rule Identifier:\n              Id: '132'\n              Version: '1'\n            Version: '2.0'\n            Citations:\n              - Cited Guidance: POOLID and USUBJID are mutually exclusive. When POOLID\n                  is used, USUBJID will be null and if a USUBJID is recorded, the\n                  POOLID will be null.\n                Document: IG v3.1\n                Section: '8.5'\nScope:\n  Classes:\n    Include:\n      - INTERVENTIONS\n      - FINDINGS\n  Domains:\n    Include:\n      - ALL\n",
    "created": "2022-09-16T11:50:19.342Z",
    "creator": {
        "id": "dc8bf014-df32-4631-8684-9a09a16c5071"
    },
    "json": {
        "Check": {
            "all": [
                {
                    "name": "POOLID",
                    "operator": "non_empty"
                },
                {
                    "name": "USUBJID",
                    "operator": "non_empty"
                }
            ]
        },
        "Core": {
            "Id": "CDISC.SENDIG.132",
            "Version": "1",
            "Status": "Draft"
        },
        "Description": "Raise an error when both USUBJID and POOLID are empty",
        "Outcome": {
            "Message": "When POOLID is populated, USUBJID may not be populated",
            "Output_Variables": [
                "USUBJID",
                "POOLID"
            ]
        },
        "Rule_Type": "Record Data",
        "Sensitivity": "Record",
        "Authorities": [
            {
                "Organization": "CDISC",
                "Standards": [
                    {
                        "Name": "SENDIG",
                        "Version": "3.1",
                        "References": [
                            {
                                "Origin": "SDTM and SENDIG Conformance Rules",
                                "Rule_Identifier": {
                                    "Id": "132",
                                    "Version": "1"
                                },
                                "Version": "2.0",
                                "Citations": [
                                    {
                                        "Cited_Guidance": "POOLID and USUBJID are mutually exclusive. When POOLID is used, USUBJID will be null and if a USUBJID is recorded, the POOLID will be null.",
                                        "Document": "IG v3.1",
                                        "Section": "8.5"
                                    }
                                ]
                            }
                        ]
                    }
                ]
            }
        ],
        "Scope": {
            "Classes": {
                "Include": [
                    "INTERVENTIONS",
                    "FINDINGS"
                ]
            },
            "Domains": {
                "Include": [
                    "ALL"
                ]
            }
        }
    },
    "id": "4ac5e2c1-ef36-455a-8068-93308f68a9d5"
}