{
    "changed": "2022-09-22T09:31:56.252Z",
    "content": "Check:\n  all:\n    - name: ETCD\n      operator: exists\n    - name: ELEMENT\n      operator: exists\n    - any:\n        - name: ETCD\n          operator: is_not_unique_relationship\n          value: ELEMENT\n        - name: ELEMENT\n          operator: is_not_unique_relationship\n          value: ETCD\nCore:\n  Id: CDISC.SENDIG.213\n  Version: '1'\n  Status: Draft\nDescription: ETCD and ELEMENT have a one-to-one relationship\nOutcome:\n  Message: ELEMENT and ETCD do not have a one-to-one relationship.\n  Output Variables:\n    - ETCD\n    - ELEMENT\nRule Type: Record Data\nSensitivity: Record\nAuthorities:\n  - Organization: CDISC\n    Standards:\n      - Name: SENDIG\n        Version: '3.1'\n        References:\n          - Origin: SDTM and SENDIG Conformance Rules\n            Rule Identifier:\n              Id: '213'\n              Version: '1'\n            Version: '2.0'\n            Citations:\n              - Cited Guidance: Elements with different start and end rules are different\n                  Elements and must be represented as unique values in ELEMENT and\n                  ETCD.\n                Document: IG v3.1\n                Item: Specification\n                Section: 7.2.1.1\nScope:\n  Classes:\n    Include:\n      - TRIAL DESIGN\n  Domains:\n    Include:\n      - TE\n",
    "created": "2022-09-22T09:31:56.252Z",
    "creator": {
        "id": "dc8bf014-df32-4631-8684-9a09a16c5071"
    },
    "json": {
        "Check": {
            "all": [
                {
                    "name": "ETCD",
                    "operator": "exists"
                },
                {
                    "name": "ELEMENT",
                    "operator": "exists"
                },
                {
                    "any": [
                        {
                            "name": "ETCD",
                            "operator": "is_not_unique_relationship",
                            "value": "ELEMENT"
                        },
                        {
                            "name": "ELEMENT",
                            "operator": "is_not_unique_relationship",
                            "value": "ETCD"
                        }
                    ]
                }
            ]
        },
        "Core": {
            "Id": "CDISC.SENDIG.213",
            "Version": "1",
            "Status": "Draft"
        },
        "Description": "ETCD and ELEMENT have a one-to-one relationship",
        "Outcome": {
            "Message": "ELEMENT and ETCD do not have a one-to-one relationship.",
            "Output_Variables": [
                "ETCD",
                "ELEMENT"
            ]
        },
        "Rule_Type": "Record Data",
        "Sensitivity": "Record",
        "Authorities": [
            {
                "Organization": "CDISC",
                "Standards": [
                    {
                        "Name": "SENDIG",
                        "Version": "3.1",
                        "References": [
                            {
                                "Origin": "SDTM and SENDIG Conformance Rules",
                                "Rule_Identifier": {
                                    "Id": "213",
                                    "Version": "1"
                                },
                                "Version": "2.0",
                                "Citations": [
                                    {
                                        "Cited_Guidance": "Elements with different start and end rules are different Elements and must be represented as unique values in ELEMENT and ETCD.",
                                        "Document": "IG v3.1",
                                        "Item": "Specification",
                                        "Section": "7.2.1.1"
                                    }
                                ]
                            }
                        ]
                    }
                ]
            }
        ],
        "Scope": {
            "Classes": {
                "Include": [
                    "TRIAL DESIGN"
                ]
            },
            "Domains": {
                "Include": [
                    "TE"
                ]
            }
        }
    },
    "id": "986a1f42-9704-400a-9629-5dec7ca9fabc"
}