{
    "id": "8d5482f5-b941-49bd-8509-8408a3f9648f",
    "changed": "2022-10-19T14:56:04.531Z",
    "content": "Check:\n  all:\n    - name: SESEQ\n      operator: target_is_sorted_by\n      value:\n        - SESTDTC\n        - USUBJID\nCore:\n  Id: CDISC.SENDIG.130\n  Version: '1'\n  Status: Draft\nDescription: Trigger error when the order of SESEQ is not chronologically (based on\n  SESTDTC) within USUBJID\nOutcome:\n  Message: SESEQ is not chronologically (based on SESTDTC) within USUBJID\n  Output Variables:\n    - USUBJID\n#    - SESEQ\r\n    - SESTDTC\n\nRule Type: Record Data\nSensitivity: Record\nAuthorities:\n  - Organization: CDISC\n    Standards:\n      - Name: SENDIG\n        Version: '3.1'\n        References:\n          - Origin: SDTM and SENDIG Conformance Rules\n            Rule Identifier:\n              Id: '130'\n              Version: '1'\n            Version: '2.0'\n            Citations:\n              - Cited Guidance: The values of SESTDTC provide the chronological order\n                  of the actual subject Elements.  SESEQ should be assigned to be\n                  consistent with the chronological order.\n                Document: IG v3.1\n                Item: Specification\n                Section: 5.3.1.1\nScope:\n  Classes:\n    Include:\n      - SPECIAL-PURPOSE\n  Domains:\n    Include:\n      - SE\n",
    "created": "2021-11-06T09:08:48Z",
    "creator": {
        "id": "ff471ff8-f131-4cf5-9712-c79cce6301a1"
    },
    "json": {
        "Check": {
            "all": [
                {
                    "name": "SESEQ",
                    "operator": "target_is_sorted_by",
                    "value": [
                        "SESTDTC",
                        "USUBJID"
                    ]
                }
            ]
        },
        "Core": {
            "Id": "CDISC.SENDIG.130",
            "Version": "1",
            "Status": "Draft"
        },
        "Description": "Trigger error when the order of SESEQ is not chronologically (based on SESTDTC) within USUBJID",
        "Outcome": {
            "Message": "SESEQ is not chronologically (based on SESTDTC) within USUBJID",
            "Output_Variables": [
                "USUBJID",
                "SESTDTC"
            ]
        },
        "Rule_Type": "Record Data",
        "Sensitivity": "Record",
        "Authorities": [
            {
                "Organization": "CDISC",
                "Standards": [
                    {
                        "Name": "SENDIG",
                        "Version": "3.1",
                        "References": [
                            {
                                "Origin": "SDTM and SENDIG Conformance Rules",
                                "Rule_Identifier": {
                                    "Id": "130",
                                    "Version": "1"
                                },
                                "Version": "2.0",
                                "Citations": [
                                    {
                                        "Cited_Guidance": "The values of SESTDTC provide the chronological order of the actual subject Elements.  SESEQ should be assigned to be consistent with the chronological order.",
                                        "Document": "IG v3.1",
                                        "Item": "Specification",
                                        "Section": "5.3.1.1"
                                    }
                                ]
                            }
                        ]
                    }
                ]
            }
        ],
        "Scope": {
            "Classes": {
                "Include": [
                    "SPECIAL-PURPOSE"
                ]
            },
            "Domains": {
                "Include": [
                    "SE"
                ]
            }
        }
    }
}