{
    "changed": "2022-09-30T12:50:29.454Z",
    "content": "Check:\n  all:\n    - name: USUBJID\n      operator: non_empty\n    - name: COSEQ\n      operator: is_not_unique_set\n      value: USUBJID\nCore:\n  Id: CDISC.SENDIG.311\n  Version: '1'\n  Status: Draft\nDescription: Raise an error when COSEQ is not unique within USUBJID or within POOLID\nOutcome:\n  Message: The value of COSEQ is not unique within USUBJID\nRule Type: Record Data\nSensitivity: Record\nAuthorities:\n  - Organization: CDISC\n    Standards:\n      - Name: SENDIG\n        Version: '3.1'\n        References:\n          - Origin: SDTM and SENDIG Conformance Rules\n            Rule Identifier:\n              Id: '311'\n              Version: '1'\n            Version: '2.0'\n            Citations:\n              - Cited Guidance: The sequence number must be unique for each record\n                  within a USUBJID or POOLID, whichever applies for the record.\n                Document: IG v3.1\n                Section: '5.2'\nScope:\n  Classes:\n    Include:\n      - SPECIAL-PURPOSE\n  Domains:\n    Include:\n      - CO\n",
    "created": "2022-09-30T12:02:23.122Z",
    "creator": {
        "id": "dc8bf014-df32-4631-8684-9a09a16c5071"
    },
    "json": {
        "Check": {
            "all": [
                {
                    "name": "USUBJID",
                    "operator": "non_empty"
                },
                {
                    "name": "COSEQ",
                    "operator": "is_not_unique_set",
                    "value": "USUBJID"
                }
            ]
        },
        "Core": {
            "Id": "CDISC.SENDIG.311",
            "Version": "1",
            "Status": "Draft"
        },
        "Description": "Raise an error when COSEQ is not unique within USUBJID or within POOLID",
        "Outcome": {
            "Message": "The value of COSEQ is not unique within USUBJID"
        },
        "Rule_Type": "Record Data",
        "Sensitivity": "Record",
        "Authorities": [
            {
                "Organization": "CDISC",
                "Standards": [
                    {
                        "Name": "SENDIG",
                        "Version": "3.1",
                        "References": [
                            {
                                "Origin": "SDTM and SENDIG Conformance Rules",
                                "Rule_Identifier": {
                                    "Id": "311",
                                    "Version": "1"
                                },
                                "Version": "2.0",
                                "Citations": [
                                    {
                                        "Cited_Guidance": "The sequence number must be unique for each record within a USUBJID or POOLID, whichever applies for the record.",
                                        "Document": "IG v3.1",
                                        "Section": "5.2"
                                    }
                                ]
                            }
                        ]
                    }
                ]
            }
        ],
        "Scope": {
            "Classes": {
                "Include": [
                    "SPECIAL-PURPOSE"
                ]
            },
            "Domains": {
                "Include": [
                    "CO"
                ]
            }
        }
    },
    "id": "90353001-7abc-44dd-b3ba-6d2179fb37bf"
}