{
    "changed": "2022-09-13T08:32:18.676Z",
    "content": "Check:\n  all:\n    - name: --RFTDTC\n      operator: exists\n    - name: --TPTREF\n      operator: exists\n    - name: --RFTDTC\n      operator: non_empty\n    - name: --TPTREF\n      operator: empty\nCore:\n  Id: CDISC.SENDIG.63\n  Version: '1'\n  Status: Draft\nDescription: Trigger error when --RFTDTC is populated and --TPTREF = null\nOutcome:\n  Message: --TPTREF must be populated when --RFTDTC is populated\n  Output Variables:\n    - --RFTDTC\n    - --TPTREF\nRule Type: Record Data\nSensitivity: Record\nAuthorities:\n  - Organization: CDISC\n    Standards:\n      - Name: SENDIG\n        Version: '3.1'\n        References:\n          - Origin: SDTM and SENDIG Conformance Rules\n            Rule Identifier:\n              Id: '63'\n              Version: '1'\n            Version: '2.0'\n            Citations:\n              - Cited Guidance: Since the --RFTDTC represents the actual date/time\n                  of the fixed reference point (--TPTREF), the --TPTREF should be\n                  provided whenever --RFTDTC is populated.\n                Document: IG v3.1\n                Section: 4.4.7.2.2\nScope:\n  Classes:\n    Include:\n      - ALL\n  Domains:\n    Include:\n      - ALL\n",
    "created": "2022-09-13T08:27:26.143Z",
    "creator": {
        "id": "dc8bf014-df32-4631-8684-9a09a16c5071"
    },
    "json": {
        "Check": {
            "all": [
                {
                    "name": "--RFTDTC",
                    "operator": "exists"
                },
                {
                    "name": "--TPTREF",
                    "operator": "exists"
                },
                {
                    "name": "--RFTDTC",
                    "operator": "non_empty"
                },
                {
                    "name": "--TPTREF",
                    "operator": "empty"
                }
            ]
        },
        "Core": {
            "Id": "CDISC.SENDIG.63",
            "Version": "1",
            "Status": "Draft"
        },
        "Description": "Trigger error when --RFTDTC is populated and --TPTREF = null",
        "Outcome": {
            "Message": "--TPTREF must be populated when --RFTDTC is populated",
            "Output_Variables": [
                "--RFTDTC",
                "--TPTREF"
            ]
        },
        "Rule_Type": "Record Data",
        "Sensitivity": "Record",
        "Authorities": [
            {
                "Organization": "CDISC",
                "Standards": [
                    {
                        "Name": "SENDIG",
                        "Version": "3.1",
                        "References": [
                            {
                                "Origin": "SDTM and SENDIG Conformance Rules",
                                "Rule_Identifier": {
                                    "Id": "63",
                                    "Version": "1"
                                },
                                "Version": "2.0",
                                "Citations": [
                                    {
                                        "Cited_Guidance": "Since the --RFTDTC represents the actual date/time of the fixed reference point (--TPTREF), the --TPTREF should be provided whenever --RFTDTC is populated.",
                                        "Document": "IG v3.1",
                                        "Section": "4.4.7.2.2"
                                    }
                                ]
                            }
                        ]
                    }
                ]
            }
        ],
        "Scope": {
            "Classes": {
                "Include": [
                    "ALL"
                ]
            },
            "Domains": {
                "Include": [
                    "ALL"
                ]
            }
        }
    },
    "id": "1e4405b6-00d5-43ca-b785-6a808a61aa92"
}