{
    "changed": "2022-11-02T08:45:54.708Z",
    "content": "Check:\n  any:\n    - all:\n        - name: LBDTC\n          operator: non_empty\n        - name: USUBJID\n          operator: non_empty\n        - name: LBTESTCD\n          operator: is_not_unique_set\n          value:\n            - USUBJID\n            - LBSPEC\n            - LBDTC\n    - all:\n        - name: LBDTC\n          operator: non_empty\n        - name: POOLID\n          operator: non_empty\n        - name: LBTESTCD\n          operator: is_not_unique_set\n          value:\n            - POOLID\n            - LBSPEC\n            - LBDTC\nCore:\n  Id: CDISC.SENDIG.169\n  Version: '1'\n  Status: Draft\nDescription: Raise an error when there is more than one record present for any particular\n  Result or Findings as Collected, in the CL Domain, for a subject or pool on a particular\n  date.\n#The check for this rule was revised to NOT check the records where CLDTC is null\r\nOutcome:\n  Message: The Clinical Observation test result is not unique for this subject and\n    date/time.\n  Output Variables:\n    - USUBJID\n    - POOLID\n    - LBTESTCD\n    - LBSPEC\n    - LBDTC\nRule Type: Record Data\nSensitivity: Record\nAuthorities:\n  - Organization: CDISC\n    Standards:\n      - Name: SENDIG\n        Version: '3.1'\n        References:\n          - Origin: SDTM and SENDIG Conformance Rules\n            Rule Identifier:\n              Id: '169'\n              Version: '1'\n            Version: '2.0'\n            Citations:\n              - Cited Guidance: One record per test per specimen per observation time\n                  per subject or pool\n                Document: SENDIG v3.1\n                Section: 6.3.6\nScope:\n  Classes:\n    Include:\n      - FINDINGS\n  Domains:\n    Include:\n      - LB\n",
    "created": "2022-11-02T08:45:54.708Z",
    "creator": {
        "id": "dc8bf014-df32-4631-8684-9a09a16c5071"
    },
    "json": {
        "Check": {
            "any": [
                {
                    "all": [
                        {
                            "name": "LBDTC",
                            "operator": "non_empty"
                        },
                        {
                            "name": "USUBJID",
                            "operator": "non_empty"
                        },
                        {
                            "name": "LBTESTCD",
                            "operator": "is_not_unique_set",
                            "value": [
                                "USUBJID",
                                "LBSPEC",
                                "LBDTC"
                            ]
                        }
                    ]
                },
                {
                    "all": [
                        {
                            "name": "LBDTC",
                            "operator": "non_empty"
                        },
                        {
                            "name": "POOLID",
                            "operator": "non_empty"
                        },
                        {
                            "name": "LBTESTCD",
                            "operator": "is_not_unique_set",
                            "value": [
                                "POOLID",
                                "LBSPEC",
                                "LBDTC"
                            ]
                        }
                    ]
                }
            ]
        },
        "Core": {
            "Id": "CDISC.SENDIG.169",
            "Version": "1",
            "Status": "Draft"
        },
        "Description": "Raise an error when there is more than one record present for any particular Result or Findings as Collected, in the CL Domain, for a subject or pool on a particular date.",
        "Outcome": {
            "Message": "The Clinical Observation test result is not unique for this subject and date/time.",
            "Output_Variables": [
                "USUBJID",
                "POOLID",
                "LBTESTCD",
                "LBSPEC",
                "LBDTC"
            ]
        },
        "Rule_Type": "Record Data",
        "Sensitivity": "Record",
        "Authorities": [
            {
                "Organization": "CDISC",
                "Standards": [
                    {
                        "Name": "SENDIG",
                        "Version": "3.1",
                        "References": [
                            {
                                "Origin": "SDTM and SENDIG Conformance Rules",
                                "Rule_Identifier": {
                                    "Id": "169",
                                    "Version": "1"
                                },
                                "Version": "2.0",
                                "Citations": [
                                    {
                                        "Cited_Guidance": "One record per test per specimen per observation time per subject or pool",
                                        "Document": "SENDIG v3.1",
                                        "Section": "6.3.6"
                                    }
                                ]
                            }
                        ]
                    }
                ]
            }
        ],
        "Scope": {
            "Classes": {
                "Include": [
                    "FINDINGS"
                ]
            },
            "Domains": {
                "Include": [
                    "LB"
                ]
            }
        }
    },
    "id": "40bf32ef-e821-4597-8e56-28c7d9a9fa40"
}