{
    "changed": "2022-09-19T09:55:22.207Z",
    "content": "Check:\n  all:\n    - name: --EXFL\n      operator: non_empty\n    - name: --EXFL\n      operator: not_equal_to\n      value: Y\nCore:\n  Id: CDISC.SENDIG.148\n  Version: '1'\n  Status: Draft\nDescription: Trigger error when --EXFL is populated and the value is different from\n  \"Y\"\nOutcome:\n  Message: --EXFL value must either be 'Y' or null\nRule Type: Record Data\nSensitivity: Record\nAuthorities:\n  - Organization: CDISC\n    Standards:\n      - Name: SENDIG\n        Version: '3.1'\n        References:\n          - Origin: SDTM and SENDIG Conformance Rules\n            Rule Identifier:\n              Id: '148'\n              Version: '1'\n            Version: '2.0'\n            Citations:\n              - Cited Guidance: Y if the result should be excluded from all calculations,\n                  otherwise null.\n                Document: IG v3.1\n                Section: 6.3.1\nScope:\n  Classes:\n    Include:\n      - FINDINGS\n  Domains:\n    Include:\n      - ALL\n",
    "created": "2022-09-19T09:46:51.335Z",
    "creator": {
        "id": "dc8bf014-df32-4631-8684-9a09a16c5071"
    },
    "json": {
        "Check": {
            "all": [
                {
                    "name": "--EXFL",
                    "operator": "non_empty"
                },
                {
                    "name": "--EXFL",
                    "operator": "not_equal_to",
                    "value": "Y"
                }
            ]
        },
        "Core": {
            "Id": "CDISC.SENDIG.148",
            "Version": "1",
            "Status": "Draft"
        },
        "Description": "Trigger error when --EXFL is populated and the value is different from \"Y\"",
        "Outcome": {
            "Message": "--EXFL value must either be 'Y' or null"
        },
        "Rule_Type": "Record Data",
        "Sensitivity": "Record",
        "Authorities": [
            {
                "Organization": "CDISC",
                "Standards": [
                    {
                        "Name": "SENDIG",
                        "Version": "3.1",
                        "References": [
                            {
                                "Origin": "SDTM and SENDIG Conformance Rules",
                                "Rule_Identifier": {
                                    "Id": "148",
                                    "Version": "1"
                                },
                                "Version": "2.0",
                                "Citations": [
                                    {
                                        "Cited_Guidance": "Y if the result should be excluded from all calculations, otherwise null.",
                                        "Document": "IG v3.1",
                                        "Section": "6.3.1"
                                    }
                                ]
                            }
                        ]
                    }
                ]
            }
        ],
        "Scope": {
            "Classes": {
                "Include": [
                    "FINDINGS"
                ]
            },
            "Domains": {
                "Include": [
                    "ALL"
                ]
            }
        }
    },
    "id": "6591e748-e213-4033-a4f4-a84fa2b2213b"
}