{
    "id": "b0b0bec5-7fd4-49f2-8d49-4f5a002454d9",
    "changed": "2022-09-08T13:49:11Z",
    "content": "Check:\n  any:\n    - name: --TESTCD\n      operator: matches_regex\n      value: ^[0-9]\nCore:\n  Id: CDISC.SENDIG.18\n  Version: '1'\n  Status: Draft\nDescription: Raise an error when --TESTCD starts with a number\nOutcome:\n  Message: --TESTCD may not start with a number\n  Output Variables:\n    - --TESTCD\nRule Type: Record Data\nSensitivity: Record\nAuthorities:\n  - Organization: CDISC\n    Standards:\n      - Name: SENDIG\n        Version: '3.1'\n        References:\n          - Origin: SDTM and SENDIG Conformance Rules\n            Rule Identifier:\n              Id: '18'\n              Version: '1'\n            Version: '2.0'\n            Citations:\n              - Cited Guidance: Values of --TESTCD and QNAM values must be limited\n                  to 8 characters, and cannot start with a number, nor can they contain\n                  characters other than letters, numbers, or underscores.\n                Document: IG v3.1\n                Section: 4.2.1\nScope:\n  Classes:\n    Include:\n      - FINDINGS\n  Domains:\n    Include:\n      - ALL\n",
    "created": "2022-09-08T13:43:25Z",
    "creator": {
        "id": "dc8bf014-df32-4631-8684-9a09a16c5071"
    },
    "json": {
        "Check": {
            "any": [
                {
                    "name": "--TESTCD",
                    "operator": "matches_regex",
                    "value": "^[0-9]"
                }
            ]
        },
        "Core": {
            "Id": "CDISC.SENDIG.18",
            "Version": "1",
            "Status": "Draft"
        },
        "Description": "Raise an error when --TESTCD starts with a number",
        "Outcome": {
            "Message": "--TESTCD may not start with a number",
            "Output_Variables": [
                "--TESTCD"
            ]
        },
        "Rule_Type": "Record Data",
        "Sensitivity": "Record",
        "Authorities": [
            {
                "Organization": "CDISC",
                "Standards": [
                    {
                        "Name": "SENDIG",
                        "Version": "3.1",
                        "References": [
                            {
                                "Origin": "SDTM and SENDIG Conformance Rules",
                                "Rule_Identifier": {
                                    "Id": "18",
                                    "Version": "1"
                                },
                                "Version": "2.0",
                                "Citations": [
                                    {
                                        "Cited_Guidance": "Values of --TESTCD and QNAM values must be limited to 8 characters, and cannot start with a number, nor can they contain characters other than letters, numbers, or underscores.",
                                        "Document": "IG v3.1",
                                        "Section": "4.2.1"
                                    }
                                ]
                            }
                        ]
                    }
                ]
            }
        ],
        "Scope": {
            "Classes": {
                "Include": [
                    "FINDINGS"
                ]
            },
            "Domains": {
                "Include": [
                    "ALL"
                ]
            }
        }
    }
}