{
    "changed": "2022-09-27T15:06:49.107Z",
    "content": "Check:\n  all:\n    - name: TXPARMCD\n      operator: longer_than\n      value: 8\nCore:\n  Id: CDISC.SENDIG.232\n  Version: '1'\n  Status: Draft\nDescription: TXPARMCD Short character value for the Trial Set parameter described\n  in TXPARM.  Maximum 8 characters.\nOutcome:\n  Message: TXPARMCD value has more than 8 characters\nRule Type: Record Data\nSensitivity: Record\nAuthorities:\n  - Organization: CDISC\n    Standards:\n      - Name: SENDIG\n        Version: '3.1'\n        References:\n          - Origin: SDTM and SENDIG Conformance Rules\n            Rule Identifier:\n              Id: '232'\n              Version: '1'\n            Version: '2.0'\n            Citations:\n              - Cited Guidance: TXPARMCD Short character value for the Trial Set parameter\n                  described in TXPARM.  Maximum 8 characters.\n                Document: IG v3.1\n                Item: Specification\n                Section: 7.4.1\nScope:\n  Classes:\n    Include:\n      - TRIAL DESIGN\n  Domains:\n    Include:\n      - TX\n",
    "created": "2022-09-27T15:04:38.881Z",
    "creator": {
        "id": "dc8bf014-df32-4631-8684-9a09a16c5071"
    },
    "json": {
        "Check": {
            "all": [
                {
                    "name": "TXPARMCD",
                    "operator": "longer_than",
                    "value": 8
                }
            ]
        },
        "Core": {
            "Id": "CDISC.SENDIG.232",
            "Version": "1",
            "Status": "Draft"
        },
        "Description": "TXPARMCD Short character value for the Trial Set parameter described in TXPARM.  Maximum 8 characters.",
        "Outcome": {
            "Message": "TXPARMCD value has more than 8 characters"
        },
        "Rule_Type": "Record Data",
        "Sensitivity": "Record",
        "Authorities": [
            {
                "Organization": "CDISC",
                "Standards": [
                    {
                        "Name": "SENDIG",
                        "Version": "3.1",
                        "References": [
                            {
                                "Origin": "SDTM and SENDIG Conformance Rules",
                                "Rule_Identifier": {
                                    "Id": "232",
                                    "Version": "1"
                                },
                                "Version": "2.0",
                                "Citations": [
                                    {
                                        "Cited_Guidance": "TXPARMCD Short character value for the Trial Set parameter described in TXPARM.  Maximum 8 characters.",
                                        "Document": "IG v3.1",
                                        "Item": "Specification",
                                        "Section": "7.4.1"
                                    }
                                ]
                            }
                        ]
                    }
                ]
            }
        ],
        "Scope": {
            "Classes": {
                "Include": [
                    "TRIAL DESIGN"
                ]
            },
            "Domains": {
                "Include": [
                    "TX"
                ]
            }
        }
    },
    "id": "be391228-b4e4-461d-bf1e-e3f60b45195d"
}