{
    "changed": "2022-11-02T14:55:58.172Z",
    "content": "Check:\n  all:\n    - name: TFORRES\n      operator: is_not_unique_set\n      value:\n        - USUBJID\n        - TFSPEC\nCore:\n  Id: CDISC.SENDIG.200\n  Version: '1'\n  Status: Draft\nDescription: Raise an error when there is more than one record present for any particular\n  tumor test result for a subject and specimen.\nOutcome:\n  Message: The Tumor Findings test result is not unique for this subject and specimen.\n  Output Variables:\n    - USUBJID\n    - TFTESTCD\n    - TFORRES\n    - TFSPEC\nRule Type: Record Data\nSensitivity: Record\nAuthorities:\n  - Organization: CDISC\n    Standards:\n      - Name: SENDIG\n        Version: '3.1'\n        References:\n          - Origin: SDTM and SENDIG Conformance Rules\n            Rule Identifier:\n              Id: '200'\n              Version: '1'\n            Version: '2.0'\n            Citations:\n              - Cited Guidance: One record per tumor per specimen per subject\n                Document: SENDIG v3.1\n                Section: 6.3.14\nScope:\n  Classes:\n    Include:\n      - FINDINGS\n  Domains:\n    Include:\n      - TF\n",
    "created": "2022-11-02T14:55:58.172Z",
    "creator": {
        "id": "dc8bf014-df32-4631-8684-9a09a16c5071"
    },
    "json": {
        "Check": {
            "all": [
                {
                    "name": "TFORRES",
                    "operator": "is_not_unique_set",
                    "value": [
                        "USUBJID",
                        "TFSPEC"
                    ]
                }
            ]
        },
        "Core": {
            "Id": "CDISC.SENDIG.200",
            "Version": "1",
            "Status": "Draft"
        },
        "Description": "Raise an error when there is more than one record present for any particular tumor test result for a subject and specimen.",
        "Outcome": {
            "Message": "The Tumor Findings test result is not unique for this subject and specimen.",
            "Output_Variables": [
                "USUBJID",
                "TFTESTCD",
                "TFORRES",
                "TFSPEC"
            ]
        },
        "Rule_Type": "Record Data",
        "Sensitivity": "Record",
        "Authorities": [
            {
                "Organization": "CDISC",
                "Standards": [
                    {
                        "Name": "SENDIG",
                        "Version": "3.1",
                        "References": [
                            {
                                "Origin": "SDTM and SENDIG Conformance Rules",
                                "Rule_Identifier": {
                                    "Id": "200",
                                    "Version": "1"
                                },
                                "Version": "2.0",
                                "Citations": [
                                    {
                                        "Cited_Guidance": "One record per tumor per specimen per subject",
                                        "Document": "SENDIG v3.1",
                                        "Section": "6.3.14"
                                    }
                                ]
                            }
                        ]
                    }
                ]
            }
        ],
        "Scope": {
            "Classes": {
                "Include": [
                    "FINDINGS"
                ]
            },
            "Domains": {
                "Include": [
                    "TF"
                ]
            }
        }
    },
    "id": "34768a60-f462-4f10-8d97-4cde98b60d5f"
}