{
    "changed": "2022-09-16T10:57:21.749Z",
    "content": "Check:\n  all:\n    - name: ETCD\n      operator: equal_to\n      value: UNPLAN\n    - name: SEUPDES\n      operator: empty\nCore:\n  Id: CDISC.SENDIG.125\n  Version: '1'\n  Status: Draft\nDescription: Verify that SEUPDES is populated when ETCD is equal to UNPLAN\nOutcome:\n  Message: SEUPDES variable has a null value when ETCD has a value of 'UNPLAN'\n  Output Variables:\n    - ETCD\n    - SEUPDES\nRule Type: Record Data\nSensitivity: Record\nAuthorities:\n  - Organization: CDISC\n    Standards:\n      - Name: SENDIG\n        Version: '3.1'\n        References:\n          - Origin: SDTM and SENDIG Conformance Rules\n            Rule Identifier:\n              Id: '125'\n              Version: '1'\n            Version: '2.0'\n            Citations:\n              - Cited Guidance: If the sponsor decides that the subject\u2019s experience\n                  for a particular period of time cannot be represented with one of\n                  the planned Elements, then that period of time should be represented\n                  as an unplanned Element.For unplanned Elements, ETCD should be populated\n                  with 'UNPLAN', ELEMENT should be left blank, and SEUPDES should\n                  be populated with a description of the unplanned Element.\n                Document: SENDIG v3.1\n                Item: Specification\n                Section: 5.3.1.1\nScope:\n  Classes:\n    Include:\n      - SPECIAL-PURPOSE\n  Domains:\n    Include:\n      - SE\n",
    "created": "2022-09-16T10:53:33.858Z",
    "creator": {
        "id": "dc8bf014-df32-4631-8684-9a09a16c5071"
    },
    "json": {
        "Check": {
            "all": [
                {
                    "name": "ETCD",
                    "operator": "equal_to",
                    "value": "UNPLAN"
                },
                {
                    "name": "SEUPDES",
                    "operator": "empty"
                }
            ]
        },
        "Core": {
            "Id": "CDISC.SENDIG.125",
            "Version": "1",
            "Status": "Draft"
        },
        "Description": "Verify that SEUPDES is populated when ETCD is equal to UNPLAN",
        "Outcome": {
            "Message": "SEUPDES variable has a null value when ETCD has a value of 'UNPLAN'",
            "Output_Variables": [
                "ETCD",
                "SEUPDES"
            ]
        },
        "Rule_Type": "Record Data",
        "Sensitivity": "Record",
        "Authorities": [
            {
                "Organization": "CDISC",
                "Standards": [
                    {
                        "Name": "SENDIG",
                        "Version": "3.1",
                        "References": [
                            {
                                "Origin": "SDTM and SENDIG Conformance Rules",
                                "Rule_Identifier": {
                                    "Id": "125",
                                    "Version": "1"
                                },
                                "Version": "2.0",
                                "Citations": [
                                    {
                                        "Cited_Guidance": "If the sponsor decides that the subject\u2019s experience for a particular period of time cannot be represented with one of the planned Elements, then that period of time should be represented as an unplanned Element.For unplanned Elements, ETCD should be populated with 'UNPLAN', ELEMENT should be left blank, and SEUPDES should be populated with a description of the unplanned Element.",
                                        "Document": "SENDIG v3.1",
                                        "Item": "Specification",
                                        "Section": "5.3.1.1"
                                    }
                                ]
                            }
                        ]
                    }
                ]
            }
        ],
        "Scope": {
            "Classes": {
                "Include": [
                    "SPECIAL-PURPOSE"
                ]
            },
            "Domains": {
                "Include": [
                    "SE"
                ]
            }
        }
    },
    "id": "d38dc6ee-9087-4e07-826c-35f12e39b622"
}