{
    "changed": "2022-10-12T09:26:11.484Z",
    "content": "Check:\n  all:\n    - name: POOLID\n      operator: non_empty\n    - name: POOLID\n      operator: is_not_contained_by\n      value: $pooldef_poolid\nCore:\n  Id: CDISC.SENDIG.139\n  Version: '1'\n  Status: Draft\nDescription: Trigger error when POOLID is not present in POOLDEF in DM.USUBJID\nOperations:\n  - domain: POOLDEF\n    id: $pooldef_poolid\n    name: POOLID\n    operator: distinct\nOutcome:\n  Message: POOLID is not found in POOLDEF.POOLID\nRule Type: Record Data\nSensitivity: Record\nAuthorities:\n  - Organization: CDISC\n    Standards:\n      - Name: SENDIG\n        Version: '3.1'\n        References:\n          - Origin: SDTM and SENDIG Conformance Rules\n            Rule Identifier:\n              Id: '139'\n              Version: '1'\n            Version: '2.0'\n            Citations:\n              - Cited Guidance: To identify a subject uniquely across a submission,\n                  a unique identifier (USUBJID) should be signed and included in all\n                  subject-related datasets in the submission.\n                Document: IG v3.1\n                Section: 6.1.1\nScope:\n  Classes:\n    Include:\n      - ALL\n  Domains:\n    Include:\n      - ALL\n",
    "created": "2022-09-16T15:39:28.612Z",
    "creator": {
        "id": "dc8bf014-df32-4631-8684-9a09a16c5071"
    },
    "json": {
        "Check": {
            "all": [
                {
                    "name": "POOLID",
                    "operator": "non_empty"
                },
                {
                    "name": "POOLID",
                    "operator": "is_not_contained_by",
                    "value": "$pooldef_poolid"
                }
            ]
        },
        "Core": {
            "Id": "CDISC.SENDIG.139",
            "Version": "1",
            "Status": "Draft"
        },
        "Description": "Trigger error when POOLID is not present in POOLDEF in DM.USUBJID",
        "Operations": [
            {
                "domain": "POOLDEF",
                "id": "$pooldef_poolid",
                "name": "POOLID",
                "operator": "distinct"
            }
        ],
        "Outcome": {
            "Message": "POOLID is not found in POOLDEF.POOLID"
        },
        "Rule_Type": "Record Data",
        "Sensitivity": "Record",
        "Authorities": [
            {
                "Organization": "CDISC",
                "Standards": [
                    {
                        "Name": "SENDIG",
                        "Version": "3.1",
                        "References": [
                            {
                                "Origin": "SDTM and SENDIG Conformance Rules",
                                "Rule_Identifier": {
                                    "Id": "139",
                                    "Version": "1"
                                },
                                "Version": "2.0",
                                "Citations": [
                                    {
                                        "Cited_Guidance": "To identify a subject uniquely across a submission, a unique identifier (USUBJID) should be signed and included in all subject-related datasets in the submission.",
                                        "Document": "IG v3.1",
                                        "Section": "6.1.1"
                                    }
                                ]
                            }
                        ]
                    }
                ]
            }
        ],
        "Scope": {
            "Classes": {
                "Include": [
                    "ALL"
                ]
            },
            "Domains": {
                "Include": [
                    "ALL"
                ]
            }
        }
    },
    "id": "d3e7f701-8e97-462a-9e5b-e7422d8f91a0"
}