{
    "changed": "2022-09-19T10:08:28.239Z",
    "content": "Check:\n  all:\n    - name: --EXFL\n      operator: not_equal_to\n      value: Y\n    - name: --REASEX\n      operator: non_empty\nCore:\n  Id: CDISC.SENDIG.149\n  Version: '1'\n  Status: Draft\nDescription: Trigger error when --REASEX is populated and --EXCLFL is not 'Y'\nOutcome:\n  Message: --REASEX may only be present when --EXCLFL is 'Y'\nRule Type: Record Data\nSensitivity: Record\nAuthorities:\n  - Organization: CDISC\n    Standards:\n      - Name: SENDIG\n        Version: '3.1'\n        References:\n          - Origin: SDTM and SENDIG Conformance Rules\n            Rule Identifier:\n              Id: '149'\n              Version: '1'\n            Version: '2.0'\n            Citations:\n              - Cited Guidance: The reason the result should be excluded from all\n                  calculations. Used only when BWEXCLFL is Y.\n                Document: IG v3.1\n                Section: 6.3.1\nScope:\n  Classes:\n    Include:\n      - FINDINGS\n  Domains:\n    Include:\n      - ALL\n",
    "created": "2022-09-19T10:08:28.239Z",
    "creator": {
        "id": "dc8bf014-df32-4631-8684-9a09a16c5071"
    },
    "json": {
        "Check": {
            "all": [
                {
                    "name": "--EXFL",
                    "operator": "not_equal_to",
                    "value": "Y"
                },
                {
                    "name": "--REASEX",
                    "operator": "non_empty"
                }
            ]
        },
        "Core": {
            "Id": "CDISC.SENDIG.149",
            "Version": "1",
            "Status": "Draft"
        },
        "Description": "Trigger error when --REASEX is populated and --EXCLFL is not 'Y'",
        "Outcome": {
            "Message": "--REASEX may only be present when --EXCLFL is 'Y'"
        },
        "Rule_Type": "Record Data",
        "Sensitivity": "Record",
        "Authorities": [
            {
                "Organization": "CDISC",
                "Standards": [
                    {
                        "Name": "SENDIG",
                        "Version": "3.1",
                        "References": [
                            {
                                "Origin": "SDTM and SENDIG Conformance Rules",
                                "Rule_Identifier": {
                                    "Id": "149",
                                    "Version": "1"
                                },
                                "Version": "2.0",
                                "Citations": [
                                    {
                                        "Cited_Guidance": "The reason the result should be excluded from all calculations. Used only when BWEXCLFL is Y.",
                                        "Document": "IG v3.1",
                                        "Section": "6.3.1"
                                    }
                                ]
                            }
                        ]
                    }
                ]
            }
        ],
        "Scope": {
            "Classes": {
                "Include": [
                    "FINDINGS"
                ]
            },
            "Domains": {
                "Include": [
                    "ALL"
                ]
            }
        }
    },
    "id": "4cd30525-0d98-473d-9227-c2be2f082608"
}