{
    "id": "8921a864-7a9a-45c3-9dad-55fef363c475",
    "changed": "2022-03-22T13:16:55Z",
    "content": "Check:\n  all:\n    - name: AGEU\n      operator: non_empty\n    - name: AGE\n      operator: empty\nCore:\n  Id: CDISC.SDTMIG.CG0433_not IG V3.4 rule\n  Version: '1'\n  Status: Draft\nDescription: Raise an error when AGE is empty, but AGEU is not empty.\nOutcome:\n  Message: Missing value for AGE, when AGEU is provided\n  Output Variables:\n    - AGE\n    - AGEU\nRule Type: Record Data\nSensitivity: Record\nAuthorities:\n  - Organization: CDISC\n    Standards:\n      - Name: SDTMIG\n        Version: '3.4'\n        References:\n          - Origin: SDTM and SDTMIG Conformance Rules\n            Rule Identifier:\n              Id: CG0433\n              Version: '1'\n            Version: '2.0'\n            Citations:\n              - Cited Guidance: '[AGEU]Variable Qualifier of AGE or AGETXT.|[AGETXT]Not\n                  in human clinical trials.'\n                Document: Model v2.0\n                Item: AGEU|AGETXT\n                Section: Demographics\nScope:\n  Classes:\n    Include:\n      - SPECIAL-PURPOSE\n  Domains:\n    Include:\n      - DM\n",
    "created": "2021-10-12T02:37:32Z",
    "creator": {
        "id": "d0881041-369e-4940-b721-5b456d12101b"
    },
    "json": {
        "Check": {
            "all": [
                {
                    "name": "AGEU",
                    "operator": "non_empty"
                },
                {
                    "name": "AGE",
                    "operator": "empty"
                }
            ]
        },
        "Core": {
            "Id": "CDISC.SDTMIG.CG0433_not IG V3.4 rule",
            "Version": "1",
            "Status": "Draft"
        },
        "Description": "Raise an error when AGE is empty, but AGEU is not empty.",
        "Outcome": {
            "Message": "Missing value for AGE, when AGEU is provided",
            "Output_Variables": [
                "AGE",
                "AGEU"
            ]
        },
        "Rule_Type": "Record Data",
        "Sensitivity": "Record",
        "Authorities": [
            {
                "Organization": "CDISC",
                "Standards": [
                    {
                        "Name": "SDTMIG",
                        "Version": "3.4",
                        "References": [
                            {
                                "Origin": "SDTM and SDTMIG Conformance Rules",
                                "Rule_Identifier": {
                                    "Id": "CG0433",
                                    "Version": "1"
                                },
                                "Version": "2.0",
                                "Citations": [
                                    {
                                        "Cited_Guidance": "[AGEU]Variable Qualifier of AGE or AGETXT.|[AGETXT]Not in human clinical trials.",
                                        "Document": "Model v2.0",
                                        "Item": "AGEU|AGETXT",
                                        "Section": "Demographics"
                                    }
                                ]
                            }
                        ]
                    }
                ]
            }
        ],
        "Scope": {
            "Classes": {
                "Include": [
                    "SPECIAL-PURPOSE"
                ]
            },
            "Domains": {
                "Include": [
                    "DM"
                ]
            }
        }
    }
}