{
    "changed": "2022-09-28T07:35:07.876Z",
    "content": "Check:\n  all:\n    - any:\n        - name: TXPARMCD\n          operator: equal_to\n          value: DOSENDTC\n        - name: TXPARMCD\n          operator: equal_to\n          value: DOSSTDTC\n    - name: TXVAL\n      operator: invalid_date\nCore:\n  Id: CDISC.SENDIG.243\n  Version: '1'\n  Status: Draft\nDescription: Trial Set Parameters that include dates are required to be presented\n  according to the international standard ISO 8601\nOutcome:\n  Message: The value of TXVAL is not in ISO 8601 date/datetime format\nRule Type: Record Data\nSensitivity: Record\nAuthorities:\n  - Organization: CDISC\n    Standards:\n      - Name: SENDIG\n        Version: '3.1'\n        References:\n          - Origin: SDTM and SENDIG Conformance Rules\n            Rule Identifier:\n              Id: '243'\n              Version: '1'\n            Version: '2.0'\n            Citations:\n              - Cited Guidance: Trial Set Parameters that include dates are required\n                  to be presented according to the international standard ISO 8601\n                Document: IG v3.1\n                Item: Specification\n                Section: 7.4.2\nScope:\n  Classes:\n    Include:\n      - TRIAL DESIGN\n  Domains:\n    Include:\n      - TX\n",
    "created": "2022-09-28T07:35:07.876Z",
    "creator": {
        "id": "dc8bf014-df32-4631-8684-9a09a16c5071"
    },
    "json": {
        "Check": {
            "all": [
                {
                    "any": [
                        {
                            "name": "TXPARMCD",
                            "operator": "equal_to",
                            "value": "DOSENDTC"
                        },
                        {
                            "name": "TXPARMCD",
                            "operator": "equal_to",
                            "value": "DOSSTDTC"
                        }
                    ]
                },
                {
                    "name": "TXVAL",
                    "operator": "invalid_date"
                }
            ]
        },
        "Core": {
            "Id": "CDISC.SENDIG.243",
            "Version": "1",
            "Status": "Draft"
        },
        "Description": "Trial Set Parameters that include dates are required to be presented according to the international standard ISO 8601",
        "Outcome": {
            "Message": "The value of TXVAL is not in ISO 8601 date/datetime format"
        },
        "Rule_Type": "Record Data",
        "Sensitivity": "Record",
        "Authorities": [
            {
                "Organization": "CDISC",
                "Standards": [
                    {
                        "Name": "SENDIG",
                        "Version": "3.1",
                        "References": [
                            {
                                "Origin": "SDTM and SENDIG Conformance Rules",
                                "Rule_Identifier": {
                                    "Id": "243",
                                    "Version": "1"
                                },
                                "Version": "2.0",
                                "Citations": [
                                    {
                                        "Cited_Guidance": "Trial Set Parameters that include dates are required to be presented according to the international standard ISO 8601",
                                        "Document": "IG v3.1",
                                        "Item": "Specification",
                                        "Section": "7.4.2"
                                    }
                                ]
                            }
                        ]
                    }
                ]
            }
        ],
        "Scope": {
            "Classes": {
                "Include": [
                    "TRIAL DESIGN"
                ]
            },
            "Domains": {
                "Include": [
                    "TX"
                ]
            }
        }
    },
    "id": "e637652b-cb35-434d-bf80-a123e75d4297"
}