{
    "id": "c6828f28-c1e0-4f03-85de-39d7642e5e81",
    "changed": "2022-09-08T13:37:33Z",
    "content": "Check:\n  any:\n    - name: --TESTCD\n      operator: not_matches_regex\n      value: ^[A-Z0-9_]*$\nCore:\n  Id: CDISC.SENDIG.19\n  Version: '1'\n  Status: Draft\nDescription: Raise an error when --TESTCD contains anything else than a letter, number\n  or underscore\nOutcome:\n  Message: --TESTCD value cannot contain characters other than letters, numbers or\n    underscores\n  Output Variables:\n    - --TESTCD\nRule Type: Record Data\nSensitivity: Record\nAuthorities:\n  - Organization: CDISC\n    Standards:\n      - Name: SENDIG\n        Version: '3.1'\n        References:\n          - Origin: SDTM and SENDIG Conformance Rules\n            Rule Identifier:\n              Id: '19'\n              Version: '1'\n            Version: '2.0'\n            Citations:\n              - Cited Guidance: Values of --TESTCD and QNAM values must be limited\n                  to 8 characters, and cannot start with a number, nor can they contain\n                  characters other than letters, numbers, or underscores.\n                Document: IG v3.1\n                Section: 4.2.1\nScope:\n  Classes:\n    Include:\n      - FINDINGS\n  Domains:\n    Include:\n      - ALL\n",
    "created": "2022-09-08T12:21:25Z",
    "creator": {
        "id": "dc8bf014-df32-4631-8684-9a09a16c5071"
    },
    "json": {
        "Check": {
            "any": [
                {
                    "name": "--TESTCD",
                    "operator": "not_matches_regex",
                    "value": "^[A-Z0-9_]*$"
                }
            ]
        },
        "Core": {
            "Id": "CDISC.SENDIG.19",
            "Version": "1",
            "Status": "Draft"
        },
        "Description": "Raise an error when --TESTCD contains anything else than a letter, number or underscore",
        "Outcome": {
            "Message": "--TESTCD value cannot contain characters other than letters, numbers or underscores",
            "Output_Variables": [
                "--TESTCD"
            ]
        },
        "Rule_Type": "Record Data",
        "Sensitivity": "Record",
        "Authorities": [
            {
                "Organization": "CDISC",
                "Standards": [
                    {
                        "Name": "SENDIG",
                        "Version": "3.1",
                        "References": [
                            {
                                "Origin": "SDTM and SENDIG Conformance Rules",
                                "Rule_Identifier": {
                                    "Id": "19",
                                    "Version": "1"
                                },
                                "Version": "2.0",
                                "Citations": [
                                    {
                                        "Cited_Guidance": "Values of --TESTCD and QNAM values must be limited to 8 characters, and cannot start with a number, nor can they contain characters other than letters, numbers, or underscores.",
                                        "Document": "IG v3.1",
                                        "Section": "4.2.1"
                                    }
                                ]
                            }
                        ]
                    }
                ]
            }
        ],
        "Scope": {
            "Classes": {
                "Include": [
                    "FINDINGS"
                ]
            },
            "Domains": {
                "Include": [
                    "ALL"
                ]
            }
        }
    }
}