{
    "changed": "2023-03-02T17:46:26.311Z",
    "content": "Check:\r\n  all:\r\n    - name: variable_name\r\n      operator: exists\r\n    - name: variable_name\r\n      operator: matches_regex\r\n      value: /substr(varibale_name,1,length(variable_anme)-2\\FN  /\r\n    - name: --FN\r\n      operator: not_contains_all\r\n      value: ('Y','N','')  #check if null '' ok or if empty operator required\r\nCore:\r\n  Id: CDISC.ADAMIG.AD0006\r\n  Version: '1'\r\n  Status: Draft\r\nDescription: >-\r\n  'A variable with a suffix of FN must have a value that is not 0, 1 or null'\r\nOutcome:\r\n  Message: Variable with a suffix of FN does must have the value  Y, N or null\r\n  Output Variables:\r\n    - --FL\r\n    - --FN\r\nRule Type: Record Data\r\n\r\nSensitivity: Record\r\nAuthorities:\r\n  - Organization: CDISC\r\n    Standards:\r\n      - Name: ADaMIG\r\n        Version: '1.3'\r\n        References:\r\n          - Origin: ADaM Conformance Rules\r\n            Rule Identifier:\r\n              Id: '6'\r\n            Version: '4.0'\r\n            Citations:\r\n              - Cited Guidance: >-\r\n                  For subject-level numeric population flag variables':'' 0 = no (not\r\n                  included), 1 = yes (included). Null values are not allowed.  \r\n                Document: ADaM IG v1.3\r\n                Item: '5'\r\n                Section: 3.1.4\r\n              - Cited Guidance: >-\r\n                  For character flags with variable names that end in FL and that\r\n                  are not population flags, a scheme of Y/N/null, or Y/null may be\r\n                  specified. As indicated in Tables 3.3.4.3.1 and 3.3.8.1, some common\r\n                  character flags use the scheme Y/null. The choice of Y/N/null vs\r\n                  Y/null is dependent on analysis needs. Y/N/null should be used when\r\n                  N and null values need to be analyzed differently. Y/null can be\r\n                  used when the need is to analyze just the Y values. Corresponding\r\n                  1/0/null and 1/null schemes apply to numeric flags with variable\r\n                  names that end in FN and which are not population indicators.\r\n                Document: ADaM IG v1.3\r\n                Item: '9'\r\n                Section: 3.1.4\r\n            \r\n      - Name: ADaMIG\r\n        Version: '1.2'\r\n        References:\r\n          - Origin: ADaM Conformance Rules\r\n            Rule Identifier:\r\n              Id: '6'\r\n            Version: '4.0'\r\n            Citations:\r\n              - Cited Guidance: >-\r\n                  For subject-level numeric population flag variables':'0 = no (not\r\n                  included), 1 = yes (included). Null values are not allowed.\r\n                Document: ADaM IG v1.2\r\n                Item: '5'\r\n                Section: 3.1.4\r\n              - Cited Guidance: >-\r\n                  For character flags with variable names that end in FL and that\r\n                  are not population flags, a scheme of Y/N/null, or Y/null may be\r\n                  specified. As indicated in Tables 3.3.4.3.1 and 3.3.8.1, some common\r\n                  character flags use the scheme Y/null. The choice of Y/N/null vs\r\n                  Y/null is dependent on analysis needs. Y/N/null should be used when\r\n                  N and null values need to be analyzed differently. Y/null can be\r\n                  used when the need is to analyze just the Y values. Corresponding\r\n                  1/0/null and 1/null schemes apply to numeric flags with variable\r\n                  names that end in FN and which are not population indicators.\r\n                Document: ADaM IG v1.2\r\n                Item: '9'\r\n                Section: 3.1.4\r\n      - Name: ADaMIG\r\n        Version: '1.1'\r\n        References:\r\n          - Origin: ADaM Conformance Rules\r\n            Rule Identifier:\r\n              Id: '6'\r\n            Version: '4.0'\r\n            Citations:\r\n              - Cited Guidance: >-\r\n                  For subject-level numeric population flag variables':'' 0 = no (not\r\n                  included), 1 = yes (included). Null values are not allowed.\r\n                Document: ADaM IG v1.1\r\n                Item: '5'\r\n                Section: 3.1.4\r\n              - Cited Guidance: >-\r\n                  For character flags with variable names that end in FL and that\r\n                  are not population flags, a scheme of Y/N/null, or Y/null may be\r\n                  specified. As indicated in Table 3.3.4.2, and Table 3.3.8.1, some\r\n                  common character flags use the scheme Y/null. Corresponding 1/0/null\r\n                  and 1/null schemes apply to numeric flags with variable names that\r\n                  end in FN and that are not population indicators.\r\n                Document: ADaM IG v1.1\r\n                Item: '9'\r\n                Section: 3.1.4\r\n      - Name: ADaMIG\r\n        Version: '1.0'\r\n        References:\r\n          - Origin: ADaM Conformance Rules\r\n            Rule Identifier:\r\n              Id: '6'\r\n            Version: '4.0'\r\n            Citations:\r\n              - Cited Guidance: >-\r\n                  For character flags with variable names that end in FL and that\r\n                  are not population flags, a scheme of Y/N/null, or Y/null may be\r\n                  specified. As indicated in Table 3.3.4.2, and Table 3.3.8.1, some\r\n                  common character flags use the scheme Y/null. Corresponding 1/0/null\r\n                  and 1/null schemes apply to numeric flags with variable names that\r\n                  end in FN and that are not population indicators.\r\n                Document: ADaM IG v1.0\r\n                Item: 9 (General Flag Variable Conventions)\r\n                Section: '3'\r\n              - Cited Guidance: >-\r\n                  For subject-level numeric population flag variables':' 0 = no (not\r\n                  included), 1 = yes (included). Null values are not allowed.\r\n                Document: ADaM IG v1.0\r\n                Item: 9 (General Flag Variable Conventions)\r\n                Section: '3'\r\nScope:\r\n  Classes:\r\n    Include:\r\n      - ALL\r\n  Data Structures:\r\n    Include:\r\n      - ADAM OTHER\r\n      - BASIC DATA STRUCTURE\r\n      - OCCURRENCE DATA STRUCTURE\r\n      - SUBJECT LEVEL ANALYSIS DATASET\r\n\r\n  Subclasses:\r\n    Include:\r\n      - ALL\r\n",
    "created": "2023-01-31T16:27:09.748Z",
    "creator": {
        "id": "57474fac-237e-4693-bb37-7826b02737da"
    },
    "json": {
        "Check": {
            "all": [
                {
                    "name": "variable_name",
                    "operator": "exists"
                },
                {
                    "name": "variable_name",
                    "operator": "matches_regex",
                    "value": "/substr(varibale_name,1,length(variable_anme)-2\\FN  /"
                },
                {
                    "name": "--FN",
                    "operator": "not_contains_all",
                    "value": "('Y','N','')"
                }
            ]
        },
        "Core": {
            "Id": "CDISC.ADAMIG.AD0006",
            "Version": "1",
            "Status": "Draft"
        },
        "Description": "'A variable with a suffix of FN must have a value that is not 0, 1 or null'",
        "Outcome": {
            "Message": "Variable with a suffix of FN does must have the value  Y, N or null",
            "Output_Variables": [
                "--FL",
                "--FN"
            ]
        },
        "Sensitivity": "Record",
        "Authorities": [
            {
                "Organization": "CDISC",
                "Standards": [
                    {
                        "Name": "ADaMIG",
                        "Version": "1.3",
                        "References": [
                            {
                                "Origin": "ADaM Conformance Rules",
                                "Version": "4.0",
                                "Citations": [
                                    {
                                        "Document": "ADaM IG v1.3",
                                        "Item": "5",
                                        "Section": "3.1.4",
                                        "Cited_Guidance": "For subject-level numeric population flag variables':'' 0 = no (not included), 1 = yes (included). Null values are not allowed.  "
                                    },
                                    {
                                        "Document": "ADaM IG v1.3",
                                        "Item": "9",
                                        "Section": "3.1.4",
                                        "Cited_Guidance": "For character flags with variable names that end in FL and that are not population flags, a scheme of Y/N/null, or Y/null may be specified. As indicated in Tables 3.3.4.3.1 and 3.3.8.1, some common character flags use the scheme Y/null. The choice of Y/N/null vs Y/null is dependent on analysis needs. Y/N/null should be used when N and null values need to be analyzed differently. Y/null can be used when the need is to analyze just the Y values. Corresponding 1/0/null and 1/null schemes apply to numeric flags with variable names that end in FN and which are not population indicators."
                                    }
                                ],
                                "Rule_Identifier": {
                                    "Id": "6"
                                }
                            }
                        ]
                    },
                    {
                        "Name": "ADaMIG",
                        "Version": "1.2",
                        "References": [
                            {
                                "Origin": "ADaM Conformance Rules",
                                "Version": "4.0",
                                "Citations": [
                                    {
                                        "Document": "ADaM IG v1.2",
                                        "Item": "5",
                                        "Section": "3.1.4",
                                        "Cited_Guidance": "For subject-level numeric population flag variables':'0 = no (not included), 1 = yes (included). Null values are not allowed."
                                    },
                                    {
                                        "Document": "ADaM IG v1.2",
                                        "Item": "9",
                                        "Section": "3.1.4",
                                        "Cited_Guidance": "For character flags with variable names that end in FL and that are not population flags, a scheme of Y/N/null, or Y/null may be specified. As indicated in Tables 3.3.4.3.1 and 3.3.8.1, some common character flags use the scheme Y/null. The choice of Y/N/null vs Y/null is dependent on analysis needs. Y/N/null should be used when N and null values need to be analyzed differently. Y/null can be used when the need is to analyze just the Y values. Corresponding 1/0/null and 1/null schemes apply to numeric flags with variable names that end in FN and which are not population indicators."
                                    }
                                ],
                                "Rule_Identifier": {
                                    "Id": "6"
                                }
                            }
                        ]
                    },
                    {
                        "Name": "ADaMIG",
                        "Version": "1.1",
                        "References": [
                            {
                                "Origin": "ADaM Conformance Rules",
                                "Version": "4.0",
                                "Citations": [
                                    {
                                        "Document": "ADaM IG v1.1",
                                        "Item": "5",
                                        "Section": "3.1.4",
                                        "Cited_Guidance": "For subject-level numeric population flag variables':'' 0 = no (not included), 1 = yes (included). Null values are not allowed."
                                    },
                                    {
                                        "Document": "ADaM IG v1.1",
                                        "Item": "9",
                                        "Section": "3.1.4",
                                        "Cited_Guidance": "For character flags with variable names that end in FL and that are not population flags, a scheme of Y/N/null, or Y/null may be specified. As indicated in Table 3.3.4.2, and Table 3.3.8.1, some common character flags use the scheme Y/null. Corresponding 1/0/null and 1/null schemes apply to numeric flags with variable names that end in FN and that are not population indicators."
                                    }
                                ],
                                "Rule_Identifier": {
                                    "Id": "6"
                                }
                            }
                        ]
                    },
                    {
                        "Name": "ADaMIG",
                        "Version": "1.0",
                        "References": [
                            {
                                "Origin": "ADaM Conformance Rules",
                                "Version": "4.0",
                                "Citations": [
                                    {
                                        "Document": "ADaM IG v1.0",
                                        "Item": "9 (General Flag Variable Conventions)",
                                        "Section": "3",
                                        "Cited_Guidance": "For character flags with variable names that end in FL and that are not population flags, a scheme of Y/N/null, or Y/null may be specified. As indicated in Table 3.3.4.2, and Table 3.3.8.1, some common character flags use the scheme Y/null. Corresponding 1/0/null and 1/null schemes apply to numeric flags with variable names that end in FN and that are not population indicators."
                                    },
                                    {
                                        "Document": "ADaM IG v1.0",
                                        "Item": "9 (General Flag Variable Conventions)",
                                        "Section": "3",
                                        "Cited_Guidance": "For subject-level numeric population flag variables':' 0 = no (not included), 1 = yes (included). Null values are not allowed."
                                    }
                                ],
                                "Rule_Identifier": {
                                    "Id": "6"
                                }
                            }
                        ]
                    }
                ]
            }
        ],
        "Scope": {
            "Classes": {
                "Include": [
                    "ALL"
                ]
            },
            "Subclasses": {
                "Include": [
                    "ALL"
                ]
            },
            "Data_Structures": {
                "Include": [
                    "ADAM OTHER",
                    "BASIC DATA STRUCTURE",
                    "OCCURRENCE DATA STRUCTURE",
                    "SUBJECT LEVEL ANALYSIS DATASET"
                ]
            }
        },
        "Rule_Type": "Record Data"
    },
    "id": "b93431d9-923e-440d-a5db-fa4d30c92faf"
}