{
    "changed": "2022-09-27T13:27:16.965Z",
    "content": "Check:\n  all:\n    - name: BWDTC\n      operator: non_empty\n    - name: BWTESTCD\n      operator: is_not_unique_set\n      value:\n        - USUBJID\n        - BWDTC\nCore:\n  Id: CDISC.SENDIG.SEND142\n  Version: '1'\n  Status: Draft\nDescription: Raise an error when there is more than one record present for any particular\n  Body Weight test, in the BW Domain, for a subject on a particular date.\n#The check for this rule was revised to NOT check the records where BWDTC is null\nOutcome:\n  Message: The Body Weight test is not unique for this subject and date/time.\n  Output Variables:\n    - USUBJID\n    - BWTESTCD\n    - BWDTC\nRule Type: Record Data\nSensitivity: Domain\nAuthorities:\n  - Organization: CDISC\n    Standards:\n      - Name: SENDIG\n        Version: '3.0'\n        References:\n          - Origin: SENDIG Conformance Rules\n            Rule Identifier:\n              Id: '142'\n              Version: '1'\n            Version: '4'\n      #need to determine what can be done with catalog version 5 if anything\n            Citations:\n              - Cited Guidance: One record per test per observation time per subject,\n                  Tabulation.\n    #SMEs do we want to keep \"Tabulation\" for any reason?\n                Document: SENDIG v3.1\n                Section: 6.3.1\n      - Name: SENDIG\n        Version: '3.1'\n        References:\n          - Origin: SENDIG Conformance Rules\n            Rule Identifier:\n              Id: '142'\n              Version: '1'\n            Version: '4'\n      #need to determine what can be done with catalog version 5 if anything\n            Citations:\n              - Cited Guidance: One record per test per observation time per subject,\n                  Tabulation.\n    #SMEs do we want to keep \"Tabulation\" for any reason?\n                Document: SENDIG v3.1\n                Section: 6.3.1\n      - Name: SENDIG-DART\n        Version: v1.1\n        References:\n          - Origin: SENDIG Conformance Rules\n            Rule Identifier:\n              Id: '142'\n              Version: '1'\n            Version: '4'\n      #need to determine what can be done with catalog version 5 if anything\n            Citations:\n              - Cited Guidance: One record per test per observation time per subject,\n                  Tabulation.\n    #SMEs do we want to keep \"Tabulation\" for any reason?\n                Document: SENDIG v3.1\n                Section: 6.3.1\n      - Name: SENDIG-DART\n        Version: v1.2\n        References:\n          - Origin: SENDIG Conformance Rules\n            Rule Identifier:\n              Id: '142'\n              Version: '1'\n            Version: '4'\n      #need to determine what can be done with catalog version 5 if anything\n            Citations:\n              - Cited Guidance: One record per test per observation time per subject,\n                  Tabulation.\n    #SMEs do we want to keep \"Tabulation\" for any reason?\n                Document: SENDIG v3.1\n                Section: 6.3.1\n      - Name: SENDID-GENETOX\n        Version: v1.0\n              #double check the last few\n        References:\n          - Origin: SENDIG Conformance Rules\n            Rule Identifier:\n              Id: '142'\n              Version: '1'\n            Version: '4'\n      #need to determine what can be done with catalog version 5 if anything\n            Citations:\n              - Cited Guidance: One record per test per observation time per subject,\n                  Tabulation.\n    #SMEs do we want to keep \"Tabulation\" for any reason?\n                Document: SENDIG v3.1\n                Section: 6.3.1\nScope:\n  Classes:\n    Include:\n      - FINDINGS\n  Domains:\n    Include:\n      - BW\n",
    "created": "2022-09-26T21:13:11.703Z",
    "creator": {
        "id": "5042c868-b79a-415d-b5aa-12e6474ce80c"
    },
    "json": {
        "Check": {
            "all": [
                {
                    "name": "BWDTC",
                    "operator": "non_empty"
                },
                {
                    "name": "BWTESTCD",
                    "operator": "is_not_unique_set",
                    "value": [
                        "USUBJID",
                        "BWDTC"
                    ]
                }
            ]
        },
        "Core": {
            "Id": "CDISC.SENDIG.SEND142",
            "Version": "1",
            "Status": "Draft"
        },
        "Description": "Raise an error when there is more than one record present for any particular Body Weight test, in the BW Domain, for a subject on a particular date.",
        "Outcome": {
            "Message": "The Body Weight test is not unique for this subject and date/time.",
            "Output_Variables": [
                "USUBJID",
                "BWTESTCD",
                "BWDTC"
            ]
        },
        "Rule_Type": "Record Data",
        "Sensitivity": "Domain",
        "Authorities": [
            {
                "Organization": "CDISC",
                "Standards": [
                    {
                        "Name": "SENDIG",
                        "Version": "3.0",
                        "References": [
                            {
                                "Origin": "SENDIG Conformance Rules",
                                "Rule_Identifier": {
                                    "Id": "142",
                                    "Version": "1"
                                },
                                "Version": "4",
                                "Citations": [
                                    {
                                        "Cited_Guidance": "One record per test per observation time per subject, Tabulation.",
                                        "Document": "SENDIG v3.1",
                                        "Section": "6.3.1"
                                    }
                                ]
                            }
                        ]
                    },
                    {
                        "Name": "SENDIG",
                        "Version": "3.1",
                        "References": [
                            {
                                "Origin": "SENDIG Conformance Rules",
                                "Rule_Identifier": {
                                    "Id": "142",
                                    "Version": "1"
                                },
                                "Version": "4",
                                "Citations": [
                                    {
                                        "Cited_Guidance": "One record per test per observation time per subject, Tabulation.",
                                        "Document": "SENDIG v3.1",
                                        "Section": "6.3.1"
                                    }
                                ]
                            }
                        ]
                    },
                    {
                        "Name": "SENDIG-DART",
                        "Version": "v1.1",
                        "References": [
                            {
                                "Origin": "SENDIG Conformance Rules",
                                "Rule_Identifier": {
                                    "Id": "142",
                                    "Version": "1"
                                },
                                "Version": "4",
                                "Citations": [
                                    {
                                        "Cited_Guidance": "One record per test per observation time per subject, Tabulation.",
                                        "Document": "SENDIG v3.1",
                                        "Section": "6.3.1"
                                    }
                                ]
                            }
                        ]
                    },
                    {
                        "Name": "SENDIG-DART",
                        "Version": "v1.2",
                        "References": [
                            {
                                "Origin": "SENDIG Conformance Rules",
                                "Rule_Identifier": {
                                    "Id": "142",
                                    "Version": "1"
                                },
                                "Version": "4",
                                "Citations": [
                                    {
                                        "Cited_Guidance": "One record per test per observation time per subject, Tabulation.",
                                        "Document": "SENDIG v3.1",
                                        "Section": "6.3.1"
                                    }
                                ]
                            }
                        ]
                    },
                    {
                        "Name": "SENDID-GENETOX",
                        "Version": "v1.0",
                        "References": [
                            {
                                "Origin": "SENDIG Conformance Rules",
                                "Rule_Identifier": {
                                    "Id": "142",
                                    "Version": "1"
                                },
                                "Version": "4",
                                "Citations": [
                                    {
                                        "Cited_Guidance": "One record per test per observation time per subject, Tabulation.",
                                        "Document": "SENDIG v3.1",
                                        "Section": "6.3.1"
                                    }
                                ]
                            }
                        ]
                    }
                ]
            }
        ],
        "Scope": {
            "Classes": {
                "Include": [
                    "FINDINGS"
                ]
            },
            "Domains": {
                "Include": [
                    "BW"
                ]
            }
        }
    },
    "id": "057768c5-07b9-4224-a235-29d67fbea484"
}