{
    "changed": "2022-09-10T13:54:57.035Z",
    "content": "Check:\n  all:\n    - name: variable_name\n      operator: not_matches_regex\n      value: ^[A-Z]*$\nCore:\n  Id: CDISC.SENDIG.30\n  Version: '1'\n  Status: Draft\nDescription: Raise an error when variable name is not in uppercase\nOutcome:\n  Message: Variable name must be in uppercase\nRule Type: Variable Metadata Check\nSensitivity: Variable\nAuthorities:\n  - Organization: CDISC\n    Standards:\n      - Name: SENDIG\n        Version: '3.1'\n        References:\n          - Origin: SDTM and SENDIG Conformance Rules\n            Rule Identifier:\n              Id: '30'\n              Version: '1'\n            Version: '2.0'\n            Citations:\n              - Cited Guidance: Variable names should be represented in uppercase.\n                Document: IG v3.1\n                Section: 4.2.1\nScope:\n  Classes:\n    Include:\n      - ALL\n  Domains:\n    Include:\n      - ALL\n",
    "created": "2022-09-10T13:39:32.499Z",
    "creator": {
        "id": "dc8bf014-df32-4631-8684-9a09a16c5071"
    },
    "json": {
        "Check": {
            "all": [
                {
                    "name": "variable_name",
                    "operator": "not_matches_regex",
                    "value": "^[A-Z]*$"
                }
            ]
        },
        "Core": {
            "Id": "CDISC.SENDIG.30",
            "Version": "1",
            "Status": "Draft"
        },
        "Description": "Raise an error when variable name is not in uppercase",
        "Outcome": {
            "Message": "Variable name must be in uppercase"
        },
        "Rule_Type": "Variable Metadata Check",
        "Sensitivity": "Variable",
        "Authorities": [
            {
                "Organization": "CDISC",
                "Standards": [
                    {
                        "Name": "SENDIG",
                        "Version": "3.1",
                        "References": [
                            {
                                "Origin": "SDTM and SENDIG Conformance Rules",
                                "Rule_Identifier": {
                                    "Id": "30",
                                    "Version": "1"
                                },
                                "Version": "2.0",
                                "Citations": [
                                    {
                                        "Cited_Guidance": "Variable names should be represented in uppercase.",
                                        "Document": "IG v3.1",
                                        "Section": "4.2.1"
                                    }
                                ]
                            }
                        ]
                    }
                ]
            }
        ],
        "Scope": {
            "Classes": {
                "Include": [
                    "ALL"
                ]
            },
            "Domains": {
                "Include": [
                    "ALL"
                ]
            }
        }
    },
    "id": "ea944866-e8a1-45c5-b374-bdf9b5dcc541"
}