{
    "id": "2da38f25-dc11-4265-ae2f-4ca830ab4870",
    "changed": "2023-02-28T16:37:36.314Z",
    "content": "Check:\n  all:\n    - name: $TRTSDT_EXISTS\n      operator: equal_to\n      value: false\n    - name: $TRTSDTM_EXISTS\n      operator: equal_to\n      value: false\n    - name: EX\n      operator: exists\nOperations:\n  - id: $TRTSDT_EXISTS\n    domain: ADSL\n    name: TRTSDT\n    operator: variable_exists\n  - id: $TRTSDTM_EXISTS\n    domain: ADSL\n    name: TRTSDTM\n    operator: variable_exists\n\nCore:\n  # Need to make yaml validation accept ADAMIG\n  # Will we need to prepend ADaM rules with \"AD0...\"? \n  # (column \"Check Number\" in ADaM_Conformance_Rules_v4.0 is 1-3 digits only, some with a \",1\" (e.g. \"37,01\") )\n  Id: CDISC.ADAMIG.AD0061\n  Version: '1'\n  Status: Draft\nDescription: Raise an error when TRTSDT and/or TRTSDTM are not present, though data\n  exist in SDTM.EX\nOutcome:\n  Message: SDTM.EX is present and neither TRTSDT or TRTSDTM are present\n  Output Variables: \nRule Type: Domain Presence Check\nSensitivity: Dataset\nAuthorities:\n  - Organization: CDISC\n    Standards:\n      - Name: ADAMIG\n        Version: '1.3'\n        References:\n  # Origin for ADaM/ADaMIG should be defined in yaml validation schema\n          - Origin: ADaM Conformance Rules\n            Rule Identifier:\n              Id: AD0061\n              Version: '1'\n    # Version 4.0 for ADaM/ADaMIG should be allowed according to yaml validation schema\n            Version: '4.0'\n            Citations:\n              - Document: IG v1.3\n                Section: 3.2\n                Cited Guidance: >-\n                  ADaM IG v1.3, Section 3.2, Table 3.2.6:  TRTSDT and/or TRTSDTM are\n                  required if there is an investigational product.\nScope:\n  Classes:\n    Include:\n      # What ADaM classes will be defined? ADSL, BDS, OCCDS, OTHER?\n      - ADSL\n  Domains:\n    Include:\n      - ADSL\n      - EX\n",
    "created": "2022-08-11T08:56:35Z",
    "creator": {
        "id": "ff3f6fbb-6aa3-4353-9941-60f9da14b0e4"
    },
    "json": {
        "Check": {
            "all": [
                {
                    "name": "$TRTSDT_EXISTS",
                    "operator": "equal_to",
                    "value": false
                },
                {
                    "name": "$TRTSDTM_EXISTS",
                    "operator": "equal_to",
                    "value": false
                },
                {
                    "name": "EX",
                    "operator": "exists"
                }
            ]
        },
        "Operations": [
            {
                "id": "$TRTSDT_EXISTS",
                "domain": "ADSL",
                "name": "TRTSDT",
                "operator": "variable_exists"
            },
            {
                "id": "$TRTSDTM_EXISTS",
                "domain": "ADSL",
                "name": "TRTSDTM",
                "operator": "variable_exists"
            }
        ],
        "Core": {
            "Id": "CDISC.ADAMIG.AD0061",
            "Version": "1",
            "Status": "Draft"
        },
        "Description": "Raise an error when TRTSDT and/or TRTSDTM are not present, though data exist in SDTM.EX",
        "Outcome": {
            "Message": "SDTM.EX is present and neither TRTSDT or TRTSDTM are present",
            "Output_Variables": null
        },
        "Sensitivity": "Dataset",
        "Authorities": [
            {
                "Organization": "CDISC",
                "Standards": [
                    {
                        "Name": "ADAMIG",
                        "Version": "1.3",
                        "References": [
                            {
                                "Origin": "ADaM Conformance Rules",
                                "Version": "4.0",
                                "Citations": [
                                    {
                                        "Document": "IG v1.3",
                                        "Section": 3.2,
                                        "Cited_Guidance": "ADaM IG v1.3, Section 3.2, Table 3.2.6:  TRTSDT and/or TRTSDTM are required if there is an investigational product."
                                    }
                                ],
                                "Rule_Identifier": {
                                    "Id": "AD0061",
                                    "Version": "1"
                                }
                            }
                        ]
                    }
                ]
            }
        ],
        "Scope": {
            "Classes": {
                "Include": [
                    "ADSL"
                ]
            },
            "Domains": {
                "Include": [
                    "ADSL",
                    "EX"
                ]
            }
        },
        "Rule_Type": "Domain Presence Check"
    }
}