{
    "changed": "2022-09-27T12:33:44.075Z",
    "content": "Check:\n  all:\n    - name: ARM\n      operator: non_empty\n    - name: ARM\n      operator: is_not_contained_by\n      value: $ta_arm\nOperations:\n  - domain: TA\n    id: $ta_arm\n    name: ARM\n    operator: distinct\nCore:\n  Id: CDISC.SENDIG.225\n  Version: '1'\n  Status: Draft\nDescription: When study does not use multi-stage arm assignments and ARMCD is populated,\n  ARMCD must be present in TA.ARMCD. This rule has been executed to identify all cases\n  when ARMCD is not present in TA.ARMCD and therefore acknowledges that false positives\n  may be recorded when multi-stage arm assignments are in use.\nOutcome:\n  Message: ARM is not present in TA.ARM\nRule Type: Record Data\nSensitivity: Record\nAuthorities:\n  - Organization: CDISC\n    Standards:\n      - Name: SENDIG\n        Version: '3.1'\n        References:\n          - Origin: SDTM and SENDIG Conformance Rules\n            Rule Identifier:\n              Id: '225'\n              Version: '1'\n            Version: '2.0'\n            Citations:\n              - Cited Guidance: ARM and ARMCD values in DM and TA must coincide (ARM\n                  and ARMCD are defined as the planned Trial Arms in TA, and the planned\n                  Arms are then applied to subjects in DM).\n                Document: IG v3.1\n                Item: Specification\n                Section: 7.3.3.1\nScope:\n  Classes:\n    Include:\n      - SPECIAL-PURPOSE\n  Domains:\n    Include:\n      - DM\n",
    "created": "2022-09-27T12:33:44.075Z",
    "creator": {
        "id": "dc8bf014-df32-4631-8684-9a09a16c5071"
    },
    "json": {
        "Check": {
            "all": [
                {
                    "name": "ARM",
                    "operator": "non_empty"
                },
                {
                    "name": "ARM",
                    "operator": "is_not_contained_by",
                    "value": "$ta_arm"
                }
            ]
        },
        "Operations": [
            {
                "domain": "TA",
                "id": "$ta_arm",
                "name": "ARM",
                "operator": "distinct"
            }
        ],
        "Core": {
            "Id": "CDISC.SENDIG.225",
            "Version": "1",
            "Status": "Draft"
        },
        "Description": "When study does not use multi-stage arm assignments and ARMCD is populated, ARMCD must be present in TA.ARMCD. This rule has been executed to identify all cases when ARMCD is not present in TA.ARMCD and therefore acknowledges that false positives may be recorded when multi-stage arm assignments are in use.",
        "Outcome": {
            "Message": "ARM is not present in TA.ARM"
        },
        "Rule_Type": "Record Data",
        "Sensitivity": "Record",
        "Authorities": [
            {
                "Organization": "CDISC",
                "Standards": [
                    {
                        "Name": "SENDIG",
                        "Version": "3.1",
                        "References": [
                            {
                                "Origin": "SDTM and SENDIG Conformance Rules",
                                "Rule_Identifier": {
                                    "Id": "225",
                                    "Version": "1"
                                },
                                "Version": "2.0",
                                "Citations": [
                                    {
                                        "Cited_Guidance": "ARM and ARMCD values in DM and TA must coincide (ARM and ARMCD are defined as the planned Trial Arms in TA, and the planned Arms are then applied to subjects in DM).",
                                        "Document": "IG v3.1",
                                        "Item": "Specification",
                                        "Section": "7.3.3.1"
                                    }
                                ]
                            }
                        ]
                    }
                ]
            }
        ],
        "Scope": {
            "Classes": {
                "Include": [
                    "SPECIAL-PURPOSE"
                ]
            },
            "Domains": {
                "Include": [
                    "DM"
                ]
            }
        }
    },
    "id": "f9e455a9-6fa6-4365-971f-a61bd35392f5"
}