{
    "changed": "2022-09-16T13:48:34.466Z",
    "content": "Check:\n  all:\n    - name: EXDOSE\n      operator: equal_to\n      value: 0\n    - name: EXLOT\n      operator: non_empty\nCore:\n  Id: CDISC.SENDIG.134\n  Version: '1'\n  Status: Draft\nDescription: If no test article (as described in EXTRT) is administered (i.e., EXDOSE\n  is 0), EXLOT is null.\nOutcome:\n  Message: EXDOSE is 0, EXLOT may not be populated\n  Output Variables:\n    - EXDOSE\n    - EXLOT\nRule Type: Record Data\nSensitivity: Record\nAuthorities:\n  - Organization: CDISC\n    Standards:\n      - Name: SENDIG\n        Version: '3.1'\n        References:\n          - Origin: SDTM and SENDIG Conformance Rules\n            Rule Identifier:\n              Id: '134'\n              Version: '1'\n            Version: '2.0'\n            Citations:\n              - Cited Guidance:\n                Document: IG v3.1\n                Section: 6.1.1\nScope:\n  Classes:\n    Include:\n      - INTERVENTIONS\n  Domains:\n    Include:\n      - EX\n",
    "created": "2022-09-16T13:46:51.694Z",
    "creator": {
        "id": "dc8bf014-df32-4631-8684-9a09a16c5071"
    },
    "json": {
        "Check": {
            "all": [
                {
                    "name": "EXDOSE",
                    "operator": "equal_to",
                    "value": 0
                },
                {
                    "name": "EXLOT",
                    "operator": "non_empty"
                }
            ]
        },
        "Core": {
            "Id": "CDISC.SENDIG.134",
            "Version": "1",
            "Status": "Draft"
        },
        "Description": "If no test article (as described in EXTRT) is administered (i.e., EXDOSE is 0), EXLOT is null.",
        "Outcome": {
            "Message": "EXDOSE is 0, EXLOT may not be populated",
            "Output_Variables": [
                "EXDOSE",
                "EXLOT"
            ]
        },
        "Rule_Type": "Record Data",
        "Sensitivity": "Record",
        "Authorities": [
            {
                "Organization": "CDISC",
                "Standards": [
                    {
                        "Name": "SENDIG",
                        "Version": "3.1",
                        "References": [
                            {
                                "Origin": "SDTM and SENDIG Conformance Rules",
                                "Rule_Identifier": {
                                    "Id": "134",
                                    "Version": "1"
                                },
                                "Version": "2.0",
                                "Citations": [
                                    {
                                        "Cited_Guidance": null,
                                        "Document": "IG v3.1",
                                        "Section": "6.1.1"
                                    }
                                ]
                            }
                        ]
                    }
                ]
            }
        ],
        "Scope": {
            "Classes": {
                "Include": [
                    "INTERVENTIONS"
                ]
            },
            "Domains": {
                "Include": [
                    "EX"
                ]
            }
        }
    },
    "id": "0c72eebe-d3e8-4dc5-ae26-c20d3e10c72f"
}