{
    "changed": "2023-02-16T16:40:11.978Z",
    "content": "Executability: Fully Executable\r\nCheck:\r\n  all:\r\n    - name: FASFL\r\n      operator: exists\r\n    - name: FASFL\r\n      operator: is_not_contained_by\r\n      value:\r\n        - 'Y'\r\n        - 'N'\r\nCore:\r\n  Id: CDISC.ADAMIG.AD0020\r\n  Version: '1'\r\n  Status: Draft\r\nDescription: >-\r\n  Raise an error when FASFL is present and has a value that is not Y or N\r\nOutcome:\r\n  Message: The values of FASFL are not following the \"Y, N\" codelist\r\n  Output Variables:\r\n    - FASFL\r\nRule Type: Record Data\r\nSensitivity: Record\r\nAuthorities:\r\n  - Organization: CDISC\r\n    Standards:\r\n      - Name: ADaMIG\r\n        Version: '1.3'\r\n        References:\r\n          - Origin: ADaM Conformance Rules\r\n            Rule Identifier:\r\n              Id: '20'\r\n              Version: '1'\r\n            Version: '4.0'\r\n            Citations:\r\n              - Document: ADaM IG v1.3\r\n                Section: '3.2'\r\n                Item: Table 3.2.3\r\n                Cited Guidance: >-\r\n                  ADaM IG v1.3, Section 3.2, Table 3.2.3: Population Indicator(s)\r\n                  have a Codelist / Controlled Term value of \"Y, N\".\r\n      - Name: ADaMIG\r\n        Version: '1.2'\r\n        References:\r\n          - Origin: ADaM Conformance Rules\r\n            Rule Identifier:\r\n              Id: '20'\r\n              Version: '1'\r\n            Version: '4.0'\r\n            Citations:\r\n              - Document: ADaM IG v1.2\r\n                Section: '3.2'\r\n                Item: Table 3.2.3\r\n                Cited Guidance: >-\r\n                  ADaM IG v1.2, Section 3.2, Table 3.2.3: Population Indicator(s)\r\n                  have a Codelist / Controlled Term value of \"Y, N\".\r\n      - Name: ADaMIG\r\n        Version: '1.1'\r\n        References:\r\n          - Origin: ADaM Conformance Rules\r\n            Rule Identifier:\r\n              Id: '20'\r\n              Version: '1'\r\n            Version: '4.0'\r\n            Citations:\r\n              - Document: ADaM IG v1.1\r\n                Section: '3.2'\r\n                Item: Table 3.2.3\r\n                Cited Guidance: >-\r\n                  ADaM IG v1.1, Section 3.2, Table 3.2.3: Population Indicator(s)\r\n                  have a Codelist / Controlled Term value of \"Y, N\".\r\n      - Name: ADaMIG\r\n        Version: '1.0'\r\n        References:\r\n          - Origin: ADaM Conformance Rules\r\n            Rule Identifier:\r\n              Id: '20'\r\n              Version: '1'\r\n            Version: '4.0'\r\n            Citations:\r\n              - Document: ADaM IG v1.0\r\n                Section: '3.1'\r\n                Item: Table 3.1.1\r\n                Cited Guidance: >-\r\n                  ADaM IG v1.0, Section 3.1, Table 3.1.1: Population Indicator(s)\r\n                  have a Codelist / Controlled Term value of \"Y, N\".\r\nScope:\r\n  Data Structures:\r\n    Include:\r\n      - SUBJECT LEVEL ANALYSIS DATASET\r\n",
    "created": "2022-12-22T04:50:26.937Z",
    "creator": {
        "id": "748e82c6-80f0-41af-be9b-499879aa2943"
    },
    "json": {
        "Executability": "Fully Executable",
        "Check": {
            "all": [
                {
                    "name": "FASFL",
                    "operator": "exists"
                },
                {
                    "name": "FASFL",
                    "operator": "is_not_contained_by",
                    "value": [
                        "Y",
                        "N"
                    ]
                }
            ]
        },
        "Core": {
            "Id": "CDISC.ADAMIG.AD0020",
            "Version": "1",
            "Status": "Draft"
        },
        "Description": "Raise an error when FASFL is present and has a value that is not Y or N",
        "Outcome": {
            "Message": "The values of FASFL are not following the \"Y, N\" codelist",
            "Output_Variables": [
                "FASFL"
            ]
        },
        "Sensitivity": "Record",
        "Authorities": [
            {
                "Organization": "CDISC",
                "Standards": [
                    {
                        "Name": "ADaMIG",
                        "Version": "1.3",
                        "References": [
                            {
                                "Origin": "ADaM Conformance Rules",
                                "Version": "4.0",
                                "Citations": [
                                    {
                                        "Document": "ADaM IG v1.3",
                                        "Section": "3.2",
                                        "Item": "Table 3.2.3",
                                        "Cited_Guidance": "ADaM IG v1.3, Section 3.2, Table 3.2.3: Population Indicator(s) have a Codelist / Controlled Term value of \"Y, N\"."
                                    }
                                ],
                                "Rule_Identifier": {
                                    "Id": "20",
                                    "Version": "1"
                                }
                            }
                        ]
                    },
                    {
                        "Name": "ADaMIG",
                        "Version": "1.2",
                        "References": [
                            {
                                "Origin": "ADaM Conformance Rules",
                                "Version": "4.0",
                                "Citations": [
                                    {
                                        "Document": "ADaM IG v1.2",
                                        "Section": "3.2",
                                        "Item": "Table 3.2.3",
                                        "Cited_Guidance": "ADaM IG v1.2, Section 3.2, Table 3.2.3: Population Indicator(s) have a Codelist / Controlled Term value of \"Y, N\"."
                                    }
                                ],
                                "Rule_Identifier": {
                                    "Id": "20",
                                    "Version": "1"
                                }
                            }
                        ]
                    },
                    {
                        "Name": "ADaMIG",
                        "Version": "1.1",
                        "References": [
                            {
                                "Origin": "ADaM Conformance Rules",
                                "Version": "4.0",
                                "Citations": [
                                    {
                                        "Document": "ADaM IG v1.1",
                                        "Section": "3.2",
                                        "Item": "Table 3.2.3",
                                        "Cited_Guidance": "ADaM IG v1.1, Section 3.2, Table 3.2.3: Population Indicator(s) have a Codelist / Controlled Term value of \"Y, N\"."
                                    }
                                ],
                                "Rule_Identifier": {
                                    "Id": "20",
                                    "Version": "1"
                                }
                            }
                        ]
                    },
                    {
                        "Name": "ADaMIG",
                        "Version": "1.0",
                        "References": [
                            {
                                "Origin": "ADaM Conformance Rules",
                                "Version": "4.0",
                                "Citations": [
                                    {
                                        "Document": "ADaM IG v1.0",
                                        "Section": "3.1",
                                        "Item": "Table 3.1.1",
                                        "Cited_Guidance": "ADaM IG v1.0, Section 3.1, Table 3.1.1: Population Indicator(s) have a Codelist / Controlled Term value of \"Y, N\"."
                                    }
                                ],
                                "Rule_Identifier": {
                                    "Id": "20",
                                    "Version": "1"
                                }
                            }
                        ]
                    }
                ]
            }
        ],
        "Scope": {
            "Data_Structures": {
                "Include": [
                    "SUBJECT LEVEL ANALYSIS DATASET"
                ]
            }
        },
        "Rule_Type": "Record Data"
    },
    "id": "65d7dc9a-01d3-4171-b0bc-ef94fafc2fa3"
}