{
    "changed": "2022-09-15T14:19:36.620Z",
    "content": "Check:\n  all:\n    - name: AGEU\n      operator: empty\n    - any:\n        - name: AGETXT\n          operator: non_empty\n        - name: AGE\n          operator: non_empty\nCore:\n  Id: CDISC.SENDIG.104\n  Version: '1'\n  Status: Draft\nDescription: AGEU is the until associated with AGE or AGETXT.  If either of those\n  variables is populated, AGEU should be populated.\nOutcome:\n  Message: AGE or AGETXT is populated, but AGEU is not populated\n  Output Variables:\n    - USUBJID\n    - AGETXT\n    - AGE\n    - AGEU\nRule Type: Record Data\nSensitivity: Study\nAuthorities:\n  - Organization: CDISC\n    Standards:\n      - Name: SENDIG\n        Version: '3.1'\n        References:\n          - Origin: SDTM and SENDIG Conformance Rules\n            Rule Identifier:\n              Id: '104'\n              Version: '1'\n            Version: '2.0'\n            Citations:\n              - Cited Guidance: AGETXT is used to present the age range in situations\n                  where the exact birthdate is not known.  If AGETXT is included both\n                  BRTHDTC and AGE should not be populated.\n                Document: IG v3.1\n                Item: Specification\n                Section: 5.1.1\nScope:\n  Classes:\n    Include:\n      - SPECIAL-PURPOSE\n  Domains:\n    Include:\n      - DM\n",
    "created": "2022-09-15T13:50:42.794Z",
    "creator": {
        "id": "dc8bf014-df32-4631-8684-9a09a16c5071"
    },
    "json": {
        "Check": {
            "all": [
                {
                    "name": "AGEU",
                    "operator": "empty"
                },
                {
                    "any": [
                        {
                            "name": "AGETXT",
                            "operator": "non_empty"
                        },
                        {
                            "name": "AGE",
                            "operator": "non_empty"
                        }
                    ]
                }
            ]
        },
        "Core": {
            "Id": "CDISC.SENDIG.104",
            "Version": "1",
            "Status": "Draft"
        },
        "Description": "AGEU is the until associated with AGE or AGETXT.  If either of those variables is populated, AGEU should be populated.",
        "Outcome": {
            "Message": "AGE or AGETXT is populated, but AGEU is not populated",
            "Output_Variables": [
                "USUBJID",
                "AGETXT",
                "AGE",
                "AGEU"
            ]
        },
        "Rule_Type": "Record Data",
        "Sensitivity": "Study",
        "Authorities": [
            {
                "Organization": "CDISC",
                "Standards": [
                    {
                        "Name": "SENDIG",
                        "Version": "3.1",
                        "References": [
                            {
                                "Origin": "SDTM and SENDIG Conformance Rules",
                                "Rule_Identifier": {
                                    "Id": "104",
                                    "Version": "1"
                                },
                                "Version": "2.0",
                                "Citations": [
                                    {
                                        "Cited_Guidance": "AGETXT is used to present the age range in situations where the exact birthdate is not known.  If AGETXT is included both BRTHDTC and AGE should not be populated.",
                                        "Document": "IG v3.1",
                                        "Item": "Specification",
                                        "Section": "5.1.1"
                                    }
                                ]
                            }
                        ]
                    }
                ]
            }
        ],
        "Scope": {
            "Classes": {
                "Include": [
                    "SPECIAL-PURPOSE"
                ]
            },
            "Domains": {
                "Include": [
                    "DM"
                ]
            }
        }
    },
    "id": "8948f2b4-494a-481a-a4d0-4010b088dff5"
}