{
    "changed": "2022-09-15T08:04:08.466Z",
    "content": "Check:\n  all:\n    - name: --STAT\n      operator: not_equal_to\n      value: NOT DONE\n    - name: --ORRES\n      operator: empty\nCore:\n  Id: CDISC.SENDIG.85\n  Version: '1'\n  Status: Draft\nDescription: There should always be data presented in the --ORRES variable unless  --STAT\n  = \"NOT DONE\".\nOutcome:\n  Message: --ORRES must be populated as --STAT is not equal to 'NOT DONE'\n  Output Variables:\n    - --STAT\n    - --ORRES\nRule Type: Record Data\nSensitivity: Record\nAuthorities:\n  - Organization: CDISC\n    Standards:\n      - Name: SENDIG\n        Version: '3.1'\n        References:\n          - Origin: SDTM and SENDIG Conformance Rules\n            Rule Identifier:\n              Id: '85'\n              Version: '1'\n            Version: '2.0'\n            Citations:\n              - Cited Guidance: --ORRES is an Expected variable and should always\n                  be populated except when --STAT = 'NOT DONE'\n                Document: IG v3.1\n                Section: 4.5.1.1\nScope:\n  Classes:\n    Include:\n      - FINDINGS\n  Domains:\n    Include:\n      - ALL\n",
    "created": "2022-09-15T06:35:33.546Z",
    "creator": {
        "id": "dc8bf014-df32-4631-8684-9a09a16c5071"
    },
    "json": {
        "Check": {
            "all": [
                {
                    "name": "--STAT",
                    "operator": "not_equal_to",
                    "value": "NOT DONE"
                },
                {
                    "name": "--ORRES",
                    "operator": "empty"
                }
            ]
        },
        "Core": {
            "Id": "CDISC.SENDIG.85",
            "Version": "1",
            "Status": "Draft"
        },
        "Description": "There should always be data presented in the --ORRES variable unless  --STAT = \"NOT DONE\".",
        "Outcome": {
            "Message": "--ORRES must be populated as --STAT is not equal to 'NOT DONE'",
            "Output_Variables": [
                "--STAT",
                "--ORRES"
            ]
        },
        "Rule_Type": "Record Data",
        "Sensitivity": "Record",
        "Authorities": [
            {
                "Organization": "CDISC",
                "Standards": [
                    {
                        "Name": "SENDIG",
                        "Version": "3.1",
                        "References": [
                            {
                                "Origin": "SDTM and SENDIG Conformance Rules",
                                "Rule_Identifier": {
                                    "Id": "85",
                                    "Version": "1"
                                },
                                "Version": "2.0",
                                "Citations": [
                                    {
                                        "Cited_Guidance": "--ORRES is an Expected variable and should always be populated except when --STAT = 'NOT DONE'",
                                        "Document": "IG v3.1",
                                        "Section": "4.5.1.1"
                                    }
                                ]
                            }
                        ]
                    }
                ]
            }
        ],
        "Scope": {
            "Classes": {
                "Include": [
                    "FINDINGS"
                ]
            },
            "Domains": {
                "Include": [
                    "ALL"
                ]
            }
        }
    },
    "id": "efb5f026-e2ce-45f3-aa1e-bbe7ccd0e173"
}