{
    "id": "1dced49a-2a56-471e-a21c-d8a8030de454",
    "changed": "2022-09-20T15:50:59.053Z",
    "content": "Check:\n  all:\n    - name: dataset_name\n      operator: equal_to_case_insensitive\n      value: DOMAIN\nCore:\n  Id: CDISC.SENDIG.SEND1\n  Version: '1'\n  Status: Draft\nDescription: Raise an error when the filename is not equal to the value of DOMAIN.\nOutcome:\n  Message: The filename is not equal to the 2-character domain code.\n  Output Variables:\n    - DOMAIN\nRule Type: Dataset Metadata Check\nSensitivity: Dataset\nAuthorities:\n  - Organization: CDISC\n    Standards:\n      - Name: SENDIG\n        Version: '3.1'\n        References:\n          - Origin: SENDIG Conformance Rules\n            Rule Identifier:\n              Id: '1'\n              Version: '1'\n            Version: '5'\n            Citations:\n              - Cited Guidance: SDTM datasets are normally named to be consistent\n                  with the domain code.\n                Document: SENDIG v3.1\n                Section: 4.1.4\nScope:\n  Classes:\n    Include:\n      - ALL\n  Domains:\n    Include:\n      - ALL\n",
    "created": "2021-10-25T18:58:17Z",
    "creator": {
        "id": "5042c868-b79a-415d-b5aa-12e6474ce80c"
    },
    "json": {
        "Check": {
            "all": [
                {
                    "name": "dataset_name",
                    "operator": "equal_to_case_insensitive",
                    "value": "DOMAIN"
                }
            ]
        },
        "Core": {
            "Id": "CDISC.SENDIG.SEND1",
            "Version": "1",
            "Status": "Draft"
        },
        "Description": "Raise an error when the filename is not equal to the value of DOMAIN.",
        "Outcome": {
            "Message": "The filename is not equal to the 2-character domain code.",
            "Output_Variables": [
                "DOMAIN"
            ]
        },
        "Rule_Type": "Dataset Metadata Check",
        "Sensitivity": "Dataset",
        "Authorities": [
            {
                "Organization": "CDISC",
                "Standards": [
                    {
                        "Name": "SENDIG",
                        "Version": "3.1",
                        "References": [
                            {
                                "Origin": "SENDIG Conformance Rules",
                                "Rule_Identifier": {
                                    "Id": "1",
                                    "Version": "1"
                                },
                                "Version": "5",
                                "Citations": [
                                    {
                                        "Cited_Guidance": "SDTM datasets are normally named to be consistent with the domain code.",
                                        "Document": "SENDIG v3.1",
                                        "Section": "4.1.4"
                                    }
                                ]
                            }
                        ]
                    }
                ]
            }
        ],
        "Scope": {
            "Classes": {
                "Include": [
                    "ALL"
                ]
            },
            "Domains": {
                "Include": [
                    "ALL"
                ]
            }
        }
    }
}