{
    "changed": "2022-09-22T10:45:21.788Z",
    "content": "Check:\n  any:\n    - all:\n        - name: ETCD\n          operator: is_not_unique_set\n          value:\n            - ELEMENT\n            - TESTRL\n            - TEENRL\n        - name: TEDUR\n          operator: not_exists\n    - all:\n        - name: ETCD\n          operator: is_not_unique_set\n          value:\n            - ELEMENT\n            - TESTRL\n            - TEDUR\n        - name: TEENRL\n          operator: not_exists\n    - name: ETCD\n      operator: is_not_unique_set\n      value:\n        - ELEMENT\n        - TESTRL\n        - TEENRL\n        - TEDUR\nCore:\n  Id: CDISC.SENDIG.216\n  Version: '1'\n  Status: Draft\nDescription: The combination of ELEMENT, TESTRL, TEENRL, and TEDUR must be unique\n  for each ETCD.\nOutcome:\n  Message: The combination of ELEMENT, TESTRL, TEENRL, and TEDUR is not unique for\n    each ETCD\n  Output Variables:\n    - ELEMENT\n    - TESTRL\n    - TEENRL\n    - TEDUR\nRule Type: Record Data\nSensitivity: Dataset\nAuthorities:\n  - Organization: CDISC\n    Standards:\n      - Name: SENDIG\n        Version: '3.1'\n        References:\n          - Origin: SDTM and SENDIG Conformance Rules\n            Rule Identifier:\n              Id: '216'\n              Version: '2'\n            Version: '2.0'\n            Citations:\n              - Cited Guidance: Elements with different start and end rules are different\n                  Elements and must be represented as unique values in ELEMENT and\n                  ETCD (i.e., Elements involving the same treatment but different\n                  durations are different Elements). The same applies to nontreatment\n                  Elements (e.g., a washout with a fixed duration of 14 days is different\n                  from a washout that ends after 7 days if drug cannot be detected\n                  in a blood sample or after 14 days if drug can be detected in a\n                  blood sample). Additional factors beyond treatment, start rule,\n                  and either end rule or duration do not distinguish separate Elements.\n                Document: IG v3.1\n                Section: 7.2.1.1\nScope:\n  Classes:\n    Include:\n      - TRIAL DESIGN\n  Domains:\n    Include:\n      - TE\n",
    "created": "2022-09-22T10:45:21.788Z",
    "creator": {
        "id": "dc8bf014-df32-4631-8684-9a09a16c5071"
    },
    "json": {
        "Check": {
            "any": [
                {
                    "all": [
                        {
                            "name": "ETCD",
                            "operator": "is_not_unique_set",
                            "value": [
                                "ELEMENT",
                                "TESTRL",
                                "TEENRL"
                            ]
                        },
                        {
                            "name": "TEDUR",
                            "operator": "not_exists"
                        }
                    ]
                },
                {
                    "all": [
                        {
                            "name": "ETCD",
                            "operator": "is_not_unique_set",
                            "value": [
                                "ELEMENT",
                                "TESTRL",
                                "TEDUR"
                            ]
                        },
                        {
                            "name": "TEENRL",
                            "operator": "not_exists"
                        }
                    ]
                },
                {
                    "name": "ETCD",
                    "operator": "is_not_unique_set",
                    "value": [
                        "ELEMENT",
                        "TESTRL",
                        "TEENRL",
                        "TEDUR"
                    ]
                }
            ]
        },
        "Core": {
            "Id": "CDISC.SENDIG.216",
            "Version": "1",
            "Status": "Draft"
        },
        "Description": "The combination of ELEMENT, TESTRL, TEENRL, and TEDUR must be unique for each ETCD.",
        "Outcome": {
            "Message": "The combination of ELEMENT, TESTRL, TEENRL, and TEDUR is not unique for each ETCD",
            "Output_Variables": [
                "ELEMENT",
                "TESTRL",
                "TEENRL",
                "TEDUR"
            ]
        },
        "Rule_Type": "Record Data",
        "Sensitivity": "Dataset",
        "Authorities": [
            {
                "Organization": "CDISC",
                "Standards": [
                    {
                        "Name": "SENDIG",
                        "Version": "3.1",
                        "References": [
                            {
                                "Origin": "SDTM and SENDIG Conformance Rules",
                                "Rule_Identifier": {
                                    "Id": "216",
                                    "Version": "2"
                                },
                                "Version": "2.0",
                                "Citations": [
                                    {
                                        "Cited_Guidance": "Elements with different start and end rules are different Elements and must be represented as unique values in ELEMENT and ETCD (i.e., Elements involving the same treatment but different durations are different Elements). The same applies to nontreatment Elements (e.g., a washout with a fixed duration of 14 days is different from a washout that ends after 7 days if drug cannot be detected in a blood sample or after 14 days if drug can be detected in a blood sample). Additional factors beyond treatment, start rule, and either end rule or duration do not distinguish separate Elements.",
                                        "Document": "IG v3.1",
                                        "Section": "7.2.1.1"
                                    }
                                ]
                            }
                        ]
                    }
                ]
            }
        ],
        "Scope": {
            "Classes": {
                "Include": [
                    "TRIAL DESIGN"
                ]
            },
            "Domains": {
                "Include": [
                    "TE"
                ]
            }
        }
    },
    "id": "501e4478-9875-4051-8b1f-2d2c3ce5eb09"
}