{
    "changed": "2022-10-02T09:08:30.485Z",
    "content": "Check:\n  all:\n    - name: TSPARMCD\n      operator: equal_to\n      value: SNDIGVER\n    - name: TSPARMCD\n      operator: is_not_unique_set\n      value:\n        - DOMAIN\nCore:\n  Id: CDISC.SENDIG.341\n  Version: '1'\n  Status: Draft\nDescription: Raise an error when there is more than record with TSPARMCD=SNDIGVER\nOutcome:\n  Message: Only one record with TSPARMCD=SNDIGVER is allowed\nRule Type: Record Data\nSensitivity: Record\nAuthorities:\n  - Organization: CDISC\n    Standards:\n      - Name: SENDIG\n        Version: '3.1'\n        References:\n          - Origin: SDTM and SENDIG Conformance Rules\n            Rule Identifier:\n              Id: '341'\n              Version: '1'\n            Version: '2.0'\n            Citations:\n              - Cited Guidance: This Implementation Guide (IG) defines recommended\n                  standards for the submission of data from nonclinical Developmental\n                  and Reproductive Toxicology (DART) studies, and is referred to as\n                  the SENDIG-DART. This IG is based on and should be used in close\n                  concert with Version 3.1 of the Standard for Exchange of Nonclinical\n                  Data Implementation Guide (SENDIG) and Version 1.6 of the CDISC\n                  Study Data Tabulation Model (SDTM), available at https://www.cdisc.org/standards/.\n                Document: IG v3.1\n                Section: '1.1'\nScope:\n  Classes:\n    Include:\n      - TRIAL DESIGN\n  Domains:\n    Include:\n      - TS\n",
    "created": "2022-10-02T09:06:30.288Z",
    "creator": {
        "id": "dc8bf014-df32-4631-8684-9a09a16c5071"
    },
    "json": {
        "Check": {
            "all": [
                {
                    "name": "TSPARMCD",
                    "operator": "equal_to",
                    "value": "SNDIGVER"
                },
                {
                    "name": "TSPARMCD",
                    "operator": "is_not_unique_set",
                    "value": [
                        "DOMAIN"
                    ]
                }
            ]
        },
        "Core": {
            "Id": "CDISC.SENDIG.341",
            "Version": "1",
            "Status": "Draft"
        },
        "Description": "Raise an error when there is more than record with TSPARMCD=SNDIGVER",
        "Outcome": {
            "Message": "Only one record with TSPARMCD=SNDIGVER is allowed"
        },
        "Rule_Type": "Record Data",
        "Sensitivity": "Record",
        "Authorities": [
            {
                "Organization": "CDISC",
                "Standards": [
                    {
                        "Name": "SENDIG",
                        "Version": "3.1",
                        "References": [
                            {
                                "Origin": "SDTM and SENDIG Conformance Rules",
                                "Rule_Identifier": {
                                    "Id": "341",
                                    "Version": "1"
                                },
                                "Version": "2.0",
                                "Citations": [
                                    {
                                        "Cited_Guidance": "This Implementation Guide (IG) defines recommended standards for the submission of data from nonclinical Developmental and Reproductive Toxicology (DART) studies, and is referred to as the SENDIG-DART. This IG is based on and should be used in close concert with Version 3.1 of the Standard for Exchange of Nonclinical Data Implementation Guide (SENDIG) and Version 1.6 of the CDISC Study Data Tabulation Model (SDTM), available at https://www.cdisc.org/standards/.",
                                        "Document": "IG v3.1",
                                        "Section": "1.1"
                                    }
                                ]
                            }
                        ]
                    }
                ]
            }
        ],
        "Scope": {
            "Classes": {
                "Include": [
                    "TRIAL DESIGN"
                ]
            },
            "Domains": {
                "Include": [
                    "TS"
                ]
            }
        }
    },
    "id": "44177072-fc54-4b57-bc0d-d2b624b4ee3f"
}