{
    "changed": "2023-02-23T16:54:44.546Z",
    "content": "Check:\n  all:\n    - name: USUBJID\n      operator: is_not_unique_set\n      value: DOMAIN\nCore:\n  Id: CDISC.SENDIG.97\n  Version: '1'\n  Status: Draft\nDescription: DM - One record per subject\nOutcome:\n  Message: USUBJID is not unique within DM\n  Output Variables:\n    - USUBJID\nRule Type: Record Data\nSensitivity: Record\nExecutability: Fully Executable\nAuthorities:\n  - Organization: CDISC\n    Standards:\n      - Name: SENDIG-DART\n        Version: '1.1'\n        References:\n          - Origin: SEND Conformance Rules\n            Rule Identifier:\n              Id: '97'\n              Version: '1'\n            Version: '2.0'\n            Citations:\n              - Cited Guidance: dm.xpt, Demographics - Special-Purpose Domains. One\n                  record per subject, Tabulation.\n                Document: IG v1.1\n                Item: Specification\n                Section: 5.1.1\n      - Name: SENDIG\n        Version: '3.1.1'\n        References:\n          - Origin: SDTM and SENDIG Conformance Rules\n            Rule Identifier:\n              Id: '97'\n              Version: '1'\n            Version: '2.0'\n            Citations:\n              - Cited Guidance: dm.xpt, Demographics - Special-Purpose Domains. One\n                  record per subject, Tabulation.\n                Document: IG v3.1.1\n                Item: Specification\n                Section: 5.1.1\n      - Name: SENDIG\n        Version: '3.1'\n        References:\n          - Origin: SDTM and SENDIG Conformance Rules\n            Rule Identifier:\n              Id: '97'\n              Version: '1'\n            Version: '2.0'\n            Citations:\n              - Cited Guidance: dm.xpt, Demographics - Special-Purpose Domains. One\n                  record per subject, Tabulation.\n                Document: IG v3.1\n                Item: Specification\n                Section: 5.1.1\n      - Name: SENDIG\n        Version: '3.0'\n        References:\n          - Origin: SDTM and SENDIG Conformance Rules\n            Rule Identifier:\n              Id: '97'\n              Version: '1'\n            Version: '2.0'\n            Citations:\n              - Cited Guidance: dm.xpt, Demographics - Special-Purpose Domains. One\n                  record per subject, Tabulation.\n                Document: IG v3.0\n                Item: Specification\n                Section: 5.1.1\nScope:\n  Classes:\n    Include:\n      - SPECIAL PURPOSE\n  Domains:\n    Include:\n      - DM\n",
    "created": "2022-09-15T10:59:42.677Z",
    "creator": {
        "id": "dc8bf014-df32-4631-8684-9a09a16c5071"
    },
    "json": {
        "Check": {
            "all": [
                {
                    "name": "USUBJID",
                    "operator": "is_not_unique_set",
                    "value": "DOMAIN"
                }
            ]
        },
        "Core": {
            "Id": "CDISC.SENDIG.97",
            "Version": "1",
            "Status": "Draft"
        },
        "Description": "DM - One record per subject",
        "Outcome": {
            "Message": "USUBJID is not unique within DM",
            "Output_Variables": [
                "USUBJID"
            ]
        },
        "Sensitivity": "Record",
        "Executability": "Fully Executable",
        "Authorities": [
            {
                "Organization": "CDISC",
                "Standards": [
                    {
                        "Name": "SENDIG-DART",
                        "Version": "1.1",
                        "References": [
                            {
                                "Origin": "SEND Conformance Rules",
                                "Version": "2.0",
                                "Citations": [
                                    {
                                        "Document": "IG v1.1",
                                        "Item": "Specification",
                                        "Section": "5.1.1",
                                        "Cited_Guidance": "dm.xpt, Demographics - Special-Purpose Domains. One record per subject, Tabulation."
                                    }
                                ],
                                "Rule_Identifier": {
                                    "Id": "97",
                                    "Version": "1"
                                }
                            }
                        ]
                    },
                    {
                        "Name": "SENDIG",
                        "Version": "3.1.1",
                        "References": [
                            {
                                "Origin": "SDTM and SENDIG Conformance Rules",
                                "Version": "2.0",
                                "Citations": [
                                    {
                                        "Document": "IG v3.1.1",
                                        "Item": "Specification",
                                        "Section": "5.1.1",
                                        "Cited_Guidance": "dm.xpt, Demographics - Special-Purpose Domains. One record per subject, Tabulation."
                                    }
                                ],
                                "Rule_Identifier": {
                                    "Id": "97",
                                    "Version": "1"
                                }
                            }
                        ]
                    },
                    {
                        "Name": "SENDIG",
                        "Version": "3.1",
                        "References": [
                            {
                                "Origin": "SDTM and SENDIG Conformance Rules",
                                "Version": "2.0",
                                "Citations": [
                                    {
                                        "Document": "IG v3.1",
                                        "Item": "Specification",
                                        "Section": "5.1.1",
                                        "Cited_Guidance": "dm.xpt, Demographics - Special-Purpose Domains. One record per subject, Tabulation."
                                    }
                                ],
                                "Rule_Identifier": {
                                    "Id": "97",
                                    "Version": "1"
                                }
                            }
                        ]
                    },
                    {
                        "Name": "SENDIG",
                        "Version": "3.0",
                        "References": [
                            {
                                "Origin": "SDTM and SENDIG Conformance Rules",
                                "Version": "2.0",
                                "Citations": [
                                    {
                                        "Document": "IG v3.0",
                                        "Item": "Specification",
                                        "Section": "5.1.1",
                                        "Cited_Guidance": "dm.xpt, Demographics - Special-Purpose Domains. One record per subject, Tabulation."
                                    }
                                ],
                                "Rule_Identifier": {
                                    "Id": "97",
                                    "Version": "1"
                                }
                            }
                        ]
                    }
                ]
            }
        ],
        "Scope": {
            "Classes": {
                "Include": [
                    "SPECIAL PURPOSE"
                ]
            },
            "Domains": {
                "Include": [
                    "DM"
                ]
            }
        },
        "Rule_Type": "Record Data"
    },
    "id": "0232e16d-bf34-4494-a934-46dba653a0b0"
}