{
    "changed": "2022-09-19T17:06:20.680Z",
    "content": "Check:\n  all:\n    - name: BGSTRESU\n      operator: is_unique_set\n      value: BGTESTCD\nCore:\n  Id: CDISC.SENDIG.153\n  Version: '1'\n  Status: Draft\nDescription: Trigger error when --BGSTRESU is not consistent within BGTESTCD\nOutcome:\n  Message: BGSTRESU is not consistent within BGTESTCD\n  Output Variables:\n    - BGSTRESU\n    - BGTESTCD\nRule Type: Record Data\nSensitivity: Record\nAuthorities:\n  - Organization: CDISC\n    Standards:\n      - Name: SENDIG\n        Version: '3.1'\n        References:\n          - Origin: SDTM and SENDIG Conformance Rules\n            Rule Identifier:\n              Id: '153'\n              Version: '1'\n            Version: '2.0'\n            Citations:\n              - Cited Guidance: The BGORRESU may change over the course of the study,\n                  e.g., g to kg, but the BGSTRESU should remain consistent throughout\n                  the course of the study.\n                Document: IG v3.1\n                Section: 6.3.1\nScope:\n  Classes:\n    Include:\n      - FINDINGS\n  Domains:\n    Include:\n      - BG\n",
    "created": "2022-09-19T11:33:54.173Z",
    "creator": {
        "id": "dc8bf014-df32-4631-8684-9a09a16c5071"
    },
    "json": {
        "Check": {
            "all": [
                {
                    "name": "BGSTRESU",
                    "operator": "is_unique_set",
                    "value": "BGTESTCD"
                }
            ]
        },
        "Core": {
            "Id": "CDISC.SENDIG.153",
            "Version": "1",
            "Status": "Draft"
        },
        "Description": "Trigger error when --BGSTRESU is not consistent within BGTESTCD",
        "Outcome": {
            "Message": "BGSTRESU is not consistent within BGTESTCD",
            "Output_Variables": [
                "BGSTRESU",
                "BGTESTCD"
            ]
        },
        "Rule_Type": "Record Data",
        "Sensitivity": "Record",
        "Authorities": [
            {
                "Organization": "CDISC",
                "Standards": [
                    {
                        "Name": "SENDIG",
                        "Version": "3.1",
                        "References": [
                            {
                                "Origin": "SDTM and SENDIG Conformance Rules",
                                "Rule_Identifier": {
                                    "Id": "153",
                                    "Version": "1"
                                },
                                "Version": "2.0",
                                "Citations": [
                                    {
                                        "Cited_Guidance": "The BGORRESU may change over the course of the study, e.g., g to kg, but the BGSTRESU should remain consistent throughout the course of the study.",
                                        "Document": "IG v3.1",
                                        "Section": "6.3.1"
                                    }
                                ]
                            }
                        ]
                    }
                ]
            }
        ],
        "Scope": {
            "Classes": {
                "Include": [
                    "FINDINGS"
                ]
            },
            "Domains": {
                "Include": [
                    "BG"
                ]
            }
        }
    },
    "id": "f7531a25-c9de-4fc7-9c06-f8d87f5ec9dc"
}