{
    "changed": "2022-09-15T04:50:06.441Z",
    "content": "Check:\n  any:\n    - name: --DY\n      operator: equal_to\n      value: 0\n    - name: --DY\n      operator: not_matches_regex\n      value: ^-?[0-9]\nCore:\n  Id: CDISC.SENDIG.72\n  Version: '1'\n  Status: Draft\nDescription:\nOutcome:\n  Message: --DY is not a non-zero integer\n  Output Variables:\n    - --DY\nRule Type: Record Data\nSensitivity: Record\nAuthorities:\n  - Organization: CDISC\n    Standards:\n      - Name: SENDIG\n        Version: '3.1'\n        References:\n          - Origin: SDTM and SENDIG Conformance Rules\n            Rule Identifier:\n              Id: '72'\n              Version: '1'\n            Version: '2.0'\n            Citations:\n              - Cited Guidance: All Study Day values are integers.\n                Document: IG v3.1\n                Section: 4.4.4\nScope:\n  Classes:\n    Include:\n      - ALL\n  Domains:\n    Include:\n      - ALL\n",
    "created": "2022-09-14T16:02:18.800Z",
    "creator": {
        "id": "dc8bf014-df32-4631-8684-9a09a16c5071"
    },
    "json": {
        "Check": {
            "any": [
                {
                    "name": "--DY",
                    "operator": "equal_to",
                    "value": 0
                },
                {
                    "name": "--DY",
                    "operator": "not_matches_regex",
                    "value": "^-?[0-9]"
                }
            ]
        },
        "Core": {
            "Id": "CDISC.SENDIG.72",
            "Version": "1",
            "Status": "Draft"
        },
        "Description": null,
        "Outcome": {
            "Message": "--DY is not a non-zero integer",
            "Output_Variables": [
                "--DY"
            ]
        },
        "Rule_Type": "Record Data",
        "Sensitivity": "Record",
        "Authorities": [
            {
                "Organization": "CDISC",
                "Standards": [
                    {
                        "Name": "SENDIG",
                        "Version": "3.1",
                        "References": [
                            {
                                "Origin": "SDTM and SENDIG Conformance Rules",
                                "Rule_Identifier": {
                                    "Id": "72",
                                    "Version": "1"
                                },
                                "Version": "2.0",
                                "Citations": [
                                    {
                                        "Cited_Guidance": "All Study Day values are integers.",
                                        "Document": "IG v3.1",
                                        "Section": "4.4.4"
                                    }
                                ]
                            }
                        ]
                    }
                ]
            }
        ],
        "Scope": {
            "Classes": {
                "Include": [
                    "ALL"
                ]
            },
            "Domains": {
                "Include": [
                    "ALL"
                ]
            }
        }
    },
    "id": "315aab1f-d9cf-42a9-a999-77202a18194b"
}