{
    "changed": "2022-11-08T13:45:01.606Z",
    "content": "Check:\n  all:\n    - name: RETESTCD\n      operator: is_not_unique_set\n      value:\n        - USUBJID\n        - REDTC\n    - name: RETESTCD\n      operator: is_not_unique_set\n      value:\n        - USUBJID\n        - REDTC\n        - RESTINT\nCore:\n  Id: CDISC.SENDIG.338\n  Version: '1'\n  Status: Draft\nDescription: Raise an error when there is more than one record present for any particular\n  respiratory test for a subject and measurement date/time or evaluation interval.\nOutcome:\n  Message: The respiratory test is not unique for this subject and measurement datetime\n    and/or evaluation interval.\n  Output Variables:\n    - USUBJID\n    - RETESTCD\n    - REDTC\n    - RESTINT\nRule Type: Record Data\nSensitivity: Record\nAuthorities:\n  - Organization: CDISC\n    Standards:\n      - Name: SENDIG\n        Version: '3.1'\n        References:\n          - Origin: SDTM and SENDIG Conformance Rules\n            Rule Identifier:\n              Id: '338'\n              Version: '1'\n            Version: '2.0'\n            Citations:\n              - Cited Guidance: One record per test per observation time or evaluation\n                  interval per subject\n                Document: SENDIG v3.1\n                Section: 6.3.18.1\nScope:\n  Classes:\n    Include:\n      - FINDINGS\n  Domains:\n    Include:\n      - RE\n",
    "created": "2022-11-08T13:34:27.290Z",
    "creator": {
        "id": "dc8bf014-df32-4631-8684-9a09a16c5071"
    },
    "json": {
        "Check": {
            "all": [
                {
                    "name": "RETESTCD",
                    "operator": "is_not_unique_set",
                    "value": [
                        "USUBJID",
                        "REDTC"
                    ]
                },
                {
                    "name": "RETESTCD",
                    "operator": "is_not_unique_set",
                    "value": [
                        "USUBJID",
                        "REDTC",
                        "RESTINT"
                    ]
                }
            ]
        },
        "Core": {
            "Id": "CDISC.SENDIG.338",
            "Version": "1",
            "Status": "Draft"
        },
        "Description": "Raise an error when there is more than one record present for any particular respiratory test for a subject and measurement date/time or evaluation interval.",
        "Outcome": {
            "Message": "The respiratory test is not unique for this subject and measurement datetime and/or evaluation interval.",
            "Output_Variables": [
                "USUBJID",
                "RETESTCD",
                "REDTC",
                "RESTINT"
            ]
        },
        "Rule_Type": "Record Data",
        "Sensitivity": "Record",
        "Authorities": [
            {
                "Organization": "CDISC",
                "Standards": [
                    {
                        "Name": "SENDIG",
                        "Version": "3.1",
                        "References": [
                            {
                                "Origin": "SDTM and SENDIG Conformance Rules",
                                "Rule_Identifier": {
                                    "Id": "338",
                                    "Version": "1"
                                },
                                "Version": "2.0",
                                "Citations": [
                                    {
                                        "Cited_Guidance": "One record per test per observation time or evaluation interval per subject",
                                        "Document": "SENDIG v3.1",
                                        "Section": "6.3.18.1"
                                    }
                                ]
                            }
                        ]
                    }
                ]
            }
        ],
        "Scope": {
            "Classes": {
                "Include": [
                    "FINDINGS"
                ]
            },
            "Domains": {
                "Include": [
                    "RE"
                ]
            }
        }
    },
    "id": "695bc144-d649-4502-80b8-008b3a4b81bf"
}