{
    "changed": "2022-09-16T15:08:18.707Z",
    "content": "Check:\n  any:\n    - all:\n        - name: USUBJID\n          operator: non_empty\n        - name: --SEQ\n          operator: is_not_unique_set\n          value: USUBJID\n    - all:\n        - name: POOLID\n          operator: non_empty\n        - name: --SEQ\n          operator: is_not_unique_set\n          value: POOLID\nCore:\n  Id: CDISC.SENDIG.138\n  Version: '1'\n  Status: Draft\nDescription: Sequence number given to ensure uniqueness of subject records within\n  a domain. May be any valid number.\nOutcome:\n  Message: --SEQ is not unique within USUBJID or POOLID\n  Output Variables:\n    - USUBJID\n    - POOLID\n    - --SEQ\nRule Type: Record Data\nSensitivity: Record\nAuthorities:\n  - Organization: CDISC\n    Standards:\n      - Name: SENDIG\n        Version: '3.1'\n        References:\n          - Origin: SDTM and SENDIG Conformance Rules\n            Rule Identifier:\n              Id: '138'\n              Version: '1'\n            Version: '2.0'\n            Citations:\n              - Cited Guidance: Sequence number given to ensure uniqueness of subject\n                  records within a domain. May be any valid number.\n                Document: IG v3.1\n                Section: 6.1.1\nScope:\n  Classes:\n    Include:\n      - INTERVENTIONS\n      - EVENTS\n      - FINDINGS\n  Domains:\n    Include:\n      - ALL\n",
    "created": "2022-09-16T14:18:39.670Z",
    "creator": {
        "id": "dc8bf014-df32-4631-8684-9a09a16c5071"
    },
    "json": {
        "Check": {
            "any": [
                {
                    "all": [
                        {
                            "name": "USUBJID",
                            "operator": "non_empty"
                        },
                        {
                            "name": "--SEQ",
                            "operator": "is_not_unique_set",
                            "value": "USUBJID"
                        }
                    ]
                },
                {
                    "all": [
                        {
                            "name": "POOLID",
                            "operator": "non_empty"
                        },
                        {
                            "name": "--SEQ",
                            "operator": "is_not_unique_set",
                            "value": "POOLID"
                        }
                    ]
                }
            ]
        },
        "Core": {
            "Id": "CDISC.SENDIG.138",
            "Version": "1",
            "Status": "Draft"
        },
        "Description": "Sequence number given to ensure uniqueness of subject records within a domain. May be any valid number.",
        "Outcome": {
            "Message": "--SEQ is not unique within USUBJID or POOLID",
            "Output_Variables": [
                "USUBJID",
                "POOLID",
                "--SEQ"
            ]
        },
        "Rule_Type": "Record Data",
        "Sensitivity": "Record",
        "Authorities": [
            {
                "Organization": "CDISC",
                "Standards": [
                    {
                        "Name": "SENDIG",
                        "Version": "3.1",
                        "References": [
                            {
                                "Origin": "SDTM and SENDIG Conformance Rules",
                                "Rule_Identifier": {
                                    "Id": "138",
                                    "Version": "1"
                                },
                                "Version": "2.0",
                                "Citations": [
                                    {
                                        "Cited_Guidance": "Sequence number given to ensure uniqueness of subject records within a domain. May be any valid number.",
                                        "Document": "IG v3.1",
                                        "Section": "6.1.1"
                                    }
                                ]
                            }
                        ]
                    }
                ]
            }
        ],
        "Scope": {
            "Classes": {
                "Include": [
                    "INTERVENTIONS",
                    "EVENTS",
                    "FINDINGS"
                ]
            },
            "Domains": {
                "Include": [
                    "ALL"
                ]
            }
        }
    },
    "id": "7ac0ee44-8f0d-4dfc-b111-d58f76185105"
}