{
    "changed": "2022-12-31T07:25:11.712Z",
    "content": "Check:\n  all:\n    - name: --STRESC\n      operator: non_empty\n    - name: --STRESC\n      operator: matches_regex\n      value: ^-?(0|[1-9]\\d*)(\\.\\d+)?$\n    - name: --STRESN\n      operator: empty\nCore:\n  Id: CDISC.SENDIG.88\n  Version: '1'\n  Status: Draft\nDescription: When --STRESC represents numeric data, --STRESN must be populated.\nOutcome:\n  Message: --STRESC must be populated as --ORRES is populated\n  Output Variables:\n    - --STRESC\n    - --STRESN\nRule Type: Record Data\nSensitivity: Record\nAuthorities:\n  - Organization: CDISC\n    Standards:\n      - Name: SENDIG\n        Version: '3.1'\n        References:\n          - Origin: SDTM and SENDIG Conformance Rules\n            Rule Identifier:\n              Id: '88'\n              Version: '1'\n            Version: '2.0'\n            Citations:\n              - Cited Guidance: --STRESN will only contain data values if the data\n                  values presented in --STRESC are numeric values\n                Document: IG v3.1\n                Section: 4.5.1.1\nScope:\n  Classes:\n    Include:\n      - FINDINGS\n  Domains:\n    Include:\n      - ALL\n",
    "created": "2022-09-15T08:05:21.704Z",
    "creator": {
        "id": "dc8bf014-df32-4631-8684-9a09a16c5071"
    },
    "json": {
        "Check": {
            "all": [
                {
                    "name": "--STRESC",
                    "operator": "non_empty"
                },
                {
                    "name": "--STRESC",
                    "operator": "matches_regex",
                    "value": "^-?(0|[1-9]\\d*)(\\.\\d+)?$"
                },
                {
                    "name": "--STRESN",
                    "operator": "empty"
                }
            ]
        },
        "Core": {
            "Id": "CDISC.SENDIG.88",
            "Version": "1",
            "Status": "Draft"
        },
        "Description": "When --STRESC represents numeric data, --STRESN must be populated.",
        "Outcome": {
            "Message": "--STRESC must be populated as --ORRES is populated",
            "Output_Variables": [
                "--STRESC",
                "--STRESN"
            ]
        },
        "Rule_Type": "Record Data",
        "Sensitivity": "Record",
        "Authorities": [
            {
                "Organization": "CDISC",
                "Standards": [
                    {
                        "Name": "SENDIG",
                        "Version": "3.1",
                        "References": [
                            {
                                "Origin": "SDTM and SENDIG Conformance Rules",
                                "Rule_Identifier": {
                                    "Id": "88",
                                    "Version": "1"
                                },
                                "Version": "2.0",
                                "Citations": [
                                    {
                                        "Cited_Guidance": "--STRESN will only contain data values if the data values presented in --STRESC are numeric values",
                                        "Document": "IG v3.1",
                                        "Section": "4.5.1.1"
                                    }
                                ]
                            }
                        ]
                    }
                ]
            }
        ],
        "Scope": {
            "Classes": {
                "Include": [
                    "FINDINGS"
                ]
            },
            "Domains": {
                "Include": [
                    "ALL"
                ]
            }
        }
    },
    "id": "42198890-6fb4-4ef0-8e58-b1e8effa1f80"
}