{
    "changed": "2022-09-29T13:52:57.340Z",
    "content": "Check:\n  all:\n    - name: USUBJID\n      operator: is_contained_by\n      value: $ex_usubjid\n    - name: RFXSTDTC\n      operator: not_equal_to\n      value: $min_ex_exstdtc\nCore:\n  Id: CDISC.SENDIG.305\n  Version: '1'\n  Status: Draft\nDescription: Raise an error when EX records are present for subject but RFXSTDTC does\n  not equal the earliest value of EX.EXSTDTC\nOperations:\n  - operator: distinct\n    domain: EX\n    name: USUBJID\n    id: $ex_usubjid\n  - operator: min_date\n    domain: EX\n    name: EXSTDTC\n    id: $min_ex_exstdtc\n    group:\n      - USUBJID\nOutcome:\n  Message: RFXSTDTC does not equal the earliest value of EX.EXSTDTC\n  Output Variables:\n    - RFXSTDTC\n    - $min_ex_exstdtc\nRule Type: Record Data\nSensitivity: Record\nAuthorities:\n  - Organization: CDISC\n    Standards:\n      - Name: SENDIG\n        Version: '3.1'\n        References:\n          - Origin: SDTM and SENDIG Conformance Rules\n            Rule Identifier:\n              Id: '305'\n              Version: '2'\n            Version: '2.0'\n            Citations:\n              - Cited Guidance: First date/time of exposure to any protocol-specified\n                  treatment or therapy, equal to the earliest value of EXSTDTC.\n                Document: IG v3.1\n                Item: Specification\n                Section: 5.1.1\nScope:\n  Classes:\n    Include:\n      - SPECIAL-PURPOSE\n  Domains:\n    Include:\n      - DM\n",
    "created": "2022-09-29T13:52:57.340Z",
    "creator": {
        "id": "dc8bf014-df32-4631-8684-9a09a16c5071"
    },
    "json": {
        "Check": {
            "all": [
                {
                    "name": "USUBJID",
                    "operator": "is_contained_by",
                    "value": "$ex_usubjid"
                },
                {
                    "name": "RFXSTDTC",
                    "operator": "not_equal_to",
                    "value": "$min_ex_exstdtc"
                }
            ]
        },
        "Core": {
            "Id": "CDISC.SENDIG.305",
            "Version": "1",
            "Status": "Draft"
        },
        "Description": "Raise an error when EX records are present for subject but RFXSTDTC does not equal the earliest value of EX.EXSTDTC",
        "Operations": [
            {
                "operator": "distinct",
                "domain": "EX",
                "name": "USUBJID",
                "id": "$ex_usubjid"
            },
            {
                "operator": "min_date",
                "domain": "EX",
                "name": "EXSTDTC",
                "id": "$min_ex_exstdtc",
                "group": [
                    "USUBJID"
                ]
            }
        ],
        "Outcome": {
            "Message": "RFXSTDTC does not equal the earliest value of EX.EXSTDTC",
            "Output_Variables": [
                "RFXSTDTC",
                "$min_ex_exstdtc"
            ]
        },
        "Rule_Type": "Record Data",
        "Sensitivity": "Record",
        "Authorities": [
            {
                "Organization": "CDISC",
                "Standards": [
                    {
                        "Name": "SENDIG",
                        "Version": "3.1",
                        "References": [
                            {
                                "Origin": "SDTM and SENDIG Conformance Rules",
                                "Rule_Identifier": {
                                    "Id": "305",
                                    "Version": "2"
                                },
                                "Version": "2.0",
                                "Citations": [
                                    {
                                        "Cited_Guidance": "First date/time of exposure to any protocol-specified treatment or therapy, equal to the earliest value of EXSTDTC.",
                                        "Document": "IG v3.1",
                                        "Item": "Specification",
                                        "Section": "5.1.1"
                                    }
                                ]
                            }
                        ]
                    }
                ]
            }
        ],
        "Scope": {
            "Classes": {
                "Include": [
                    "SPECIAL-PURPOSE"
                ]
            },
            "Domains": {
                "Include": [
                    "DM"
                ]
            }
        }
    },
    "id": "dd3adaed-3184-40e3-9ddb-befcc445772f"
}