{
    "changed": "2022-10-13T13:00:04.884Z",
    "content": "Check:\n  all:\n    - name: SPECIES\n      operator: not_exists\n    - name: USUBJID\n      operator: exists\n    - name: TS.TSPARMCD\n      operator: not_equal_to\n      value: SPECIES\nCore:\n  Id: CDISC.SENDIG.105\n  Version: '1'\n  Status: Draft\nDescription: Raise an error when the variable SPECIES is not oresent in DM, and there\n  is no record TSPARMCD=SPECIES in TS and there is no record TXPARMCD=SPECIES in TX\nOperations:\n  - domain: TS\n    id: $ts_species\n    name: TSPARMCD\n    operator: equal_to\n    value: SPECIES\nOutcome:\n  Message: SPECIES in not present in DM and there is no record TSPARMCD=SPECIES in\n    TS and there is no record TXPARMCD=SPECIES in TX\nRule Type: Record Data\nSensitivity: Dataset\nAuthorities:\n  - Organization: CDISC\n    Standards:\n      - Name: SENDIG\n        Version: '3.1'\n        References:\n          - Origin: SDTM and SENDIG Conformance Rules\n            Rule Identifier:\n              Id: 105\n              Version: '2'\n            Version: '2.0'\n            Citations:\n              - Cited Guidance: If this variable is excluded in the DM domain, the\n                  information must be present at a higher level (either Trial Sets\n                  or Trial Summary).\n                Document: IG v3.1\n                Item: Specification\n                Section: 5.1.1\nScope:\n  Classes:\n    Include:\n      - SPECIAL-PURPOSE\n  Domains:\n    Include:\n      - DM\n",
    "created": "2022-10-13T11:21:21.852Z",
    "creator": {
        "id": "dc8bf014-df32-4631-8684-9a09a16c5071"
    },
    "json": {
        "Check": {
            "all": [
                {
                    "name": "SPECIES",
                    "operator": "not_exists"
                },
                {
                    "name": "USUBJID",
                    "operator": "exists"
                },
                {
                    "name": "TS.TSPARMCD",
                    "operator": "not_equal_to",
                    "value": "SPECIES"
                }
            ]
        },
        "Core": {
            "Id": "CDISC.SENDIG.105",
            "Version": "1",
            "Status": "Draft"
        },
        "Description": "Raise an error when the variable SPECIES is not oresent in DM, and there is no record TSPARMCD=SPECIES in TS and there is no record TXPARMCD=SPECIES in TX",
        "Operations": [
            {
                "domain": "TS",
                "id": "$ts_species",
                "name": "TSPARMCD",
                "operator": "equal_to",
                "value": "SPECIES"
            }
        ],
        "Outcome": {
            "Message": "SPECIES in not present in DM and there is no record TSPARMCD=SPECIES in TS and there is no record TXPARMCD=SPECIES in TX"
        },
        "Rule_Type": "Record Data",
        "Sensitivity": "Dataset",
        "Authorities": [
            {
                "Organization": "CDISC",
                "Standards": [
                    {
                        "Name": "SENDIG",
                        "Version": "3.1",
                        "References": [
                            {
                                "Origin": "SDTM and SENDIG Conformance Rules",
                                "Rule_Identifier": {
                                    "Id": 105,
                                    "Version": "2"
                                },
                                "Version": "2.0",
                                "Citations": [
                                    {
                                        "Cited_Guidance": "If this variable is excluded in the DM domain, the information must be present at a higher level (either Trial Sets or Trial Summary).",
                                        "Document": "IG v3.1",
                                        "Item": "Specification",
                                        "Section": "5.1.1"
                                    }
                                ]
                            }
                        ]
                    }
                ]
            }
        ],
        "Scope": {
            "Classes": {
                "Include": [
                    "SPECIAL-PURPOSE"
                ]
            },
            "Domains": {
                "Include": [
                    "DM"
                ]
            }
        }
    },
    "id": "d2a4c932-ccd7-42f7-a83e-fa04504cda2a"
}