{
    "id": "2021cf05-d864-4245-bf55-9ced6223e4ff",
    "changed": "2022-09-01T14:26:14Z",
    "content": "Check:\n  all:\n#     - name: \"variable_name\"\r\n#       operator: matches_regex\r\n#       value: ^[A-Z][A-Z0-9]{0,4}DTF$\r\n#     - name: \"variable_name\"\r\n#       operator: non_empty\r\n    - name: ADTF\n      operator: does_not_use_valid_codelist_terms\n      value: DATEFL\nCore:\n  # Need to make yaml validation accept ADAMIG\r\n  # Will we need to prepend ADaM rules with \"AD0...\"? \r\n  # (column \"Check Number\" in ADaM_Conformance_Rules_v4.0 is 1-3 digits only, some with a \",1\" (e.g. \"37,01\") )\r\n  Id: CDISC.ADAMIG.AD0039\n  Version: '1'\n  Status: Draft\nDescription: Raise an error when a variable ends with DTF and values are not according\n  to the DATEFL controlled terminology codelist\nOutcome:\n  Message: The values of ADTF are not following the DATEFL codelist\n  Output Variables:\n    - ADTF\nRule Type: Record Data\nSensitivity: Variable\nAuthorities:\n  - Organization: CDISC\n    Standards:\n      - Name: ADAMIG\n        Version: '1.3'\n        References:\n  # Origin for ADaM/ADaMIG should be defined in yaml validation schema\r\n          - Origin: ADaM and ADaMIG Conformance Rules\n            Rule Identifier:\n              Id: AD0039\n              Version: '1'\n    # Version 4.0 for ADaM/ADaMIG should be allowed according to yaml validation schema\r\n            Version: '4.0'\n            Citations:\n              - Document: IG v1.3\n                Section: 3.1.3\n                Item: '1'\n                Cited Guidance: >-\n                  ADaM IG v1.3, Section 3.1.3, Item 1:  As described in Table 3.1.5.1,\n                  variables whose names end in DTF are date imputation flags. *DTF\n                  variables represent the\n                  highest level of imputation of the *DT variable based on the source\n                  SDTM dataset DTC variable. *DTF = Y if the year is\n                  imputed. *DTF = M if year is present and month is imputed. *DTF\n                  = D if only day is imputed. *DTF = null if *DT equals the\n                  SDTM dataset DTC variable date part equivalent. If a date was imputed,\n                  *DTF must be populated and is required. Both *DTF and\n                  *TMF may be needed to describe the level of imputation in *DTM if\n                  imputation was done. Note that the list of examples in\n                  Table 3.1.3.1 is not exhaustive.\nScope:\n  Classes:\n    Include:\n      # What ADaM classes will be defined? ADSL, BDS, OCCDS, OTHER?\r\n      - ALL\n  Domains:\n    Include:\n      - ADLB\n",
    "created": "2022-09-01T12:41:36Z",
    "creator": {
        "id": "ff3f6fbb-6aa3-4353-9941-60f9da14b0e4"
    },
    "json": {
        "Check": {
            "all": [
                {
                    "name": "ADTF",
                    "operator": "does_not_use_valid_codelist_terms",
                    "value": "DATEFL"
                }
            ]
        },
        "Core": {
            "Id": "CDISC.ADAMIG.AD0039",
            "Version": "1",
            "Status": "Draft"
        },
        "Description": "Raise an error when a variable ends with DTF and values are not according to the DATEFL controlled terminology codelist",
        "Outcome": {
            "Message": "The values of ADTF are not following the DATEFL codelist",
            "Output_Variables": [
                "ADTF"
            ]
        },
        "Rule_Type": "Record Data",
        "Sensitivity": "Variable",
        "Authorities": [
            {
                "Organization": "CDISC",
                "Standards": [
                    {
                        "Name": "ADAMIG",
                        "Version": "1.3",
                        "References": [
                            {
                                "Origin": "ADaM and ADaMIG Conformance Rules",
                                "Rule_Identifier": {
                                    "Id": "AD0039",
                                    "Version": "1"
                                },
                                "Version": "4.0",
                                "Citations": [
                                    {
                                        "Document": "IG v1.3",
                                        "Section": "3.1.3",
                                        "Item": "1",
                                        "Cited_Guidance": "ADaM IG v1.3, Section 3.1.3, Item 1:  As described in Table 3.1.5.1, variables whose names end in DTF are date imputation flags. *DTF variables represent the highest level of imputation of the *DT variable based on the source SDTM dataset DTC variable. *DTF = Y if the year is imputed. *DTF = M if year is present and month is imputed. *DTF = D if only day is imputed. *DTF = null if *DT equals the SDTM dataset DTC variable date part equivalent. If a date was imputed, *DTF must be populated and is required. Both *DTF and *TMF may be needed to describe the level of imputation in *DTM if imputation was done. Note that the list of examples in Table 3.1.3.1 is not exhaustive."
                                    }
                                ]
                            }
                        ]
                    }
                ]
            }
        ],
        "Scope": {
            "Classes": {
                "Include": [
                    "ALL"
                ]
            },
            "Domains": {
                "Include": [
                    "ADLB"
                ]
            }
        }
    }
}