{
    "changed": "2022-09-29T11:44:08.811Z",
    "content": "Check:\n  all:\n    - name: --STINT\n      operator: non_empty\n    - name: --ENINT\n      operator: non_empty\n    - name: --TPTREF\n      operator: empty\nCore:\n  Id: CDISC.SENDIG.294\n  Version: '1'\n  Status: Draft\nDescription: Raise an error when --STINT and -ENINT are populated but --TPTREF is\n  not populated.\nOutcome:\n  Message: --STINT and --ENINT are populated but --TPTREF is not populated\nRule Type: Record Data\nSensitivity: Record\nAuthorities:\n  - Organization: CDISC\n    Standards:\n      - Name: SENDIG\n        Version: '3.1'\n        References:\n          - Origin: SDTM and SENDIG Conformance Rules\n            Rule Identifier:\n              Id: '294'\n              Version: '1'\n            Version: '2.0'\n            Citations:\n              - Cited Guidance: Time points with collections over a duration also\n                  typically include the --STINT and --ENINT variables, which specify\n                  the start and end of the period over which the assessment was evaluated,\n                  based on the --TPTREF anchor.\n                Document: IG v3.1\n                Section: 4.4.7.2.3\nScope:\n  Classes:\n    Include:\n      - FINDINGS\n  Domains:\n    Include:\n      - ALL\n",
    "created": "2022-09-29T11:44:08.811Z",
    "creator": {
        "id": "dc8bf014-df32-4631-8684-9a09a16c5071"
    },
    "json": {
        "Check": {
            "all": [
                {
                    "name": "--STINT",
                    "operator": "non_empty"
                },
                {
                    "name": "--ENINT",
                    "operator": "non_empty"
                },
                {
                    "name": "--TPTREF",
                    "operator": "empty"
                }
            ]
        },
        "Core": {
            "Id": "CDISC.SENDIG.294",
            "Version": "1",
            "Status": "Draft"
        },
        "Description": "Raise an error when --STINT and -ENINT are populated but --TPTREF is not populated.",
        "Outcome": {
            "Message": "--STINT and --ENINT are populated but --TPTREF is not populated"
        },
        "Rule_Type": "Record Data",
        "Sensitivity": "Record",
        "Authorities": [
            {
                "Organization": "CDISC",
                "Standards": [
                    {
                        "Name": "SENDIG",
                        "Version": "3.1",
                        "References": [
                            {
                                "Origin": "SDTM and SENDIG Conformance Rules",
                                "Rule_Identifier": {
                                    "Id": "294",
                                    "Version": "1"
                                },
                                "Version": "2.0",
                                "Citations": [
                                    {
                                        "Cited_Guidance": "Time points with collections over a duration also typically include the --STINT and --ENINT variables, which specify the start and end of the period over which the assessment was evaluated, based on the --TPTREF anchor.",
                                        "Document": "IG v3.1",
                                        "Section": "4.4.7.2.3"
                                    }
                                ]
                            }
                        ]
                    }
                ]
            }
        ],
        "Scope": {
            "Classes": {
                "Include": [
                    "FINDINGS"
                ]
            },
            "Domains": {
                "Include": [
                    "ALL"
                ]
            }
        }
    },
    "id": "6efa754f-7d85-414c-a477-ab456bb4705a"
}