{
    "changed": "2022-11-02T09:50:36.358Z",
    "content": "Check:\n  all:\n    - name: MADTC\n      operator: non_empty\n    - name: MASPEC\n      operator: non_empty\n    - name: MAORRES\n      operator: is_not_unique_set\n      value:\n        - USUBJID\n        - MASPEC\n        - MADTC\nCore:\n  Id: CDISC.SENDIG.175\n  Version: '1'\n  Status: Draft\nDescription: Raise an error when there is more than one record present for any particular\n  Macroscopic Finding in the MA Domain, for a subject on a particular date.\n#The check for this rule was revised to NOT check the records where CLDTC is null\r\nOutcome:\n  Message: The Macroscopy Finding test result is not unique for this subject and date/time.\n  Output Variables:\n    - USUBJID\n    - MATESTCD\n    - MAORRES\n    - MASPEC\n    - MADTC\nRule Type: Record Data\nSensitivity: Record\nAuthorities:\n  - Organization: CDISC\n    Standards:\n      - Name: SENDIG\n        Version: '3.1'\n        References:\n          - Origin: SDTM and SENDIG Conformance Rules\n            Rule Identifier:\n              Id: '175'\n              Version: '1'\n            Version: '2.0'\n            Citations:\n              - Cited Guidance: One record per finding per specimen per subject\n                Document: SENDIG v3.1\n                Section: 6.3.7\nScope:\n  Classes:\n    Include:\n      - FINDINGS\n  Domains:\n    Include:\n      - MA\n",
    "created": "2022-11-02T09:32:35.892Z",
    "creator": {
        "id": "dc8bf014-df32-4631-8684-9a09a16c5071"
    },
    "json": {
        "Check": {
            "all": [
                {
                    "name": "MADTC",
                    "operator": "non_empty"
                },
                {
                    "name": "MASPEC",
                    "operator": "non_empty"
                },
                {
                    "name": "MAORRES",
                    "operator": "is_not_unique_set",
                    "value": [
                        "USUBJID",
                        "MASPEC",
                        "MADTC"
                    ]
                }
            ]
        },
        "Core": {
            "Id": "CDISC.SENDIG.175",
            "Version": "1",
            "Status": "Draft"
        },
        "Description": "Raise an error when there is more than one record present for any particular Macroscopic Finding in the MA Domain, for a subject on a particular date.",
        "Outcome": {
            "Message": "The Macroscopy Finding test result is not unique for this subject and date/time.",
            "Output_Variables": [
                "USUBJID",
                "MATESTCD",
                "MAORRES",
                "MASPEC",
                "MADTC"
            ]
        },
        "Rule_Type": "Record Data",
        "Sensitivity": "Record",
        "Authorities": [
            {
                "Organization": "CDISC",
                "Standards": [
                    {
                        "Name": "SENDIG",
                        "Version": "3.1",
                        "References": [
                            {
                                "Origin": "SDTM and SENDIG Conformance Rules",
                                "Rule_Identifier": {
                                    "Id": "175",
                                    "Version": "1"
                                },
                                "Version": "2.0",
                                "Citations": [
                                    {
                                        "Cited_Guidance": "One record per finding per specimen per subject",
                                        "Document": "SENDIG v3.1",
                                        "Section": "6.3.7"
                                    }
                                ]
                            }
                        ]
                    }
                ]
            }
        ],
        "Scope": {
            "Classes": {
                "Include": [
                    "FINDINGS"
                ]
            },
            "Domains": {
                "Include": [
                    "MA"
                ]
            }
        }
    },
    "id": "a0c7177c-2b30-4ef9-aea9-4da8ef55fc70"
}