{
    "changed": "2022-09-21T13:02:19.976Z",
    "content": "Check:\n  all:\n    - name: --DRVFL\n      operator: non_empty\n    - name: --DRVFL\n      operator: not_equal_to\n      value: Y\nCore:\n  Id: CDISC.SENDIG.172\n  Version: '1'\n  Status: Draft\nDescription: Raise an error when record is derived in a --DRVFL is not null and is\n  not equal to 'Y'\nOutcome:\n  Message: --DRVFL must be null or 'Y'\nRule Type: Record Data\nSensitivity: Record\nAuthorities:\n  - Organization: CDISC\n    Standards:\n      - Name: SENDIG\n        Version: '3.1'\n        References:\n          - Origin: SDTM and SENDIG Conformance Rules\n            Rule Identifier:\n              Id: '172'\n              Version: '1'\n            Version: '2.0'\n            Citations:\n              - Cited Guidance: Used to indicate a derived record. The value should\n                  be Y or null.\n                Document: SENDIG v3.1\n                Section: Section 6.3.6\nScope:\n  Classes:\n    Include:\n      - FINDINGS\n  Domains:\n    Include:\n      - ALL\n",
    "created": "2022-09-21T13:02:19.976Z",
    "creator": {
        "id": "dc8bf014-df32-4631-8684-9a09a16c5071"
    },
    "json": {
        "Check": {
            "all": [
                {
                    "name": "--DRVFL",
                    "operator": "non_empty"
                },
                {
                    "name": "--DRVFL",
                    "operator": "not_equal_to",
                    "value": "Y"
                }
            ]
        },
        "Core": {
            "Id": "CDISC.SENDIG.172",
            "Version": "1",
            "Status": "Draft"
        },
        "Description": "Raise an error when record is derived in a --DRVFL is not null and is not equal to 'Y'",
        "Outcome": {
            "Message": "--DRVFL must be null or 'Y'"
        },
        "Rule_Type": "Record Data",
        "Sensitivity": "Record",
        "Authorities": [
            {
                "Organization": "CDISC",
                "Standards": [
                    {
                        "Name": "SENDIG",
                        "Version": "3.1",
                        "References": [
                            {
                                "Origin": "SDTM and SENDIG Conformance Rules",
                                "Rule_Identifier": {
                                    "Id": "172",
                                    "Version": "1"
                                },
                                "Version": "2.0",
                                "Citations": [
                                    {
                                        "Cited_Guidance": "Used to indicate a derived record. The value should be Y or null.",
                                        "Document": "SENDIG v3.1",
                                        "Section": "Section 6.3.6"
                                    }
                                ]
                            }
                        ]
                    }
                ]
            }
        ],
        "Scope": {
            "Classes": {
                "Include": [
                    "FINDINGS"
                ]
            },
            "Domains": {
                "Include": [
                    "ALL"
                ]
            }
        }
    },
    "id": "6cf1afb4-1460-481d-9f61-30b61d4d61a4"
}