{
    "changed": "2022-09-28T07:06:14.765Z",
    "content": "Check:\n  all:\n    - name: SETCD\n      operator: is_not_unique_relationship\n      value: SET\nCore:\n  Id: CDISC.SENDIG.237\n  Version: '1'\n  Status: Draft\nDescription: Each SETCD/SET is a unique pair.\nOutcome:\n  Message: The combination of SETCD and SET is not a unique pair\nRule Type: Record Data\nSensitivity: Record\nAuthorities:\n  - Organization: CDISC\n    Standards:\n      - Name: SENDIG\n        Version: '3.1'\n        References:\n          - Origin: SDTM and SENDIG Conformance Rules\n            Rule Identifier:\n              Id: '237'\n              Version: '1'\n            Version: '2.0'\n            Citations:\n              - Cited Guidance: 'SETCD: Short name of the Trial Set. SET: Long description\n                  of a specific Trial Set, as defined by the sponsor.'\n                Document: IG v3.1\n                Item: Specification\n                Section: 7.4.1\nScope:\n  Classes:\n    Include:\n      - TRIAL DESIGN\n  Domains:\n    Include:\n      - TX\n",
    "created": "2022-09-27T16:12:26.600Z",
    "creator": {
        "id": "dc8bf014-df32-4631-8684-9a09a16c5071"
    },
    "json": {
        "Check": {
            "all": [
                {
                    "name": "SETCD",
                    "operator": "is_not_unique_relationship",
                    "value": "SET"
                }
            ]
        },
        "Core": {
            "Id": "CDISC.SENDIG.237",
            "Version": "1",
            "Status": "Draft"
        },
        "Description": "Each SETCD/SET is a unique pair.",
        "Outcome": {
            "Message": "The combination of SETCD and SET is not a unique pair"
        },
        "Rule_Type": "Record Data",
        "Sensitivity": "Record",
        "Authorities": [
            {
                "Organization": "CDISC",
                "Standards": [
                    {
                        "Name": "SENDIG",
                        "Version": "3.1",
                        "References": [
                            {
                                "Origin": "SDTM and SENDIG Conformance Rules",
                                "Rule_Identifier": {
                                    "Id": "237",
                                    "Version": "1"
                                },
                                "Version": "2.0",
                                "Citations": [
                                    {
                                        "Cited_Guidance": "SETCD: Short name of the Trial Set. SET: Long description of a specific Trial Set, as defined by the sponsor.",
                                        "Document": "IG v3.1",
                                        "Item": "Specification",
                                        "Section": "7.4.1"
                                    }
                                ]
                            }
                        ]
                    }
                ]
            }
        ],
        "Scope": {
            "Classes": {
                "Include": [
                    "TRIAL DESIGN"
                ]
            },
            "Domains": {
                "Include": [
                    "TX"
                ]
            }
        }
    },
    "id": "eadd192a-11de-4245-8e5b-56647fe94ba1"
}