{
    "changed": "2022-09-27T14:50:36.419Z",
    "content": "Check:\n  all:\n    - name: TXSEQ\n      operator: is_not_unique_set\n      value: DOMAIN\nCore:\n  Id: CDISC.SENDIG.231\n  Version: '1'\n  Status: Draft\nDescription: TXSEQ should be unique for each record within the TX dataset.\nOutcome:\n  Message: TXSEQ is not unique in TX\nRule Type: Record Data\nSensitivity: Record\nAuthorities:\n  - Organization: CDISC\n    Standards:\n      - Name: SENDIG\n        Version: '3.1'\n        References:\n          - Origin: SDTM and SENDIG Conformance Rules\n            Rule Identifier:\n              Id: '231'\n              Version: '1'\n            Version: '2.0'\n            Citations:\n              - Cited Guidance: Unique number for this record within this dataset.\n                  (This sequence should be unique within the entire dataset because\n                  there is no USUBJID.)\n                Document: IG v3.1\n                Item: Specification\n                Section: 7.4.1\nScope:\n  Classes:\n    Include:\n      - TRIAL DESIGN\n  Domains:\n    Include:\n      - TX\n",
    "created": "2022-09-27T14:27:35.554Z",
    "creator": {
        "id": "dc8bf014-df32-4631-8684-9a09a16c5071"
    },
    "json": {
        "Check": {
            "all": [
                {
                    "name": "TXSEQ",
                    "operator": "is_not_unique_set",
                    "value": "DOMAIN"
                }
            ]
        },
        "Core": {
            "Id": "CDISC.SENDIG.231",
            "Version": "1",
            "Status": "Draft"
        },
        "Description": "TXSEQ should be unique for each record within the TX dataset.",
        "Outcome": {
            "Message": "TXSEQ is not unique in TX"
        },
        "Rule_Type": "Record Data",
        "Sensitivity": "Record",
        "Authorities": [
            {
                "Organization": "CDISC",
                "Standards": [
                    {
                        "Name": "SENDIG",
                        "Version": "3.1",
                        "References": [
                            {
                                "Origin": "SDTM and SENDIG Conformance Rules",
                                "Rule_Identifier": {
                                    "Id": "231",
                                    "Version": "1"
                                },
                                "Version": "2.0",
                                "Citations": [
                                    {
                                        "Cited_Guidance": "Unique number for this record within this dataset. (This sequence should be unique within the entire dataset because there is no USUBJID.)",
                                        "Document": "IG v3.1",
                                        "Item": "Specification",
                                        "Section": "7.4.1"
                                    }
                                ]
                            }
                        ]
                    }
                ]
            }
        ],
        "Scope": {
            "Classes": {
                "Include": [
                    "TRIAL DESIGN"
                ]
            },
            "Domains": {
                "Include": [
                    "TX"
                ]
            }
        }
    },
    "id": "0749085f-b086-4c5f-8a9e-493d2ec9d90c"
}