{
    "changed": "2022-11-02T07:48:21.735Z",
    "content": "Check:\n  all:\n    - name: BGDTC\n      operator: non_empty\n    - name: BGTESTCD\n      operator: is_not_unique_set\n      value:\n        - USUBJID\n        - BGDTC\nCore:\n  Id: CDISC.SENDIG.150\n  Version: '1'\n  Status: Draft\nDescription: Raise an error when there is more than one record present for any particular\n  Body Weight Gain test, in the BG Domain, for a subject on a particular date.\n#The check for this rule was revised to NOT check the records where BGDTC is null\r\nOutcome:\n  Message: The Body Weight Gain test is not unique for this subject and date/time.\n  Output Variables:\n    - USUBJID\n    - BGTESTCD\n    - BGDTC\nRule Type: Record Data\nSensitivity: Record\nAuthorities:\n  - Organization: CDISC\n    Standards:\n      - Name: SENDIG\n        Version: '3.1'\n        References:\n          - Origin: SDTM and SENDIG Conformance Rules\n            Rule Identifier:\n              Id: '150'\n              Version: '1'\n            Version: '2.0'\n            Citations:\n              - Cited Guidance: One record per test per observation time per subject\n                Document: SENDIG v3.1\n                Section: 6.3.2\nScope:\n  Classes:\n    Include:\n      - FINDINGS\n  Domains:\n    Include:\n      - BG\n",
    "created": "2022-11-02T07:45:41.324Z",
    "creator": {
        "id": "dc8bf014-df32-4631-8684-9a09a16c5071"
    },
    "json": {
        "Check": {
            "all": [
                {
                    "name": "BGDTC",
                    "operator": "non_empty"
                },
                {
                    "name": "BGTESTCD",
                    "operator": "is_not_unique_set",
                    "value": [
                        "USUBJID",
                        "BGDTC"
                    ]
                }
            ]
        },
        "Core": {
            "Id": "CDISC.SENDIG.150",
            "Version": "1",
            "Status": "Draft"
        },
        "Description": "Raise an error when there is more than one record present for any particular Body Weight Gain test, in the BG Domain, for a subject on a particular date.",
        "Outcome": {
            "Message": "The Body Weight Gain test is not unique for this subject and date/time.",
            "Output_Variables": [
                "USUBJID",
                "BGTESTCD",
                "BGDTC"
            ]
        },
        "Rule_Type": "Record Data",
        "Sensitivity": "Record",
        "Authorities": [
            {
                "Organization": "CDISC",
                "Standards": [
                    {
                        "Name": "SENDIG",
                        "Version": "3.1",
                        "References": [
                            {
                                "Origin": "SDTM and SENDIG Conformance Rules",
                                "Rule_Identifier": {
                                    "Id": "150",
                                    "Version": "1"
                                },
                                "Version": "2.0",
                                "Citations": [
                                    {
                                        "Cited_Guidance": "One record per test per observation time per subject",
                                        "Document": "SENDIG v3.1",
                                        "Section": "6.3.2"
                                    }
                                ]
                            }
                        ]
                    }
                ]
            }
        ],
        "Scope": {
            "Classes": {
                "Include": [
                    "FINDINGS"
                ]
            },
            "Domains": {
                "Include": [
                    "BG"
                ]
            }
        }
    },
    "id": "b4852b50-57f3-44cd-8f93-f8beb9bfd4f4"
}