{
    "changed": "2022-09-28T08:38:46.412Z",
    "content": "Check:\n  all:\n    - name: TSSEQ\n      operator: is_not_unique_set\n      value: TSPARMCD\nCore:\n  Id: CDISC.SENDIG.246\n  Version: '1'\n  Status: Draft\nDescription: The TSSEQ variable is a unique identifier for each record and is required\n  to identify each record as unique in cases where the same TSPARMCD is used within\n  the dataset.\nOutcome:\n  Message: The value of TSSEQ is not unique within the value for TSPARMCD\nRule Type: Record Data\nSensitivity: Record\nAuthorities:\n  - Organization: CDISC\n    Standards:\n      - Name: SENDIG\n        Version: '3.1'\n        References:\n          - Origin: SDTM and SENDIG Conformance Rules\n            Rule Identifier:\n              Id: '246'\n              Version: '1'\n            Version: '2.0'\n            Citations:\n              - Cited Guidance: The TSSEQ variable is a unique identifier for each\n                  record and is Required to identify each record as unique in cases\n                  where the same TSPARMCD is used within the dataset. The TSSEQ variable\n                  must be populated for all records within the TS dataset.\n                Document: IG v3.1\n                Item: Specification\n                Section: 7.4.2\nScope:\n  Classes:\n    Include:\n      - TRIAL DESIGN\n  Domains:\n    Include:\n      - TS\n",
    "created": "2022-09-28T08:38:24.619Z",
    "creator": {
        "id": "dc8bf014-df32-4631-8684-9a09a16c5071"
    },
    "json": {
        "Check": {
            "all": [
                {
                    "name": "TSSEQ",
                    "operator": "is_not_unique_set",
                    "value": "TSPARMCD"
                }
            ]
        },
        "Core": {
            "Id": "CDISC.SENDIG.246",
            "Version": "1",
            "Status": "Draft"
        },
        "Description": "The TSSEQ variable is a unique identifier for each record and is required to identify each record as unique in cases where the same TSPARMCD is used within the dataset.",
        "Outcome": {
            "Message": "The value of TSSEQ is not unique within the value for TSPARMCD"
        },
        "Rule_Type": "Record Data",
        "Sensitivity": "Record",
        "Authorities": [
            {
                "Organization": "CDISC",
                "Standards": [
                    {
                        "Name": "SENDIG",
                        "Version": "3.1",
                        "References": [
                            {
                                "Origin": "SDTM and SENDIG Conformance Rules",
                                "Rule_Identifier": {
                                    "Id": "246",
                                    "Version": "1"
                                },
                                "Version": "2.0",
                                "Citations": [
                                    {
                                        "Cited_Guidance": "The TSSEQ variable is a unique identifier for each record and is Required to identify each record as unique in cases where the same TSPARMCD is used within the dataset. The TSSEQ variable must be populated for all records within the TS dataset.",
                                        "Document": "IG v3.1",
                                        "Item": "Specification",
                                        "Section": "7.4.2"
                                    }
                                ]
                            }
                        ]
                    }
                ]
            }
        ],
        "Scope": {
            "Classes": {
                "Include": [
                    "TRIAL DESIGN"
                ]
            },
            "Domains": {
                "Include": [
                    "TS"
                ]
            }
        }
    },
    "id": "315b7882-a85b-4348-9bff-2f9e018a5d85"
}