{
    "changed": "2022-09-21T12:14:31.892Z",
    "content": "Check:\n  any:\n    - name: CLRESCAT\n      operator: equal_to\n      value: CLTEST\n    - name: CLRESCAT\n      operator: equal_to\n      value: CLSCAT\nCore:\n  Id: CDISC.SENDIG.161\n  Version: '1'\n  Status: Draft\nDescription: Trigger error when CLRESCAT is equal to CLTEST or when CLRESCAT is equal\n  to CLSCAT\nOutcome:\n  Message: CLRESCAT may not be equal to CLTEST and CLRESCAT may not be equal to CLSCAT\n  Output Variables:\n    - CLRESCAT\n    - CLTEST\n    - CLSCAT\nRule Type: Record Data\nSensitivity: Record\nAuthorities:\n  - Organization: CDISC\n    Standards:\n      - Name: SENDIG\n        Version: '3.1'\n        References:\n          - Origin: SDTM and SENDIG Conformance Rules\n            Rule Identifier:\n              Id: '161'\n              Version: '1'\n            Version: '2.0'\n            Citations:\n              - Cited Guidance: CLRESCAT is used for post collection categorization\n                  of results and should not be a duplication of CLTEST or CLSCAT which\n                  are considered categories at the time of collection.\n                Document: IG v.3.1\n                Section: 6.3.3.1\nScope:\n  Classes:\n    Include:\n      - FINDINGS\n  Domains:\n    Include:\n      - CL\n",
    "created": "2022-09-21T11:50:23.210Z",
    "creator": {
        "id": "dc8bf014-df32-4631-8684-9a09a16c5071"
    },
    "json": {
        "Check": {
            "any": [
                {
                    "name": "CLRESCAT",
                    "operator": "equal_to",
                    "value": "CLTEST"
                },
                {
                    "name": "CLRESCAT",
                    "operator": "equal_to",
                    "value": "CLSCAT"
                }
            ]
        },
        "Core": {
            "Id": "CDISC.SENDIG.161",
            "Version": "1",
            "Status": "Draft"
        },
        "Description": "Trigger error when CLRESCAT is equal to CLTEST or when CLRESCAT is equal to CLSCAT",
        "Outcome": {
            "Message": "CLRESCAT may not be equal to CLTEST and CLRESCAT may not be equal to CLSCAT",
            "Output_Variables": [
                "CLRESCAT",
                "CLTEST",
                "CLSCAT"
            ]
        },
        "Rule_Type": "Record Data",
        "Sensitivity": "Record",
        "Authorities": [
            {
                "Organization": "CDISC",
                "Standards": [
                    {
                        "Name": "SENDIG",
                        "Version": "3.1",
                        "References": [
                            {
                                "Origin": "SDTM and SENDIG Conformance Rules",
                                "Rule_Identifier": {
                                    "Id": "161",
                                    "Version": "1"
                                },
                                "Version": "2.0",
                                "Citations": [
                                    {
                                        "Cited_Guidance": "CLRESCAT is used for post collection categorization of results and should not be a duplication of CLTEST or CLSCAT which are considered categories at the time of collection.",
                                        "Document": "IG v.3.1",
                                        "Section": "6.3.3.1"
                                    }
                                ]
                            }
                        ]
                    }
                ]
            }
        ],
        "Scope": {
            "Classes": {
                "Include": [
                    "FINDINGS"
                ]
            },
            "Domains": {
                "Include": [
                    "CL"
                ]
            }
        }
    },
    "id": "007b8722-e757-4f0b-adfb-55803fa8f501"
}