{
    "changed": "2022-09-30T14:11:38.426Z",
    "content": "Check:\n  all:\n    - name: DSSTDTC\n      operator: non_empty\n    - name: DSSTDTC\n      operator: contains\n      value: /\nCore:\n  Id: CDISC.SENDIG.317\n  Version: '1'\n  Status: Draft\nDescription: Raise an error when the value of DSSTDTC is not a valid ISO 8601 date/time.\n  This automatically excludes composite date/time-s\nOutcome:\n  Message: The value of DSSTDTC is not a valid ISO 8601 date/time\nRule Type: Record Data\nSensitivity: Record\nAuthorities:\n  - Organization: CDISC\n    Standards:\n      - Name: SENDIG\n        Version: '3.1'\n        References:\n          - Origin: SDTM and SENDIG Conformance Rules\n            Rule Identifier:\n              Id: '317'\n              Version: '1'\n            Version: '2.0'\n            Citations:\n              - Cited Guidance: The use of an interval of uncertainty, as described\n                  in Section 4.4.2, cannot be used for DSSTDTC.\n                Document: IG v3.1\n                Section: 6.2.1.1\nScope:\n  Classes:\n    Include:\n      - EVENTS\n  Domains:\n    Include:\n      - DS\n",
    "created": "2022-09-30T13:51:48.165Z",
    "creator": {
        "id": "dc8bf014-df32-4631-8684-9a09a16c5071"
    },
    "json": {
        "Check": {
            "all": [
                {
                    "name": "DSSTDTC",
                    "operator": "non_empty"
                },
                {
                    "name": "DSSTDTC",
                    "operator": "contains",
                    "value": "/"
                }
            ]
        },
        "Core": {
            "Id": "CDISC.SENDIG.317",
            "Version": "1",
            "Status": "Draft"
        },
        "Description": "Raise an error when the value of DSSTDTC is not a valid ISO 8601 date/time. This automatically excludes composite date/time-s",
        "Outcome": {
            "Message": "The value of DSSTDTC is not a valid ISO 8601 date/time"
        },
        "Rule_Type": "Record Data",
        "Sensitivity": "Record",
        "Authorities": [
            {
                "Organization": "CDISC",
                "Standards": [
                    {
                        "Name": "SENDIG",
                        "Version": "3.1",
                        "References": [
                            {
                                "Origin": "SDTM and SENDIG Conformance Rules",
                                "Rule_Identifier": {
                                    "Id": "317",
                                    "Version": "1"
                                },
                                "Version": "2.0",
                                "Citations": [
                                    {
                                        "Cited_Guidance": "The use of an interval of uncertainty, as described in Section 4.4.2, cannot be used for DSSTDTC.",
                                        "Document": "IG v3.1",
                                        "Section": "6.2.1.1"
                                    }
                                ]
                            }
                        ]
                    }
                ]
            }
        ],
        "Scope": {
            "Classes": {
                "Include": [
                    "EVENTS"
                ]
            },
            "Domains": {
                "Include": [
                    "DS"
                ]
            }
        }
    },
    "id": "312c23d4-e11b-4732-9db9-7513fb0c71a5"
}