{
    "changed": "2022-09-11T16:46:48.905Z",
    "content": "Check:\n  all:\n    - name: --CAT\n      operator: non_empty\n    - name: --CAT\n      operator: equal_to\n      value: DOMAIN\nCore:\n  Id: CDISC.SENDIG.46\n  Version: '1'\n  Status: Draft\nDescription: Trigger error when --CAT is not null and --CAT is equal to DOMAIN\nOutcome:\n  Message: --CAT is equal to DOMAIN\n  Output Variables:\n    - --CAT\n    - DOMAIN\nRule Type: Record Data\nSensitivity: Record\nAuthorities:\n  - Organization: CDISC\n    Standards:\n      - Name: SENDIG\n        Version: '3.1'\n        References:\n          - Origin: SDTM and SENDIG Conformance Rules\n            Rule Identifier:\n              Id: '46'\n              Version: '1'\n            Version: '2.0'\n            Citations:\n              - Cited Guidance: Values for --CAT and --SCAT should not be redundant\n                  with the domain or dictionary classification provided by --DECOD\n                  and --BODSYS.\n                Document: IG v.3.1\n                Section: 4.2.6\nScope:\n  Classes:\n    Include:\n      - ALL\n  Domains:\n    Include:\n      - ALL\n",
    "created": "2022-09-11T16:46:48.905Z",
    "creator": {
        "id": "dc8bf014-df32-4631-8684-9a09a16c5071"
    },
    "json": {
        "Check": {
            "all": [
                {
                    "name": "--CAT",
                    "operator": "non_empty"
                },
                {
                    "name": "--CAT",
                    "operator": "equal_to",
                    "value": "DOMAIN"
                }
            ]
        },
        "Core": {
            "Id": "CDISC.SENDIG.46",
            "Version": "1",
            "Status": "Draft"
        },
        "Description": "Trigger error when --CAT is not null and --CAT is equal to DOMAIN",
        "Outcome": {
            "Message": "--CAT is equal to DOMAIN",
            "Output_Variables": [
                "--CAT",
                "DOMAIN"
            ]
        },
        "Rule_Type": "Record Data",
        "Sensitivity": "Record",
        "Authorities": [
            {
                "Organization": "CDISC",
                "Standards": [
                    {
                        "Name": "SENDIG",
                        "Version": "3.1",
                        "References": [
                            {
                                "Origin": "SDTM and SENDIG Conformance Rules",
                                "Rule_Identifier": {
                                    "Id": "46",
                                    "Version": "1"
                                },
                                "Version": "2.0",
                                "Citations": [
                                    {
                                        "Cited_Guidance": "Values for --CAT and --SCAT should not be redundant with the domain or dictionary classification provided by --DECOD and --BODSYS.",
                                        "Document": "IG v.3.1",
                                        "Section": "4.2.6"
                                    }
                                ]
                            }
                        ]
                    }
                ]
            }
        ],
        "Scope": {
            "Classes": {
                "Include": [
                    "ALL"
                ]
            },
            "Domains": {
                "Include": [
                    "ALL"
                ]
            }
        }
    },
    "id": "9e4949a7-0d87-4268-bee4-bca4ba4135cb"
}