{
    "changed": "2022-12-01T16:54:45.178Z",
    "content": "Check:\n  all:\n    - name: AGETXT\n      operator: non_empty\n    - name: AGETXT\n      operator: not_matches_regex\n      value: ^[0-9]+-[0-9]+$\nCore:\n  Id: CDISC.SENDIG.102\n  Version: '1'\n  Status: Draft\nDescription: AGETXT must be in number dash number format\nOutcome:\n  Message: AGETXT must be in number dash number format\n  Output Variables:\n    - USUBJID\n    - AGETXT\nRule Type: Record Data\nSensitivity: Record\nAuthorities:\n  - Organization: CDISC\n    Standards:\n      - Name: SENDIG\n        Version: '3.1'\n        References:\n          - Origin: SDTM and SENDIG Conformance Rules\n            Rule Identifier:\n              Id: '102'\n              Version: '1'\n            Version: '2.0'\n            Citations:\n              - Cited Guidance: AGETXT is used to present the age range in situations\n                  where the exact birthdate is not known.  It should be presented\n                  in number-number format..\n                Document: IG v3.1\n                Item: Specification\n                Section: 5.1.1\nScope:\n  Classes:\n    Include:\n      - SPECIAL-PURPOSE\n  Domains:\n    Include:\n      - DM\n",
    "created": "2022-09-15T13:20:04.442Z",
    "creator": {
        "id": "dc8bf014-df32-4631-8684-9a09a16c5071"
    },
    "json": {
        "Check": {
            "all": [
                {
                    "name": "AGETXT",
                    "operator": "non_empty"
                },
                {
                    "name": "AGETXT",
                    "operator": "not_matches_regex",
                    "value": "^[0-9]+-[0-9]+$"
                }
            ]
        },
        "Core": {
            "Id": "CDISC.SENDIG.102",
            "Version": "1",
            "Status": "Draft"
        },
        "Description": "AGETXT must be in number dash number format",
        "Outcome": {
            "Message": "AGETXT must be in number dash number format",
            "Output_Variables": [
                "USUBJID",
                "AGETXT"
            ]
        },
        "Rule_Type": "Record Data",
        "Sensitivity": "Record",
        "Authorities": [
            {
                "Organization": "CDISC",
                "Standards": [
                    {
                        "Name": "SENDIG",
                        "Version": "3.1",
                        "References": [
                            {
                                "Origin": "SDTM and SENDIG Conformance Rules",
                                "Rule_Identifier": {
                                    "Id": "102",
                                    "Version": "1"
                                },
                                "Version": "2.0",
                                "Citations": [
                                    {
                                        "Cited_Guidance": "AGETXT is used to present the age range in situations where the exact birthdate is not known.  It should be presented in number-number format..",
                                        "Document": "IG v3.1",
                                        "Item": "Specification",
                                        "Section": "5.1.1"
                                    }
                                ]
                            }
                        ]
                    }
                ]
            }
        ],
        "Scope": {
            "Classes": {
                "Include": [
                    "SPECIAL-PURPOSE"
                ]
            },
            "Domains": {
                "Include": [
                    "DM"
                ]
            }
        }
    },
    "id": "9cc3b54e-b973-4f21-b1a3-8a7058225801"
}