{
    "changed": "2022-11-09T08:21:51.540Z",
    "content": "Check:\n  all:\n    - name: POOLID\n      operator: non_empty\n    - name: USUBJID\n      operator: empty\nCore:\n  Id: CDISC.SENDIG.263\n  Version: '1'\n  Status: Draft\nDescription: Trigger error when POOLID does not contain a subject in POOLDEF\nOutcome:\n  Message: No subject is defined in POOLDEF for POOLID\nRule Type: Record Data\nSensitivity: Record\nAuthorities:\n  - Organization: CDISC\n    Standards:\n      - Name: SENDIG\n        Version: '3.1'\n        References:\n          - Origin: SDTM and SENDIG Conformance Rules\n            Rule Identifier:\n              Id: '263'\n              Version: '1'\n            Version: '2.0'\n            Citations:\n              - Cited Guidance: A pool must consist of at least one subject.\n                Document: IG v3.1\n                Section: 8.5.1.1\nScope:\n  Classes:\n    Include:\n      - SPECIAL-PURPOSE\n  Domains:\n    Include:\n      - POOLDEF\n",
    "created": "2022-11-09T08:21:51.540Z",
    "creator": {
        "id": "dc8bf014-df32-4631-8684-9a09a16c5071"
    },
    "json": {
        "Check": {
            "all": [
                {
                    "name": "POOLID",
                    "operator": "non_empty"
                },
                {
                    "name": "USUBJID",
                    "operator": "empty"
                }
            ]
        },
        "Core": {
            "Id": "CDISC.SENDIG.263",
            "Version": "1",
            "Status": "Draft"
        },
        "Description": "Trigger error when POOLID does not contain a subject in POOLDEF",
        "Outcome": {
            "Message": "No subject is defined in POOLDEF for POOLID"
        },
        "Rule_Type": "Record Data",
        "Sensitivity": "Record",
        "Authorities": [
            {
                "Organization": "CDISC",
                "Standards": [
                    {
                        "Name": "SENDIG",
                        "Version": "3.1",
                        "References": [
                            {
                                "Origin": "SDTM and SENDIG Conformance Rules",
                                "Rule_Identifier": {
                                    "Id": "263",
                                    "Version": "1"
                                },
                                "Version": "2.0",
                                "Citations": [
                                    {
                                        "Cited_Guidance": "A pool must consist of at least one subject.",
                                        "Document": "IG v3.1",
                                        "Section": "8.5.1.1"
                                    }
                                ]
                            }
                        ]
                    }
                ]
            }
        ],
        "Scope": {
            "Classes": {
                "Include": [
                    "SPECIAL-PURPOSE"
                ]
            },
            "Domains": {
                "Include": [
                    "POOLDEF"
                ]
            }
        }
    },
    "id": "b15278a1-dd0e-4a5e-9209-0dfcba48a039"
}