{
    "changed": "2022-09-28T17:47:37.094Z",
    "content": "Check:\n  all:\n    - name: --STAT\n      operator: equal_to\n      value: NOT DONE\n    - name: --REASND\n      operator: empty\nCore:\n  Id: CDISC.SENDIG.280\n  Version: '1'\n  Status: Draft\nDescription: Trigger error when --STAT=\"NOT DONE\" and --REASND is not populated\nOutcome:\n  Message: When --STAT is \"NOT DONE\", --REASND must be populated.\nRule Type: Record Data\nSensitivity: Record\nAuthorities:\n  - Organization: CDISC\n    Standards:\n      - Name: SENDIG\n        Version: '3.1'\n        References:\n          - Origin: SDTM and SENDIG Conformance Rules\n            Rule Identifier:\n              Id: '280'\n              Version: '1'\n            Version: '2.0'\n            Citations:\n              - Cited Guidance: Whenever MISTAT is \u201cNOT DONE\u201d; MIREASND should provide\n                  the reason for not completing the evaluation as scheduled in the\n                  study plan\n                Document: IG v3.1\n                Section: 6.3.1\nScope:\n  Classes:\n    Include:\n      - FINDINGS\n  Domains:\n    Include:\n      - LB\n      - MI\n",
    "created": "2022-09-28T15:55:12.811Z",
    "creator": {
        "id": "dc8bf014-df32-4631-8684-9a09a16c5071"
    },
    "json": {
        "Check": {
            "all": [
                {
                    "name": "--STAT",
                    "operator": "equal_to",
                    "value": "NOT DONE"
                },
                {
                    "name": "--REASND",
                    "operator": "empty"
                }
            ]
        },
        "Core": {
            "Id": "CDISC.SENDIG.280",
            "Version": "1",
            "Status": "Draft"
        },
        "Description": "Trigger error when --STAT=\"NOT DONE\" and --REASND is not populated",
        "Outcome": {
            "Message": "When --STAT is \"NOT DONE\", --REASND must be populated."
        },
        "Rule_Type": "Record Data",
        "Sensitivity": "Record",
        "Authorities": [
            {
                "Organization": "CDISC",
                "Standards": [
                    {
                        "Name": "SENDIG",
                        "Version": "3.1",
                        "References": [
                            {
                                "Origin": "SDTM and SENDIG Conformance Rules",
                                "Rule_Identifier": {
                                    "Id": "280",
                                    "Version": "1"
                                },
                                "Version": "2.0",
                                "Citations": [
                                    {
                                        "Cited_Guidance": "Whenever MISTAT is \u201cNOT DONE\u201d; MIREASND should provide the reason for not completing the evaluation as scheduled in the study plan",
                                        "Document": "IG v3.1",
                                        "Section": "6.3.1"
                                    }
                                ]
                            }
                        ]
                    }
                ]
            }
        ],
        "Scope": {
            "Classes": {
                "Include": [
                    "FINDINGS"
                ]
            },
            "Domains": {
                "Include": [
                    "LB",
                    "MI"
                ]
            }
        }
    },
    "id": "13cc7c64-214b-4635-be0c-e1c8261cf60c"
}