{
    "changed": "2022-11-02T13:15:30.384Z",
    "content": "Check:\n  all:\n    - name: PMDTC\n      operator: non_empty\n    - name: PMDTC\n      operator: is_not_unique_set\n      value:\n        - USUBJID\n        - PMTESTCD\n        - PMORRES\nCore:\n  Id: CDISC.SENDIG.191\n  Version: '1'\n  Status: Draft\nDescription: Raise an error when there is more than one record present for any particular\n  Palpable Mass test per Palpable Mass test in the PM Domain, for a subject on a particular\n  date.\nOutcome:\n  Message: The palpable mass test and result is not unique for this subject and date/time.\n  Output Variables:\n    - USUBJID\n    - PMTESTCD\n    - PMORRES\n    - PMDTC\nRule Type: Record Data\nSensitivity: Record\nAuthorities:\n  - Organization: CDISC\n    Standards:\n      - Name: SENDIG\n        Version: '3.1'\n        References:\n          - Origin: SDTM and SENDIG Conformance Rules\n            Rule Identifier:\n              Id: '191'\n              Version: '1'\n            Version: '2.0'\n            Citations:\n              - Cited Guidance: One record per test per palpable mass per observation\n                  time per subject\n                Document: SENDIG v3.1\n                Section: 6.3.910\nScope:\n  Classes:\n    Include:\n      - FINDINGS\n  Domains:\n    Include:\n      - PM\n",
    "created": "2022-11-02T13:12:50.579Z",
    "creator": {
        "id": "dc8bf014-df32-4631-8684-9a09a16c5071"
    },
    "json": {
        "Check": {
            "all": [
                {
                    "name": "PMDTC",
                    "operator": "non_empty"
                },
                {
                    "name": "PMDTC",
                    "operator": "is_not_unique_set",
                    "value": [
                        "USUBJID",
                        "PMTESTCD",
                        "PMORRES"
                    ]
                }
            ]
        },
        "Core": {
            "Id": "CDISC.SENDIG.191",
            "Version": "1",
            "Status": "Draft"
        },
        "Description": "Raise an error when there is more than one record present for any particular Palpable Mass test per Palpable Mass test in the PM Domain, for a subject on a particular date.",
        "Outcome": {
            "Message": "The palpable mass test and result is not unique for this subject and date/time.",
            "Output_Variables": [
                "USUBJID",
                "PMTESTCD",
                "PMORRES",
                "PMDTC"
            ]
        },
        "Rule_Type": "Record Data",
        "Sensitivity": "Record",
        "Authorities": [
            {
                "Organization": "CDISC",
                "Standards": [
                    {
                        "Name": "SENDIG",
                        "Version": "3.1",
                        "References": [
                            {
                                "Origin": "SDTM and SENDIG Conformance Rules",
                                "Rule_Identifier": {
                                    "Id": "191",
                                    "Version": "1"
                                },
                                "Version": "2.0",
                                "Citations": [
                                    {
                                        "Cited_Guidance": "One record per test per palpable mass per observation time per subject",
                                        "Document": "SENDIG v3.1",
                                        "Section": "6.3.910"
                                    }
                                ]
                            }
                        ]
                    }
                ]
            }
        ],
        "Scope": {
            "Classes": {
                "Include": [
                    "FINDINGS"
                ]
            },
            "Domains": {
                "Include": [
                    "PM"
                ]
            }
        }
    },
    "id": "20f4b291-7cf3-4a5e-91db-f437963d4ad4"
}