{
    "changed": "2022-09-30T13:23:49.736Z",
    "content": "Check:\n  all:\n    - name: EXDOSTXT\n      operator: non_empty\n    - name: EXDOSE\n      operator: non_empty\nCore:\n  Id: CDISC.SENDIG.314\n  Version: '1'\n  Status: Draft\nDescription: Raise an error when EXDOSE is populated when EXDOSTXT is populated\nOutcome:\n  Message: The value of COSEQ is not unique within POOLID\nRule Type: Record Data\nSensitivity: Record\nAuthorities:\n  - Organization: CDISC\n    Standards:\n      - Name: SENDIG\n        Version: '3.1'\n        References:\n          - Origin: SDTM and SENDIG Conformance Rules\n            Rule Identifier:\n              Id: '314'\n              Version: '1'\n            Version: '2.0'\n            Citations:\n              - Cited Guidance: If the amount of treatment administered cannot be\n                  represented as a number and populated in EXDOSE, this field is used\n                  to describe the amount of treatment administered.\n                Document: IG v3.1\n                Section: 6.1.1\nScope:\n  Classes:\n    Include:\n      - INTERVENTIONS\n  Domains:\n    Include:\n      - EX\n",
    "created": "2022-09-30T13:23:49.736Z",
    "creator": {
        "id": "dc8bf014-df32-4631-8684-9a09a16c5071"
    },
    "json": {
        "Check": {
            "all": [
                {
                    "name": "EXDOSTXT",
                    "operator": "non_empty"
                },
                {
                    "name": "EXDOSE",
                    "operator": "non_empty"
                }
            ]
        },
        "Core": {
            "Id": "CDISC.SENDIG.314",
            "Version": "1",
            "Status": "Draft"
        },
        "Description": "Raise an error when EXDOSE is populated when EXDOSTXT is populated",
        "Outcome": {
            "Message": "The value of COSEQ is not unique within POOLID"
        },
        "Rule_Type": "Record Data",
        "Sensitivity": "Record",
        "Authorities": [
            {
                "Organization": "CDISC",
                "Standards": [
                    {
                        "Name": "SENDIG",
                        "Version": "3.1",
                        "References": [
                            {
                                "Origin": "SDTM and SENDIG Conformance Rules",
                                "Rule_Identifier": {
                                    "Id": "314",
                                    "Version": "1"
                                },
                                "Version": "2.0",
                                "Citations": [
                                    {
                                        "Cited_Guidance": "If the amount of treatment administered cannot be represented as a number and populated in EXDOSE, this field is used to describe the amount of treatment administered.",
                                        "Document": "IG v3.1",
                                        "Section": "6.1.1"
                                    }
                                ]
                            }
                        ]
                    }
                ]
            }
        ],
        "Scope": {
            "Classes": {
                "Include": [
                    "INTERVENTIONS"
                ]
            },
            "Domains": {
                "Include": [
                    "EX"
                ]
            }
        }
    },
    "id": "aabf5d94-8a61-4ecb-9601-6885febfed64"
}