{
    "id": "c260c44f-9914-4616-be6e-9205ec9b0412",
    "changed": "2022-09-08T09:45:57Z",
    "content": "Check:\n  all:\n    - name: variable_label\n      operator: longer_than\n      value: 40\nCore:\n  Id: CDISC.SENDIG.3\n  Version: '1'\n  Status: Draft\nDescription: Raise and error if Variable label length > 40 characters\nOutcome:\n  Message: Variable label length should be less than or equal to 40 characters\nRule Type: Variable Metadata Check\nSensitivity: Dataset\nAuthorities:\n  - Organization: CDISC\n    Standards:\n      - Name: SENDIG\n        Version: '3.1'\n        References:\n          - Origin: SDTM and SENDIG Conformance Rules\n            Rule Identifier:\n              Id: 3\n              Version: '1'\n            Version: '2.0'\n            Citations:\n              - Cited Guidance: A descriptive Variable Label, using up to 40 characters,\n                  which should be unique for each variable in the dataset.\n                Document: IG v3.1\n                Section: 3.2.2\nScope:\n  Classes:\n    Include:\n      - ALL\n  Domains:\n    Include:\n      - ALL\n",
    "created": "2022-09-08T09:45:57Z",
    "creator": {
        "id": "dc8bf014-df32-4631-8684-9a09a16c5071"
    },
    "json": {
        "Check": {
            "all": [
                {
                    "name": "variable_label",
                    "operator": "longer_than",
                    "value": 40
                }
            ]
        },
        "Core": {
            "Id": "CDISC.SENDIG.3",
            "Version": "1",
            "Status": "Draft"
        },
        "Description": "Raise and error if Variable label length > 40 characters",
        "Outcome": {
            "Message": "Variable label length should be less than or equal to 40 characters"
        },
        "Rule_Type": "Variable Metadata Check",
        "Sensitivity": "Dataset",
        "Authorities": [
            {
                "Organization": "CDISC",
                "Standards": [
                    {
                        "Name": "SENDIG",
                        "Version": "3.1",
                        "References": [
                            {
                                "Origin": "SDTM and SENDIG Conformance Rules",
                                "Rule_Identifier": {
                                    "Id": 3,
                                    "Version": "1"
                                },
                                "Version": "2.0",
                                "Citations": [
                                    {
                                        "Cited_Guidance": "A descriptive Variable Label, using up to 40 characters, which should be unique for each variable in the dataset.",
                                        "Document": "IG v3.1",
                                        "Section": "3.2.2"
                                    }
                                ]
                            }
                        ]
                    }
                ]
            }
        ],
        "Scope": {
            "Classes": {
                "Include": [
                    "ALL"
                ]
            },
            "Domains": {
                "Include": [
                    "ALL"
                ]
            }
        }
    }
}