{
    "changed": "2022-09-21T15:30:59.776Z",
    "content": "Check:\n  all:\n    - name: --DTHREL\n      operator: non_empty\n    - name: --DTHREL\n      operator: not_equal_to\n      value: Y\n    - name: --DTHREL\n      operator: not_equal_to\n      value: U\n    - name: --DTHREL\n      operator: not_equal_to\n      value: N\nCore:\n  Id: CDISC.SENDIG.183\n  Version: '1'\n  Status: Draft\nDescription: Raise an error when record is --DTHREL is not null and is not equal to\n  'Y', 'N' or 'U'\nOutcome:\n  Message: --DTHREF must be 'Y, 'N', 'U' or null.\nRule Type: Record Data\nSensitivity: Record\nAuthorities:\n  - Organization: CDISC\n    Standards:\n      - Name: SENDIG\n        Version: '3.1'\n        References:\n          - Origin: SDTM and SENDIG Conformance Rules\n            Rule Identifier:\n              Id: '183'\n              Version: '1'\n            Version: '2.0'\n            Citations:\n              - Cited Guidance: --DTHREL Describes the relationship of a particular\n                  finding to the death of a subject (Y=caused death, N=did not cause\n                  death, U=unknown). May be left null if not available.\n                Document: SENDIG v3.1\n                Section: Section 6.3.7-6.3.8\nScope:\n  Classes:\n    Include:\n      - FINDINGS\n  Domains:\n    Include:\n      - MA\n      - MI\n",
    "created": "2022-09-21T15:30:59.776Z",
    "creator": {
        "id": "dc8bf014-df32-4631-8684-9a09a16c5071"
    },
    "json": {
        "Check": {
            "all": [
                {
                    "name": "--DTHREL",
                    "operator": "non_empty"
                },
                {
                    "name": "--DTHREL",
                    "operator": "not_equal_to",
                    "value": "Y"
                },
                {
                    "name": "--DTHREL",
                    "operator": "not_equal_to",
                    "value": "U"
                },
                {
                    "name": "--DTHREL",
                    "operator": "not_equal_to",
                    "value": "N"
                }
            ]
        },
        "Core": {
            "Id": "CDISC.SENDIG.183",
            "Version": "1",
            "Status": "Draft"
        },
        "Description": "Raise an error when record is --DTHREL is not null and is not equal to 'Y', 'N' or 'U'",
        "Outcome": {
            "Message": "--DTHREF must be 'Y, 'N', 'U' or null."
        },
        "Rule_Type": "Record Data",
        "Sensitivity": "Record",
        "Authorities": [
            {
                "Organization": "CDISC",
                "Standards": [
                    {
                        "Name": "SENDIG",
                        "Version": "3.1",
                        "References": [
                            {
                                "Origin": "SDTM and SENDIG Conformance Rules",
                                "Rule_Identifier": {
                                    "Id": "183",
                                    "Version": "1"
                                },
                                "Version": "2.0",
                                "Citations": [
                                    {
                                        "Cited_Guidance": "--DTHREL Describes the relationship of a particular finding to the death of a subject (Y=caused death, N=did not cause death, U=unknown). May be left null if not available.",
                                        "Document": "SENDIG v3.1",
                                        "Section": "Section 6.3.7-6.3.8"
                                    }
                                ]
                            }
                        ]
                    }
                ]
            }
        ],
        "Scope": {
            "Classes": {
                "Include": [
                    "FINDINGS"
                ]
            },
            "Domains": {
                "Include": [
                    "MA",
                    "MI"
                ]
            }
        }
    },
    "id": "a34de3f8-e0db-47cb-80ae-37bed8f404fa"
}