{
    "id": "e25da6b4-b65a-4c4a-8ba4-38a0e4f101ba",
    "changed": "2022-03-03T15:59:46Z",
    "content": "Core:\n  Id: CDISC.SEND.320\n  Version: '1'\n  Status: Draft\nDescription: Raise an error when MADTC or MIDTC or TFDTC is not null and not equal\n  to the date/time of the subject disposition from DS domain\nRule Type: Record Data\nSensitivity: Record\nAuthorities:\n  - Organization: CDISC\n    Standards:\n      - Name: SENDIG\n        Version: v3.1\n        References:\n          - Origin: SEND Conformance Rules\n            Rule Identifier:\n              Id: SEND320\n              Version: '1'\n            Version: '4.0'\n            Citations:\n              - Cited Guidance:\n                Document:\n                Section:\n      - Name: SENDIG\n        Version: v3.1.1\n        References:\n          - Origin: SEND Conformance Rules\n            Rule Identifier:\n              Id: SEND320\n              Version: '1'\n            Version: '4.0'\n            Citations:\n              - Cited Guidance:\n                Document:\n                Section:\n      - Name: SENDIG-DART\n        Version: v1.1\n        References:\n          - Origin: SEND Conformance Rules\n            Rule Identifier:\n              Id: SEND320\n              Version: '1'\n            Version: '4.0'\n            Citations:\n              - Cited Guidance:\n                Document:\n                Section:\nScope:\n  Classes:\n    Include:\n      - ALL\n",
    "created": "2022-02-14T17:20:46Z",
    "creator": {
        "id": "5042c868-b79a-415d-b5aa-12e6474ce80c"
    },
    "json": {
        "Core": {
            "Id": "CDISC.SEND.320",
            "Version": "1",
            "Status": "Draft"
        },
        "Description": "Raise an error when MADTC or MIDTC or TFDTC is not null and not equal to the date/time of the subject disposition from DS domain",
        "Rule_Type": "Record Data",
        "Sensitivity": "Record",
        "Authorities": [
            {
                "Organization": "CDISC",
                "Standards": [
                    {
                        "Name": "SENDIG",
                        "Version": "v3.1",
                        "References": [
                            {
                                "Origin": "SEND Conformance Rules",
                                "Rule_Identifier": {
                                    "Id": "SEND320",
                                    "Version": "1"
                                },
                                "Version": "4.0",
                                "Citations": [
                                    {
                                        "Cited_Guidance": null,
                                        "Document": null,
                                        "Section": null
                                    }
                                ]
                            }
                        ]
                    },
                    {
                        "Name": "SENDIG",
                        "Version": "v3.1.1",
                        "References": [
                            {
                                "Origin": "SEND Conformance Rules",
                                "Rule_Identifier": {
                                    "Id": "SEND320",
                                    "Version": "1"
                                },
                                "Version": "4.0",
                                "Citations": [
                                    {
                                        "Cited_Guidance": null,
                                        "Document": null,
                                        "Section": null
                                    }
                                ]
                            }
                        ]
                    },
                    {
                        "Name": "SENDIG-DART",
                        "Version": "v1.1",
                        "References": [
                            {
                                "Origin": "SEND Conformance Rules",
                                "Rule_Identifier": {
                                    "Id": "SEND320",
                                    "Version": "1"
                                },
                                "Version": "4.0",
                                "Citations": [
                                    {
                                        "Cited_Guidance": null,
                                        "Document": null,
                                        "Section": null
                                    }
                                ]
                            }
                        ]
                    }
                ]
            }
        ],
        "Scope": {
            "Classes": {
                "Include": [
                    "ALL"
                ]
            }
        }
    }
}