{
    "changed": "2022-09-21T15:12:10.281Z",
    "content": "Check:\n  all:\n    - name: --SPCUFL\n      operator: non_empty\n    - name: --SPCUFL\n      operator: not_equal_to\n      value: N\nCore:\n  Id: CDISC.SENDIG.182\n  Version: '1'\n  Status: Draft\nDescription: Raise an error when record is --SPCUFL is not null and is not equal to\n  'N'\nOutcome:\n  Message: --SPCUFL must be 'N' or null.\nRule Type: Record Data\nSensitivity: Record\nAuthorities:\n  - Organization: CDISC\n    Standards:\n      - Name: SENDIG\n        Version: '3.1'\n        References:\n          - Origin: SDTM and SENDIG Conformance Rules\n            Rule Identifier:\n              Id: '182'\n              Version: '1'\n            Version: '2.0'\n            Citations:\n              - Cited Guidance: -SPCUFL describes the usability of the specimen for\n                  the test. Example, N = the specimen is not usable; otherwise null.\n                Document: SENDIG v3.1\n                Section: Section 6.3.6\nScope:\n  Classes:\n    Include:\n      - FINDINGS\n  Domains:\n    Include:\n      - LB\n      - MA\n      - MI\n      - PC\n",
    "created": "2022-09-21T15:01:21.026Z",
    "creator": {
        "id": "dc8bf014-df32-4631-8684-9a09a16c5071"
    },
    "json": {
        "Check": {
            "all": [
                {
                    "name": "--SPCUFL",
                    "operator": "non_empty"
                },
                {
                    "name": "--SPCUFL",
                    "operator": "not_equal_to",
                    "value": "N"
                }
            ]
        },
        "Core": {
            "Id": "CDISC.SENDIG.182",
            "Version": "1",
            "Status": "Draft"
        },
        "Description": "Raise an error when record is --SPCUFL is not null and is not equal to 'N'",
        "Outcome": {
            "Message": "--SPCUFL must be 'N' or null."
        },
        "Rule_Type": "Record Data",
        "Sensitivity": "Record",
        "Authorities": [
            {
                "Organization": "CDISC",
                "Standards": [
                    {
                        "Name": "SENDIG",
                        "Version": "3.1",
                        "References": [
                            {
                                "Origin": "SDTM and SENDIG Conformance Rules",
                                "Rule_Identifier": {
                                    "Id": "182",
                                    "Version": "1"
                                },
                                "Version": "2.0",
                                "Citations": [
                                    {
                                        "Cited_Guidance": "-SPCUFL describes the usability of the specimen for the test. Example, N = the specimen is not usable; otherwise null.",
                                        "Document": "SENDIG v3.1",
                                        "Section": "Section 6.3.6"
                                    }
                                ]
                            }
                        ]
                    }
                ]
            }
        ],
        "Scope": {
            "Classes": {
                "Include": [
                    "FINDINGS"
                ]
            },
            "Domains": {
                "Include": [
                    "LB",
                    "MA",
                    "MI",
                    "PC"
                ]
            }
        }
    },
    "id": "bdadbc0f-f9a4-4347-80bf-4870f66baab1"
}