{
    "changed": "2022-09-29T09:14:10.022Z",
    "content": "Check:\n  all:\n    - name: --DTC\n      operator: empty\n    - name: --DY\n      operator: empty\nCore:\n  Id: CDISC.SENDIG.289\n  Version: '1'\n  Status: Draft\nDescription: When a domain belongs to the Findings General Observation Class, and\n  the domain is one in which data are usually collected at multiple study days, at\n  least --DTC or --DY must be populated.\nOutcome:\n  Message: Neither --DTC nor --DY is populated\nRule Type: Record Data\nSensitivity: Record\nAuthorities:\n  - Organization: CDISC\n    Standards:\n      - Name: SENDIG\n        Version: '3.1'\n        References:\n          - Origin: SDTM and SENDIG Conformance Rules\n            Rule Identifier:\n              Id: '289'\n              Version: '1'\n            Version: '2.0'\n            Citations:\n              - Cited Guidance: In the Findings observation class, where data are\n                  usually collected at multiple study days, either --DTC or --DY must\n                  be used.\n                Document: IG v3.1\n                Section: '4.4'\nScope:\n  Classes:\n    Include:\n      - FINDINGS\n  Domains:\n    Include:\n      - BW\n      - BG\n      - CL\n      - FW\n      - LB\n      - OM\n      - PM\n      - PC\n      - VS\n      - EG\n      - CV\n      - RE\n",
    "created": "2022-09-29T08:55:24.832Z",
    "creator": {
        "id": "dc8bf014-df32-4631-8684-9a09a16c5071"
    },
    "json": {
        "Check": {
            "all": [
                {
                    "name": "--DTC",
                    "operator": "empty"
                },
                {
                    "name": "--DY",
                    "operator": "empty"
                }
            ]
        },
        "Core": {
            "Id": "CDISC.SENDIG.289",
            "Version": "1",
            "Status": "Draft"
        },
        "Description": "When a domain belongs to the Findings General Observation Class, and the domain is one in which data are usually collected at multiple study days, at least --DTC or --DY must be populated.",
        "Outcome": {
            "Message": "Neither --DTC nor --DY is populated"
        },
        "Rule_Type": "Record Data",
        "Sensitivity": "Record",
        "Authorities": [
            {
                "Organization": "CDISC",
                "Standards": [
                    {
                        "Name": "SENDIG",
                        "Version": "3.1",
                        "References": [
                            {
                                "Origin": "SDTM and SENDIG Conformance Rules",
                                "Rule_Identifier": {
                                    "Id": "289",
                                    "Version": "1"
                                },
                                "Version": "2.0",
                                "Citations": [
                                    {
                                        "Cited_Guidance": "In the Findings observation class, where data are usually collected at multiple study days, either --DTC or --DY must be used.",
                                        "Document": "IG v3.1",
                                        "Section": "4.4"
                                    }
                                ]
                            }
                        ]
                    }
                ]
            }
        ],
        "Scope": {
            "Classes": {
                "Include": [
                    "FINDINGS"
                ]
            },
            "Domains": {
                "Include": [
                    "BW",
                    "BG",
                    "CL",
                    "FW",
                    "LB",
                    "OM",
                    "PM",
                    "PC",
                    "VS",
                    "EG",
                    "CV",
                    "RE"
                ]
            }
        }
    },
    "id": "58420b2b-d9fa-47d2-85a9-583b3f9ca636"
}