{
    "changed": "2022-10-12T13:28:42.825Z",
    "content": "Check:\n  all:\n    - name: --DY\n      operator: non_empty\n    - name: --DTC\n      operator: is_complete_date\n    - name: RFSTDTC\n      operator: is_complete_date\n    - name: --DY       # checking failure criteria\r\n      operator: not_equal_to\n      value: $val_dy   # this is created in the operations statement that follows\r\nOperations:\n  - name: --DTC\n    operator: dy     # does dy op take into acct +1?\r\n    id: $val_dy      # ex in devops 2538 used -- but that threw an error\r\nCore:\n  Id: CDISC.SENDIG.74\n  Version: '1'\n  Status: Draft\nDescription: Raise an error when --DY is not calculated as per the study day algorithm\n  as a non-zero integer value when the date portion of --DTC is complete and the date\n  portion of DM.RFSTDTC is a complete date AND --DY is not empty\nMatch Datasets:\n  - Name: DM\n    Keys:\n      - USUBJID\nOutcome:\n  Message: --DY is not calculated correctly even though the date portion of --DTC\n    is complete, the date portion of DM.RFSTDTC is a complete date, and --DY is not\n    empty.\n  Output Variables:\n    - --DY\n    - --DTC\n    - RFSTDTC\nRule Type: Record Data\nSensitivity: Record\nAuthorities:\n  - Organization: CDISC\n    Standards:\n      - Name: SENDIG\n        Version: '3.1'\n        References:\n          - Origin: SDTM and SDTMIG Conformance Rules\n            Rule Identifier:\n              Id: SENDIG74\n              Version: '2'\n            Version: '2.0'\n            Citations:\n              - Cited Guidance: All Study Day values are integers. Thus, to calculate\n                  Study Day --DY = (date portion of --DTC) minus (date portion of\n                  RFSTDTC) + 1 if --DTC is on or after RFSTDTC.\n                Document: SENDIG v3.1\n                Section: 4.4.4\nScope:\n  Classes:\n    Include:\n      - ALL\n  Domains:\n    Include:\n      - ALL\n",
    "created": "2022-10-12T13:28:42.825Z",
    "creator": {
        "id": "dc8bf014-df32-4631-8684-9a09a16c5071"
    },
    "json": {
        "Check": {
            "all": [
                {
                    "name": "--DY",
                    "operator": "non_empty"
                },
                {
                    "name": "--DTC",
                    "operator": "is_complete_date"
                },
                {
                    "name": "RFSTDTC",
                    "operator": "is_complete_date"
                },
                {
                    "name": "--DY",
                    "operator": "not_equal_to",
                    "value": "$val_dy"
                }
            ]
        },
        "Operations": [
            {
                "name": "--DTC",
                "operator": "dy",
                "id": "$val_dy"
            }
        ],
        "Core": {
            "Id": "CDISC.SENDIG.74",
            "Version": "1",
            "Status": "Draft"
        },
        "Description": "Raise an error when --DY is not calculated as per the study day algorithm as a non-zero integer value when the date portion of --DTC is complete and the date portion of DM.RFSTDTC is a complete date AND --DY is not empty",
        "Match_Datasets": [
            {
                "Name": "DM",
                "Keys": [
                    "USUBJID"
                ]
            }
        ],
        "Outcome": {
            "Message": "--DY is not calculated correctly even though the date portion of --DTC is complete, the date portion of DM.RFSTDTC is a complete date, and --DY is not empty.",
            "Output_Variables": [
                "--DY",
                "--DTC",
                "RFSTDTC"
            ]
        },
        "Rule_Type": "Record Data",
        "Sensitivity": "Record",
        "Authorities": [
            {
                "Organization": "CDISC",
                "Standards": [
                    {
                        "Name": "SENDIG",
                        "Version": "3.1",
                        "References": [
                            {
                                "Origin": "SDTM and SDTMIG Conformance Rules",
                                "Rule_Identifier": {
                                    "Id": "SENDIG74",
                                    "Version": "2"
                                },
                                "Version": "2.0",
                                "Citations": [
                                    {
                                        "Cited_Guidance": "All Study Day values are integers. Thus, to calculate Study Day --DY = (date portion of --DTC) minus (date portion of RFSTDTC) + 1 if --DTC is on or after RFSTDTC.",
                                        "Document": "SENDIG v3.1",
                                        "Section": "4.4.4"
                                    }
                                ]
                            }
                        ]
                    }
                ]
            }
        ],
        "Scope": {
            "Classes": {
                "Include": [
                    "ALL"
                ]
            },
            "Domains": {
                "Include": [
                    "ALL"
                ]
            }
        }
    },
    "id": "d86df2e5-c610-421d-be94-9e3000a2fa4a"
}