{
    "changed": "2022-09-15T09:19:49.936Z",
    "content": "Check:\n  all:\n    - name: --ORRES\n      operator: not_matches_regex\n      value: ^[+-]?([0-9]*[.])?[0-9]\n    - name: --STRESN\n      operator: non_empty\nCore:\n  Id: CDISC.SENDIG.91\n  Version: '1'\n  Status: Draft\nDescription: When --ORRES is representing numeric data with special characters like\n  '<' and '>', , --STRESN may not be populated.\nOutcome:\n  Message: --STRESN may not be populated as --ORRES does not represent a pure numeric\n    value\n  Output Variables:\n    - --ORRES\n    - --STRESN\nRule Type: Record Data\nSensitivity: Record\nAuthorities:\n  - Organization: CDISC\n    Standards:\n      - Name: SENDIG\n        Version: '3.1'\n        References:\n          - Origin: SDTM and SENDIG Conformance Rules\n            Rule Identifier:\n              Id: '91'\n              Version: '1'\n            Version: '2.0'\n            Citations:\n              - Cited Guidance: If numeric data are collected with characters attached\n                  (e.g., >, <) no data value should be populated in --STRESN\n                Document: IG v3.1\n                Section: 4.5.1.1\nScope:\n  Classes:\n    Include:\n      - FINDINGS\n  Domains:\n    Include:\n      - ALL\n",
    "created": "2022-09-15T09:19:49.936Z",
    "creator": {
        "id": "dc8bf014-df32-4631-8684-9a09a16c5071"
    },
    "json": {
        "Check": {
            "all": [
                {
                    "name": "--ORRES",
                    "operator": "not_matches_regex",
                    "value": "^[+-]?([0-9]*[.])?[0-9]"
                },
                {
                    "name": "--STRESN",
                    "operator": "non_empty"
                }
            ]
        },
        "Core": {
            "Id": "CDISC.SENDIG.91",
            "Version": "1",
            "Status": "Draft"
        },
        "Description": "When --ORRES is representing numeric data with special characters like '<' and '>', , --STRESN may not be populated.",
        "Outcome": {
            "Message": "--STRESN may not be populated as --ORRES does not represent a pure numeric value",
            "Output_Variables": [
                "--ORRES",
                "--STRESN"
            ]
        },
        "Rule_Type": "Record Data",
        "Sensitivity": "Record",
        "Authorities": [
            {
                "Organization": "CDISC",
                "Standards": [
                    {
                        "Name": "SENDIG",
                        "Version": "3.1",
                        "References": [
                            {
                                "Origin": "SDTM and SENDIG Conformance Rules",
                                "Rule_Identifier": {
                                    "Id": "91",
                                    "Version": "1"
                                },
                                "Version": "2.0",
                                "Citations": [
                                    {
                                        "Cited_Guidance": "If numeric data are collected with characters attached (e.g., >, <) no data value should be populated in --STRESN",
                                        "Document": "IG v3.1",
                                        "Section": "4.5.1.1"
                                    }
                                ]
                            }
                        ]
                    }
                ]
            }
        ],
        "Scope": {
            "Classes": {
                "Include": [
                    "FINDINGS"
                ]
            },
            "Domains": {
                "Include": [
                    "ALL"
                ]
            }
        }
    },
    "id": "fc41322a-99cd-49ea-9abb-1449b39b19ca"
}