{
    "changed": "2022-09-09T16:32:15.015Z",
    "content": "Check:\n  all:\n    - name: ARMCD\n      operator: longer_than\n      value: 20\nCore:\n  Id: CDISC.SENDIG.27.1\n  Version: '1'\n  Status: Draft\nDescription: Verify ARMCD value length is <= 20\nOutcome:\n  Message: ARMCD value length is greater than 20\n  Output Variables:\n    - ARMCD\nRule Type: Record Data\nSensitivity: Record\nAuthorities:\n  - Organization: CDISC\n    Standards:\n      - Name: SENDIG\n        Version: '3.1'\n        References:\n          - Origin: SDTM and SENDIG Conformance Rules\n            Rule Identifier:\n              Id: '27.1'\n              Version: '1'\n            Version: '2.0'\n            Citations:\n              - Cited Guidance: ARMCD is limited to 20 characters, but does not have\n                  special character restrictions.\n                Document: SENDIG v3.1\n                Section: 4.2.1\nScope:\n  Classes:\n    Include:\n      - SPECIAL-PURPOSE\n      - TRIAL DESIGN\n  Domains:\n    Include:\n      - DM\n      - TA\n      - TX\n",
    "created": "2022-09-09T16:32:15.015Z",
    "creator": {
        "id": "dc8bf014-df32-4631-8684-9a09a16c5071"
    },
    "json": {
        "Check": {
            "all": [
                {
                    "name": "ARMCD",
                    "operator": "longer_than",
                    "value": 20
                }
            ]
        },
        "Core": {
            "Id": "CDISC.SENDIG.27.1",
            "Version": "1",
            "Status": "Draft"
        },
        "Description": "Verify ARMCD value length is <= 20",
        "Outcome": {
            "Message": "ARMCD value length is greater than 20",
            "Output_Variables": [
                "ARMCD"
            ]
        },
        "Rule_Type": "Record Data",
        "Sensitivity": "Record",
        "Authorities": [
            {
                "Organization": "CDISC",
                "Standards": [
                    {
                        "Name": "SENDIG",
                        "Version": "3.1",
                        "References": [
                            {
                                "Origin": "SDTM and SENDIG Conformance Rules",
                                "Rule_Identifier": {
                                    "Id": "27.1",
                                    "Version": "1"
                                },
                                "Version": "2.0",
                                "Citations": [
                                    {
                                        "Cited_Guidance": "ARMCD is limited to 20 characters, but does not have special character restrictions.",
                                        "Document": "SENDIG v3.1",
                                        "Section": "4.2.1"
                                    }
                                ]
                            }
                        ]
                    }
                ]
            }
        ],
        "Scope": {
            "Classes": {
                "Include": [
                    "SPECIAL-PURPOSE",
                    "TRIAL DESIGN"
                ]
            },
            "Domains": {
                "Include": [
                    "DM",
                    "TA",
                    "TX"
                ]
            }
        }
    },
    "id": "fa6f598b-ef9b-48d1-bda6-b8c03a8b2bbf"
}