{
    "changed": "2022-09-29T09:45:06.032Z",
    "content": "Check:\n  all:\n    # TODO: although we use \"exists\" here, I get a \"Column not found in data\" execution error when there is no xxTPTNUM column\r\n    - name: --TPTNUM\n      operator: exists\n    - name: --TPT\n      operator: exists\n    - name: --TPTNUM\n      operator: non_empty\n    - name: --TPT\n      operator: non_empty\n    - name: --TPTNUM\n      operator: is_not_unique_relationship\n      value: --TPT\nCore:\n  Id: CDISC.SENDIG.290\n  Version: '1'\n  Status: Draft\nDescription: There must be a one-to-one relationship between the values of --TPT and\n  --TPTNUM\nOutcome:\n  Message: The relationship between --TPT and --TPTNUM is not a one-to-one relationship\nRule Type: Record Data\nSensitivity: Record\nAuthorities:\n  - Organization: CDISC\n    Standards:\n      - Name: SENDIG\n        Version: '3.1'\n        References:\n          - Origin: SDTM and SENDIG Conformance Rules\n            Rule Identifier:\n              Id: '290'\n              Version: '1'\n            Version: '2.0'\n            Citations:\n              - Cited Guidance: For each unique planned time point (--TPT), there\n                  must be a one-to-one relationship between the values of --TPT and\n                  --TPTNUM. Uniqueness for these time points is determined by a combination\n                  of the domain, study day, and, if present, category and/or subcategory\n                  (--CAT/--SCAT). Other variables, such as --TESTCD and --METHOD,\n                  may also be needed in some cases to define uniqueness. When this\n                  occurs, clarification should be provided as a comment to --TPTNUM\n                  in the define file.\n                Document: IG v3.1\n                Section: '4.4'\nScope:\n  Classes:\n    Include:\n      - FINDINGS\n  Domains:\n    Include:\n      - ALL\n",
    "created": "2022-09-29T09:32:33.656Z",
    "creator": {
        "id": "dc8bf014-df32-4631-8684-9a09a16c5071"
    },
    "json": {
        "Check": {
            "all": [
                {
                    "name": "--TPTNUM",
                    "operator": "exists"
                },
                {
                    "name": "--TPT",
                    "operator": "exists"
                },
                {
                    "name": "--TPTNUM",
                    "operator": "non_empty"
                },
                {
                    "name": "--TPT",
                    "operator": "non_empty"
                },
                {
                    "name": "--TPTNUM",
                    "operator": "is_not_unique_relationship",
                    "value": "--TPT"
                }
            ]
        },
        "Core": {
            "Id": "CDISC.SENDIG.290",
            "Version": "1",
            "Status": "Draft"
        },
        "Description": "There must be a one-to-one relationship between the values of --TPT and --TPTNUM",
        "Outcome": {
            "Message": "The relationship between --TPT and --TPTNUM is not a one-to-one relationship"
        },
        "Rule_Type": "Record Data",
        "Sensitivity": "Record",
        "Authorities": [
            {
                "Organization": "CDISC",
                "Standards": [
                    {
                        "Name": "SENDIG",
                        "Version": "3.1",
                        "References": [
                            {
                                "Origin": "SDTM and SENDIG Conformance Rules",
                                "Rule_Identifier": {
                                    "Id": "290",
                                    "Version": "1"
                                },
                                "Version": "2.0",
                                "Citations": [
                                    {
                                        "Cited_Guidance": "For each unique planned time point (--TPT), there must be a one-to-one relationship between the values of --TPT and --TPTNUM. Uniqueness for these time points is determined by a combination of the domain, study day, and, if present, category and/or subcategory (--CAT/--SCAT). Other variables, such as --TESTCD and --METHOD, may also be needed in some cases to define uniqueness. When this occurs, clarification should be provided as a comment to --TPTNUM in the define file.",
                                        "Document": "IG v3.1",
                                        "Section": "4.4"
                                    }
                                ]
                            }
                        ]
                    }
                ]
            }
        ],
        "Scope": {
            "Classes": {
                "Include": [
                    "FINDINGS"
                ]
            },
            "Domains": {
                "Include": [
                    "ALL"
                ]
            }
        }
    },
    "id": "c9ba683e-e1a6-479b-a71e-ba1a57e437ab"
}