{
    "changed": "2022-09-19T07:49:13.420Z",
    "content": "Check:\n  all:\n    - name: --STAT\n      operator: non_empty\n    - name: --STAT\n      operator: not_equal_to\n      value: NOT DONE\n# TODO: Essentially requires a lookup in the (ND) codelist through a CDISC-Library query     \r\nCore:\n  Id: CDISC.SENDIG.143\n  Version: '1'\n  Status: Draft\nDescription: Trigger error when --STAT is non-empty and does not contain a value from\n  the ND codelist\nOutcome:\n  Message: --STAT does not contain a value from the (ND) codelist\nRule Type: Record Data\nSensitivity: Record\nAuthorities:\n  - Organization: CDISC\n    Standards:\n      - Name: SENDIG\n        Version: '3.1'\n        References:\n          - Origin: SDTM and SENDIG Conformance Rules\n            Rule Identifier:\n              Id: '143'\n              Version: '1'\n            Version: '2.0'\n            Citations:\n              - Cited Guidance: (ND) codelist is referenced in the domain table\n                Document: IG v3.1\n                Section: 6.3.1\nScope:\n  Classes:\n    Include:\n      - FINDINGS\n  Domains:\n    Exclude:\n      - SC\n",
    "created": "2022-09-19T07:40:59.532Z",
    "creator": {
        "id": "dc8bf014-df32-4631-8684-9a09a16c5071"
    },
    "json": {
        "Check": {
            "all": [
                {
                    "name": "--STAT",
                    "operator": "non_empty"
                },
                {
                    "name": "--STAT",
                    "operator": "not_equal_to",
                    "value": "NOT DONE"
                }
            ]
        },
        "Core": {
            "Id": "CDISC.SENDIG.143",
            "Version": "1",
            "Status": "Draft"
        },
        "Description": "Trigger error when --STAT is non-empty and does not contain a value from the ND codelist",
        "Outcome": {
            "Message": "--STAT does not contain a value from the (ND) codelist"
        },
        "Rule_Type": "Record Data",
        "Sensitivity": "Record",
        "Authorities": [
            {
                "Organization": "CDISC",
                "Standards": [
                    {
                        "Name": "SENDIG",
                        "Version": "3.1",
                        "References": [
                            {
                                "Origin": "SDTM and SENDIG Conformance Rules",
                                "Rule_Identifier": {
                                    "Id": "143",
                                    "Version": "1"
                                },
                                "Version": "2.0",
                                "Citations": [
                                    {
                                        "Cited_Guidance": "(ND) codelist is referenced in the domain table",
                                        "Document": "IG v3.1",
                                        "Section": "6.3.1"
                                    }
                                ]
                            }
                        ]
                    }
                ]
            }
        ],
        "Scope": {
            "Classes": {
                "Include": [
                    "FINDINGS"
                ]
            },
            "Domains": {
                "Exclude": [
                    "SC"
                ]
            }
        }
    },
    "id": "b6761379-29df-4da9-b845-6ecd6c0d4077"
}