{
    "changed": "2022-09-16T07:07:13.508Z",
    "content": "Check:\n  all:\n    - name: USUBJID\n      operator: non_empty\n    - name: USUBJID\n      operator: is_not_contained_by\n      value: $dm_usubjid\nCore:\n  Id: CDISC.SENDIG.109\n  Version: '1'\n  Status: Draft\nDescription: Trigger error when USUBJID is not present in DM in DM.USUBJID\nOperations:\n  - domain: DM\n    id: $dm_usubjid\n    name: USUBJID\n    operator: distinct\nOutcome:\n  Message: USUBJID is not found in DM.USUBJID\nRule Type: Record Data\nSensitivity: Record\nAuthorities:\n  - Organization: CDISC\n    Standards:\n      - Name: SENDIG\n        Version: '3.1'\n        References:\n          - Origin: SDTM and SENDIG Conformance Rules\n            Rule Identifier:\n              Id: '109'\n              Version: '1'\n            Version: '2.0'\n            Citations:\n              - Cited Guidance: To identify a subject uniquely across a submission,\n                  a unique identifier (USUBJID) should be signed and included in all\n                  subject-related datasets in the submission.\n                Document: IG v3.1\n                Section: 5.5.5.1\nScope:\n  Classes:\n    Include:\n      - ALL\n  Domains:\n    Include:\n      - ALL\n",
    "created": "2022-09-16T07:07:13.508Z",
    "creator": {
        "id": "dc8bf014-df32-4631-8684-9a09a16c5071"
    },
    "json": {
        "Check": {
            "all": [
                {
                    "name": "USUBJID",
                    "operator": "non_empty"
                },
                {
                    "name": "USUBJID",
                    "operator": "is_not_contained_by",
                    "value": "$dm_usubjid"
                }
            ]
        },
        "Core": {
            "Id": "CDISC.SENDIG.109",
            "Version": "1",
            "Status": "Draft"
        },
        "Description": "Trigger error when USUBJID is not present in DM in DM.USUBJID",
        "Operations": [
            {
                "domain": "DM",
                "id": "$dm_usubjid",
                "name": "USUBJID",
                "operator": "distinct"
            }
        ],
        "Outcome": {
            "Message": "USUBJID is not found in DM.USUBJID"
        },
        "Rule_Type": "Record Data",
        "Sensitivity": "Record",
        "Authorities": [
            {
                "Organization": "CDISC",
                "Standards": [
                    {
                        "Name": "SENDIG",
                        "Version": "3.1",
                        "References": [
                            {
                                "Origin": "SDTM and SENDIG Conformance Rules",
                                "Rule_Identifier": {
                                    "Id": "109",
                                    "Version": "1"
                                },
                                "Version": "2.0",
                                "Citations": [
                                    {
                                        "Cited_Guidance": "To identify a subject uniquely across a submission, a unique identifier (USUBJID) should be signed and included in all subject-related datasets in the submission.",
                                        "Document": "IG v3.1",
                                        "Section": "5.5.5.1"
                                    }
                                ]
                            }
                        ]
                    }
                ]
            }
        ],
        "Scope": {
            "Classes": {
                "Include": [
                    "ALL"
                ]
            },
            "Domains": {
                "Include": [
                    "ALL"
                ]
            }
        }
    },
    "id": "33d8730a-c090-495e-8acb-b567a2589f21"
}