{
    "changed": "2022-09-27T18:38:42.282Z",
    "content": "Check:\n  all:\n    - name: TXPARMCD\n      operator: equal_to\n      value: TRTDOS\n    - name: TXVAL\n      operator: not_matches_regex\n      value: '[+-]?([0-9]*[.])?[0-9]+$'\n    - name: TXVAL\n      operator: not_matches_regex\n      # see https://stackoverflow.com/questions/44374088/regex-to-match-comma-separated-numbers-or-stop-full-match-only\r\n      value: ^(\\s*-?\\d+(\\.\\d+)?)(\\s*,\\s*-?\\d+(\\.\\d+)?)*$\n    - name: TXVAL\n      operator: not_equal_to\n      value: SEE PROTOCOL\nCore:\n  Id: CDISC.SENDIG.240\n  Version: '1'\n  Status: Draft\nDescription: The value of TRTDOS is either a number, a semicolon-delimited string\n  containing numbers without spaces, or \"SEE PROTOCOL\" for more complex dosing regimens.\nOutcome:\n  Message: The value of TXVAL for TXPARMCD=TRTDOS is neither a number, a semicolon-delimited\n    string containing numbers without spaces, or \"SEE PROTOCOL\"\nRule Type: Record Data\nSensitivity: Record\nAuthorities:\n  - Organization: CDISC\n    Standards:\n      - Name: SENDIG\n        Version: '3.1'\n        References:\n          - Origin: SDTM and SENDIG Conformance Rules\n            Rule Identifier:\n              Id: '240'\n              Version: '1'\n            Version: '2.0'\n            Citations:\n              - Cited Guidance: Numeric representation of the planned test article\n                  dose level. For dose levels that vary over time within a set, a\n                  semicolon-delimited string without spaces can be used (e.g., 100;150;7).\n                  For more complex dosing regimens, sponsor should enter \"SEE PROTOCOL\".\n                Document: IG v3.1\n                Item: Specification\n                Section: 7.4.2\nScope:\n  Classes:\n    Include:\n      - TRIAL DESIGN\n  Domains:\n    Include:\n      - TX\n",
    "created": "2022-09-27T18:21:37.108Z",
    "creator": {
        "id": "dc8bf014-df32-4631-8684-9a09a16c5071"
    },
    "json": {
        "Check": {
            "all": [
                {
                    "name": "TXPARMCD",
                    "operator": "equal_to",
                    "value": "TRTDOS"
                },
                {
                    "name": "TXVAL",
                    "operator": "not_matches_regex",
                    "value": "[+-]?([0-9]*[.])?[0-9]+$"
                },
                {
                    "name": "TXVAL",
                    "operator": "not_matches_regex",
                    "value": "^(\\s*-?\\d+(\\.\\d+)?)(\\s*,\\s*-?\\d+(\\.\\d+)?)*$"
                },
                {
                    "name": "TXVAL",
                    "operator": "not_equal_to",
                    "value": "SEE PROTOCOL"
                }
            ]
        },
        "Core": {
            "Id": "CDISC.SENDIG.240",
            "Version": "1",
            "Status": "Draft"
        },
        "Description": "The value of TRTDOS is either a number, a semicolon-delimited string containing numbers without spaces, or \"SEE PROTOCOL\" for more complex dosing regimens.",
        "Outcome": {
            "Message": "The value of TXVAL for TXPARMCD=TRTDOS is neither a number, a semicolon-delimited string containing numbers without spaces, or \"SEE PROTOCOL\""
        },
        "Rule_Type": "Record Data",
        "Sensitivity": "Record",
        "Authorities": [
            {
                "Organization": "CDISC",
                "Standards": [
                    {
                        "Name": "SENDIG",
                        "Version": "3.1",
                        "References": [
                            {
                                "Origin": "SDTM and SENDIG Conformance Rules",
                                "Rule_Identifier": {
                                    "Id": "240",
                                    "Version": "1"
                                },
                                "Version": "2.0",
                                "Citations": [
                                    {
                                        "Cited_Guidance": "Numeric representation of the planned test article dose level. For dose levels that vary over time within a set, a semicolon-delimited string without spaces can be used (e.g., 100;150;7). For more complex dosing regimens, sponsor should enter \"SEE PROTOCOL\".",
                                        "Document": "IG v3.1",
                                        "Item": "Specification",
                                        "Section": "7.4.2"
                                    }
                                ]
                            }
                        ]
                    }
                ]
            }
        ],
        "Scope": {
            "Classes": {
                "Include": [
                    "TRIAL DESIGN"
                ]
            },
            "Domains": {
                "Include": [
                    "TX"
                ]
            }
        }
    },
    "id": "1e2a050a-e19c-4386-b3e1-97df469f3b0c"
}