{
    "changed": "2022-11-02T10:55:04.547Z",
    "content": "Check:\n  all:\n    - name: OMDTC\n      operator: non_empty\n    - name: OMSPEC\n      operator: non_empty\n    - name: OMDTC\n      operator: is_not_unique_set\n      value:\n        - USUBJID\n        - OMTESTCD\n        - OMSPEC\nCore:\n  Id: CDISC.SENDIG.188\n  Version: '1'\n  Status: Draft\nDescription: Raise an error when there is more than one record present for any particular\n  Organ Measurement test in the MO Domain, for a subject on a particular date.\n#The check for this rule was revised to NOT check the records where MIDTC is null\r\nOutcome:\n  Message: The Organ Measurement test is not unique for this subject and date/time.\n  Output Variables:\n    - USUBJID\n    - OMTESTCD\n    - OMSPEC\n    - OMDTC\nRule Type: Record Data\nSensitivity: Record\nAuthorities:\n  - Organization: CDISC\n    Standards:\n      - Name: SENDIG\n        Version: '3.1'\n        References:\n          - Origin: SDTM and SENDIG Conformance Rules\n            Rule Identifier:\n              Id: '180'\n              Version: '1'\n            Version: '2.0'\n            Citations:\n              - Cited Guidance: One record per finding per specimen per subject\n                Document: SENDIG v3.1\n                Section: 6.3.9.1\nScope:\n  Classes:\n    Include:\n      - FINDINGS\n  Domains:\n    Include:\n      - OM\n",
    "created": "2022-11-02T10:53:18.679Z",
    "creator": {
        "id": "dc8bf014-df32-4631-8684-9a09a16c5071"
    },
    "json": {
        "Check": {
            "all": [
                {
                    "name": "OMDTC",
                    "operator": "non_empty"
                },
                {
                    "name": "OMSPEC",
                    "operator": "non_empty"
                },
                {
                    "name": "OMDTC",
                    "operator": "is_not_unique_set",
                    "value": [
                        "USUBJID",
                        "OMTESTCD",
                        "OMSPEC"
                    ]
                }
            ]
        },
        "Core": {
            "Id": "CDISC.SENDIG.188",
            "Version": "1",
            "Status": "Draft"
        },
        "Description": "Raise an error when there is more than one record present for any particular Organ Measurement test in the MO Domain, for a subject on a particular date.",
        "Outcome": {
            "Message": "The Organ Measurement test is not unique for this subject and date/time.",
            "Output_Variables": [
                "USUBJID",
                "OMTESTCD",
                "OMSPEC",
                "OMDTC"
            ]
        },
        "Rule_Type": "Record Data",
        "Sensitivity": "Record",
        "Authorities": [
            {
                "Organization": "CDISC",
                "Standards": [
                    {
                        "Name": "SENDIG",
                        "Version": "3.1",
                        "References": [
                            {
                                "Origin": "SDTM and SENDIG Conformance Rules",
                                "Rule_Identifier": {
                                    "Id": "180",
                                    "Version": "1"
                                },
                                "Version": "2.0",
                                "Citations": [
                                    {
                                        "Cited_Guidance": "One record per finding per specimen per subject",
                                        "Document": "SENDIG v3.1",
                                        "Section": "6.3.9.1"
                                    }
                                ]
                            }
                        ]
                    }
                ]
            }
        ],
        "Scope": {
            "Classes": {
                "Include": [
                    "FINDINGS"
                ]
            },
            "Domains": {
                "Include": [
                    "OM"
                ]
            }
        }
    },
    "id": "f5a4b61a-7112-4544-97ce-171259b9363a"
}