{
    "changed": "2022-09-28T09:24:29.400Z",
    "content": "Check:\n  # TODO: this is not correct as the rule is about values in different rows\r\n  all:\n    - name: TSPARMCD\n      operator: equal_to\n      value: AGE\n    - name: TSPARMCD\n      operator: equal_to\n      value: AGETXT\n  # TODO: second part: there is no record with TSPARMCD=AGE nor is there a record with TSPARMCD=AGETXT\r\nCore:\n  Id: CDISC.SENDIG.250\n  Version: '1'\n  Status: Draft\nDescription: Either the AGE or the AGETXT variable should be populated.\nOutcome:\n  Message: There is a record with TSPARMCD=AGE and there is a record with TSPARMCD=AGETXT\nRule Type: Record Data\nSensitivity: Dataset\nAuthorities:\n  - Organization: CDISC\n    Standards:\n      - Name: SENDIG\n        Version: '3.1'\n        References:\n          - Origin: SDTM and SENDIG Conformance Rules\n            Rule Identifier:\n              Id: '250'\n              Version: '1'\n            Version: '2.0'\n            Citations:\n              - Cited Guidance: Either the AGE or the AGETXT variable should be populated.\n                Document: IG v3.1\n                Item: Specification\n                Section: 7.6.3\nScope:\n  Classes:\n    Include:\n      - TRIAL DESIGN\n  Domains:\n    Include:\n      - TS\n",
    "created": "2022-09-28T09:10:45.440Z",
    "creator": {
        "id": "dc8bf014-df32-4631-8684-9a09a16c5071"
    },
    "json": {
        "Check": {
            "all": [
                {
                    "name": "TSPARMCD",
                    "operator": "equal_to",
                    "value": "AGE"
                },
                {
                    "name": "TSPARMCD",
                    "operator": "equal_to",
                    "value": "AGETXT"
                }
            ]
        },
        "Core": {
            "Id": "CDISC.SENDIG.250",
            "Version": "1",
            "Status": "Draft"
        },
        "Description": "Either the AGE or the AGETXT variable should be populated.",
        "Outcome": {
            "Message": "There is a record with TSPARMCD=AGE and there is a record with TSPARMCD=AGETXT"
        },
        "Rule_Type": "Record Data",
        "Sensitivity": "Dataset",
        "Authorities": [
            {
                "Organization": "CDISC",
                "Standards": [
                    {
                        "Name": "SENDIG",
                        "Version": "3.1",
                        "References": [
                            {
                                "Origin": "SDTM and SENDIG Conformance Rules",
                                "Rule_Identifier": {
                                    "Id": "250",
                                    "Version": "1"
                                },
                                "Version": "2.0",
                                "Citations": [
                                    {
                                        "Cited_Guidance": "Either the AGE or the AGETXT variable should be populated.",
                                        "Document": "IG v3.1",
                                        "Item": "Specification",
                                        "Section": "7.6.3"
                                    }
                                ]
                            }
                        ]
                    }
                ]
            }
        ],
        "Scope": {
            "Classes": {
                "Include": [
                    "TRIAL DESIGN"
                ]
            },
            "Domains": {
                "Include": [
                    "TS"
                ]
            }
        }
    },
    "id": "a883d8d0-001c-480f-b26e-25372ebaa69d"
}