{
    "changed": "2023-02-02T14:06:48.060Z",
    "content": "Check:\n  all:\n    - name: variable_name\n      operator: is_not_contained_by\n      value: $model_variables\nCore:\n  Id: CDISC.SENDIG.266\n  Version: '1'\n  Status: Draft\nDescription: Trigger when variable cannot be found in the SDTM model (v.1.7 for SENDIG-3.1)\nRule Type: Variable Metadata Check\nOperations:\n  - id: $model_variables\n    operator: get_column_order_from_library\n    name: MODELVARIABLES\nOutcome:\n  Message: Variable is not allowed in SDTM/SEND\nSensitivity: Dataset\nAuthorities:\n  - Organization: CDISC\n    Standards:\n      - Name: SENDIG\n        Version: '3.1'\n        References:\n          - Origin: SDTM and SENDIG Conformance Rules\n            Rule Identifier:\n              Id: '266'\n              Version: '1'\n            Version: '2.0'\n            Citations:\n              - Cited Guidance: TODO\n                Document: IG v3.1\n                Section: 2.1 2.3\nScope:\n  Classes:\n    Include:\n      - ALL\n  Domains:\n    Include:\n      - ALL\n",
    "created": "2023-01-24T19:34:02.291Z",
    "creator": {
        "id": "dc8bf014-df32-4631-8684-9a09a16c5071"
    },
    "json": {
        "Check": {
            "all": [
                {
                    "name": "variable_name",
                    "operator": "is_not_contained_by",
                    "value": "$model_variables"
                }
            ]
        },
        "Core": {
            "Id": "CDISC.SENDIG.266",
            "Version": "1",
            "Status": "Draft"
        },
        "Description": "Trigger when variable cannot be found in the SDTM model (v.1.7 for SENDIG-3.1)",
        "Rule_Type": "Variable Metadata Check",
        "Operations": [
            {
                "id": "$model_variables",
                "operator": "get_column_order_from_library",
                "name": "MODELVARIABLES"
            }
        ],
        "Outcome": {
            "Message": "Variable is not allowed in SDTM/SEND"
        },
        "Sensitivity": "Dataset",
        "Authorities": [
            {
                "Organization": "CDISC",
                "Standards": [
                    {
                        "Name": "SENDIG",
                        "Version": "3.1",
                        "References": [
                            {
                                "Origin": "SDTM and SENDIG Conformance Rules",
                                "Rule_Identifier": {
                                    "Id": "266",
                                    "Version": "1"
                                },
                                "Version": "2.0",
                                "Citations": [
                                    {
                                        "Cited_Guidance": "TODO",
                                        "Document": "IG v3.1",
                                        "Section": "2.1 2.3"
                                    }
                                ]
                            }
                        ]
                    }
                ]
            }
        ],
        "Scope": {
            "Classes": {
                "Include": [
                    "ALL"
                ]
            },
            "Domains": {
                "Include": [
                    "ALL"
                ]
            }
        }
    },
    "id": "dd773583-33eb-45e9-a3bb-760bc429e90a"
}