{
    "changed": "2022-09-12T13:51:04.923Z",
    "content": "Check:\n  any:\n    - name: --SCAT\n      operator: non_empty\n    - all:\n        - name: --DECOD\n          operator: non_empty\n        - name: --SCAT\n          operator: equal_to\n          value: --DECOD\n    - all:\n        - name: --BODSYS\n          operator: non_empty\n        - name: --SCAT\n          operator: equal_to\n          value: --BODSYS\nCore:\n  Id: CDISC.SENDIG.45\n  Version: '1'\n  Status: Draft\nDescription: Trigger error when --SCAT is not null and --SCAT is equal to --DECOD\n  or --SCAT is equal to --BODSYS\nOutcome:\n  Message: --SCAT is equal to --DECOD\n  Output Variables:\n    - --CAT\n    - --SCAT\n    - --DECOD\n    - --BODSYS\nRule Type: Record Data\nSensitivity: Record\nAuthorities:\n  - Organization: CDISC\n    Standards:\n      - Name: SENDIG\n        Version: '3.1'\n        References:\n          - Origin: SDTM and SENDIG Conformance Rules\n            Rule Identifier:\n              Id: '45'\n              Version: '1'\n            Version: '2.0'\n            Citations:\n              - Cited Guidance: Values for --CAT and --SCAT should not be redundant\n                  with the domain or dictionary classification provided by --DECOD\n                  and --BODSYS.\n                Document: IG v.3.1\n                Section: 4.2.6\nScope:\n  Classes:\n    Include:\n      - ALL\n  Domains:\n    Include:\n      - ALL\n",
    "created": "2022-09-11T13:56:04.895Z",
    "creator": {
        "id": "dc8bf014-df32-4631-8684-9a09a16c5071"
    },
    "json": {
        "Check": {
            "any": [
                {
                    "name": "--SCAT",
                    "operator": "non_empty"
                },
                {
                    "all": [
                        {
                            "name": "--DECOD",
                            "operator": "non_empty"
                        },
                        {
                            "name": "--SCAT",
                            "operator": "equal_to",
                            "value": "--DECOD"
                        }
                    ]
                },
                {
                    "all": [
                        {
                            "name": "--BODSYS",
                            "operator": "non_empty"
                        },
                        {
                            "name": "--SCAT",
                            "operator": "equal_to",
                            "value": "--BODSYS"
                        }
                    ]
                }
            ]
        },
        "Core": {
            "Id": "CDISC.SENDIG.45",
            "Version": "1",
            "Status": "Draft"
        },
        "Description": "Trigger error when --SCAT is not null and --SCAT is equal to --DECOD or --SCAT is equal to --BODSYS",
        "Outcome": {
            "Message": "--SCAT is equal to --DECOD",
            "Output_Variables": [
                "--CAT",
                "--SCAT",
                "--DECOD",
                "--BODSYS"
            ]
        },
        "Rule_Type": "Record Data",
        "Sensitivity": "Record",
        "Authorities": [
            {
                "Organization": "CDISC",
                "Standards": [
                    {
                        "Name": "SENDIG",
                        "Version": "3.1",
                        "References": [
                            {
                                "Origin": "SDTM and SENDIG Conformance Rules",
                                "Rule_Identifier": {
                                    "Id": "45",
                                    "Version": "1"
                                },
                                "Version": "2.0",
                                "Citations": [
                                    {
                                        "Cited_Guidance": "Values for --CAT and --SCAT should not be redundant with the domain or dictionary classification provided by --DECOD and --BODSYS.",
                                        "Document": "IG v.3.1",
                                        "Section": "4.2.6"
                                    }
                                ]
                            }
                        ]
                    }
                ]
            }
        ],
        "Scope": {
            "Classes": {
                "Include": [
                    "ALL"
                ]
            },
            "Domains": {
                "Include": [
                    "ALL"
                ]
            }
        }
    },
    "id": "b463fc32-bb81-4f6c-b69a-c24358ee1f36"
}