{
    "changed": "2022-11-07T15:36:17.659Z",
    "content": "Check:\n  all:\n    - name: VSTESTCD\n      operator: is_not_unique_set\n      value:\n        - USUBJID\n        - VSDTC\nCore:\n  Id: CDISC.SENDIG.206\n  Version: '1'\n  Status: Draft\nDescription: Raise an error when there is more than one record present for any particular\n  Vital Signs test for a subject and measurement date/time.\nOutcome:\n  Message: The Vital Signs test is not unique for this subject and measurement datetime.\n  Output Variables:\n    - USUBJID\n    - VSTESTCD\n    - VSDTC\nRule Type: Record Data\nSensitivity: Record\nAuthorities:\n  - Organization: CDISC\n    Standards:\n      - Name: SENDIG\n        Version: '3.1'\n        References:\n          - Origin: SDTM and SENDIG Conformance Rules\n            Rule Identifier:\n              Id: '206'\n              Version: '1'\n            Version: '2.0'\n            Citations:\n              - Cited Guidance: One record per measurement per observation time per\n                  subject\n                Document: SENDIG v3.1\n                Section: 6.3.15\nScope:\n  Classes:\n    Include:\n      - FINDINGS\n  Domains:\n    Include:\n      - VS\n",
    "created": "2022-11-07T15:36:17.659Z",
    "creator": {
        "id": "dc8bf014-df32-4631-8684-9a09a16c5071"
    },
    "json": {
        "Check": {
            "all": [
                {
                    "name": "VSTESTCD",
                    "operator": "is_not_unique_set",
                    "value": [
                        "USUBJID",
                        "VSDTC"
                    ]
                }
            ]
        },
        "Core": {
            "Id": "CDISC.SENDIG.206",
            "Version": "1",
            "Status": "Draft"
        },
        "Description": "Raise an error when there is more than one record present for any particular Vital Signs test for a subject and measurement date/time.",
        "Outcome": {
            "Message": "The Vital Signs test is not unique for this subject and measurement datetime.",
            "Output_Variables": [
                "USUBJID",
                "VSTESTCD",
                "VSDTC"
            ]
        },
        "Rule_Type": "Record Data",
        "Sensitivity": "Record",
        "Authorities": [
            {
                "Organization": "CDISC",
                "Standards": [
                    {
                        "Name": "SENDIG",
                        "Version": "3.1",
                        "References": [
                            {
                                "Origin": "SDTM and SENDIG Conformance Rules",
                                "Rule_Identifier": {
                                    "Id": "206",
                                    "Version": "1"
                                },
                                "Version": "2.0",
                                "Citations": [
                                    {
                                        "Cited_Guidance": "One record per measurement per observation time per subject",
                                        "Document": "SENDIG v3.1",
                                        "Section": "6.3.15"
                                    }
                                ]
                            }
                        ]
                    }
                ]
            }
        ],
        "Scope": {
            "Classes": {
                "Include": [
                    "FINDINGS"
                ]
            },
            "Domains": {
                "Include": [
                    "VS"
                ]
            }
        }
    },
    "id": "70d8e6c7-0707-4db9-a907-2d2e35095eb3"
}