{
    "changed": "2022-09-30T11:46:54.914Z",
    "content": "Check:\n  all:\n    # TODO: this is NOT a correct implementation yet!\r\n    - name: SPECIES\n      operator: is_not_unique_set\n      value:\n        - DOMAIN\n        - SETCD\nCore:\n  Id: CDISC.SENDIG.309\n  Version: '1'\n  Status: Draft\nDescription: DM records with different values for SPECIES may not have the same SETCD\n  value.\nOutcome:\n  Message: The same SETCD is assigned to different SPECIES\n  Output Variables:\n    - SPECIES\n    - SETCD\nRule Type: Record Data\nSensitivity: Record\nAuthorities:\n  - Organization: CDISC\n    Standards:\n      - Name: SENDIG\n        Version: '3.1'\n        References:\n          - Origin: SDTM and SENDIG Conformance Rules\n            Rule Identifier:\n              Id: '309'\n              Version: '1'\n            Version: '2.0'\n            Citations:\n              - Cited Guidance: Trial Sets (TX) can have multiple species and/or strains\n                  if they are different by set. DM records with different values for\n                  SPECIES cannot have the same SETCD value.\n                Document: IG v3.1\n                Section: 6.3.1\nScope:\n  Classes:\n    Include:\n      - SPECIAL-PURPOSE\n  Domains:\n    Include:\n      - DM\n",
    "created": "2022-09-30T11:29:15.082Z",
    "creator": {
        "id": "dc8bf014-df32-4631-8684-9a09a16c5071"
    },
    "json": {
        "Check": {
            "all": [
                {
                    "name": "SPECIES",
                    "operator": "is_not_unique_set",
                    "value": [
                        "DOMAIN",
                        "SETCD"
                    ]
                }
            ]
        },
        "Core": {
            "Id": "CDISC.SENDIG.309",
            "Version": "1",
            "Status": "Draft"
        },
        "Description": "DM records with different values for SPECIES may not have the same SETCD value.",
        "Outcome": {
            "Message": "The same SETCD is assigned to different SPECIES",
            "Output_Variables": [
                "SPECIES",
                "SETCD"
            ]
        },
        "Rule_Type": "Record Data",
        "Sensitivity": "Record",
        "Authorities": [
            {
                "Organization": "CDISC",
                "Standards": [
                    {
                        "Name": "SENDIG",
                        "Version": "3.1",
                        "References": [
                            {
                                "Origin": "SDTM and SENDIG Conformance Rules",
                                "Rule_Identifier": {
                                    "Id": "309",
                                    "Version": "1"
                                },
                                "Version": "2.0",
                                "Citations": [
                                    {
                                        "Cited_Guidance": "Trial Sets (TX) can have multiple species and/or strains if they are different by set. DM records with different values for SPECIES cannot have the same SETCD value.",
                                        "Document": "IG v3.1",
                                        "Section": "6.3.1"
                                    }
                                ]
                            }
                        ]
                    }
                ]
            }
        ],
        "Scope": {
            "Classes": {
                "Include": [
                    "SPECIAL-PURPOSE"
                ]
            },
            "Domains": {
                "Include": [
                    "DM"
                ]
            }
        }
    },
    "id": "fa4b93d7-4699-4def-8549-bb2722c5e60c"
}