{
    "changed": "2023-03-02T15:34:02.102Z",
    "content": "Check:\n  #1. check variable type is numeric 2. has suffix DT  3. has date format (look up list?)\n  all:\n    - name: variable_type   #1\n      operator: is_numeric    #type should be avialble from metadata variable_type\n    - name: variable_name   #2\n      operator: ends_with   \n      value: DT\n    - name: variable_name   #3\n      operator: does_not_use_valid_format_terms\n       #need to be able to extract metadata from xpt and read format from unit test data: add row call format under each column \n\nCore:\n  Id: CDISC.ADAMIG.AD0041\n  Version: '1'\n  Status: Draft\nDescription: Raise an error when a variable ends with DT and does not have a date\n  format                                                                                 #list of all valid date format available?\nOutcome:\n  Message: Value of --DT  do not have a date format  #human readable as per guidance then could  define a list of acceptable formats?\n  #Output Variables:\n   # - --DT \n   #wildcard bing used\nRule Type: Record Data\nSensitivity: Record\nAuthorities:\n  - Organization: CDISC\n    Standards:\n      - Name: ADAMIG\n        Version: '1.3'\n        References:\n          - Origin: ADaM Conformance Rules\n            Rule Identifier:\n              Id: AD0041\n            Version: '4.0'\n            Citations:\n              - Document: IG v1.3\n                Section: 3.1.2\n                Item: '1'\n                Cited Guidance: >-\n                  Numeric date, time, and datetime variables should be formatted,\n                  so as to be human-readable with no loss of precision. \n              - Document: IG v1.3\n                Section: 3.1.2\n                Item: '2'\n                Cited Guidance: >-\n                  Variables whose names end in DT are numeric dates.   \nScope:\n  Classes:\n    Include:\n      - ALL\n  Domains:\n    Include:\n      - ADLB\n",
    "created": "2022-12-14T14:03:05.597Z",
    "creator": {
        "id": "57474fac-237e-4693-bb37-7826b02737da"
    },
    "json": {
        "Check": {
            "all": [
                {
                    "name": "variable_type",
                    "operator": "is_numeric"
                },
                {
                    "name": "variable_name",
                    "operator": "ends_with",
                    "value": "DT"
                },
                {
                    "name": "variable_name",
                    "operator": "does_not_use_valid_format_terms"
                }
            ]
        },
        "Core": {
            "Id": "CDISC.ADAMIG.AD0041",
            "Version": "1",
            "Status": "Draft"
        },
        "Description": "Raise an error when a variable ends with DT and does not have a date format",
        "Outcome": {
            "Message": "Value of --DT  do not have a date format"
        },
        "Sensitivity": "Record",
        "Authorities": [
            {
                "Organization": "CDISC",
                "Standards": [
                    {
                        "Name": "ADAMIG",
                        "Version": "1.3",
                        "References": [
                            {
                                "Origin": "ADaM Conformance Rules",
                                "Version": "4.0",
                                "Citations": [
                                    {
                                        "Document": "IG v1.3",
                                        "Section": "3.1.2",
                                        "Item": "1",
                                        "Cited_Guidance": "Numeric date, time, and datetime variables should be formatted, so as to be human-readable with no loss of precision. "
                                    },
                                    {
                                        "Document": "IG v1.3",
                                        "Section": "3.1.2",
                                        "Item": "2",
                                        "Cited_Guidance": "Variables whose names end in DT are numeric dates.   "
                                    }
                                ],
                                "Rule_Identifier": {
                                    "Id": "AD0041"
                                }
                            }
                        ]
                    }
                ]
            }
        ],
        "Scope": {
            "Classes": {
                "Include": [
                    "ALL"
                ]
            },
            "Domains": {
                "Include": [
                    "ADLB"
                ]
            }
        },
        "Rule_Type": "Record Data"
    },
    "id": "176a575c-688f-4232-8ac9-3c7a83049a72"
}