{
    "id": "6c39f754-d359-424f-a378-b5a6d02f751e",
    "changed": "2022-03-08T17:16:32Z",
    "content": "Check:\n  any:\n    - name: --DOSE\n      operator: non_empty\n    - name: --DOSTXT\n      operator: non_empty\nCore:\n  Id: CDISC.SDTMIG.CG0114.gerry3\n  Version: '1'\n  Status: Draft\nDescription: Engine Test\nOutcome:\n  Message: Engine Test\n  Output Variables:\n    - --DOSE\n    - --DOSTXT\nRule Type: Record Data\nSensitivity: Record\nAuthorities:\n  - Organization: CDISC\n    Standards:\n      - Name: SDTMIG\n        Version: '3.4'\n        References:\n          - Origin: SDTM and SDTMIG Conformance Rules\n            Rule Identifier:\n              Id: CG0114\n              Version: '1'\n            Version: '2.0'\n            Citations:\n              - Cited Guidance: Units for --DOSE, --DOSTOT, or --DOSTXT\n                Document: Model v2.0\n                Item: --DOSU\n                Section: Interventions\nScope:\n  Classes:\n    Include:\n      - INTERVENTIONS\n  Domains:\n    Include:\n      - ALL\n",
    "created": "2022-03-03T18:26:55Z",
    "creator": {
        "id": "e4113eae-4854-4831-a2f1-a0f1639da65a"
    },
    "json": {
        "Check": {
            "any": [
                {
                    "name": "--DOSE",
                    "operator": "non_empty"
                },
                {
                    "name": "--DOSTXT",
                    "operator": "non_empty"
                }
            ]
        },
        "Core": {
            "Id": "CDISC.SDTMIG.CG0114.gerry3",
            "Version": "1",
            "Status": "Draft"
        },
        "Description": "Engine Test",
        "Outcome": {
            "Message": "Engine Test",
            "Output_Variables": [
                "--DOSE",
                "--DOSTXT"
            ]
        },
        "Rule_Type": "Record Data",
        "Sensitivity": "Record",
        "Authorities": [
            {
                "Organization": "CDISC",
                "Standards": [
                    {
                        "Name": "SDTMIG",
                        "Version": "3.4",
                        "References": [
                            {
                                "Origin": "SDTM and SDTMIG Conformance Rules",
                                "Rule_Identifier": {
                                    "Id": "CG0114",
                                    "Version": "1"
                                },
                                "Version": "2.0",
                                "Citations": [
                                    {
                                        "Cited_Guidance": "Units for --DOSE, --DOSTOT, or --DOSTXT",
                                        "Document": "Model v2.0",
                                        "Item": "--DOSU",
                                        "Section": "Interventions"
                                    }
                                ]
                            }
                        ]
                    }
                ]
            }
        ],
        "Scope": {
            "Classes": {
                "Include": [
                    "INTERVENTIONS"
                ]
            },
            "Domains": {
                "Include": [
                    "ALL"
                ]
            }
        }
    }
}