{
    "changed": "2022-10-12T09:37:42.166Z",
    "content": "Check:\n  any:\n    - name: RFSTDTC\n      operator: invalid_date\n    - name: RFENDTC\n      operator: invalid_date\n    - name: BRTHDTC\n      operator: invalid_date\n    - name: --STDTC\n      operator: invalid_date\n    - name: --ENDTC\n      operator: invalid_date\n    - name: --DTC\n      operator: invalid_date\n    - name: --RFTDTC\n      operator: invalid_date\n\nCore:\n  Id: CDISC.SENDIG.67\n  Version: '1'\n  Status: Draft\nDescription: Values of variables RFSTDTC,  RFENDTC, BRTHDTC, --STDTC, --ENDTC, --DTC,\n  --RFTDTC must be correct ISO-8601 dates / datetimes\nOutcome:\n  Message: Variable value is not in correct ISO 8601 date or datetime format\n  # Output Variables:\r\n  #  - --DY\r\n  #  - --STDY\r\n  #  - --ENDY\r\nRule Type: Record Data\nSensitivity: Record\nAuthorities:\n  - Organization: CDISC\n    Standards:\n      - Name: SENDIG\n        Version: '3.1'\n        References:\n          - Origin: SDTM and SENDIG Conformance Rules\n            Rule Identifier:\n              Id: '67'\n              Version: '1'\n            Version: '2.0'\n            Citations:\n              - Cited Guidance: The SENDIG requires dates and times of day to be stored\n                  according to the international standard ISO 8601 (http://www.iso.org).\n                Document: IG v3.1\n                Section: '4.4'\nScope:\n  Classes:\n    Include:\n      - ALL\n  Domains:\n    Include:\n      - ALL\n",
    "created": "2022-10-12T09:37:42.166Z",
    "creator": {
        "id": "dc8bf014-df32-4631-8684-9a09a16c5071"
    },
    "json": {
        "Check": {
            "any": [
                {
                    "name": "RFSTDTC",
                    "operator": "invalid_date"
                },
                {
                    "name": "RFENDTC",
                    "operator": "invalid_date"
                },
                {
                    "name": "BRTHDTC",
                    "operator": "invalid_date"
                },
                {
                    "name": "--STDTC",
                    "operator": "invalid_date"
                },
                {
                    "name": "--ENDTC",
                    "operator": "invalid_date"
                },
                {
                    "name": "--DTC",
                    "operator": "invalid_date"
                },
                {
                    "name": "--RFTDTC",
                    "operator": "invalid_date"
                }
            ]
        },
        "Core": {
            "Id": "CDISC.SENDIG.67",
            "Version": "1",
            "Status": "Draft"
        },
        "Description": "Values of variables RFSTDTC,  RFENDTC, BRTHDTC, --STDTC, --ENDTC, --DTC, --RFTDTC must be correct ISO-8601 dates / datetimes",
        "Outcome": {
            "Message": "Variable value is not in correct ISO 8601 date or datetime format"
        },
        "Rule_Type": "Record Data",
        "Sensitivity": "Record",
        "Authorities": [
            {
                "Organization": "CDISC",
                "Standards": [
                    {
                        "Name": "SENDIG",
                        "Version": "3.1",
                        "References": [
                            {
                                "Origin": "SDTM and SENDIG Conformance Rules",
                                "Rule_Identifier": {
                                    "Id": "67",
                                    "Version": "1"
                                },
                                "Version": "2.0",
                                "Citations": [
                                    {
                                        "Cited_Guidance": "The SENDIG requires dates and times of day to be stored according to the international standard ISO 8601 (http://www.iso.org).",
                                        "Document": "IG v3.1",
                                        "Section": "4.4"
                                    }
                                ]
                            }
                        ]
                    }
                ]
            }
        ],
        "Scope": {
            "Classes": {
                "Include": [
                    "ALL"
                ]
            },
            "Domains": {
                "Include": [
                    "ALL"
                ]
            }
        }
    },
    "id": "816605c6-5dd0-44f8-8067-95e837fc8acc"
}