{
    "changed": "2022-11-07T16:03:17.397Z",
    "content": "Check:\n  all:\n    - name: EGTESTCD\n      operator: is_not_unique_set\n      value:\n        - USUBJID\n        - EGDTC\nCore:\n  Id: CDISC.SENDIG.208\n  Version: '1'\n  Status: Draft\nDescription: Raise an error when there is more than one record present for any particular\n  ECG test for a subject and measurement date/time.\nOutcome:\n  Message: The ECG test is not unique for this subject and measurement datetime.\n  Output Variables:\n    - USUBJID\n    - EGTESTCD\n    - EGDTC\nRule Type: Record Data\nSensitivity: Record\nAuthorities:\n  - Organization: CDISC\n    Standards:\n      - Name: SENDIG\n        Version: '3.1'\n        References:\n          - Origin: SDTM and SENDIG Conformance Rules\n            Rule Identifier:\n              Id: '208'\n              Version: '1'\n            Version: '2.0'\n            Citations:\n              - Cited Guidance: One record per test per observation time per subject\n                Document: SENDIG v3.1\n                Section: 6.3.16\nScope:\n  Classes:\n    Include:\n      - FINDINGS\n  Domains:\n    Include:\n      - EG\n",
    "created": "2022-11-07T16:03:17.397Z",
    "creator": {
        "id": "dc8bf014-df32-4631-8684-9a09a16c5071"
    },
    "json": {
        "Check": {
            "all": [
                {
                    "name": "EGTESTCD",
                    "operator": "is_not_unique_set",
                    "value": [
                        "USUBJID",
                        "EGDTC"
                    ]
                }
            ]
        },
        "Core": {
            "Id": "CDISC.SENDIG.208",
            "Version": "1",
            "Status": "Draft"
        },
        "Description": "Raise an error when there is more than one record present for any particular ECG test for a subject and measurement date/time.",
        "Outcome": {
            "Message": "The ECG test is not unique for this subject and measurement datetime.",
            "Output_Variables": [
                "USUBJID",
                "EGTESTCD",
                "EGDTC"
            ]
        },
        "Rule_Type": "Record Data",
        "Sensitivity": "Record",
        "Authorities": [
            {
                "Organization": "CDISC",
                "Standards": [
                    {
                        "Name": "SENDIG",
                        "Version": "3.1",
                        "References": [
                            {
                                "Origin": "SDTM and SENDIG Conformance Rules",
                                "Rule_Identifier": {
                                    "Id": "208",
                                    "Version": "1"
                                },
                                "Version": "2.0",
                                "Citations": [
                                    {
                                        "Cited_Guidance": "One record per test per observation time per subject",
                                        "Document": "SENDIG v3.1",
                                        "Section": "6.3.16"
                                    }
                                ]
                            }
                        ]
                    }
                ]
            }
        ],
        "Scope": {
            "Classes": {
                "Include": [
                    "FINDINGS"
                ]
            },
            "Domains": {
                "Include": [
                    "EG"
                ]
            }
        }
    },
    "id": "7d137d34-0675-4ca2-af4d-f2055bd9e94f"
}