{
    "changed": "2023-01-24T14:14:37.254Z",
    "content": "Check:\n  all:\n    - name: --ORRES\n      operator: non_empty\n    - name: --STRESC\n      operator: empty\nCore:\n  Id: CDISC.SENDIG.87\n  Version: '1'\n  Status: Draft\nDescription: When --ORRES is populated, --STRESC must also be populated.\nOutcome:\n  Message: --STRESC must be be populated as --ORRES is populated.\n  Output Variables:\n    - --ORRES\n    - --STRESC\nRule Type: Record Data\nSensitivity: Record\nAuthorities:\n  - Organization: CDISC\n    Standards:\n      - Name: SENDIG\n        Version: '3.1'\n        References:\n          - Origin: SDTM and SENDIG Conformance Rules\n            Rule Identifier:\n              Id: '87'\n              Version: '1'\n            Version: '2.0'\n            Citations:\n              - Cited Guidance: When --ORRES is populated, --STRESC must also be populated,\n                  regardless of whether the data values are character or numeric\n                Document: IG v3.1\n                Section: 4.5.1.1\nScope:\n  Classes:\n    Include:\n      - FINDINGS\n  Domains:\n    Include:\n      - ALL\n",
    "created": "2022-09-15T06:59:09.210Z",
    "creator": {
        "id": "dc8bf014-df32-4631-8684-9a09a16c5071"
    },
    "json": {
        "Check": {
            "all": [
                {
                    "name": "--ORRES",
                    "operator": "non_empty"
                },
                {
                    "name": "--STRESC",
                    "operator": "empty"
                }
            ]
        },
        "Core": {
            "Id": "CDISC.SENDIG.87",
            "Version": "1",
            "Status": "Draft"
        },
        "Description": "When --ORRES is populated, --STRESC must also be populated.",
        "Outcome": {
            "Message": "--STRESC must be be populated as --ORRES is populated.",
            "Output_Variables": [
                "--ORRES",
                "--STRESC"
            ]
        },
        "Rule_Type": "Record Data",
        "Sensitivity": "Record",
        "Authorities": [
            {
                "Organization": "CDISC",
                "Standards": [
                    {
                        "Name": "SENDIG",
                        "Version": "3.1",
                        "References": [
                            {
                                "Origin": "SDTM and SENDIG Conformance Rules",
                                "Rule_Identifier": {
                                    "Id": "87",
                                    "Version": "1"
                                },
                                "Version": "2.0",
                                "Citations": [
                                    {
                                        "Cited_Guidance": "When --ORRES is populated, --STRESC must also be populated, regardless of whether the data values are character or numeric",
                                        "Document": "IG v3.1",
                                        "Section": "4.5.1.1"
                                    }
                                ]
                            }
                        ]
                    }
                ]
            }
        ],
        "Scope": {
            "Classes": {
                "Include": [
                    "FINDINGS"
                ]
            },
            "Domains": {
                "Include": [
                    "ALL"
                ]
            }
        }
    },
    "id": "94d4f782-e8c9-4cf8-b719-9d1990ee0763"
}