{
    "changed": "2022-09-29T11:23:41.631Z",
    "content": "Check:\n  all:\n    - name: --TPT\n      operator: non_empty\n    - name: --TPTNUM\n      operator: empty\nCore:\n  Id: CDISC.SENDIG.293\n  Version: '1'\n  Status: Draft\nDescription: Raise an error when --TPT is populated but --TPTNUM is not populated.\nOutcome:\n  Message: --TPT is populated but --TPTNUM is not populated\nRule Type: Record Data\nSensitivity: Record\nAuthorities:\n  - Organization: CDISC\n    Standards:\n      - Name: SENDIG\n        Version: '3.1'\n        References:\n          - Origin: SDTM and SENDIG Conformance Rules\n            Rule Identifier:\n              Id: '293'\n              Version: '1'\n            Version: '2.0'\n            Citations:\n              - Cited Guidance: For each unique planned time point (--TPT), there\n                  must be a one-to-one relationship between the values of --TPT and\n                  --TPTNUM. Uniqueness for these time points is determined by a combination\n                  of the domain, study day, and, if present, category and/or subcategory\n                  (--CAT/--SCAT). Other variables, such as --TESTCD and --METHOD,\n                  may also be needed in some cases to define uniqueness. When this\n                  occurs, clarification should be provided as a comment to --TPTNUM\n                  in the define file.\n                Document: IG v3.1\n                Section: 4.4.7.2.2\nScope:\n  Classes:\n    Include:\n      - FINDINGS\n  Domains:\n    Include:\n      - ALL\n",
    "created": "2022-09-29T11:23:41.631Z",
    "creator": {
        "id": "dc8bf014-df32-4631-8684-9a09a16c5071"
    },
    "json": {
        "Check": {
            "all": [
                {
                    "name": "--TPT",
                    "operator": "non_empty"
                },
                {
                    "name": "--TPTNUM",
                    "operator": "empty"
                }
            ]
        },
        "Core": {
            "Id": "CDISC.SENDIG.293",
            "Version": "1",
            "Status": "Draft"
        },
        "Description": "Raise an error when --TPT is populated but --TPTNUM is not populated.",
        "Outcome": {
            "Message": "--TPT is populated but --TPTNUM is not populated"
        },
        "Rule_Type": "Record Data",
        "Sensitivity": "Record",
        "Authorities": [
            {
                "Organization": "CDISC",
                "Standards": [
                    {
                        "Name": "SENDIG",
                        "Version": "3.1",
                        "References": [
                            {
                                "Origin": "SDTM and SENDIG Conformance Rules",
                                "Rule_Identifier": {
                                    "Id": "293",
                                    "Version": "1"
                                },
                                "Version": "2.0",
                                "Citations": [
                                    {
                                        "Cited_Guidance": "For each unique planned time point (--TPT), there must be a one-to-one relationship between the values of --TPT and --TPTNUM. Uniqueness for these time points is determined by a combination of the domain, study day, and, if present, category and/or subcategory (--CAT/--SCAT). Other variables, such as --TESTCD and --METHOD, may also be needed in some cases to define uniqueness. When this occurs, clarification should be provided as a comment to --TPTNUM in the define file.",
                                        "Document": "IG v3.1",
                                        "Section": "4.4.7.2.2"
                                    }
                                ]
                            }
                        ]
                    }
                ]
            }
        ],
        "Scope": {
            "Classes": {
                "Include": [
                    "FINDINGS"
                ]
            },
            "Domains": {
                "Include": [
                    "ALL"
                ]
            }
        }
    },
    "id": "96898736-7cad-4caf-a1d0-65b0efcf9e5c"
}