{
    "changed": "2022-11-02T08:24:35.647Z",
    "content": "Check:\n  any:\n    - all:\n        - name: CLDTC\n          operator: non_empty\n        - name: USUBJID\n          operator: non_empty\n        - name: CLORRES\n          operator: is_not_unique_set\n          value:\n            - USUBJID\n            - CLDTC\n    - all:\n        - name: CLDTC\n          operator: non_empty\n        - name: POOLID\n          operator: non_empty\n        - name: CLORRES\n          operator: is_not_unique_set\n          value:\n            - POOLID\n            - CLDTC\nCore:\n  Id: CDISC.SENDIG.156\n  Version: '1'\n  Status: Draft\nDescription: Raise an error when there is more than one record present for any particular\n  Result or Findings as Collected, in the CL Domain, for a subject or pool on a particular\n  date.\n#The check for this rule was revised to NOT check the records where CLDTC is null\r\nOutcome:\n  Message: The Clinical Observation test result is not unique for this subject and\n    date/time.\n  Output Variables:\n    - USUBJID\n    - POOLID\n    - CLTESTCD\n    - CLORRES\n    - CLDTC\nRule Type: Record Data\nSensitivity: Record\nAuthorities:\n  - Organization: CDISC\n    Standards:\n      - Name: SENDIG\n        Version: '3.1'\n        References:\n          - Origin: SDTM and SENDIG Conformance Rules\n            Rule Identifier:\n              Id: '156'\n              Version: '1'\n            Version: '2.0'\n            Citations:\n              - Cited Guidance: One record per finding per observation time per subject\n                  or pool\n                Document: SENDIG v3.1\n                Section: 6.3.2.1\nScope:\n  Classes:\n    Include:\n      - FINDINGS\n  Domains:\n    Include:\n      - CL\n",
    "created": "2022-11-02T08:12:28.774Z",
    "creator": {
        "id": "dc8bf014-df32-4631-8684-9a09a16c5071"
    },
    "json": {
        "Check": {
            "any": [
                {
                    "all": [
                        {
                            "name": "CLDTC",
                            "operator": "non_empty"
                        },
                        {
                            "name": "USUBJID",
                            "operator": "non_empty"
                        },
                        {
                            "name": "CLORRES",
                            "operator": "is_not_unique_set",
                            "value": [
                                "USUBJID",
                                "CLDTC"
                            ]
                        }
                    ]
                },
                {
                    "all": [
                        {
                            "name": "CLDTC",
                            "operator": "non_empty"
                        },
                        {
                            "name": "POOLID",
                            "operator": "non_empty"
                        },
                        {
                            "name": "CLORRES",
                            "operator": "is_not_unique_set",
                            "value": [
                                "POOLID",
                                "CLDTC"
                            ]
                        }
                    ]
                }
            ]
        },
        "Core": {
            "Id": "CDISC.SENDIG.156",
            "Version": "1",
            "Status": "Draft"
        },
        "Description": "Raise an error when there is more than one record present for any particular Result or Findings as Collected, in the CL Domain, for a subject or pool on a particular date.",
        "Outcome": {
            "Message": "The Clinical Observation test result is not unique for this subject and date/time.",
            "Output_Variables": [
                "USUBJID",
                "POOLID",
                "CLTESTCD",
                "CLORRES",
                "CLDTC"
            ]
        },
        "Rule_Type": "Record Data",
        "Sensitivity": "Record",
        "Authorities": [
            {
                "Organization": "CDISC",
                "Standards": [
                    {
                        "Name": "SENDIG",
                        "Version": "3.1",
                        "References": [
                            {
                                "Origin": "SDTM and SENDIG Conformance Rules",
                                "Rule_Identifier": {
                                    "Id": "156",
                                    "Version": "1"
                                },
                                "Version": "2.0",
                                "Citations": [
                                    {
                                        "Cited_Guidance": "One record per finding per observation time per subject or pool",
                                        "Document": "SENDIG v3.1",
                                        "Section": "6.3.2.1"
                                    }
                                ]
                            }
                        ]
                    }
                ]
            }
        ],
        "Scope": {
            "Classes": {
                "Include": [
                    "FINDINGS"
                ]
            },
            "Domains": {
                "Include": [
                    "CL"
                ]
            }
        }
    },
    "id": "0d395142-e3b8-4cf0-8f28-96bda4a86384"
}