{
    "id": "c20e0a0b-2093-445a-aaeb-5bd3be3b0714",
    "changed": "2022-02-15T21:30:55Z",
    "content": "Check:\n  all:\n    - name:\n      operator:\n    - name:\n      operator:\nCore:\n  Id: CDISC.SDTMIG.CG0012\n  Version: '1'\n  Status: Draft\nDescription: Trigger error when variable type does not match IG Type (for domains\n  in IG) or Model Type (custom domains)\nOutcome:\n  Message: Variable type does not match IG Type or Model Type\nRule Type: Variable Metadata Check against Define XML\nSensitivity: Dataset\nAuthorities:\n  - Organization: CDISC\n    Standards:\n      - Name: SDTMIG\n        Version: '3.4'\n        References:\n          - Origin: SDTM and SDTMIG Conformance Rules\n            Rule Identifier:\n              Id: CG0012\n              Version: '1'\n            Version: '2.0'\n            Citations:\n              - Cited Guidance: Using SDTM-specified data types for all variables\n                Document: IG v3.4\n                Item:\n                Section: 3.2.2\n              - Cited Guidance: Note that the SDTM type specified in this document\n                  is either character or numeric, as these are the only types supported\n                  by SAS v.5 transport files.]\n                Document: Model v2.0\n                Section: '2.1'\nScope:\n  Classes:\n    Include:\n      - ALL\n  Domains:\n    Include:\n      - ALL\n",
    "created": "2021-11-06T04:43:13Z",
    "creator": {
        "id": "ff471ff8-f131-4cf5-9712-c79cce6301a1"
    },
    "json": {
        "Check": {
            "all": [
                {
                    "name": null,
                    "operator": null
                },
                {
                    "name": null,
                    "operator": null
                }
            ]
        },
        "Core": {
            "Id": "CDISC.SDTMIG.CG0012",
            "Version": "1",
            "Status": "Draft"
        },
        "Description": "Trigger error when variable type does not match IG Type (for domains in IG) or Model Type (custom domains)",
        "Outcome": {
            "Message": "Variable type does not match IG Type or Model Type"
        },
        "Rule_Type": "Variable Metadata Check against Define XML",
        "Sensitivity": "Dataset",
        "Authorities": [
            {
                "Organization": "CDISC",
                "Standards": [
                    {
                        "Name": "SDTMIG",
                        "Version": "3.4",
                        "References": [
                            {
                                "Origin": "SDTM and SDTMIG Conformance Rules",
                                "Rule_Identifier": {
                                    "Id": "CG0012",
                                    "Version": "1"
                                },
                                "Version": "2.0",
                                "Citations": [
                                    {
                                        "Cited_Guidance": "Using SDTM-specified data types for all variables",
                                        "Document": "IG v3.4",
                                        "Item": null,
                                        "Section": "3.2.2"
                                    },
                                    {
                                        "Cited_Guidance": "Note that the SDTM type specified in this document is either character or numeric, as these are the only types supported by SAS v.5 transport files.]",
                                        "Document": "Model v2.0",
                                        "Section": "2.1"
                                    }
                                ]
                            }
                        ]
                    }
                ]
            }
        ],
        "Scope": {
            "Classes": {
                "Include": [
                    "ALL"
                ]
            },
            "Domains": {
                "Include": [
                    "ALL"
                ]
            }
        }
    }
}