{
    "id": "4ef5ff9e-72d0-4864-a343-c96576b4d838",
    "changed": "2023-01-24T20:15:44.133Z",
    "content": "Check:\n  all:\n    - name: DSTERM\n      operator: equal_to\n      value: COMPLETED\n    - name: DSDECOD\n      operator: not_equal_to\n      value: COMPLETED\nCore:\n  Id: CORE-000033\n  Version: '1'\n  Status: Published\nDescription: Raise an error when DSTERM = \"COMPLETED\" and DSDECOD not equal to \"COMPLETED\".\nOutcome:\n  Message: DSDECOD is not equal to \"COMPLETED\" when DSTERM equals \"COMPLETED\".\n  Output Variables:\n    - DSTERM\n    - DSDECOD\nRule Type: Record Data\nSensitivity: Record\nAuthorities:\n  - Organization: CDISC\n    Standards:\n      - Name: SDTMIG\n        Version: '3.4'\n        References:\n          - Origin: SDTM and SDTMIG Conformance Rules\n            Rule Identifier:\n              Id: CG0065\n              Version: '1'\n            Version: '2.0'\n            Citations:\n              - Cited Guidance: When DSTERM = \"COMPLETED\", DSDECOD is the term \"COMPLETED\"\n                  from the controlled terminology codelist NCOMPLT.\n                Document: SDTMIG v3.4\n                Item: Assumption 3.b.i.\n                Section: 6.2.3\n      - Name: SDTMIG\n        Version: '3.3'\n        References:\n          - Origin: SDTM and SDTMIG Conformance Rules\n            Rule Identifier:\n              Id: CG0065\n              Version: '1'\n            Version: '2.0'\n            Citations:\n              - Cited Guidance: b. When DSTERM = 'COMPLETED', DSDECOD = 'COMPLETED'.\n                Document: SDTMIG v3.3\n                Item: Assumption 3b\n                Section: 6.2.3\n      - Name: SDTMIG\n        Version: '3.2'\n        References:\n          - Origin: SDTM and SDTMIG Conformance Rules\n            Rule Identifier:\n              Id: CG0065\n              Version: '1'\n            Version: '2.0'\n            Citations:\n              - Cited Guidance: b. When DSTERM = 'COMPLETED', DSDECOD = 'COMPLETED'.\n                Document: SDTMIG v3.2\n                Item: Assumption 3b\n                Section: '6.2'\nScope:\n  Classes:\n    Include:\n      - EVENTS\n  Domains:\n    Include:\n      - DS\n",
    "created": "2021-10-03T04:08:21Z",
    "creator": {
        "id": "d0881041-369e-4940-b721-5b456d12101b"
    },
    "json": {
        "Check": {
            "all": [
                {
                    "name": "DSTERM",
                    "operator": "equal_to",
                    "value": "COMPLETED"
                },
                {
                    "name": "DSDECOD",
                    "operator": "not_equal_to",
                    "value": "COMPLETED"
                }
            ]
        },
        "Core": {
            "Id": "CORE-000033",
            "Version": "1",
            "Status": "Published"
        },
        "Description": "Raise an error when DSTERM = \"COMPLETED\" and DSDECOD not equal to \"COMPLETED\".",
        "Outcome": {
            "Message": "DSDECOD is not equal to \"COMPLETED\" when DSTERM equals \"COMPLETED\".",
            "Output_Variables": [
                "DSTERM",
                "DSDECOD"
            ]
        },
        "Rule_Type": "Record Data",
        "Sensitivity": "Record",
        "Authorities": [
            {
                "Organization": "CDISC",
                "Standards": [
                    {
                        "Name": "SDTMIG",
                        "Version": "3.4",
                        "References": [
                            {
                                "Origin": "SDTM and SDTMIG Conformance Rules",
                                "Rule_Identifier": {
                                    "Id": "CG0065",
                                    "Version": "1"
                                },
                                "Version": "2.0",
                                "Citations": [
                                    {
                                        "Cited_Guidance": "When DSTERM = \"COMPLETED\", DSDECOD is the term \"COMPLETED\" from the controlled terminology codelist NCOMPLT.",
                                        "Document": "SDTMIG v3.4",
                                        "Item": "Assumption 3.b.i.",
                                        "Section": "6.2.3"
                                    }
                                ]
                            }
                        ]
                    },
                    {
                        "Name": "SDTMIG",
                        "Version": "3.3",
                        "References": [
                            {
                                "Origin": "SDTM and SDTMIG Conformance Rules",
                                "Rule_Identifier": {
                                    "Id": "CG0065",
                                    "Version": "1"
                                },
                                "Version": "2.0",
                                "Citations": [
                                    {
                                        "Cited_Guidance": "b. When DSTERM = 'COMPLETED', DSDECOD = 'COMPLETED'.",
                                        "Document": "SDTMIG v3.3",
                                        "Item": "Assumption 3b",
                                        "Section": "6.2.3"
                                    }
                                ]
                            }
                        ]
                    },
                    {
                        "Name": "SDTMIG",
                        "Version": "3.2",
                        "References": [
                            {
                                "Origin": "SDTM and SDTMIG Conformance Rules",
                                "Rule_Identifier": {
                                    "Id": "CG0065",
                                    "Version": "1"
                                },
                                "Version": "2.0",
                                "Citations": [
                                    {
                                        "Cited_Guidance": "b. When DSTERM = 'COMPLETED', DSDECOD = 'COMPLETED'.",
                                        "Document": "SDTMIG v3.2",
                                        "Item": "Assumption 3b",
                                        "Section": "6.2"
                                    }
                                ]
                            }
                        ]
                    }
                ]
            }
        ],
        "Scope": {
            "Classes": {
                "Include": [
                    "EVENTS"
                ]
            },
            "Domains": {
                "Include": [
                    "DS"
                ]
            }
        }
    }
}