{
    "id": "4fde4818-9467-4b2b-9e47-a19ab7d804ae",
    "changed": "2023-02-01T14:04:17.031Z",
    "content": "Check:\n  all:\n    - name: --BDSYCD\n      operator: exists\n    - name: --BODSYS\n      operator: exists\n    - name: --BDSYCD\n      operator: is_not_unique_relationship\n      value: --BODSYS\nCore:\n  Id: CORE-000184\n  Version: '1'\n  Status: Published\nDescription: There must be a one-to-one relationship between --BDSYSCD and --BODSYS\nOutcome:\n  Message: There is not a one-to-one relationship between --BODSYS and --BDSYSCD\n  Output Variables:\n    - --BODSYS\n    - --BDSYCD\nRule Type: Record Data\nSensitivity: Dataset\nAuthorities:\n  - Organization: CDISC\n    Standards:\n      - Name: SDTMIG\n        Version: '3.4'\n        References:\n          - Origin: SDTM and SDTMIG Conformance Rules\n            Rule Identifier:\n              Id: CG0083\n              Version: '2'\n            Version: '2.0'\n            Citations:\n              - Cited Guidance: Events[--BODSYSCD][Variable Qualifier of BODSYS]\n                Document: Model v2.0\n                Item: --BODSYS\n                Section: Events\n      - Name: SDTMIG\n        Version: '3.3'\n        References:\n          - Origin: SDTM and SDTMIG Conformance Rules\n            Rule Identifier:\n              Id: CG0083\n              Version: '2'\n            Version: '2.0'\n            Citations:\n              - Cited Guidance: Variable Qualifier of --BODSYS\n                Document: Model v1.7\n                Section: 2.2.2\n      - Name: SDTMIG\n        Version: '3.2'\n        References:\n          - Origin: SDTM and SDTMIG Conformance Rules\n            Rule Identifier:\n              Id: CG0083\n              Version: '2'\n            Version: '2.0'\n            Citations:\n              - Cited Guidance: Variable Qualifier of --BODSYS\n                Document: Model v1.4\n                Section: 2.2.2\nScope:\n  Classes:\n    Include:\n      - EVENTS\n  Domains:\n    Include:\n      - ALL\n",
    "created": "2021-10-29T05:54:22Z",
    "creator": {
        "id": "ff471ff8-f131-4cf5-9712-c79cce6301a1"
    },
    "json": {
        "Check": {
            "all": [
                {
                    "name": "--BDSYCD",
                    "operator": "exists"
                },
                {
                    "name": "--BODSYS",
                    "operator": "exists"
                },
                {
                    "name": "--BDSYCD",
                    "operator": "is_not_unique_relationship",
                    "value": "--BODSYS"
                }
            ]
        },
        "Core": {
            "Id": "CORE-000184",
            "Version": "1",
            "Status": "Published"
        },
        "Description": "There must be a one-to-one relationship between --BDSYSCD and --BODSYS",
        "Outcome": {
            "Message": "There is not a one-to-one relationship between --BODSYS and --BDSYSCD",
            "Output_Variables": [
                "--BODSYS",
                "--BDSYCD"
            ]
        },
        "Rule_Type": "Record Data",
        "Sensitivity": "Dataset",
        "Authorities": [
            {
                "Organization": "CDISC",
                "Standards": [
                    {
                        "Name": "SDTMIG",
                        "Version": "3.4",
                        "References": [
                            {
                                "Origin": "SDTM and SDTMIG Conformance Rules",
                                "Rule_Identifier": {
                                    "Id": "CG0083",
                                    "Version": "2"
                                },
                                "Version": "2.0",
                                "Citations": [
                                    {
                                        "Cited_Guidance": "Events[--BODSYSCD][Variable Qualifier of BODSYS]",
                                        "Document": "Model v2.0",
                                        "Item": "--BODSYS",
                                        "Section": "Events"
                                    }
                                ]
                            }
                        ]
                    },
                    {
                        "Name": "SDTMIG",
                        "Version": "3.3",
                        "References": [
                            {
                                "Origin": "SDTM and SDTMIG Conformance Rules",
                                "Rule_Identifier": {
                                    "Id": "CG0083",
                                    "Version": "2"
                                },
                                "Version": "2.0",
                                "Citations": [
                                    {
                                        "Cited_Guidance": "Variable Qualifier of --BODSYS",
                                        "Document": "Model v1.7",
                                        "Section": "2.2.2"
                                    }
                                ]
                            }
                        ]
                    },
                    {
                        "Name": "SDTMIG",
                        "Version": "3.2",
                        "References": [
                            {
                                "Origin": "SDTM and SDTMIG Conformance Rules",
                                "Rule_Identifier": {
                                    "Id": "CG0083",
                                    "Version": "2"
                                },
                                "Version": "2.0",
                                "Citations": [
                                    {
                                        "Cited_Guidance": "Variable Qualifier of --BODSYS",
                                        "Document": "Model v1.4",
                                        "Section": "2.2.2"
                                    }
                                ]
                            }
                        ]
                    }
                ]
            }
        ],
        "Scope": {
            "Classes": {
                "Include": [
                    "EVENTS"
                ]
            },
            "Domains": {
                "Include": [
                    "ALL"
                ]
            }
        }
    }
}