{
    "id": "05d5feca-413e-4d0b-a802-2e70ea5a0bfd",
    "changed": "2023-01-24T15:51:37.273Z",
    "content": "Check:\n  all:\n    - name: AEOCCUR\n      operator: exists\nCore:\n  Id: CORE-000012\n  Version: '1'\n  Status: Published\nDescription: Raise an error when AEOCCUR exists in AE dataset.\nOutcome:\n  Message: AEOCCUR is present in AE dataset.\n  Output Variables:\n    - AEOCCUR\nRule Type: Record Data\nSensitivity: Dataset\nAuthorities:\n  - Organization: CDISC\n    Standards:\n      - Name: SDTMIG\n        Version: '3.4'\n        References:\n          - Origin: SDTM and SDTMIG Conformance Rules\n            Rule Identifier:\n              Id: CG0040\n              Version: '1'\n            Version: '2.0'\n            Citations:\n              - Cited Guidance: The following Qualifiers would not be used in AE;\n                  --OCCUR, --STAT, and --REASND. They are the only Qualifiers from\n                  the SDTM Events Class not in the AE domain. They are not permitted\n                  because the AE domain contains only records for adverse events that\n                  actually occurred.\n                Document: SDTMIG v3.4\n                Item: Assumption 9\n                Section: 6.2.1\n      - Name: SDTMIG\n        Version: '3.3'\n        References:\n          - Origin: SDTM and SDTMIG Conformance Rules\n            Rule Identifier:\n              Id: CG0040\n              Version: '1'\n            Version: '2.0'\n            Citations:\n              - Cited Guidance: The following Qualifiers would not be used in AE;\n                  --OCCUR, --STAT, and--REASND. They are the only Qualifiers from\n                  the SDTM Events Class not in the AE domain. They are not permitted\n                  because the AE domain contains only records for adverse events that\n                  actually occurred.\n                Document: SDTMIG v3.3\n                Item: Assumption 9\n                Section: 6.2.1\n      - Name: SDTMIG\n        Version: '3.2'\n        References:\n          - Origin: SDTM and SDTMIG Conformance Rules\n            Rule Identifier:\n              Id: CG0040\n              Version: '1'\n            Version: '2.0'\n            Citations:\n              - Cited Guidance: The following Qualifiers would not be used in AE;\n                  --OCCUR, --STAT, and--REASND. They are the only Qualifiers from\n                  the SDTM Events Class not in the AE domain. They are not permitted\n                  because the AE domain contains only records for adverse events that\n                  actually occurred.\n                Document: SDTMIG v3.2\n                Item: Assumption 8\n                Section: 6.2.\nScope:\n  Classes:\n    Include:\n      - EVENTS\n  Domains:\n    Include:\n      - AE\n",
    "created": "2021-09-28T08:22:43Z",
    "creator": {
        "id": "02c3c969-4787-4d57-b164-e2851035c0e8"
    },
    "json": {
        "Check": {
            "all": [
                {
                    "name": "AEOCCUR",
                    "operator": "exists"
                }
            ]
        },
        "Core": {
            "Id": "CORE-000012",
            "Version": "1",
            "Status": "Published"
        },
        "Description": "Raise an error when AEOCCUR exists in AE dataset.",
        "Outcome": {
            "Message": "AEOCCUR is present in AE dataset.",
            "Output_Variables": [
                "AEOCCUR"
            ]
        },
        "Rule_Type": "Record Data",
        "Sensitivity": "Dataset",
        "Authorities": [
            {
                "Organization": "CDISC",
                "Standards": [
                    {
                        "Name": "SDTMIG",
                        "Version": "3.4",
                        "References": [
                            {
                                "Origin": "SDTM and SDTMIG Conformance Rules",
                                "Rule_Identifier": {
                                    "Id": "CG0040",
                                    "Version": "1"
                                },
                                "Version": "2.0",
                                "Citations": [
                                    {
                                        "Cited_Guidance": "The following Qualifiers would not be used in AE; --OCCUR, --STAT, and --REASND. They are the only Qualifiers from the SDTM Events Class not in the AE domain. They are not permitted because the AE domain contains only records for adverse events that actually occurred.",
                                        "Document": "SDTMIG v3.4",
                                        "Item": "Assumption 9",
                                        "Section": "6.2.1"
                                    }
                                ]
                            }
                        ]
                    },
                    {
                        "Name": "SDTMIG",
                        "Version": "3.3",
                        "References": [
                            {
                                "Origin": "SDTM and SDTMIG Conformance Rules",
                                "Rule_Identifier": {
                                    "Id": "CG0040",
                                    "Version": "1"
                                },
                                "Version": "2.0",
                                "Citations": [
                                    {
                                        "Cited_Guidance": "The following Qualifiers would not be used in AE; --OCCUR, --STAT, and--REASND. They are the only Qualifiers from the SDTM Events Class not in the AE domain. They are not permitted because the AE domain contains only records for adverse events that actually occurred.",
                                        "Document": "SDTMIG v3.3",
                                        "Item": "Assumption 9",
                                        "Section": "6.2.1"
                                    }
                                ]
                            }
                        ]
                    },
                    {
                        "Name": "SDTMIG",
                        "Version": "3.2",
                        "References": [
                            {
                                "Origin": "SDTM and SDTMIG Conformance Rules",
                                "Rule_Identifier": {
                                    "Id": "CG0040",
                                    "Version": "1"
                                },
                                "Version": "2.0",
                                "Citations": [
                                    {
                                        "Cited_Guidance": "The following Qualifiers would not be used in AE; --OCCUR, --STAT, and--REASND. They are the only Qualifiers from the SDTM Events Class not in the AE domain. They are not permitted because the AE domain contains only records for adverse events that actually occurred.",
                                        "Document": "SDTMIG v3.2",
                                        "Item": "Assumption 8",
                                        "Section": "6.2."
                                    }
                                ]
                            }
                        ]
                    }
                ]
            }
        ],
        "Scope": {
            "Classes": {
                "Include": [
                    "EVENTS"
                ]
            },
            "Domains": {
                "Include": [
                    "AE"
                ]
            }
        }
    }
}