{
    "id": "9959136a-523f-4546-9520-ffa22cda8867",
    "changed": "2022-10-04T17:10:44.152Z",
    "content": "Check:\n  all:\n    - name: --DY\n      operator: non_empty\n    - name: --DTC\n      operator: is_complete_date\n    - name: RFSTDTC\n      operator: is_complete_date\n    - name: --DY # checking failure criteria\n      operator: not_equal_to\n      value: $val_dy # this is created in the operations statement that follows\nOperations:\n  - name: RFSTDTC\n    domain: DM\n    operator: dy # does dy op take into acct +1?\n    id: $val_dy # ex in devops 2538 used -- but that threw an error\nCore:\n  Id: CDISC.SDTMIG.CG0006\n  Version: '1'\n  Status: Draft\nDescription: Raise an error when --DY is not calculated as per the study day algorithm\n  as a non-zero integer value when the date portion of --DTC is complete and the date\n  portion of DM.RFSTDTC is a complete date AND --DY is not empty\nMatch Datasets:\n  - Name: DM\n    Keys:\n      - USUBJID\nOutcome:\n  Message: --DY is not calculated correctly even though the date portion of --DTC\n    is complete, the date portion of DM.RFSTDTC is a complete date, and --DY is not\n    empty.\n  Output Variables:\n    - --DY\n    - --DTC\n    - RFSTDTC\nRule Type: Record Data\nSensitivity: Record\nAuthorities:\n  - Organization: CDISC\n    Standards:\n      - Name: SDTMIG\n        Version: '3.4'\n        References:\n          - Origin: SDTM and SDTMIG Conformance Rules\n            Rule Identifier:\n              Id: CG0006\n              Version: '2'\n            Version: '2.0'\n            Citations:\n              - Cited Guidance: The Study Day value is incremented by 1 for each date\n                  following RFSTDTC. Dates prior to RFSTDTC are decreased by 1, with\n                  the date preceding RFSTDTC designated as Study Day -1 (there is\n                  no Study Day 0)....All Study Day values are integers. Thus to calculate\n                  Study Day, --DY = (date portion of --DTC) - (date portion of RFSTDTC)\n                  + 1 if --DTC is on or after RFSTDTC, --DY = (date portion of --DTC)\n                  - (date portion of RFSTDTC) if --DTC precedes RFSTDTC. This algorithm\n                  should be used across all domains.\n                Document: SDTMIG v3.4\n                Section: 4.4.4\nScope:\n  Classes:\n    Include:\n      - ALL\n  Domains:\n    Include:\n      - ALL\n",
    "created": "2022-04-11T04:35:12Z",
    "creator": {
        "id": "6ae4d700-ba2d-4fad-9812-f33baa02bc82"
    },
    "json": {
        "Check": {
            "all": [
                {
                    "name": "--DY",
                    "operator": "non_empty"
                },
                {
                    "name": "--DTC",
                    "operator": "is_complete_date"
                },
                {
                    "name": "RFSTDTC",
                    "operator": "is_complete_date"
                },
                {
                    "name": "--DY",
                    "operator": "not_equal_to",
                    "value": "$val_dy"
                }
            ]
        },
        "Operations": [
            {
                "name": "RFSTDTC",
                "domain": "DM",
                "operator": "dy",
                "id": "$val_dy"
            }
        ],
        "Core": {
            "Id": "CDISC.SDTMIG.CG0006",
            "Version": "1",
            "Status": "Draft"
        },
        "Description": "Raise an error when --DY is not calculated as per the study day algorithm as a non-zero integer value when the date portion of --DTC is complete and the date portion of DM.RFSTDTC is a complete date AND --DY is not empty",
        "Match_Datasets": [
            {
                "Name": "DM",
                "Keys": [
                    "USUBJID"
                ]
            }
        ],
        "Outcome": {
            "Message": "--DY is not calculated correctly even though the date portion of --DTC is complete, the date portion of DM.RFSTDTC is a complete date, and --DY is not empty.",
            "Output_Variables": [
                "--DY",
                "--DTC",
                "RFSTDTC"
            ]
        },
        "Rule_Type": "Record Data",
        "Sensitivity": "Record",
        "Authorities": [
            {
                "Organization": "CDISC",
                "Standards": [
                    {
                        "Name": "SDTMIG",
                        "Version": "3.4",
                        "References": [
                            {
                                "Origin": "SDTM and SDTMIG Conformance Rules",
                                "Rule_Identifier": {
                                    "Id": "CG0006",
                                    "Version": "2"
                                },
                                "Version": "2.0",
                                "Citations": [
                                    {
                                        "Cited_Guidance": "The Study Day value is incremented by 1 for each date following RFSTDTC. Dates prior to RFSTDTC are decreased by 1, with the date preceding RFSTDTC designated as Study Day -1 (there is no Study Day 0)....All Study Day values are integers. Thus to calculate Study Day, --DY = (date portion of --DTC) - (date portion of RFSTDTC) + 1 if --DTC is on or after RFSTDTC, --DY = (date portion of --DTC) - (date portion of RFSTDTC) if --DTC precedes RFSTDTC. This algorithm should be used across all domains.",
                                        "Document": "SDTMIG v3.4",
                                        "Section": "4.4.4"
                                    }
                                ]
                            }
                        ]
                    }
                ]
            }
        ],
        "Scope": {
            "Classes": {
                "Include": [
                    "ALL"
                ]
            },
            "Domains": {
                "Include": [
                    "ALL"
                ]
            }
        }
    }
}