{
    "id": "57074ddc-43f0-4421-90f7-b0b2ad32dff0",
    "changed": "2022-02-15T21:28:22Z",
    "content": "Check:\n  all:\nCore:\n  Id: CDISC.SDTMIG.CG0076\n  Version: '1'\n  Status: Draft\nDescription: Trigger error if deviation record is a derived variable, not a deviation\n  that was collected\nOutcome:\n  Message: Deviation event must not be derived deviation\nRule Type: Record Data\nSensitivity: Record\nAuthorities:\n  - Organization: CDISC\n    Standards:\n      - Name: SDTMIG\n        Version: '3.4'\n        References:\n          - Origin: SDTM and SDTMIG Conformance Rules\n            Rule Identifier:\n              Id: CG0076\n              Version: '1'\n            Version: '2.0'\n            Citations:\n              - Cited Guidance: The DV domain is an Events model for collected protocol\n                  deviations and not for derived protocol deviations that are more\n                  likely to be part of analysis.\n                Document: IG v3.4\n                Item: Assumption 1\n                Section: 6.2.7\nScope:\n  Classes:\n    Include:\n      - EVENTS\n  Domains:\n    Include:\n      - DV\n",
    "created": "2021-10-29T05:28:31Z",
    "creator": {
        "id": "ff471ff8-f131-4cf5-9712-c79cce6301a1"
    },
    "json": {
        "Check": {
            "all": null
        },
        "Core": {
            "Id": "CDISC.SDTMIG.CG0076",
            "Version": "1",
            "Status": "Draft"
        },
        "Description": "Trigger error if deviation record is a derived variable, not a deviation that was collected",
        "Outcome": {
            "Message": "Deviation event must not be derived deviation"
        },
        "Rule_Type": "Record Data",
        "Sensitivity": "Record",
        "Authorities": [
            {
                "Organization": "CDISC",
                "Standards": [
                    {
                        "Name": "SDTMIG",
                        "Version": "3.4",
                        "References": [
                            {
                                "Origin": "SDTM and SDTMIG Conformance Rules",
                                "Rule_Identifier": {
                                    "Id": "CG0076",
                                    "Version": "1"
                                },
                                "Version": "2.0",
                                "Citations": [
                                    {
                                        "Cited_Guidance": "The DV domain is an Events model for collected protocol deviations and not for derived protocol deviations that are more likely to be part of analysis.",
                                        "Document": "IG v3.4",
                                        "Item": "Assumption 1",
                                        "Section": "6.2.7"
                                    }
                                ]
                            }
                        ]
                    }
                ]
            }
        ],
        "Scope": {
            "Classes": {
                "Include": [
                    "EVENTS"
                ]
            },
            "Domains": {
                "Include": [
                    "DV"
                ]
            }
        }
    }
}