{
    "id": "46af32e5-2fe4-463a-a3f3-5eb606727a07",
    "changed": "2022-06-22T19:33:31Z",
    "content": "Check:\n  all:\n    - name: --SOCCD\n      operator: not_equal_to\n      value: --BDSYCD\nCore:\n  Id: CDISC.SDTMIG.CG0037\n  Version: '1'\n  Status: Draft\nDescription: Raise an error when primary SOC is used for analysis and SOC Code is\n  not equal to Body System Code\nOutcome:\n  Message: Primary analysis was used but --SOCCD and --BDSYCD are not equal\n  Output Variables:\n    - --TERM\n    - --BDSYCD\n    - --SOCCD\nRule Type: Record Data\nSensitivity: Record\nAuthorities:\n  - Organization: CDISC\n    Standards:\n      - Name: SDTMIG\n        Version: '3.4'\n        References:\n          - Origin: SDTM and SDTMIG Conformance Rules\n            Rule Identifier:\n              Id: CG0037\n              Version: '1'\n            Version: '2.0'\n            Citations:\n              - Cited Guidance: Dictionary derived. Code for the body system or organ\n                  class used by the sponsor. When using a multi-axial dictionary such\n                  as MedDRA, this should contain the SOC used for the sponsor's analyses\n                  and summary tables, which may not necessarily be the primary SOC.\n                Document: SDTMIG v3.4\n                Item: Specification 6.2.1\n                Section: Events\n              - Cited Guidance: MedDRA System Organ Class code corresponding to --BODSYS\n                  assigned for analysis.\n                Document: Model v2.0\n                Section: Events\nScope:\n  Classes:\n    Include:\n      - EVENTS\n  Domains:\n    Exclude:\n      - DS\n      - DV\n      - HO\n",
    "created": "2021-10-07T13:58:57Z",
    "creator": {
        "id": "1c66dcb2-42dc-4edc-a938-0267a0dc6cac"
    },
    "json": {
        "Check": {
            "all": [
                {
                    "name": "--SOCCD",
                    "operator": "not_equal_to",
                    "value": "--BDSYCD"
                }
            ]
        },
        "Core": {
            "Id": "CDISC.SDTMIG.CG0037",
            "Version": "1",
            "Status": "Draft"
        },
        "Description": "Raise an error when primary SOC is used for analysis and SOC Code is not equal to Body System Code",
        "Outcome": {
            "Message": "Primary analysis was used but --SOCCD and --BDSYCD are not equal",
            "Output_Variables": [
                "--TERM",
                "--BDSYCD",
                "--SOCCD"
            ]
        },
        "Rule_Type": "Record Data",
        "Sensitivity": "Record",
        "Authorities": [
            {
                "Organization": "CDISC",
                "Standards": [
                    {
                        "Name": "SDTMIG",
                        "Version": "3.4",
                        "References": [
                            {
                                "Origin": "SDTM and SDTMIG Conformance Rules",
                                "Rule_Identifier": {
                                    "Id": "CG0037",
                                    "Version": "1"
                                },
                                "Version": "2.0",
                                "Citations": [
                                    {
                                        "Cited_Guidance": "Dictionary derived. Code for the body system or organ class used by the sponsor. When using a multi-axial dictionary such as MedDRA, this should contain the SOC used for the sponsor's analyses and summary tables, which may not necessarily be the primary SOC.",
                                        "Document": "SDTMIG v3.4",
                                        "Item": "Specification 6.2.1",
                                        "Section": "Events"
                                    },
                                    {
                                        "Cited_Guidance": "MedDRA System Organ Class code corresponding to --BODSYS assigned for analysis.",
                                        "Document": "Model v2.0",
                                        "Section": "Events"
                                    }
                                ]
                            }
                        ]
                    }
                ]
            }
        ],
        "Scope": {
            "Classes": {
                "Include": [
                    "EVENTS"
                ]
            },
            "Domains": {
                "Exclude": [
                    "DS",
                    "DV",
                    "HO"
                ]
            }
        }
    }
}