{
    "id": "6140401e-594d-45a7-9a35-2f812d9f26a8",
    "changed": "2023-01-20T16:00:03.135Z",
    "content": "Check:\n  all:\n    - name: VISITNUM\n      operator: non_empty\n    - name: VISITNUM\n      operator: is_not_contained_by\n      value: $sv_visitnum\nOperations:\n  - operator: distinct\n    domain: SV\n    name: VISITNUM\n    id: $sv_visitnum\nCore:\n  Id: CORE-000168\n  Version: '1'\n  Status: Published\nDescription: If VISITNUM is not null then VISITNUM should be among SV.VISITNUM\nOutcome:\n  Message: VISITNUM is not among VISITNUM in SV domain.\n  Output Variables:\n    - VISITNUM\nRule Type: Record Data\nSensitivity: Record\nAuthorities:\n  - Organization: CDISC\n    Standards:\n      - Name: SDTMIG\n        Version: '3.4'\n        References:\n          - Origin: SDTM and SDTMIG Conformance Rules\n            Rule Identifier:\n              Id: CG0034\n              Version: '2'\n            Version: '2.0'\n            Citations:\n              - Cited Guidance: The Subject Visits domain consolidates information\n                  about the timing of subject visits that is otherwise spread over\n                  domains that include the visit variables (VISITNUM and possibly\n                  VISIT and/or VISITDY).\n                Document: IG v3.4\n                Section: '5.5'\n      - Name: SDTMIG\n        Version: '3.3'\n        References:\n          - Origin: SDTM and SDTMIG Conformance Rules\n            Rule Identifier:\n              Id: CG0034\n              Version: '2'\n            Version: '2.0'\n            Citations:\n              - Cited Guidance: The Subject Visits domain consolidates information\n                  about the timing of subject visits that is otherwise spread over\n                  domains that include the visit variables (VISITNUM and possibly\n                  VISIT and/or VISITDY).\n                Document: IG v3.3\n                Section: '5.5'\n      - Name: SDTMIG\n        Version: '3.2'\n        References:\n          - Origin: SDTM and SDTMIG Conformance Rules\n            Rule Identifier:\n              Id: CG0034\n              Version: '2'\n            Version: '2.0'\n            Citations:\n              - Cited Guidance: The Subject Visits domain consolidates information\n                  about the timing of subject visits that is otherwise spread over\n                  domains that include the visit variables (VISITNUM and possibly\n                  VISIT and/or VISITDY).\n                Document: IG v3.2\n                Section: '5'\nScope:\n  Classes:\n    Include:\n      - ALL\n  Domains:\n    Exclude:\n      - SV\n",
    "created": "2021-10-21T00:52:13Z",
    "creator": {
        "id": "57b54e45-6455-401d-bba2-4bd1de21716d"
    },
    "json": {
        "Check": {
            "all": [
                {
                    "name": "VISITNUM",
                    "operator": "non_empty"
                },
                {
                    "name": "VISITNUM",
                    "operator": "is_not_contained_by",
                    "value": "$sv_visitnum"
                }
            ]
        },
        "Operations": [
            {
                "operator": "distinct",
                "domain": "SV",
                "name": "VISITNUM",
                "id": "$sv_visitnum"
            }
        ],
        "Core": {
            "Id": "CORE-000168",
            "Version": "1",
            "Status": "Published"
        },
        "Description": "If VISITNUM is not null then VISITNUM should be among SV.VISITNUM",
        "Outcome": {
            "Message": "VISITNUM is not among VISITNUM in SV domain.",
            "Output_Variables": [
                "VISITNUM"
            ]
        },
        "Rule_Type": "Record Data",
        "Sensitivity": "Record",
        "Authorities": [
            {
                "Organization": "CDISC",
                "Standards": [
                    {
                        "Name": "SDTMIG",
                        "Version": "3.4",
                        "References": [
                            {
                                "Origin": "SDTM and SDTMIG Conformance Rules",
                                "Rule_Identifier": {
                                    "Id": "CG0034",
                                    "Version": "2"
                                },
                                "Version": "2.0",
                                "Citations": [
                                    {
                                        "Cited_Guidance": "The Subject Visits domain consolidates information about the timing of subject visits that is otherwise spread over domains that include the visit variables (VISITNUM and possibly VISIT and/or VISITDY).",
                                        "Document": "IG v3.4",
                                        "Section": "5.5"
                                    }
                                ]
                            }
                        ]
                    },
                    {
                        "Name": "SDTMIG",
                        "Version": "3.3",
                        "References": [
                            {
                                "Origin": "SDTM and SDTMIG Conformance Rules",
                                "Rule_Identifier": {
                                    "Id": "CG0034",
                                    "Version": "2"
                                },
                                "Version": "2.0",
                                "Citations": [
                                    {
                                        "Cited_Guidance": "The Subject Visits domain consolidates information about the timing of subject visits that is otherwise spread over domains that include the visit variables (VISITNUM and possibly VISIT and/or VISITDY).",
                                        "Document": "IG v3.3",
                                        "Section": "5.5"
                                    }
                                ]
                            }
                        ]
                    },
                    {
                        "Name": "SDTMIG",
                        "Version": "3.2",
                        "References": [
                            {
                                "Origin": "SDTM and SDTMIG Conformance Rules",
                                "Rule_Identifier": {
                                    "Id": "CG0034",
                                    "Version": "2"
                                },
                                "Version": "2.0",
                                "Citations": [
                                    {
                                        "Cited_Guidance": "The Subject Visits domain consolidates information about the timing of subject visits that is otherwise spread over domains that include the visit variables (VISITNUM and possibly VISIT and/or VISITDY).",
                                        "Document": "IG v3.2",
                                        "Section": "5"
                                    }
                                ]
                            }
                        ]
                    }
                ]
            }
        ],
        "Scope": {
            "Classes": {
                "Include": [
                    "ALL"
                ]
            },
            "Domains": {
                "Exclude": [
                    "SV"
                ]
            }
        }
    }
}