{
    "id": "077d7787-475f-42a5-8b1a-035bec25f4f7",
    "changed": "2022-12-23T10:05:16.420Z",
    "content": "Check:\n  all:\n    - name: USUBJID\n      operator: non_empty\n    - name: USUBJID\n      operator: is_not_contained_by\n      value: $dm_usubjid\nCore:\n  Id: CORE-000201\n  Version: '1'\n  Status: Published\nDescription: Trigger error when domain is not an AP-- domain and USUBJID is not present\n  in DM.USUBJID\nOperations:\n  - domain: DM\n    id: $dm_usubjid\n    name: USUBJID\n    operator: distinct\nOutcome:\n  Message: USUBJID is not found in DM.USUBJID\nRule Type: Record Data\nSensitivity: Record\nAuthorities:\n  - Organization: CDISC\n    Standards:\n      - Name: SDTMIG\n        Version: '3.4'\n        References:\n          - Origin: SDTM and SDTMIG Conformance Rules\n            Rule Identifier:\n              Id: CG0029\n              Version: '1'\n            Version: '2.0'\n            Citations:\n              - Cited Guidance: The unique subject identifier (USUBJID) is required\n                  in all datasets containing subject-level data. USUBJID values must\n                  be unique for each trial participant (subject) across all trials\n                  in the submission.\n                Document: IG v3.4\n                Section: 4.2.3\n      - Name: SDTMIG\n        Version: '3.3'\n        References:\n          - Origin: SDTM and SDTMIG Conformance Rules\n            Rule Identifier:\n              Id: CG0029\n              Version: '1'\n            Version: '2.0'\n            Citations:\n              - Cited Guidance: The unique subject identifier (USUBJID) is required\n                  in all datasets containing subject-level data. USUBJID values must\n                  be unique for each trial participant (subject) across all trials\n                  in the submission.\n                Document: IG v3.3\n                Section: 4.2.3\n      - Name: SDTMIG\n        Version: '3.2'\n        References:\n          - Origin: SDTM and SDTMIG Conformance Rules\n            Rule Identifier:\n              Id: CG0029\n              Version: '1'\n            Version: '2.0'\n            Citations:\n              - Cited Guidance: '... a unique identifier (USUBJID) should be assigned\n                  and included in all datasets. The unique subject identifier (USUBJID)\n                  is required in all datasets containing subject-level data.'\n                Document: IG v3.2\n                Section: 4.1.2.3\nScope:\n  Classes:\n    Include:\n      - ALL\n  Domains:\n    Exclude:\n      - AP\n",
    "created": "2021-11-06T07:01:10Z",
    "creator": {
        "id": "ff471ff8-f131-4cf5-9712-c79cce6301a1"
    },
    "json": {
        "Check": {
            "all": [
                {
                    "name": "USUBJID",
                    "operator": "non_empty"
                },
                {
                    "name": "USUBJID",
                    "operator": "is_not_contained_by",
                    "value": "$dm_usubjid"
                }
            ]
        },
        "Core": {
            "Id": "CORE-000201",
            "Version": "1",
            "Status": "Published"
        },
        "Description": "Trigger error when domain is not an AP-- domain and USUBJID is not present in DM.USUBJID",
        "Operations": [
            {
                "domain": "DM",
                "id": "$dm_usubjid",
                "name": "USUBJID",
                "operator": "distinct"
            }
        ],
        "Outcome": {
            "Message": "USUBJID is not found in DM.USUBJID"
        },
        "Rule_Type": "Record Data",
        "Sensitivity": "Record",
        "Authorities": [
            {
                "Organization": "CDISC",
                "Standards": [
                    {
                        "Name": "SDTMIG",
                        "Version": "3.4",
                        "References": [
                            {
                                "Origin": "SDTM and SDTMIG Conformance Rules",
                                "Rule_Identifier": {
                                    "Id": "CG0029",
                                    "Version": "1"
                                },
                                "Version": "2.0",
                                "Citations": [
                                    {
                                        "Cited_Guidance": "The unique subject identifier (USUBJID) is required in all datasets containing subject-level data. USUBJID values must be unique for each trial participant (subject) across all trials in the submission.",
                                        "Document": "IG v3.4",
                                        "Section": "4.2.3"
                                    }
                                ]
                            }
                        ]
                    },
                    {
                        "Name": "SDTMIG",
                        "Version": "3.3",
                        "References": [
                            {
                                "Origin": "SDTM and SDTMIG Conformance Rules",
                                "Rule_Identifier": {
                                    "Id": "CG0029",
                                    "Version": "1"
                                },
                                "Version": "2.0",
                                "Citations": [
                                    {
                                        "Cited_Guidance": "The unique subject identifier (USUBJID) is required in all datasets containing subject-level data. USUBJID values must be unique for each trial participant (subject) across all trials in the submission.",
                                        "Document": "IG v3.3",
                                        "Section": "4.2.3"
                                    }
                                ]
                            }
                        ]
                    },
                    {
                        "Name": "SDTMIG",
                        "Version": "3.2",
                        "References": [
                            {
                                "Origin": "SDTM and SDTMIG Conformance Rules",
                                "Rule_Identifier": {
                                    "Id": "CG0029",
                                    "Version": "1"
                                },
                                "Version": "2.0",
                                "Citations": [
                                    {
                                        "Cited_Guidance": "... a unique identifier (USUBJID) should be assigned and included in all datasets. The unique subject identifier (USUBJID) is required in all datasets containing subject-level data.",
                                        "Document": "IG v3.2",
                                        "Section": "4.1.2.3"
                                    }
                                ]
                            }
                        ]
                    }
                ]
            }
        ],
        "Scope": {
            "Classes": {
                "Include": [
                    "ALL"
                ]
            },
            "Domains": {
                "Exclude": [
                    "AP"
                ]
            }
        }
    }
}