{
    "id": "3c874254-99d8-4b67-b925-a5cc547a06cd",
    "changed": "2023-02-21T15:07:08.347Z",
    "content": "Check:\n  all:\n    - name: MHCAT\n      operator: has_same_values\nCore:\n  Id: CDISC.SDTMIG.CG0077\n  Version: '1'\n  Status: Draft\nDescription: MHCAT should not group all records.  If no smaller categorization can\n  be applied, then it is not necessary to include or populate this variable.\nOutcome:\n  Message: MHCAT is grouping all records into one generic group. If no smaller categorization\n    can be applied, then it is not necessary to include or populate this variable.\n  Output Variables:\n    - MHCAT\nRule Type: Record Data\nSensitivity: Dataset\nAuthorities:\n  - Organization: CDISC\n    Standards:\n      - Name: SDTMIG\n        Version: '3.4'\n        References:\n          - Origin: SDTM and SDTMIG Conformance Rules\n            Rule Identifier:\n              Id: CG0077\n              Version: '1'\n            Version: '2.0'\n            Citations:\n              - Cited Guidance: This categorization should not group all records (within\n                  the MH Domain) into one generic group such as \"Medical History\"\n                  or \"General Medical History\" because this is  redundant information\n                  with the domain code. If no smaller categorization can be applied,\n                  then it is not necessary to include or populate this variable.\n                Document: IG v3.4\n                Item: Assumptions 3.a.1\n                Section: 6.2.6\nScope:\n  Classes:\n    Include:\n      - EVENTS\n  Domains:\n    Include:\n      - MH\n",
    "created": "2021-11-11T21:02:49Z",
    "creator": {
        "id": "7de48ba7-1548-45ca-bfc8-3ad35590ae62"
    },
    "json": {
        "Check": {
            "all": [
                {
                    "name": "MHCAT",
                    "operator": "has_same_values"
                }
            ]
        },
        "Core": {
            "Id": "CDISC.SDTMIG.CG0077",
            "Version": "1",
            "Status": "Draft"
        },
        "Description": "MHCAT should not group all records.  If no smaller categorization can be applied, then it is not necessary to include or populate this variable.",
        "Outcome": {
            "Message": "MHCAT is grouping all records into one generic group. If no smaller categorization can be applied, then it is not necessary to include or populate this variable.",
            "Output_Variables": [
                "MHCAT"
            ]
        },
        "Sensitivity": "Dataset",
        "Authorities": [
            {
                "Organization": "CDISC",
                "Standards": [
                    {
                        "Name": "SDTMIG",
                        "Version": "3.4",
                        "References": [
                            {
                                "Origin": "SDTM and SDTMIG Conformance Rules",
                                "Version": "2.0",
                                "Citations": [
                                    {
                                        "Document": "IG v3.4",
                                        "Item": "Assumptions 3.a.1",
                                        "Section": "6.2.6",
                                        "Cited_Guidance": "This categorization should not group all records (within the MH Domain) into one generic group such as \"Medical History\" or \"General Medical History\" because this is  redundant information with the domain code. If no smaller categorization can be applied, then it is not necessary to include or populate this variable."
                                    }
                                ],
                                "Rule_Identifier": {
                                    "Id": "CG0077",
                                    "Version": "1"
                                }
                            }
                        ]
                    }
                ]
            }
        ],
        "Scope": {
            "Classes": {
                "Include": [
                    "EVENTS"
                ]
            },
            "Domains": {
                "Include": [
                    "MH"
                ]
            }
        },
        "Rule_Type": "Record Data"
    }
}