{
    "id": "926537f2-56e9-43f0-b8af-e87ca471b85f",
    "changed": "2022-03-15T17:18:38Z",
    "content": "Check:\n  all:\n    - name: --LOC\n      operator: not_exists\n    - name: --LAT\n      operator: exists\nCore:\n  Id: CORE-000079\n  Version: '1'\n  Status: Published\nDescription: Raise an error when --LOC is not present and --LAT is present.\nOutcome:\n  Message: --LAT is present when --LOC is not present.\n  Output Variables:\n    - --LOC\n    - --LAT\nRule Type: Record Data\nSensitivity: Dataset\nAuthorities:\n  - Organization: CDISC\n    Standards:\n      - Name: SDTMIG\n        Version: '3.4'\n        References:\n          - Origin: SDTM and SDTMIG Conformance Rules\n            Rule Identifier:\n              Id: CG0095\n              Version: '2'\n            Version: '2.0'\n            Citations:\n              - Cited Guidance: Events[Variable Qualifier of --LOC]|Interventions[Variable\n                  Qualifier of --LOC]|Findings[Variable Qualifier of --LOC]\n                Document: Model v2.0\n                Section: Events|Interventions|Findings\n                Item: --LAT\nScope:\n  Classes:\n    Include:\n      - ALL\n  Domains:\n    Include:\n      - ALL\n",
    "created": "2021-10-04T05:37:16Z",
    "creator": {
        "id": "ff471ff8-f131-4cf5-9712-c79cce6301a1"
    },
    "json": {
        "Check": {
            "all": [
                {
                    "name": "--LOC",
                    "operator": "not_exists"
                },
                {
                    "name": "--LAT",
                    "operator": "exists"
                }
            ]
        },
        "Core": {
            "Id": "CORE-000079",
            "Version": "1",
            "Status": "Published"
        },
        "Description": "Raise an error when --LOC is not present and --LAT is present.",
        "Outcome": {
            "Message": "--LAT is present when --LOC is not present.",
            "Output_Variables": [
                "--LOC",
                "--LAT"
            ]
        },
        "Rule_Type": "Record Data",
        "Sensitivity": "Dataset",
        "Authorities": [
            {
                "Organization": "CDISC",
                "Standards": [
                    {
                        "Name": "SDTMIG",
                        "Version": "3.4",
                        "References": [
                            {
                                "Origin": "SDTM and SDTMIG Conformance Rules",
                                "Rule_Identifier": {
                                    "Id": "CG0095",
                                    "Version": "2"
                                },
                                "Version": "2.0",
                                "Citations": [
                                    {
                                        "Cited_Guidance": "Events[Variable Qualifier of --LOC]|Interventions[Variable Qualifier of --LOC]|Findings[Variable Qualifier of --LOC]",
                                        "Document": "Model v2.0",
                                        "Section": "Events|Interventions|Findings",
                                        "Item": "--LAT"
                                    }
                                ]
                            }
                        ]
                    }
                ]
            }
        ],
        "Scope": {
            "Classes": {
                "Include": [
                    "ALL"
                ]
            },
            "Domains": {
                "Include": [
                    "ALL"
                ]
            }
        }
    }
}