{
    "id": "c61f13af-e552-4367-ba6a-3b573ed030be",
    "changed": "2022-12-02T13:07:50.920Z",
    "content": "Check:\n  all:\n    - name: VISITNUM\n      operator: is_contained_by\n      value: $tv_visitnum\n    - name: VISIT\n      operator: is_not_unique_relationship\n      value: VISITNUM\nCore:\n  Id: CDISC.SDTMIG.CG0035\n  Version: '1'\n  Status: Draft\nDescription: Trigger error when VISITNUM is present in TV.VISITNUM and does not have\n  a one-to-one relationship with VISIT\nOperations:\n  - domain: TV\n    id: $tv_visitnum\n    name: VISITNUM\n    operator: distinct\nOutcome:\n  Message: VISIT and VISITNUM do not have a one-to-one relationship\n  Output Variables:\n    - VISITNUM\n    - VISIT\nRule Type: Record Data\nSensitivity: Dataset\nAuthorities:\n  - Organization: CDISC\n    Standards:\n      - Name: SDTMIG\n        Version: '3.4'\n        References:\n          - Origin: SDTM and SDTMIG Conformance Rules\n            Rule Identifier:\n              Id: CG0035\n              Version: '1'\n            Version: '2.0'\n            Citations:\n              - Cited Guidance: There should be a one-to-one relationship between\n                  values of VISIT and VISITNUM.\n                Document: IG v3.4\n                Section: 4.4.5\n      - Name: SDTMIG\n        Version: '3.3'\n        References:\n          - Origin: SDTM and SDTMIG Conformance Rules\n            Rule Identifier:\n              Id: CG0035\n              Version: '1'\n            Version: '2.0'\n            Citations:\n              - Cited Guidance: There should be a one-to-one relationship between\n                  values of VISIT and VISITNUM.\n                Document: IG v3.3\n                Section: 4.4.5\n      - Name: SDTMIG\n        Version: '3.2'\n        References:\n          - Origin: SDTM and SDTMIG Conformance Rules\n            Rule Identifier:\n              Id: CG0035\n              Version: '1'\n            Version: '2.0'\n            Citations:\n              - Cited Guidance: There should be a one-to-one relationship between\n                  values of VISIT and VISITNUM.\n                Document: IG v3.2\n                Section: 4.1.4.5\nScope:\n  Classes:\n    Include:\n      - ALL\n  Domains:\n    Include:\n      - ALL\n",
    "created": "2021-11-06T07:01:27Z",
    "creator": {
        "id": "ff471ff8-f131-4cf5-9712-c79cce6301a1"
    },
    "json": {
        "Check": {
            "all": [
                {
                    "name": "VISITNUM",
                    "operator": "is_contained_by",
                    "value": "$tv_visitnum"
                },
                {
                    "name": "VISIT",
                    "operator": "is_not_unique_relationship",
                    "value": "VISITNUM"
                }
            ]
        },
        "Core": {
            "Id": "CDISC.SDTMIG.CG0035",
            "Version": "1",
            "Status": "Draft"
        },
        "Description": "Trigger error when VISITNUM is present in TV.VISITNUM and does not have a one-to-one relationship with VISIT",
        "Operations": [
            {
                "domain": "TV",
                "id": "$tv_visitnum",
                "name": "VISITNUM",
                "operator": "distinct"
            }
        ],
        "Outcome": {
            "Message": "VISIT and VISITNUM do not have a one-to-one relationship",
            "Output_Variables": [
                "VISITNUM",
                "VISIT"
            ]
        },
        "Rule_Type": "Record Data",
        "Sensitivity": "Dataset",
        "Authorities": [
            {
                "Organization": "CDISC",
                "Standards": [
                    {
                        "Name": "SDTMIG",
                        "Version": "3.4",
                        "References": [
                            {
                                "Origin": "SDTM and SDTMIG Conformance Rules",
                                "Rule_Identifier": {
                                    "Id": "CG0035",
                                    "Version": "1"
                                },
                                "Version": "2.0",
                                "Citations": [
                                    {
                                        "Cited_Guidance": "There should be a one-to-one relationship between values of VISIT and VISITNUM.",
                                        "Document": "IG v3.4",
                                        "Section": "4.4.5"
                                    }
                                ]
                            }
                        ]
                    },
                    {
                        "Name": "SDTMIG",
                        "Version": "3.3",
                        "References": [
                            {
                                "Origin": "SDTM and SDTMIG Conformance Rules",
                                "Rule_Identifier": {
                                    "Id": "CG0035",
                                    "Version": "1"
                                },
                                "Version": "2.0",
                                "Citations": [
                                    {
                                        "Cited_Guidance": "There should be a one-to-one relationship between values of VISIT and VISITNUM.",
                                        "Document": "IG v3.3",
                                        "Section": "4.4.5"
                                    }
                                ]
                            }
                        ]
                    },
                    {
                        "Name": "SDTMIG",
                        "Version": "3.2",
                        "References": [
                            {
                                "Origin": "SDTM and SDTMIG Conformance Rules",
                                "Rule_Identifier": {
                                    "Id": "CG0035",
                                    "Version": "1"
                                },
                                "Version": "2.0",
                                "Citations": [
                                    {
                                        "Cited_Guidance": "There should be a one-to-one relationship between values of VISIT and VISITNUM.",
                                        "Document": "IG v3.2",
                                        "Section": "4.1.4.5"
                                    }
                                ]
                            }
                        ]
                    }
                ]
            }
        ],
        "Scope": {
            "Classes": {
                "Include": [
                    "ALL"
                ]
            },
            "Domains": {
                "Include": [
                    "ALL"
                ]
            }
        }
    }
}