{
    "id": "1c016fac-f9b7-49b5-811d-cf931b3ee93b",
    "changed": "2022-02-15T21:12:00Z",
    "content": "Check:\n  all:\n    - name:\n      operator:\n    - name:\n      operator:\nCore:\n  Id: CDISC.SDTMIG.CG0097\n  Version: '1'\n  Status: Draft\nDescription: Trigger error if CMTRT was not collected on CRF\nOutcome:\n  Message: CMTRT was not collected on CRF\nRule Type: Record Data\nSensitivity: Record\nAuthorities:\n  - Organization: CDISC\n    Standards:\n      - Name: SDTMIG\n        Version: '3.4'\n        References:\n          - Origin: SDTM and SDTMIG Conformance Rules\n            Rule Identifier:\n              Id: CG0097\n              Version: '1'\n            Version: '2.0'\n            Citations:\n              - Cited Guidance: Verbatim medication name that is either pre-printed\n                  or collected on a CRF.\n                Document: IG v3.4\n                Item: Specification\n                Section: 6.1.2\nScope:\n  Classes:\n    Include:\n      - INTERVENTIONS\n  Domains:\n    Include:\n      - CM\n",
    "created": "2021-10-29T06:04:45Z",
    "creator": {
        "id": "ff471ff8-f131-4cf5-9712-c79cce6301a1"
    },
    "json": {
        "Check": {
            "all": [
                {
                    "name": null,
                    "operator": null
                },
                {
                    "name": null,
                    "operator": null
                }
            ]
        },
        "Core": {
            "Id": "CDISC.SDTMIG.CG0097",
            "Version": "1",
            "Status": "Draft"
        },
        "Description": "Trigger error if CMTRT was not collected on CRF",
        "Outcome": {
            "Message": "CMTRT was not collected on CRF"
        },
        "Rule_Type": "Record Data",
        "Sensitivity": "Record",
        "Authorities": [
            {
                "Organization": "CDISC",
                "Standards": [
                    {
                        "Name": "SDTMIG",
                        "Version": "3.4",
                        "References": [
                            {
                                "Origin": "SDTM and SDTMIG Conformance Rules",
                                "Rule_Identifier": {
                                    "Id": "CG0097",
                                    "Version": "1"
                                },
                                "Version": "2.0",
                                "Citations": [
                                    {
                                        "Cited_Guidance": "Verbatim medication name that is either pre-printed or collected on a CRF.",
                                        "Document": "IG v3.4",
                                        "Item": "Specification",
                                        "Section": "6.1.2"
                                    }
                                ]
                            }
                        ]
                    }
                ]
            }
        ],
        "Scope": {
            "Classes": {
                "Include": [
                    "INTERVENTIONS"
                ]
            },
            "Domains": {
                "Include": [
                    "CM"
                ]
            }
        }
    }
}