{
    "id": "f036bfa2-0c7c-4f3c-bd36-ef95b2c37865",
    "changed": "2022-07-31T07:52:54Z",
    "content": "Check:\n  all:\n    - name: --SEQ\n      operator: is_not_unique_set\n      value: -\"DOMAIN\" -\"USUBJID\"\n    - name: --SEQ\n      operator: is_not_unique_set\n      value: -POOLID\nCore:\n  Id: CDISC.SDTMIG.CG0028\n  Version: '1'\n  Status: Draft\nDescription: Excluding TS.TSSEQ, --SEQ must be a unique number per USUBJID per domain,\n  or a unique number per POOLID per domain, including when the domain is split into\n  multiple files.\nOutcome:\n  Message: --SEQ is not a unique number per USUBJID per domain, nor a unique number\n    per POOLID per domain, including when the domain is split into multiple files\n  Output Variables:\n    - POOLID\n    - SEQ\nRule Type: Record Data\nSensitivity: Domain\nAuthorities:\n  - Organization: CDISC\n    Standards:\n      - Name: SDTMIG\n        Version: '3.4'\n        References:\n          - Origin: SDTM and SDTMIG Conformance Rules\n            Rule Identifier:\n              Id: CG0028\n              Version: '1'\n            Version: '2.0'\n            Citations:\n              - Cited Guidance: A number used to uniquely identify records for a subject\n                  within a domain.\u00a0The Trial Summary domain does not contain subject\n                  data, and TSSEQ is a sequence number to ensure uniqueness within\n                  the dataset.\n                Document: Model v2.0\n                Item: --SEQ\n                Section: Identifiers\nScope:\n  Classes:\n    Include:\n      - ALL\n  Domains:\n    include_split_datasets: true\n    Exclude:\n      - TS\n",
    "created": "2021-11-06T07:01:02Z",
    "creator": {
        "id": "ff471ff8-f131-4cf5-9712-c79cce6301a1"
    },
    "json": {
        "Check": {
            "all": [
                {
                    "name": "--SEQ",
                    "operator": "is_not_unique_set",
                    "value": "-\"DOMAIN\" -\"USUBJID\""
                },
                {
                    "name": "--SEQ",
                    "operator": "is_not_unique_set",
                    "value": "-POOLID"
                }
            ]
        },
        "Core": {
            "Id": "CDISC.SDTMIG.CG0028",
            "Version": "1",
            "Status": "Draft"
        },
        "Description": "Excluding TS.TSSEQ, --SEQ must be a unique number per USUBJID per domain, or a unique number per POOLID per domain, including when the domain is split into multiple files.",
        "Outcome": {
            "Message": "--SEQ is not a unique number per USUBJID per domain, nor a unique number per POOLID per domain, including when the domain is split into multiple files",
            "Output_Variables": [
                "POOLID",
                "SEQ"
            ]
        },
        "Rule_Type": "Record Data",
        "Sensitivity": "Domain",
        "Authorities": [
            {
                "Organization": "CDISC",
                "Standards": [
                    {
                        "Name": "SDTMIG",
                        "Version": "3.4",
                        "References": [
                            {
                                "Origin": "SDTM and SDTMIG Conformance Rules",
                                "Rule_Identifier": {
                                    "Id": "CG0028",
                                    "Version": "1"
                                },
                                "Version": "2.0",
                                "Citations": [
                                    {
                                        "Cited_Guidance": "A number used to uniquely identify records for a subject within a domain.\u00a0The Trial Summary domain does not contain subject data, and TSSEQ is a sequence number to ensure uniqueness within the dataset.",
                                        "Document": "Model v2.0",
                                        "Item": "--SEQ",
                                        "Section": "Identifiers"
                                    }
                                ]
                            }
                        ]
                    }
                ]
            }
        ],
        "Scope": {
            "Classes": {
                "Include": [
                    "ALL"
                ]
            },
            "Domains": {
                "include_split_datasets": true,
                "Exclude": [
                    "TS"
                ]
            }
        }
    }
}