{
    "id": "13734ffc-4cd1-4f96-9f3a-5235dc610354",
    "changed": "2023-03-02T16:37:56.379Z",
    "content": "Check:\n  all:\n    - name: --STTPT\n      operator: exists\n    - name: --STRTPT\n      operator: not_exists\nCore:\n  Id: CDISC.SDTMIG.CG0060\n  Version: '1'\n  Status: Draft\nDescription: Raise an error when --STTPT is present in dataset and --STRTPT is not\n  present in dataset.\nOutcome:\n  Message: --STTPT is present in dataset, but --STRTPT is not present in dataset.\n  Output Variables:\n    - --STTPT\nRule Type: Record Data\nSensitivity: Dataset\nExecutability: Fully Executable\nAuthorities:\n  - Organization: CDISC\n    Standards:\n      - Name: SDTMIG\n        Version: '3.4'\n        References:\n          - Origin: SDTM and SDTMIG Conformance Rules\n            Rule Identifier:\n              Id: CG0060\n              Version: '1'\n            Version: '2.0'\n            Citations:\n              - Cited Guidance: The characterization of the start of an observation\n                  relative to a reference time point.  The sponsor-defined reference\n                  time point is in --STTPT.\n                Document: Model v2.0\n                Item: --STRTPT\n                Section: Timing\n      - Name: SDTMIG\n        Version: '3.3'\n        References:\n          - Origin: SDTM and SDTMIG Conformance Rules\n            Rule Identifier:\n              Id: CG0060\n              Version: '1'\n            Version: '2.0'\n            Citations:\n              - Cited Guidance: Identifies the start of the observation as being before\n                  or after the sponsor-defined reference time point defined by variable\n                  --STTPT.\n                Document: Model v1.7\n                Item: Table 2.2.5.1 --STRTPT\n                Section: 2.2.5 Timing Variables for All Classes\n      - Name: SDTMIG\n        Version: '3.2'\n        References:\n          - Origin: SDTM and SDTMIG Conformance Rules\n            Rule Identifier:\n              Id: CG0060\n              Version: '1'\n            Version: '2.0'\n            Citations:\n              - Cited Guidance: (--STRTPT) Identifies the start of the observation\n                  as being before or after the sponsor-defined reference time point\n                  defined by variable --STTPT.\n                Document: Model v1.4\n                Item: Specification\n                Section: 2.2.5 Timing Variables for All Classes\nScope:\n  Classes:\n    Include:\n      - ALL\n  Domains:\n    Include:\n      - ALL\n",
    "created": "2021-10-07T09:39:08Z",
    "creator": {
        "id": "02c3c969-4787-4d57-b164-e2851035c0e8"
    },
    "json": {
        "Check": {
            "all": [
                {
                    "name": "--STTPT",
                    "operator": "exists"
                },
                {
                    "name": "--STRTPT",
                    "operator": "not_exists"
                }
            ]
        },
        "Core": {
            "Id": "CDISC.SDTMIG.CG0060",
            "Version": "1",
            "Status": "Draft"
        },
        "Description": "Raise an error when --STTPT is present in dataset and --STRTPT is not present in dataset.",
        "Outcome": {
            "Message": "--STTPT is present in dataset, but --STRTPT is not present in dataset.",
            "Output_Variables": [
                "--STTPT"
            ]
        },
        "Sensitivity": "Dataset",
        "Executability": "Fully Executable",
        "Authorities": [
            {
                "Organization": "CDISC",
                "Standards": [
                    {
                        "Name": "SDTMIG",
                        "Version": "3.4",
                        "References": [
                            {
                                "Origin": "SDTM and SDTMIG Conformance Rules",
                                "Version": "2.0",
                                "Citations": [
                                    {
                                        "Document": "Model v2.0",
                                        "Item": "--STRTPT",
                                        "Section": "Timing",
                                        "Cited_Guidance": "The characterization of the start of an observation relative to a reference time point.  The sponsor-defined reference time point is in --STTPT."
                                    }
                                ],
                                "Rule_Identifier": {
                                    "Id": "CG0060",
                                    "Version": "1"
                                }
                            }
                        ]
                    },
                    {
                        "Name": "SDTMIG",
                        "Version": "3.3",
                        "References": [
                            {
                                "Origin": "SDTM and SDTMIG Conformance Rules",
                                "Version": "2.0",
                                "Citations": [
                                    {
                                        "Document": "Model v1.7",
                                        "Item": "Table 2.2.5.1 --STRTPT",
                                        "Section": "2.2.5 Timing Variables for All Classes",
                                        "Cited_Guidance": "Identifies the start of the observation as being before or after the sponsor-defined reference time point defined by variable --STTPT."
                                    }
                                ],
                                "Rule_Identifier": {
                                    "Id": "CG0060",
                                    "Version": "1"
                                }
                            }
                        ]
                    },
                    {
                        "Name": "SDTMIG",
                        "Version": "3.2",
                        "References": [
                            {
                                "Origin": "SDTM and SDTMIG Conformance Rules",
                                "Version": "2.0",
                                "Citations": [
                                    {
                                        "Document": "Model v1.4",
                                        "Item": "Specification",
                                        "Section": "2.2.5 Timing Variables for All Classes",
                                        "Cited_Guidance": "(--STRTPT) Identifies the start of the observation as being before or after the sponsor-defined reference time point defined by variable --STTPT."
                                    }
                                ],
                                "Rule_Identifier": {
                                    "Id": "CG0060",
                                    "Version": "1"
                                }
                            }
                        ]
                    }
                ]
            }
        ],
        "Scope": {
            "Classes": {
                "Include": [
                    "ALL"
                ]
            },
            "Domains": {
                "Include": [
                    "ALL"
                ]
            }
        },
        "Rule_Type": "Record Data"
    }
}