{
    "id": "5bf58189-2a4c-4a83-a5e4-de85a2aa3f0d",
    "changed": "2022-02-15T21:28:28Z",
    "content": "Check:\n  all:\n    - name: --ENRTPT\n      operator: exists\n    - name: -ENTPT\n      operator: not_exists\nCoreId: VariablePresenceExample\nDescription: Raise an error when --ENRTPT exists in a dataset, --ENTPT does not exist.\nOutcome:\n  Message: --ENRTPT exists in a dataset, but --ENTPT does not exist.\nRule Type: Record Data\nSensitivity: Dataset\nVersion: '1'\nAuthorities:\n  - Organization: CDISC\n    Standards:\n      - Name: SDTMIG\n        Version: '3.3'\n        References:\n          - Origin: SDTM and SDTMIG Conformance Rules\n            Rule Identifier:\n              Id: CG0058\n            Version: '1.1'\n            Citations:\n              - Cited Guidance: (--ENTPT) Description or date/time in ISO 8601 or\n                  other character format of the sponsor-defined reference point referred\n                  to by --ENRTPT.\n                Document: SDTM v1.4\n                Section: 2.2.5 Timing Variables for All Classes\nScope:\n  Classes:\n    Include:\n      - ALL\n  Domains:\n    Include:\n      - ALL\nCore:\n  Status: Draft\n",
    "created": "2021-09-22T12:40:37Z",
    "creator": {
        "id": "92b43f00-2def-4c75-ba44-95ac37a97553"
    },
    "json": {
        "Check": {
            "all": [
                {
                    "name": "--ENRTPT",
                    "operator": "exists"
                },
                {
                    "name": "-ENTPT",
                    "operator": "not_exists"
                }
            ]
        },
        "CoreId": "VariablePresenceExample",
        "Description": "Raise an error when --ENRTPT exists in a dataset, --ENTPT does not exist.",
        "Outcome": {
            "Message": "--ENRTPT exists in a dataset, but --ENTPT does not exist."
        },
        "Rule_Type": "Record Data",
        "Sensitivity": "Dataset",
        "Version": "1",
        "Authorities": [
            {
                "Organization": "CDISC",
                "Standards": [
                    {
                        "Name": "SDTMIG",
                        "Version": "3.3",
                        "References": [
                            {
                                "Origin": "SDTM and SDTMIG Conformance Rules",
                                "Rule_Identifier": {
                                    "Id": "CG0058"
                                },
                                "Version": "1.1",
                                "Citations": [
                                    {
                                        "Cited_Guidance": "(--ENTPT) Description or date/time in ISO 8601 or other character format of the sponsor-defined reference point referred to by --ENRTPT.",
                                        "Document": "SDTM v1.4",
                                        "Section": "2.2.5 Timing Variables for All Classes"
                                    }
                                ]
                            }
                        ]
                    }
                ]
            }
        ],
        "Scope": {
            "Classes": {
                "Include": [
                    "ALL"
                ]
            },
            "Domains": {
                "Include": [
                    "ALL"
                ]
            }
        },
        "Core": {
            "Status": "Draft"
        }
    }
}