{
    "id": "8d7b6f06-40a9-4ab1-834f-753c9fcc5bd3",
    "changed": "2022-11-30T14:48:11.302Z",
    "content": "Check:\n  all:\n    - name: --DY\n      operator: non_empty\n    - any:\n        - name: --DTC\n          operator: is_incomplete_date\n        - name: RFSTDTC\n          operator: is_incomplete_date\nCore:\n  Id: CDISC.SDTMIG.CG0007\n  Version: '1'\n  Status: Draft\nDescription: Raise an error when the date portion of --DTC is an incomplete date and\n  the date portion of DM.RFSTDTC is an incomplete date, but --DY is not empty\nMatch Datasets:\n  - Name: DM\n    Keys:\n      - USUBJID\nOutcome:\n  Message: The date portion of --DTC is not complete date or the date portion of DM.RFSTDTC\n    is not complete date, but --DY is not empty\n  Output Variables:\n    - --DY\n    - --DTC\n    - RFSTDTC\nRule Type: Record Data\nSensitivity: Record\nAuthorities:\n  - Organization: CDISC\n    Standards:\n      - Name: SDTMIG\n        Version: '3.4'\n        References:\n          - Origin: SDTM and SDTMIG Conformance Rules\n            Rule Identifier:\n              Id: CG0007\n              Version: '1'\n            Version: '2.0'\n            Citations:\n              - Cited Guidance: The permissible Study Day variables (--DY, --STDY,\n                  and --ENDY) . . . are determined by comparing the date portion of\n                  the respective date/time variables (--DTC, --STDTC, and --ENDTC)\n                  to the date portion of the Subject Reference Start Date (RFSTDTC\n                  from the Demographics domain)\n                Document: SDTMIG v3.4\n                Section: 4.4.4\n      - Name: SDTMIG\n        Version: '3.3'\n        References:\n          - Origin: SDTM and SDTMIG Conformance Rules\n            Rule Identifier:\n              Id: CG0007\n              Version: '1'\n            Version: '2.0'\n            Citations:\n              - Cited Guidance: The permissible Study Day variables (--DY, --STDY,\n                  and --ENDY) . . . are determined by comparing the date portion of\n                  the respective date/time variables (--DTC, --STDTC, and --ENDTC)\n                  to the date portion of the Subject Reference Start Date (RFSTDTC\n                  from the Demographics domain).\n                Document: SDTMIG v3.3\n                Section: 4.4.4\n      - Name: SDTMIG\n        Version: '3.2'\n        References:\n          - Origin: SDTM and SDTMIG Conformance Rules\n            Rule Identifier:\n              Id: CG0007\n              Version: '1'\n            Version: '2.0'\n            Citations:\n              - Cited Guidance: The permissible Study Day variables (--DY, --STDY,\n                  and --ENDY) . . . are determined by comparing the date portion of\n                  the respective date/time variables (--DTC, --STDTC, and --ENDTC)\n                  to the date portion of the Subject Reference Start Date (RFSTDTC\n                  from the Demographics domain).\n                Document: SDTMIG v3.2\n                Section: 4.1.4.4\nScope:\n  Classes:\n    Include:\n      - ALL\n  Domains:\n    Include:\n      - ALL\n",
    "created": "2021-09-29T20:42:55Z",
    "creator": {
        "id": "e7bbd139-9a5c-4b86-859e-e4854e7724fe"
    },
    "json": {
        "Check": {
            "all": [
                {
                    "name": "--DY",
                    "operator": "non_empty"
                },
                {
                    "any": [
                        {
                            "name": "--DTC",
                            "operator": "is_incomplete_date"
                        },
                        {
                            "name": "RFSTDTC",
                            "operator": "is_incomplete_date"
                        }
                    ]
                }
            ]
        },
        "Core": {
            "Id": "CDISC.SDTMIG.CG0007",
            "Version": "1",
            "Status": "Draft"
        },
        "Description": "Raise an error when the date portion of --DTC is an incomplete date and the date portion of DM.RFSTDTC is an incomplete date, but --DY is not empty",
        "Match_Datasets": [
            {
                "Name": "DM",
                "Keys": [
                    "USUBJID"
                ]
            }
        ],
        "Outcome": {
            "Message": "The date portion of --DTC is not complete date or the date portion of DM.RFSTDTC is not complete date, but --DY is not empty",
            "Output_Variables": [
                "--DY",
                "--DTC",
                "RFSTDTC"
            ]
        },
        "Rule_Type": "Record Data",
        "Sensitivity": "Record",
        "Authorities": [
            {
                "Organization": "CDISC",
                "Standards": [
                    {
                        "Name": "SDTMIG",
                        "Version": "3.4",
                        "References": [
                            {
                                "Origin": "SDTM and SDTMIG Conformance Rules",
                                "Rule_Identifier": {
                                    "Id": "CG0007",
                                    "Version": "1"
                                },
                                "Version": "2.0",
                                "Citations": [
                                    {
                                        "Cited_Guidance": "The permissible Study Day variables (--DY, --STDY, and --ENDY) . . . are determined by comparing the date portion of the respective date/time variables (--DTC, --STDTC, and --ENDTC) to the date portion of the Subject Reference Start Date (RFSTDTC from the Demographics domain)",
                                        "Document": "SDTMIG v3.4",
                                        "Section": "4.4.4"
                                    }
                                ]
                            }
                        ]
                    },
                    {
                        "Name": "SDTMIG",
                        "Version": "3.3",
                        "References": [
                            {
                                "Origin": "SDTM and SDTMIG Conformance Rules",
                                "Rule_Identifier": {
                                    "Id": "CG0007",
                                    "Version": "1"
                                },
                                "Version": "2.0",
                                "Citations": [
                                    {
                                        "Cited_Guidance": "The permissible Study Day variables (--DY, --STDY, and --ENDY) . . . are determined by comparing the date portion of the respective date/time variables (--DTC, --STDTC, and --ENDTC) to the date portion of the Subject Reference Start Date (RFSTDTC from the Demographics domain).",
                                        "Document": "SDTMIG v3.3",
                                        "Section": "4.4.4"
                                    }
                                ]
                            }
                        ]
                    },
                    {
                        "Name": "SDTMIG",
                        "Version": "3.2",
                        "References": [
                            {
                                "Origin": "SDTM and SDTMIG Conformance Rules",
                                "Rule_Identifier": {
                                    "Id": "CG0007",
                                    "Version": "1"
                                },
                                "Version": "2.0",
                                "Citations": [
                                    {
                                        "Cited_Guidance": "The permissible Study Day variables (--DY, --STDY, and --ENDY) . . . are determined by comparing the date portion of the respective date/time variables (--DTC, --STDTC, and --ENDTC) to the date portion of the Subject Reference Start Date (RFSTDTC from the Demographics domain).",
                                        "Document": "SDTMIG v3.2",
                                        "Section": "4.1.4.4"
                                    }
                                ]
                            }
                        ]
                    }
                ]
            }
        ],
        "Scope": {
            "Classes": {
                "Include": [
                    "ALL"
                ]
            },
            "Domains": {
                "Include": [
                    "ALL"
                ]
            }
        }
    }
}