{
    "id": "9e29cd43-4cc3-4e46-bf4f-252b67f41319",
    "changed": "2022-04-14T00:45:17Z",
    "content": "Check:\n  all:\n    - name: --REASND\n      operator: non_empty\n    - name: --STAT\n      operator: not_equal_to\n      value: NOT DONE\nCore:\n  Id: CORE-000225\n  Version: '1'\n  Status: Published\nDescription: Raise an error when --REASND is provided and --STAT is not equal to \"NOT\n  DONE\".\nOutcome:\n  Message: --STAT should be \"NOT DONE\" when --REASND is provided.\n  Output Variables:\n    - --STAT\n    - --REASND\nRule Type: Record Data\nSensitivity: Record\nAuthorities:\n  - Organization: CDISC\n    Standards:\n      - Name: SDTMIG\n        Version: '3.4'\n        References:\n          - Origin: SDTM and SDTMIG Conformance Rules\n            Rule Identifier:\n              Id: CG0094\n              Version: '1'\n            Version: '2.0'\n            Citations:\n              - Cited Guidance: The explanation for why requested information was\n                  not available. Used in conjunction with --STAT when value is \"NOT\n                  DONE\".\n                Document: Model v2.0\n                Section: Interventions\n              - Cited Guidance: The explanation for why requested information was\n                  not available. Used in conjunction with --STAT when value is \"NOT\n                  DONE\".\n                Document: Model v2.0\n                Section: Events\n              - Cited Guidance: The explanation for why requested information was\n                  not available. Used in conjunction with --STAT when value is \"NOT\n                  DONE\".\n                Document: Model v2.0\n                Section: Findings\nScope:\n  Classes:\n    Include:\n      - ALL\n  Domains:\n    Exclude:\n      - EX\n      - AE\n      - DS\n      - DV\n      - IE\n",
    "created": "2021-11-19T00:45:10Z",
    "creator": {
        "id": "57b54e45-6455-401d-bba2-4bd1de21716d"
    },
    "json": {
        "Check": {
            "all": [
                {
                    "name": "--REASND",
                    "operator": "non_empty"
                },
                {
                    "name": "--STAT",
                    "operator": "not_equal_to",
                    "value": "NOT DONE"
                }
            ]
        },
        "Core": {
            "Id": "CORE-000225",
            "Version": "1",
            "Status": "Published"
        },
        "Description": "Raise an error when --REASND is provided and --STAT is not equal to \"NOT DONE\".",
        "Outcome": {
            "Message": "--STAT should be \"NOT DONE\" when --REASND is provided.",
            "Output_Variables": [
                "--STAT",
                "--REASND"
            ]
        },
        "Rule_Type": "Record Data",
        "Sensitivity": "Record",
        "Authorities": [
            {
                "Organization": "CDISC",
                "Standards": [
                    {
                        "Name": "SDTMIG",
                        "Version": "3.4",
                        "References": [
                            {
                                "Origin": "SDTM and SDTMIG Conformance Rules",
                                "Rule_Identifier": {
                                    "Id": "CG0094",
                                    "Version": "1"
                                },
                                "Version": "2.0",
                                "Citations": [
                                    {
                                        "Cited_Guidance": "The explanation for why requested information was not available. Used in conjunction with --STAT when value is \"NOT DONE\".",
                                        "Document": "Model v2.0",
                                        "Section": "Interventions"
                                    },
                                    {
                                        "Cited_Guidance": "The explanation for why requested information was not available. Used in conjunction with --STAT when value is \"NOT DONE\".",
                                        "Document": "Model v2.0",
                                        "Section": "Events"
                                    },
                                    {
                                        "Cited_Guidance": "The explanation for why requested information was not available. Used in conjunction with --STAT when value is \"NOT DONE\".",
                                        "Document": "Model v2.0",
                                        "Section": "Findings"
                                    }
                                ]
                            }
                        ]
                    }
                ]
            }
        ],
        "Scope": {
            "Classes": {
                "Include": [
                    "ALL"
                ]
            },
            "Domains": {
                "Exclude": [
                    "EX",
                    "AE",
                    "DS",
                    "DV",
                    "IE"
                ]
            }
        }
    }
}