{
    "id": "7a333a2a-cbb3-4d02-8590-b8836270515f",
    "changed": "2022-04-07T10:09:13Z",
    "content": "Check:\n  all:\n    - name: --PRESP\n      operator: equal_to\n      value: Y\n    - name: --OCCUR\n      operator: empty\n    - name: --STAT\n      operator: not_equal_to\n      value: NOT DONE\nCore:\n  Id: CORE-000117\n  Version: '1'\n  Status: Published\nDescription: Raise an error when --STAT not equal to 'NOT DONE' when --PRESP = 'Y'\n  and --OCCUR is null\nOutcome:\n  Message: --STAT should equal 'NOT DONE' when --PRESP = 'Y' and --OCCUR = null\n  Output Variables:\n    - --STAT\n    - --PRESP\n    - --OCCUR\nRule Type: Record Data\nSensitivity: Record\nAuthorities:\n  - Organization: CDISC\n    Standards:\n      - Name: SDTMIG\n        Version: '3.4'\n        References:\n          - Origin: SDTM and SDTMIG Conformance Rules\n            Rule Identifier:\n              Id: CG0081\n              Version: '1.0'\n            Version: '2.0'\n            Citations:\n              - Cited Guidance: An indication that the event was prospectively stated\n                  or detailed on the CRF.\n                Document: Model v2.0\n                Item: --PRESP\n                Section: Events\n              - Cited Guidance: An indication as to whether a prespecified event has\n                  occurred.\n                Document: Model v2.0\n                Item: --OCCUR\n                Section: Events\n              - Cited Guidance: Used to indicate when a question about the occurrence\n                  of a prespecified event was not answered.\n                Document: Model v2.0\n                Item: STAT\n                Section: Events\n              - Cited Guidance: An indication that the intervention was prospectively\n                  stated or detailed on the CRF.\n                Document: Model v2.0\n                Item: --PRESP\n                Section: Interventions\n              - Cited Guidance: An indication as to whether a prespecified intervention\n                  has occurred.\n                Document: Model v2.0\n                Item: --OCCUR\n                Section: Interventions\n              - Cited Guidance: Used to indicate when a question about the occurrence\n                  of a prespecified intervention was not answered. Should be null\n                  or have a value of \"NOT DONE\".\n                Document: Model v2.0\n                Item: STAT\n                Section: Interventions\nScope:\n  Classes:\n    Include:\n      - EVENTS\n      - INTERVENTIONS\n  Domains:\n    Exclude:\n      - DS\n      - DV\n      - EX\n",
    "created": "2021-10-11T16:45:02Z",
    "creator": {
        "id": "58534b88-88e7-41a5-be67-a4d0742ed999"
    },
    "json": {
        "Check": {
            "all": [
                {
                    "name": "--PRESP",
                    "operator": "equal_to",
                    "value": "Y"
                },
                {
                    "name": "--OCCUR",
                    "operator": "empty"
                },
                {
                    "name": "--STAT",
                    "operator": "not_equal_to",
                    "value": "NOT DONE"
                }
            ]
        },
        "Core": {
            "Id": "CORE-000117",
            "Version": "1",
            "Status": "Published"
        },
        "Description": "Raise an error when --STAT not equal to 'NOT DONE' when --PRESP = 'Y' and --OCCUR is null",
        "Outcome": {
            "Message": "--STAT should equal 'NOT DONE' when --PRESP = 'Y' and --OCCUR = null",
            "Output_Variables": [
                "--STAT",
                "--PRESP",
                "--OCCUR"
            ]
        },
        "Rule_Type": "Record Data",
        "Sensitivity": "Record",
        "Authorities": [
            {
                "Organization": "CDISC",
                "Standards": [
                    {
                        "Name": "SDTMIG",
                        "Version": "3.4",
                        "References": [
                            {
                                "Origin": "SDTM and SDTMIG Conformance Rules",
                                "Rule_Identifier": {
                                    "Id": "CG0081",
                                    "Version": "1.0"
                                },
                                "Version": "2.0",
                                "Citations": [
                                    {
                                        "Cited_Guidance": "An indication that the event was prospectively stated or detailed on the CRF.",
                                        "Document": "Model v2.0",
                                        "Item": "--PRESP",
                                        "Section": "Events"
                                    },
                                    {
                                        "Cited_Guidance": "An indication as to whether a prespecified event has occurred.",
                                        "Document": "Model v2.0",
                                        "Item": "--OCCUR",
                                        "Section": "Events"
                                    },
                                    {
                                        "Cited_Guidance": "Used to indicate when a question about the occurrence of a prespecified event was not answered.",
                                        "Document": "Model v2.0",
                                        "Item": "STAT",
                                        "Section": "Events"
                                    },
                                    {
                                        "Cited_Guidance": "An indication that the intervention was prospectively stated or detailed on the CRF.",
                                        "Document": "Model v2.0",
                                        "Item": "--PRESP",
                                        "Section": "Interventions"
                                    },
                                    {
                                        "Cited_Guidance": "An indication as to whether a prespecified intervention has occurred.",
                                        "Document": "Model v2.0",
                                        "Item": "--OCCUR",
                                        "Section": "Interventions"
                                    },
                                    {
                                        "Cited_Guidance": "Used to indicate when a question about the occurrence of a prespecified intervention was not answered. Should be null or have a value of \"NOT DONE\".",
                                        "Document": "Model v2.0",
                                        "Item": "STAT",
                                        "Section": "Interventions"
                                    }
                                ]
                            }
                        ]
                    }
                ]
            }
        ],
        "Scope": {
            "Classes": {
                "Include": [
                    "EVENTS",
                    "INTERVENTIONS"
                ]
            },
            "Domains": {
                "Exclude": [
                    "DS",
                    "DV",
                    "EX"
                ]
            }
        }
    }
}