{
    "id": "24e4a12c-7cf2-4b12-93d8-8e3e3ae84722",
    "changed": "2023-01-20T16:26:26.398Z",
    "content": "Check:\n  all:\n    - name: --STRTPT\n      operator: exists\n    - name: --STTPT\n      operator: not_exists\nCore:\n  Id: CDISC.SDTMIG.CG0062\n  Version: '1'\n  Status: Draft\nDescription: Raise an error when --STRTPT is present in dataset and --STTPT is not\n  present in dataset.\nOutcome:\n  Message: --STRTPT is present in dataset, but --STTPT is not present in dataset.\n  Output Variables:\n    - --STRTPT\nRule Type: Record Data\nSensitivity: Dataset\nAuthorities:\n  - Organization: CDISC\n    Standards:\n      - Name: SDTMIG\n        Version: '3.4'\n        References:\n          - Origin: SDTM and SDTMIG Conformance Rules\n            Rule Identifier:\n              Id: CG0062\n              Version: '1'\n            Version: '2.0'\n            Citations:\n              - Cited Guidance: The description or date and/or time of a time point\n                  that acts as a fixed reference  for characterizing the start of\n                  an observation. This is the sponsor-defined reference  point referred\n                  to by --STRTPT.\n                Document: Model v2.0\n                Item: --STTPT\n                Section: Timing\n      - Name: SDTMIG\n        Version: '3.3'\n        References:\n          - Origin: SDTM and SDTMIG Conformance Rules\n            Rule Identifier:\n              Id: CG0062\n              Version: '1'\n            Version: '2.0'\n            Citations:\n              - Cited Guidance: Description or date/time in ISO 8601 or other character\n                  format of the sponsor-defined reference point referred to by --STRTPT.\n                  Examples; \"2003-12-15\" or \"VISIT 1\".\n                Document: Model v1.7\n                Item: Table 2.2.5.1 --STTPT\n                Section: 2.2.5 Timing Variables for All Classes\n      - Name: SDTMIG\n        Version: '3.2'\n        References:\n          - Origin: SDTM and SDTMIG Conformance Rules\n            Rule Identifier:\n              Id: CG0062\n              Version: '1'\n            Version: '2.0'\n            Citations:\n              - Cited Guidance: (--STTPT) Description or date/time in ISO 8601 or\n                  other character format of the sponsor-defined reference point referred\n                  to by --STRTPT. Examples; \"2003-12-15\" or \"VISIT 1\".\n                Document: Model v1.4\n                Item: Specification\n                Section: 2.2.5 Timing Variables for All Classes\nScope:\n  Classes:\n    Include:\n      - ALL\n  Domains:\n    Include:\n      - ALL\n",
    "created": "2021-10-07T09:42:53Z",
    "creator": {
        "id": "02c3c969-4787-4d57-b164-e2851035c0e8"
    },
    "json": {
        "Check": {
            "all": [
                {
                    "name": "--STRTPT",
                    "operator": "exists"
                },
                {
                    "name": "--STTPT",
                    "operator": "not_exists"
                }
            ]
        },
        "Core": {
            "Id": "CDISC.SDTMIG.CG0062",
            "Version": "1",
            "Status": "Draft"
        },
        "Description": "Raise an error when --STRTPT is present in dataset and --STTPT is not present in dataset.",
        "Outcome": {
            "Message": "--STRTPT is present in dataset, but --STTPT is not present in dataset.",
            "Output_Variables": [
                "--STRTPT"
            ]
        },
        "Rule_Type": "Record Data",
        "Sensitivity": "Dataset",
        "Authorities": [
            {
                "Organization": "CDISC",
                "Standards": [
                    {
                        "Name": "SDTMIG",
                        "Version": "3.4",
                        "References": [
                            {
                                "Origin": "SDTM and SDTMIG Conformance Rules",
                                "Rule_Identifier": {
                                    "Id": "CG0062",
                                    "Version": "1"
                                },
                                "Version": "2.0",
                                "Citations": [
                                    {
                                        "Cited_Guidance": "The description or date and/or time of a time point that acts as a fixed reference  for characterizing the start of an observation. This is the sponsor-defined reference  point referred to by --STRTPT.",
                                        "Document": "Model v2.0",
                                        "Item": "--STTPT",
                                        "Section": "Timing"
                                    }
                                ]
                            }
                        ]
                    },
                    {
                        "Name": "SDTMIG",
                        "Version": "3.3",
                        "References": [
                            {
                                "Origin": "SDTM and SDTMIG Conformance Rules",
                                "Rule_Identifier": {
                                    "Id": "CG0062",
                                    "Version": "1"
                                },
                                "Version": "2.0",
                                "Citations": [
                                    {
                                        "Cited_Guidance": "Description or date/time in ISO 8601 or other character format of the sponsor-defined reference point referred to by --STRTPT. Examples; \"2003-12-15\" or \"VISIT 1\".",
                                        "Document": "Model v1.7",
                                        "Item": "Table 2.2.5.1 --STTPT",
                                        "Section": "2.2.5 Timing Variables for All Classes"
                                    }
                                ]
                            }
                        ]
                    },
                    {
                        "Name": "SDTMIG",
                        "Version": "3.2",
                        "References": [
                            {
                                "Origin": "SDTM and SDTMIG Conformance Rules",
                                "Rule_Identifier": {
                                    "Id": "CG0062",
                                    "Version": "1"
                                },
                                "Version": "2.0",
                                "Citations": [
                                    {
                                        "Cited_Guidance": "(--STTPT) Description or date/time in ISO 8601 or other character format of the sponsor-defined reference point referred to by --STRTPT. Examples; \"2003-12-15\" or \"VISIT 1\".",
                                        "Document": "Model v1.4",
                                        "Item": "Specification",
                                        "Section": "2.2.5 Timing Variables for All Classes"
                                    }
                                ]
                            }
                        ]
                    }
                ]
            }
        ],
        "Scope": {
            "Classes": {
                "Include": [
                    "ALL"
                ]
            },
            "Domains": {
                "Include": [
                    "ALL"
                ]
            }
        }
    }
}