{
    "id": "b3f0921a-9d6f-488a-bbc2-f317b80ad31c",
    "changed": "2022-12-06T15:07:34.843Z",
    "content": "Check:\n  all:\n    - name: --TPTREF\n      operator: empty\n    - name: --RFTDTC\n      operator: exists\n    - name: --RFTDTC\n      operator: non_empty\nCore:\n  Id: CORE-000248\n  Version: '1'\n  Status: Published\nDescription: Trigger error when --TPTREF = null and --RFTDTC is populated\nOutcome:\n  Message: --RFTDTC is populated when --TPTREF is null\nRule Type: Record Data\nSensitivity: Record\nAuthorities:\n  - Organization: CDISC\n    Standards:\n      - Name: SDTMIG\n        Version: '3.4'\n        References:\n          - Origin: SDTM and SDTMIG Conformance Rules\n            Rule Identifier:\n              Id: CG0026\n              Version: '1'\n            Version: '2.0'\n            Citations:\n              - Cited Guidance: The actual date or date and time of a time point that\n                  acts as a fixed reference for a series of planned time points, represented\n                  in a standardized character format. The fixed reference point is\n                  in --TPTREF\n                Document: Model v2.0\n                Item: --RFTDTC\n                Section: Timing\n      - Name: SDTMIG\n        Version: '3.3'\n        References:\n          - Origin: SDTM and SDTMIG Conformance Rules\n            Rule Identifier:\n              Id: CG0026\n              Version: '1'\n            Version: '2.0'\n            Citations:\n              - Cited Guidance: Date/time for a fixed reference time point defined\n                  by --TPTREF\n                Document: Model v1.7\n                Item: --RFTDTC\n                Section: 2.2.5\n      - Name: SDTMIG\n        Version: '3.2'\n        References:\n          - Origin: SDTM and SDTMIG Conformance Rules\n            Rule Identifier:\n              Id: CG0026\n              Version: '1'\n            Version: '2.0'\n            Citations:\n              - Cited Guidance: Date/time for a fixed reference time point defined\n                  by --TPTREF in ISO 8601 character format.\n                Document: Model v1.4\n                Item: Table 2.2.5, --RFTDTC\n                Section: 2.2.5\nScope:\n  Classes:\n    Include:\n      - ALL\n  Domains:\n    Include:\n      - ALL\n",
    "created": "2022-02-06T02:03:57Z",
    "creator": {
        "id": "ff471ff8-f131-4cf5-9712-c79cce6301a1"
    },
    "json": {
        "Check": {
            "all": [
                {
                    "name": "--TPTREF",
                    "operator": "empty"
                },
                {
                    "name": "--RFTDTC",
                    "operator": "exists"
                },
                {
                    "name": "--RFTDTC",
                    "operator": "non_empty"
                }
            ]
        },
        "Core": {
            "Id": "CORE-000248",
            "Version": "1",
            "Status": "Published"
        },
        "Description": "Trigger error when --TPTREF = null and --RFTDTC is populated",
        "Outcome": {
            "Message": "--RFTDTC is populated when --TPTREF is null"
        },
        "Rule_Type": "Record Data",
        "Sensitivity": "Record",
        "Authorities": [
            {
                "Organization": "CDISC",
                "Standards": [
                    {
                        "Name": "SDTMIG",
                        "Version": "3.4",
                        "References": [
                            {
                                "Origin": "SDTM and SDTMIG Conformance Rules",
                                "Rule_Identifier": {
                                    "Id": "CG0026",
                                    "Version": "1"
                                },
                                "Version": "2.0",
                                "Citations": [
                                    {
                                        "Cited_Guidance": "The actual date or date and time of a time point that acts as a fixed reference for a series of planned time points, represented in a standardized character format. The fixed reference point is in --TPTREF",
                                        "Document": "Model v2.0",
                                        "Item": "--RFTDTC",
                                        "Section": "Timing"
                                    }
                                ]
                            }
                        ]
                    },
                    {
                        "Name": "SDTMIG",
                        "Version": "3.3",
                        "References": [
                            {
                                "Origin": "SDTM and SDTMIG Conformance Rules",
                                "Rule_Identifier": {
                                    "Id": "CG0026",
                                    "Version": "1"
                                },
                                "Version": "2.0",
                                "Citations": [
                                    {
                                        "Cited_Guidance": "Date/time for a fixed reference time point defined by --TPTREF",
                                        "Document": "Model v1.7",
                                        "Item": "--RFTDTC",
                                        "Section": "2.2.5"
                                    }
                                ]
                            }
                        ]
                    },
                    {
                        "Name": "SDTMIG",
                        "Version": "3.2",
                        "References": [
                            {
                                "Origin": "SDTM and SDTMIG Conformance Rules",
                                "Rule_Identifier": {
                                    "Id": "CG0026",
                                    "Version": "1"
                                },
                                "Version": "2.0",
                                "Citations": [
                                    {
                                        "Cited_Guidance": "Date/time for a fixed reference time point defined by --TPTREF in ISO 8601 character format.",
                                        "Document": "Model v1.4",
                                        "Item": "Table 2.2.5, --RFTDTC",
                                        "Section": "2.2.5"
                                    }
                                ]
                            }
                        ]
                    }
                ]
            }
        ],
        "Scope": {
            "Classes": {
                "Include": [
                    "ALL"
                ]
            },
            "Domains": {
                "Include": [
                    "ALL"
                ]
            }
        }
    }
}