{
    "id": "4149291d-77be-4976-a202-50ad728a5e1f",
    "changed": "2022-02-15T21:27:41Z",
    "content": "Check:\n  all:\n    - name:\nCore:\n  Id: CDISC.SDTMIG.CG0071\n  Version: '1'\n  Status: Draft\nDescription: Trigger error when DSCAT = 'DISPOSITION EVENT' and DSTERM does not equal\n  'COMPLETED' or the reason for discontinuation\nOutcome:\n  Message: DSTERM does not equal 'COMPLETED' or the reason for discontinuation when\n    DSCAT = 'DISPOSITION EVENT'\nRule Type: Record Data\nSensitivity: Record\nAuthorities:\n  - Organization: CDISC\n    Standards:\n      - Name: SDTMIG\n        Version: '3.4'\n        References:\n          - Origin: SDTM and SDTMIG Conformance Rules\n            Rule Identifier:\n              Id: CG0071\n              Version: '1'\n            Version: '2.0'\n            Citations:\n              - Cited Guidance: When DSCAT = \"DISPOSITION EVENT\" DSTERM contains either\n                  \"COMPLETED\" or, if the subject did not complete, specific verbatim\n                  information about the reason for non-completion\n                Document: IG v3.4\n                Item: Assumption 3b\n                Section: 6.2.4\nScope:\n  Classes:\n    Include:\n      - EVENTS\n  Domains:\n    Include:\n      - DS\n",
    "created": "2022-02-05T05:41:36Z",
    "creator": {
        "id": "ff471ff8-f131-4cf5-9712-c79cce6301a1"
    },
    "json": {
        "Check": {
            "all": [
                {
                    "name": null
                }
            ]
        },
        "Core": {
            "Id": "CDISC.SDTMIG.CG0071",
            "Version": "1",
            "Status": "Draft"
        },
        "Description": "Trigger error when DSCAT = 'DISPOSITION EVENT' and DSTERM does not equal 'COMPLETED' or the reason for discontinuation",
        "Outcome": {
            "Message": "DSTERM does not equal 'COMPLETED' or the reason for discontinuation when DSCAT = 'DISPOSITION EVENT'"
        },
        "Rule_Type": "Record Data",
        "Sensitivity": "Record",
        "Authorities": [
            {
                "Organization": "CDISC",
                "Standards": [
                    {
                        "Name": "SDTMIG",
                        "Version": "3.4",
                        "References": [
                            {
                                "Origin": "SDTM and SDTMIG Conformance Rules",
                                "Rule_Identifier": {
                                    "Id": "CG0071",
                                    "Version": "1"
                                },
                                "Version": "2.0",
                                "Citations": [
                                    {
                                        "Cited_Guidance": "When DSCAT = \"DISPOSITION EVENT\" DSTERM contains either \"COMPLETED\" or, if the subject did not complete, specific verbatim information about the reason for non-completion",
                                        "Document": "IG v3.4",
                                        "Item": "Assumption 3b",
                                        "Section": "6.2.4"
                                    }
                                ]
                            }
                        ]
                    }
                ]
            }
        ],
        "Scope": {
            "Classes": {
                "Include": [
                    "EVENTS"
                ]
            },
            "Domains": {
                "Include": [
                    "DS"
                ]
            }
        }
    }
}