{
    "id": "eef9f7e1-0ca8-4aa6-a7d2-0fa46a73c007",
    "changed": "2023-01-24T20:27:20.834Z",
    "content": "Check:\n  all:\n    - name: DSDECOD\n      operator: equal_to\n      value: DEATH\n    - name: DSSTDTC\n      operator: not_equal_to\n      value: DTHDTC\nMatch Datasets:\n  - Name: DM\n    Keys:\n      - USUBJID\nCore:\n  Id: CORE-000034\n  Version: '1'\n  Status: Published\nDescription: Raise an error when DSSTDTC is not equal to DM.DTHDTC and DSDECOD is\n  equal to \"DEATH\"\nOutcome:\n  Message: DSSTDTC does not equal DM.DTHDTC, when DSDECOD equals \"DEATH\".\n  Output Variables:\n    - DSDECOD\n    - DSSTDTC\n    - DTHDTC\nRule Type: Record Data\nSensitivity: Record\nAuthorities:\n  - Organization: CDISC\n    Standards:\n      - Name: SDTMIG\n        Version: '3.4'\n        References:\n          - Origin: SDTM and SDTMIG Conformance Rules\n            Rule Identifier:\n              Id: CG0069\n              Version: '1'\n            Version: '2.0'\n            Citations:\n              - Cited Guidance: Date/time of death for any subject who died, in ISO\n                  8601 format. Should represent the date/time that is captured in\n                  the clinical-trial database.\n                Document: SDTMIG v3.4\n                Item: Specification\n                Section: '5.2'\n      - Name: SDTMIG\n        Version: '3.3'\n        References:\n          - Origin: SDTM and SDTMIG Conformance Rules\n            Rule Identifier:\n              Id: CG0069\n              Version: '1'\n            Version: '2.0'\n            Citations:\n              - Cited Guidance: Date/time of death for any subject who died, in ISO\n                  8601 format. Should represent the date/time that is captured in\n                  the clinical-trial database.\n                Document: SDTMIG v3.3\n                Item: Specification\n                Section: '5.2'\n      - Name: SDTMIG\n        Version: '3.2'\n        References:\n          - Origin: SDTM and SDTMIG Conformance Rules\n            Rule Identifier:\n              Id: CG0069\n              Version: '1'\n            Version: '2.0'\n            Citations:\n              - Cited Guidance: Date/time of death for any subject who died, in ISO\n                  8601 format. Should represent the date/time that is captured in\n                  the clinical-trial database.\n                Document: SDTMIG v3.2\n                Item: Specification\n                Section: '5'\nScope:\n  Classes:\n    Include:\n      - EVENTS\n  Domains:\n    Include:\n      - DS\n",
    "created": "2021-10-03T04:55:43Z",
    "creator": {
        "id": "d0881041-369e-4940-b721-5b456d12101b"
    },
    "json": {
        "Check": {
            "all": [
                {
                    "name": "DSDECOD",
                    "operator": "equal_to",
                    "value": "DEATH"
                },
                {
                    "name": "DSSTDTC",
                    "operator": "not_equal_to",
                    "value": "DTHDTC"
                }
            ]
        },
        "Match_Datasets": [
            {
                "Name": "DM",
                "Keys": [
                    "USUBJID"
                ]
            }
        ],
        "Core": {
            "Id": "CORE-000034",
            "Version": "1",
            "Status": "Published"
        },
        "Description": "Raise an error when DSSTDTC is not equal to DM.DTHDTC and DSDECOD is equal to \"DEATH\"",
        "Outcome": {
            "Message": "DSSTDTC does not equal DM.DTHDTC, when DSDECOD equals \"DEATH\".",
            "Output_Variables": [
                "DSDECOD",
                "DSSTDTC",
                "DTHDTC"
            ]
        },
        "Rule_Type": "Record Data",
        "Sensitivity": "Record",
        "Authorities": [
            {
                "Organization": "CDISC",
                "Standards": [
                    {
                        "Name": "SDTMIG",
                        "Version": "3.4",
                        "References": [
                            {
                                "Origin": "SDTM and SDTMIG Conformance Rules",
                                "Rule_Identifier": {
                                    "Id": "CG0069",
                                    "Version": "1"
                                },
                                "Version": "2.0",
                                "Citations": [
                                    {
                                        "Cited_Guidance": "Date/time of death for any subject who died, in ISO 8601 format. Should represent the date/time that is captured in the clinical-trial database.",
                                        "Document": "SDTMIG v3.4",
                                        "Item": "Specification",
                                        "Section": "5.2"
                                    }
                                ]
                            }
                        ]
                    },
                    {
                        "Name": "SDTMIG",
                        "Version": "3.3",
                        "References": [
                            {
                                "Origin": "SDTM and SDTMIG Conformance Rules",
                                "Rule_Identifier": {
                                    "Id": "CG0069",
                                    "Version": "1"
                                },
                                "Version": "2.0",
                                "Citations": [
                                    {
                                        "Cited_Guidance": "Date/time of death for any subject who died, in ISO 8601 format. Should represent the date/time that is captured in the clinical-trial database.",
                                        "Document": "SDTMIG v3.3",
                                        "Item": "Specification",
                                        "Section": "5.2"
                                    }
                                ]
                            }
                        ]
                    },
                    {
                        "Name": "SDTMIG",
                        "Version": "3.2",
                        "References": [
                            {
                                "Origin": "SDTM and SDTMIG Conformance Rules",
                                "Rule_Identifier": {
                                    "Id": "CG0069",
                                    "Version": "1"
                                },
                                "Version": "2.0",
                                "Citations": [
                                    {
                                        "Cited_Guidance": "Date/time of death for any subject who died, in ISO 8601 format. Should represent the date/time that is captured in the clinical-trial database.",
                                        "Document": "SDTMIG v3.2",
                                        "Item": "Specification",
                                        "Section": "5"
                                    }
                                ]
                            }
                        ]
                    }
                ]
            }
        ],
        "Scope": {
            "Classes": {
                "Include": [
                    "EVENTS"
                ]
            },
            "Domains": {
                "Include": [
                    "DS"
                ]
            }
        }
    }
}