{
    "id": "dda0fae7-c066-4f15-9288-0dc71ea444ef",
    "changed": "2022-03-03T10:37:15Z",
    "content": "Check:\n  all:\n    - name: CMTRT\n      operator: non_empty\n    - name: CMDECOD\n      operator: empty\nCore:\n  Id: CDISC.SDTMIG.CG0096\n  Version: '1'\n  Status: Draft\nDescription: Raise an error when CMTRT is populated, CMDECOD is empty\nOutcome:\n  Message: CMDECOD must be populated when CMTRT is populated\n  Output Variables:\n    - CMTRT\n    - CMDECOD\nRule Type: Record Data\nSensitivity: Record\nAuthorities:\n  - Organization: CDISC\n    Standards:\n      - Name: SDTMIG\n        Version: '3.4'\n        References:\n          - Origin: SDTM and SDTMIG Conformance Rules\n            Rule Identifier:\n              Id: CG0096\n              Version: '1'\n            Version: '2.0'\n            Citations:\n              - Cited Guidance: CMDECOD is the standardized medication/therapy term\n                  derived by the sponsor from  the coding dictionary. It is expected\n                  that the reported term (CMTRT) or the modified term (CMMODIFY) will\n                  be coded using a standard dictionary\n                Document: IG v3.4\n                Item: Assumption 2c\n                Section: 6.1.2\n              - Cited Guidance: Standardized or dictionary-derived text description\n                  of CMTRT or CMMODIFY.  Equivalent to the generic medication name\n                  in WHO Drug. The sponsor is expected to provide the dictionary name\n                  and version used to map  the terms utilizing the define.xml external\n                  codelist attributes. If an intervention term does not have a decode\n                  value in the dictionary then  CMDECOD will be left blank.\n                Document: IG v3.3\n                Item: Specification\n                Section: 6.1.2\nScope:\n  Classes:\n    Include:\n      - INTERVENTIONS\n  Domains:\n    Include:\n      - CM\n",
    "created": "2021-10-12T15:47:20Z",
    "creator": {
        "id": "57474fac-237e-4693-bb37-7826b02737da"
    },
    "json": {
        "Check": {
            "all": [
                {
                    "name": "CMTRT",
                    "operator": "non_empty"
                },
                {
                    "name": "CMDECOD",
                    "operator": "empty"
                }
            ]
        },
        "Core": {
            "Id": "CDISC.SDTMIG.CG0096",
            "Version": "1",
            "Status": "Draft"
        },
        "Description": "Raise an error when CMTRT is populated, CMDECOD is empty",
        "Outcome": {
            "Message": "CMDECOD must be populated when CMTRT is populated",
            "Output_Variables": [
                "CMTRT",
                "CMDECOD"
            ]
        },
        "Rule_Type": "Record Data",
        "Sensitivity": "Record",
        "Authorities": [
            {
                "Organization": "CDISC",
                "Standards": [
                    {
                        "Name": "SDTMIG",
                        "Version": "3.4",
                        "References": [
                            {
                                "Origin": "SDTM and SDTMIG Conformance Rules",
                                "Rule_Identifier": {
                                    "Id": "CG0096",
                                    "Version": "1"
                                },
                                "Version": "2.0",
                                "Citations": [
                                    {
                                        "Cited_Guidance": "CMDECOD is the standardized medication/therapy term derived by the sponsor from  the coding dictionary. It is expected that the reported term (CMTRT) or the modified term (CMMODIFY) will be coded using a standard dictionary",
                                        "Document": "IG v3.4",
                                        "Item": "Assumption 2c",
                                        "Section": "6.1.2"
                                    },
                                    {
                                        "Cited_Guidance": "Standardized or dictionary-derived text description of CMTRT or CMMODIFY.  Equivalent to the generic medication name in WHO Drug. The sponsor is expected to provide the dictionary name and version used to map  the terms utilizing the define.xml external codelist attributes. If an intervention term does not have a decode value in the dictionary then  CMDECOD will be left blank.",
                                        "Document": "IG v3.3",
                                        "Item": "Specification",
                                        "Section": "6.1.2"
                                    }
                                ]
                            }
                        ]
                    }
                ]
            }
        ],
        "Scope": {
            "Classes": {
                "Include": [
                    "INTERVENTIONS"
                ]
            },
            "Domains": {
                "Include": [
                    "CM"
                ]
            }
        }
    }
}