{
    "id": "c9516454-a0d4-4c0e-9ff3-4b95adb7f68e",
    "changed": "2022-03-14T20:08:42Z",
    "content": "Check:\n  all:\n    - name: --ELTM\n      operator: exists\n    - name: --TPTREF\n      operator: not_exists\nCore:\n  Id: CORE-000167\n  Version: '1'\n  Status: Published\nDescription: Raise an error when--ELTM is present but --TPTREF is not present in dataset.\nOutcome:\n  Message: --TPTREF must be present when --ELTM is present in a dataset\n  Output Variables:\n    - --ELTM\n    - --TPTREF\nRule Type: Record Data\nSensitivity: Variable\nAuthorities:\n  - Organization: CDISC\n    Standards:\n      - Name: SDTMIG\n        Version: '3.4'\n        References:\n          - Origin: SDTM and SDTMIG Conformance Rules\n            Rule Identifier:\n              Id: CG0092\n              Version: '1'\n            Version: '2.0'\n            Citations:\n              - Cited Guidance: The description of a time point that acts as a fixed\n                  reference for a series of planned time points, used for study data\n                  tabulation. Description of the fixed  reference point referred to\n                  by --ELTM, --TPTNUM, --TPT, --STINT, and --ENINT.\n                Document: Model v2.0\n                Section: Timing\nScope:\n  Classes:\n    Include:\n      - ALL\n  Domains:\n    Include:\n      - ALL\n",
    "created": "2021-10-19T14:51:16Z",
    "creator": {
        "id": "57474fac-237e-4693-bb37-7826b02737da"
    },
    "json": {
        "Check": {
            "all": [
                {
                    "name": "--ELTM",
                    "operator": "exists"
                },
                {
                    "name": "--TPTREF",
                    "operator": "not_exists"
                }
            ]
        },
        "Core": {
            "Id": "CORE-000167",
            "Version": "1",
            "Status": "Published"
        },
        "Description": "Raise an error when--ELTM is present but --TPTREF is not present in dataset.",
        "Outcome": {
            "Message": "--TPTREF must be present when --ELTM is present in a dataset",
            "Output_Variables": [
                "--ELTM",
                "--TPTREF"
            ]
        },
        "Rule_Type": "Record Data",
        "Sensitivity": "Variable",
        "Authorities": [
            {
                "Organization": "CDISC",
                "Standards": [
                    {
                        "Name": "SDTMIG",
                        "Version": "3.4",
                        "References": [
                            {
                                "Origin": "SDTM and SDTMIG Conformance Rules",
                                "Rule_Identifier": {
                                    "Id": "CG0092",
                                    "Version": "1"
                                },
                                "Version": "2.0",
                                "Citations": [
                                    {
                                        "Cited_Guidance": "The description of a time point that acts as a fixed reference for a series of planned time points, used for study data tabulation. Description of the fixed  reference point referred to by --ELTM, --TPTNUM, --TPT, --STINT, and --ENINT.",
                                        "Document": "Model v2.0",
                                        "Section": "Timing"
                                    }
                                ]
                            }
                        ]
                    }
                ]
            }
        ],
        "Scope": {
            "Classes": {
                "Include": [
                    "ALL"
                ]
            },
            "Domains": {
                "Include": [
                    "ALL"
                ]
            }
        }
    }
}