{
    "id": "903017e3-f0c7-4f03-a6bc-ae228e02f3bd",
    "changed": "2022-03-14T20:09:09Z",
    "content": "Check:\n  all:\n    - any:\n        - all:\n            - name: --PRESP\n              operator: not_equal_to\n              value: Y\n            - name: --OCCUR\n              operator: exists\n            - name: --OCCUR\n              operator: non_empty\n        - all:\n            - name: --STAT\n              operator: equal_to\n              value: NOT DONE\n    - all:\n        - name: --OCCUR\n          operator: non_empty\n\nCore:\n  Id: CORE-000014\n  Version: '1'\n  Status: Published\nDescription: Raise an error when --PRESP is not equals to \"Y\" and --OCCUR is present\n  in dataset or --STAT is equal to \"NOT DONE\" and --OCCUR is not blank\nOutcome:\n  Message: --OCCUR should only be provided when --PRESP is equal to \"Y\".\n  Output Variables:\n    - --PRESP\n    - --OCCUR\n    - --STAT\nRule Type: Record Data\nSensitivity: Record\nAuthorities:\n  - Organization: CDISC\n    Standards:\n      - Name: SDTMIG\n        Version: '3.4'\n        References:\n          - Origin: SDTM and SDTMIG Conformance Rules\n            Rule Identifier:\n              Id: CG0087\n              Version: '1'\n            Version: '2.0'\n            Citations:\n              - Cited Guidance: Events[--PRESP][An indication that the event was prospectively\n                  stated or detailed on the CRF. Values should be \"Y\" or null.]|Events|[--OCCUR][An\n                  indication as to whether a prespecified event has occurred.]|Events[--STAT][Used\n                  to indicate when a question about the occurrence of a prespecified\n                  event was not answered. Should be null or have a value of \"NOT DONE\".]|Interventions[--PRESP][An\n                  indication that the intervention was prospectively stated or detailed\n                  on the CRF. Values should be \"Y\" or null.]|Interventions[--OCCUR][An\n                  indication as to whether a prespecified intervention has occurred.]|Interventions[--STAT][Used\n                  to indicate when a question about the occurrence of a prespecified\n                  intervention was not answered. Should be null or have a value of\n                  \"NOT DONE\".]\n                Document: Model v2.0\n                Item: --PRESP|--OCCUR|--STAT\n                Section: Events|Interventions\nScope:\n  Classes:\n    Include:\n      - EVENTS\n      - INTERVENTIONS\n  Domains:\n    Exclude:\n      - AE\n      - DS\n      - DV\n      - EX\n",
    "created": "2021-09-28T14:01:37Z",
    "creator": {
        "id": "fac95de6-5815-411a-a579-ddbc7ee4b97a"
    },
    "json": {
        "Check": {
            "all": [
                {
                    "any": [
                        {
                            "all": [
                                {
                                    "name": "--PRESP",
                                    "operator": "not_equal_to",
                                    "value": "Y"
                                },
                                {
                                    "name": "--OCCUR",
                                    "operator": "exists"
                                },
                                {
                                    "name": "--OCCUR",
                                    "operator": "non_empty"
                                }
                            ]
                        },
                        {
                            "all": [
                                {
                                    "name": "--STAT",
                                    "operator": "equal_to",
                                    "value": "NOT DONE"
                                }
                            ]
                        }
                    ]
                },
                {
                    "all": [
                        {
                            "name": "--OCCUR",
                            "operator": "non_empty"
                        }
                    ]
                }
            ]
        },
        "Core": {
            "Id": "CORE-000014",
            "Version": "1",
            "Status": "Published"
        },
        "Description": "Raise an error when --PRESP is not equals to \"Y\" and --OCCUR is present in dataset or --STAT is equal to \"NOT DONE\" and --OCCUR is not blank",
        "Outcome": {
            "Message": "--OCCUR should only be provided when --PRESP is equal to \"Y\".",
            "Output_Variables": [
                "--PRESP",
                "--OCCUR",
                "--STAT"
            ]
        },
        "Rule_Type": "Record Data",
        "Sensitivity": "Record",
        "Authorities": [
            {
                "Organization": "CDISC",
                "Standards": [
                    {
                        "Name": "SDTMIG",
                        "Version": "3.4",
                        "References": [
                            {
                                "Origin": "SDTM and SDTMIG Conformance Rules",
                                "Rule_Identifier": {
                                    "Id": "CG0087",
                                    "Version": "1"
                                },
                                "Version": "2.0",
                                "Citations": [
                                    {
                                        "Cited_Guidance": "Events[--PRESP][An indication that the event was prospectively stated or detailed on the CRF. Values should be \"Y\" or null.]|Events|[--OCCUR][An indication as to whether a prespecified event has occurred.]|Events[--STAT][Used to indicate when a question about the occurrence of a prespecified event was not answered. Should be null or have a value of \"NOT DONE\".]|Interventions[--PRESP][An indication that the intervention was prospectively stated or detailed on the CRF. Values should be \"Y\" or null.]|Interventions[--OCCUR][An indication as to whether a prespecified intervention has occurred.]|Interventions[--STAT][Used to indicate when a question about the occurrence of a prespecified intervention was not answered. Should be null or have a value of \"NOT DONE\".]",
                                        "Document": "Model v2.0",
                                        "Item": "--PRESP|--OCCUR|--STAT",
                                        "Section": "Events|Interventions"
                                    }
                                ]
                            }
                        ]
                    }
                ]
            }
        ],
        "Scope": {
            "Classes": {
                "Include": [
                    "EVENTS",
                    "INTERVENTIONS"
                ]
            },
            "Domains": {
                "Exclude": [
                    "AE",
                    "DS",
                    "DV",
                    "EX"
                ]
            }
        }
    }
}