{
    "id": "7fe1b1c2-94e3-41ec-a12c-a178df4d129c",
    "changed": "2022-02-15T21:29:16Z",
    "content": "Check:\n  all:\n    - name: --DUR\n      operator: exists\nCore:\n  Id: CDISC.SDTMIG.CG0002\n  Version: '1'\n  Status: Draft\nDescription: Raise a message when --DUR exists in a dataset, confirm collected and\n  not derived .\nOutcome:\n  Message: --DUR exists in a dataset, confirm collected and not derived.\nRule Type: Record Data\nSensitivity: Dataset\nAuthorities:\n  - Organization: CDISC\n    Standards:\n      - Name: SDTMIG\n        Version: '3.4'\n        References:\n          - Origin: SDTM and SDTMIG Conformance Rules\n            Rule Identifier:\n              Id: CG0002\n              Version: '1'\n            Version: '2.0'\n            Citations:\n              - Cited Guidance: Used only if collected on the CRF and not derived.\n                Document: SDTM v2.0\n                Section: Timing\nScope:\n  Classes:\n    Include:\n      - ALL\n  Domains:\n    Include:\n      - ALL\n",
    "created": "2021-09-29T21:30:03Z",
    "creator": {
        "id": "46705a62-7c94-4fbe-8199-8c6d29fe55e3"
    },
    "json": {
        "Check": {
            "all": [
                {
                    "name": "--DUR",
                    "operator": "exists"
                }
            ]
        },
        "Core": {
            "Id": "CDISC.SDTMIG.CG0002",
            "Version": "1",
            "Status": "Draft"
        },
        "Description": "Raise a message when --DUR exists in a dataset, confirm collected and not derived .",
        "Outcome": {
            "Message": "--DUR exists in a dataset, confirm collected and not derived."
        },
        "Rule_Type": "Record Data",
        "Sensitivity": "Dataset",
        "Authorities": [
            {
                "Organization": "CDISC",
                "Standards": [
                    {
                        "Name": "SDTMIG",
                        "Version": "3.4",
                        "References": [
                            {
                                "Origin": "SDTM and SDTMIG Conformance Rules",
                                "Rule_Identifier": {
                                    "Id": "CG0002",
                                    "Version": "1"
                                },
                                "Version": "2.0",
                                "Citations": [
                                    {
                                        "Cited_Guidance": "Used only if collected on the CRF and not derived.",
                                        "Document": "SDTM v2.0",
                                        "Section": "Timing"
                                    }
                                ]
                            }
                        ]
                    }
                ]
            }
        ],
        "Scope": {
            "Classes": {
                "Include": [
                    "ALL"
                ]
            },
            "Domains": {
                "Include": [
                    "ALL"
                ]
            }
        }
    }
}