{
    "id": "dd3f32b1-9679-40c0-8330-ba7d839a97c4",
    "changed": "2022-03-04T20:05:39Z",
    "content": "Check:\n  all:\n    - any:\n        - name: AESCAN\n          operator: equal_to_case_insensitive\n          value: Y\n        - name: AESCONG\n          operator: equal_to_case_insensitive\n          value: Y\n        - name: AESDISAB\n          operator: equal_to_case_insensitive\n          value: Y\n        - name: AESDTH\n          operator: equal_to_case_insensitive\n          value: Y\n        - name: AESHOSP\n          operator: equal_to_case_insensitive\n          value: Y\n        - name: AESLIFE\n          operator: equal_to_case_insensitive\n          value: Y\n        - name: AESOD\n          operator: equal_to_case_insensitive\n          value: Y\n        - name: AESMIE\n          operator: equal_to_case_insensitive\n          value: Y\n    - name: AESER\n      operator: not_equal_to_case_insensitive\n      value: Y\nCore:\n  Id: QC.CDISC.SDTMIG.CG0041\n  Version: '1'\n  Status: Draft\nDescription: Raise an error when AESCAN, AESCONG, AESDISAB, AESDTH, AESHOSP, AESLIFE,\n  AESOD or AESMIE = 'Y' and AESER = 'N' or is empty.\nOutcome:\n  Message: At least one of the Seriousness criteria (AESCAN, AESCONG, AESDISAB, AESDTH,\n    AESHOSP, AESLIFE, AESOD or AESMIE)  = 'Y', but AESER = 'N' or empty.\n  Output Variables:\n    - AETERM\n    - AESTDTC\nRule Type: Record Data\nSensitivity: Record\nAuthorities:\n  - Organization: CDISC\n    Standards:\n      - Name: SDTMIG\n        Version: '3.4'\n        References:\n          - Origin: SDTM and SDTMIG Conformance Rules\n            Rule Identifier:\n              Id: CG0041\n              Version: '1'\n            Version: '2.0'\n            Citations:\n              - Cited Guidance: If categories of serious events are collected secondarily\n                  to a leading question, as in the example below,  the values of the\n                  variables that capture reasons an event is considered serious (i.e.,\n                  AESCAN, AESCONG, etc.)  may be null. For example, if Serious is\n                  answered \"No\", the values for these variables maybe null. However,\n                  if  Serious is answered \"Yes\", at least one of them will have a\n                  \"Y\" response.\n                Document: SDTMIG v3.4\n                Item: Assumption 6a\n                Section: 6.2.1\nScope:\n  Classes:\n    Include:\n      - EVENTS\n  Domains:\n    Include:\n      - AE\n",
    "created": "2022-01-26T19:43:48Z",
    "creator": {
        "id": "b5bc818b-4ec4-4952-951f-0fbca010be52"
    },
    "json": {
        "Check": {
            "all": [
                {
                    "any": [
                        {
                            "name": "AESCAN",
                            "operator": "equal_to_case_insensitive",
                            "value": "Y"
                        },
                        {
                            "name": "AESCONG",
                            "operator": "equal_to_case_insensitive",
                            "value": "Y"
                        },
                        {
                            "name": "AESDISAB",
                            "operator": "equal_to_case_insensitive",
                            "value": "Y"
                        },
                        {
                            "name": "AESDTH",
                            "operator": "equal_to_case_insensitive",
                            "value": "Y"
                        },
                        {
                            "name": "AESHOSP",
                            "operator": "equal_to_case_insensitive",
                            "value": "Y"
                        },
                        {
                            "name": "AESLIFE",
                            "operator": "equal_to_case_insensitive",
                            "value": "Y"
                        },
                        {
                            "name": "AESOD",
                            "operator": "equal_to_case_insensitive",
                            "value": "Y"
                        },
                        {
                            "name": "AESMIE",
                            "operator": "equal_to_case_insensitive",
                            "value": "Y"
                        }
                    ]
                },
                {
                    "name": "AESER",
                    "operator": "not_equal_to_case_insensitive",
                    "value": "Y"
                }
            ]
        },
        "Core": {
            "Id": "QC.CDISC.SDTMIG.CG0041",
            "Version": "1",
            "Status": "Draft"
        },
        "Description": "Raise an error when AESCAN, AESCONG, AESDISAB, AESDTH, AESHOSP, AESLIFE, AESOD or AESMIE = 'Y' and AESER = 'N' or is empty.",
        "Outcome": {
            "Message": "At least one of the Seriousness criteria (AESCAN, AESCONG, AESDISAB, AESDTH, AESHOSP, AESLIFE, AESOD or AESMIE)  = 'Y', but AESER = 'N' or empty.",
            "Output_Variables": [
                "AETERM",
                "AESTDTC"
            ]
        },
        "Rule_Type": "Record Data",
        "Sensitivity": "Record",
        "Authorities": [
            {
                "Organization": "CDISC",
                "Standards": [
                    {
                        "Name": "SDTMIG",
                        "Version": "3.4",
                        "References": [
                            {
                                "Origin": "SDTM and SDTMIG Conformance Rules",
                                "Rule_Identifier": {
                                    "Id": "CG0041",
                                    "Version": "1"
                                },
                                "Version": "2.0",
                                "Citations": [
                                    {
                                        "Cited_Guidance": "If categories of serious events are collected secondarily to a leading question, as in the example below,  the values of the variables that capture reasons an event is considered serious (i.e., AESCAN, AESCONG, etc.)  may be null. For example, if Serious is answered \"No\", the values for these variables maybe null. However, if  Serious is answered \"Yes\", at least one of them will have a \"Y\" response.",
                                        "Document": "SDTMIG v3.4",
                                        "Item": "Assumption 6a",
                                        "Section": "6.2.1"
                                    }
                                ]
                            }
                        ]
                    }
                ]
            }
        ],
        "Scope": {
            "Classes": {
                "Include": [
                    "EVENTS"
                ]
            },
            "Domains": {
                "Include": [
                    "AE"
                ]
            }
        }
    }
}