{
    "id": "57b6e3f0-17b4-430c-8f69-ba7bc84f0063",
    "changed": "2022-02-15T21:28:24Z",
    "content": "Check:\n  all:\n    - name: DSDECOD\n      operator: equal_to\n      value: INFORMED CONSENT OBTAINED\n    - name: RFICDTC\n      operator: not_equal_to\n      value: Min(DS.SSTDTC)\nCore:\n  Id: CDISC.SDTMIG.CG0068 (DUPLICATE)\n  Version: '1'\n  Status: Draft\nDescription: Raise an error when DSDECOD = \"INFORMED CONSENT OBTAINED\" and min(DS.DSSTDTC)\n  for a subject ^= to DM.RFICDTC\nOutcome:\n  Message: Earliest DSSTDTC does not equal DM.RFICDTC, When multiple informed consents\n    obtained for a subject.\nRule Type: Record Data\nSensitivity: Record\nAuthorities:\n  - Organization: CDISC\n    Standards:\n      - Name: SDTMIG\n        Version: '3.4'\n        References:\n          - Origin: SDTMIG and SDTMIG Conformance Rules\n            Rule Identifier:\n              Id: CG0068\n              Version: '1'\n            Version: '2.0'\n            Citations:\n              - Cited Guidance: \"Date/time of informed consent in ISO 8601 character\\\n                  \\ format. This will be the same as the date of informed consent\\\n                  \\ in the Disposition domain,\\n if that protocol milestone is documented.\"\n                Document: SDTMIG v3.4\n                Item: Specification\n                Section: '5.2'\nScope:\n  Classes:\n    Include:\n      - EVENTS\n  Domains:\n    Include:\n      - DS\n",
    "created": "2021-10-06T13:56:50Z",
    "creator": {
        "id": "d0881041-369e-4940-b721-5b456d12101b"
    },
    "json": {
        "Check": {
            "all": [
                {
                    "name": "DSDECOD",
                    "operator": "equal_to",
                    "value": "INFORMED CONSENT OBTAINED"
                },
                {
                    "name": "RFICDTC",
                    "operator": "not_equal_to",
                    "value": "Min(DS.SSTDTC)"
                }
            ]
        },
        "Core": {
            "Id": "CDISC.SDTMIG.CG0068 (DUPLICATE)",
            "Version": "1",
            "Status": "Draft"
        },
        "Description": "Raise an error when DSDECOD = \"INFORMED CONSENT OBTAINED\" and min(DS.DSSTDTC) for a subject ^= to DM.RFICDTC",
        "Outcome": {
            "Message": "Earliest DSSTDTC does not equal DM.RFICDTC, When multiple informed consents obtained for a subject."
        },
        "Rule_Type": "Record Data",
        "Sensitivity": "Record",
        "Authorities": [
            {
                "Organization": "CDISC",
                "Standards": [
                    {
                        "Name": "SDTMIG",
                        "Version": "3.4",
                        "References": [
                            {
                                "Origin": "SDTMIG and SDTMIG Conformance Rules",
                                "Rule_Identifier": {
                                    "Id": "CG0068",
                                    "Version": "1"
                                },
                                "Version": "2.0",
                                "Citations": [
                                    {
                                        "Cited_Guidance": "Date/time of informed consent in ISO 8601 character format. This will be the same as the date of informed consent in the Disposition domain,\n if that protocol milestone is documented.",
                                        "Document": "SDTMIG v3.4",
                                        "Item": "Specification",
                                        "Section": "5.2"
                                    }
                                ]
                            }
                        ]
                    }
                ]
            }
        ],
        "Scope": {
            "Classes": {
                "Include": [
                    "EVENTS"
                ]
            },
            "Domains": {
                "Include": [
                    "DS"
                ]
            }
        }
    }
}