{
    "id": "bdb525cd-0259-4f72-ac9b-960fea994021",
    "changed": "2022-02-15T21:30:48Z",
    "content": "Check:\n  all:\n    - name:\n      operator:\n    - name:\n      operator:\nCore:\n  Id: CDISC.SDTMIG.CG0098\n  Version: '1'\n  Status: Draft\nDescription: Trigger error if CMTRT contains more than just the medication name\nOutcome:\n  Message: CMTRT must record the collected medication name only\nRule Type: Record Data\nSensitivity: Record\nAuthorities:\n  - Organization: CDISC\n    Standards:\n      - Name: SDTMIG\n        Version: '3.4'\n        References:\n          - Origin: SDTM and SDTMIG Conformance Rules\n            Rule Identifier:\n              Id: CG0098\n              Version: '1'\n            Version: '2.0'\n            Citations:\n              - Cited Guidance: CMTRT should only include the medication/therapy name\n                  and should not include dosage, formulation, or other qualifying\n                  information.\n                Document: IG v3.4\n                Item: Assumption 2a\n                Section: 6.1.2\nScope:\n  Classes:\n    Include:\n      - INTERVENTIONS\n  Domains:\n    Include:\n      - CM\n",
    "created": "2021-10-29T06:07:56Z",
    "creator": {
        "id": "ff471ff8-f131-4cf5-9712-c79cce6301a1"
    },
    "json": {
        "Check": {
            "all": [
                {
                    "name": null,
                    "operator": null
                },
                {
                    "name": null,
                    "operator": null
                }
            ]
        },
        "Core": {
            "Id": "CDISC.SDTMIG.CG0098",
            "Version": "1",
            "Status": "Draft"
        },
        "Description": "Trigger error if CMTRT contains more than just the medication name",
        "Outcome": {
            "Message": "CMTRT must record the collected medication name only"
        },
        "Rule_Type": "Record Data",
        "Sensitivity": "Record",
        "Authorities": [
            {
                "Organization": "CDISC",
                "Standards": [
                    {
                        "Name": "SDTMIG",
                        "Version": "3.4",
                        "References": [
                            {
                                "Origin": "SDTM and SDTMIG Conformance Rules",
                                "Rule_Identifier": {
                                    "Id": "CG0098",
                                    "Version": "1"
                                },
                                "Version": "2.0",
                                "Citations": [
                                    {
                                        "Cited_Guidance": "CMTRT should only include the medication/therapy name and should not include dosage, formulation, or other qualifying information.",
                                        "Document": "IG v3.4",
                                        "Item": "Assumption 2a",
                                        "Section": "6.1.2"
                                    }
                                ]
                            }
                        ]
                    }
                ]
            }
        ],
        "Scope": {
            "Classes": {
                "Include": [
                    "INTERVENTIONS"
                ]
            },
            "Domains": {
                "Include": [
                    "CM"
                ]
            }
        }
    }
}