{
    "id": "120af9b1-1db7-4e11-a126-3ac265103fa9",
    "changed": "2022-07-04T03:54:12Z",
    "content": "Check:\n  all:\n    - name: DOMAIN\n      operator: uses_valid_codelist_terms\n      value: DOMAIN\nCore:\n  Id: CDISC.SDTMIG.CG0001\n  Version: '1'\n  Status: Draft\nDescription: DOMAIN name should use a SDTM-specified standard domain name and prefixes\n  where applicable\nOutcome:\n  Message: DOMAIN Code is not a published DOMAIN Code in CDISC Controlled Terminology,\n    confirm if domain is a custom domain\nRule Type: Record Data\nSensitivity: Record\nAuthorities:\n  - Organization: CDISC\n    Standards:\n      - Name: SDTMIG\n        Version: '3.4'\n        References:\n          - Origin: SDTM and SDTMIG Conformance Rules\n            Rule Identifier:\n              Id: CG0001\n              Version: '1'\n            Version: '2.0'\n            Citations:\n              - Cited Guidance: Using SDTM-specified standard domain names and prefixes\n                  where applicable.\n                Document: SDTMIG v3.4\n                Section: 3.2.2\nScope:\n  Classes:\n    Include:\n      - ALL\n  Domains:\n    Include:\n      - ALL\n",
    "created": "2021-09-28T16:27:29Z",
    "creator": {
        "id": "46705a62-7c94-4fbe-8199-8c6d29fe55e3"
    },
    "json": {
        "Check": {
            "all": [
                {
                    "name": "DOMAIN",
                    "operator": "uses_valid_codelist_terms",
                    "value": "DOMAIN"
                }
            ]
        },
        "Core": {
            "Id": "CDISC.SDTMIG.CG0001",
            "Version": "1",
            "Status": "Draft"
        },
        "Description": "DOMAIN name should use a SDTM-specified standard domain name and prefixes where applicable",
        "Outcome": {
            "Message": "DOMAIN Code is not a published DOMAIN Code in CDISC Controlled Terminology, confirm if domain is a custom domain"
        },
        "Rule_Type": "Record Data",
        "Sensitivity": "Record",
        "Authorities": [
            {
                "Organization": "CDISC",
                "Standards": [
                    {
                        "Name": "SDTMIG",
                        "Version": "3.4",
                        "References": [
                            {
                                "Origin": "SDTM and SDTMIG Conformance Rules",
                                "Rule_Identifier": {
                                    "Id": "CG0001",
                                    "Version": "1"
                                },
                                "Version": "2.0",
                                "Citations": [
                                    {
                                        "Cited_Guidance": "Using SDTM-specified standard domain names and prefixes where applicable.",
                                        "Document": "SDTMIG v3.4",
                                        "Section": "3.2.2"
                                    }
                                ]
                            }
                        ]
                    }
                ]
            }
        ],
        "Scope": {
            "Classes": {
                "Include": [
                    "ALL"
                ]
            },
            "Domains": {
                "Include": [
                    "ALL"
                ]
            }
        }
    }
}