{
    "id": "062da4b3-0c48-4ed3-a97b-c1e92d7bcf95",
    "changed": "2022-07-17T04:30:54Z",
    "content": "Check:\n  all:\n    - name: --LNKGRP\n      operator: value_does_not_have_multiple_references\n      value: $VALUE_COUNTS\n    - name: --LNKGRP\n      operator: non_empty\nCore:\n  Id: CDISC.SDTMIG.CG0022\n  Version: '1'\n  Status: Draft\nDescription: Verify that an --LNKGRP value specified in one domain is also present\n  in the  --LNKGRP variable in another domain\nOperations:\n  - id: $VALUE_COUNTS\n    name: --LNKGRP\n    operator: variable_value_count\nOutcome:\n  Message: A value specified in --LNKGRP variable is not found in any of the other\n    submitted domains.\n  Output Variables:\n    - --LNKGRP\nRule Type: Record Data\nSensitivity: Record\nAuthorities:\n  - Organization: CDISC\n    Standards:\n      - Name: SDTMIG\n        Version: '3.4'\n        References:\n          - Origin: SDTM and SDTMIG Conformance Rules\n            Rule Identifier:\n              Id: CG0022\n              Version: '1'\n            Version: '2.0'\n            Citations:\n              - Cited Guidance: --LNKGRP is a grouping identifier used to identify\n                  a group of records in one domain that is related to a record in\n                  another domain, often forming a many-to-one relationship.\n                Document: SDTMIG v3.4\n                Item: 2.E.2\n                Section: 4.2.6\nScope:\n  Classes:\n    Include:\n      - ALL\n  Domains:\n    Include:\n      - ALL\n",
    "created": "2022-06-07T11:32:15Z",
    "creator": {
        "id": "24709aaa-3e57-4ee4-a635-6006b165bb1b"
    },
    "json": {
        "Check": {
            "all": [
                {
                    "name": "--LNKGRP",
                    "operator": "value_does_not_have_multiple_references",
                    "value": "$VALUE_COUNTS"
                },
                {
                    "name": "--LNKGRP",
                    "operator": "non_empty"
                }
            ]
        },
        "Core": {
            "Id": "CDISC.SDTMIG.CG0022",
            "Version": "1",
            "Status": "Draft"
        },
        "Description": "Verify that an --LNKGRP value specified in one domain is also present in the  --LNKGRP variable in another domain",
        "Operations": [
            {
                "id": "$VALUE_COUNTS",
                "name": "--LNKGRP",
                "operator": "variable_value_count"
            }
        ],
        "Outcome": {
            "Message": "A value specified in --LNKGRP variable is not found in any of the other submitted domains.",
            "Output_Variables": [
                "--LNKGRP"
            ]
        },
        "Rule_Type": "Record Data",
        "Sensitivity": "Record",
        "Authorities": [
            {
                "Organization": "CDISC",
                "Standards": [
                    {
                        "Name": "SDTMIG",
                        "Version": "3.4",
                        "References": [
                            {
                                "Origin": "SDTM and SDTMIG Conformance Rules",
                                "Rule_Identifier": {
                                    "Id": "CG0022",
                                    "Version": "1"
                                },
                                "Version": "2.0",
                                "Citations": [
                                    {
                                        "Cited_Guidance": "--LNKGRP is a grouping identifier used to identify a group of records in one domain that is related to a record in another domain, often forming a many-to-one relationship.",
                                        "Document": "SDTMIG v3.4",
                                        "Item": "2.E.2",
                                        "Section": "4.2.6"
                                    }
                                ]
                            }
                        ]
                    }
                ]
            }
        ],
        "Scope": {
            "Classes": {
                "Include": [
                    "ALL"
                ]
            },
            "Domains": {
                "Include": [
                    "ALL"
                ]
            }
        }
    }
}