{
    "id": "108893ff-cc21-4ac2-9284-7081986d6287",
    "changed": "2022-09-27T13:30:51.262Z",
    "content": "Check:\n  any:\n    - name: dataset_name\n      operator: shorter_than\n      value: 3\n    - name: dataset_name\n      operator: longer_than\n      value: 4\nCore:\n  Id: CDISC.SDTMIG.CG0017\n  Version: '1'\n  Status: Draft\nDescription: Split datasets (excluding supplemental qualifiers) is expected to have\n  a have a length of 3 or 4 characters\nOutcome:\n  Message: Split dataset name is not 3 or 4 characters in length\nRule Type: Variable Metadata Check\nSensitivity: Dataset\nAuthorities:\n  - Organization: CDISC\n    Standards:\n      - Name: SDTMIG\n        Version: '3.4'\n        References:\n          - Origin: SDTM and SDTMIG Conformance Rules\n            Rule Identifier:\n              Id: CG0017\n              Version: '2'\n            Version: '2.0'\n            Citations:\n              - Cited Guidance: For domains with two-letter domain codes (i.e., other\n                  than SUPPxx and RELREC), split dataset names can be up to four characters\n                  in length... The four-character dataset-name limitation allows the\n                  use of a Supplemental Qualifier dataset associated with the split\n                  dataset\n                Document: IG v3.4\n                Item: '6'\n                Section: 4.1.7\n              - Cited Guidance: AP domain codes are therefore four characters long.\n                Document: AP Guide v1.0\n                Section: '2'\nScope:\n  Classes:\n    Include:\n      - ALL\n  Domains:\n    include_split_datasets: true\n    Exclude:\n      - SUPP--\n      - AP--\n",
    "created": "2022-02-06T00:10:58Z",
    "creator": {
        "id": "ff471ff8-f131-4cf5-9712-c79cce6301a1"
    },
    "json": {
        "Check": {
            "any": [
                {
                    "name": "dataset_name",
                    "operator": "shorter_than",
                    "value": 3
                },
                {
                    "name": "dataset_name",
                    "operator": "longer_than",
                    "value": 4
                }
            ]
        },
        "Core": {
            "Id": "CDISC.SDTMIG.CG0017",
            "Version": "1",
            "Status": "Draft"
        },
        "Description": "Split datasets (excluding supplemental qualifiers) is expected to have a have a length of 3 or 4 characters",
        "Outcome": {
            "Message": "Split dataset name is not 3 or 4 characters in length"
        },
        "Rule_Type": "Variable Metadata Check",
        "Sensitivity": "Dataset",
        "Authorities": [
            {
                "Organization": "CDISC",
                "Standards": [
                    {
                        "Name": "SDTMIG",
                        "Version": "3.4",
                        "References": [
                            {
                                "Origin": "SDTM and SDTMIG Conformance Rules",
                                "Rule_Identifier": {
                                    "Id": "CG0017",
                                    "Version": "2"
                                },
                                "Version": "2.0",
                                "Citations": [
                                    {
                                        "Cited_Guidance": "For domains with two-letter domain codes (i.e., other than SUPPxx and RELREC), split dataset names can be up to four characters in length... The four-character dataset-name limitation allows the use of a Supplemental Qualifier dataset associated with the split dataset",
                                        "Document": "IG v3.4",
                                        "Item": "6",
                                        "Section": "4.1.7"
                                    },
                                    {
                                        "Cited_Guidance": "AP domain codes are therefore four characters long.",
                                        "Document": "AP Guide v1.0",
                                        "Section": "2"
                                    }
                                ]
                            }
                        ]
                    }
                ]
            }
        ],
        "Scope": {
            "Classes": {
                "Include": [
                    "ALL"
                ]
            },
            "Domains": {
                "include_split_datasets": true,
                "Exclude": [
                    "SUPP--",
                    "AP--"
                ]
            }
        }
    }
}