{
    "id": "f560ecaa-135e-44db-89f5-109e3c8346e4",
    "changed": "2023-01-24T19:55:04.809Z",
    "content": "Check:\n  all:\n    - name: --PRESP\n      operator: not_exists\n    - name: --REASND\n      operator: exists\nCore:\n  Id: CORE-000030\n  Version: '1'\n  Status: Published\nDescription: Raise and error when --REASND is present in dataset and --PRESP is not\n  present in dataset\nOutcome:\n  Message: --REASND should not be present in dataset when --PRESP is not present in\n    dataset\nRule Type: Record Data\nSensitivity: Dataset\nAuthorities:\n  - Organization: CDISC\n    Standards:\n      - Name: SDTMIG\n        Version: '3.4'\n        References:\n          - Origin: SDTM and SDTMIG Conformance Rules\n            Rule Identifier:\n              Id: CG0053\n              Version: '1'\n            Version: '2.0'\n            Citations:\n              - Cited Guidance: --PRESP[An indication that the event or intervention\n                  was prospectively stated or detailed on the CRF.]|--OCCUR[An indication\n                  as to whether a prespecified event or intervention has occurred.]\n                Document: SDTM v2.0\n                Section: Events|Interventions\n      - Name: SDTMIG\n        Version: '3.3'\n        References:\n          - Origin: SDTM and SDTMIG Conformance Rules\n            Rule Identifier:\n              Id: CG0053\n              Version: '1'\n            Version: '2.0'\n            Citations:\n              - Cited Guidance: (--PRESP/Events) Used to indicate whether the event\n                  describe by --TERM was pre-specified on a CRF. Value is Y for pre-specified\n                  events, null for spontaneously reported events. (--PRESP/Interventions)\n                  Used when a specific intervention is pre-specified on a CRF. Values\n                  should be \"Y\" or null. (--REASND) Used in conjunction with --STAT\n                  when value is NOT DONE\n                Document: SDTM v1.7\n                Section: 2.2.1 (Interventions )|2.2.2 (Events)\n      - Name: SDTMIG\n        Version: '3.2'\n        References:\n          - Origin: SDTM and SDTMIG Conformance Rules\n            Rule Identifier:\n              Id: CG0053\n              Version: '1'\n            Version: '2.0'\n            Citations:\n              - Cited Guidance: (--PRESP/Events) Used to indicate whether the event\n                  describe by --TERM was pre-specified on a CRF. Value is Y for pre-specified\n                  events, null for spontaneously reported events. (--PRESP/Interventions)\n                  Used when a specific intervention is pre-specified on a CRF. Values\n                  should be \"Y\" or null. (--REASND) Used in conjunction with --STAT\n                  when value is NOT DONE\n                Document: SDTM v1.4\n                Section: 2.2.1 (Interventions )|2.2.2 (Events)\nScope:\n  Classes:\n    Include:\n      - EVENTS\n      - INTERVENTIONS\n  Domains:\n    Exclude:\n      - DS\n      - DV\n      - EX\n",
    "created": "2021-09-30T14:19:16Z",
    "creator": {
        "id": "58534b88-88e7-41a5-be67-a4d0742ed999"
    },
    "json": {
        "Check": {
            "all": [
                {
                    "name": "--PRESP",
                    "operator": "not_exists"
                },
                {
                    "name": "--REASND",
                    "operator": "exists"
                }
            ]
        },
        "Core": {
            "Id": "CORE-000030",
            "Version": "1",
            "Status": "Published"
        },
        "Description": "Raise and error when --REASND is present in dataset and --PRESP is not present in dataset",
        "Outcome": {
            "Message": "--REASND should not be present in dataset when --PRESP is not present in dataset"
        },
        "Rule_Type": "Record Data",
        "Sensitivity": "Dataset",
        "Authorities": [
            {
                "Organization": "CDISC",
                "Standards": [
                    {
                        "Name": "SDTMIG",
                        "Version": "3.4",
                        "References": [
                            {
                                "Origin": "SDTM and SDTMIG Conformance Rules",
                                "Rule_Identifier": {
                                    "Id": "CG0053",
                                    "Version": "1"
                                },
                                "Version": "2.0",
                                "Citations": [
                                    {
                                        "Cited_Guidance": "--PRESP[An indication that the event or intervention was prospectively stated or detailed on the CRF.]|--OCCUR[An indication as to whether a prespecified event or intervention has occurred.]",
                                        "Document": "SDTM v2.0",
                                        "Section": "Events|Interventions"
                                    }
                                ]
                            }
                        ]
                    },
                    {
                        "Name": "SDTMIG",
                        "Version": "3.3",
                        "References": [
                            {
                                "Origin": "SDTM and SDTMIG Conformance Rules",
                                "Rule_Identifier": {
                                    "Id": "CG0053",
                                    "Version": "1"
                                },
                                "Version": "2.0",
                                "Citations": [
                                    {
                                        "Cited_Guidance": "(--PRESP/Events) Used to indicate whether the event describe by --TERM was pre-specified on a CRF. Value is Y for pre-specified events, null for spontaneously reported events. (--PRESP/Interventions) Used when a specific intervention is pre-specified on a CRF. Values should be \"Y\" or null. (--REASND) Used in conjunction with --STAT when value is NOT DONE",
                                        "Document": "SDTM v1.7",
                                        "Section": "2.2.1 (Interventions )|2.2.2 (Events)"
                                    }
                                ]
                            }
                        ]
                    },
                    {
                        "Name": "SDTMIG",
                        "Version": "3.2",
                        "References": [
                            {
                                "Origin": "SDTM and SDTMIG Conformance Rules",
                                "Rule_Identifier": {
                                    "Id": "CG0053",
                                    "Version": "1"
                                },
                                "Version": "2.0",
                                "Citations": [
                                    {
                                        "Cited_Guidance": "(--PRESP/Events) Used to indicate whether the event describe by --TERM was pre-specified on a CRF. Value is Y for pre-specified events, null for spontaneously reported events. (--PRESP/Interventions) Used when a specific intervention is pre-specified on a CRF. Values should be \"Y\" or null. (--REASND) Used in conjunction with --STAT when value is NOT DONE",
                                        "Document": "SDTM v1.4",
                                        "Section": "2.2.1 (Interventions )|2.2.2 (Events)"
                                    }
                                ]
                            }
                        ]
                    }
                ]
            }
        ],
        "Scope": {
            "Classes": {
                "Include": [
                    "EVENTS",
                    "INTERVENTIONS"
                ]
            },
            "Domains": {
                "Exclude": [
                    "DS",
                    "DV",
                    "EX"
                ]
            }
        }
    }
}