{
    "id": "e2e25146-d4b5-43e4-80e3-cec8f3ca136d",
    "changed": "2022-07-31T09:12:39Z",
    "content": "Check:\n  all:\n    - name: dataset_name\n      operator: longer_than\n      value: 8\nCore:\n  Id: CDISC.SDTMIG.CG0018\n  Version: '1'\n  Status: Draft\nDescription: When a supplemental qualifier dataset is associated with a split dataset,\n  the dataset name length must not be greater than 8 characters.\nOutcome:\n  Message: Supplemental qualifier dataset associated with a split dataset is greater\n    than 8 characters in length\nRule Type: Dataset Metadata Check\nSensitivity: Dataset\nAuthorities:\n  - Organization: CDISC\n    Standards:\n      - Name: SDTMIG\n        Version: '3.4'\n        References:\n          - Origin: SDTM and SDTMIG Conformance Rules\n            Rule Identifier:\n              Id: CG0018\n              Version: '1'\n            Version: '2.0'\n            Citations:\n              - Cited Guidance: Supplemental Qualifier datasets for split domains\n                  would also be split. The nomenclature would include the additional\n                  one-to-two characters used to identify the split dataset.\n                Document: IG v3.4\n                Item: '7'\n                Section: 4.1.7\nScope:\n  Classes:\n    Include:\n      - ALL\n  Domains:\n    include_split_datasets: true\n    Include:\n      - SUPP--\n",
    "created": "2021-11-06T04:43:42Z",
    "creator": {
        "id": "ff471ff8-f131-4cf5-9712-c79cce6301a1"
    },
    "json": {
        "Check": {
            "all": [
                {
                    "name": "dataset_name",
                    "operator": "longer_than",
                    "value": 8
                }
            ]
        },
        "Core": {
            "Id": "CDISC.SDTMIG.CG0018",
            "Version": "1",
            "Status": "Draft"
        },
        "Description": "When a supplemental qualifier dataset is associated with a split dataset, the dataset name length must not be greater than 8 characters.",
        "Outcome": {
            "Message": "Supplemental qualifier dataset associated with a split dataset is greater than 8 characters in length"
        },
        "Rule_Type": "Dataset Metadata Check",
        "Sensitivity": "Dataset",
        "Authorities": [
            {
                "Organization": "CDISC",
                "Standards": [
                    {
                        "Name": "SDTMIG",
                        "Version": "3.4",
                        "References": [
                            {
                                "Origin": "SDTM and SDTMIG Conformance Rules",
                                "Rule_Identifier": {
                                    "Id": "CG0018",
                                    "Version": "1"
                                },
                                "Version": "2.0",
                                "Citations": [
                                    {
                                        "Cited_Guidance": "Supplemental Qualifier datasets for split domains would also be split. The nomenclature would include the additional one-to-two characters used to identify the split dataset.",
                                        "Document": "IG v3.4",
                                        "Item": "7",
                                        "Section": "4.1.7"
                                    }
                                ]
                            }
                        ]
                    }
                ]
            }
        ],
        "Scope": {
            "Classes": {
                "Include": [
                    "ALL"
                ]
            },
            "Domains": {
                "include_split_datasets": true,
                "Include": [
                    "SUPP--"
                ]
            }
        }
    }
}