{
    "id": "8e4ce5f6-5d7d-420c-887d-26c09b89b793",
    "changed": "2022-12-02T16:10:42.162Z",
    "content": "Check:\n  all:\n    - name: --TPTREF\n      operator: empty\n    - name: --ELTM\n      operator: non_empty\nCore:\n  Id: CORE-000028\n  Version: '1'\n  Status: Published\nDescription: Raise an error when --TPTREF is empty, but --ELTM is not empty\nOutcome:\n  Message: --TPTREF is empty and --ELTM is not empty\n  Output Variables:\n    - --TPTREF\n    - --ELTM\nRule Type: Record Data\nSensitivity: Record\nAuthorities:\n  - Organization: CDISC\n    Standards:\n      - Name: SDTMIG\n        Version: '3.4'\n        References:\n          - Origin: SDTM and SDTMIG Conformance Rules\n            Rule Identifier:\n              Id: CG0008\n              Version: '1'\n            Version: '2.0'\n            Citations:\n              - Cited Guidance: The interval of time between a planned time point\n                  and a fixed reference point, represented in a standardized character\n                  format. The fixed reference point is in --TPTREF.\n                Document: SDTM Model v2.0\n                Item: --ELTM\n                Section: Timing\n      - Name: SDTMIG\n        Version: '3.3'\n        References:\n          - Origin: SDTM and SDTMIG Conformance Rules\n            Rule Identifier:\n              Id: CG0008\n              Version: '1'\n            Version: '2.0'\n            Citations:\n              - Cited Guidance: Planned Elapsed time relative to a planned fixed reference\n                  (--TPTREF) such as \"Previous Dose\" or \"Previous Meal\". This variable\n                  is useful where there are repetitive measures. Not a clock time\n                  or a date/time variable, but an interval.   Format=ISO8601\n                Document: SDTM Model v1.7\n                Item: Table 2.2.5, --ELTM\n                Section: 2.2.5\n      - Name: SDTMIG\n        Version: '3.2'\n        References:\n          - Origin: SDTM and SDTMIG Conformance Rules\n            Rule Identifier:\n              Id: CG0008\n              Version: '1'\n            Version: '2.0'\n            Citations:\n              - Cited Guidance: Planned Elapsed time in ISO 8601 character format\n                  relative to a planned fixed reference (--TPTREF) such as \"Previous\n                  Dose\" or \"Previous Meal\".\n                Document: SDTM Model v1.4\n                Item: Table 2.2.5, --ELTM\n                Section: 2.2.5\nScope:\n  Classes:\n    Include:\n      - ALL\n  Domains:\n    Include:\n      - ALL\n",
    "created": "2021-09-29T22:40:39Z",
    "creator": {
        "id": "e7bbd139-9a5c-4b86-859e-e4854e7724fe"
    },
    "json": {
        "Check": {
            "all": [
                {
                    "name": "--TPTREF",
                    "operator": "empty"
                },
                {
                    "name": "--ELTM",
                    "operator": "non_empty"
                }
            ]
        },
        "Core": {
            "Id": "CORE-000028",
            "Version": "1",
            "Status": "Published"
        },
        "Description": "Raise an error when --TPTREF is empty, but --ELTM is not empty",
        "Outcome": {
            "Message": "--TPTREF is empty and --ELTM is not empty",
            "Output_Variables": [
                "--TPTREF",
                "--ELTM"
            ]
        },
        "Rule_Type": "Record Data",
        "Sensitivity": "Record",
        "Authorities": [
            {
                "Organization": "CDISC",
                "Standards": [
                    {
                        "Name": "SDTMIG",
                        "Version": "3.4",
                        "References": [
                            {
                                "Origin": "SDTM and SDTMIG Conformance Rules",
                                "Rule_Identifier": {
                                    "Id": "CG0008",
                                    "Version": "1"
                                },
                                "Version": "2.0",
                                "Citations": [
                                    {
                                        "Cited_Guidance": "The interval of time between a planned time point and a fixed reference point, represented in a standardized character format. The fixed reference point is in --TPTREF.",
                                        "Document": "SDTM Model v2.0",
                                        "Item": "--ELTM",
                                        "Section": "Timing"
                                    }
                                ]
                            }
                        ]
                    },
                    {
                        "Name": "SDTMIG",
                        "Version": "3.3",
                        "References": [
                            {
                                "Origin": "SDTM and SDTMIG Conformance Rules",
                                "Rule_Identifier": {
                                    "Id": "CG0008",
                                    "Version": "1"
                                },
                                "Version": "2.0",
                                "Citations": [
                                    {
                                        "Cited_Guidance": "Planned Elapsed time relative to a planned fixed reference (--TPTREF) such as \"Previous Dose\" or \"Previous Meal\". This variable is useful where there are repetitive measures. Not a clock time or a date/time variable, but an interval.   Format=ISO8601",
                                        "Document": "SDTM Model v1.7",
                                        "Item": "Table 2.2.5, --ELTM",
                                        "Section": "2.2.5"
                                    }
                                ]
                            }
                        ]
                    },
                    {
                        "Name": "SDTMIG",
                        "Version": "3.2",
                        "References": [
                            {
                                "Origin": "SDTM and SDTMIG Conformance Rules",
                                "Rule_Identifier": {
                                    "Id": "CG0008",
                                    "Version": "1"
                                },
                                "Version": "2.0",
                                "Citations": [
                                    {
                                        "Cited_Guidance": "Planned Elapsed time in ISO 8601 character format relative to a planned fixed reference (--TPTREF) such as \"Previous Dose\" or \"Previous Meal\".",
                                        "Document": "SDTM Model v1.4",
                                        "Item": "Table 2.2.5, --ELTM",
                                        "Section": "2.2.5"
                                    }
                                ]
                            }
                        ]
                    }
                ]
            }
        ],
        "Scope": {
            "Classes": {
                "Include": [
                    "ALL"
                ]
            },
            "Domains": {
                "Include": [
                    "ALL"
                ]
            }
        }
    }
}