{
    "id": "e371c255-1a1f-4a7f-8470-e8ccd851ccef",
    "changed": "2023-02-07T20:22:07.252Z",
    "content": "Check:\n  all:\n    - name: --RFTDTC\n      operator: exists\n    - name: --TPTREF\n      operator: not_exists\nCore:\n  Id: CORE-000165\n  Version: '1'\n  Status: Published\nDescription: Raise an error when --TPTREF is not present in dataset when --RFTDTC\n  is present.\nOutcome:\n  Message: --TPTREF is not present when --RFTDTC is present in a dataset\n  Output Variables:\n    - --RFTDTC\n    - --TPTREF\nRule Type: Record Data\nSensitivity: Dataset\nAuthorities:\n  - Organization: CDISC\n    Standards:\n      - Name: SDTMIG\n        Version: '3.4'\n        References:\n          - Origin: SDTM and SDTMIG Conformance Rules\n            Rule Identifier:\n              Id: CG0090\n              Version: '1'\n            Version: '2.0'\n            Citations:\n              - Cited Guidance: '\"The actual date or date and time of a time point\n                  that acts as a fixed reference for a series of planned time points,\n                  represented in a standardized character format. The fixed reference\n                  point is in --TPTREF\"'\n                Document: Model v2.0\n                Section: Timing\n      - Name: SDTMIG\n        Version: '3.3'\n        References:\n          - Origin: SDTM and SDTMIG Conformance Rules\n            Rule Identifier:\n              Id: CG0090\n              Version: '1'\n            Version: '2.0'\n            Citations:\n              - Cited Guidance: '\"Date/time for a fixed reference time point defined by --TPTREF.\"'\n                Document: Model v1.7\n                Section: 2.2.5 Timing Variables for All Classes\n                Item: Table 2.2.5.1 --RFTDTC \n      - Name: SDTMIG\n        Version: '3.2'\n        References:\n          - Origin: SDTM and SDTMIG Conformance Rules\n            Rule Identifier:\n              Id: CG0090\n              Version: '1'\n            Version: '2.0'\n            Citations:\n              - Cited Guidance: '\"(--RFTDTC) Date/time for a fixed reference time point defined by --TPTREF in ISO 8601 character format.\"'\n                Document: Model v1.4\n                Section: 2.2.5 Timing Variables for All Classes\n                Item: Specification \nScope:\n  Classes:\n    Include:\n      - ALL\n  Domains:\n    Include:\n      - ALL\n",
    "created": "2021-10-19T11:55:52Z",
    "creator": {
        "id": "57474fac-237e-4693-bb37-7826b02737da"
    },
    "json": {
        "Check": {
            "all": [
                {
                    "name": "--RFTDTC",
                    "operator": "exists"
                },
                {
                    "name": "--TPTREF",
                    "operator": "not_exists"
                }
            ]
        },
        "Core": {
            "Id": "CORE-000165",
            "Version": "1",
            "Status": "Published"
        },
        "Description": "Raise an error when --TPTREF is not present in dataset when --RFTDTC is present.",
        "Outcome": {
            "Message": "--TPTREF is not present when --RFTDTC is present in a dataset",
            "Output_Variables": [
                "--RFTDTC",
                "--TPTREF"
            ]
        },
        "Sensitivity": "Dataset",
        "Authorities": [
            {
                "Organization": "CDISC",
                "Standards": [
                    {
                        "Name": "SDTMIG",
                        "Version": "3.4",
                        "References": [
                            {
                                "Origin": "SDTM and SDTMIG Conformance Rules",
                                "Version": "2.0",
                                "Citations": [
                                    {
                                        "Document": "Model v2.0",
                                        "Section": "Timing",
                                        "Cited_Guidance": "\"The actual date or date and time of a time point that acts as a fixed reference for a series of planned time points, represented in a standardized character format. The fixed reference point is in --TPTREF\""
                                    }
                                ],
                                "Rule_Identifier": {
                                    "Id": "CG0090",
                                    "Version": "1"
                                }
                            }
                        ]
                    },
                    {
                        "Name": "SDTMIG",
                        "Version": "3.3",
                        "References": [
                            {
                                "Origin": "SDTM and SDTMIG Conformance Rules",
                                "Version": "2.0",
                                "Citations": [
                                    {
                                        "Document": "Model v1.7",
                                        "Section": "2.2.5 Timing Variables for All Classes",
                                        "Item": "Table 2.2.5.1 --RFTDTC",
                                        "Cited_Guidance": "\"Date/time for a fixed reference time point defined by --TPTREF.\""
                                    }
                                ],
                                "Rule_Identifier": {
                                    "Id": "CG0090",
                                    "Version": "1"
                                }
                            }
                        ]
                    },
                    {
                        "Name": "SDTMIG",
                        "Version": "3.2",
                        "References": [
                            {
                                "Origin": "SDTM and SDTMIG Conformance Rules",
                                "Version": "2.0",
                                "Citations": [
                                    {
                                        "Document": "Model v1.4",
                                        "Section": "2.2.5 Timing Variables for All Classes",
                                        "Item": "Specification",
                                        "Cited_Guidance": "\"(--RFTDTC) Date/time for a fixed reference time point defined by --TPTREF in ISO 8601 character format.\""
                                    }
                                ],
                                "Rule_Identifier": {
                                    "Id": "CG0090",
                                    "Version": "1"
                                }
                            }
                        ]
                    }
                ]
            }
        ],
        "Scope": {
            "Classes": {
                "Include": [
                    "ALL"
                ]
            },
            "Domains": {
                "Include": [
                    "ALL"
                ]
            }
        },
        "Rule_Type": "Record Data"
    }
}