{
    "id": "1fcf500c-48ad-47fe-80f7-d74b7d5f7039",
    "changed": "2022-12-02T12:57:46.353Z",
    "content": "Check:\n  all:\n    - name: --PTCD\n      operator: is_not_unique_relationship\n      value: --DECOD\nCore:\n  Id: CDISC.SDTMIG.CG0049\n  Version: '1'\n  Status: Draft\nDescription: Trigger error when --DECOD and --PTCD do not have a one-to-one relationship\nOutcome:\n  Message: --DECOD and --PTCD do not have a one-to-one relationship\n  Output Variables:\n    - --PTCD\n    - --DECOD\nRule Type: Record Data\nSensitivity: Domain\nAuthorities:\n  - Organization: CDISC\n    Standards:\n      - Name: SDTMIG\n        Version: '3.4'\n        References:\n          - Origin: SDTM and SDTMIG Conformance Rules\n            Rule Identifier:\n              Id: CG0049\n              Version: '1'\n            Version: '2.0'\n            Citations:\n              - Cited Guidance: Standardized or dictionary-derived text for the description\n                  of an event or intervention. Equivalent to the Preferred Term (PT\n                  in MedDRA).\n                Document: Model v2.0\n                Item: --DECOD\n                Section: Events\n              - Cited Guidance: The preferred term code assigned to the event from\n                  MedDRA.\n                Document: Model v2.0\n                Item: --PTCD\n                Section: Events\nScope:\n  Classes:\n    Include:\n      - EVENTS\n  Domains:\n    Include:\n      - ALL\n",
    "created": "2021-11-06T07:01:58Z",
    "creator": {
        "id": "ff471ff8-f131-4cf5-9712-c79cce6301a1"
    },
    "json": {
        "Check": {
            "all": [
                {
                    "name": "--PTCD",
                    "operator": "is_not_unique_relationship",
                    "value": "--DECOD"
                }
            ]
        },
        "Core": {
            "Id": "CDISC.SDTMIG.CG0049",
            "Version": "1",
            "Status": "Draft"
        },
        "Description": "Trigger error when --DECOD and --PTCD do not have a one-to-one relationship",
        "Outcome": {
            "Message": "--DECOD and --PTCD do not have a one-to-one relationship",
            "Output_Variables": [
                "--PTCD",
                "--DECOD"
            ]
        },
        "Rule_Type": "Record Data",
        "Sensitivity": "Domain",
        "Authorities": [
            {
                "Organization": "CDISC",
                "Standards": [
                    {
                        "Name": "SDTMIG",
                        "Version": "3.4",
                        "References": [
                            {
                                "Origin": "SDTM and SDTMIG Conformance Rules",
                                "Rule_Identifier": {
                                    "Id": "CG0049",
                                    "Version": "1"
                                },
                                "Version": "2.0",
                                "Citations": [
                                    {
                                        "Cited_Guidance": "Standardized or dictionary-derived text for the description of an event or intervention. Equivalent to the Preferred Term (PT in MedDRA).",
                                        "Document": "Model v2.0",
                                        "Item": "--DECOD",
                                        "Section": "Events"
                                    },
                                    {
                                        "Cited_Guidance": "The preferred term code assigned to the event from MedDRA.",
                                        "Document": "Model v2.0",
                                        "Item": "--PTCD",
                                        "Section": "Events"
                                    }
                                ]
                            }
                        ]
                    }
                ]
            }
        ],
        "Scope": {
            "Classes": {
                "Include": [
                    "EVENTS"
                ]
            },
            "Domains": {
                "Include": [
                    "ALL"
                ]
            }
        }
    }
}