{
    "id": "a992707e-91d9-40ea-a8e9-a22b5eeb3afa",
    "changed": "2022-12-09T15:51:15.916Z",
    "content": "Check:\n  all:\n    - name: --SCAT\n      operator: non_empty\n    - name: --SCAT\n      operator: equal_to\n      value: --CAT\nCore:\n  Id: CORE-000237\n  Version: '1'\n  Status: Published\nDescription: Trigger error when --SCAT is not null and --SCAT is equal to --CAT\nOutcome:\n  Message: --SCAT is equal to --CAT\n  Output Variables:\n    - --CAT\n    - --SCAT\nRule Type: Record Data\nSensitivity: Record\nAuthorities:\n  - Organization: CDISC\n    Standards:\n      - Name: SDTMIG\n        Version: '3.4'\n        References:\n          - Origin: SDTM and SDTMIG Conformance Rules\n            Rule Identifier:\n              Id: CG0027\n              Version: '1'\n            Version: '2.0'\n            Citations:\n              - Cited Guidance: A further grouping or classification of the category\n                  for the topic of the finding, event, or intervention. The category\n                  is in --CAT.\n                Document: Model v2.0\n                Item: --SCAT\n                Section: Interventions\n      - Name: SDTMIG\n        Version: '3.3'\n        References:\n          - Origin: SDTM and SDTMIG Conformance Rules\n            Rule Identifier:\n              Id: CG0027\n              Version: '1'\n            Version: '2.0'\n            Citations:\n              - Cited Guidance: Used to define a further categorization of --CAT values.\n                Document: Model v1.7\n                Item: --SCAT\n                Section: 2.2.1\n      - Name: SDTMIG\n        Version: '3.2'\n        References:\n          - Origin: SDTM and SDTMIG Conformance Rules\n            Rule Identifier:\n              Id: CG0027\n              Version: '1'\n            Version: '2.0'\n            Citations:\n              - Cited Guidance: Used to define a further categorization of --CAT values.\n                Document: Model v1.4\n                Item: Table 2.2.1, --SCAT\n                Section: 2.2.1\nScope:\n  Classes:\n    Include:\n      - ALL\n  Domains:\n    Include:\n      - ALL\n",
    "created": "2022-02-05T05:33:28Z",
    "creator": {
        "id": "ff471ff8-f131-4cf5-9712-c79cce6301a1"
    },
    "json": {
        "Check": {
            "all": [
                {
                    "name": "--SCAT",
                    "operator": "non_empty"
                },
                {
                    "name": "--SCAT",
                    "operator": "equal_to",
                    "value": "--CAT"
                }
            ]
        },
        "Core": {
            "Id": "CORE-000237",
            "Version": "1",
            "Status": "Published"
        },
        "Description": "Trigger error when --SCAT is not null and --SCAT is equal to --CAT",
        "Outcome": {
            "Message": "--SCAT is equal to --CAT",
            "Output_Variables": [
                "--CAT",
                "--SCAT"
            ]
        },
        "Rule_Type": "Record Data",
        "Sensitivity": "Record",
        "Authorities": [
            {
                "Organization": "CDISC",
                "Standards": [
                    {
                        "Name": "SDTMIG",
                        "Version": "3.4",
                        "References": [
                            {
                                "Origin": "SDTM and SDTMIG Conformance Rules",
                                "Rule_Identifier": {
                                    "Id": "CG0027",
                                    "Version": "1"
                                },
                                "Version": "2.0",
                                "Citations": [
                                    {
                                        "Cited_Guidance": "A further grouping or classification of the category for the topic of the finding, event, or intervention. The category is in --CAT.",
                                        "Document": "Model v2.0",
                                        "Item": "--SCAT",
                                        "Section": "Interventions"
                                    }
                                ]
                            }
                        ]
                    },
                    {
                        "Name": "SDTMIG",
                        "Version": "3.3",
                        "References": [
                            {
                                "Origin": "SDTM and SDTMIG Conformance Rules",
                                "Rule_Identifier": {
                                    "Id": "CG0027",
                                    "Version": "1"
                                },
                                "Version": "2.0",
                                "Citations": [
                                    {
                                        "Cited_Guidance": "Used to define a further categorization of --CAT values.",
                                        "Document": "Model v1.7",
                                        "Item": "--SCAT",
                                        "Section": "2.2.1"
                                    }
                                ]
                            }
                        ]
                    },
                    {
                        "Name": "SDTMIG",
                        "Version": "3.2",
                        "References": [
                            {
                                "Origin": "SDTM and SDTMIG Conformance Rules",
                                "Rule_Identifier": {
                                    "Id": "CG0027",
                                    "Version": "1"
                                },
                                "Version": "2.0",
                                "Citations": [
                                    {
                                        "Cited_Guidance": "Used to define a further categorization of --CAT values.",
                                        "Document": "Model v1.4",
                                        "Item": "Table 2.2.1, --SCAT",
                                        "Section": "2.2.1"
                                    }
                                ]
                            }
                        ]
                    }
                ]
            }
        ],
        "Scope": {
            "Classes": {
                "Include": [
                    "ALL"
                ]
            },
            "Domains": {
                "Include": [
                    "ALL"
                ]
            }
        }
    }
}