{
    "id": "96a3315b-0ff8-4b73-976c-ba433831ab25",
    "changed": "2022-06-22T15:32:06Z",
    "content": "Check:\n  all:\n    - name: --BODSYS\n      operator: not_equal_to\n      value: --SOC\nCore:\n  Id: CDISC.SDTMIG.CG0039\n  Version: '1'\n  Status: Draft\nDescription: Raise an error if primary SOC is used for analysis and -BODSYS is not\n  equal to -SOC\nOutcome:\n  Message: Primary analysis used but --BODSYS and --SOC are not equal\n  Output Variables:\n    - --TERM\n    - --BODSYS\n    - --SOC\nRule Type: Record Data\nSensitivity: Record\nAuthorities:\n  - Organization: CDISC\n    Standards:\n      - Name: SDTMIG\n        Version: '3.4'\n        References:\n          - Origin: SDTM and SDTMIG Conformance Rules\n            Rule Identifier:\n              Id: CG0039\n              Version: '1'\n            Version: '2.0'\n            Citations:\n              - Cited Guidance: Dictionary derived. Body system or organ class used\n                  by the sponsor from the coding dictionary (e.g., MedDRA). When using\n                  a multi-axial dictionary such as MedDRA, this should contain the\n                  SOC used for the sponsor's analyses and summary tables which may\n                  not necessarily be the primary SOC.\n                Document: SDTMIG v3.4\n                Section: 6.2.1\n              - Cited Guidance: Body system or system organ class assigned for analysis\n                  from a standard hierarchy (e.g. MedDRA) associated with an event.\n                Document: Model v2.0\n                Section: Events\nScope:\n  Classes:\n    Include:\n      - EVENTS\n  Domains:\n    Exclude:\n      - DS\n      - DV\n      - HO\n",
    "created": "2021-10-07T14:22:16Z",
    "creator": {
        "id": "1c66dcb2-42dc-4edc-a938-0267a0dc6cac"
    },
    "json": {
        "Check": {
            "all": [
                {
                    "name": "--BODSYS",
                    "operator": "not_equal_to",
                    "value": "--SOC"
                }
            ]
        },
        "Core": {
            "Id": "CDISC.SDTMIG.CG0039",
            "Version": "1",
            "Status": "Draft"
        },
        "Description": "Raise an error if primary SOC is used for analysis and -BODSYS is not equal to -SOC",
        "Outcome": {
            "Message": "Primary analysis used but --BODSYS and --SOC are not equal",
            "Output_Variables": [
                "--TERM",
                "--BODSYS",
                "--SOC"
            ]
        },
        "Rule_Type": "Record Data",
        "Sensitivity": "Record",
        "Authorities": [
            {
                "Organization": "CDISC",
                "Standards": [
                    {
                        "Name": "SDTMIG",
                        "Version": "3.4",
                        "References": [
                            {
                                "Origin": "SDTM and SDTMIG Conformance Rules",
                                "Rule_Identifier": {
                                    "Id": "CG0039",
                                    "Version": "1"
                                },
                                "Version": "2.0",
                                "Citations": [
                                    {
                                        "Cited_Guidance": "Dictionary derived. Body system or organ class used by the sponsor from the coding dictionary (e.g., MedDRA). When using a multi-axial dictionary such as MedDRA, this should contain the SOC used for the sponsor's analyses and summary tables which may not necessarily be the primary SOC.",
                                        "Document": "SDTMIG v3.4",
                                        "Section": "6.2.1"
                                    },
                                    {
                                        "Cited_Guidance": "Body system or system organ class assigned for analysis from a standard hierarchy (e.g. MedDRA) associated with an event.",
                                        "Document": "Model v2.0",
                                        "Section": "Events"
                                    }
                                ]
                            }
                        ]
                    }
                ]
            }
        ],
        "Scope": {
            "Classes": {
                "Include": [
                    "EVENTS"
                ]
            },
            "Domains": {
                "Exclude": [
                    "DS",
                    "DV",
                    "HO"
                ]
            }
        }
    }
}