{
    "id": "80b4b95b-7298-4efb-839e-95c69c414d3c",
    "changed": "2022-12-13T18:56:34.720Z",
    "content": "Check:\n  all:\n    - name: VISITNUM\n      operator: non_empty\n    - domain: is_not_contained_by\n      name: VISTNUM\n      operator: get_dataset\n      value:\n        Target: VISITNUM\n        comparator: $tv_visitnum\n    - domain: not_equal_to\n      operator: get_dataset\n      value:\n        Target: SVUPRES\n        comparator: $tv_svupres\nCoreId: CORE-CG0033 - duplicate do not use\nDescription: Verify that visitnum is planned and exists in TV\nOperations:\n  - domain: TV\n    id: $tv_visitnum\n    name: VISITNUM\n    operator: distinct\n  - domain: SV\n    id: $sv_svpressp = 'Y'\n    name: VISITNUM\n    operator: distinct\nOutcome:\n  Message: Planned Visit Value cannot be found Trial Visit (TV) domain\nRule Type: Record Data\nSensitivity: Record\nVersion: '1'\nAuthorities:\n  - Organization: CDISC\n    Standards:\n      - Name: SDTMIG\n        Version: '3.4'\n        References:\n          - Origin: SDTM and SDTMIG Conformance Rules\n            Rule Identifier:\n              Id: CG0033\n            Version: '2.0'\n            Citations:\n              - Cited Guidance: For planned visits, values of VISIT, VISITNUM, and\n                  VISITDY must be those defined in the Trial Visits (TV) dataset (Section\n                  7.3.1, Trial Visits).\n                Document: IG v3.4\n                Item:\n                Section: 4.4.5\nScope:\n  Classes:\n    Include:\n      - ALL\n  Domains:\n    Include:\n      - ALL\nCore:\n  Status: Draft\n",
    "created": "2021-12-09T12:09:29Z",
    "creator": {
        "id": "57474fac-237e-4693-bb37-7826b02737da"
    },
    "json": {
        "Check": {
            "all": [
                {
                    "name": "VISITNUM",
                    "operator": "non_empty"
                },
                {
                    "domain": "is_not_contained_by",
                    "name": "VISTNUM",
                    "operator": "get_dataset",
                    "value": {
                        "Target": "VISITNUM",
                        "comparator": "$tv_visitnum"
                    }
                },
                {
                    "domain": "not_equal_to",
                    "operator": "get_dataset",
                    "value": {
                        "Target": "SVUPRES",
                        "comparator": "$tv_svupres"
                    }
                }
            ]
        },
        "CoreId": "CORE-CG0033 - duplicate do not use",
        "Description": "Verify that visitnum is planned and exists in TV",
        "Operations": [
            {
                "domain": "TV",
                "id": "$tv_visitnum",
                "name": "VISITNUM",
                "operator": "distinct"
            },
            {
                "domain": "SV",
                "id": "$sv_svpressp = 'Y'",
                "name": "VISITNUM",
                "operator": "distinct"
            }
        ],
        "Outcome": {
            "Message": "Planned Visit Value cannot be found Trial Visit (TV) domain"
        },
        "Rule_Type": "Record Data",
        "Sensitivity": "Record",
        "Version": "1",
        "Authorities": [
            {
                "Organization": "CDISC",
                "Standards": [
                    {
                        "Name": "SDTMIG",
                        "Version": "3.4",
                        "References": [
                            {
                                "Origin": "SDTM and SDTMIG Conformance Rules",
                                "Rule_Identifier": {
                                    "Id": "CG0033"
                                },
                                "Version": "2.0",
                                "Citations": [
                                    {
                                        "Cited_Guidance": "For planned visits, values of VISIT, VISITNUM, and VISITDY must be those defined in the Trial Visits (TV) dataset (Section 7.3.1, Trial Visits).",
                                        "Document": "IG v3.4",
                                        "Item": null,
                                        "Section": "4.4.5"
                                    }
                                ]
                            }
                        ]
                    }
                ]
            }
        ],
        "Scope": {
            "Classes": {
                "Include": [
                    "ALL"
                ]
            },
            "Domains": {
                "Include": [
                    "ALL"
                ]
            }
        },
        "Core": {
            "Status": "Draft"
        }
    }
}