{
    "id": "4a2a24d5-00bb-40a9-a3c5-5d818e4f473c",
    "changed": "2023-03-02T21:09:23.022Z",
    "content": "Check:\n  all:\n    - name: --ENTPT\n      operator: exists\n    - name: --ENRTPT\n      operator: not_exists\nCore:\n  Id: CORE-000084\n  Version: '1'\n  Status: Published\nDescription: Raise an error when --ENTPT exists in a dataset and --ENRTPT does not\n  exist.\nOutcome:\n  Message: --ENTPT exists in a dataset, but --ENRTPT does not exist.\n  Output Variables:\n    - --ENTPT\nRule Type: Record Data\nSensitivity: Dataset\nExecutability: \nAuthorities:\n  - Organization: CDISC\n    Standards:\n      - Name: SDTMIG\n        Version: '3.4'\n        References:\n          - Origin: SDTM and SDTMIG Conformance Rules\n            Rule Identifier:\n              Id: CG0057\n              Version: '1'\n            Version: '2.0'\n            Citations:\n              - Cited Guidance: The characterization of the end of an observation\n                  relative to a reference time point. The sponsor-defined reference\n                  time point is in --ENTPT.\n                Document: Model v2.0\n                Section: Timing\n                Item: --ENRTPT\n      - Name: SDTMIG\n        Version: '3.3'\n        References:\n          - Origin: SDTM and SDTMIG Conformance Rules\n            Rule Identifier:\n              Id: CG0057\n              Version: '1'\n            Version: '2.0'\n            Citations:\n              - Cited Guidance: Identifies the end of the observation as being before\n                  or after the sponsor-defined reference time point defined by variable\n                  --ENTPT.\n                Document: Model v1.7\n                Section: 2.2.5 Timing Variables for All Classes\n                Item: Table 2.2.5.1 --ENRTPT\n      - Name: SDTMIG\n        Version: '3.2'\n        References:\n          - Origin: SDTM and SDTMIG Conformance Rules\n            Rule Identifier:\n              Id: CG0057\n              Version: '1'\n            Version: '2.0'\n            Citations:\n              - Cited Guidance: (--ENRTPT) Identifies the end of the observation as\n                  being before or after the sponsor-defined reference time point defined\n                  by variable --ENTPT.\n                Document: Model v1.4\n                Section: 2.2.5 Timing Variables for All Classes\n                Item: Specification\nScope:\n  Classes:\n    Include:\n      - ALL\n  Domains:\n    Include:\n      - ALL\n",
    "created": "2021-10-05T18:38:29Z",
    "creator": {
        "id": "ae6dbbf3-4c9a-4149-b596-8183766167d4"
    },
    "json": {
        "Check": {
            "all": [
                {
                    "name": "--ENTPT",
                    "operator": "exists"
                },
                {
                    "name": "--ENRTPT",
                    "operator": "not_exists"
                }
            ]
        },
        "Core": {
            "Id": "CORE-000084",
            "Version": "1",
            "Status": "Published"
        },
        "Description": "Raise an error when --ENTPT exists in a dataset and --ENRTPT does not exist.",
        "Outcome": {
            "Message": "--ENTPT exists in a dataset, but --ENRTPT does not exist.",
            "Output_Variables": [
                "--ENTPT"
            ]
        },
        "Sensitivity": "Dataset",
        "Executability": null,
        "Authorities": [
            {
                "Organization": "CDISC",
                "Standards": [
                    {
                        "Name": "SDTMIG",
                        "Version": "3.4",
                        "References": [
                            {
                                "Origin": "SDTM and SDTMIG Conformance Rules",
                                "Version": "2.0",
                                "Citations": [
                                    {
                                        "Document": "Model v2.0",
                                        "Section": "Timing",
                                        "Item": "--ENRTPT",
                                        "Cited_Guidance": "The characterization of the end of an observation relative to a reference time point. The sponsor-defined reference time point is in --ENTPT."
                                    }
                                ],
                                "Rule_Identifier": {
                                    "Id": "CG0057",
                                    "Version": "1"
                                }
                            }
                        ]
                    },
                    {
                        "Name": "SDTMIG",
                        "Version": "3.3",
                        "References": [
                            {
                                "Origin": "SDTM and SDTMIG Conformance Rules",
                                "Version": "2.0",
                                "Citations": [
                                    {
                                        "Document": "Model v1.7",
                                        "Section": "2.2.5 Timing Variables for All Classes",
                                        "Item": "Table 2.2.5.1 --ENRTPT",
                                        "Cited_Guidance": "Identifies the end of the observation as being before or after the sponsor-defined reference time point defined by variable --ENTPT."
                                    }
                                ],
                                "Rule_Identifier": {
                                    "Id": "CG0057",
                                    "Version": "1"
                                }
                            }
                        ]
                    },
                    {
                        "Name": "SDTMIG",
                        "Version": "3.2",
                        "References": [
                            {
                                "Origin": "SDTM and SDTMIG Conformance Rules",
                                "Version": "2.0",
                                "Citations": [
                                    {
                                        "Document": "Model v1.4",
                                        "Section": "2.2.5 Timing Variables for All Classes",
                                        "Item": "Specification",
                                        "Cited_Guidance": "(--ENRTPT) Identifies the end of the observation as being before or after the sponsor-defined reference time point defined by variable --ENTPT."
                                    }
                                ],
                                "Rule_Identifier": {
                                    "Id": "CG0057",
                                    "Version": "1"
                                }
                            }
                        ]
                    }
                ]
            }
        ],
        "Scope": {
            "Classes": {
                "Include": [
                    "ALL"
                ]
            },
            "Domains": {
                "Include": [
                    "ALL"
                ]
            }
        },
        "Rule_Type": "Record Data"
    }
}