{
    "id": "6962ab00-18f7-4037-b5d4-3eb32cfe17a5",
    "changed": "2022-03-10T13:03:30Z",
    "content": "Check:\n  all:\n    - name: --OCCUR\n      operator: non_empty\n    - name: --PRESP\n      operator: not_equal_to\n      value: Y\nCore:\n  Id: CORE-000016\n  Version: '1'\n  Status: Published\nDescription: Raise an error when --OCCUR is not empty and --PRESP is not equal to\n  \"Y\".\nOutcome:\n  Message: --PRESP should be populated as \"Y\" when --OCCUR is provided.\n  Output Variables:\n    - --PRESP\n    - --OCCUR\nRule Type: Record Data\nSensitivity: Dataset\nAuthorities:\n  - Organization: CDISC\n    Standards:\n      - Name: SDTMIG\n        Version: '3.4'\n        References:\n          - Origin: SDTM and SDTMIG Conformance Rules\n            Rule Identifier:\n              Id: CG0089\n              Version: '1'\n            Version: '2.0'\n            Citations:\n              - Cited Guidance: Events[--PRESP][An indication that the event was prospectively\n                  stated or detailed on the CRF. Values should be \"Y\" or null.]|Events|[--OCCUR][An\n                  indication as to whether a prespecified event has occurred.]\n                Document: Model v2.0\n                Section: Events\n              - Cited Guidance: Interventions[--PRESP][An indication that the intervention\n                  was prospectively stated or detailed on the CRF. Values should be\n                  \"Y\" or null.]|Interventions[--OCCUR][An indication as to whether\n                  a prespecified intervention has occurred.]\n                Document: Model v2.0\n                Section: Interventions\nScope:\n  Classes:\n    Include:\n      - EVENTS\n      - INTERVENTIONS\n  Domains:\n    Exclude:\n      - AE\n      - DS\n      - DV\n      - EX\n",
    "created": "2021-09-28T16:10:40Z",
    "creator": {
        "id": "fac95de6-5815-411a-a579-ddbc7ee4b97a"
    },
    "json": {
        "Check": {
            "all": [
                {
                    "name": "--OCCUR",
                    "operator": "non_empty"
                },
                {
                    "name": "--PRESP",
                    "operator": "not_equal_to",
                    "value": "Y"
                }
            ]
        },
        "Core": {
            "Id": "CORE-000016",
            "Version": "1",
            "Status": "Published"
        },
        "Description": "Raise an error when --OCCUR is not empty and --PRESP is not equal to \"Y\".",
        "Outcome": {
            "Message": "--PRESP should be populated as \"Y\" when --OCCUR is provided.",
            "Output_Variables": [
                "--PRESP",
                "--OCCUR"
            ]
        },
        "Rule_Type": "Record Data",
        "Sensitivity": "Dataset",
        "Authorities": [
            {
                "Organization": "CDISC",
                "Standards": [
                    {
                        "Name": "SDTMIG",
                        "Version": "3.4",
                        "References": [
                            {
                                "Origin": "SDTM and SDTMIG Conformance Rules",
                                "Rule_Identifier": {
                                    "Id": "CG0089",
                                    "Version": "1"
                                },
                                "Version": "2.0",
                                "Citations": [
                                    {
                                        "Cited_Guidance": "Events[--PRESP][An indication that the event was prospectively stated or detailed on the CRF. Values should be \"Y\" or null.]|Events|[--OCCUR][An indication as to whether a prespecified event has occurred.]",
                                        "Document": "Model v2.0",
                                        "Section": "Events"
                                    },
                                    {
                                        "Cited_Guidance": "Interventions[--PRESP][An indication that the intervention was prospectively stated or detailed on the CRF. Values should be \"Y\" or null.]|Interventions[--OCCUR][An indication as to whether a prespecified intervention has occurred.]",
                                        "Document": "Model v2.0",
                                        "Section": "Interventions"
                                    }
                                ]
                            }
                        ]
                    }
                ]
            }
        ],
        "Scope": {
            "Classes": {
                "Include": [
                    "EVENTS",
                    "INTERVENTIONS"
                ]
            },
            "Domains": {
                "Exclude": [
                    "AE",
                    "DS",
                    "DV",
                    "EX"
                ]
            }
        }
    }
}