{
    "id": "5c6e5191-58b3-40e9-9a22-63f6a7d131d4",
    "changed": "2022-12-02T13:06:33.029Z",
    "content": "Check:\n  all:\n    - name: SVPRESP\n      operator: equal_to\n      value: Y\n    - name: VISITNUM\n      operator: is_not_contained_by\n      value: $TV_VISITNUM\nMatch Datasets:\n  - Name: SV\n    Keys:\n      - USUBJID\n      - VISITNUM\nCore:\n  Id: CDISC.SDTMIG.CG0033\n  Version: '1'\n  Status: Draft\nDescription: Verify when VISITNUM is not null in any given domain and VISITNUM is\n  planned (SVPRESP = 'Y'), then VISIT should be among TV.VISITNUM.\nOperations:\n  - domain: TV\n    id: $TV_VISITNUM\n    name: VISITNUM\n    operator: distinct\nOutcome:\n  Message: For a planned visit (SVPRESP = 'Y'), non-missing VISITNUM value must be\n    among those present in TV.VISITNUM. in TV.VISITNUM\n  Output Variables:\n    - VISITNUM\n    - SVPRESP\nRule Type: Record Data\nSensitivity: Record\nAuthorities:\n  - Organization: CDISC\n    Standards:\n      - Name: SDTMIG\n        Version: '3.4'\n        References:\n          - Origin: SDTM and SDTMIG Conformance Rules\n            Rule Identifier:\n              Id: CG0033\n              Version: '2'\n            Version: '2.0'\n            Citations:\n              - Cited Guidance: For planned visits, values of VISIT, VISITNUM, and\n                  VISITDY must be those defined in the Trial Visits (TV) dataset (Section\n                  7.3.1, Trial Visits).\n                Document: SDTMIG v3.4\n                Item: ''\n                Section: 4.4.5\n      - Name: SDTMIG\n        Version: '3.3'\n        References:\n          - Origin: SDTM and SDTMIG Conformance Rules\n            Rule Identifier:\n              Id: CG0033\n              Version: '2'\n            Version: '2.0'\n            Citations:\n              - Cited Guidance: For planned visits, values of VISIT, VISITNUM, and\n                  VISITDY must be those defined in the Trial Visits dataset.\n                Document: SDTMIG v3.3\n                Item: ''\n                Section: 4.4.5\n      - Name: SDTMIG\n        Version: '3.2'\n        References:\n          - Origin: SDTM and SDTMIG Conformance Rules\n            Rule Identifier:\n              Id: CG0033\n              Version: '2'\n            Version: '2.0'\n            Citations:\n              - Cited Guidance: For planned visits, values of VISIT, VISITNUM, and\n                  VISITDY must be those defined in the Trial Visits dataset.\n                Document: SDTMIG v3.2\n                Item: ''\n                Section: 4.1.4.5\nScope:\n  Classes:\n    Include:\n      - ALL\n  Domains:\n    Exclude:\n      - TV\n",
    "created": "2022-02-23T05:44:44Z",
    "creator": {
        "id": "24709aaa-3e57-4ee4-a635-6006b165bb1b"
    },
    "json": {
        "Check": {
            "all": [
                {
                    "name": "SVPRESP",
                    "operator": "equal_to",
                    "value": "Y"
                },
                {
                    "name": "VISITNUM",
                    "operator": "is_not_contained_by",
                    "value": "$TV_VISITNUM"
                }
            ]
        },
        "Match_Datasets": [
            {
                "Name": "SV",
                "Keys": [
                    "USUBJID",
                    "VISITNUM"
                ]
            }
        ],
        "Core": {
            "Id": "CDISC.SDTMIG.CG0033",
            "Version": "1",
            "Status": "Draft"
        },
        "Description": "Verify when VISITNUM is not null in any given domain and VISITNUM is planned (SVPRESP = 'Y'), then VISIT should be among TV.VISITNUM.",
        "Operations": [
            {
                "domain": "TV",
                "id": "$TV_VISITNUM",
                "name": "VISITNUM",
                "operator": "distinct"
            }
        ],
        "Outcome": {
            "Message": "For a planned visit (SVPRESP = 'Y'), non-missing VISITNUM value must be among those present in TV.VISITNUM. in TV.VISITNUM",
            "Output_Variables": [
                "VISITNUM",
                "SVPRESP"
            ]
        },
        "Rule_Type": "Record Data",
        "Sensitivity": "Record",
        "Authorities": [
            {
                "Organization": "CDISC",
                "Standards": [
                    {
                        "Name": "SDTMIG",
                        "Version": "3.4",
                        "References": [
                            {
                                "Origin": "SDTM and SDTMIG Conformance Rules",
                                "Rule_Identifier": {
                                    "Id": "CG0033",
                                    "Version": "2"
                                },
                                "Version": "2.0",
                                "Citations": [
                                    {
                                        "Cited_Guidance": "For planned visits, values of VISIT, VISITNUM, and VISITDY must be those defined in the Trial Visits (TV) dataset (Section 7.3.1, Trial Visits).",
                                        "Document": "SDTMIG v3.4",
                                        "Item": "",
                                        "Section": "4.4.5"
                                    }
                                ]
                            }
                        ]
                    },
                    {
                        "Name": "SDTMIG",
                        "Version": "3.3",
                        "References": [
                            {
                                "Origin": "SDTM and SDTMIG Conformance Rules",
                                "Rule_Identifier": {
                                    "Id": "CG0033",
                                    "Version": "2"
                                },
                                "Version": "2.0",
                                "Citations": [
                                    {
                                        "Cited_Guidance": "For planned visits, values of VISIT, VISITNUM, and VISITDY must be those defined in the Trial Visits dataset.",
                                        "Document": "SDTMIG v3.3",
                                        "Item": "",
                                        "Section": "4.4.5"
                                    }
                                ]
                            }
                        ]
                    },
                    {
                        "Name": "SDTMIG",
                        "Version": "3.2",
                        "References": [
                            {
                                "Origin": "SDTM and SDTMIG Conformance Rules",
                                "Rule_Identifier": {
                                    "Id": "CG0033",
                                    "Version": "2"
                                },
                                "Version": "2.0",
                                "Citations": [
                                    {
                                        "Cited_Guidance": "For planned visits, values of VISIT, VISITNUM, and VISITDY must be those defined in the Trial Visits dataset.",
                                        "Document": "SDTMIG v3.2",
                                        "Item": "",
                                        "Section": "4.1.4.5"
                                    }
                                ]
                            }
                        ]
                    }
                ]
            }
        ],
        "Scope": {
            "Classes": {
                "Include": [
                    "ALL"
                ]
            },
            "Domains": {
                "Exclude": [
                    "TV"
                ]
            }
        }
    }
}