{
    "id": "8217f16c-83a9-4b11-a4e0-faac50771673",
    "changed": "2023-01-20T19:03:45.300Z",
    "content": "Check:\n  all:\n    - name: --ENTPT\n      operator: non_empty\n    - name: --ENRTPT\n      operator: empty\nCore:\n  Id: CORE-000106\n  Version: '1'\n  Status: Published\nDescription: Raise an error when --ENTPT is completed and --ENRTPT is not completed.\nOutcome:\n  Message: --ENTPT is completed, but --ENRTPT is not completed.\n  Output Variables:\n    - --ENRTPT\n    - --ENTPT\nRule Type: Record Data\nSensitivity: Record\nAuthorities:\n  - Organization: CDISC\n    Standards:\n      - Name: SDTMIG\n        Version: '3.4'\n        References:\n          - Origin: SDTM and SDTMIG Conformance Rules\n            Rule Identifier:\n              Id: CG0045\n              Version: '1'\n            Version: '2.0'\n            Citations:\n              - Cited Guidance: The description or date and/or time of a time point\n                  that acts as a fixed reference for characterizing the end of an\n                  observation. This is the sponsor-defined reference point referred\n                  to by --ENRTPT.\n                Document: Model v2.0\n                Item: --ENTPT\n                Section: Timing\n      - Name: SDTMIG\n        Version: '3.3'\n        References:\n          - Origin: SDTM and SDTMIG Conformance Rules\n            Rule Identifier:\n              Id: CG0045\n              Version: '1'\n            Version: '2.0'\n            Citations:\n              - Cited Guidance: Identifies the end of the observation as being before\n                  or after the sponsor-defined reference time point defined by variable\n                  --ENTPT.\n                Document: Model v1.7\n                Item: Table 2.2.5.1 --ENTPT\n                Section: 2.2.5 Timing Variables for All Classes\n      - Name: SDTMIG\n        Version: '3.2'\n        References:\n          - Origin: SDTM and SDTMIG Conformance Rules\n            Rule Identifier:\n              Id: CG0045\n              Version: '1'\n            Version: '2.0'\n            Citations:\n              - Cited Guidance: (--ENRTPT) Identifies the end of the observation as\n                  being before or after the sponsor-defined reference time point defined\n                  by variable --ENTPT.\n                Document: Model v1.4\n                Item: Specification\n                Section: 2.2.5 Timing Variables for All Classes\nScope:\n  Classes:\n    Include:\n      - ALL\n  Domains:\n    Include:\n      - ALL\n",
    "created": "2021-10-07T09:12:48Z",
    "creator": {
        "id": "02c3c969-4787-4d57-b164-e2851035c0e8"
    },
    "json": {
        "Check": {
            "all": [
                {
                    "name": "--ENTPT",
                    "operator": "non_empty"
                },
                {
                    "name": "--ENRTPT",
                    "operator": "empty"
                }
            ]
        },
        "Core": {
            "Id": "CORE-000106",
            "Version": "1",
            "Status": "Published"
        },
        "Description": "Raise an error when --ENTPT is completed and --ENRTPT is not completed.",
        "Outcome": {
            "Message": "--ENTPT is completed, but --ENRTPT is not completed.",
            "Output_Variables": [
                "--ENRTPT",
                "--ENTPT"
            ]
        },
        "Rule_Type": "Record Data",
        "Sensitivity": "Record",
        "Authorities": [
            {
                "Organization": "CDISC",
                "Standards": [
                    {
                        "Name": "SDTMIG",
                        "Version": "3.4",
                        "References": [
                            {
                                "Origin": "SDTM and SDTMIG Conformance Rules",
                                "Rule_Identifier": {
                                    "Id": "CG0045",
                                    "Version": "1"
                                },
                                "Version": "2.0",
                                "Citations": [
                                    {
                                        "Cited_Guidance": "The description or date and/or time of a time point that acts as a fixed reference for characterizing the end of an observation. This is the sponsor-defined reference point referred to by --ENRTPT.",
                                        "Document": "Model v2.0",
                                        "Item": "--ENTPT",
                                        "Section": "Timing"
                                    }
                                ]
                            }
                        ]
                    },
                    {
                        "Name": "SDTMIG",
                        "Version": "3.3",
                        "References": [
                            {
                                "Origin": "SDTM and SDTMIG Conformance Rules",
                                "Rule_Identifier": {
                                    "Id": "CG0045",
                                    "Version": "1"
                                },
                                "Version": "2.0",
                                "Citations": [
                                    {
                                        "Cited_Guidance": "Identifies the end of the observation as being before or after the sponsor-defined reference time point defined by variable --ENTPT.",
                                        "Document": "Model v1.7",
                                        "Item": "Table 2.2.5.1 --ENTPT",
                                        "Section": "2.2.5 Timing Variables for All Classes"
                                    }
                                ]
                            }
                        ]
                    },
                    {
                        "Name": "SDTMIG",
                        "Version": "3.2",
                        "References": [
                            {
                                "Origin": "SDTM and SDTMIG Conformance Rules",
                                "Rule_Identifier": {
                                    "Id": "CG0045",
                                    "Version": "1"
                                },
                                "Version": "2.0",
                                "Citations": [
                                    {
                                        "Cited_Guidance": "(--ENRTPT) Identifies the end of the observation as being before or after the sponsor-defined reference time point defined by variable --ENTPT.",
                                        "Document": "Model v1.4",
                                        "Item": "Specification",
                                        "Section": "2.2.5 Timing Variables for All Classes"
                                    }
                                ]
                            }
                        ]
                    }
                ]
            }
        ],
        "Scope": {
            "Classes": {
                "Include": [
                    "ALL"
                ]
            },
            "Domains": {
                "Include": [
                    "ALL"
                ]
            }
        }
    }
}