{
    "id": "d31a8c98-2abd-4ef7-bf50-468a8d14d66e",
    "changed": "2022-02-15T21:31:23Z",
    "content": "Check:\n  all:\n    - name:\n      operator: not_equal_to\n      value:\nCore:\n  Id: CDISC.SDTMIG.CG0011\n  Version: '1'\n  Status: Draft\nDescription: Trigger error when variable format does not match SDTM-specified controlled\n  terminology or format guidelines for variables (when provided)\nOutcome:\n  Message: Variable format does not match SDTM-specified controlled terminology or\n    format guidelines for variables (when provided)\nRule Type: Record Data\nSensitivity: Dataset\nAuthorities:\n  - Organization: CDISC\n    Standards:\n      - Name: SDTMIG\n        Version: '3.4'\n        References:\n          - Origin: SDTM and SDTMIG Conformance Rules\n            Rule Identifier:\n              Id: CG0011\n              Version: '1'\n            Version: '2.0'\n            Citations:\n              - Cited Guidance: Following SDTM-specified controlled terminology and\n                  format guidelines for variables, when provided\n                Document: IG v3.4\n                Section: 3.2.2\nScope:\n  Classes:\n    Include:\n      - ALL\n  Domains:\n    Include:\n      - ALL\n",
    "created": "2021-11-06T04:43:01Z",
    "creator": {
        "id": "ff471ff8-f131-4cf5-9712-c79cce6301a1"
    },
    "json": {
        "Check": {
            "all": [
                {
                    "name": null,
                    "operator": "not_equal_to",
                    "value": null
                }
            ]
        },
        "Core": {
            "Id": "CDISC.SDTMIG.CG0011",
            "Version": "1",
            "Status": "Draft"
        },
        "Description": "Trigger error when variable format does not match SDTM-specified controlled terminology or format guidelines for variables (when provided)",
        "Outcome": {
            "Message": "Variable format does not match SDTM-specified controlled terminology or format guidelines for variables (when provided)"
        },
        "Rule_Type": "Record Data",
        "Sensitivity": "Dataset",
        "Authorities": [
            {
                "Organization": "CDISC",
                "Standards": [
                    {
                        "Name": "SDTMIG",
                        "Version": "3.4",
                        "References": [
                            {
                                "Origin": "SDTM and SDTMIG Conformance Rules",
                                "Rule_Identifier": {
                                    "Id": "CG0011",
                                    "Version": "1"
                                },
                                "Version": "2.0",
                                "Citations": [
                                    {
                                        "Cited_Guidance": "Following SDTM-specified controlled terminology and format guidelines for variables, when provided",
                                        "Document": "IG v3.4",
                                        "Section": "3.2.2"
                                    }
                                ]
                            }
                        ]
                    }
                ]
            }
        ],
        "Scope": {
            "Classes": {
                "Include": [
                    "ALL"
                ]
            },
            "Domains": {
                "Include": [
                    "ALL"
                ]
            }
        }
    }
}