{
    "id": "f0888938-2ed4-4441-b0f0-7af404c94f40",
    "changed": "2023-01-24T20:55:50.005Z",
    "content": "Check:\n  all:\n    - name: MHENDTC\n      operator: non_empty\n    - name: MHENDTC\n      operator: date_greater_than_or_equal_to\n      value: RFSTDTC\nMatch Datasets:\n  - Name: DM\n    Keys:\n      - USUBJID\nCore:\n  Id: CORE-000250\n  Version: '1'\n  Status: Published\nDescription: Raise an issue if MHENDTC has a non-empty date that is on or after DM.RFSTDTC\nOutcome:\n  Message: MHENDTC ^= null and MHENDTC is on or after the DM.RFSTDTC. The medical\n    history dataset should include the subject's prior history at the start of the\n    trial.\n  Output Variables:\n    - MHENDTC\n    - RFSTDTC\nRule Type: Record Data\nSensitivity: Record\nAuthorities:\n  - Organization: CDISC\n    Standards:\n      - Name: SDTMIG\n        Version: '3.4'\n        References:\n          - Origin: SDTM and SDTMIG Conformance Rules\n            Rule Identifier:\n              Id: CG0078\n              Version: '1'\n            Version: '2.0'\n            Citations:\n              - Cited Guidance: Do not create separate domains based on time; rather,\n                  represent both prior and current observations in a domain (e.g.,\n                  CM for all non-study medications). Note that Adverse Events and\n                  Medical History are an exception to this best practice because of\n                  regulatory reporting needs.\n                Document: SDTMIG v3.4\n                Section: '2.6'\n              - Cited Guidance: Adverse Events (AE), Medical History (MH), and Clinical\n                  Events (CE), for example, are conceptually the same data, the only\n                  differences being when the event started relative to the study start\n                  and whether the event is considered a regulatory-reportable adverse\n                  event in the study.\n                Document: SDTMIG v3.4\n                Item: 2.B.3.a\n                Section: 4.2.6\n              - Cited Guidance: MH Description The medical history dataset includes\n                  the subject's prior history at the start of the trial.\n                Document: SDTMIG v3.4\n                Section: '6.2'\n              - Cited Guidance: Do not create separate domains based on time; rather,\n                  represent both prior and current observations in a domain (e.g.,\n                  CM for all non-study medications). Note that AE and MH are an exception\n                  to this best practice because of regulatory reporting needs\n                Document: SDTMIG v3.3\n                Section: '2.6'\n              - Cited Guidance: (Discussion of --CAT/--SCAT) Adverse Events (AE),\n                  Medical History (MH), and Clinical Events (CE), for example, are\n                  conceptually the same data, the only differences being when the\n                  event started relative to the study start and whether the event\n                  is considered a regulatory reportable adverse event in the study.\n                Document: SDTMIG v3.3\n                Item: 2.B.3.A\n                Section: 4.2.6\n              - Cited Guidance: The medical history dataset includes the subject's\n                  prior history at the start of the trial.][MH The medical history\n                  dataset includes the subject's prior history at the start of the\n                  trial.\n                Document: SDTMIG v3.3\n                Section: '6.2'\n              - Cited Guidance: Do not create separate domains based on time, rather\n                  represent both prior and current observations in a domain (e.g.,\n                  CM for all non-study medications). Note that AE and MH are an exception\n                  to this best practice because of regulatory reporting needs.\n                Document: SDTMIG v3.2\n                Section: '2.6'\n              - Cited Guidance: Discussion of --CAT/--SCAT) Adverse Events (AE), Medical\n                  History (MH) and Clinical Events (CE), for example, are conceptually\n                  the same data, the only differences being when the event started\n                  relative to the study start and whether the event is considered\n                  a regulatory reportable adverse event in the study.\n                Document: SDTMIG v3.2\n                Item: Item 2.B.3.A (Discussion of --CAT/--SCAT)\n                Section: 4.1.2.6\n              - Cited Guidance: The medical history dataset includes the subject's\n                  prior history at the start of the trial.][MH The medical history\n                  dataset includes the subject's prior history at the start of the\n                  trial.][Assumption 1:The Medical History dataset generally includes\n                  the subject's prior and concomitant conditions at the start of the\n                  trial.]\n                Document: SDTMIG v3.2\n                Item: Domain Code Table | Assumption 1\n                Section: '6.2'\n      - Name: SDTMIG\n        Version: '3.3'\n        References:\n          - Origin: SDTM and SDTMIG Conformance Rules\n            Rule Identifier:\n              Id: CG0078\n              Version: '1'\n            Version: '2.0'\n            Citations:\n              - Cited Guidance: Do not create separate domains based on time; rather,\n                  represent both prior and current observations in a domain (e.g.,\n                  CM for all non-study medications). Note that Adverse Events and\n                  Medical History are an exception to this best practice because of\n                  regulatory reporting needs.\n                Document: SDTMIG v3.4\n                Section: '2.6'\n              - Cited Guidance: Adverse Events (AE), Medical History (MH), and Clinical\n                  Events (CE), for example, are conceptually the same data, the only\n                  differences being when the event started relative to the study start\n                  and whether the event is considered a regulatory-reportable adverse\n                  event in the study.\n                Document: SDTMIG v3.4\n                Item: 2.B.3.a\n                Section: 4.2.6\n              - Cited Guidance: MH Description The medical history dataset includes\n                  the subject's prior history at the start of the trial.\n                Document: SDTMIG v3.4\n                Section: '6.2'\n              - Cited Guidance: Do not create separate domains based on time; rather,\n                  represent both prior and current observations in a domain (e.g.,\n                  CM for all non-study medications). Note that AE and MH are an exception\n                  to this best practice because of regulatory reporting needs\n                Document: SDTMIG v3.3\n                Section: '2.6'\n              - Cited Guidance: (Discussion of --CAT/--SCAT) Adverse Events (AE),\n                  Medical History (MH), and Clinical Events (CE), for example, are\n                  conceptually the same data, the only differences being when the\n                  event started relative to the study start and whether the event\n                  is considered a regulatory reportable adverse event in the study.\n                Document: SDTMIG v3.3\n                Item: 2.B.3.A\n                Section: 4.2.6\n              - Cited Guidance: The medical history dataset includes the subject's\n                  prior history at the start of the trial.][MH The medical history\n                  dataset includes the subject's prior history at the start of the\n                  trial.\n                Document: SDTMIG v3.3\n                Section: '6.2'\n              - Cited Guidance: Do not create separate domains based on time, rather\n                  represent both prior and current observations in a domain (e.g.,\n                  CM for all non-study medications). Note that AE and MH are an exception\n                  to this best practice because of regulatory reporting needs.\n                Document: SDTMIG v3.2\n                Section: '2.6'\n              - Cited Guidance: Discussion of --CAT/--SCAT) Adverse Events (AE), Medical\n                  History (MH) and Clinical Events (CE), for example, are conceptually\n                  the same data, the only differences being when the event started\n                  relative to the study start and whether the event is considered\n                  a regulatory reportable adverse event in the study.\n                Document: SDTMIG v3.2\n                Item: Item 2.B.3.A (Discussion of --CAT/--SCAT)\n                Section: 4.1.2.6\n              - Cited Guidance: The medical history dataset includes the subject's\n                  prior history at the start of the trial.][MH The medical history\n                  dataset includes the subject's prior history at the start of the\n                  trial.][Assumption 1:The Medical History dataset generally includes\n                  the subject's prior and concomitant conditions at the start of the\n                  trial.]\n                Document: SDTMIG v3.2\n                Item: Domain Code Table | Assumption 1\n                Section: '6.2'\n      - Name: SDTMIG\n        Version: '3.2'\n        References:\n          - Origin: SDTM and SDTMIG Conformance Rules\n            Rule Identifier:\n              Id: CG0078\n              Version: '1'\n            Version: '2.0'\n            Citations:\n              - Cited Guidance: Do not create separate domains based on time; rather,\n                  represent both prior and current observations in a domain (e.g.,\n                  CM for all non-study medications). Note that Adverse Events and\n                  Medical History are an exception to this best practice because of\n                  regulatory reporting needs.\n                Document: SDTMIG v3.4\n                Section: '2.6'\n              - Cited Guidance: Adverse Events (AE), Medical History (MH), and Clinical\n                  Events (CE), for example, are conceptually the same data, the only\n                  differences being when the event started relative to the study start\n                  and whether the event is considered a regulatory-reportable adverse\n                  event in the study.\n                Document: SDTMIG v3.4\n                Item: 2.B.3.a\n                Section: 4.2.6\n              - Cited Guidance: MH Description The medical history dataset includes\n                  the subject's prior history at the start of the trial.\n                Document: SDTMIG v3.4\n                Section: '6.2'\n              - Cited Guidance: Do not create separate domains based on time; rather,\n                  represent both prior and current observations in a domain (e.g.,\n                  CM for all non-study medications). Note that AE and MH are an exception\n                  to this best practice because of regulatory reporting needs\n                Document: SDTMIG v3.3\n                Section: '2.6'\n              - Cited Guidance: (Discussion of --CAT/--SCAT) Adverse Events (AE),\n                  Medical History (MH), and Clinical Events (CE), for example, are\n                  conceptually the same data, the only differences being when the\n                  event started relative to the study start and whether the event\n                  is considered a regulatory reportable adverse event in the study.\n                Document: SDTMIG v3.3\n                Item: 2.B.3.A\n                Section: 4.2.6\n              - Cited Guidance: The medical history dataset includes the subject's\n                  prior history at the start of the trial.][MH The medical history\n                  dataset includes the subject's prior history at the start of the\n                  trial.\n                Document: SDTMIG v3.3\n                Section: '6.2'\n              - Cited Guidance: Do not create separate domains based on time, rather\n                  represent both prior and current observations in a domain (e.g.,\n                  CM for all non-study medications). Note that AE and MH are an exception\n                  to this best practice because of regulatory reporting needs.\n                Document: SDTMIG v3.2\n                Section: '2.6'\n              - Cited Guidance: Discussion of --CAT/--SCAT) Adverse Events (AE), Medical\n                  History (MH) and Clinical Events (CE), for example, are conceptually\n                  the same data, the only differences being when the event started\n                  relative to the study start and whether the event is considered\n                  a regulatory reportable adverse event in the study.\n                Document: SDTMIG v3.2\n                Item: Item 2.B.3.A (Discussion of --CAT/--SCAT)\n                Section: 4.1.2.6\n              - Cited Guidance: The medical history dataset includes the subject's\n                  prior history at the start of the trial.][MH The medical history\n                  dataset includes the subject's prior history at the start of the\n                  trial.][Assumption 1:The Medical History dataset generally includes\n                  the subject's prior and concomitant conditions at the start of the\n                  trial.]\n                Document: SDTMIG v3.2\n                Item: Domain Code Table | Assumption 1\n                Section: '6.2'\nScope:\n  Classes:\n    Include:\n      - EVENTS\n  Domains:\n    Include:\n      - MH\n",
    "created": "2022-03-18T12:55:33Z",
    "creator": {
        "id": "b5bc818b-4ec4-4952-951f-0fbca010be52"
    },
    "json": {
        "Check": {
            "all": [
                {
                    "name": "MHENDTC",
                    "operator": "non_empty"
                },
                {
                    "name": "MHENDTC",
                    "operator": "date_greater_than_or_equal_to",
                    "value": "RFSTDTC"
                }
            ]
        },
        "Match_Datasets": [
            {
                "Name": "DM",
                "Keys": [
                    "USUBJID"
                ]
            }
        ],
        "Core": {
            "Id": "CORE-000250",
            "Version": "1",
            "Status": "Published"
        },
        "Description": "Raise an issue if MHENDTC has a non-empty date that is on or after DM.RFSTDTC",
        "Outcome": {
            "Message": "MHENDTC ^= null and MHENDTC is on or after the DM.RFSTDTC. The medical history dataset should include the subject's prior history at the start of the trial.",
            "Output_Variables": [
                "MHENDTC",
                "RFSTDTC"
            ]
        },
        "Rule_Type": "Record Data",
        "Sensitivity": "Record",
        "Authorities": [
            {
                "Organization": "CDISC",
                "Standards": [
                    {
                        "Name": "SDTMIG",
                        "Version": "3.4",
                        "References": [
                            {
                                "Origin": "SDTM and SDTMIG Conformance Rules",
                                "Rule_Identifier": {
                                    "Id": "CG0078",
                                    "Version": "1"
                                },
                                "Version": "2.0",
                                "Citations": [
                                    {
                                        "Cited_Guidance": "Do not create separate domains based on time; rather, represent both prior and current observations in a domain (e.g., CM for all non-study medications). Note that Adverse Events and Medical History are an exception to this best practice because of regulatory reporting needs.",
                                        "Document": "SDTMIG v3.4",
                                        "Section": "2.6"
                                    },
                                    {
                                        "Cited_Guidance": "Adverse Events (AE), Medical History (MH), and Clinical Events (CE), for example, are conceptually the same data, the only differences being when the event started relative to the study start and whether the event is considered a regulatory-reportable adverse event in the study.",
                                        "Document": "SDTMIG v3.4",
                                        "Item": "2.B.3.a",
                                        "Section": "4.2.6"
                                    },
                                    {
                                        "Cited_Guidance": "MH Description The medical history dataset includes the subject's prior history at the start of the trial.",
                                        "Document": "SDTMIG v3.4",
                                        "Section": "6.2"
                                    },
                                    {
                                        "Cited_Guidance": "Do not create separate domains based on time; rather, represent both prior and current observations in a domain (e.g., CM for all non-study medications). Note that AE and MH are an exception to this best practice because of regulatory reporting needs",
                                        "Document": "SDTMIG v3.3",
                                        "Section": "2.6"
                                    },
                                    {
                                        "Cited_Guidance": "(Discussion of --CAT/--SCAT) Adverse Events (AE), Medical History (MH), and Clinical Events (CE), for example, are conceptually the same data, the only differences being when the event started relative to the study start and whether the event is considered a regulatory reportable adverse event in the study.",
                                        "Document": "SDTMIG v3.3",
                                        "Item": "2.B.3.A",
                                        "Section": "4.2.6"
                                    },
                                    {
                                        "Cited_Guidance": "The medical history dataset includes the subject's prior history at the start of the trial.][MH The medical history dataset includes the subject's prior history at the start of the trial.",
                                        "Document": "SDTMIG v3.3",
                                        "Section": "6.2"
                                    },
                                    {
                                        "Cited_Guidance": "Do not create separate domains based on time, rather represent both prior and current observations in a domain (e.g., CM for all non-study medications). Note that AE and MH are an exception to this best practice because of regulatory reporting needs.",
                                        "Document": "SDTMIG v3.2",
                                        "Section": "2.6"
                                    },
                                    {
                                        "Cited_Guidance": "Discussion of --CAT/--SCAT) Adverse Events (AE), Medical History (MH) and Clinical Events (CE), for example, are conceptually the same data, the only differences being when the event started relative to the study start and whether the event is considered a regulatory reportable adverse event in the study.",
                                        "Document": "SDTMIG v3.2",
                                        "Item": "Item 2.B.3.A (Discussion of --CAT/--SCAT)",
                                        "Section": "4.1.2.6"
                                    },
                                    {
                                        "Cited_Guidance": "The medical history dataset includes the subject's prior history at the start of the trial.][MH The medical history dataset includes the subject's prior history at the start of the trial.][Assumption 1:The Medical History dataset generally includes the subject's prior and concomitant conditions at the start of the trial.]",
                                        "Document": "SDTMIG v3.2",
                                        "Item": "Domain Code Table | Assumption 1",
                                        "Section": "6.2"
                                    }
                                ]
                            }
                        ]
                    },
                    {
                        "Name": "SDTMIG",
                        "Version": "3.3",
                        "References": [
                            {
                                "Origin": "SDTM and SDTMIG Conformance Rules",
                                "Rule_Identifier": {
                                    "Id": "CG0078",
                                    "Version": "1"
                                },
                                "Version": "2.0",
                                "Citations": [
                                    {
                                        "Cited_Guidance": "Do not create separate domains based on time; rather, represent both prior and current observations in a domain (e.g., CM for all non-study medications). Note that Adverse Events and Medical History are an exception to this best practice because of regulatory reporting needs.",
                                        "Document": "SDTMIG v3.4",
                                        "Section": "2.6"
                                    },
                                    {
                                        "Cited_Guidance": "Adverse Events (AE), Medical History (MH), and Clinical Events (CE), for example, are conceptually the same data, the only differences being when the event started relative to the study start and whether the event is considered a regulatory-reportable adverse event in the study.",
                                        "Document": "SDTMIG v3.4",
                                        "Item": "2.B.3.a",
                                        "Section": "4.2.6"
                                    },
                                    {
                                        "Cited_Guidance": "MH Description The medical history dataset includes the subject's prior history at the start of the trial.",
                                        "Document": "SDTMIG v3.4",
                                        "Section": "6.2"
                                    },
                                    {
                                        "Cited_Guidance": "Do not create separate domains based on time; rather, represent both prior and current observations in a domain (e.g., CM for all non-study medications). Note that AE and MH are an exception to this best practice because of regulatory reporting needs",
                                        "Document": "SDTMIG v3.3",
                                        "Section": "2.6"
                                    },
                                    {
                                        "Cited_Guidance": "(Discussion of --CAT/--SCAT) Adverse Events (AE), Medical History (MH), and Clinical Events (CE), for example, are conceptually the same data, the only differences being when the event started relative to the study start and whether the event is considered a regulatory reportable adverse event in the study.",
                                        "Document": "SDTMIG v3.3",
                                        "Item": "2.B.3.A",
                                        "Section": "4.2.6"
                                    },
                                    {
                                        "Cited_Guidance": "The medical history dataset includes the subject's prior history at the start of the trial.][MH The medical history dataset includes the subject's prior history at the start of the trial.",
                                        "Document": "SDTMIG v3.3",
                                        "Section": "6.2"
                                    },
                                    {
                                        "Cited_Guidance": "Do not create separate domains based on time, rather represent both prior and current observations in a domain (e.g., CM for all non-study medications). Note that AE and MH are an exception to this best practice because of regulatory reporting needs.",
                                        "Document": "SDTMIG v3.2",
                                        "Section": "2.6"
                                    },
                                    {
                                        "Cited_Guidance": "Discussion of --CAT/--SCAT) Adverse Events (AE), Medical History (MH) and Clinical Events (CE), for example, are conceptually the same data, the only differences being when the event started relative to the study start and whether the event is considered a regulatory reportable adverse event in the study.",
                                        "Document": "SDTMIG v3.2",
                                        "Item": "Item 2.B.3.A (Discussion of --CAT/--SCAT)",
                                        "Section": "4.1.2.6"
                                    },
                                    {
                                        "Cited_Guidance": "The medical history dataset includes the subject's prior history at the start of the trial.][MH The medical history dataset includes the subject's prior history at the start of the trial.][Assumption 1:The Medical History dataset generally includes the subject's prior and concomitant conditions at the start of the trial.]",
                                        "Document": "SDTMIG v3.2",
                                        "Item": "Domain Code Table | Assumption 1",
                                        "Section": "6.2"
                                    }
                                ]
                            }
                        ]
                    },
                    {
                        "Name": "SDTMIG",
                        "Version": "3.2",
                        "References": [
                            {
                                "Origin": "SDTM and SDTMIG Conformance Rules",
                                "Rule_Identifier": {
                                    "Id": "CG0078",
                                    "Version": "1"
                                },
                                "Version": "2.0",
                                "Citations": [
                                    {
                                        "Cited_Guidance": "Do not create separate domains based on time; rather, represent both prior and current observations in a domain (e.g., CM for all non-study medications). Note that Adverse Events and Medical History are an exception to this best practice because of regulatory reporting needs.",
                                        "Document": "SDTMIG v3.4",
                                        "Section": "2.6"
                                    },
                                    {
                                        "Cited_Guidance": "Adverse Events (AE), Medical History (MH), and Clinical Events (CE), for example, are conceptually the same data, the only differences being when the event started relative to the study start and whether the event is considered a regulatory-reportable adverse event in the study.",
                                        "Document": "SDTMIG v3.4",
                                        "Item": "2.B.3.a",
                                        "Section": "4.2.6"
                                    },
                                    {
                                        "Cited_Guidance": "MH Description The medical history dataset includes the subject's prior history at the start of the trial.",
                                        "Document": "SDTMIG v3.4",
                                        "Section": "6.2"
                                    },
                                    {
                                        "Cited_Guidance": "Do not create separate domains based on time; rather, represent both prior and current observations in a domain (e.g., CM for all non-study medications). Note that AE and MH are an exception to this best practice because of regulatory reporting needs",
                                        "Document": "SDTMIG v3.3",
                                        "Section": "2.6"
                                    },
                                    {
                                        "Cited_Guidance": "(Discussion of --CAT/--SCAT) Adverse Events (AE), Medical History (MH), and Clinical Events (CE), for example, are conceptually the same data, the only differences being when the event started relative to the study start and whether the event is considered a regulatory reportable adverse event in the study.",
                                        "Document": "SDTMIG v3.3",
                                        "Item": "2.B.3.A",
                                        "Section": "4.2.6"
                                    },
                                    {
                                        "Cited_Guidance": "The medical history dataset includes the subject's prior history at the start of the trial.][MH The medical history dataset includes the subject's prior history at the start of the trial.",
                                        "Document": "SDTMIG v3.3",
                                        "Section": "6.2"
                                    },
                                    {
                                        "Cited_Guidance": "Do not create separate domains based on time, rather represent both prior and current observations in a domain (e.g., CM for all non-study medications). Note that AE and MH are an exception to this best practice because of regulatory reporting needs.",
                                        "Document": "SDTMIG v3.2",
                                        "Section": "2.6"
                                    },
                                    {
                                        "Cited_Guidance": "Discussion of --CAT/--SCAT) Adverse Events (AE), Medical History (MH) and Clinical Events (CE), for example, are conceptually the same data, the only differences being when the event started relative to the study start and whether the event is considered a regulatory reportable adverse event in the study.",
                                        "Document": "SDTMIG v3.2",
                                        "Item": "Item 2.B.3.A (Discussion of --CAT/--SCAT)",
                                        "Section": "4.1.2.6"
                                    },
                                    {
                                        "Cited_Guidance": "The medical history dataset includes the subject's prior history at the start of the trial.][MH The medical history dataset includes the subject's prior history at the start of the trial.][Assumption 1:The Medical History dataset generally includes the subject's prior and concomitant conditions at the start of the trial.]",
                                        "Document": "SDTMIG v3.2",
                                        "Item": "Domain Code Table | Assumption 1",
                                        "Section": "6.2"
                                    }
                                ]
                            }
                        ]
                    }
                ]
            }
        ],
        "Scope": {
            "Classes": {
                "Include": [
                    "EVENTS"
                ]
            },
            "Domains": {
                "Include": [
                    "MH"
                ]
            }
        }
    }
}