{
    "id": "70c55c3c-6227-4f8c-865f-5bebe73d1149",
    "changed": "2022-12-13T09:25:17.411Z",
    "content": "Check:\n  all:\n    - name: --STTPT\n      operator: non_empty\n    - name: --STRTPT\n      operator: empty\nCore:\n  Id: CORE-000085\n  Version: '1'\n  Status: Published\nDescription: Raise an error when --STTPT is completed and --STRTPT is empty\nOutcome:\n  Message: --STTPT is completed and --STRTPT is empty\n  Output Variables:\n    - --STTPT\n    - --STRTPT\nRule Type: Record Data\nSensitivity: Record\nAuthorities:\n  - Organization: CDISC\n    Standards:\n      - Name: SDTMIG\n        Version: '3.4'\n        References:\n          - Origin: SDTM and SDTMIG Conformance Rules\n            Rule Identifier:\n              Id: CG0059\n              Version: '1'\n            Version: '2.0'\n            Citations:\n              - Cited Guidance: The characterization of the start of an observation\n                  relative to a reference time point. The sponsor-defined reference\n                  time point is in --STTPT.\n                Document: Model v2.0\n                Section: Timing\n                Item: --STRTPT\n      - Name: SDTMIG\n        Version: '3.3'\n        References:\n          - Origin: SDTM and SDTMIG Conformance Rules\n            Rule Identifier:\n              Id: CG0059\n              Version: '1'\n            Version: '2.0'\n            Citations:\n              - Cited Guidance: Identifies the start of the observation as being before\n                  or after the sponsor-defined reference time point defined by variable\n                  --STTPT.\n                Document: Model v1.7\n                Section: 2.2.5. Timing Variables for All Classes\n                Item: Table 2.2.5.1, --STRTPT\n      - Name: SDTMIG\n        Version: '3.2'\n        References:\n          - Origin: SDTM and SDTMIG Conformance Rules\n            Rule Identifier:\n              Id: CG0059\n              Version: '1'\n            Version: '2.0'\n            Citations:\n              - Cited Guidance: (--STRTPT) Identifies the start of the observation\n                  as being before or after the sponsor-defined reference time point\n                  defined by variable --STTPT.\n                Document: Model v1.4\n                Section: 2.2.5 Timing Variables for All Classes\n                Item: Specification\nScope:\n  Classes:\n    Include:\n      - ALL\n  Domains:\n    Include:\n      - ALL\n",
    "created": "2021-10-05T18:50:28Z",
    "creator": {
        "id": "ae6dbbf3-4c9a-4149-b596-8183766167d4"
    },
    "json": {
        "Check": {
            "all": [
                {
                    "name": "--STTPT",
                    "operator": "non_empty"
                },
                {
                    "name": "--STRTPT",
                    "operator": "empty"
                }
            ]
        },
        "Core": {
            "Id": "CORE-000085",
            "Version": "1",
            "Status": "Published"
        },
        "Description": "Raise an error when --STTPT is completed and --STRTPT is empty",
        "Outcome": {
            "Message": "--STTPT is completed and --STRTPT is empty",
            "Output_Variables": [
                "--STTPT",
                "--STRTPT"
            ]
        },
        "Rule_Type": "Record Data",
        "Sensitivity": "Record",
        "Authorities": [
            {
                "Organization": "CDISC",
                "Standards": [
                    {
                        "Name": "SDTMIG",
                        "Version": "3.4",
                        "References": [
                            {
                                "Origin": "SDTM and SDTMIG Conformance Rules",
                                "Rule_Identifier": {
                                    "Id": "CG0059",
                                    "Version": "1"
                                },
                                "Version": "2.0",
                                "Citations": [
                                    {
                                        "Cited_Guidance": "The characterization of the start of an observation relative to a reference time point. The sponsor-defined reference time point is in --STTPT.",
                                        "Document": "Model v2.0",
                                        "Section": "Timing",
                                        "Item": "--STRTPT"
                                    }
                                ]
                            }
                        ]
                    },
                    {
                        "Name": "SDTMIG",
                        "Version": "3.3",
                        "References": [
                            {
                                "Origin": "SDTM and SDTMIG Conformance Rules",
                                "Rule_Identifier": {
                                    "Id": "CG0059",
                                    "Version": "1"
                                },
                                "Version": "2.0",
                                "Citations": [
                                    {
                                        "Cited_Guidance": "Identifies the start of the observation as being before or after the sponsor-defined reference time point defined by variable --STTPT.",
                                        "Document": "Model v1.7",
                                        "Section": "2.2.5. Timing Variables for All Classes",
                                        "Item": "Table 2.2.5.1, --STRTPT"
                                    }
                                ]
                            }
                        ]
                    },
                    {
                        "Name": "SDTMIG",
                        "Version": "3.2",
                        "References": [
                            {
                                "Origin": "SDTM and SDTMIG Conformance Rules",
                                "Rule_Identifier": {
                                    "Id": "CG0059",
                                    "Version": "1"
                                },
                                "Version": "2.0",
                                "Citations": [
                                    {
                                        "Cited_Guidance": "(--STRTPT) Identifies the start of the observation as being before or after the sponsor-defined reference time point defined by variable --STTPT.",
                                        "Document": "Model v1.4",
                                        "Section": "2.2.5 Timing Variables for All Classes",
                                        "Item": "Specification"
                                    }
                                ]
                            }
                        ]
                    }
                ]
            }
        ],
        "Scope": {
            "Classes": {
                "Include": [
                    "ALL"
                ]
            },
            "Domains": {
                "Include": [
                    "ALL"
                ]
            }
        }
    }
}