{
    "id": "ec12d0f6-9fee-4821-a4ae-c82de6c2b3fa",
    "changed": "2022-04-15T12:32:21Z",
    "content": "Check:\n  all:\n    - name: VISITDY\n      operator: exists\n    - name: VISITNUM\n      operator: is_contained_by\n      value: $tv_visitnum\n    - name: VISITDY\n      operator: not_equal_to\n      value: TV.VISITDY\nMatch Datasets:\n  - Name: TV\n    Keys:\n      - VISITNUM\nOperations:\n  - domain: TV\n    id: $tv_visitnum\n    name: VISITNUM\n    operator: distinct\nCore:\n  Id: QC.CDISC.SDTMIG.CG0032\n  Version: '1'\n  Status: Draft\nDescription: Verify that visitdy is planned and exists in TV\n\nOutcome:\n  Message: Visit Day cannot be found in Trial Visit (TV) domain\n  Output Variables:\n    - VISITDY\n    - VISITNUM\nRule Type: Record Data\nSensitivity: Value\nAuthorities:\n  - Organization: CDISC\n    Standards:\n      - Name: SDTMIG\n        Version: '3.4'\n        References:\n          - Origin: SDTM and SDTMIG Conformance Rules\n            Rule Identifier:\n              Id: CG0032\n              Version: '1'\n            Version: '2.0'\n            Citations:\n              - Cited Guidance: For planned visits, values of VISIT, VISITNUM, and\n                  VISITDY must be those defined in the Trial Visits (TV) dataset (Section\n                  7.3.1, Trial Visits).\n                Document: IG v3.4\n                Item: ''\n                Section: 4.4.5\nScope:\n  Classes:\n    Include:\n      - ALL\n  Domains:\n    Exclude:\n      - TV\n",
    "created": "2022-04-06T12:46:03Z",
    "creator": {
        "id": "b5bc818b-4ec4-4952-951f-0fbca010be52"
    },
    "json": {
        "Check": {
            "all": [
                {
                    "name": "VISITDY",
                    "operator": "exists"
                },
                {
                    "name": "VISITNUM",
                    "operator": "is_contained_by",
                    "value": "$tv_visitnum"
                },
                {
                    "name": "VISITDY",
                    "operator": "not_equal_to",
                    "value": "TV.VISITDY"
                }
            ]
        },
        "Match_Datasets": [
            {
                "Name": "TV",
                "Keys": [
                    "VISITNUM"
                ]
            }
        ],
        "Operations": [
            {
                "domain": "TV",
                "id": "$tv_visitnum",
                "name": "VISITNUM",
                "operator": "distinct"
            }
        ],
        "Core": {
            "Id": "QC.CDISC.SDTMIG.CG0032",
            "Version": "1",
            "Status": "Draft"
        },
        "Description": "Verify that visitdy is planned and exists in TV",
        "Outcome": {
            "Message": "Visit Day cannot be found in Trial Visit (TV) domain",
            "Output_Variables": [
                "VISITDY",
                "VISITNUM"
            ]
        },
        "Rule_Type": "Record Data",
        "Sensitivity": "Value",
        "Authorities": [
            {
                "Organization": "CDISC",
                "Standards": [
                    {
                        "Name": "SDTMIG",
                        "Version": "3.4",
                        "References": [
                            {
                                "Origin": "SDTM and SDTMIG Conformance Rules",
                                "Rule_Identifier": {
                                    "Id": "CG0032",
                                    "Version": "1"
                                },
                                "Version": "2.0",
                                "Citations": [
                                    {
                                        "Cited_Guidance": "For planned visits, values of VISIT, VISITNUM, and VISITDY must be those defined in the Trial Visits (TV) dataset (Section 7.3.1, Trial Visits).",
                                        "Document": "IG v3.4",
                                        "Item": "",
                                        "Section": "4.4.5"
                                    }
                                ]
                            }
                        ]
                    }
                ]
            }
        ],
        "Scope": {
            "Classes": {
                "Include": [
                    "ALL"
                ]
            },
            "Domains": {
                "Exclude": [
                    "TV"
                ]
            }
        }
    }
}