{
    "id": "4ca6b0d1-d661-4625-8c9e-9db4a1435bb0",
    "changed": "2022-02-15T21:27:56Z",
    "content": "Check:\n  all:\n    - name: CORE\n      operator: equal_to\n      value: Exp\n    - name: GEN\n      operator: not_exists\nCore:\n  Id: CDISC.SDTMIG.CG0016\n  Version: '1'\n  Status: Draft\nDescription: Raise an error when Variable Core Status = Expected and Variable does\n  not exist.\nOutcome:\n  Message: SDTM Expected variable not found in the dataset.\nRule Type: Record Data\nSensitivity: Dataset\nAuthorities:\n  - Organization: CDISC\n    Standards:\n      - Name: SDTMIG\n        Version: '3.4'\n        References:\n          - Origin: SDTM and SDTMIG Conformance Rules\n            Rule Identifier:\n              Id: CG0016\n              Version: '1'\n            Version: '2.0'\n            Citations:\n              - Cited Guidance: \"When the study does not include the data item for\\\n                  \\ an expected variable, however, a null column must still be included\\\n                  \\ in the dataset,\\n and a comment must be included in the Define-XML\\\n                  \\ document to state that the study does not include the data item.\"\n                Document: SDTM v1.4\n                Section: 4.1.5\nScope:\n  Classes:\n    Include:\n      - ALL\n  Domains:\n    Include:\n      - ALL\n",
    "created": "2021-09-26T22:46:52Z",
    "creator": {
        "id": "d0881041-369e-4940-b721-5b456d12101b"
    },
    "json": {
        "Check": {
            "all": [
                {
                    "name": "CORE",
                    "operator": "equal_to",
                    "value": "Exp"
                },
                {
                    "name": "GEN",
                    "operator": "not_exists"
                }
            ]
        },
        "Core": {
            "Id": "CDISC.SDTMIG.CG0016",
            "Version": "1",
            "Status": "Draft"
        },
        "Description": "Raise an error when Variable Core Status = Expected and Variable does not exist.",
        "Outcome": {
            "Message": "SDTM Expected variable not found in the dataset."
        },
        "Rule_Type": "Record Data",
        "Sensitivity": "Dataset",
        "Authorities": [
            {
                "Organization": "CDISC",
                "Standards": [
                    {
                        "Name": "SDTMIG",
                        "Version": "3.4",
                        "References": [
                            {
                                "Origin": "SDTM and SDTMIG Conformance Rules",
                                "Rule_Identifier": {
                                    "Id": "CG0016",
                                    "Version": "1"
                                },
                                "Version": "2.0",
                                "Citations": [
                                    {
                                        "Cited_Guidance": "When the study does not include the data item for an expected variable, however, a null column must still be included in the dataset,\n and a comment must be included in the Define-XML document to state that the study does not include the data item.",
                                        "Document": "SDTM v1.4",
                                        "Section": "4.1.5"
                                    }
                                ]
                            }
                        ]
                    }
                ]
            }
        ],
        "Scope": {
            "Classes": {
                "Include": [
                    "ALL"
                ]
            },
            "Domains": {
                "Include": [
                    "ALL"
                ]
            }
        }
    }
}