{
    "id": "e9edacd3-cbea-475d-bb3d-72f1e133f2c9",
    "changed": "2022-02-23T05:44:15Z",
    "content": "Check:\n  all:\n    - name: VISITNUM\n      operator: non_empty\n    - name: SVPRESP\n      operator: equal_to\n      value: Y\n    - name: VISITNUM\n      operator: is_not_contained_by\n      value: $TV_VISITNUM\nCore:\n  Id: CDISC.SDTMIG.CG0033_OLD_TO_BE_DISCARDED\n  Version: '1'\n  Status: Draft\nDescription: If VISITNUM is not null and VISIT is planned then VISITNUM should be\n  among TV.VISITNUM\nOperations:\n  - domain: TV\n    id: $TV_VISITNUM\n    name: VISITNUM\n    operator: distinct\nOutcome:\n  Message: For a planned visit, non missing VISITNUM value must be among those present\n    in TV.VISITNUM\nRule Type: Record Data\nSensitivity: Record\nAuthorities:\n  - Organization: CDISC\n    Standards:\n      - Name: SDTMIG\n        Version: '3.4'\n        References:\n          - Origin: SDTM and SDTMIG Conformance Rules\n            Rule Identifier:\n              Id: CG0033\n              Version: '1'\n            Version: '2.0'\n            Citations:\n              - Cited Guidance: For planned visits, values of VISIT, VISITNUM, and\n                  VISITDY must be those defined in the Trial Visits (TV) dataset (Section\n                  7.3.1, Trial Visits).\n                Document: SDTMIG v3.4\n                Item: Specification\n                Section: 4.4.5\nScope:\n  Classes:\n    Include:\n      - SPECIAL-PURPOSE\n  Domains:\n    Include:\n      - SV\n",
    "created": "2021-11-04T07:00:42Z",
    "creator": {
        "id": "24709aaa-3e57-4ee4-a635-6006b165bb1b"
    },
    "json": {
        "Check": {
            "all": [
                {
                    "name": "VISITNUM",
                    "operator": "non_empty"
                },
                {
                    "name": "SVPRESP",
                    "operator": "equal_to",
                    "value": "Y"
                },
                {
                    "name": "VISITNUM",
                    "operator": "is_not_contained_by",
                    "value": "$TV_VISITNUM"
                }
            ]
        },
        "Core": {
            "Id": "CDISC.SDTMIG.CG0033_OLD_TO_BE_DISCARDED",
            "Version": "1",
            "Status": "Draft"
        },
        "Description": "If VISITNUM is not null and VISIT is planned then VISITNUM should be among TV.VISITNUM",
        "Operations": [
            {
                "domain": "TV",
                "id": "$TV_VISITNUM",
                "name": "VISITNUM",
                "operator": "distinct"
            }
        ],
        "Outcome": {
            "Message": "For a planned visit, non missing VISITNUM value must be among those present in TV.VISITNUM"
        },
        "Rule_Type": "Record Data",
        "Sensitivity": "Record",
        "Authorities": [
            {
                "Organization": "CDISC",
                "Standards": [
                    {
                        "Name": "SDTMIG",
                        "Version": "3.4",
                        "References": [
                            {
                                "Origin": "SDTM and SDTMIG Conformance Rules",
                                "Rule_Identifier": {
                                    "Id": "CG0033",
                                    "Version": "1"
                                },
                                "Version": "2.0",
                                "Citations": [
                                    {
                                        "Cited_Guidance": "For planned visits, values of VISIT, VISITNUM, and VISITDY must be those defined in the Trial Visits (TV) dataset (Section 7.3.1, Trial Visits).",
                                        "Document": "SDTMIG v3.4",
                                        "Item": "Specification",
                                        "Section": "4.4.5"
                                    }
                                ]
                            }
                        ]
                    }
                ]
            }
        ],
        "Scope": {
            "Classes": {
                "Include": [
                    "SPECIAL-PURPOSE"
                ]
            },
            "Domains": {
                "Include": [
                    "SV"
                ]
            }
        }
    }
}