{
    "id": "85e52016-c51a-4ce9-80b0-197d86fcbd63",
    "changed": "2022-03-10T18:18:02Z",
    "content": "Check:\n  all:\n    - name: VISIT\n      operator: non_empty\n    - name: SVPRESP\n      operator: equal_to\n      value: Y\n    - name: VISIT\n      operator: is_not_contained_by\n      value: $tv_visit\nMatch Datasets:\n  - Name: SV\n    Keys:\n      - USUBJID\n      - VISIT\n\nCore:\n  Id: CDISC.SDTMIG.CG0031_sfqc\n  Version: '1'\n  Status: Draft\nDescription: Verify that a domain visit value is planned by existing in TV.VISIT\nOperations:\n  - domain: TV\n    id: $tv_visit\n    name: VISIT\n    operator: distinct\nOutcome:\n  Message: Visit Value cannot be found in Trial Visit (TV) domain\n  Output Variables:\n    - VISIT\n    - VISITNUM\n\nRule Type: Record Data\nSensitivity: Value\nAuthorities:\n  - Organization: CDISC\n    Standards:\n      - Name: SDTMIG\n        Version: '3.4'\n        References:\n          - Origin: SDTM and SDTMIG Conformance Rules\n            Rule Identifier:\n              Id: CG0031\n              Version: '1'\n            Version: '2.0'\n            Citations:\n              - Cited Guidance: For planned visits, values of VISIT, VISITNUM, and\n                  VISITDY must be those  defined in the Trial Visits (TV) dataset\n                  (Section 7.3.1, Trial Visits).\n                Document: IG v3.4\n                Item: ''\n                Section: 4.4.5\nScope:\n  Classes:\n    Include:\n      - ALL\n  Domains:\n    Exclude:\n      - TV\n",
    "created": "2022-03-10T17:14:52Z",
    "creator": {
        "id": "57474fac-237e-4693-bb37-7826b02737da"
    },
    "json": {
        "Check": {
            "all": [
                {
                    "name": "VISIT",
                    "operator": "non_empty"
                },
                {
                    "name": "SVPRESP",
                    "operator": "equal_to",
                    "value": "Y"
                },
                {
                    "name": "VISIT",
                    "operator": "is_not_contained_by",
                    "value": "$tv_visit"
                }
            ]
        },
        "Match_Datasets": [
            {
                "Name": "SV",
                "Keys": [
                    "USUBJID",
                    "VISIT"
                ]
            }
        ],
        "Core": {
            "Id": "CDISC.SDTMIG.CG0031_sfqc",
            "Version": "1",
            "Status": "Draft"
        },
        "Description": "Verify that a domain visit value is planned by existing in TV.VISIT",
        "Operations": [
            {
                "domain": "TV",
                "id": "$tv_visit",
                "name": "VISIT",
                "operator": "distinct"
            }
        ],
        "Outcome": {
            "Message": "Visit Value cannot be found in Trial Visit (TV) domain",
            "Output_Variables": [
                "VISIT",
                "VISITNUM"
            ]
        },
        "Rule_Type": "Record Data",
        "Sensitivity": "Value",
        "Authorities": [
            {
                "Organization": "CDISC",
                "Standards": [
                    {
                        "Name": "SDTMIG",
                        "Version": "3.4",
                        "References": [
                            {
                                "Origin": "SDTM and SDTMIG Conformance Rules",
                                "Rule_Identifier": {
                                    "Id": "CG0031",
                                    "Version": "1"
                                },
                                "Version": "2.0",
                                "Citations": [
                                    {
                                        "Cited_Guidance": "For planned visits, values of VISIT, VISITNUM, and VISITDY must be those  defined in the Trial Visits (TV) dataset (Section 7.3.1, Trial Visits).",
                                        "Document": "IG v3.4",
                                        "Item": "",
                                        "Section": "4.4.5"
                                    }
                                ]
                            }
                        ]
                    }
                ]
            }
        ],
        "Scope": {
            "Classes": {
                "Include": [
                    "ALL"
                ]
            },
            "Domains": {
                "Exclude": [
                    "TV"
                ]
            }
        }
    }
}