{
    "id": "c2a79a5b-32a4-40f4-bc84-9ec8a457105a",
    "changed": "2022-03-15T22:58:30Z",
    "content": "Check:\n  all:\n    - name: variable_name\n      operator: not_equal_to\n      value: define_variable_name\nCore:\n  Id: CDISC.SDTMIG.CG0013\n  Version: '1'\n  Status: Draft\nDescription: Trigger error when variable is not an allowed variable for an Observation\n  Class\nOutcome:\n  Message: Variable is not an allowed variable for an Observation Class\nRule Type: Variable Metadata Check against Define XML\nSensitivity: Record\nAuthorities:\n  - Organization: CDISC\n    Standards:\n      - Name: SDTMIG\n        Version: '3.4'\n        References:\n          - Origin: SDTM and SDTMIG Conformance Rules\n            Rule Identifier:\n              Id: CG0013\n              Version: '1'\n            Version: '2.0'\n            Citations:\n              - Cited Guidance: Sponsors may not add any variables other than those\n                  described in the preceding three bullets. . . . Standard variables\n                  must not be renamed or modified for novel usage.\n                Document: IG v3.4\n                Section: '2.5'\n              - Cited Guidance: Each observation consists of a series of named variables.\n                Document: Model v2.0\n                Section: Model Concepts and Terms --Variables\n              - Cited Guidance: Domain-specific variables, a concept introduced in\n                  SDTM v1.5, are for use in a limited number of designated domains\n                  and will be identified in the appropriate implementation guide.]\n                Document: Model v2.0\n                Section: The General Observation Classes\nScope:\n  Classes:\n    Include:\n      - ALL\n  Domains:\n    Include:\n      - ALL\n",
    "created": "2021-11-06T04:43:23Z",
    "creator": {
        "id": "ff471ff8-f131-4cf5-9712-c79cce6301a1"
    },
    "json": {
        "Check": {
            "all": [
                {
                    "name": "variable_name",
                    "operator": "not_equal_to",
                    "value": "define_variable_name"
                }
            ]
        },
        "Core": {
            "Id": "CDISC.SDTMIG.CG0013",
            "Version": "1",
            "Status": "Draft"
        },
        "Description": "Trigger error when variable is not an allowed variable for an Observation Class",
        "Outcome": {
            "Message": "Variable is not an allowed variable for an Observation Class"
        },
        "Rule_Type": "Variable Metadata Check against Define XML",
        "Sensitivity": "Record",
        "Authorities": [
            {
                "Organization": "CDISC",
                "Standards": [
                    {
                        "Name": "SDTMIG",
                        "Version": "3.4",
                        "References": [
                            {
                                "Origin": "SDTM and SDTMIG Conformance Rules",
                                "Rule_Identifier": {
                                    "Id": "CG0013",
                                    "Version": "1"
                                },
                                "Version": "2.0",
                                "Citations": [
                                    {
                                        "Cited_Guidance": "Sponsors may not add any variables other than those described in the preceding three bullets. . . . Standard variables must not be renamed or modified for novel usage.",
                                        "Document": "IG v3.4",
                                        "Section": "2.5"
                                    },
                                    {
                                        "Cited_Guidance": "Each observation consists of a series of named variables.",
                                        "Document": "Model v2.0",
                                        "Section": "Model Concepts and Terms --Variables"
                                    },
                                    {
                                        "Cited_Guidance": "Domain-specific variables, a concept introduced in SDTM v1.5, are for use in a limited number of designated domains and will be identified in the appropriate implementation guide.]",
                                        "Document": "Model v2.0",
                                        "Section": "The General Observation Classes"
                                    }
                                ]
                            }
                        ]
                    }
                ]
            }
        ],
        "Scope": {
            "Classes": {
                "Include": [
                    "ALL"
                ]
            },
            "Domains": {
                "Include": [
                    "ALL"
                ]
            }
        }
    }
}