{
    "id": "fbcb6a83-c67a-4d4c-a8ab-c15eb9bf0ec8",
    "changed": "2022-03-05T21:38:34Z",
    "content": "Check:\n  all:\n    - name: SVPRESP\n      operator: equal_to\n      value: Y\n    - name: VISITNUM\n      operator: is_not_contained_by\n      value: $TV_VISITNUM\nMatch Datasets:\n  - Name: SV\n    Keys:\n      - USUBJID\n      - VISITNUM\nOperations:\n  - domain: TV\n    id: $TV_VISITNUM\n    name: VISITNUM\n    operator: distinct\nCore:\n  Id: QC.CDISC.SDTMIG.CG0033\n  Version: '1'\n  Status: Draft\nDescription: If VISITNUM is not null and VISIT is planned then VISITNUM should be\n  among TV.VISITNUM\nOutcome:\n  Message: For a planned visit, non missing VISITNUM value must be among those present\n    in TV.VISITNUM\n  Output Variables:\n    - VISITNUM\n    - SVPRESP\nRule Type: Record Data\nSensitivity: Record\nAuthorities:\n  - Organization: CDISC\n    Standards:\n      - Name: SDTMIG\n        Version: '3.4'\n        References:\n          - Origin: SDTM and SDTMIG Conformance Rules\n            Rule Identifier:\n              Id: CG0033\n              Version: '1'\n            Version: '2.0'\n            Citations:\n              - Cited Guidance: For planned visits, values of VISIT, VISITNUM, and\n                  VISITDY must be those defined in the Trial Visits (TV) dataset (Section\n                  7.3.1, Trial Visits).\n                Document: SDTMIG v3.4\n                Item: Specification\n                Section: 4.4.5\nScope:\n  Classes:\n    Include:\n      - ALL\n  Domains:\n    Exclude:\n      - TV\n",
    "created": "2022-03-04T21:26:34Z",
    "creator": {
        "id": "b5bc818b-4ec4-4952-951f-0fbca010be52"
    },
    "json": {
        "Check": {
            "all": [
                {
                    "name": "SVPRESP",
                    "operator": "equal_to",
                    "value": "Y"
                },
                {
                    "name": "VISITNUM",
                    "operator": "is_not_contained_by",
                    "value": "$TV_VISITNUM"
                }
            ]
        },
        "Match_Datasets": [
            {
                "Name": "SV",
                "Keys": [
                    "USUBJID",
                    "VISITNUM"
                ]
            }
        ],
        "Operations": [
            {
                "domain": "TV",
                "id": "$TV_VISITNUM",
                "name": "VISITNUM",
                "operator": "distinct"
            }
        ],
        "Core": {
            "Id": "QC.CDISC.SDTMIG.CG0033",
            "Version": "1",
            "Status": "Draft"
        },
        "Description": "If VISITNUM is not null and VISIT is planned then VISITNUM should be among TV.VISITNUM",
        "Outcome": {
            "Message": "For a planned visit, non missing VISITNUM value must be among those present in TV.VISITNUM",
            "Output_Variables": [
                "VISITNUM",
                "SVPRESP"
            ]
        },
        "Rule_Type": "Record Data",
        "Sensitivity": "Record",
        "Authorities": [
            {
                "Organization": "CDISC",
                "Standards": [
                    {
                        "Name": "SDTMIG",
                        "Version": "3.4",
                        "References": [
                            {
                                "Origin": "SDTM and SDTMIG Conformance Rules",
                                "Rule_Identifier": {
                                    "Id": "CG0033",
                                    "Version": "1"
                                },
                                "Version": "2.0",
                                "Citations": [
                                    {
                                        "Cited_Guidance": "For planned visits, values of VISIT, VISITNUM, and VISITDY must be those defined in the Trial Visits (TV) dataset (Section 7.3.1, Trial Visits).",
                                        "Document": "SDTMIG v3.4",
                                        "Item": "Specification",
                                        "Section": "4.4.5"
                                    }
                                ]
                            }
                        ]
                    }
                ]
            }
        ],
        "Scope": {
            "Classes": {
                "Include": [
                    "ALL"
                ]
            },
            "Domains": {
                "Exclude": [
                    "TV"
                ]
            }
        }
    }
}