{
    "id": "568cf2e7-e79d-4cf4-9ba9-29f18335c3ff",
    "changed": "2022-12-02T13:10:25.931Z",
    "content": "Check:\n  all:\n    - name: EPOCH\n      operator: is_not_contained_by\n      value: $ta_epoch\n    - name: EPOCH\n      operator: non_empty\nCore:\n  Id: CDISC.SDTMIG.CG0009\n  Version: '1'\n  Status: Draft\nDescription: Raise an error when EPOCH is not in TA.EPOCH\nOperations:\n  - domain: TA\n    id: $ta_epoch\n    name: EPOCH\n    operator: distinct\nOutcome:\n  Message: EPOCH is not in TA.EPOCH\n  Output Variables:\n    - EPOCH\nRule Type: Record Data\nSensitivity: Record\nAuthorities:\n  - Organization: CDISC\n    Standards:\n      - Name: SDTMIG\n        Version: '3.4'\n        References:\n          - Origin: SDTM and SDTMIG Conformance Rules\n            Rule Identifier:\n              Id: CG0009\n              Version: '1'\n            Version: '2.0'\n            Citations:\n              - Cited Guidance: EPOCH may be included as a timing variable as in other\n                  general-observation-class domains. In DS, EPOCH is based on DSSTDTC.\n                  The values of EPOCH are drawn from the Trial Arms(TA) dataset (Section\n                  7.2.1, Trial Arms).\n                Document: SDTMIG v3.4\n                Item: DS, Assumption 4.c\n                Section: 6.2.3\n      - Name: SDTMIG\n        Version: '3.3'\n        References:\n          - Origin: SDTM and SDTMIG Conformance Rules\n            Rule Identifier:\n              Id: CG0009\n              Version: '1'\n            Version: '2.0'\n            Citations:\n              - Cited Guidance: EPOCH may be included as a timing variable as in other\n                  general-observation-class domains. In DS, EPOCH is based on DSSTDTC.\n                  The values of EPOCH are drawn from the Trial Arms (TA) dataset (Section\n                  7.2.1, Trial Arms).\n                Document: SDTMIG v3.3\n                Item: DS, Assumption 4.c\n                Section: 6.2.3\n      - Name: SDTMIG\n        Version: '3.2'\n        References:\n          - Origin: SDTM and SDTMIG Conformance Rules\n            Rule Identifier:\n              Id: CG0009\n              Version: '1'\n            Version: '2.0'\n            Citations:\n              - Cited Guidance: '...EPOCH, as a Timing variable, is the name of the\n                  Epoch during which --STDTC or --DTC falls. The values of EPOCH are\n                  drawn from the Trial Arms domain, Section 7.2 - Experimental Design\n                  Trial Arms (TA)'\n                Document: SDTMIG v3.2\n                Item: DS, Assumption 3.c\n                Section: '6.2'\nScope:\n  Classes:\n    Include:\n      - ALL\n  Domains:\n    Include:\n      - ALL\n",
    "created": "2021-09-29T23:51:34Z",
    "creator": {
        "id": "e7bbd139-9a5c-4b86-859e-e4854e7724fe"
    },
    "json": {
        "Check": {
            "all": [
                {
                    "name": "EPOCH",
                    "operator": "is_not_contained_by",
                    "value": "$ta_epoch"
                },
                {
                    "name": "EPOCH",
                    "operator": "non_empty"
                }
            ]
        },
        "Core": {
            "Id": "CDISC.SDTMIG.CG0009",
            "Version": "1",
            "Status": "Draft"
        },
        "Description": "Raise an error when EPOCH is not in TA.EPOCH",
        "Operations": [
            {
                "domain": "TA",
                "id": "$ta_epoch",
                "name": "EPOCH",
                "operator": "distinct"
            }
        ],
        "Outcome": {
            "Message": "EPOCH is not in TA.EPOCH",
            "Output_Variables": [
                "EPOCH"
            ]
        },
        "Rule_Type": "Record Data",
        "Sensitivity": "Record",
        "Authorities": [
            {
                "Organization": "CDISC",
                "Standards": [
                    {
                        "Name": "SDTMIG",
                        "Version": "3.4",
                        "References": [
                            {
                                "Origin": "SDTM and SDTMIG Conformance Rules",
                                "Rule_Identifier": {
                                    "Id": "CG0009",
                                    "Version": "1"
                                },
                                "Version": "2.0",
                                "Citations": [
                                    {
                                        "Cited_Guidance": "EPOCH may be included as a timing variable as in other general-observation-class domains. In DS, EPOCH is based on DSSTDTC. The values of EPOCH are drawn from the Trial Arms(TA) dataset (Section 7.2.1, Trial Arms).",
                                        "Document": "SDTMIG v3.4",
                                        "Item": "DS, Assumption 4.c",
                                        "Section": "6.2.3"
                                    }
                                ]
                            }
                        ]
                    },
                    {
                        "Name": "SDTMIG",
                        "Version": "3.3",
                        "References": [
                            {
                                "Origin": "SDTM and SDTMIG Conformance Rules",
                                "Rule_Identifier": {
                                    "Id": "CG0009",
                                    "Version": "1"
                                },
                                "Version": "2.0",
                                "Citations": [
                                    {
                                        "Cited_Guidance": "EPOCH may be included as a timing variable as in other general-observation-class domains. In DS, EPOCH is based on DSSTDTC. The values of EPOCH are drawn from the Trial Arms (TA) dataset (Section 7.2.1, Trial Arms).",
                                        "Document": "SDTMIG v3.3",
                                        "Item": "DS, Assumption 4.c",
                                        "Section": "6.2.3"
                                    }
                                ]
                            }
                        ]
                    },
                    {
                        "Name": "SDTMIG",
                        "Version": "3.2",
                        "References": [
                            {
                                "Origin": "SDTM and SDTMIG Conformance Rules",
                                "Rule_Identifier": {
                                    "Id": "CG0009",
                                    "Version": "1"
                                },
                                "Version": "2.0",
                                "Citations": [
                                    {
                                        "Cited_Guidance": "...EPOCH, as a Timing variable, is the name of the Epoch during which --STDTC or --DTC falls. The values of EPOCH are drawn from the Trial Arms domain, Section 7.2 - Experimental Design Trial Arms (TA)",
                                        "Document": "SDTMIG v3.2",
                                        "Item": "DS, Assumption 3.c",
                                        "Section": "6.2"
                                    }
                                ]
                            }
                        ]
                    }
                ]
            }
        ],
        "Scope": {
            "Classes": {
                "Include": [
                    "ALL"
                ]
            },
            "Domains": {
                "Include": [
                    "ALL"
                ]
            }
        }
    }
}