{
    "id": "c6639cb5-0af4-4ed6-a38c-091c40127054",
    "changed": "2022-03-08T12:55:36Z",
    "content": "Check:\n  all:\n    - name: --TRTV\n      operator: empty\n    - name: --VAMT\n      operator: non_empty\nCore:\n  Id: CORE-000089\n  Version: '1'\n  Status: Published\nDescription: Raise an error when --TRTV is empty, --VAMT is not empty\nOutcome:\n  Message: Value for --VAMT is populated, when --TRTV is NULL.\n  Output Variables:\n    - --TRTV\n    - --VAMT\nRule Type: Record Data\nSensitivity: Record\nAuthorities:\n  - Organization: CDISC\n    Standards:\n      - Name: SDTMIG\n        Version: '3.4'\n        References:\n          - Origin: SDTM and SDTMIG Conformance Rules\n            Rule Identifier:\n              Id: CG0106\n              Version: '1'\n            Version: '2.0'\n            Citations:\n              - Cited Guidance: '\"--TRTV[A carrier or inert medium in which a medicinally\n                  active agent is administered.]| --VAMT[Amount of the prepared product\n                  (treatment plus vehicle) administered.]\"'\n                Document: Model v2.0\n                Item: --TRTV|--VAMT\n                Section: Interventions\nScope:\n  Classes:\n    Include:\n      - INTERVENTIONS\n  Domains:\n    Include:\n      - ALL\n",
    "created": "2021-10-06T16:24:08Z",
    "creator": {
        "id": "d0881041-369e-4940-b721-5b456d12101b"
    },
    "json": {
        "Check": {
            "all": [
                {
                    "name": "--TRTV",
                    "operator": "empty"
                },
                {
                    "name": "--VAMT",
                    "operator": "non_empty"
                }
            ]
        },
        "Core": {
            "Id": "CORE-000089",
            "Version": "1",
            "Status": "Published"
        },
        "Description": "Raise an error when --TRTV is empty, --VAMT is not empty",
        "Outcome": {
            "Message": "Value for --VAMT is populated, when --TRTV is NULL.",
            "Output_Variables": [
                "--TRTV",
                "--VAMT"
            ]
        },
        "Rule_Type": "Record Data",
        "Sensitivity": "Record",
        "Authorities": [
            {
                "Organization": "CDISC",
                "Standards": [
                    {
                        "Name": "SDTMIG",
                        "Version": "3.4",
                        "References": [
                            {
                                "Origin": "SDTM and SDTMIG Conformance Rules",
                                "Rule_Identifier": {
                                    "Id": "CG0106",
                                    "Version": "1"
                                },
                                "Version": "2.0",
                                "Citations": [
                                    {
                                        "Cited_Guidance": "\"--TRTV[A carrier or inert medium in which a medicinally active agent is administered.]| --VAMT[Amount of the prepared product (treatment plus vehicle) administered.]\"",
                                        "Document": "Model v2.0",
                                        "Item": "--TRTV|--VAMT",
                                        "Section": "Interventions"
                                    }
                                ]
                            }
                        ]
                    }
                ]
            }
        ],
        "Scope": {
            "Classes": {
                "Include": [
                    "INTERVENTIONS"
                ]
            },
            "Domains": {
                "Include": [
                    "ALL"
                ]
            }
        }
    }
}