{
    "id": "84396b9f-09a6-4cc0-bf6c-98a35b9244d9",
    "changed": "2022-07-31T10:01:50Z",
    "content": "Check:\n  all:\n    - name: DTHFL\n      operator: empty\n    - name: DDDTC\n      operator: non_empty\nMatch Datasets:\n  - Name: DD\n    Keys:\n      - USUBJID\nCore:\n  Id: CORE-000108\n  Version: '1'\n  Status: Published\nDescription: When a death date is recorded in DD, DM.DTHFL should equal 'Y'\nOutcome:\n  Message: DD record present for subject, but DTHFL is not equal to \"Y\".\nRule Type: Record Data\nSensitivity: Dataset\nAuthorities:\n  - Organization: CDISC\n    Standards:\n      - Name: SDTMIG\n        Version: '3.4'\n        References:\n          - Origin: SDTM and SDTMIG Conformance Rules\n            Rule Identifier:\n              Id: CG0133\n              Version: '1'\n            Version: '2.0'\n            Citations:\n              - Cited Guidance: Indicates the subject died. Should be \"Y\" or null.\n                  Should be populated even when the death date is unknown\n                Document: IG v3.4\n                Item: Specification\n                Section: '5.2'\n              - Cited Guidance: A findings domain that contains the diagnosis of the\n                  cause of death for a subject.\n                Document: IG v3.4\n                Item: DD Description\n                Section: 6.3.2\nScope:\n  Classes:\n    Include:\n      - SPECIAL-PURPOSE\n  Domains:\n    Include:\n      - DM\n",
    "created": "2021-10-07T14:42:50Z",
    "creator": {
        "id": "2b4aeb2c-5005-4368-8540-ce8c88561cee"
    },
    "json": {
        "Check": {
            "all": [
                {
                    "name": "DTHFL",
                    "operator": "empty"
                },
                {
                    "name": "DDDTC",
                    "operator": "non_empty"
                }
            ]
        },
        "Match_Datasets": [
            {
                "Name": "DD",
                "Keys": [
                    "USUBJID"
                ]
            }
        ],
        "Core": {
            "Id": "CORE-000108",
            "Version": "1",
            "Status": "Published"
        },
        "Description": "When a death date is recorded in DD, DM.DTHFL should equal 'Y'",
        "Outcome": {
            "Message": "DD record present for subject, but DTHFL is not equal to \"Y\"."
        },
        "Rule_Type": "Record Data",
        "Sensitivity": "Dataset",
        "Authorities": [
            {
                "Organization": "CDISC",
                "Standards": [
                    {
                        "Name": "SDTMIG",
                        "Version": "3.4",
                        "References": [
                            {
                                "Origin": "SDTM and SDTMIG Conformance Rules",
                                "Rule_Identifier": {
                                    "Id": "CG0133",
                                    "Version": "1"
                                },
                                "Version": "2.0",
                                "Citations": [
                                    {
                                        "Cited_Guidance": "Indicates the subject died. Should be \"Y\" or null. Should be populated even when the death date is unknown",
                                        "Document": "IG v3.4",
                                        "Item": "Specification",
                                        "Section": "5.2"
                                    },
                                    {
                                        "Cited_Guidance": "A findings domain that contains the diagnosis of the cause of death for a subject.",
                                        "Document": "IG v3.4",
                                        "Item": "DD Description",
                                        "Section": "6.3.2"
                                    }
                                ]
                            }
                        ]
                    }
                ]
            }
        ],
        "Scope": {
            "Classes": {
                "Include": [
                    "SPECIAL-PURPOSE"
                ]
            },
            "Domains": {
                "Include": [
                    "DM"
                ]
            }
        }
    }
}