{
    "id": "589b21fa-a4e9-45b1-a791-a3adbb365f44",
    "changed": "2022-03-14T20:11:34Z",
    "content": "Check:\n  all:\n    - name: IDVAR\n      operator: non_empty\n    - name: RDOMAIN\n      operator: empty\nCore:\n  Id: CORE-000090\n  Version: '1'\n  Status: Published\nDescription: Verify IDVAR is null when RDOMAIN is null\nOutcome:\n  Message: RDOMAIN has a missing value but IDVAR has a non-missing value\n  Output Variables:\n    - RDOMAIN\n    - IDVAR\nRule Type: Record Data\nSensitivity: Record\nAuthorities:\n  - Organization: CDISC\n    Standards:\n      - Name: SDTMIG\n        Version: '3.4'\n        References:\n          - Origin: SDTM and SDTMIG Conformance Rules\n            Rule Identifier:\n              Id: CG0164\n              Version: '1'\n            Version: '2.0'\n            Citations:\n              - Cited Guidance: Identifying variable in the parent dataset that identifies\n                  the record(s) to which the   comment  applies. Examples AESEQ or\n                  CMGRPID. Used only when individual comments are related to domain\n                  records.Null for comments collected on separate CRFs.\n                Document: SDTMIG v3.4\n                Item: Specification\n                Section: '5.1'\nScope:\n  Classes:\n    Include:\n      - SPECIAL-PURPOSE\n  Domains:\n    Include:\n      - CO\n",
    "created": "2021-10-06T16:37:49Z",
    "creator": {
        "id": "24709aaa-3e57-4ee4-a635-6006b165bb1b"
    },
    "json": {
        "Check": {
            "all": [
                {
                    "name": "IDVAR",
                    "operator": "non_empty"
                },
                {
                    "name": "RDOMAIN",
                    "operator": "empty"
                }
            ]
        },
        "Core": {
            "Id": "CORE-000090",
            "Version": "1",
            "Status": "Published"
        },
        "Description": "Verify IDVAR is null when RDOMAIN is null",
        "Outcome": {
            "Message": "RDOMAIN has a missing value but IDVAR has a non-missing value",
            "Output_Variables": [
                "RDOMAIN",
                "IDVAR"
            ]
        },
        "Rule_Type": "Record Data",
        "Sensitivity": "Record",
        "Authorities": [
            {
                "Organization": "CDISC",
                "Standards": [
                    {
                        "Name": "SDTMIG",
                        "Version": "3.4",
                        "References": [
                            {
                                "Origin": "SDTM and SDTMIG Conformance Rules",
                                "Rule_Identifier": {
                                    "Id": "CG0164",
                                    "Version": "1"
                                },
                                "Version": "2.0",
                                "Citations": [
                                    {
                                        "Cited_Guidance": "Identifying variable in the parent dataset that identifies the record(s) to which the   comment  applies. Examples AESEQ or CMGRPID. Used only when individual comments are related to domain records.Null for comments collected on separate CRFs.",
                                        "Document": "SDTMIG v3.4",
                                        "Item": "Specification",
                                        "Section": "5.1"
                                    }
                                ]
                            }
                        ]
                    }
                ]
            }
        ],
        "Scope": {
            "Classes": {
                "Include": [
                    "SPECIAL-PURPOSE"
                ]
            },
            "Domains": {
                "Include": [
                    "CO"
                ]
            }
        }
    }
}