{
    "id": "f20e17a4-e78f-4e35-8c53-efda99424c83",
    "changed": "2022-07-17T09:50:48Z",
    "content": "Check:\n  all:\n    - name: IETEST\n      operator: is_not_contained_by\n      value: $ti_ietest\nOperations:\n  - operator: distinct\n    domain: TI\n    name: IETEST\n    id: $ti_ietest\nCore:\n  Id: CORE-000227\n  Version: '1'\n  Status: Published\nDescription: Check if IETEST is not in TI.IETEST\nOutcome:\n  Message: IETEST is not in TI.IETEST\nRule Type: Record Data\nSensitivity: Record\nAuthorities:\n  - Organization: CDISC\n    Standards:\n      - Name: SDTMIG\n        Version: '3.4'\n        References:\n          - Origin: SDTM and SDTMIG Conformance Rules\n            Rule Identifier:\n              Id: CG0178\n              Version: '1.0'\n            Version: '2.0'\n            Citations:\n              - Cited Guidance: The complete list of Inclusion/Exclusion criteria\n                  can be found in the Trial Inclusion/Exclusion Criteria\u00a0(TI) dataset\n                  described in Section 7.4.1,\u00a0Trial Inclusion/Exclusion Criteria.\n                Document: IG v3.4\n                Item: Specification\n                Section: 6.3.4\nScope:\n  Classes:\n    Include:\n      - FINDINGS\n  Domains:\n    Include:\n      - IE\n",
    "created": "2021-12-09T15:01:32Z",
    "creator": {
        "id": "57b54e45-6455-401d-bba2-4bd1de21716d"
    },
    "json": {
        "Check": {
            "all": [
                {
                    "name": "IETEST",
                    "operator": "is_not_contained_by",
                    "value": "$ti_ietest"
                }
            ]
        },
        "Operations": [
            {
                "operator": "distinct",
                "domain": "TI",
                "name": "IETEST",
                "id": "$ti_ietest"
            }
        ],
        "Core": {
            "Id": "CORE-000227",
            "Version": "1",
            "Status": "Published"
        },
        "Description": "Check if IETEST is not in TI.IETEST",
        "Outcome": {
            "Message": "IETEST is not in TI.IETEST"
        },
        "Rule_Type": "Record Data",
        "Sensitivity": "Record",
        "Authorities": [
            {
                "Organization": "CDISC",
                "Standards": [
                    {
                        "Name": "SDTMIG",
                        "Version": "3.4",
                        "References": [
                            {
                                "Origin": "SDTM and SDTMIG Conformance Rules",
                                "Rule_Identifier": {
                                    "Id": "CG0178",
                                    "Version": "1.0"
                                },
                                "Version": "2.0",
                                "Citations": [
                                    {
                                        "Cited_Guidance": "The complete list of Inclusion/Exclusion criteria can be found in the Trial Inclusion/Exclusion Criteria\u00a0(TI) dataset described in Section 7.4.1,\u00a0Trial Inclusion/Exclusion Criteria.",
                                        "Document": "IG v3.4",
                                        "Item": "Specification",
                                        "Section": "6.3.4"
                                    }
                                ]
                            }
                        ]
                    }
                ]
            }
        ],
        "Scope": {
            "Classes": {
                "Include": [
                    "FINDINGS"
                ]
            },
            "Domains": {
                "Include": [
                    "IE"
                ]
            }
        }
    }
}