{
    "id": "df47583e-71e0-4fdb-b054-5bf3bf1a5f0b",
    "changed": "2022-06-15T11:09:30Z",
    "content": "Check:\n  all:\n    - name: LBTOXGR\n      operator: matches_regex\n      value: .*[a-zA-Z].*     # identifiers string contains characters\r\n    - name: LBTOXGR\n      operator: matches_regex\n      value: .*[0-9].*      #identifies that string also contains a number  \r\nCore:\n  Id: CORE-000169\n  Version: '1'\n  Status: Published\nDescription: Raise a warning when LBTOXGR is not numeric\nOutcome:\n  Message: Verify that LBTOXGR value is not from a numeric scale\n  Output Variables:\n    - LBTOXGR\n    - LBTOX\nRule Type: Record Data\nSensitivity: Record\nAuthorities:\n  - Organization: CDISC\n    Standards:\n      - Name: SDTMIG\n        Version: '3.4'\n        References:\n          - Origin: SDTM and SDTMIG Conformance Rules\n            Rule Identifier:\n              Id: CG0185\n              Version: '1'\n            Version: '2.0'\n            Citations:\n              - Cited Guidance: '\"If value is from a numeric scale, represent only\n                  the number  (e.g., \"2\" and not \"Grade 2\").\"'\n                Document: IG v3.4\n                Section: 6.3.5.6\n                Item: Specification\nScope:\n  Classes:\n    Include:\n      - FINDINGS\n  Domains:\n    Include:\n      - LB\n",
    "created": "2021-10-21T11:30:34Z",
    "creator": {
        "id": "57474fac-237e-4693-bb37-7826b02737da"
    },
    "json": {
        "Check": {
            "all": [
                {
                    "name": "LBTOXGR",
                    "operator": "matches_regex",
                    "value": ".*[a-zA-Z].*"
                },
                {
                    "name": "LBTOXGR",
                    "operator": "matches_regex",
                    "value": ".*[0-9].*"
                }
            ]
        },
        "Core": {
            "Id": "CORE-000169",
            "Version": "1",
            "Status": "Published"
        },
        "Description": "Raise a warning when LBTOXGR is not numeric",
        "Outcome": {
            "Message": "Verify that LBTOXGR value is not from a numeric scale",
            "Output_Variables": [
                "LBTOXGR",
                "LBTOX"
            ]
        },
        "Rule_Type": "Record Data",
        "Sensitivity": "Record",
        "Authorities": [
            {
                "Organization": "CDISC",
                "Standards": [
                    {
                        "Name": "SDTMIG",
                        "Version": "3.4",
                        "References": [
                            {
                                "Origin": "SDTM and SDTMIG Conformance Rules",
                                "Rule_Identifier": {
                                    "Id": "CG0185",
                                    "Version": "1"
                                },
                                "Version": "2.0",
                                "Citations": [
                                    {
                                        "Cited_Guidance": "\"If value is from a numeric scale, represent only the number  (e.g., \"2\" and not \"Grade 2\").\"",
                                        "Document": "IG v3.4",
                                        "Section": "6.3.5.6",
                                        "Item": "Specification"
                                    }
                                ]
                            }
                        ]
                    }
                ]
            }
        ],
        "Scope": {
            "Classes": {
                "Include": [
                    "FINDINGS"
                ]
            },
            "Domains": {
                "Include": [
                    "LB"
                ]
            }
        }
    }
}