{
    "id": "dd47884e-99fc-4263-9430-bafbd09aa32f",
    "changed": "2022-07-17T11:02:59Z",
    "content": "Check:\n  all:\n    - name: LBSTRESU\n      operator: non_empty\n    - name: LBORRESU\n      operator: equals\n      value: LBSTRESU\n    - name: LBORNRHI\n      operator: not_equals\n      value: LBSTNRHI\nCore:\n  Id: CDISC.SDTMIG.CG0189\n  Version: '1'\n  Status: Draft\nDescription: Trigger error if LBSTNRHI is not expressed using the units in LBSTRESU\nOutcome:\n  Message: LBSTNRHI is not expressed using the units in LBSTRESU\nRule Type: Record Data\nSensitivity: Record\nAuthorities:\n  - Organization: CDISC\n    Standards:\n      - Name: SDTMIG\n        Version: '3.4'\n        References:\n          - Origin: SDTM and SDTMIG Conformance Rules\n            Rule Identifier:\n              Id: CG0189\n              Version: '2'\n            Version: '2.0'\n            Citations:\n              - Cited Guidance: Upper end of reference range for continuous measurements\n                  in standardized units.\n                Document: IG v3.4\n                Item: Specification\n                Section: 6.3.5.6\nScope:\n  Classes:\n    Include:\n      - FINDINGS\n  Domains:\n    Include:\n      - LB\n",
    "created": "2021-10-29T06:17:56Z",
    "creator": {
        "id": "ff471ff8-f131-4cf5-9712-c79cce6301a1"
    },
    "json": {
        "Check": {
            "all": [
                {
                    "name": "LBSTRESU",
                    "operator": "non_empty"
                },
                {
                    "name": "LBORRESU",
                    "operator": "equals",
                    "value": "LBSTRESU"
                },
                {
                    "name": "LBORNRHI",
                    "operator": "not_equals",
                    "value": "LBSTNRHI"
                }
            ]
        },
        "Core": {
            "Id": "CDISC.SDTMIG.CG0189",
            "Version": "1",
            "Status": "Draft"
        },
        "Description": "Trigger error if LBSTNRHI is not expressed using the units in LBSTRESU",
        "Outcome": {
            "Message": "LBSTNRHI is not expressed using the units in LBSTRESU"
        },
        "Rule_Type": "Record Data",
        "Sensitivity": "Record",
        "Authorities": [
            {
                "Organization": "CDISC",
                "Standards": [
                    {
                        "Name": "SDTMIG",
                        "Version": "3.4",
                        "References": [
                            {
                                "Origin": "SDTM and SDTMIG Conformance Rules",
                                "Rule_Identifier": {
                                    "Id": "CG0189",
                                    "Version": "2"
                                },
                                "Version": "2.0",
                                "Citations": [
                                    {
                                        "Cited_Guidance": "Upper end of reference range for continuous measurements in standardized units.",
                                        "Document": "IG v3.4",
                                        "Item": "Specification",
                                        "Section": "6.3.5.6"
                                    }
                                ]
                            }
                        ]
                    }
                ]
            }
        ],
        "Scope": {
            "Classes": {
                "Include": [
                    "FINDINGS"
                ]
            },
            "Domains": {
                "Include": [
                    "LB"
                ]
            }
        }
    }
}