{
    "id": "45b8aa3a-3842-4679-bbc8-689acc4a64c6",
    "changed": "2022-02-15T21:27:49Z",
    "content": "Check:\n  all:\n    - name: EXTRT\n      operator: not_equal_to\n      value: TS.TSVAL\n    - name: TS.TSPARMCD\n      operator: starts_with\n      value: TRT\nCore:\n  Id: CDISC.SDTMIG.CG0104\n  Version: '1'\n  Status: Draft\nDescription: Trigger error if EXTRT is not the protocol-specified treatment\nOutcome:\n  Message: EXTRT is not a protocol-specified treatment\nRule Type: Record Data\nSensitivity: Study\nAuthorities:\n  - Organization: CDISC\n    Standards:\n      - Name: SDTMIG\n        Version: '3.4'\n        References:\n          - Origin: SDTM and SDTMIG Conformance Rules\n            Rule Identifier:\n              Id: CG0104\n              Version: '1'\n            Version: '2.0'\n            Citations:\n              - Cited Guidance: Name of the protocol-specified study treatment given\n                  during the dosing period for the observation.\n                Document: IG v3.4\n                Item: Specification\n                Section: 6.1.3.1\nScope:\n  Classes:\n    Include:\n      - INTERVENTIONS\n  Domains:\n    Include:\n      - EX\n",
    "created": "2021-10-29T06:15:00Z",
    "creator": {
        "id": "ff471ff8-f131-4cf5-9712-c79cce6301a1"
    },
    "json": {
        "Check": {
            "all": [
                {
                    "name": "EXTRT",
                    "operator": "not_equal_to",
                    "value": "TS.TSVAL"
                },
                {
                    "name": "TS.TSPARMCD",
                    "operator": "starts_with",
                    "value": "TRT"
                }
            ]
        },
        "Core": {
            "Id": "CDISC.SDTMIG.CG0104",
            "Version": "1",
            "Status": "Draft"
        },
        "Description": "Trigger error if EXTRT is not the protocol-specified treatment",
        "Outcome": {
            "Message": "EXTRT is not a protocol-specified treatment"
        },
        "Rule_Type": "Record Data",
        "Sensitivity": "Study",
        "Authorities": [
            {
                "Organization": "CDISC",
                "Standards": [
                    {
                        "Name": "SDTMIG",
                        "Version": "3.4",
                        "References": [
                            {
                                "Origin": "SDTM and SDTMIG Conformance Rules",
                                "Rule_Identifier": {
                                    "Id": "CG0104",
                                    "Version": "1"
                                },
                                "Version": "2.0",
                                "Citations": [
                                    {
                                        "Cited_Guidance": "Name of the protocol-specified study treatment given during the dosing period for the observation.",
                                        "Document": "IG v3.4",
                                        "Item": "Specification",
                                        "Section": "6.1.3.1"
                                    }
                                ]
                            }
                        ]
                    }
                ]
            }
        ],
        "Scope": {
            "Classes": {
                "Include": [
                    "INTERVENTIONS"
                ]
            },
            "Domains": {
                "Include": [
                    "EX"
                ]
            }
        }
    }
}