{
    "id": "f4130222-f757-4a46-8a0b-902a3353b774",
    "changed": "2022-02-15T21:32:19Z",
    "content": "Check:\n  all:\n    - name:\n      operator:\nCore:\n  Id: CDISC.SDTMIG.CG0167\n  Version: '1'\n  Status: Draft\nDescription: Trigger error when comments are not unsolicited, free-text and voluntary\nOutcome:\n  Message: Comments are not unsolicited, free-text and voluntary\nRule Type: Record Data\nSensitivity: Record\nAuthorities:\n  - Organization: CDISC\n    Standards:\n      - Name: SDTMIG\n        Version: '3.4'\n        References:\n          - Origin: SDTM and SDTMIG Conformance Rules\n            Rule Identifier:\n              Id: CG0167\n              Version: '1'\n            Version: '2.0'\n            Citations:\n              - Cited Guidance: The Comments special-purpose domain provides a solution\n                  for submitting free-text comments related to data in one or more\n                  SDTM domains (as described in Section 8.5, Relating Comments to\n                  a Parent Domain) or collected on a separate CRF page dedicated to\n                  comments. Comments are generally not responses to specific questions;\n                  instead, comments usually consist of voluntary, free-text or unsolicited\n                  observations.\n                Document: IG v3.4\n                Item: Assumption 1\n                Section: '5.1'\nScope:\n  Classes:\n    Include:\n      - SPECIAL-PURPOSE\n  Domains:\n    Include:\n      - CO\n",
    "created": "2021-10-29T06:16:52Z",
    "creator": {
        "id": "ff471ff8-f131-4cf5-9712-c79cce6301a1"
    },
    "json": {
        "Check": {
            "all": [
                {
                    "name": null,
                    "operator": null
                }
            ]
        },
        "Core": {
            "Id": "CDISC.SDTMIG.CG0167",
            "Version": "1",
            "Status": "Draft"
        },
        "Description": "Trigger error when comments are not unsolicited, free-text and voluntary",
        "Outcome": {
            "Message": "Comments are not unsolicited, free-text and voluntary"
        },
        "Rule_Type": "Record Data",
        "Sensitivity": "Record",
        "Authorities": [
            {
                "Organization": "CDISC",
                "Standards": [
                    {
                        "Name": "SDTMIG",
                        "Version": "3.4",
                        "References": [
                            {
                                "Origin": "SDTM and SDTMIG Conformance Rules",
                                "Rule_Identifier": {
                                    "Id": "CG0167",
                                    "Version": "1"
                                },
                                "Version": "2.0",
                                "Citations": [
                                    {
                                        "Cited_Guidance": "The Comments special-purpose domain provides a solution for submitting free-text comments related to data in one or more SDTM domains (as described in Section 8.5, Relating Comments to a Parent Domain) or collected on a separate CRF page dedicated to comments. Comments are generally not responses to specific questions; instead, comments usually consist of voluntary, free-text or unsolicited observations.",
                                        "Document": "IG v3.4",
                                        "Item": "Assumption 1",
                                        "Section": "5.1"
                                    }
                                ]
                            }
                        ]
                    }
                ]
            }
        ],
        "Scope": {
            "Classes": {
                "Include": [
                    "SPECIAL-PURPOSE"
                ]
            },
            "Domains": {
                "Include": [
                    "CO"
                ]
            }
        }
    }
}