{
    "id": "0588b8b5-d903-4357-9b7d-c07df40e0cce",
    "changed": "2022-03-15T19:33:12Z",
    "content": "Check:\n  all:\n    - name: --DOSTXT\n      operator: matches_regex\n      value: ^\\d*\\.?\\d*$\n    - name: --DOSTXT\n      operator: non_empty\nCore:\n  Id: CORE-000094\n  Version: '1'\n  Status: Published\nDescription: Raise an error if --DOSTXT value is numeric.\nOutcome:\n  Message: --DOSTXT value is numeric.\nRule Type: Record Data\nSensitivity: Record\nAuthorities:\n  - Organization: CDISC\n    Standards:\n      - Name: SDTMIG\n        Version: '3.4'\n        References:\n          - Origin: SDTM and SDTMIG Conformance Rules\n            Rule Identifier:\n              Id: CG0112\n              Version: '1'\n            Version: '2.0'\n            Citations:\n              - Cited Guidance: A textual description of the quantity of an agent\n                  (e.g., drug, substance, radiation) taken or absorbed at a single\n                  administration.\n                Document: Model v2.0\n                Section: Interventions\nScope:\n  Classes:\n    Include:\n      - INTERVENTIONS\n  Domains:\n    Include:\n      - ALL\n",
    "created": "2021-10-06T19:04:03Z",
    "creator": {
        "id": "d0881041-369e-4940-b721-5b456d12101b"
    },
    "json": {
        "Check": {
            "all": [
                {
                    "name": "--DOSTXT",
                    "operator": "matches_regex",
                    "value": "^\\d*\\.?\\d*$"
                },
                {
                    "name": "--DOSTXT",
                    "operator": "non_empty"
                }
            ]
        },
        "Core": {
            "Id": "CORE-000094",
            "Version": "1",
            "Status": "Published"
        },
        "Description": "Raise an error if --DOSTXT value is numeric.",
        "Outcome": {
            "Message": "--DOSTXT value is numeric."
        },
        "Rule_Type": "Record Data",
        "Sensitivity": "Record",
        "Authorities": [
            {
                "Organization": "CDISC",
                "Standards": [
                    {
                        "Name": "SDTMIG",
                        "Version": "3.4",
                        "References": [
                            {
                                "Origin": "SDTM and SDTMIG Conformance Rules",
                                "Rule_Identifier": {
                                    "Id": "CG0112",
                                    "Version": "1"
                                },
                                "Version": "2.0",
                                "Citations": [
                                    {
                                        "Cited_Guidance": "A textual description of the quantity of an agent (e.g., drug, substance, radiation) taken or absorbed at a single administration.",
                                        "Document": "Model v2.0",
                                        "Section": "Interventions"
                                    }
                                ]
                            }
                        ]
                    }
                ]
            }
        ],
        "Scope": {
            "Classes": {
                "Include": [
                    "INTERVENTIONS"
                ]
            },
            "Domains": {
                "Include": [
                    "ALL"
                ]
            }
        }
    }
}