{
    "id": "70059b27-800e-4a23-a6e1-0159c03351df",
    "changed": "2022-02-15T21:28:53Z",
    "content": "Check:\n  all:\n    - name: LBORRES\n      operator: non_empty\n    - name: LBSTNRLO\n      operator: empty\nCore:\n  Id: CDISC.SDTMIG.CG0182\n  Version: '1'\n  Status: Draft\nDescription: Raise an error when LBORRES is not empty and LBSTNRLO is empty.\nOutcome:\n  Message: LBORRES is not empty and LBSTNRLO is empty.\nRule Type: Record Data\nSensitivity: Record\nAuthorities:\n  - Organization: CDISC\n    Standards:\n      - Name: SDTMIG\n        Version: '3.4'\n        References:\n          - Origin: SDTM and SDTMIG Conformance Rules\n            Rule Identifier:\n              Id: CG0182\n              Version: '1'\n            Version: '2.0'\n            Citations:\n              - Cited Guidance: 'Lower end of reference range for continuous measurements\n                  for LBSTRESC/LBSTRESN in standardized units. Should be populated  only\n                  for continuous results. '\n                Document: SDTMIG v3.4\n                Item: Specification\n                Section: 6.3.5.6\nScope:\n  Classes:\n    Include:\n      - FINDINGS\n  Domains:\n    Include:\n      - LB\n",
    "created": "2021-12-09T15:21:58Z",
    "creator": {
        "id": "57b54e45-6455-401d-bba2-4bd1de21716d"
    },
    "json": {
        "Check": {
            "all": [
                {
                    "name": "LBORRES",
                    "operator": "non_empty"
                },
                {
                    "name": "LBSTNRLO",
                    "operator": "empty"
                }
            ]
        },
        "Core": {
            "Id": "CDISC.SDTMIG.CG0182",
            "Version": "1",
            "Status": "Draft"
        },
        "Description": "Raise an error when LBORRES is not empty and LBSTNRLO is empty.",
        "Outcome": {
            "Message": "LBORRES is not empty and LBSTNRLO is empty."
        },
        "Rule_Type": "Record Data",
        "Sensitivity": "Record",
        "Authorities": [
            {
                "Organization": "CDISC",
                "Standards": [
                    {
                        "Name": "SDTMIG",
                        "Version": "3.4",
                        "References": [
                            {
                                "Origin": "SDTM and SDTMIG Conformance Rules",
                                "Rule_Identifier": {
                                    "Id": "CG0182",
                                    "Version": "1"
                                },
                                "Version": "2.0",
                                "Citations": [
                                    {
                                        "Cited_Guidance": "Lower end of reference range for continuous measurements for LBSTRESC/LBSTRESN in standardized units. Should be populated  only for continuous results. ",
                                        "Document": "SDTMIG v3.4",
                                        "Item": "Specification",
                                        "Section": "6.3.5.6"
                                    }
                                ]
                            }
                        ]
                    }
                ]
            }
        ],
        "Scope": {
            "Classes": {
                "Include": [
                    "FINDINGS"
                ]
            },
            "Domains": {
                "Include": [
                    "LB"
                ]
            }
        }
    }
}