{
    "id": "fd1ecd41-1265-43eb-87bd-f772e7e45b9f",
    "changed": "2022-02-15T21:32:33Z",
    "content": "Check:\n  all:\n    - name:\n      operator:\n    - name: RSUBJID\n      operator: non_empty\nCore:\n  Id: CDISC.SDTMIG.CG0159\n  Version: '1'\n  Status: Draft\nDescription: Trigger error if relationship described is to a study (but not to individual\n  study subject) and RSUBJID is not null\nOutcome:\n  Message: Relationship described is to a study (but not to individua study subject)\n    and RSUBJID is not null\nRule Type: Record Data\nSensitivity: Record\nAuthorities:\n  - Organization: CDISC\n    Standards:\n      - Name: SDTMIG\n        Version: '3.4'\n        References:\n          - Origin: SDTM and SDTMIG Conformance Rules\n            Rule Identifier:\n              Id: CG0159\n              Version: '1'\n            Version: '2.0'\n            Citations:\n              - Cited Guidance: RSUBJID will be populated with the USUBJID of the\n                  related subject or the POOLID of the related pool.\n                Document: AP Guide v1.0\n                Item: Specification\n                Section: 2.1.1\nScope:\n  Classes:\n    Include:\n      - ASSOCIATED PERSONS\n  Domains:\n    Include:\n      - ALL\n",
    "created": "2021-10-29T06:16:04Z",
    "creator": {
        "id": "ff471ff8-f131-4cf5-9712-c79cce6301a1"
    },
    "json": {
        "Check": {
            "all": [
                {
                    "name": null,
                    "operator": null
                },
                {
                    "name": "RSUBJID",
                    "operator": "non_empty"
                }
            ]
        },
        "Core": {
            "Id": "CDISC.SDTMIG.CG0159",
            "Version": "1",
            "Status": "Draft"
        },
        "Description": "Trigger error if relationship described is to a study (but not to individual study subject) and RSUBJID is not null",
        "Outcome": {
            "Message": "Relationship described is to a study (but not to individua study subject) and RSUBJID is not null"
        },
        "Rule_Type": "Record Data",
        "Sensitivity": "Record",
        "Authorities": [
            {
                "Organization": "CDISC",
                "Standards": [
                    {
                        "Name": "SDTMIG",
                        "Version": "3.4",
                        "References": [
                            {
                                "Origin": "SDTM and SDTMIG Conformance Rules",
                                "Rule_Identifier": {
                                    "Id": "CG0159",
                                    "Version": "1"
                                },
                                "Version": "2.0",
                                "Citations": [
                                    {
                                        "Cited_Guidance": "RSUBJID will be populated with the USUBJID of the related subject or the POOLID of the related pool.",
                                        "Document": "AP Guide v1.0",
                                        "Item": "Specification",
                                        "Section": "2.1.1"
                                    }
                                ]
                            }
                        ]
                    }
                ]
            }
        ],
        "Scope": {
            "Classes": {
                "Include": [
                    "ASSOCIATED PERSONS"
                ]
            },
            "Domains": {
                "Include": [
                    "ALL"
                ]
            }
        }
    }
}