{
    "id": "9607a46e-1e4e-458c-83f4-86c757f8ea63",
    "changed": "2022-02-15T21:30:05Z",
    "content": "Check:\n  all:\n    - name: COVAL1\n      operator: exists\n    - name: COVAL1\n      operator: empty\nCore:\n  Id: CDISC.SDTMIG.CG0169\n  Version: '1'\n  Status: Draft\nDescription: Trigger error when there are no comments greater than 200 characters\n  and COVALn is present\nOutcome:\n  Message: COVALn is present in dataset when no comments are greater than 200 characters\nRule Type: Record Data\nSensitivity: Dataset\nAuthorities:\n  - Organization: CDISC\n    Standards:\n      - Name: SDTMIG\n        Version: '3.4'\n        References:\n          - Origin: SDTM and SDTMIG Conformance Rules\n            Rule Identifier:\n              Id: CG0169\n              Version: '1'\n            Version: '2.0'\n            Citations:\n              - Cited Guidance: 'When the comment text is longer than 200 characters,\n                  the first 200 characters of the comment will be in COVAL, the next\n                  200 in COVAL1, and additional text stored as needed to COVALn. See\n                  example, Rows 3-4. '\n                Document: IG v3.4\n                Item: Assumption 3\n                Section: '5.1'\nScope:\n  Classes:\n    Include:\n      - SPECIAL-PURPOSE\n  Domains:\n    Include:\n      - CO\n",
    "created": "2021-10-29T06:17:14Z",
    "creator": {
        "id": "ff471ff8-f131-4cf5-9712-c79cce6301a1"
    },
    "json": {
        "Check": {
            "all": [
                {
                    "name": "COVAL1",
                    "operator": "exists"
                },
                {
                    "name": "COVAL1",
                    "operator": "empty"
                }
            ]
        },
        "Core": {
            "Id": "CDISC.SDTMIG.CG0169",
            "Version": "1",
            "Status": "Draft"
        },
        "Description": "Trigger error when there are no comments greater than 200 characters and COVALn is present",
        "Outcome": {
            "Message": "COVALn is present in dataset when no comments are greater than 200 characters"
        },
        "Rule_Type": "Record Data",
        "Sensitivity": "Dataset",
        "Authorities": [
            {
                "Organization": "CDISC",
                "Standards": [
                    {
                        "Name": "SDTMIG",
                        "Version": "3.4",
                        "References": [
                            {
                                "Origin": "SDTM and SDTMIG Conformance Rules",
                                "Rule_Identifier": {
                                    "Id": "CG0169",
                                    "Version": "1"
                                },
                                "Version": "2.0",
                                "Citations": [
                                    {
                                        "Cited_Guidance": "When the comment text is longer than 200 characters, the first 200 characters of the comment will be in COVAL, the next 200 in COVAL1, and additional text stored as needed to COVALn. See example, Rows 3-4. ",
                                        "Document": "IG v3.4",
                                        "Item": "Assumption 3",
                                        "Section": "5.1"
                                    }
                                ]
                            }
                        ]
                    }
                ]
            }
        ],
        "Scope": {
            "Classes": {
                "Include": [
                    "SPECIAL-PURPOSE"
                ]
            },
            "Domains": {
                "Include": [
                    "CO"
                ]
            }
        }
    }
}