{
    "id": "0066ab1c-982c-42e6-96f8-e7cbec162a91",
    "changed": "2022-07-30T12:44:23Z",
    "content": "Check:\n  all:\n    - name: USUBJID\n      operator: is_not_unique_set\n      value: DOMAIN\nCore:\n  Id: CDISC.SDTMIG.CG0151\n  Version: '1'\n  Status: Draft\nDescription: USUBJID must be unique across all studies\nOutcome:\n  Message: USUBJID is not unique within study\n  Output Variables:\n    - USUBJID\nRule Type: Record Data\nSensitivity: Study\nAuthorities:\n  - Organization: CDISC\n    Standards:\n      - Name: SDTMIG\n        Version: '3.4'\n        References:\n          - Origin: SDTM and SDTMIG Conformance Rules\n            Rule Identifier:\n              Id: CG0151\n              Version: '1'\n            Version: '2.0'\n            Citations:\n              - Cited Guidance: Identifier used to uniquely identify a subject across\n                  all studies for all applications or submissions involving the product.\n                Document: IG v3.4\n                Item: Specification\n                Section: '5.2'\nScope:\n  Classes:\n    Include:\n      - SPECIAL-PURPOSE\n  Domains:\n    Include:\n      - DM\n",
    "created": "2021-10-29T06:15:36Z",
    "creator": {
        "id": "ff471ff8-f131-4cf5-9712-c79cce6301a1"
    },
    "json": {
        "Check": {
            "all": [
                {
                    "name": "USUBJID",
                    "operator": "is_not_unique_set",
                    "value": "DOMAIN"
                }
            ]
        },
        "Core": {
            "Id": "CDISC.SDTMIG.CG0151",
            "Version": "1",
            "Status": "Draft"
        },
        "Description": "USUBJID must be unique across all studies",
        "Outcome": {
            "Message": "USUBJID is not unique within study",
            "Output_Variables": [
                "USUBJID"
            ]
        },
        "Rule_Type": "Record Data",
        "Sensitivity": "Study",
        "Authorities": [
            {
                "Organization": "CDISC",
                "Standards": [
                    {
                        "Name": "SDTMIG",
                        "Version": "3.4",
                        "References": [
                            {
                                "Origin": "SDTM and SDTMIG Conformance Rules",
                                "Rule_Identifier": {
                                    "Id": "CG0151",
                                    "Version": "1"
                                },
                                "Version": "2.0",
                                "Citations": [
                                    {
                                        "Cited_Guidance": "Identifier used to uniquely identify a subject across all studies for all applications or submissions involving the product.",
                                        "Document": "IG v3.4",
                                        "Item": "Specification",
                                        "Section": "5.2"
                                    }
                                ]
                            }
                        ]
                    }
                ]
            }
        ],
        "Scope": {
            "Classes": {
                "Include": [
                    "SPECIAL-PURPOSE"
                ]
            },
            "Domains": {
                "Include": [
                    "DM"
                ]
            }
        }
    }
}