{
    "id": "029342ac-3023-43f2-8d13-444142f50383",
    "changed": "2022-09-27T11:40:39.545Z",
    "content": "Check:\n  all:\n    - name: DSDECOD\n      operator: equal_to\n      value: DEATH\n      value_is_literal: true\n    - name: DTHFL\n      operator: not_equal_to\n      value: Y\n      value_is_literal: true\nMatch Datasets:\n  - Name: DS\n    Keys:\n      - USUBJID\nCore:\n  Id: CORE-000252\n  Version: '1'\n  Status: Published\nDescription: When DS.DSDECOD is 'DEATH', DTHFL must be 'Y'\nOutcome:\n  Message: DTHFL is not 'Y' when DS.DECOD is \"DEATH\"\n  Output Variables:\n    - USUBJID\nRule Type: Record Data\nSensitivity: Record\nAuthorities:\n  - Organization: CDISC\n    Standards:\n      - Name: SDTMIG\n        Version: '3.4'\n        References:\n          - Origin: SDTM and SDTMIG Conformance Rules\n            Rule Identifier:\n              Id: CG0136\n              Version: '1'\n            Version: '2.0'\n            Citations:\n              - Cited Guidance: Indicates the subject died. Should be Y or null. Should\n                  be populated even when the death date is unknown.\n                Document: IG v3.4\n                Item: Specification\n                Section: '5.2'\nScope:\n  Classes:\n    Include:\n      - SPECIAL-PURPOSE\n  Domains:\n    Include:\n      - DM\n",
    "created": "2022-06-29T12:46:36Z",
    "creator": {
        "id": "ff471ff8-f131-4cf5-9712-c79cce6301a1"
    },
    "json": {
        "Check": {
            "all": [
                {
                    "name": "DSDECOD",
                    "operator": "equal_to",
                    "value": "DEATH",
                    "value_is_literal": true
                },
                {
                    "name": "DTHFL",
                    "operator": "not_equal_to",
                    "value": "Y",
                    "value_is_literal": true
                }
            ]
        },
        "Match_Datasets": [
            {
                "Name": "DS",
                "Keys": [
                    "USUBJID"
                ]
            }
        ],
        "Core": {
            "Id": "CORE-000252",
            "Version": "1",
            "Status": "Published"
        },
        "Description": "When DS.DSDECOD is 'DEATH', DTHFL must be 'Y'",
        "Outcome": {
            "Message": "DTHFL is not 'Y' when DS.DECOD is \"DEATH\"",
            "Output_Variables": [
                "USUBJID"
            ]
        },
        "Rule_Type": "Record Data",
        "Sensitivity": "Record",
        "Authorities": [
            {
                "Organization": "CDISC",
                "Standards": [
                    {
                        "Name": "SDTMIG",
                        "Version": "3.4",
                        "References": [
                            {
                                "Origin": "SDTM and SDTMIG Conformance Rules",
                                "Rule_Identifier": {
                                    "Id": "CG0136",
                                    "Version": "1"
                                },
                                "Version": "2.0",
                                "Citations": [
                                    {
                                        "Cited_Guidance": "Indicates the subject died. Should be Y or null. Should be populated even when the death date is unknown.",
                                        "Document": "IG v3.4",
                                        "Item": "Specification",
                                        "Section": "5.2"
                                    }
                                ]
                            }
                        ]
                    }
                ]
            }
        ],
        "Scope": {
            "Classes": {
                "Include": [
                    "SPECIAL-PURPOSE"
                ]
            },
            "Domains": {
                "Include": [
                    "DM"
                ]
            }
        }
    }
}