{
    "id": "f9ea9a58-254d-42e9-af55-1137344bd2bb",
    "changed": "2022-02-15T21:32:28Z",
    "content": "Check:\n  all:\n    - name: DOMAIN\n      operator: starts_with\n      value: AP\n    - name: DOMAIN\n      operator: matches_regex\n      value: '[A-Z]{0,4}$'\nCore:\n  Id: CDISC.SDTMIG.CG0155\n  Version: '1'\n  Status: Draft\nDescription: Raise error if variable label length = 4\nOutcome:\n  Message: AP Core Domain should start with 'AP' and length should be equal to 4.\nRule Type: Record Data\nSensitivity: Record\nAuthorities:\n  - Organization: CDISC\n    Standards:\n      - Name: SDTMIG\n        Version: '3.4'\n        References:\n          - Origin: SDTM and SDTMIG Conformance Rules\n            Rule Identifier:\n              Id: CG0155\n              Version: '1'\n            Version: '2.0'\n            Citations:\n              - Cited Guidance: Value length = 4 characters beginning with 'AP' and\n                  ending with 2 character SDTM domain.\n                Document: APGuidev1.0\n                Section: '2'\nScope:\n  Classes:\n    Include:\n      - ALL\n  Domains:\n    Include:\n      - AP\n",
    "created": "2021-10-13T19:30:52Z",
    "creator": {
        "id": "bd422eaf-bc35-4410-a098-59b9fe63965e"
    },
    "json": {
        "Check": {
            "all": [
                {
                    "name": "DOMAIN",
                    "operator": "starts_with",
                    "value": "AP"
                },
                {
                    "name": "DOMAIN",
                    "operator": "matches_regex",
                    "value": "[A-Z]{0,4}$"
                }
            ]
        },
        "Core": {
            "Id": "CDISC.SDTMIG.CG0155",
            "Version": "1",
            "Status": "Draft"
        },
        "Description": "Raise error if variable label length = 4",
        "Outcome": {
            "Message": "AP Core Domain should start with 'AP' and length should be equal to 4."
        },
        "Rule_Type": "Record Data",
        "Sensitivity": "Record",
        "Authorities": [
            {
                "Organization": "CDISC",
                "Standards": [
                    {
                        "Name": "SDTMIG",
                        "Version": "3.4",
                        "References": [
                            {
                                "Origin": "SDTM and SDTMIG Conformance Rules",
                                "Rule_Identifier": {
                                    "Id": "CG0155",
                                    "Version": "1"
                                },
                                "Version": "2.0",
                                "Citations": [
                                    {
                                        "Cited_Guidance": "Value length = 4 characters beginning with 'AP' and ending with 2 character SDTM domain.",
                                        "Document": "APGuidev1.0",
                                        "Section": "2"
                                    }
                                ]
                            }
                        ]
                    }
                ]
            }
        ],
        "Scope": {
            "Classes": {
                "Include": [
                    "ALL"
                ]
            },
            "Domains": {
                "Include": [
                    "AP"
                ]
            }
        }
    }
}