{
    "id": "c213248c-ed20-4c98-a70f-29f7005a2bee",
    "changed": "2022-07-31T09:55:47Z",
    "content": "Check:\n  all:\n    - name: --DOSE\n      operator: non_empty\n    - name: --DOSTXT\n      operator: non_empty\nCore:\n  Id: DELETE_CDISC.SDTMIG.CG0111\n  Version: '1'\n  Status: Draft\nDescription: Raise an error when --DOSTXT ^= null and --DOSE ^= null\nOutcome:\n  Message: Both --DOSE and --DOSTXT values are populated\n  Output Variables:\n    - --DOSE\n    - --DOSTXT\nRule Type: Record Data\nSensitivity: Record\nAuthorities:\n  - Organization: CDISC\n    Standards:\n      - Name: SDTMIG\n        Version: '3.4'\n        References:\n          - Origin: SDTM and SDTMIG Conformance Rules\n            Rule Identifier:\n              Id: CG0111\n              Version: '1'\n            Version: '2.0'\n            Citations:\n              - Cited Guidance: Not populated when --DOSE is populated.\n                Document: Model v2.0\n                Item: --DOSTXT\n                Section: Interventions\nScope:\n  Classes:\n    Include:\n      - INTERVENTIONS\n  Domains:\n    Include:\n      - ALL\n",
    "created": "2021-10-06T17:06:28Z",
    "creator": {
        "id": "d0881041-369e-4940-b721-5b456d12101b"
    },
    "json": {
        "Check": {
            "all": [
                {
                    "name": "--DOSE",
                    "operator": "non_empty"
                },
                {
                    "name": "--DOSTXT",
                    "operator": "non_empty"
                }
            ]
        },
        "Core": {
            "Id": "DELETE_CDISC.SDTMIG.CG0111",
            "Version": "1",
            "Status": "Draft"
        },
        "Description": "Raise an error when --DOSTXT ^= null and --DOSE ^= null",
        "Outcome": {
            "Message": "Both --DOSE and --DOSTXT values are populated",
            "Output_Variables": [
                "--DOSE",
                "--DOSTXT"
            ]
        },
        "Rule_Type": "Record Data",
        "Sensitivity": "Record",
        "Authorities": [
            {
                "Organization": "CDISC",
                "Standards": [
                    {
                        "Name": "SDTMIG",
                        "Version": "3.4",
                        "References": [
                            {
                                "Origin": "SDTM and SDTMIG Conformance Rules",
                                "Rule_Identifier": {
                                    "Id": "CG0111",
                                    "Version": "1"
                                },
                                "Version": "2.0",
                                "Citations": [
                                    {
                                        "Cited_Guidance": "Not populated when --DOSE is populated.",
                                        "Document": "Model v2.0",
                                        "Item": "--DOSTXT",
                                        "Section": "Interventions"
                                    }
                                ]
                            }
                        ]
                    }
                ]
            }
        ],
        "Scope": {
            "Classes": {
                "Include": [
                    "INTERVENTIONS"
                ]
            },
            "Domains": {
                "Include": [
                    "ALL"
                ]
            }
        }
    }
}