{
    "id": "94e33b6f-fb7f-4fed-a9d9-c07bc83a8ab2",
    "changed": "2022-07-17T09:54:49Z",
    "content": "Check:\n  all:\n    - name: PESTRESC\n      operator: non_empty\n    - any:\n        - name: PESTRESC\n          operator: equal_to\n          value: PEORRES\n        - name: PESTRES\n          operator: is_contained_by\n          value:\nCore:\n  Id: CDISC.SDTMIG.CG0197\n  Version: '1'\n  Status: Draft\nDescription: Trigger error when PESTRESC ^= null but PESTRESC does not equal PEORRES\n  OR a dictionary coded preferred term\nOutcome:\n  Message: PESTRESC does not equal PEORRES OR a dictionary coded preferred term\n  Output Variables:\n    - PESTRESC\nRule Type: Record Data\nSensitivity: Record\nAuthorities:\n  - Organization: CDISC\n    Standards:\n      - Name: SDTMIG\n        Version: '3.4'\n        References:\n          - Origin: SDTM and SDTMIG Conformance Rules\n            Rule Identifier:\n              Id: CG0197\n              Version: '1'\n            Version: '2.0'\n            Citations:\n              - Cited Guidance: If there are findings for a body system, then either\n                  the dictionary preferred term (if findings are coded using a dictionary)\n                  or PEORRES (if findings are not encoded) should appear here.\n                Document: IG v3.4\n                Item: Specification\n                Section: 6.3.8\nScope:\n  Classes:\n    Include:\n      - FINDINGS\n  Domains:\n    Include:\n      - PE\n",
    "created": "2022-02-05T06:21:48Z",
    "creator": {
        "id": "ff471ff8-f131-4cf5-9712-c79cce6301a1"
    },
    "json": {
        "Check": {
            "all": [
                {
                    "name": "PESTRESC",
                    "operator": "non_empty"
                },
                {
                    "any": [
                        {
                            "name": "PESTRESC",
                            "operator": "equal_to",
                            "value": "PEORRES"
                        },
                        {
                            "name": "PESTRES",
                            "operator": "is_contained_by",
                            "value": null
                        }
                    ]
                }
            ]
        },
        "Core": {
            "Id": "CDISC.SDTMIG.CG0197",
            "Version": "1",
            "Status": "Draft"
        },
        "Description": "Trigger error when PESTRESC ^= null but PESTRESC does not equal PEORRES OR a dictionary coded preferred term",
        "Outcome": {
            "Message": "PESTRESC does not equal PEORRES OR a dictionary coded preferred term",
            "Output_Variables": [
                "PESTRESC"
            ]
        },
        "Rule_Type": "Record Data",
        "Sensitivity": "Record",
        "Authorities": [
            {
                "Organization": "CDISC",
                "Standards": [
                    {
                        "Name": "SDTMIG",
                        "Version": "3.4",
                        "References": [
                            {
                                "Origin": "SDTM and SDTMIG Conformance Rules",
                                "Rule_Identifier": {
                                    "Id": "CG0197",
                                    "Version": "1"
                                },
                                "Version": "2.0",
                                "Citations": [
                                    {
                                        "Cited_Guidance": "If there are findings for a body system, then either the dictionary preferred term (if findings are coded using a dictionary) or PEORRES (if findings are not encoded) should appear here.",
                                        "Document": "IG v3.4",
                                        "Item": "Specification",
                                        "Section": "6.3.8"
                                    }
                                ]
                            }
                        ]
                    }
                ]
            }
        ],
        "Scope": {
            "Classes": {
                "Include": [
                    "FINDINGS"
                ]
            },
            "Domains": {
                "Include": [
                    "PE"
                ]
            }
        }
    }
}