{
    "id": "1f63cd8c-cd94-4fdf-b042-d7e2b9391c27",
    "changed": "2022-03-21T19:38:41Z",
    "content": "Check:\n  all:\n    - name: MS\n      operator: exists\n    - name: MB\n      operator: not_exists\nCore:\n  Id: CORE-000188\n  Version: '1'\n  Status: Published\nDescription: Trigger error if MS dataset is present and MB dataset is not present.\nOutcome:\n  Message: The MB dataset is not present when the MS dataset is present.\nRule Type: Domain Presence Check\nSensitivity: Dataset\nAuthorities:\n  - Organization: CDISC\n    Standards:\n      - Name: SDTMIG\n        Version: '3.4'\n        References:\n          - Origin: SDTM and SDTMIG Conformance Rules\n            Rule Identifier:\n              Id: CG0191\n              Version: '1'\n            Version: '2.0'\n            Citations:\n              - Cited Guidance: The domain pair uses DOMAIN as an Identifier to group\n                  parent records (e.g., MB) from child records (e.g., MS) and enables\n                  a dataset-level relationship to be described in RELREC.\n                Document: IG v3.4\n                Item: Item 1, bullet 5\n                Section: '2.6'\n              - Cited Guidance: MS is used for representing data from drug susceptibility\n                  testing on the organisms identified in MB.\n                Document: IG v3.4\n                Section: 6.3.5.4\nScope:\n  Classes:\n    Include:\n      - FINDINGS\n  Domains:\n    Include:\n      - MS\n",
    "created": "2021-10-29T06:18:15Z",
    "creator": {
        "id": "ff471ff8-f131-4cf5-9712-c79cce6301a1"
    },
    "json": {
        "Check": {
            "all": [
                {
                    "name": "MS",
                    "operator": "exists"
                },
                {
                    "name": "MB",
                    "operator": "not_exists"
                }
            ]
        },
        "Core": {
            "Id": "CORE-000188",
            "Version": "1",
            "Status": "Published"
        },
        "Description": "Trigger error if MS dataset is present and MB dataset is not present.",
        "Outcome": {
            "Message": "The MB dataset is not present when the MS dataset is present."
        },
        "Rule_Type": "Domain Presence Check",
        "Sensitivity": "Dataset",
        "Authorities": [
            {
                "Organization": "CDISC",
                "Standards": [
                    {
                        "Name": "SDTMIG",
                        "Version": "3.4",
                        "References": [
                            {
                                "Origin": "SDTM and SDTMIG Conformance Rules",
                                "Rule_Identifier": {
                                    "Id": "CG0191",
                                    "Version": "1"
                                },
                                "Version": "2.0",
                                "Citations": [
                                    {
                                        "Cited_Guidance": "The domain pair uses DOMAIN as an Identifier to group parent records (e.g., MB) from child records (e.g., MS) and enables a dataset-level relationship to be described in RELREC.",
                                        "Document": "IG v3.4",
                                        "Item": "Item 1, bullet 5",
                                        "Section": "2.6"
                                    },
                                    {
                                        "Cited_Guidance": "MS is used for representing data from drug susceptibility testing on the organisms identified in MB.",
                                        "Document": "IG v3.4",
                                        "Section": "6.3.5.4"
                                    }
                                ]
                            }
                        ]
                    }
                ]
            }
        ],
        "Scope": {
            "Classes": {
                "Include": [
                    "FINDINGS"
                ]
            },
            "Domains": {
                "Include": [
                    "MS"
                ]
            }
        }
    }
}