{
    "id": "c0028f16-721f-4e5c-883e-99417c12214d",
    "changed": "2022-08-02T12:46:32Z",
    "content": "Check:\n  all:\n    - name: EXTRT\n      operator: equal_to\n      value: PLACEBO\n    - name: EXDOSE\n      operator: not_equal_to\n      value: 0\nCore:\n  Id: CORE-000005\n  Version: '1'\n  Status: Published\nDescription: When EXTRT is PLACEBO, EXDOSE must equal 0\nOutcome:\n  Message: EXTRT is PLACEBO, but EXDOSE is not equal to 0.\n  Output Variables:\n    - EXTRT\n    - EXDOSE\nRule Type: Record Data\nSensitivity: Record\nAuthorities:\n  - Organization: CDISC\n    Standards:\n      - Name: SDTMIG\n        Version: '3.4'\n        References:\n          - Origin: SDTM and SDTMIG Conformance Rules\n            Rule Identifier:\n              Id: CG0102\n              Version: '1'\n            Version: '2.0'\n            Citations:\n              - Cited Guidance: Doses of placebo should be represented by EXTRT =\n                  \"PLACEBO\" and EXDOSE = \"0\" (indicating 0 mg of active ingredient\n                  was taken or administered).\n                Document: SDTMIG v3.4\n                Item: Assumption 2b\n                Section: 6.1.3.1\nScope:\n  Classes:\n    Include:\n      - INTERVENTIONS\n  Domains:\n    Include:\n      - EX\n",
    "created": "2021-09-24T22:27:58Z",
    "creator": {
        "id": "f9333394-14e8-48f3-9a3a-62f1e3cf098c"
    },
    "json": {
        "Check": {
            "all": [
                {
                    "name": "EXTRT",
                    "operator": "equal_to",
                    "value": "PLACEBO"
                },
                {
                    "name": "EXDOSE",
                    "operator": "not_equal_to",
                    "value": 0
                }
            ]
        },
        "Core": {
            "Id": "CORE-000005",
            "Version": "1",
            "Status": "Published"
        },
        "Description": "When EXTRT is PLACEBO, EXDOSE must equal 0",
        "Outcome": {
            "Message": "EXTRT is PLACEBO, but EXDOSE is not equal to 0.",
            "Output_Variables": [
                "EXTRT",
                "EXDOSE"
            ]
        },
        "Rule_Type": "Record Data",
        "Sensitivity": "Record",
        "Authorities": [
            {
                "Organization": "CDISC",
                "Standards": [
                    {
                        "Name": "SDTMIG",
                        "Version": "3.4",
                        "References": [
                            {
                                "Origin": "SDTM and SDTMIG Conformance Rules",
                                "Rule_Identifier": {
                                    "Id": "CG0102",
                                    "Version": "1"
                                },
                                "Version": "2.0",
                                "Citations": [
                                    {
                                        "Cited_Guidance": "Doses of placebo should be represented by EXTRT = \"PLACEBO\" and EXDOSE = \"0\" (indicating 0 mg of active ingredient was taken or administered).",
                                        "Document": "SDTMIG v3.4",
                                        "Item": "Assumption 2b",
                                        "Section": "6.1.3.1"
                                    }
                                ]
                            }
                        ]
                    }
                ]
            }
        ],
        "Scope": {
            "Classes": {
                "Include": [
                    "INTERVENTIONS"
                ]
            },
            "Domains": {
                "Include": [
                    "EX"
                ]
            }
        }
    }
}