{
    "id": "4a4aeaa9-02fb-4f65-ae0b-8eac62026a40",
    "changed": "2022-02-15T21:27:55Z",
    "content": "Check:\n  all:\n    - name: EXDOSU\n      operator: not_equal_to\n      value: TS.TSVAL\n    - name: TS.TSPARMCD\n      operator: starts_with\n      value: DOSU\nCore:\n  Id: CDISC.SDTMIG.CG0103\n  Version: '1'\n  Status: Draft\nDescription: Trigger error if EXDOSU not expressed in protocol-specified units\nOutcome:\n  Message: EXDOSU is not expressed using protocol-specific units\nRule Type: Record Data\nSensitivity: Domain\nAuthorities:\n  - Organization: CDISC\n    Standards:\n      - Name: SDTMIG\n        Version: '3.4'\n        References:\n          - Origin: SDTM and SDTMIG Conformance Rules\n            Rule Identifier:\n              Id: CG0103\n              Version: '1'\n            Version: '2.0'\n            Citations:\n              - Cited Guidance: Units for EXDOSE, EXDOSTOT, or EXDOSTXT representing\n                  protocol-specified values.\n                Document: IG v3.4\n                Item: Specification\n                Section: 6.1.3.1\nScope:\n  Classes:\n    Include:\n      - INTERVENTIONS\n  Domains:\n    Include:\n      - EX\n",
    "created": "2021-10-29T06:14:45Z",
    "creator": {
        "id": "ff471ff8-f131-4cf5-9712-c79cce6301a1"
    },
    "json": {
        "Check": {
            "all": [
                {
                    "name": "EXDOSU",
                    "operator": "not_equal_to",
                    "value": "TS.TSVAL"
                },
                {
                    "name": "TS.TSPARMCD",
                    "operator": "starts_with",
                    "value": "DOSU"
                }
            ]
        },
        "Core": {
            "Id": "CDISC.SDTMIG.CG0103",
            "Version": "1",
            "Status": "Draft"
        },
        "Description": "Trigger error if EXDOSU not expressed in protocol-specified units",
        "Outcome": {
            "Message": "EXDOSU is not expressed using protocol-specific units"
        },
        "Rule_Type": "Record Data",
        "Sensitivity": "Domain",
        "Authorities": [
            {
                "Organization": "CDISC",
                "Standards": [
                    {
                        "Name": "SDTMIG",
                        "Version": "3.4",
                        "References": [
                            {
                                "Origin": "SDTM and SDTMIG Conformance Rules",
                                "Rule_Identifier": {
                                    "Id": "CG0103",
                                    "Version": "1"
                                },
                                "Version": "2.0",
                                "Citations": [
                                    {
                                        "Cited_Guidance": "Units for EXDOSE, EXDOSTOT, or EXDOSTXT representing protocol-specified values.",
                                        "Document": "IG v3.4",
                                        "Item": "Specification",
                                        "Section": "6.1.3.1"
                                    }
                                ]
                            }
                        ]
                    }
                ]
            }
        ],
        "Scope": {
            "Classes": {
                "Include": [
                    "INTERVENTIONS"
                ]
            },
            "Domains": {
                "Include": [
                    "EX"
                ]
            }
        }
    }
}