{
    "id": "073dc966-c7d2-452d-baa3-05cd77320b23",
    "changed": "2022-02-15T21:11:39Z",
    "content": "Check:\n  all:\n    - name:\n      operator:\n    - name: FAOBJ\n      operator: is_not_contained_by\n      value:\n        - --TERM\n    - name: FAOBJ\n      operator: is_not_contained_by\n      value:\n        - --TERM\n    - name: FAOBJ\n      operator: is_not_contained_by\n      value:\n        - --TERM\nCore:\n  Id: CDISC.SDTMIG.CG0174\n  Version: '1'\n  Status: Draft\nDescription: Trigger error when a related record is present in the parent domain dataset\n  and FAOBJ is not in (--TERM, --TRT, --DECOD)\nOutcome:\n  Message: Related record is present in the parent domain dataset and FAOBJ is not\n    in (--TERM, --TRT, --DECOD)\nRule Type: Record Data\nSensitivity: Record\nAuthorities:\n  - Organization: CDISC\n    Standards:\n      - Name: SDTMIG\n        Version: '3.4'\n        References:\n          - Origin: SDTM and SDTMIG Conformance Rules\n            Rule Identifier:\n              Id: CG0174\n              Version: '1'\n            Version: '2.0'\n            Citations:\n              - Cited Guidance: If an FA record does have a parent record, the value\n                  in FAOBJ should match the value in --TERM or --TRT, unless the parent\n                  domain is dictionary coded or subject to controlled terminology,\n                  in which case FAOBJ should match the value in --DECOD.\n                Document: IG v3.4\n                Section: 6.4.3\nScope:\n  Classes:\n    Include:\n      - FINDINGS\n  Domains:\n    Include:\n      - FA\n",
    "created": "2021-10-29T06:17:36Z",
    "creator": {
        "id": "ff471ff8-f131-4cf5-9712-c79cce6301a1"
    },
    "json": {
        "Check": {
            "all": [
                {
                    "name": null,
                    "operator": null
                },
                {
                    "name": "FAOBJ",
                    "operator": "is_not_contained_by",
                    "value": [
                        "--TERM"
                    ]
                },
                {
                    "name": "FAOBJ",
                    "operator": "is_not_contained_by",
                    "value": [
                        "--TERM"
                    ]
                },
                {
                    "name": "FAOBJ",
                    "operator": "is_not_contained_by",
                    "value": [
                        "--TERM"
                    ]
                }
            ]
        },
        "Core": {
            "Id": "CDISC.SDTMIG.CG0174",
            "Version": "1",
            "Status": "Draft"
        },
        "Description": "Trigger error when a related record is present in the parent domain dataset and FAOBJ is not in (--TERM, --TRT, --DECOD)",
        "Outcome": {
            "Message": "Related record is present in the parent domain dataset and FAOBJ is not in (--TERM, --TRT, --DECOD)"
        },
        "Rule_Type": "Record Data",
        "Sensitivity": "Record",
        "Authorities": [
            {
                "Organization": "CDISC",
                "Standards": [
                    {
                        "Name": "SDTMIG",
                        "Version": "3.4",
                        "References": [
                            {
                                "Origin": "SDTM and SDTMIG Conformance Rules",
                                "Rule_Identifier": {
                                    "Id": "CG0174",
                                    "Version": "1"
                                },
                                "Version": "2.0",
                                "Citations": [
                                    {
                                        "Cited_Guidance": "If an FA record does have a parent record, the value in FAOBJ should match the value in --TERM or --TRT, unless the parent domain is dictionary coded or subject to controlled terminology, in which case FAOBJ should match the value in --DECOD.",
                                        "Document": "IG v3.4",
                                        "Section": "6.4.3"
                                    }
                                ]
                            }
                        ]
                    }
                ]
            }
        ],
        "Scope": {
            "Classes": {
                "Include": [
                    "FINDINGS"
                ]
            },
            "Domains": {
                "Include": [
                    "FA"
                ]
            }
        }
    }
}