{
    "id": "59216672-35b2-4501-a041-401ef05ed7a5",
    "changed": "2022-07-17T10:48:31Z",
    "content": "Check:\n  all:\n    - name: RSUBJID\n      operator: is_not_contained_by\n      value: $dm_rsubjid\nCore:\n  Id: CDISC.SDTMIG.CG0157\n  Version: '1'\n  Status: Draft\nDescription: Raise an error when RSUBJID in not in DM.USUBJID\nOperations:\n  - domain: DM\n    id: $dm_rsubjid\n    name: RSUBJID\n    operator: distinct\nOutcome:\n  Message: RSUBJID is not in DM.USUBJID.\n  Output Variables:\n    - APDM.RSUBJID\n    - DM.USUBJID\nRule Type: Record Data\nSensitivity: Record\nAuthorities:\n  - Organization: CDISC\n    Standards:\n      - Name: SDTMIG\n        Version: '3.4'\n        References:\n          - Origin: SDTM and SDTMIG Conformance Rules\n            Rule Identifier:\n              Id: CG0157\n              Version: '1'\n            Version: '2.0'\n            Citations:\n              - Cited Guidance: Relationship described is to a study subject.RSUBJID\n                  is not in DM.USUBJID.\n                Document: APGuidev1.0\n                Item: RSUBJID\n                Section: 2.1.1\nScope:\n  Classes:\n    Include:\n      - SPECIAL-PURPOSE\n  Domains:\n    Include:\n      - AP\n      - DM\n",
    "created": "2021-10-13T19:47:57Z",
    "creator": {
        "id": "bd422eaf-bc35-4410-a098-59b9fe63965e"
    },
    "json": {
        "Check": {
            "all": [
                {
                    "name": "RSUBJID",
                    "operator": "is_not_contained_by",
                    "value": "$dm_rsubjid"
                }
            ]
        },
        "Core": {
            "Id": "CDISC.SDTMIG.CG0157",
            "Version": "1",
            "Status": "Draft"
        },
        "Description": "Raise an error when RSUBJID in not in DM.USUBJID",
        "Operations": [
            {
                "domain": "DM",
                "id": "$dm_rsubjid",
                "name": "RSUBJID",
                "operator": "distinct"
            }
        ],
        "Outcome": {
            "Message": "RSUBJID is not in DM.USUBJID.",
            "Output_Variables": [
                "APDM.RSUBJID",
                "DM.USUBJID"
            ]
        },
        "Rule_Type": "Record Data",
        "Sensitivity": "Record",
        "Authorities": [
            {
                "Organization": "CDISC",
                "Standards": [
                    {
                        "Name": "SDTMIG",
                        "Version": "3.4",
                        "References": [
                            {
                                "Origin": "SDTM and SDTMIG Conformance Rules",
                                "Rule_Identifier": {
                                    "Id": "CG0157",
                                    "Version": "1"
                                },
                                "Version": "2.0",
                                "Citations": [
                                    {
                                        "Cited_Guidance": "Relationship described is to a study subject.RSUBJID is not in DM.USUBJID.",
                                        "Document": "APGuidev1.0",
                                        "Item": "RSUBJID",
                                        "Section": "2.1.1"
                                    }
                                ]
                            }
                        ]
                    }
                ]
            }
        ],
        "Scope": {
            "Classes": {
                "Include": [
                    "SPECIAL-PURPOSE"
                ]
            },
            "Domains": {
                "Include": [
                    "AP",
                    "DM"
                ]
            }
        }
    }
}