{
    "id": "918d9a04-c818-485d-9d79-44efa80862d8",
    "changed": "2022-04-14T13:51:34Z",
    "content": "Check:\n  all:\n    - name: IDVAR\n      operator: non_empty\n    - name: CODTC\n      operator: non_empty\nCore:\n  Id: CORE-000187\n  Version: '1'\n  Status: Published\nDescription: Trigger error when IDVAR is not null and CODTC is not null\nOutcome:\n  Message: CODTC is populated when IDVAR is also populated\n  Output Variables:\n    - USUBJID\n    - IDVAR\n    - CODTC\nRule Type: Record Data\nSensitivity: Record\nAuthorities:\n  - Organization: CDISC\n    Standards:\n      - Name: SDTMIG\n        Version: '3.4'\n        References:\n          - Origin: SDTM and SDTMIG Conformance Rules\n            Rule Identifier:\n              Id: CG0168\n              Version: '1'\n            Version: '2.0'\n            Citations:\n              - Cited Guidance: Date/time of comment on dedicated comment form. Should\n                  be null if this is a child record of another domain or if comment\n                  date was not collected.\n                Document: IG v3.4\n                Item: Specification\n                Section: '5.1'\n              - Cited Guidance: Those related to a specific parent record or group\n                  of parent records, in which case the value of the variable RDOMAIN\n                  is set to the DOMAIN code of the parent record(s) and the variables\n                  IDVAR and IDVARVAL are populated with the key variable name and\n                  value of the parent record(s). Assumptions for populating IDVAR\n                  and IDVARVAL are further described in Section 8.5, Relating Comments\n                  to a Parent Domain. CODTC should be null because the timing of the\n                  parent record(s) is inherited by the comment record. See example,\n                  Rows 3-5.\n                Document: IG v3.4\n                Item: Assumption 2c\n                Section: '5.1'\nScope:\n  Classes:\n    Include:\n      - SPECIAL-PURPOSE\n  Domains:\n    Include:\n      - CO\n",
    "created": "2021-10-29T06:17:02Z",
    "creator": {
        "id": "ff471ff8-f131-4cf5-9712-c79cce6301a1"
    },
    "json": {
        "Check": {
            "all": [
                {
                    "name": "IDVAR",
                    "operator": "non_empty"
                },
                {
                    "name": "CODTC",
                    "operator": "non_empty"
                }
            ]
        },
        "Core": {
            "Id": "CORE-000187",
            "Version": "1",
            "Status": "Published"
        },
        "Description": "Trigger error when IDVAR is not null and CODTC is not null",
        "Outcome": {
            "Message": "CODTC is populated when IDVAR is also populated",
            "Output_Variables": [
                "USUBJID",
                "IDVAR",
                "CODTC"
            ]
        },
        "Rule_Type": "Record Data",
        "Sensitivity": "Record",
        "Authorities": [
            {
                "Organization": "CDISC",
                "Standards": [
                    {
                        "Name": "SDTMIG",
                        "Version": "3.4",
                        "References": [
                            {
                                "Origin": "SDTM and SDTMIG Conformance Rules",
                                "Rule_Identifier": {
                                    "Id": "CG0168",
                                    "Version": "1"
                                },
                                "Version": "2.0",
                                "Citations": [
                                    {
                                        "Cited_Guidance": "Date/time of comment on dedicated comment form. Should be null if this is a child record of another domain or if comment date was not collected.",
                                        "Document": "IG v3.4",
                                        "Item": "Specification",
                                        "Section": "5.1"
                                    },
                                    {
                                        "Cited_Guidance": "Those related to a specific parent record or group of parent records, in which case the value of the variable RDOMAIN is set to the DOMAIN code of the parent record(s) and the variables IDVAR and IDVARVAL are populated with the key variable name and value of the parent record(s). Assumptions for populating IDVAR and IDVARVAL are further described in Section 8.5, Relating Comments to a Parent Domain. CODTC should be null because the timing of the parent record(s) is inherited by the comment record. See example, Rows 3-5.",
                                        "Document": "IG v3.4",
                                        "Item": "Assumption 2c",
                                        "Section": "5.1"
                                    }
                                ]
                            }
                        ]
                    }
                ]
            }
        ],
        "Scope": {
            "Classes": {
                "Include": [
                    "SPECIAL-PURPOSE"
                ]
            },
            "Domains": {
                "Include": [
                    "CO"
                ]
            }
        }
    }
}