{
    "id": "cb0c4f69-a667-4719-913a-f56226954eea",
    "changed": "2022-04-06T09:48:37Z",
    "content": "Check:\n  all:\n    - name: SSSTRESC\n      operator: equal_to\n      value: DEAD\n      value_is_literal: true\n    - name: SSDTC\n      operator: date_less_than\n      value: $max_ds_dsstdtc\nCore:\n  Id: CORE-000178\n  Version: '1'\n  Status: Published\nDescription: Raise an error when SSSTRESC = 'DEAD' and SSDTC < max DS.DSSTDTC.\nOperations:\n  - operator: max_date\n    domain: DS\n    name: DSSTDTC\n    id: $max_ds_dsstdtc\n    group:\n      - USUBJID\nOutcome:\n  Message: SSSTRESC = 'DEAD', but SSDTC < max DS.DSSTDTC.\n  Output Variables:\n    - SSSTRESC\n    - SSDTC\n    - $max_ds_dsstdtc\nRule Type: Record Data\nSensitivity: Record\nAuthorities:\n  - Organization: CDISC\n    Standards:\n      - Name: SDTMIG\n        Version: '3.4'\n        References:\n          - Origin: SDTM and SDTMIG Conformance Rules\n            Rule Identifier:\n              Id: CG0172\n              Version: '2'\n            Version: '2.0'\n            Citations:\n              - Cited Guidance: Subject Status does not contain details about the\n                  circumstances of a subject's status.  The response to the status\n                  assessment may trigger collection of additional details,  but those\n                  details are to be stored in appropriate separate domains. For example,\u00a0if\n                  a  subject's survival status\u00a0is \"DEAD\", the date of death must be\n                  stored in DM and within  a final disposition record in DS. Only\n                  the status collection date, the status question,  and the status\n                  response are stored in SS.\n                Document: IG v3.4\n                Item: Assumption 1\n                Section: 6.3.11\nScope:\n  Classes:\n    Include:\n      - FINDINGS\n  Domains:\n    Include:\n      - SS\n",
    "created": "2021-10-28T14:19:36Z",
    "creator": {
        "id": "02c3c969-4787-4d57-b164-e2851035c0e8"
    },
    "json": {
        "Check": {
            "all": [
                {
                    "name": "SSSTRESC",
                    "operator": "equal_to",
                    "value": "DEAD",
                    "value_is_literal": true
                },
                {
                    "name": "SSDTC",
                    "operator": "date_less_than",
                    "value": "$max_ds_dsstdtc"
                }
            ]
        },
        "Core": {
            "Id": "CORE-000178",
            "Version": "1",
            "Status": "Published"
        },
        "Description": "Raise an error when SSSTRESC = 'DEAD' and SSDTC < max DS.DSSTDTC.",
        "Operations": [
            {
                "operator": "max_date",
                "domain": "DS",
                "name": "DSSTDTC",
                "id": "$max_ds_dsstdtc",
                "group": [
                    "USUBJID"
                ]
            }
        ],
        "Outcome": {
            "Message": "SSSTRESC = 'DEAD', but SSDTC < max DS.DSSTDTC.",
            "Output_Variables": [
                "SSSTRESC",
                "SSDTC",
                "$max_ds_dsstdtc"
            ]
        },
        "Rule_Type": "Record Data",
        "Sensitivity": "Record",
        "Authorities": [
            {
                "Organization": "CDISC",
                "Standards": [
                    {
                        "Name": "SDTMIG",
                        "Version": "3.4",
                        "References": [
                            {
                                "Origin": "SDTM and SDTMIG Conformance Rules",
                                "Rule_Identifier": {
                                    "Id": "CG0172",
                                    "Version": "2"
                                },
                                "Version": "2.0",
                                "Citations": [
                                    {
                                        "Cited_Guidance": "Subject Status does not contain details about the circumstances of a subject's status.  The response to the status assessment may trigger collection of additional details,  but those details are to be stored in appropriate separate domains. For example,\u00a0if a  subject's survival status\u00a0is \"DEAD\", the date of death must be stored in DM and within  a final disposition record in DS. Only the status collection date, the status question,  and the status response are stored in SS.",
                                        "Document": "IG v3.4",
                                        "Item": "Assumption 1",
                                        "Section": "6.3.11"
                                    }
                                ]
                            }
                        ]
                    }
                ]
            }
        ],
        "Scope": {
            "Classes": {
                "Include": [
                    "FINDINGS"
                ]
            },
            "Domains": {
                "Include": [
                    "SS"
                ]
            }
        }
    }
}