{
    "id": "68626729-a02b-443b-8da0-666caacc30f9",
    "changed": "2022-02-15T21:28:45Z",
    "content": "Check:\n  all:\n    - name: LBORRES\n      operator: non_empty\n    - name: LBORNRLO\n      operator: non_empty\nCore:\n  Id: CDISC.SDTMIG.CG0180\n  Version: '1'\n  Status: Draft\nDescription: Raise an error when LBORRES ^= continuous measurement and LBORNRLO is\n  not empty.\nOutcome:\n  Message: LBORRES is non empty and LBORNRLO is non empty.\nRule Type: Record Data\nSensitivity: Record\nAuthorities:\n  - Organization: CDISC\n    Standards:\n      - Name: SDTMIG\n        Version: '3.4'\n        References:\n          - Origin: SDTM and SDTMIG Conformance Rules\n            Rule Identifier:\n              Id: CG0180\n              Version: '1'\n            Version: '2.0'\n            Citations:\n              - Cited Guidance: Lower end of reference range for continuous measurements\n                  for LBSTRESC/LBSTRESN in standardized units. Should be populated\n                  only for continuous results.\n                Document: SDTMIG v3.4\n                Item: Specification\n                Section: 6.3.5.6\nScope:\n  Classes:\n    Include:\n      - FINDINGS\n  Domains:\n    Include:\n      - LB\n",
    "created": "2021-09-29T07:21:13Z",
    "creator": {
        "id": "aa629571-d619-478f-970b-a71d04d96a44"
    },
    "json": {
        "Check": {
            "all": [
                {
                    "name": "LBORRES",
                    "operator": "non_empty"
                },
                {
                    "name": "LBORNRLO",
                    "operator": "non_empty"
                }
            ]
        },
        "Core": {
            "Id": "CDISC.SDTMIG.CG0180",
            "Version": "1",
            "Status": "Draft"
        },
        "Description": "Raise an error when LBORRES ^= continuous measurement and LBORNRLO is not empty.",
        "Outcome": {
            "Message": "LBORRES is non empty and LBORNRLO is non empty."
        },
        "Rule_Type": "Record Data",
        "Sensitivity": "Record",
        "Authorities": [
            {
                "Organization": "CDISC",
                "Standards": [
                    {
                        "Name": "SDTMIG",
                        "Version": "3.4",
                        "References": [
                            {
                                "Origin": "SDTM and SDTMIG Conformance Rules",
                                "Rule_Identifier": {
                                    "Id": "CG0180",
                                    "Version": "1"
                                },
                                "Version": "2.0",
                                "Citations": [
                                    {
                                        "Cited_Guidance": "Lower end of reference range for continuous measurements for LBSTRESC/LBSTRESN in standardized units. Should be populated only for continuous results.",
                                        "Document": "SDTMIG v3.4",
                                        "Item": "Specification",
                                        "Section": "6.3.5.6"
                                    }
                                ]
                            }
                        ]
                    }
                ]
            }
        ],
        "Scope": {
            "Classes": {
                "Include": [
                    "FINDINGS"
                ]
            },
            "Domains": {
                "Include": [
                    "LB"
                ]
            }
        }
    }
}