{
    "id": "db0908e8-2071-4f60-a230-42e413b4d353",
    "changed": "2022-09-27T11:41:06.835Z",
    "content": "Check:\n  all:\n    - name: ETCD\n      operator: exists\n    - name: ELEMENT\n      operator: exists\n    - any:\n        - name: ETCD\n          operator: is_not_unique_relationship\n          value: ELEMENT\n        - name: ELEMENT\n          operator: is_not_unique_relationship\n          value: ETCD\nCore:\n  Id: CORE-000132\n  Version: '1'\n  Status: Published\nDescription: When ETCD and ELEMENTCD are present, ETCD and  ELEMENT should have a\n  one-to-one relationship.\nOutcome:\n  Message: ELEMENT and ETCD do not have a one-to-one relationship.\n  Output Variables:\n    - ETCD\n    - ELEMENT\nRule Type: Record Data\nSensitivity: Record\nAuthorities:\n  - Organization: CDISC\n    Standards:\n      - Name: SDTMIG\n        Version: '3.4'\n        References:\n          - Origin: SDTM and SDTMIG Conformance Rules\n            Rule Identifier:\n              Id: CG0154\n              Version: '1'\n            Version: '2.0'\n            Citations:\n              - Cited Guidance: ETCD (the companion to ELEMENT) is limited to 8 characters\n                  and does not have special character restrictions.\n                Document: IG v3.4\n                Item: Specification\n                Section: 5.3|7.2.1|7.2.2\nScope:\n  Classes:\n    Include:\n      - TRIAL DESIGN\n  Domains:\n    Include:\n      - TE\n      - TA\n      - SE\n",
    "created": "2021-10-13T00:24:51Z",
    "creator": {
        "id": "bd422eaf-bc35-4410-a098-59b9fe63965e"
    },
    "json": {
        "Check": {
            "all": [
                {
                    "name": "ETCD",
                    "operator": "exists"
                },
                {
                    "name": "ELEMENT",
                    "operator": "exists"
                },
                {
                    "any": [
                        {
                            "name": "ETCD",
                            "operator": "is_not_unique_relationship",
                            "value": "ELEMENT"
                        },
                        {
                            "name": "ELEMENT",
                            "operator": "is_not_unique_relationship",
                            "value": "ETCD"
                        }
                    ]
                }
            ]
        },
        "Core": {
            "Id": "CORE-000132",
            "Version": "1",
            "Status": "Published"
        },
        "Description": "When ETCD and ELEMENTCD are present, ETCD and  ELEMENT should have a one-to-one relationship.",
        "Outcome": {
            "Message": "ELEMENT and ETCD do not have a one-to-one relationship.",
            "Output_Variables": [
                "ETCD",
                "ELEMENT"
            ]
        },
        "Rule_Type": "Record Data",
        "Sensitivity": "Record",
        "Authorities": [
            {
                "Organization": "CDISC",
                "Standards": [
                    {
                        "Name": "SDTMIG",
                        "Version": "3.4",
                        "References": [
                            {
                                "Origin": "SDTM and SDTMIG Conformance Rules",
                                "Rule_Identifier": {
                                    "Id": "CG0154",
                                    "Version": "1"
                                },
                                "Version": "2.0",
                                "Citations": [
                                    {
                                        "Cited_Guidance": "ETCD (the companion to ELEMENT) is limited to 8 characters and does not have special character restrictions.",
                                        "Document": "IG v3.4",
                                        "Item": "Specification",
                                        "Section": "5.3|7.2.1|7.2.2"
                                    }
                                ]
                            }
                        ]
                    }
                ]
            }
        ],
        "Scope": {
            "Classes": {
                "Include": [
                    "TRIAL DESIGN"
                ]
            },
            "Domains": {
                "Include": [
                    "TE",
                    "TA",
                    "SE"
                ]
            }
        }
    }
}