{
    "id": "bc418819-cbaa-4513-89c9-9aeb3c7ce954",
    "changed": "2022-04-14T14:12:35Z",
    "content": "Check:\n  all:\n    - name: IECAT\n      operator: equal_to\n      value: INCLUSION\n    - name: IEORRES\n      operator: not_equal_to\n      value: N\nCore:\n  Id: CORE-000001\n  Version: '1'\n  Status: Published\nDescription: Raise an error when IECAT=\"INCLUSION\" and IEORRES^=\"N\".\nOutcome:\n  Message: IECAT equals \"INCLUSION\" and IEORRES is not equal to \"N\".\nRule Type: Record Data\nSensitivity: Record\nAuthorities:\n  - Organization: CDISC\n    Standards:\n      - Name: SDTMIG\n        Version: '3.4'\n        References:\n          - Origin: SDTM and SDTMIG Conformance Rules\n            Rule Identifier:\n              Id: CG0176\n              Version: '1'\n            Version: '2.0'\n            Citations:\n              - Cited Guidance: The intent of the domain model is to collect responses\n                  to only those criteria that the subject did not meet, and not the\n                  responses to all criteria.\n                Document: SDTM v3.4\n                Section: 6.3.4\nScope:\n  Classes:\n    Include:\n      - FINDINGS\n  Domains:\n    Include:\n      - IE\n",
    "created": "2021-09-24T06:36:48Z",
    "creator": {
        "id": "ff471ff8-f131-4cf5-9712-c79cce6301a1"
    },
    "json": {
        "Check": {
            "all": [
                {
                    "name": "IECAT",
                    "operator": "equal_to",
                    "value": "INCLUSION"
                },
                {
                    "name": "IEORRES",
                    "operator": "not_equal_to",
                    "value": "N"
                }
            ]
        },
        "Core": {
            "Id": "CORE-000001",
            "Version": "1",
            "Status": "Published"
        },
        "Description": "Raise an error when IECAT=\"INCLUSION\" and IEORRES^=\"N\".",
        "Outcome": {
            "Message": "IECAT equals \"INCLUSION\" and IEORRES is not equal to \"N\"."
        },
        "Rule_Type": "Record Data",
        "Sensitivity": "Record",
        "Authorities": [
            {
                "Organization": "CDISC",
                "Standards": [
                    {
                        "Name": "SDTMIG",
                        "Version": "3.4",
                        "References": [
                            {
                                "Origin": "SDTM and SDTMIG Conformance Rules",
                                "Rule_Identifier": {
                                    "Id": "CG0176",
                                    "Version": "1"
                                },
                                "Version": "2.0",
                                "Citations": [
                                    {
                                        "Cited_Guidance": "The intent of the domain model is to collect responses to only those criteria that the subject did not meet, and not the responses to all criteria.",
                                        "Document": "SDTM v3.4",
                                        "Section": "6.3.4"
                                    }
                                ]
                            }
                        ]
                    }
                ]
            }
        ],
        "Scope": {
            "Classes": {
                "Include": [
                    "FINDINGS"
                ]
            },
            "Domains": {
                "Include": [
                    "IE"
                ]
            }
        }
    }
}