{
    "id": "1c876244-6354-430b-99f5-4d30b917e6a0",
    "changed": "2022-03-14T20:11:25Z",
    "content": "Check:\n  all:\n    - name: IDVARVAL\n      operator: non_empty\n    - name: RDOMAIN\n      operator: empty\nCore:\n  Id: CORE-000017\n  Version: '1'\n  Status: Published\nDescription: Verify RDOMAIN is not null when IDVARVAL is not null\nOutcome:\n  Message: RDOMAIN has a missing value when IDVARVAL has a non-missing value\n  Output Variables:\n    - RDOMAIN\n    - IDVARVAL\nRule Type: Record Data\nSensitivity: Record\nAuthorities:\n  - Organization: CDISC\n    Standards:\n      - Name: SDTMIG\n        Version: '3.4'\n        References:\n          - Origin: SDTM and SDTMIG Conformance Rules\n            Rule Identifier:\n              Id: CG0166\n              Version: '1'\n            Version: '2.0'\n            Citations:\n              - Cited Guidance: Two-character abbreviation for the domain of the parent\n                  record(s). Null for comments collected on a general comments or\n                  additional information CRF page.\n                Document: SDTMIG v3.4\n                Item: Specification\n                Section: '5.1'\nScope:\n  Classes:\n    Include:\n      - SPECIAL-PURPOSE\n  Domains:\n    Include:\n      - CO\n",
    "created": "2021-09-28T16:36:42Z",
    "creator": {
        "id": "24709aaa-3e57-4ee4-a635-6006b165bb1b"
    },
    "json": {
        "Check": {
            "all": [
                {
                    "name": "IDVARVAL",
                    "operator": "non_empty"
                },
                {
                    "name": "RDOMAIN",
                    "operator": "empty"
                }
            ]
        },
        "Core": {
            "Id": "CORE-000017",
            "Version": "1",
            "Status": "Published"
        },
        "Description": "Verify RDOMAIN is not null when IDVARVAL is not null",
        "Outcome": {
            "Message": "RDOMAIN has a missing value when IDVARVAL has a non-missing value",
            "Output_Variables": [
                "RDOMAIN",
                "IDVARVAL"
            ]
        },
        "Rule_Type": "Record Data",
        "Sensitivity": "Record",
        "Authorities": [
            {
                "Organization": "CDISC",
                "Standards": [
                    {
                        "Name": "SDTMIG",
                        "Version": "3.4",
                        "References": [
                            {
                                "Origin": "SDTM and SDTMIG Conformance Rules",
                                "Rule_Identifier": {
                                    "Id": "CG0166",
                                    "Version": "1"
                                },
                                "Version": "2.0",
                                "Citations": [
                                    {
                                        "Cited_Guidance": "Two-character abbreviation for the domain of the parent record(s). Null for comments collected on a general comments or additional information CRF page.",
                                        "Document": "SDTMIG v3.4",
                                        "Item": "Specification",
                                        "Section": "5.1"
                                    }
                                ]
                            }
                        ]
                    }
                ]
            }
        ],
        "Scope": {
            "Classes": {
                "Include": [
                    "SPECIAL-PURPOSE"
                ]
            },
            "Domains": {
                "Include": [
                    "CO"
                ]
            }
        }
    }
}