{
    "id": "5946b813-c208-4101-8c8a-47f86d4a2bf8",
    "changed": "2022-04-04T14:31:53Z",
    "content": "Check:\n  all:\n    - name: IETESTCD\n      operator: is_not_contained_by\n      value: $ti_ietestcd\nOperations:\n  - operator: distinct\n    domain: TI\n    name: IETESTCD\n    id: $ti_ietestcd\nCore:\n  Id: CORE-000228\n  Version: '1'\n  Status: Published\nDescription: Check if IETESTCD is present in TI.IETESTCD\nOutcome:\n  Message: IETESTCD from IE domain does not exist in IETESTCD of TI domain.\n  Output Variables:\n    - IETESTCD\nRule Type: Record Data\nSensitivity: Record\nAuthorities:\n  - Organization: CDISC\n    Standards:\n      - Name: SDTMIG\n        Version: '3.4'\n        References:\n          - Origin: SDTM and SDTMIG Conformance Rules\n            Rule Identifier:\n              Id: CG0179\n              Version: '1'\n            Version: '2.0'\n            Citations:\n              - Cited Guidance: The complete list of Inclusion/Exclusion criteria\n                  can be found in the Trial Inclusion/Exclusion Criteria (TI) dataset\n                  described in Section 7.4.1, Trial Inclusion/Exclusion Criteria.\n                Document: IG v3.4\n                Item: Specification\n                Section: 6.3.4\nScope:\n  Classes:\n    Include:\n      - FINDINGS\n  Domains:\n    Include:\n      - IE\n",
    "created": "2021-12-09T15:04:45Z",
    "creator": {
        "id": "57b54e45-6455-401d-bba2-4bd1de21716d"
    },
    "json": {
        "Check": {
            "all": [
                {
                    "name": "IETESTCD",
                    "operator": "is_not_contained_by",
                    "value": "$ti_ietestcd"
                }
            ]
        },
        "Operations": [
            {
                "operator": "distinct",
                "domain": "TI",
                "name": "IETESTCD",
                "id": "$ti_ietestcd"
            }
        ],
        "Core": {
            "Id": "CORE-000228",
            "Version": "1",
            "Status": "Published"
        },
        "Description": "Check if IETESTCD is present in TI.IETESTCD",
        "Outcome": {
            "Message": "IETESTCD from IE domain does not exist in IETESTCD of TI domain.",
            "Output_Variables": [
                "IETESTCD"
            ]
        },
        "Rule_Type": "Record Data",
        "Sensitivity": "Record",
        "Authorities": [
            {
                "Organization": "CDISC",
                "Standards": [
                    {
                        "Name": "SDTMIG",
                        "Version": "3.4",
                        "References": [
                            {
                                "Origin": "SDTM and SDTMIG Conformance Rules",
                                "Rule_Identifier": {
                                    "Id": "CG0179",
                                    "Version": "1"
                                },
                                "Version": "2.0",
                                "Citations": [
                                    {
                                        "Cited_Guidance": "The complete list of Inclusion/Exclusion criteria can be found in the Trial Inclusion/Exclusion Criteria (TI) dataset described in Section 7.4.1, Trial Inclusion/Exclusion Criteria.",
                                        "Document": "IG v3.4",
                                        "Item": "Specification",
                                        "Section": "6.3.4"
                                    }
                                ]
                            }
                        ]
                    }
                ]
            }
        ],
        "Scope": {
            "Classes": {
                "Include": [
                    "FINDINGS"
                ]
            },
            "Domains": {
                "Include": [
                    "IE"
                ]
            }
        }
    }
}