{
    "id": "3a2770dc-0acb-49f9-9de8-df7179c0762f",
    "changed": "2023-01-31T15:48:29.499Z",
    "content": "Check:\n  all:\n    - name: ECOCCUR\n      operator: not_equal_to\n      value: N\n    - name: ECSTAT\n      operator: empty\n    - name: ECDOSTXT\n      operator: empty\n    - name: ECDOSE\n      operator: less_than_or_equal_to\n      value: 0\nCore:\n  Id: CORE-000137\n  Version: '1'\n  Status: Published\nDescription: Raise an error when ECOCCUR is not equal to 'N', ECSTAT and ECDOSTXT\n  are both empty but ECDOSE less than or equal to 0.\nOutcome:\n  Message: ECOCCUR is not 'N', ECSTAT and ECDOSTXT are both empty but ECDOSE is less\n    than or equal to 0.\n  Output Variables:\n    - ECOCCUR\n    - ECSTAT\n    - ECDOSTXT\n    - ECDOSE\n    - ECSTDTC\nRule Type: Record Data\nSensitivity: Record\nAuthorities:\n  - Organization: CDISC\n    Standards:\n      - Name: SDTMIG\n        Version: '3.4'\n        References:\n          - Origin: SDTM and SDTMIG Conformance Rules\n            Rule Identifier:\n              Id: CG0100\n              Version: '2'\n            Version: '2.0'\n            Citations:\n              - Cited Guidance: For example, if 0 tablets are taken within a timeframe\n                  or 0 mL infused at a visit, then ECOCCUR = 'N' is the standard representation\n                  of the collected doses not taken, not given, or missed. Dose amount\n                  variables (e.g., ECDOSE, ECDOSTXT) must not be set to zero (0) as\n                  an alternative method for indicating doses not taken, not given,\n                  or missed.\n                Document: IG v3.4\n                Item: Assumption 4a\n                Section: 6.1.3.2\n              - Cited Guidance: Qualifiers that indicate dose amount (e.g., ECDOSE,\n                  ECDOSTXT) may be populated with positive (non-zero) values in cases\n                  where the sponsor feels it is necessary and/or appropriate to represent\n                  specific dose amounts not taken, not  given, or missed.\n                Document: IG v3.4\n                Item: Assumption 4b\n                Section: 6.1.3.2\n              - Cited Guidance: For example, if 0 tablets are taken within a timeframe\n                  or 0 mL infused at a visit, then ECOCCUR = 'N' is the standard representation\n                  of the collected doses not taken, not given, or missed. Dose amount\n                  variables (e.g., ECDOSE, ECDOSTXT) must not be set to zero (0) as\n                  an alternative method for indicating doses not taken, not given,\n                  or missed.\n                Document: IG v3.3\n                Item: Assumption 4a\n                Section: 6.1.3.2\n              - Cited Guidance: Qualifiers that indicate dose amount (e.g., ECDOSE,\n                  ECDOSTXT) may be populated with positive (non-zero) values in cases\n                  where the sponsor feels it is necessary and/or appropriate to represent\n                  specific dose amounts not taken, not  given, or missed.\n                Document: IG v3.3\n                Item: Assumption 4b\n                Section: 6.1.3.2\n              - Cited Guidance: For example, if 0 tablets are taken within a timeframe\n                  or 0 mL infused at a visit, then ECOCCUR = 'N' is the standard representation\n                  of the collected doses not taken, not given, or missed. Dose amount\n                  variables (e.g., ECDOSE, ECDOSTXT) must not be set to zero (0) as\n                  an alternative method for indicating doses not taken, not given,\n                  or missed.\n                Document: IG v3.2\n                Item: Assumption 4a\n                Section: 6.1.\n              - Cited Guidance: Qualifiers that indicate dose amount (e.g., ECDOSE,\n                  ECDOSTXT) may be populated with positive (non-zero) values in cases\n                  where the sponsor feels it is necessary and/or appropriate to represent\n                  specific dose amounts not taken, not given, or missed.\n                Document: IG v3.3\n                Item: Assumption 4b\n                Section: 6.1.\n      - Name: SDTMIG\n        Version: '3.3'\n        References:\n          - Origin: SDTM and SDTMIG Conformance Rules\n            Rule Identifier:\n              Id: CG0100\n              Version: '2'\n            Version: '2.0'\n            Citations:\n              - Cited Guidance: For example, if 0 tablets are taken within a timeframe\n                  or 0 mL infused at a visit, then ECOCCUR = 'N' is the standard representation\n                  of the collected doses not taken, not given, or missed. Dose amount\n                  variables (e.g., ECDOSE, ECDOSTXT) must not be set to zero (0) as\n                  an alternative method for indicating doses not taken, not given,\n                  or missed.\n                Document: IG v3.4\n                Item: Assumption 4a\n                Section: 6.1.3.2\n              - Cited Guidance: Qualifiers that indicate dose amount (e.g., ECDOSE,\n                  ECDOSTXT) may be populated with positive (non-zero) values in cases\n                  where the sponsor feels it is necessary and/or appropriate to represent\n                  specific dose amounts not taken, not  given, or missed.\n                Document: IG v3.4\n                Item: Assumption 4b\n                Section: 6.1.3.2\n              - Cited Guidance: For example, if 0 tablets are taken within a timeframe\n                  or 0 mL infused at a visit, then ECOCCUR = 'N' is the standard representation\n                  of the collected doses not taken, not given, or missed. Dose amount\n                  variables (e.g., ECDOSE, ECDOSTXT) must not be set to zero (0) as\n                  an alternative method for indicating doses not taken, not given,\n                  or missed.\n                Document: IG v3.3\n                Item: Assumption 4a\n                Section: 6.1.3.2\n              - Cited Guidance: Qualifiers that indicate dose amount (e.g., ECDOSE,\n                  ECDOSTXT) may be populated with positive (non-zero) values in cases\n                  where the sponsor feels it is necessary and/or appropriate to represent\n                  specific dose amounts not taken, not  given, or missed.\n                Document: IG v3.3\n                Item: Assumption 4b\n                Section: 6.1.3.2\n              - Cited Guidance: For example, if 0 tablets are taken within a timeframe\n                  or 0 mL infused at a visit, then ECOCCUR = 'N' is the standard representation\n                  of the collected doses not taken, not given, or missed. Dose amount\n                  variables (e.g., ECDOSE, ECDOSTXT) must not be set to zero (0) as\n                  an alternative method for indicating doses not taken, not given,\n                  or missed.\n                Document: IG v3.2\n                Item: Assumption 4a\n                Section: 6.1.\n              - Cited Guidance: Qualifiers that indicate dose amount (e.g., ECDOSE,\n                  ECDOSTXT) may be populated with positive (non-zero) values in cases\n                  where the sponsor feels it is necessary and/or appropriate to represent\n                  specific dose amounts not taken, not given, or missed.\n                Document: IG v3.3\n                Item: Assumption 4b\n                Section: 6.1.\n      - Name: SDTMIG\n        Version: '3.2'\n        References:\n          - Origin: SDTM and SDTMIG Conformance Rules\n            Rule Identifier:\n              Id: CG0100\n              Version: '2'\n            Version: '2.0'\n            Citations:\n              - Cited Guidance: For example, if 0 tablets are taken within a timeframe\n                  or 0 mL infused at a visit, then ECOCCUR = 'N' is the standard representation\n                  of the collected doses not taken, not given, or missed. Dose amount\n                  variables (e.g., ECDOSE, ECDOSTXT) must not be set to zero (0) as\n                  an alternative method for indicating doses not taken, not given,\n                  or missed.\n                Document: IG v3.4\n                Item: Assumption 4a\n                Section: 6.1.3.2\n              - Cited Guidance: Qualifiers that indicate dose amount (e.g., ECDOSE,\n                  ECDOSTXT) may be populated with positive (non-zero) values in cases\n                  where the sponsor feels it is necessary and/or appropriate to represent\n                  specific dose amounts not taken, not  given, or missed.\n                Document: IG v3.4\n                Item: Assumption 4b\n                Section: 6.1.3.2\n              - Cited Guidance: For example, if 0 tablets are taken within a timeframe\n                  or 0 mL infused at a visit, then ECOCCUR = 'N' is the standard representation\n                  of the collected doses not taken, not given, or missed. Dose amount\n                  variables (e.g., ECDOSE, ECDOSTXT) must not be set to zero (0) as\n                  an alternative method for indicating doses not taken, not given,\n                  or missed.\n                Document: IG v3.3\n                Item: Assumption 4a\n                Section: 6.1.3.2\n              - Cited Guidance: Qualifiers that indicate dose amount (e.g., ECDOSE,\n                  ECDOSTXT) may be populated with positive (non-zero) values in cases\n                  where the sponsor feels it is necessary and/or appropriate to represent\n                  specific dose amounts not taken, not  given, or missed.\n                Document: IG v3.3\n                Item: Assumption 4b\n                Section: 6.1.3.2\n              - Cited Guidance: For example, if 0 tablets are taken within a timeframe\n                  or 0 mL infused at a visit, then ECOCCUR = 'N' is the standard representation\n                  of the collected doses not taken, not given, or missed. Dose amount\n                  variables (e.g., ECDOSE, ECDOSTXT) must not be set to zero (0) as\n                  an alternative method for indicating doses not taken, not given,\n                  or missed.\n                Document: IG v3.2\n                Item: Assumption 4a\n                Section: 6.1.\n              - Cited Guidance: Qualifiers that indicate dose amount (e.g., ECDOSE,\n                  ECDOSTXT) may be populated with positive (non-zero) values in cases\n                  where the sponsor feels it is necessary and/or appropriate to represent\n                  specific dose amounts not taken, not given, or missed.\n                Document: IG v3.3\n                Item: Assumption 4b\n                Section: 6.1.\nScope:\n  Classes:\n    Include:\n      - INTERVENTIONS\n  Domains:\n    Include:\n      - EC\n",
    "created": "2021-10-13T13:48:24Z",
    "creator": {
        "id": "02c3c969-4787-4d57-b164-e2851035c0e8"
    },
    "json": {
        "Check": {
            "all": [
                {
                    "name": "ECOCCUR",
                    "operator": "not_equal_to",
                    "value": "N"
                },
                {
                    "name": "ECSTAT",
                    "operator": "empty"
                },
                {
                    "name": "ECDOSTXT",
                    "operator": "empty"
                },
                {
                    "name": "ECDOSE",
                    "operator": "less_than_or_equal_to",
                    "value": 0
                }
            ]
        },
        "Core": {
            "Id": "CORE-000137",
            "Version": "1",
            "Status": "Published"
        },
        "Description": "Raise an error when ECOCCUR is not equal to 'N', ECSTAT and ECDOSTXT are both empty but ECDOSE less than or equal to 0.",
        "Outcome": {
            "Message": "ECOCCUR is not 'N', ECSTAT and ECDOSTXT are both empty but ECDOSE is less than or equal to 0.",
            "Output_Variables": [
                "ECOCCUR",
                "ECSTAT",
                "ECDOSTXT",
                "ECDOSE",
                "ECSTDTC"
            ]
        },
        "Rule_Type": "Record Data",
        "Sensitivity": "Record",
        "Authorities": [
            {
                "Organization": "CDISC",
                "Standards": [
                    {
                        "Name": "SDTMIG",
                        "Version": "3.4",
                        "References": [
                            {
                                "Origin": "SDTM and SDTMIG Conformance Rules",
                                "Rule_Identifier": {
                                    "Id": "CG0100",
                                    "Version": "2"
                                },
                                "Version": "2.0",
                                "Citations": [
                                    {
                                        "Cited_Guidance": "For example, if 0 tablets are taken within a timeframe or 0 mL infused at a visit, then ECOCCUR = 'N' is the standard representation of the collected doses not taken, not given, or missed. Dose amount variables (e.g., ECDOSE, ECDOSTXT) must not be set to zero (0) as an alternative method for indicating doses not taken, not given, or missed.",
                                        "Document": "IG v3.4",
                                        "Item": "Assumption 4a",
                                        "Section": "6.1.3.2"
                                    },
                                    {
                                        "Cited_Guidance": "Qualifiers that indicate dose amount (e.g., ECDOSE, ECDOSTXT) may be populated with positive (non-zero) values in cases where the sponsor feels it is necessary and/or appropriate to represent specific dose amounts not taken, not  given, or missed.",
                                        "Document": "IG v3.4",
                                        "Item": "Assumption 4b",
                                        "Section": "6.1.3.2"
                                    },
                                    {
                                        "Cited_Guidance": "For example, if 0 tablets are taken within a timeframe or 0 mL infused at a visit, then ECOCCUR = 'N' is the standard representation of the collected doses not taken, not given, or missed. Dose amount variables (e.g., ECDOSE, ECDOSTXT) must not be set to zero (0) as an alternative method for indicating doses not taken, not given, or missed.",
                                        "Document": "IG v3.3",
                                        "Item": "Assumption 4a",
                                        "Section": "6.1.3.2"
                                    },
                                    {
                                        "Cited_Guidance": "Qualifiers that indicate dose amount (e.g., ECDOSE, ECDOSTXT) may be populated with positive (non-zero) values in cases where the sponsor feels it is necessary and/or appropriate to represent specific dose amounts not taken, not  given, or missed.",
                                        "Document": "IG v3.3",
                                        "Item": "Assumption 4b",
                                        "Section": "6.1.3.2"
                                    },
                                    {
                                        "Cited_Guidance": "For example, if 0 tablets are taken within a timeframe or 0 mL infused at a visit, then ECOCCUR = 'N' is the standard representation of the collected doses not taken, not given, or missed. Dose amount variables (e.g., ECDOSE, ECDOSTXT) must not be set to zero (0) as an alternative method for indicating doses not taken, not given, or missed.",
                                        "Document": "IG v3.2",
                                        "Item": "Assumption 4a",
                                        "Section": "6.1."
                                    },
                                    {
                                        "Cited_Guidance": "Qualifiers that indicate dose amount (e.g., ECDOSE, ECDOSTXT) may be populated with positive (non-zero) values in cases where the sponsor feels it is necessary and/or appropriate to represent specific dose amounts not taken, not given, or missed.",
                                        "Document": "IG v3.3",
                                        "Item": "Assumption 4b",
                                        "Section": "6.1."
                                    }
                                ]
                            }
                        ]
                    },
                    {
                        "Name": "SDTMIG",
                        "Version": "3.3",
                        "References": [
                            {
                                "Origin": "SDTM and SDTMIG Conformance Rules",
                                "Rule_Identifier": {
                                    "Id": "CG0100",
                                    "Version": "2"
                                },
                                "Version": "2.0",
                                "Citations": [
                                    {
                                        "Cited_Guidance": "For example, if 0 tablets are taken within a timeframe or 0 mL infused at a visit, then ECOCCUR = 'N' is the standard representation of the collected doses not taken, not given, or missed. Dose amount variables (e.g., ECDOSE, ECDOSTXT) must not be set to zero (0) as an alternative method for indicating doses not taken, not given, or missed.",
                                        "Document": "IG v3.4",
                                        "Item": "Assumption 4a",
                                        "Section": "6.1.3.2"
                                    },
                                    {
                                        "Cited_Guidance": "Qualifiers that indicate dose amount (e.g., ECDOSE, ECDOSTXT) may be populated with positive (non-zero) values in cases where the sponsor feels it is necessary and/or appropriate to represent specific dose amounts not taken, not  given, or missed.",
                                        "Document": "IG v3.4",
                                        "Item": "Assumption 4b",
                                        "Section": "6.1.3.2"
                                    },
                                    {
                                        "Cited_Guidance": "For example, if 0 tablets are taken within a timeframe or 0 mL infused at a visit, then ECOCCUR = 'N' is the standard representation of the collected doses not taken, not given, or missed. Dose amount variables (e.g., ECDOSE, ECDOSTXT) must not be set to zero (0) as an alternative method for indicating doses not taken, not given, or missed.",
                                        "Document": "IG v3.3",
                                        "Item": "Assumption 4a",
                                        "Section": "6.1.3.2"
                                    },
                                    {
                                        "Cited_Guidance": "Qualifiers that indicate dose amount (e.g., ECDOSE, ECDOSTXT) may be populated with positive (non-zero) values in cases where the sponsor feels it is necessary and/or appropriate to represent specific dose amounts not taken, not  given, or missed.",
                                        "Document": "IG v3.3",
                                        "Item": "Assumption 4b",
                                        "Section": "6.1.3.2"
                                    },
                                    {
                                        "Cited_Guidance": "For example, if 0 tablets are taken within a timeframe or 0 mL infused at a visit, then ECOCCUR = 'N' is the standard representation of the collected doses not taken, not given, or missed. Dose amount variables (e.g., ECDOSE, ECDOSTXT) must not be set to zero (0) as an alternative method for indicating doses not taken, not given, or missed.",
                                        "Document": "IG v3.2",
                                        "Item": "Assumption 4a",
                                        "Section": "6.1."
                                    },
                                    {
                                        "Cited_Guidance": "Qualifiers that indicate dose amount (e.g., ECDOSE, ECDOSTXT) may be populated with positive (non-zero) values in cases where the sponsor feels it is necessary and/or appropriate to represent specific dose amounts not taken, not given, or missed.",
                                        "Document": "IG v3.3",
                                        "Item": "Assumption 4b",
                                        "Section": "6.1."
                                    }
                                ]
                            }
                        ]
                    },
                    {
                        "Name": "SDTMIG",
                        "Version": "3.2",
                        "References": [
                            {
                                "Origin": "SDTM and SDTMIG Conformance Rules",
                                "Rule_Identifier": {
                                    "Id": "CG0100",
                                    "Version": "2"
                                },
                                "Version": "2.0",
                                "Citations": [
                                    {
                                        "Cited_Guidance": "For example, if 0 tablets are taken within a timeframe or 0 mL infused at a visit, then ECOCCUR = 'N' is the standard representation of the collected doses not taken, not given, or missed. Dose amount variables (e.g., ECDOSE, ECDOSTXT) must not be set to zero (0) as an alternative method for indicating doses not taken, not given, or missed.",
                                        "Document": "IG v3.4",
                                        "Item": "Assumption 4a",
                                        "Section": "6.1.3.2"
                                    },
                                    {
                                        "Cited_Guidance": "Qualifiers that indicate dose amount (e.g., ECDOSE, ECDOSTXT) may be populated with positive (non-zero) values in cases where the sponsor feels it is necessary and/or appropriate to represent specific dose amounts not taken, not  given, or missed.",
                                        "Document": "IG v3.4",
                                        "Item": "Assumption 4b",
                                        "Section": "6.1.3.2"
                                    },
                                    {
                                        "Cited_Guidance": "For example, if 0 tablets are taken within a timeframe or 0 mL infused at a visit, then ECOCCUR = 'N' is the standard representation of the collected doses not taken, not given, or missed. Dose amount variables (e.g., ECDOSE, ECDOSTXT) must not be set to zero (0) as an alternative method for indicating doses not taken, not given, or missed.",
                                        "Document": "IG v3.3",
                                        "Item": "Assumption 4a",
                                        "Section": "6.1.3.2"
                                    },
                                    {
                                        "Cited_Guidance": "Qualifiers that indicate dose amount (e.g., ECDOSE, ECDOSTXT) may be populated with positive (non-zero) values in cases where the sponsor feels it is necessary and/or appropriate to represent specific dose amounts not taken, not  given, or missed.",
                                        "Document": "IG v3.3",
                                        "Item": "Assumption 4b",
                                        "Section": "6.1.3.2"
                                    },
                                    {
                                        "Cited_Guidance": "For example, if 0 tablets are taken within a timeframe or 0 mL infused at a visit, then ECOCCUR = 'N' is the standard representation of the collected doses not taken, not given, or missed. Dose amount variables (e.g., ECDOSE, ECDOSTXT) must not be set to zero (0) as an alternative method for indicating doses not taken, not given, or missed.",
                                        "Document": "IG v3.2",
                                        "Item": "Assumption 4a",
                                        "Section": "6.1."
                                    },
                                    {
                                        "Cited_Guidance": "Qualifiers that indicate dose amount (e.g., ECDOSE, ECDOSTXT) may be populated with positive (non-zero) values in cases where the sponsor feels it is necessary and/or appropriate to represent specific dose amounts not taken, not given, or missed.",
                                        "Document": "IG v3.3",
                                        "Item": "Assumption 4b",
                                        "Section": "6.1."
                                    }
                                ]
                            }
                        ]
                    }
                ]
            }
        ],
        "Scope": {
            "Classes": {
                "Include": [
                    "INTERVENTIONS"
                ]
            },
            "Domains": {
                "Include": [
                    "EC"
                ]
            }
        }
    }
}