{
    "id": "fabb3730-4071-4a6c-ac99-ad81830a1b63",
    "changed": "2022-04-14T11:44:11Z",
    "content": "Check:\n  all:\n    - name: SUBJID\n      operator: is_not_unique_set\n      value:\n        - STUDYID\nCore:\n  Id: CORE-000186\n  Version: '1'\n  Status: Published\nDescription: Trigger error if SUBJID is not unique\nOutcome:\n  Message: SUBJID is not unique within study\n  Output Variables:\n    - SUBJID\nRule Type: Record Data\nSensitivity: Study\nAuthorities:\n  - Organization: CDISC\n    Standards:\n      - Name: SDTMIG\n        Version: '3.4'\n        References:\n          - Origin: SDTM and SDTMIG Conformance Rules\n            Rule Identifier:\n              Id: CG0150\n              Version: '1'\n            Version: '2.0'\n            Citations:\n              - Cited Guidance: Subject identifier, which must be unique within the\n                  study.\n                Document: IG v3.4\n                Item: Specification\n                Section: '5.2'\nScope:\n  Classes:\n    Include:\n      - SPECIAL-PURPOSE\n  Domains:\n    Include:\n      - DM\n",
    "created": "2021-10-29T06:15:26Z",
    "creator": {
        "id": "ff471ff8-f131-4cf5-9712-c79cce6301a1"
    },
    "json": {
        "Check": {
            "all": [
                {
                    "name": "SUBJID",
                    "operator": "is_not_unique_set",
                    "value": [
                        "STUDYID"
                    ]
                }
            ]
        },
        "Core": {
            "Id": "CORE-000186",
            "Version": "1",
            "Status": "Published"
        },
        "Description": "Trigger error if SUBJID is not unique",
        "Outcome": {
            "Message": "SUBJID is not unique within study",
            "Output_Variables": [
                "SUBJID"
            ]
        },
        "Rule_Type": "Record Data",
        "Sensitivity": "Study",
        "Authorities": [
            {
                "Organization": "CDISC",
                "Standards": [
                    {
                        "Name": "SDTMIG",
                        "Version": "3.4",
                        "References": [
                            {
                                "Origin": "SDTM and SDTMIG Conformance Rules",
                                "Rule_Identifier": {
                                    "Id": "CG0150",
                                    "Version": "1"
                                },
                                "Version": "2.0",
                                "Citations": [
                                    {
                                        "Cited_Guidance": "Subject identifier, which must be unique within the study.",
                                        "Document": "IG v3.4",
                                        "Item": "Specification",
                                        "Section": "5.2"
                                    }
                                ]
                            }
                        ]
                    }
                ]
            }
        ],
        "Scope": {
            "Classes": {
                "Include": [
                    "SPECIAL-PURPOSE"
                ]
            },
            "Domains": {
                "Include": [
                    "DM"
                ]
            }
        }
    }
}