{
    "id": "2a01fb4d-abde-42f7-8264-7a0203fef8b8",
    "changed": "2022-02-15T21:27:09Z",
    "content": "Check:\n  all:\n    - name: RSUBJID\n      operator: is_empty\n    - name: RDEVID\n      operator: is_empty\n    - name: SREL\n      operator:\nCore:\n  Id: CDISC.SDTMIG.CG0162\n  Version: '1'\n  Status: Draft\nDescription: Trigger error when RSUBJID = null and RDEVID = null and SREL does not\n  describe the relationship of associated person to study identified in STUDYID\nOutcome:\n  Message: SREL does not describe the relationship of associated person to study identified\n    in STUDYID when RSUBJID = null and RDEVID = null\nRule Type: Record Data\nSensitivity: Record\nAuthorities:\n  - Organization: CDISC\n    Standards:\n      - Name: SDTMIG\n        Version: '3.4'\n        References:\n          - Origin: SDTM and SDTMIG Conformance Rules\n            Rule Identifier:\n              Id: CG0162\n              Version: '1'\n            Version: '2.0'\n            Citations:\n              - Cited Guidance: If RSUBJID is populated, describes the relationship\n                  of the associated person(s) identified in APID to the subject or\n                  pool identified in RSUBJID. If RDEVID is populated, describes the\n                  relationship of the associated person(s) identified in APID to the\n                  device identified in RDEVID. If RSUBJID and RDEVID are null, SREL\n                  describes the relationship of the associated person(s) identified\n                  in APID to the study identified in STUDYID.\n                Document: AP Guide v1.0\n                Item: Specification\n                Section: 2.1.1\nScope:\n  Classes:\n    Include:\n      - ASSOCIATED PERSONS\n  Domains:\n    Include:\n      - ALL\n",
    "created": "2021-10-29T06:16:37Z",
    "creator": {
        "id": "ff471ff8-f131-4cf5-9712-c79cce6301a1"
    },
    "json": {
        "Check": {
            "all": [
                {
                    "name": "RSUBJID",
                    "operator": "is_empty"
                },
                {
                    "name": "RDEVID",
                    "operator": "is_empty"
                },
                {
                    "name": "SREL",
                    "operator": null
                }
            ]
        },
        "Core": {
            "Id": "CDISC.SDTMIG.CG0162",
            "Version": "1",
            "Status": "Draft"
        },
        "Description": "Trigger error when RSUBJID = null and RDEVID = null and SREL does not describe the relationship of associated person to study identified in STUDYID",
        "Outcome": {
            "Message": "SREL does not describe the relationship of associated person to study identified in STUDYID when RSUBJID = null and RDEVID = null"
        },
        "Rule_Type": "Record Data",
        "Sensitivity": "Record",
        "Authorities": [
            {
                "Organization": "CDISC",
                "Standards": [
                    {
                        "Name": "SDTMIG",
                        "Version": "3.4",
                        "References": [
                            {
                                "Origin": "SDTM and SDTMIG Conformance Rules",
                                "Rule_Identifier": {
                                    "Id": "CG0162",
                                    "Version": "1"
                                },
                                "Version": "2.0",
                                "Citations": [
                                    {
                                        "Cited_Guidance": "If RSUBJID is populated, describes the relationship of the associated person(s) identified in APID to the subject or pool identified in RSUBJID. If RDEVID is populated, describes the relationship of the associated person(s) identified in APID to the device identified in RDEVID. If RSUBJID and RDEVID are null, SREL describes the relationship of the associated person(s) identified in APID to the study identified in STUDYID.",
                                        "Document": "AP Guide v1.0",
                                        "Item": "Specification",
                                        "Section": "2.1.1"
                                    }
                                ]
                            }
                        ]
                    }
                ]
            }
        ],
        "Scope": {
            "Classes": {
                "Include": [
                    "ASSOCIATED PERSONS"
                ]
            },
            "Domains": {
                "Include": [
                    "ALL"
                ]
            }
        }
    }
}