{
    "id": "494e8408-74d9-41cd-b0be-ad645a6c5e86",
    "changed": "2022-07-17T11:01:13Z",
    "content": "Check:\n  all:\n    - name: --TRTV\n      operator: empty\n    - name: --VAMTU\n      operator: non_empty\nCore:\n  Id: CORE-000091\n  Version: '1'\n  Status: Published\nDescription: Raise an error when --TRTV is null, --VAMTU is not null\nOutcome:\n  Message: Value for --VAMTU is populated, when --TRTV is NULL.\n  Output Variables:\n    - --TRTV\n    - --VAMTU\nRule Type: Record Data\nSensitivity: Record\nAuthorities:\n  - Organization: CDISC\n    Standards:\n      - Name: SDTMIG\n        Version: '3.4'\n        References:\n          - Origin: SDTM and SDTMIG Conformance Rules\n            Rule Identifier:\n              Id: CG0108\n              Version: '2'\n            Version: '2.0'\n            Citations:\n              - Cited Guidance: Variable Qualifier of --VAMT.\n                Document: Model v2.0\n                Item: --VAMTU\n                Section: Interventions\nScope:\n  Classes:\n    Include:\n      - INTERVENTIONS\n  Domains:\n    Include:\n      - ALL\n",
    "created": "2021-10-06T16:45:40Z",
    "creator": {
        "id": "d0881041-369e-4940-b721-5b456d12101b"
    },
    "json": {
        "Check": {
            "all": [
                {
                    "name": "--TRTV",
                    "operator": "empty"
                },
                {
                    "name": "--VAMTU",
                    "operator": "non_empty"
                }
            ]
        },
        "Core": {
            "Id": "CORE-000091",
            "Version": "1",
            "Status": "Published"
        },
        "Description": "Raise an error when --TRTV is null, --VAMTU is not null",
        "Outcome": {
            "Message": "Value for --VAMTU is populated, when --TRTV is NULL.",
            "Output_Variables": [
                "--TRTV",
                "--VAMTU"
            ]
        },
        "Rule_Type": "Record Data",
        "Sensitivity": "Record",
        "Authorities": [
            {
                "Organization": "CDISC",
                "Standards": [
                    {
                        "Name": "SDTMIG",
                        "Version": "3.4",
                        "References": [
                            {
                                "Origin": "SDTM and SDTMIG Conformance Rules",
                                "Rule_Identifier": {
                                    "Id": "CG0108",
                                    "Version": "2"
                                },
                                "Version": "2.0",
                                "Citations": [
                                    {
                                        "Cited_Guidance": "Variable Qualifier of --VAMT.",
                                        "Document": "Model v2.0",
                                        "Item": "--VAMTU",
                                        "Section": "Interventions"
                                    }
                                ]
                            }
                        ]
                    }
                ]
            }
        ],
        "Scope": {
            "Classes": {
                "Include": [
                    "INTERVENTIONS"
                ]
            },
            "Domains": {
                "Include": [
                    "ALL"
                ]
            }
        }
    }
}