{
    "id": "07bf0e3a-e2db-4887-b843-ef8b48b58934",
    "changed": "2023-01-17T15:54:57.393Z",
    "content": "Check:\n  all:\n    - name: DSTERM\n      operator: contains\n      value: INFORMED CONSENT\n    - name: RFICDTC\n      operator: date_not_equal_to\n      value: $min_ds_dsstdtc\n    - name: DSTERM\n      operator: contains\n      value: OBTAINED\nOperations:\n  - operator: min_date\n    domain: DS\n    name: DSSTDTC\n    id: $min_ds_dsstdtc\n    group:\n      - USUBJID\nMatch Datasets:\n  - Name: DM\n    Keys:\n      - USUBJID\nCore:\n  Id: CDISC.SDTMIG.CG0143\n  Version: '1'\n  Status: Draft\nDescription: DM.RFICDTC must equal the earliest DS.DSSTDTC when DSTERM indicates informed\n  consent obtained.\nOutcome:\n  Message: DM.RFICDTC is not equal to the earliest DSSTDTC, when DSTERM indicates\n    Informed consent obtained.\n  Output Variables:\n    - DSDECOD\n    - RFICDTC\n    - DSSTDTC\n    - $min_ds_dsstdtc\nRule Type: Record Data\nSensitivity: Record\nAuthorities:\n  - Organization: CDISC\n    Standards:\n      - Name: SDTMIG\n        Version: '3.4'\n        References:\n          - Origin: SDTM and SDTMIG Conformance Rules\n            Rule Identifier:\n              Id: CG0143\n              Version: '1'\n            Version: '2.0'\n            Citations:\n              - Cited Guidance: This will be the same as the date of informed consent\n                  in the Disposition domain, if that protocol milestone is documented.  Would\n                  be null only in studies not collecting the date of informed consent.\n                Document: SDTMIG v3.4\n                Item: Specification\n                Section: '5.2'\n              - Cited Guidance: \"RFICDTC should correspond to the date of the informed\\\n                  \\ consent protocol milestone in DS, if that protocol milestone is\\\n                  \\ documented in DS.\\n In the event that there are multiple informed\\\n                  \\ consents, this will be the date of the first one.\"\n                Document: SDTMIG v3.4\n                Item: Assumption 10c\n                Section: '5.2'\nScope:\n  Classes:\n    Include:\n      - EVENTS\n  Domains:\n    Include:\n      - DS\n",
    "created": "2021-10-26T23:39:28Z",
    "creator": {
        "id": "d0881041-369e-4940-b721-5b456d12101b"
    },
    "json": {
        "Check": {
            "all": [
                {
                    "name": "DSTERM",
                    "operator": "contains",
                    "value": "INFORMED CONSENT"
                },
                {
                    "name": "RFICDTC",
                    "operator": "date_not_equal_to",
                    "value": "$min_ds_dsstdtc"
                },
                {
                    "name": "DSTERM",
                    "operator": "contains",
                    "value": "OBTAINED"
                }
            ]
        },
        "Operations": [
            {
                "operator": "min_date",
                "domain": "DS",
                "name": "DSSTDTC",
                "id": "$min_ds_dsstdtc",
                "group": [
                    "USUBJID"
                ]
            }
        ],
        "Match_Datasets": [
            {
                "Name": "DM",
                "Keys": [
                    "USUBJID"
                ]
            }
        ],
        "Core": {
            "Id": "CDISC.SDTMIG.CG0143",
            "Version": "1",
            "Status": "Draft"
        },
        "Description": "DM.RFICDTC must equal the earliest DS.DSSTDTC when DSTERM indicates informed consent obtained.",
        "Outcome": {
            "Message": "DM.RFICDTC is not equal to the earliest DSSTDTC, when DSTERM indicates Informed consent obtained.",
            "Output_Variables": [
                "DSDECOD",
                "RFICDTC",
                "DSSTDTC",
                "$min_ds_dsstdtc"
            ]
        },
        "Rule_Type": "Record Data",
        "Sensitivity": "Record",
        "Authorities": [
            {
                "Organization": "CDISC",
                "Standards": [
                    {
                        "Name": "SDTMIG",
                        "Version": "3.4",
                        "References": [
                            {
                                "Origin": "SDTM and SDTMIG Conformance Rules",
                                "Rule_Identifier": {
                                    "Id": "CG0143",
                                    "Version": "1"
                                },
                                "Version": "2.0",
                                "Citations": [
                                    {
                                        "Cited_Guidance": "This will be the same as the date of informed consent in the Disposition domain, if that protocol milestone is documented.  Would be null only in studies not collecting the date of informed consent.",
                                        "Document": "SDTMIG v3.4",
                                        "Item": "Specification",
                                        "Section": "5.2"
                                    },
                                    {
                                        "Cited_Guidance": "RFICDTC should correspond to the date of the informed consent protocol milestone in DS, if that protocol milestone is documented in DS.\n In the event that there are multiple informed consents, this will be the date of the first one.",
                                        "Document": "SDTMIG v3.4",
                                        "Item": "Assumption 10c",
                                        "Section": "5.2"
                                    }
                                ]
                            }
                        ]
                    }
                ]
            }
        ],
        "Scope": {
            "Classes": {
                "Include": [
                    "EVENTS"
                ]
            },
            "Domains": {
                "Include": [
                    "DS"
                ]
            }
        }
    }
}