{
    "id": "48a8a0e3-182d-4f2d-aa03-2c76dbbaa128",
    "changed": "2022-07-17T11:03:16Z",
    "content": "Check:\n  all:\n    - name: LBSTRESU\n      operator: non_empty\n    - name:\n      operator:\n      value:\nCore:\n  Id: CDISC.SDTMIG.CG0190\n  Version: '1'\n  Status: Draft\nDescription: Trigger error if LBSTRESU is not null and LBSTNRC is not expressed using\n  the units in LBSTRESU\nOutcome:\n  Message: LBSTNRC is not expressed using the units in LBSTRESU when LBSTRESU is populated.\nRule Type: Record Data\nSensitivity: Record\nAuthorities:\n  - Organization: CDISC\n    Standards:\n      - Name: SDTMIG\n        Version: '3.4'\n        References:\n          - Origin: SDTM and SDTMIG Conformance Rules\n            Rule Identifier:\n              Id: CG0190\n              Version: '2'\n            Version: '2.0'\n            Citations:\n              - Cited Guidance: Reference Range for Char Rslt-Std Units\n                Document: IG v3.4\n                Item: Specification\n                Section: 6.3.5.6\nScope:\n  Classes:\n    Include:\n      - FINDINGS\n  Domains:\n    Include:\n      - LB\n",
    "created": "2021-10-29T06:18:06Z",
    "creator": {
        "id": "ff471ff8-f131-4cf5-9712-c79cce6301a1"
    },
    "json": {
        "Check": {
            "all": [
                {
                    "name": "LBSTRESU",
                    "operator": "non_empty"
                },
                {
                    "name": null,
                    "operator": null,
                    "value": null
                }
            ]
        },
        "Core": {
            "Id": "CDISC.SDTMIG.CG0190",
            "Version": "1",
            "Status": "Draft"
        },
        "Description": "Trigger error if LBSTRESU is not null and LBSTNRC is not expressed using the units in LBSTRESU",
        "Outcome": {
            "Message": "LBSTNRC is not expressed using the units in LBSTRESU when LBSTRESU is populated."
        },
        "Rule_Type": "Record Data",
        "Sensitivity": "Record",
        "Authorities": [
            {
                "Organization": "CDISC",
                "Standards": [
                    {
                        "Name": "SDTMIG",
                        "Version": "3.4",
                        "References": [
                            {
                                "Origin": "SDTM and SDTMIG Conformance Rules",
                                "Rule_Identifier": {
                                    "Id": "CG0190",
                                    "Version": "2"
                                },
                                "Version": "2.0",
                                "Citations": [
                                    {
                                        "Cited_Guidance": "Reference Range for Char Rslt-Std Units",
                                        "Document": "IG v3.4",
                                        "Item": "Specification",
                                        "Section": "6.3.5.6"
                                    }
                                ]
                            }
                        ]
                    }
                ]
            }
        ],
        "Scope": {
            "Classes": {
                "Include": [
                    "FINDINGS"
                ]
            },
            "Domains": {
                "Include": [
                    "LB"
                ]
            }
        }
    }
}