{
    "id": "3b29ce79-2e4f-4ff8-bcec-3b6c817e57c2",
    "changed": "2022-03-08T09:27:33Z",
    "content": "Check:\n  all:\n    - name: SETCD\n      operator: matches_regex\n      value: ^(.){9,}$\nCore:\n  Id: CORE-000088\n  Version: '1'\n  Status: Published\nDescription: Verify that the length of value in SETCD variable is <= 8\nOutcome:\n  Message: SETCD value length is greater than 8\n  Output Variables:\n    - SETCD\nRule Type: Record Data\nSensitivity: Record\nAuthorities:\n  - Organization: CDISC\n    Standards:\n      - Name: SDTMIG\n        Version: '3.4'\n        References:\n          - Origin: SDTM and SDTMIG Conformance Rules\n            Rule Identifier:\n              Id: CG0149\n              Version: '1'\n            Version: '2.0'\n            Citations:\n              - Cited Guidance: Maximum of 8 characters.\n                Document: Model v2.0\n                Item: SETCD\n                Section: Demographics\nScope:\n  Classes:\n    Include:\n      - SPECIAL-PURPOSE\n      - TRIAL DESIGN\n  Domains:\n    Include:\n      - DM\n      - TX\n",
    "created": "2021-10-06T15:30:44Z",
    "creator": {
        "id": "24709aaa-3e57-4ee4-a635-6006b165bb1b"
    },
    "json": {
        "Check": {
            "all": [
                {
                    "name": "SETCD",
                    "operator": "matches_regex",
                    "value": "^(.){9,}$"
                }
            ]
        },
        "Core": {
            "Id": "CORE-000088",
            "Version": "1",
            "Status": "Published"
        },
        "Description": "Verify that the length of value in SETCD variable is <= 8",
        "Outcome": {
            "Message": "SETCD value length is greater than 8",
            "Output_Variables": [
                "SETCD"
            ]
        },
        "Rule_Type": "Record Data",
        "Sensitivity": "Record",
        "Authorities": [
            {
                "Organization": "CDISC",
                "Standards": [
                    {
                        "Name": "SDTMIG",
                        "Version": "3.4",
                        "References": [
                            {
                                "Origin": "SDTM and SDTMIG Conformance Rules",
                                "Rule_Identifier": {
                                    "Id": "CG0149",
                                    "Version": "1"
                                },
                                "Version": "2.0",
                                "Citations": [
                                    {
                                        "Cited_Guidance": "Maximum of 8 characters.",
                                        "Document": "Model v2.0",
                                        "Item": "SETCD",
                                        "Section": "Demographics"
                                    }
                                ]
                            }
                        ]
                    }
                ]
            }
        ],
        "Scope": {
            "Classes": {
                "Include": [
                    "SPECIAL-PURPOSE",
                    "TRIAL DESIGN"
                ]
            },
            "Domains": {
                "Include": [
                    "DM",
                    "TX"
                ]
            }
        }
    }
}