{
    "id": "c4750afc-a4bc-4c62-88b1-ffb7e982d488",
    "changed": "2022-03-08T09:29:53Z",
    "content": "Check:\n  all:\n    - name: ETCD\n      operator: equal_to\n      value: UNPLAN\n    - name: ELEMENT\n      operator: non_empty\nCore:\n  Id: CORE-000009\n  Version: '1'\n  Status: Published\nDescription: Verify that ELEMENT value is blank when ETCD is equal to UNPLAN\nOutcome:\n  Message: ELEMENT variable has a non-null value when ETCD has a value of 'UNPLAN'\n  Output Variables:\n    - ETCD\n    - ELEMENT\nRule Type: Record Data\nSensitivity: Record\nAuthorities:\n  - Organization: CDISC\n    Standards:\n      - Name: SDTMIG\n        Version: '3.4'\n        References:\n          - Origin: SDTM and SDTMIG Conformance Rules\n            Rule Identifier:\n              Id: CG0152\n              Version: '1'\n            Version: '2.0'\n            Citations:\n              - Cited Guidance: The name of the Element. If ETCD has a value of 'UNPLAN'\n                  then ELEMENT should be null.\n                Document: SDTMIG v3.4\n                Item: Specification\n                Section: 5.3 Specification\nScope:\n  Classes:\n    Include:\n      - SPECIAL-PURPOSE\n  Domains:\n    Include:\n      - SE\n",
    "created": "2021-09-27T16:25:34Z",
    "creator": {
        "id": "24709aaa-3e57-4ee4-a635-6006b165bb1b"
    },
    "json": {
        "Check": {
            "all": [
                {
                    "name": "ETCD",
                    "operator": "equal_to",
                    "value": "UNPLAN"
                },
                {
                    "name": "ELEMENT",
                    "operator": "non_empty"
                }
            ]
        },
        "Core": {
            "Id": "CORE-000009",
            "Version": "1",
            "Status": "Published"
        },
        "Description": "Verify that ELEMENT value is blank when ETCD is equal to UNPLAN",
        "Outcome": {
            "Message": "ELEMENT variable has a non-null value when ETCD has a value of 'UNPLAN'",
            "Output_Variables": [
                "ETCD",
                "ELEMENT"
            ]
        },
        "Rule_Type": "Record Data",
        "Sensitivity": "Record",
        "Authorities": [
            {
                "Organization": "CDISC",
                "Standards": [
                    {
                        "Name": "SDTMIG",
                        "Version": "3.4",
                        "References": [
                            {
                                "Origin": "SDTM and SDTMIG Conformance Rules",
                                "Rule_Identifier": {
                                    "Id": "CG0152",
                                    "Version": "1"
                                },
                                "Version": "2.0",
                                "Citations": [
                                    {
                                        "Cited_Guidance": "The name of the Element. If ETCD has a value of 'UNPLAN' then ELEMENT should be null.",
                                        "Document": "SDTMIG v3.4",
                                        "Item": "Specification",
                                        "Section": "5.3 Specification"
                                    }
                                ]
                            }
                        ]
                    }
                ]
            }
        ],
        "Scope": {
            "Classes": {
                "Include": [
                    "SPECIAL-PURPOSE"
                ]
            },
            "Domains": {
                "Include": [
                    "SE"
                ]
            }
        }
    }
}