{
    "id": "435371d7-9e2c-4953-aae1-ed43cbc62fa5",
    "changed": "2022-03-10T15:20:48Z",
    "content": "Check:\n  all:\n    - name: ECOCCUR\n      operator: not_equal_to\n      value: N\n    - name: ECSTAT\n      operator: empty\n    - name: ECDOSTXT\n      operator: empty\n    - name: ECDOSE\n      operator: less_than_or_equal_to\n      value: 0\nCore:\n  Id: CDISC.SDTMIG.CG0100_duplicate_do_not_use\n  Version: '1'\n  Status: Draft\nDescription: Raise an error when ECOCCUR not equal to 'N' and  ECSTAT = null and ECDOSTXT\n  = null and ECDOSE less than or equal to zero\nOutcome:\n  Message: ECDOSE must be greater than 0 when ECOCCUR not equal \"N\" and ECSTAT equals\n    Null and ECDOSTXT=null\n  Output Variables:\n    - ECOCCUR\n    - ECSTAT\n    - ECDOSTXT\n    - ECDOSE\nRule Type: Record Data\nSensitivity: Record\nAuthorities:\n  - Organization: CDISC\n    Standards:\n      - Name: SDTMIG\n        Version: '3.4'\n        References:\n          - Origin: SDTM and SDTMIG Conformance Rules\n            Rule Identifier:\n              Id: CG0100\n              Version: '1'\n            Version: '2.0'\n            Citations:\n              - Cited Guidance: For example, if 0 tablets are taken within a timeframe\n                  or 0 mL infused at a visit, then ECOCCUR = 'N'is the standard representation\n                  of the collected doses not taken, not given, or missed. Dose amount\n                  variables  (e.g., ECDOSE, ECDOSTXT) must not be set to zero (0)\n                  as an alternative method for indicating doses not taken, not given,\n                  or missed.\n                Document: IG v3.4\n                Item: Assumption 4a\n                Section: 6.1.3.2\n              - Cited Guidance: Qualifiers that indicate dose amount (e.g., ECDOSE,\n                  ECDOSTXT) may be populated with positive (non-zero) values in cases\n                  where the sponsor feels it is necessary and/or appropriate to represent\n                  specific dose amounts not taken, not  given, or missed.\n                Document: IG v3.4\n                Item: Assumption 4b\n                Section: 6.1.2\nScope:\n  Classes:\n    Include:\n      - INTERVENTIONS\n  Domains:\n    Include:\n      - EC\n",
    "created": "2021-10-13T15:28:09Z",
    "creator": {
        "id": "57474fac-237e-4693-bb37-7826b02737da"
    },
    "json": {
        "Check": {
            "all": [
                {
                    "name": "ECOCCUR",
                    "operator": "not_equal_to",
                    "value": "N"
                },
                {
                    "name": "ECSTAT",
                    "operator": "empty"
                },
                {
                    "name": "ECDOSTXT",
                    "operator": "empty"
                },
                {
                    "name": "ECDOSE",
                    "operator": "less_than_or_equal_to",
                    "value": 0
                }
            ]
        },
        "Core": {
            "Id": "CDISC.SDTMIG.CG0100_duplicate_do_not_use",
            "Version": "1",
            "Status": "Draft"
        },
        "Description": "Raise an error when ECOCCUR not equal to 'N' and  ECSTAT = null and ECDOSTXT = null and ECDOSE less than or equal to zero",
        "Outcome": {
            "Message": "ECDOSE must be greater than 0 when ECOCCUR not equal \"N\" and ECSTAT equals Null and ECDOSTXT=null",
            "Output_Variables": [
                "ECOCCUR",
                "ECSTAT",
                "ECDOSTXT",
                "ECDOSE"
            ]
        },
        "Rule_Type": "Record Data",
        "Sensitivity": "Record",
        "Authorities": [
            {
                "Organization": "CDISC",
                "Standards": [
                    {
                        "Name": "SDTMIG",
                        "Version": "3.4",
                        "References": [
                            {
                                "Origin": "SDTM and SDTMIG Conformance Rules",
                                "Rule_Identifier": {
                                    "Id": "CG0100",
                                    "Version": "1"
                                },
                                "Version": "2.0",
                                "Citations": [
                                    {
                                        "Cited_Guidance": "For example, if 0 tablets are taken within a timeframe or 0 mL infused at a visit, then ECOCCUR = 'N'is the standard representation of the collected doses not taken, not given, or missed. Dose amount variables  (e.g., ECDOSE, ECDOSTXT) must not be set to zero (0) as an alternative method for indicating doses not taken, not given, or missed.",
                                        "Document": "IG v3.4",
                                        "Item": "Assumption 4a",
                                        "Section": "6.1.3.2"
                                    },
                                    {
                                        "Cited_Guidance": "Qualifiers that indicate dose amount (e.g., ECDOSE, ECDOSTXT) may be populated with positive (non-zero) values in cases where the sponsor feels it is necessary and/or appropriate to represent specific dose amounts not taken, not  given, or missed.",
                                        "Document": "IG v3.4",
                                        "Item": "Assumption 4b",
                                        "Section": "6.1.2"
                                    }
                                ]
                            }
                        ]
                    }
                ]
            }
        ],
        "Scope": {
            "Classes": {
                "Include": [
                    "INTERVENTIONS"
                ]
            },
            "Domains": {
                "Include": [
                    "EC"
                ]
            }
        }
    }
}