{
    "id": "ae7de36c-a0e2-4a80-bf2f-3303d44d1bee",
    "changed": "2023-01-12T16:46:39.908Z",
    "content": "Check:\n  all:\n    - name: IETEST1\n      operator: is_not_contained_by\n      value: $ti_ietest\nOperations:\n  - domain: TI\n    id: $ti_ietest\n    name: IETEST2\n    operator: distinct\nCore:\n  Id: QC.CDISC.SDTMIG.CG0178\n  Version: '1'\n  Status: Draft\nDescription: Check if IETEST is not in TI.IETEST\nOutcome:\n  Message: IETEST is not in TI.IETEST\nRule Type: Record Data\nSensitivity: Record\nAuthorities:\n  - Organization: CDISC\n    Standards:\n      - Name: SDTMIG\n        Version: '3.4'\n        References:\n          - Origin: SDTM and SDTMIG Conformance Rules\n            Version: '2.0'\n            Rule Identifier:\n              Id: CG0178\n              Version: '1.0'\n            Citations:\n              - Cited Guidance: The complete list of Inclusion/Exclusion criteria\n                  can be found in the Trial Inclusion/Exclusion Criteria\u00a0(TI) dataset\n                  described in Section 7.4.1,\u00a0Trial Inclusion/Exclusion Criteria.\n                Document: IG v3.4\n                Item: Specification\n                Section: 6.3.4\nScope:\n  Classes:\n    Include:\n      - FINDINGS\n  Domains:\n    Include:\n      - IE\n",
    "created": "2022-03-08T17:45:25Z",
    "creator": {
        "id": "b5bc818b-4ec4-4952-951f-0fbca010be52"
    },
    "json": {
        "Check": {
            "all": [
                {
                    "name": "IETEST1",
                    "operator": "is_not_contained_by",
                    "value": "$ti_ietest"
                }
            ]
        },
        "Operations": [
            {
                "domain": "TI",
                "id": "$ti_ietest",
                "name": "IETEST2",
                "operator": "distinct"
            }
        ],
        "Core": {
            "Id": "QC.CDISC.SDTMIG.CG0178",
            "Version": "1",
            "Status": "Draft"
        },
        "Description": "Check if IETEST is not in TI.IETEST",
        "Outcome": {
            "Message": "IETEST is not in TI.IETEST"
        },
        "Rule_Type": "Record Data",
        "Sensitivity": "Record",
        "Authorities": [
            {
                "Organization": "CDISC",
                "Standards": [
                    {
                        "Name": "SDTMIG",
                        "Version": "3.4",
                        "References": [
                            {
                                "Origin": "SDTM and SDTMIG Conformance Rules",
                                "Version": "2.0",
                                "Rule_Identifier": {
                                    "Id": "CG0178",
                                    "Version": "1.0"
                                },
                                "Citations": [
                                    {
                                        "Cited_Guidance": "The complete list of Inclusion/Exclusion criteria can be found in the Trial Inclusion/Exclusion Criteria\u00a0(TI) dataset described in Section 7.4.1,\u00a0Trial Inclusion/Exclusion Criteria.",
                                        "Document": "IG v3.4",
                                        "Item": "Specification",
                                        "Section": "6.3.4"
                                    }
                                ]
                            }
                        ]
                    }
                ]
            }
        ],
        "Scope": {
            "Classes": {
                "Include": [
                    "FINDINGS"
                ]
            },
            "Domains": {
                "Include": [
                    "IE"
                ]
            }
        }
    }
}