{
    "id": "76f56eb4-5c8a-4d36-9f47-54ca4ca09442",
    "changed": "2022-04-19T14:59:48Z",
    "content": "Check:\n  all:\n    - name: ECOCCUR                     # The condition is ECOCCUR = \"N\"\n      operator: equal_to\n      value: N\n    - name: ECDOSE                      # The rule is ECDOSE is null or > 0\n                                        # so the failure criteria is not empty and LE 0\n                                        # which is the same as just LE 0\n      operator: less_than_or_equal_to\n      value: 0\nCore:\n  Id: CORE-000004\n  Version: '1'\n  Status: Published\nDescription: When ECOCCUR indicates no dose, then ECDOSE needs to be null or > 0;\n  it cannot be used to indicate a dose wasn't taken.\nOutcome:\n  Message: ECOCCUR indicates dose was not given, but ECDOSE is not blank or has a\n    value less than or equal to 0\n  Output Variables:\n    - ECDOSE\n    - ECOCCUR\nRule Type: Record Data\nSensitivity: Record\nAuthorities:\n  - Organization: CDISC\n    Standards:\n      - Name: SDTMIG\n        Version: '3.4'\n        References:\n          - Origin: SDTM and SDTMIG Conformance Rules\n            Rule Identifier:\n              Id: CG0101\n              Version: '2'\n            Version: '2.0'\n            Citations:\n              - Cited Guidance: For example, if 0 tablets are taken within a timeframe\n                  or 0 mL is infused at a visit, then  ECOCCUR = 'N' is the standard\n                  representation of the collected doses not taken, not given,  or\n                  missed. Dose amount variables (e.g., ECDOSE, ECDOSTXT) must not\n                  be set to zero (0) as  an alternative method for indicating doses\n                  not taken, not given, or missed.\n                Document: IG v3.4\n                Item: Assumption 4a\n                Section: 6.1.3.2\n              - Cited Guidance: Qualifiers that indicate dose amount (e.g., ECDOSE,\n                  ECDOSTXT) may be populated with positive (non-zero) values in cases\n                  where the sponsor feels it is necessary and/or appropriate to represent\n                  specific dose amounts not taken, not given, or missed.\n                Document: IG v3.4\n                Item: Assumption 4b\n                Section: 6.1.3.2\nScope:\n  Classes:\n    Include:\n      - INTERVENTIONS\n  Domains:\n    Include:\n      - EC\n",
    "created": "2021-09-24T17:58:37Z",
    "creator": {
        "id": "f9333394-14e8-48f3-9a3a-62f1e3cf098c"
    },
    "json": {
        "Check": {
            "all": [
                {
                    "name": "ECOCCUR",
                    "operator": "equal_to",
                    "value": "N"
                },
                {
                    "name": "ECDOSE",
                    "operator": "less_than_or_equal_to",
                    "value": 0
                }
            ]
        },
        "Core": {
            "Id": "CORE-000004",
            "Version": "1",
            "Status": "Published"
        },
        "Description": "When ECOCCUR indicates no dose, then ECDOSE needs to be null or > 0; it cannot be used to indicate a dose wasn't taken.",
        "Outcome": {
            "Message": "ECOCCUR indicates dose was not given, but ECDOSE is not blank or has a value less than or equal to 0",
            "Output_Variables": [
                "ECDOSE",
                "ECOCCUR"
            ]
        },
        "Rule_Type": "Record Data",
        "Sensitivity": "Record",
        "Authorities": [
            {
                "Organization": "CDISC",
                "Standards": [
                    {
                        "Name": "SDTMIG",
                        "Version": "3.4",
                        "References": [
                            {
                                "Origin": "SDTM and SDTMIG Conformance Rules",
                                "Rule_Identifier": {
                                    "Id": "CG0101",
                                    "Version": "2"
                                },
                                "Version": "2.0",
                                "Citations": [
                                    {
                                        "Cited_Guidance": "For example, if 0 tablets are taken within a timeframe or 0 mL is infused at a visit, then  ECOCCUR = 'N' is the standard representation of the collected doses not taken, not given,  or missed. Dose amount variables (e.g., ECDOSE, ECDOSTXT) must not be set to zero (0) as  an alternative method for indicating doses not taken, not given, or missed.",
                                        "Document": "IG v3.4",
                                        "Item": "Assumption 4a",
                                        "Section": "6.1.3.2"
                                    },
                                    {
                                        "Cited_Guidance": "Qualifiers that indicate dose amount (e.g., ECDOSE, ECDOSTXT) may be populated with positive (non-zero) values in cases where the sponsor feels it is necessary and/or appropriate to represent specific dose amounts not taken, not given, or missed.",
                                        "Document": "IG v3.4",
                                        "Item": "Assumption 4b",
                                        "Section": "6.1.3.2"
                                    }
                                ]
                            }
                        ]
                    }
                ]
            }
        ],
        "Scope": {
            "Classes": {
                "Include": [
                    "INTERVENTIONS"
                ]
            },
            "Domains": {
                "Include": [
                    "EC"
                ]
            }
        }
    }
}