{
    "id": "09182b07-93eb-4112-98de-37b3db39b457",
    "changed": "2022-04-14T14:18:17Z",
    "content": "Check:\n  all:\n    - name: IESTRESC\n      operator: not_equal_to\n      value: IEORRES\nCore:\n  Id: CORE-000025\n  Version: '1'\n  Status: Published\nDescription: IESTRESC is not equal to IEORRES\nOutcome:\n  Message: IESTRESC is not equal to IEORRES\n  Output Variables:\n    - IEORRES\n    - IESTRESC\nRule Type: Record Data\nSensitivity: Record\nAuthorities:\n  - Organization: CDISC\n    Standards:\n      - Name: SDTMIG\n        Version: '3.4'\n        References:\n          - Origin: SDTM and SDTMIG Conformance Rules\n            Rule Identifier:\n              Id: CG0177\n              Version: '1'\n            Version: '2.0'\n            Citations:\n              - Cited Guidance: Response to Inclusion/Exclusion criterion result in\n                  standard format\n                Document: SDTMIG v3.4\n                Item: ''\n                Section: 6.3.4\nScope:\n  Classes:\n    Include:\n      - FINDINGS\n  Domains:\n    Include:\n      - IE\n",
    "created": "2021-09-29T20:13:20Z",
    "creator": {
        "id": "c3910f45-cb71-431f-befb-338bab20116a"
    },
    "json": {
        "Check": {
            "all": [
                {
                    "name": "IESTRESC",
                    "operator": "not_equal_to",
                    "value": "IEORRES"
                }
            ]
        },
        "Core": {
            "Id": "CORE-000025",
            "Version": "1",
            "Status": "Published"
        },
        "Description": "IESTRESC is not equal to IEORRES",
        "Outcome": {
            "Message": "IESTRESC is not equal to IEORRES",
            "Output_Variables": [
                "IEORRES",
                "IESTRESC"
            ]
        },
        "Rule_Type": "Record Data",
        "Sensitivity": "Record",
        "Authorities": [
            {
                "Organization": "CDISC",
                "Standards": [
                    {
                        "Name": "SDTMIG",
                        "Version": "3.4",
                        "References": [
                            {
                                "Origin": "SDTM and SDTMIG Conformance Rules",
                                "Rule_Identifier": {
                                    "Id": "CG0177",
                                    "Version": "1"
                                },
                                "Version": "2.0",
                                "Citations": [
                                    {
                                        "Cited_Guidance": "Response to Inclusion/Exclusion criterion result in standard format",
                                        "Document": "SDTMIG v3.4",
                                        "Item": "",
                                        "Section": "6.3.4"
                                    }
                                ]
                            }
                        ]
                    }
                ]
            }
        ],
        "Scope": {
            "Classes": {
                "Include": [
                    "FINDINGS"
                ]
            },
            "Domains": {
                "Include": [
                    "IE"
                ]
            }
        }
    }
}