{
    "id": "6a0c4575-b736-4014-af26-0618a30047b4",
    "changed": "2022-07-31T09:54:13Z",
    "content": "Check:\n  all:\n    - name: --DOSTXT\n      operator: non_empty\n    - name: --DOSE\n      operator: non_empty\nCore:\n  Id: CORE-000092\n  Version: '1'\n  Status: Published\nDescription: Raise an error when --DOSE ^= null and --DOSTXT ^= null.\nOutcome:\n  Message: Both --DOSE and --DOSTXT values are populated\n  Output Variables:\n    - --DOSE\n    - --DOSTXT\nRule Type: Record Data\nSensitivity: Record\nAuthorities:\n  - Organization: CDISC\n    Standards:\n      - Name: SDTMIG\n        Version: '3.4'\n        References:\n          - Origin: SDTM and SDTMIG Conformance Rules\n            Rule Identifier:\n              Id: CG0110\n              Version: '1'\n            Version: '2.0'\n            Citations:\n              Cited Guidance: Not populated when --DOSTXT is populated.\n              Document: Model v2.0\n              Item: --DOSE\n              Section: Interventions\n      - Name: SDTMIG\n        Version: '3.4'\n        References:\n          - Origin: SDTM and SDTMIG Conformance Rules\n            Rule Identifier:\n              Id: CG0111\n              Version: '1'\n            Version: '2.0'\n            Citations:\n              Cited Guidance: Not populated when --DOSE is populated.\n              Document: Model v2.0\n              Item: --DOSETXT\n              Section: Interventions\nScope:\n  Classes:\n    Include:\n      - INTERVENTIONS\n  Domains:\n    Include:\n      - ALL\n",
    "created": "2021-10-06T17:01:31Z",
    "creator": {
        "id": "d0881041-369e-4940-b721-5b456d12101b"
    },
    "json": {
        "Check": {
            "all": [
                {
                    "name": "--DOSTXT",
                    "operator": "non_empty"
                },
                {
                    "name": "--DOSE",
                    "operator": "non_empty"
                }
            ]
        },
        "Core": {
            "Id": "CORE-000092",
            "Version": "1",
            "Status": "Published"
        },
        "Description": "Raise an error when --DOSE ^= null and --DOSTXT ^= null.",
        "Outcome": {
            "Message": "Both --DOSE and --DOSTXT values are populated",
            "Output_Variables": [
                "--DOSE",
                "--DOSTXT"
            ]
        },
        "Rule_Type": "Record Data",
        "Sensitivity": "Record",
        "Authorities": [
            {
                "Organization": "CDISC",
                "Standards": [
                    {
                        "Name": "SDTMIG",
                        "Version": "3.4",
                        "References": [
                            {
                                "Origin": "SDTM and SDTMIG Conformance Rules",
                                "Rule_Identifier": {
                                    "Id": "CG0110",
                                    "Version": "1"
                                },
                                "Version": "2.0",
                                "Citations": {
                                    "Cited_Guidance": "Not populated when --DOSTXT is populated.",
                                    "Document": "Model v2.0",
                                    "Item": "--DOSE",
                                    "Section": "Interventions"
                                }
                            }
                        ]
                    },
                    {
                        "Name": "SDTMIG",
                        "Version": "3.4",
                        "References": [
                            {
                                "Origin": "SDTM and SDTMIG Conformance Rules",
                                "Rule_Identifier": {
                                    "Id": "CG0111",
                                    "Version": "1"
                                },
                                "Version": "2.0",
                                "Citations": {
                                    "Cited_Guidance": "Not populated when --DOSE is populated.",
                                    "Document": "Model v2.0",
                                    "Item": "--DOSETXT",
                                    "Section": "Interventions"
                                }
                            }
                        ]
                    }
                ]
            }
        ],
        "Scope": {
            "Classes": {
                "Include": [
                    "INTERVENTIONS"
                ]
            },
            "Domains": {
                "Include": [
                    "ALL"
                ]
            }
        }
    }
}