{
    "id": "77d2ec57-77f1-40c9-9618-072d85e5a8f7",
    "changed": "2022-07-30T12:30:56Z",
    "content": "Check:\n  all:\n    - name: TAETORD\n      operator: not_exists\n    - name: EPOCH\n      operator: not_exists\n    - name: --STDTC\n      operator: not_exists\n    - name: --ENDTC\n      operator: not_exists\n    - name: --DTC\n      operator: not_exists\n    - name: --STDY\n      operator: not_exists\n    - name: --ENDY\n      operator: not_exists\n    - name: --DY\n      operator: not_exists\n    - name: --DUR\n      operator: not_exists\n    - name: --TPT\n      operator: not_exists\n    - name: --TPTNUM\n      operator: not_exists\n    - name: --REPNUM\n      operator: not_exists\n    - name: --STRF\n      operator: not_exists\n    - name: --STRTPT\n      operator: not_exists\n    - name: --STTPT\n      operator: not_exists\n    - name: --ENRF\n      operator: not_exists\n    - name: --ENRTPT\n      operator: not_exists\n    - name: --ENTPT\n      operator: not_exists\nCore:\n  Id: CDISC.SDTMIG.CG0219\n  Version: '1'\n  Status: Draft\nDescription: In general, all domains based on the three general observation classes\n  should have at least one Timing variable.\nOutcome:\n  Message: No timing variable present in dataset.\nRule Type: Record Data\nSensitivity: Dataset\nAuthorities:\n  - Organization: CDISC\n    Standards:\n      - Name: SDTMIG\n        Version: '3.4'\n        References:\n          - Origin: SDTM and SDTMIG Conformance Rules\n            Rule Identifier:\n              Id: CG0219\n              Version: '1'\n            Version: '2.0'\n            Citations:\n              - Cited Guidance: Timing variables (SDTM Table 2.2.5) are an essential\n                  component of all SDTM subject-level domain datasets. In general,\n                  all domains based on the three general observation classes should\n                  have at least one Timing variable. In the Events or Interventions\n                  general observation class, this could be the start date of the event\n                  or intervention. In the Findings observation class, where data are\n                  usually collected at multiple visits, at least one Timing variable\n                  must be used.\n                Document: IG v3.4\n                Section: '4.4'\nScope:\n  Classes:\n    Include:\n      - INTERVENTIONS\n      - FINDINGS\n      - EVENTS\n  Domains:\n    Exclude:\n      - IE\n      - SC\n",
    "created": "2021-10-16T10:19:43Z",
    "creator": {
        "id": "ff471ff8-f131-4cf5-9712-c79cce6301a1"
    },
    "json": {
        "Check": {
            "all": [
                {
                    "name": "TAETORD",
                    "operator": "not_exists"
                },
                {
                    "name": "EPOCH",
                    "operator": "not_exists"
                },
                {
                    "name": "--STDTC",
                    "operator": "not_exists"
                },
                {
                    "name": "--ENDTC",
                    "operator": "not_exists"
                },
                {
                    "name": "--DTC",
                    "operator": "not_exists"
                },
                {
                    "name": "--STDY",
                    "operator": "not_exists"
                },
                {
                    "name": "--ENDY",
                    "operator": "not_exists"
                },
                {
                    "name": "--DY",
                    "operator": "not_exists"
                },
                {
                    "name": "--DUR",
                    "operator": "not_exists"
                },
                {
                    "name": "--TPT",
                    "operator": "not_exists"
                },
                {
                    "name": "--TPTNUM",
                    "operator": "not_exists"
                },
                {
                    "name": "--REPNUM",
                    "operator": "not_exists"
                },
                {
                    "name": "--STRF",
                    "operator": "not_exists"
                },
                {
                    "name": "--STRTPT",
                    "operator": "not_exists"
                },
                {
                    "name": "--STTPT",
                    "operator": "not_exists"
                },
                {
                    "name": "--ENRF",
                    "operator": "not_exists"
                },
                {
                    "name": "--ENRTPT",
                    "operator": "not_exists"
                },
                {
                    "name": "--ENTPT",
                    "operator": "not_exists"
                }
            ]
        },
        "Core": {
            "Id": "CDISC.SDTMIG.CG0219",
            "Version": "1",
            "Status": "Draft"
        },
        "Description": "In general, all domains based on the three general observation classes should have at least one Timing variable.",
        "Outcome": {
            "Message": "No timing variable present in dataset."
        },
        "Rule_Type": "Record Data",
        "Sensitivity": "Dataset",
        "Authorities": [
            {
                "Organization": "CDISC",
                "Standards": [
                    {
                        "Name": "SDTMIG",
                        "Version": "3.4",
                        "References": [
                            {
                                "Origin": "SDTM and SDTMIG Conformance Rules",
                                "Rule_Identifier": {
                                    "Id": "CG0219",
                                    "Version": "1"
                                },
                                "Version": "2.0",
                                "Citations": [
                                    {
                                        "Cited_Guidance": "Timing variables (SDTM Table 2.2.5) are an essential component of all SDTM subject-level domain datasets. In general, all domains based on the three general observation classes should have at least one Timing variable. In the Events or Interventions general observation class, this could be the start date of the event or intervention. In the Findings observation class, where data are usually collected at multiple visits, at least one Timing variable must be used.",
                                        "Document": "IG v3.4",
                                        "Section": "4.4"
                                    }
                                ]
                            }
                        ]
                    }
                ]
            }
        ],
        "Scope": {
            "Classes": {
                "Include": [
                    "INTERVENTIONS",
                    "FINDINGS",
                    "EVENTS"
                ]
            },
            "Domains": {
                "Exclude": [
                    "IE",
                    "SC"
                ]
            }
        }
    }
}