{
    "id": "68619e28-38df-4699-a91d-7b1c1d96a944",
    "changed": "2022-04-13T21:17:05Z",
    "content": "Check:\n  all:\n    - name: TSPARM\n      operator: longer_than\n      value: 40\nCore:\n  Id: CORE-000148\n  Version: '1'\n  Status: Published\nDescription: Trigger error when length of TSPARM value is greater than 40\nOutcome:\n  Message: Length of TSPARM is greater than 40\n  Output Variables:\n    - TSPARM\n    - TSPARMCD\nRule Type: Record Data\nSensitivity: Record\nAuthorities:\n  - Organization: CDISC\n    Standards:\n      - Name: SDTMIG\n        Version: '3.4'\n        References:\n          - Origin: SDTM and SDTMIG Conformance Rules\n            Rule Identifier:\n              Id: CG0258\n              Version: '1'\n            Version: '2.0'\n            Citations:\n              - Cited Guidance: The value in TSPARM cannot be longer than 40 characters.\n                Document: IG v3.4\n                Item: Specification\n                Section: 7.4.2\nScope:\n  Classes:\n    Include:\n      - TRIAL DESIGN\n  Domains:\n    Include:\n      - TS\n",
    "created": "2021-10-17T05:00:38Z",
    "creator": {
        "id": "ff471ff8-f131-4cf5-9712-c79cce6301a1"
    },
    "json": {
        "Check": {
            "all": [
                {
                    "name": "TSPARM",
                    "operator": "longer_than",
                    "value": 40
                }
            ]
        },
        "Core": {
            "Id": "CORE-000148",
            "Version": "1",
            "Status": "Published"
        },
        "Description": "Trigger error when length of TSPARM value is greater than 40",
        "Outcome": {
            "Message": "Length of TSPARM is greater than 40",
            "Output_Variables": [
                "TSPARM",
                "TSPARMCD"
            ]
        },
        "Rule_Type": "Record Data",
        "Sensitivity": "Record",
        "Authorities": [
            {
                "Organization": "CDISC",
                "Standards": [
                    {
                        "Name": "SDTMIG",
                        "Version": "3.4",
                        "References": [
                            {
                                "Origin": "SDTM and SDTMIG Conformance Rules",
                                "Rule_Identifier": {
                                    "Id": "CG0258",
                                    "Version": "1"
                                },
                                "Version": "2.0",
                                "Citations": [
                                    {
                                        "Cited_Guidance": "The value in TSPARM cannot be longer than 40 characters.",
                                        "Document": "IG v3.4",
                                        "Item": "Specification",
                                        "Section": "7.4.2"
                                    }
                                ]
                            }
                        ]
                    }
                ]
            }
        ],
        "Scope": {
            "Classes": {
                "Include": [
                    "TRIAL DESIGN"
                ]
            },
            "Domains": {
                "Include": [
                    "TS"
                ]
            }
        }
    }
}