{
    "id": "ed6d64d9-f81a-47d1-aaf9-7671c72a6311",
    "changed": "2022-02-15T21:32:07Z",
    "content": "Check:\n  all:\n    - name:\n      operator:\n    - name: TIVERS\n      operator: is_empty\nCore:\n  Id: CDISC.SDTMIG.CG0253\n  Version: '1'\n  Status: Draft\nDescription: Trigger error when TIVERS is null and there is more than one version\n  of the IE criteria in study documentation\nOutcome:\n  Message: TIVERS is null when there is more than one version of the IE criteria in\n    study documentation\nRule Type: Record Data\nSensitivity: Study\nAuthorities:\n  - Organization: CDISC\n    Standards:\n      - Name: SDTMIG\n        Version: '3.4'\n        References:\n          - Origin: SDTM and SDTMIG Conformance Rules\n            Rule Identifier:\n              Id: CG0253\n              Version: '1'\n            Version: '2.0'\n            Citations:\n              - Cited Guidance: If inclusion/exclusion criteria were amended during\n                  the trial, then each complete set of criteria must be included in\n                  the TI domain. TIVERS is used to distinguish between the versions.\n                Document: IG v3.4\n                Item: Assumption 1\n                Section: 7.4.1\nScope:\n  Classes:\n    Include:\n      - TRIAL DESIGN\n  Domains:\n    Include:\n      - TI\n",
    "created": "2021-10-30T10:40:45Z",
    "creator": {
        "id": "ff471ff8-f131-4cf5-9712-c79cce6301a1"
    },
    "json": {
        "Check": {
            "all": [
                {
                    "name": null,
                    "operator": null
                },
                {
                    "name": "TIVERS",
                    "operator": "is_empty"
                }
            ]
        },
        "Core": {
            "Id": "CDISC.SDTMIG.CG0253",
            "Version": "1",
            "Status": "Draft"
        },
        "Description": "Trigger error when TIVERS is null and there is more than one version of the IE criteria in study documentation",
        "Outcome": {
            "Message": "TIVERS is null when there is more than one version of the IE criteria in study documentation"
        },
        "Rule_Type": "Record Data",
        "Sensitivity": "Study",
        "Authorities": [
            {
                "Organization": "CDISC",
                "Standards": [
                    {
                        "Name": "SDTMIG",
                        "Version": "3.4",
                        "References": [
                            {
                                "Origin": "SDTM and SDTMIG Conformance Rules",
                                "Rule_Identifier": {
                                    "Id": "CG0253",
                                    "Version": "1"
                                },
                                "Version": "2.0",
                                "Citations": [
                                    {
                                        "Cited_Guidance": "If inclusion/exclusion criteria were amended during the trial, then each complete set of criteria must be included in the TI domain. TIVERS is used to distinguish between the versions.",
                                        "Document": "IG v3.4",
                                        "Item": "Assumption 1",
                                        "Section": "7.4.1"
                                    }
                                ]
                            }
                        ]
                    }
                ]
            }
        ],
        "Scope": {
            "Classes": {
                "Include": [
                    "TRIAL DESIGN"
                ]
            },
            "Domains": {
                "Include": [
                    "TI"
                ]
            }
        }
    }
}