{
    "id": "387842b7-69e4-4210-97a8-d9c26dd6b5ae",
    "changed": "2022-04-14T15:38:46Z",
    "content": "Check:\n  all:\n    - name: TSVAL\n      operator: non_empty\n    - name: TSVALNF\n      operator: non_empty\nCore:\n  Id: CORE-000150\n  Version: '1'\n  Status: Published\nDescription: Trigger error when TSVAL is populated and TSVALNF is also populated.\nOutcome:\n  Message: TSVALNF is not null when TSVAL is populated\nRule Type: Record Data\nSensitivity: Record\nAuthorities:\n  - Organization: CDISC\n    Standards:\n      - Name: SDTMIG\n        Version: '3.4'\n        References:\n          - Origin: SDTM and SDTMIG Conformance Rules\n            Rule Identifier:\n              Id: CG0260\n              Version: '1'\n            Version: '2.0'\n            Citations:\n              - Cited Guidance: Null flavor for the value of TSPARM, to be populated\n                  if and only if TSVAL is null.\n                Document: IG v3.4\n                Item: Specification\n                Section: 7.4.2\nScope:\n  Classes:\n    Include:\n      - TRIAL DESIGN\n  Domains:\n    Include:\n      - TS\n",
    "created": "2021-10-17T05:06:57Z",
    "creator": {
        "id": "ff471ff8-f131-4cf5-9712-c79cce6301a1"
    },
    "json": {
        "Check": {
            "all": [
                {
                    "name": "TSVAL",
                    "operator": "non_empty"
                },
                {
                    "name": "TSVALNF",
                    "operator": "non_empty"
                }
            ]
        },
        "Core": {
            "Id": "CORE-000150",
            "Version": "1",
            "Status": "Published"
        },
        "Description": "Trigger error when TSVAL is populated and TSVALNF is also populated.",
        "Outcome": {
            "Message": "TSVALNF is not null when TSVAL is populated"
        },
        "Rule_Type": "Record Data",
        "Sensitivity": "Record",
        "Authorities": [
            {
                "Organization": "CDISC",
                "Standards": [
                    {
                        "Name": "SDTMIG",
                        "Version": "3.4",
                        "References": [
                            {
                                "Origin": "SDTM and SDTMIG Conformance Rules",
                                "Rule_Identifier": {
                                    "Id": "CG0260",
                                    "Version": "1"
                                },
                                "Version": "2.0",
                                "Citations": [
                                    {
                                        "Cited_Guidance": "Null flavor for the value of TSPARM, to be populated if and only if TSVAL is null.",
                                        "Document": "IG v3.4",
                                        "Item": "Specification",
                                        "Section": "7.4.2"
                                    }
                                ]
                            }
                        ]
                    }
                ]
            }
        ],
        "Scope": {
            "Classes": {
                "Include": [
                    "TRIAL DESIGN"
                ]
            },
            "Domains": {
                "Include": [
                    "TS"
                ]
            }
        }
    }
}