{
    "id": "90192e69-9096-4963-9639-ad26d156723f",
    "changed": "2022-03-14T20:06:21Z",
    "content": "Check:\n  all:\n    - name: RFENDTC\n      operator: empty\n    - name: --ENRF\n      operator: non_empty\nCore:\n  Id: CORE-000177\n  Version: '1'\n  Status: Published\nDescription: Raise an error when DM.RFENDTC is empty and --ENRF is not empty.\nMatch Datasets:\n  - Name: DM\n    Keys:\n      - USUBJID\nOutcome:\n  Message: DM.RFENDTC is empty, but --ENRF is completed.\n  Output Variables:\n    - --ENRF\nRule Type: Record Data\nSensitivity: Record\nAuthorities:\n  - Organization: CDISC\n    Standards:\n      - Name: SDTMIG\n        Version: '3.4'\n        References:\n          - Origin: SDTM and SDTMIG Conformance Rules\n            Rule Identifier:\n              Id: CG0227\n              Version: '1'\n            Version: '2.0'\n            Citations:\n              - Cited Guidance: The characterization of the end of an observation\n                  relative to the study reference period.\u00a0 The sponsor-defined reference\n                  period is a continuous period of time defined by a discrete starting\n                  point and a discrete ending point represented by RFSTDTC and RFENDTC\n                  in Demographics.\n                Document: Model 2.0\n                Item: --ENRF\n                Section: Timing\nScope:\n  Classes:\n    Include:\n      - ALL\n  Domains:\n    Exclude:\n      - DM\n",
    "created": "2021-10-28T14:07:02Z",
    "creator": {
        "id": "02c3c969-4787-4d57-b164-e2851035c0e8"
    },
    "json": {
        "Check": {
            "all": [
                {
                    "name": "RFENDTC",
                    "operator": "empty"
                },
                {
                    "name": "--ENRF",
                    "operator": "non_empty"
                }
            ]
        },
        "Core": {
            "Id": "CORE-000177",
            "Version": "1",
            "Status": "Published"
        },
        "Description": "Raise an error when DM.RFENDTC is empty and --ENRF is not empty.",
        "Match_Datasets": [
            {
                "Name": "DM",
                "Keys": [
                    "USUBJID"
                ]
            }
        ],
        "Outcome": {
            "Message": "DM.RFENDTC is empty, but --ENRF is completed.",
            "Output_Variables": [
                "--ENRF"
            ]
        },
        "Rule_Type": "Record Data",
        "Sensitivity": "Record",
        "Authorities": [
            {
                "Organization": "CDISC",
                "Standards": [
                    {
                        "Name": "SDTMIG",
                        "Version": "3.4",
                        "References": [
                            {
                                "Origin": "SDTM and SDTMIG Conformance Rules",
                                "Rule_Identifier": {
                                    "Id": "CG0227",
                                    "Version": "1"
                                },
                                "Version": "2.0",
                                "Citations": [
                                    {
                                        "Cited_Guidance": "The characterization of the end of an observation relative to the study reference period.\u00a0 The sponsor-defined reference period is a continuous period of time defined by a discrete starting point and a discrete ending point represented by RFSTDTC and RFENDTC in Demographics.",
                                        "Document": "Model 2.0",
                                        "Item": "--ENRF",
                                        "Section": "Timing"
                                    }
                                ]
                            }
                        ]
                    }
                ]
            }
        ],
        "Scope": {
            "Classes": {
                "Include": [
                    "ALL"
                ]
            },
            "Domains": {
                "Exclude": [
                    "DM"
                ]
            }
        }
    }
}