{
    "id": "618469da-622d-49d0-8e14-02c2b38d6c04",
    "changed": "2022-04-13T20:47:09Z",
    "content": "Check:\n  all:\n    - name: TSPARMCD\n      operator: longer_than\n      value: 8\nCore:\n  Id: CORE-000147\n  Version: '1'\n  Status: Published\nDescription: Trigger error when length of TSPARMCD is greater than 8\nOutcome:\n  Message: Length of TSPARMCD is greater than 8\n  Output Variables:\n    - TSPARM\n    - TSPARMCD\nRule Type: Record Data\nSensitivity: Record\nAuthorities:\n  - Organization: CDISC\n    Standards:\n      - Name: SDTMIG\n        Version: '3.4'\n        References:\n          - Origin: SDTM and SDTMIG Conformance Rules\n            Rule Identifier:\n              Id: CG0257\n              Version: '1'\n            Version: '2.0'\n            Citations:\n              - Cited Guidance: TSPARMCD (the companion to TSPARM) is limited to 8\n                  characters and does not have special character restrictions.\n                Document: IG v3.4\n                Item: Specification\n                Section: 7.4.2\nScope:\n  Classes:\n    Include:\n      - TRIAL DESIGN\n  Domains:\n    Include:\n      - TS\n",
    "created": "2021-10-17T04:57:48Z",
    "creator": {
        "id": "ff471ff8-f131-4cf5-9712-c79cce6301a1"
    },
    "json": {
        "Check": {
            "all": [
                {
                    "name": "TSPARMCD",
                    "operator": "longer_than",
                    "value": 8
                }
            ]
        },
        "Core": {
            "Id": "CORE-000147",
            "Version": "1",
            "Status": "Published"
        },
        "Description": "Trigger error when length of TSPARMCD is greater than 8",
        "Outcome": {
            "Message": "Length of TSPARMCD is greater than 8",
            "Output_Variables": [
                "TSPARM",
                "TSPARMCD"
            ]
        },
        "Rule_Type": "Record Data",
        "Sensitivity": "Record",
        "Authorities": [
            {
                "Organization": "CDISC",
                "Standards": [
                    {
                        "Name": "SDTMIG",
                        "Version": "3.4",
                        "References": [
                            {
                                "Origin": "SDTM and SDTMIG Conformance Rules",
                                "Rule_Identifier": {
                                    "Id": "CG0257",
                                    "Version": "1"
                                },
                                "Version": "2.0",
                                "Citations": [
                                    {
                                        "Cited_Guidance": "TSPARMCD (the companion to TSPARM) is limited to 8 characters and does not have special character restrictions.",
                                        "Document": "IG v3.4",
                                        "Item": "Specification",
                                        "Section": "7.4.2"
                                    }
                                ]
                            }
                        ]
                    }
                ]
            }
        ],
        "Scope": {
            "Classes": {
                "Include": [
                    "TRIAL DESIGN"
                ]
            },
            "Domains": {
                "Include": [
                    "TS"
                ]
            }
        }
    }
}