{
    "id": "468d44f7-8dbe-40ba-a4c1-c8e94fb900d9",
    "changed": "2022-06-22T11:30:14Z",
    "content": "Check:\n  any:\n    - all:\n        - name: --ENDTC\n          operator: is_incomplete_date\n        - name: --ENDY\n          operator: non_empty\n    - all:\n        - name: RFSTDTC\n          operator: is_incomplete_date\n        - name: --ENDY\n          operator: non_empty\nMatch Datasets:\n  - Name: DM\n    Keys:\n      - USUBJID\nCore:\n  Id: CORE-000139\n  Version: '1'\n  Status: Published\nDescription: Trigger error if --ENDTC or DM.RFSTDTC does not contain complete values\n  in their date portion, and --ENDY is not null.\nOutcome:\n  Message: --ENDY is not null when either --ENDTC or DM.RFSTDTC do not contain complete\n    values in their date portion\n  Output Variables:\n    - --ENDTC\n    - RFSTDTC\n    - --ENDY\nRule Type: Record Data\nSensitivity: Record\nAuthorities:\n  - Organization: CDISC\n    Standards:\n      - Name: SDTMIG\n        Version: '3.4'\n        References:\n          - Origin: SDTM and SDTMIG Conformance Rules\n            Rule Identifier:\n              Id: CG0223\n              Version: '1'\n            Version: '2.0'\n            Citations:\n              - Cited Guidance: The permissible Study Day variables (--DY, --STDY,\n                  and --ENDY) describe the relative day of the observation starting\n                  with the reference date as Day 1. They are determined by comparing\n                  the date portion of the  respective date/time variables (--DTC,\n                  --STDTC, and --ENDTC) to the date portion of the Subject Reference  Start\n                  Date (RFSTDTC from the Demographics domain). All Study Day values\n                  are integers. Thus, to calculate Study Day,  --DY = (date portion\n                  of --DTC) - (date portion of RFSTDTC) + 1 if --DTC is on or after\n                  RFSTDTC,  --DY = (date portion of --DTC) - (date portion of RFSTDTC)\n                  if --DTC precedes RFSTDTC.  This algorithm should be used across\n                  all domains.\n                Document: IG v3.4\n                Section: 4.4.4\nScope:\n  Classes:\n    Include:\n      - ALL\n  Domains:\n    Exclude:\n      - DM\n",
    "created": "2021-10-16T11:16:26Z",
    "creator": {
        "id": "ff471ff8-f131-4cf5-9712-c79cce6301a1"
    },
    "json": {
        "Check": {
            "any": [
                {
                    "all": [
                        {
                            "name": "--ENDTC",
                            "operator": "is_incomplete_date"
                        },
                        {
                            "name": "--ENDY",
                            "operator": "non_empty"
                        }
                    ]
                },
                {
                    "all": [
                        {
                            "name": "RFSTDTC",
                            "operator": "is_incomplete_date"
                        },
                        {
                            "name": "--ENDY",
                            "operator": "non_empty"
                        }
                    ]
                }
            ]
        },
        "Match_Datasets": [
            {
                "Name": "DM",
                "Keys": [
                    "USUBJID"
                ]
            }
        ],
        "Core": {
            "Id": "CORE-000139",
            "Version": "1",
            "Status": "Published"
        },
        "Description": "Trigger error if --ENDTC or DM.RFSTDTC does not contain complete values in their date portion, and --ENDY is not null.",
        "Outcome": {
            "Message": "--ENDY is not null when either --ENDTC or DM.RFSTDTC do not contain complete values in their date portion",
            "Output_Variables": [
                "--ENDTC",
                "RFSTDTC",
                "--ENDY"
            ]
        },
        "Rule_Type": "Record Data",
        "Sensitivity": "Record",
        "Authorities": [
            {
                "Organization": "CDISC",
                "Standards": [
                    {
                        "Name": "SDTMIG",
                        "Version": "3.4",
                        "References": [
                            {
                                "Origin": "SDTM and SDTMIG Conformance Rules",
                                "Rule_Identifier": {
                                    "Id": "CG0223",
                                    "Version": "1"
                                },
                                "Version": "2.0",
                                "Citations": [
                                    {
                                        "Cited_Guidance": "The permissible Study Day variables (--DY, --STDY, and --ENDY) describe the relative day of the observation starting with the reference date as Day 1. They are determined by comparing the date portion of the  respective date/time variables (--DTC, --STDTC, and --ENDTC) to the date portion of the Subject Reference  Start Date (RFSTDTC from the Demographics domain). All Study Day values are integers. Thus, to calculate Study Day,  --DY = (date portion of --DTC) - (date portion of RFSTDTC) + 1 if --DTC is on or after RFSTDTC,  --DY = (date portion of --DTC) - (date portion of RFSTDTC) if --DTC precedes RFSTDTC.  This algorithm should be used across all domains.",
                                        "Document": "IG v3.4",
                                        "Section": "4.4.4"
                                    }
                                ]
                            }
                        ]
                    }
                ]
            }
        ],
        "Scope": {
            "Classes": {
                "Include": [
                    "ALL"
                ]
            },
            "Domains": {
                "Exclude": [
                    "DM"
                ]
            }
        }
    }
}