{
    "id": "61766f35-7d2f-4bb3-b119-407a5397873d",
    "changed": "2022-05-18T19:56:31Z",
    "content": "Check:\n  all:\n    - name: --TPT\n      operator: non_empty\n    - name: --TPTNUM\n      operator: non_empty\n    - name: --ELTM\n      operator: non_empty\n    - name: --ELTM\n      operator: is_unique_set\n      value:\n        - DOMAIN\n        - VISITNUM\n        - --TPTREF\n        - --TPTNUM\nCore:\n  Id: CORE-000142\n  Version: '1'\n  Status: Published\nDescription: Trigger error where --TPT ^= null and --TPTNUM ^= null and --ELTM ^=\n  null and --ELTM does not have the same value across records with the same values\n  of DOMAIN, VISITNUM, --TPTREF, and --TPTNUM, when\nOutcome:\n  Message: --ELTM is not the same value across records with the same values of DOMAIN,\n    VISITNUM, --TPTREF, and --TPTNUM\n  Output Variables:\n    - --TPT\n    - --TPTNUM\n    - --ELTM\nRule Type: Record Data\nSensitivity: Domain\nAuthorities:\n  - Organization: CDISC\n    Standards:\n      - Name: SDTMIG\n        Version: '3.4'\n        References:\n          - Origin: SDTM and SDTMIG Conformance Rules\n            Rule Identifier:\n              Id: CG0241\n              Version: '1'\n            Version: '2.0'\n            Citations:\n              - Cited Guidance: Within the context that defines uniqueness for a time\n                  point, there is likely to be a one-to-one relationship between most\n                  values of --TPT and --ELTM. However, since --ELTM can only be populated\n                  with ISO 8601 periods of time (as described in Section 4.4.3, Intervals\n                  of Time and Use of Duration for --DUR Variables), --ELTM may not\n                  be populated for all time points. For example, --ELTM is likely\n                  to be null for time points described by text such as 'pre-dose'\n                  or 'before breakfast.' When --ELTM is populated, if two subjects\n                  have records with the same values of DOMAIN, VISITNUM, --TPTREF,\n                  and --TPTNUM, then these records may not have different values in\n                  --ELTM.\n                Document: IG v3.4\n                Section: 4.4.10\nScope:\n  Classes:\n    Include:\n      - ALL\n  Domains:\n    Include:\n      - ALL\n",
    "created": "2021-10-17T04:23:25Z",
    "creator": {
        "id": "ff471ff8-f131-4cf5-9712-c79cce6301a1"
    },
    "json": {
        "Check": {
            "all": [
                {
                    "name": "--TPT",
                    "operator": "non_empty"
                },
                {
                    "name": "--TPTNUM",
                    "operator": "non_empty"
                },
                {
                    "name": "--ELTM",
                    "operator": "non_empty"
                },
                {
                    "name": "--ELTM",
                    "operator": "is_unique_set",
                    "value": [
                        "DOMAIN",
                        "VISITNUM",
                        "--TPTREF",
                        "--TPTNUM"
                    ]
                }
            ]
        },
        "Core": {
            "Id": "CORE-000142",
            "Version": "1",
            "Status": "Published"
        },
        "Description": "Trigger error where --TPT ^= null and --TPTNUM ^= null and --ELTM ^= null and --ELTM does not have the same value across records with the same values of DOMAIN, VISITNUM, --TPTREF, and --TPTNUM, when",
        "Outcome": {
            "Message": "--ELTM is not the same value across records with the same values of DOMAIN, VISITNUM, --TPTREF, and --TPTNUM",
            "Output_Variables": [
                "--TPT",
                "--TPTNUM",
                "--ELTM"
            ]
        },
        "Rule_Type": "Record Data",
        "Sensitivity": "Domain",
        "Authorities": [
            {
                "Organization": "CDISC",
                "Standards": [
                    {
                        "Name": "SDTMIG",
                        "Version": "3.4",
                        "References": [
                            {
                                "Origin": "SDTM and SDTMIG Conformance Rules",
                                "Rule_Identifier": {
                                    "Id": "CG0241",
                                    "Version": "1"
                                },
                                "Version": "2.0",
                                "Citations": [
                                    {
                                        "Cited_Guidance": "Within the context that defines uniqueness for a time point, there is likely to be a one-to-one relationship between most values of --TPT and --ELTM. However, since --ELTM can only be populated with ISO 8601 periods of time (as described in Section 4.4.3, Intervals of Time and Use of Duration for --DUR Variables), --ELTM may not be populated for all time points. For example, --ELTM is likely to be null for time points described by text such as 'pre-dose' or 'before breakfast.' When --ELTM is populated, if two subjects have records with the same values of DOMAIN, VISITNUM, --TPTREF, and --TPTNUM, then these records may not have different values in --ELTM.",
                                        "Document": "IG v3.4",
                                        "Section": "4.4.10"
                                    }
                                ]
                            }
                        ]
                    }
                ]
            }
        ],
        "Scope": {
            "Classes": {
                "Include": [
                    "ALL"
                ]
            },
            "Domains": {
                "Include": [
                    "ALL"
                ]
            }
        }
    }
}