{
    "id": "6d205a21-58b1-498d-bb7b-daec58812bd4",
    "changed": "2022-02-15T21:28:52Z",
    "content": "Check:\n  all:\n    - name: TSVCDREF\n      operator: equal_to\n      value: CDISC\n    - name: TSVCDVER\n      operator: is_contained_by\n      value:\nCore:\n  Id: CDISC.SDTMIG.CG0289\n  Version: '1'\n  Status: Draft\nDescription: Trigger error when TSVCDREF = 'CDISC' and TSVCDVER is not a valid published\n  version (date)\nOutcome:\n  Message: TSVCDVER is not a valid published version (date)\nRule Type: Record Data\nSensitivity: Record\nAuthorities:\n  - Organization: CDISC\n    Standards:\n      - Name: SDTMIG\n        Version: '3.4'\n        References:\n          - Origin: SDTM and SDTMIG Conformance Rules\n            Rule Identifier:\n              Id: CG0289\n              Version: '1'\n            Version: '2.0'\n            Citations:\n              - Cited Guidance: The version number of the Reference Terminology, if\n                  applicable.\n                Document: IG v3.4\n                Section: 7.4.2\nScope:\n  Classes:\n    Include:\n      - TRIAL DESIGN\n  Domains:\n    Include:\n      - TS\n",
    "created": "2021-10-17T05:36:09Z",
    "creator": {
        "id": "ff471ff8-f131-4cf5-9712-c79cce6301a1"
    },
    "json": {
        "Check": {
            "all": [
                {
                    "name": "TSVCDREF",
                    "operator": "equal_to",
                    "value": "CDISC"
                },
                {
                    "name": "TSVCDVER",
                    "operator": "is_contained_by",
                    "value": null
                }
            ]
        },
        "Core": {
            "Id": "CDISC.SDTMIG.CG0289",
            "Version": "1",
            "Status": "Draft"
        },
        "Description": "Trigger error when TSVCDREF = 'CDISC' and TSVCDVER is not a valid published version (date)",
        "Outcome": {
            "Message": "TSVCDVER is not a valid published version (date)"
        },
        "Rule_Type": "Record Data",
        "Sensitivity": "Record",
        "Authorities": [
            {
                "Organization": "CDISC",
                "Standards": [
                    {
                        "Name": "SDTMIG",
                        "Version": "3.4",
                        "References": [
                            {
                                "Origin": "SDTM and SDTMIG Conformance Rules",
                                "Rule_Identifier": {
                                    "Id": "CG0289",
                                    "Version": "1"
                                },
                                "Version": "2.0",
                                "Citations": [
                                    {
                                        "Cited_Guidance": "The version number of the Reference Terminology, if applicable.",
                                        "Document": "IG v3.4",
                                        "Section": "7.4.2"
                                    }
                                ]
                            }
                        ]
                    }
                ]
            }
        ],
        "Scope": {
            "Classes": {
                "Include": [
                    "TRIAL DESIGN"
                ]
            },
            "Domains": {
                "Include": [
                    "TS"
                ]
            }
        }
    }
}