{
    "id": "e5656797-19d4-475b-b5c9-1a23323692fc",
    "changed": "2022-02-15T21:31:53Z",
    "content": "Check:\n  all:\n    - name:\n      operator:\n    - name: ARM\n      operator: non_empty\nCore:\n  Id: CDISC.SDTMIG.CG0296\n  Version: '1'\n  Status: Draft\nDescription: Trigger error when ARM is populated and the timing and number of Visits\n  for a trial does not depend on which ARM a subject is in\nOutcome:\n  Message:\nRule Type: Record Data\nSensitivity: Dataset\nAuthorities:\n  - Organization: CDISC\n    Standards:\n      - Name: SDTMIG\n        Version: '3.4'\n        References:\n          - Origin: SDTM and SDTMIG Conformance Rules\n            Rule Identifier:\n              Id: CG0296\n              Version: '1'\n            Version: '2.0'\n            Citations:\n              - Cited Guidance: If the timing of Visits for a trial does not depend\n                  on which Arm a subject is in, then Arm should be left blank.\n                Document: IG v3.4\n                Item: Specification\n                Section: 7.3.1\nScope:\n  Classes:\n    Include:\n      - TRIAL DESIGN\n  Domains:\n    Include:\n      - TV\n",
    "created": "2021-10-30T10:48:41Z",
    "creator": {
        "id": "ff471ff8-f131-4cf5-9712-c79cce6301a1"
    },
    "json": {
        "Check": {
            "all": [
                {
                    "name": null,
                    "operator": null
                },
                {
                    "name": "ARM",
                    "operator": "non_empty"
                }
            ]
        },
        "Core": {
            "Id": "CDISC.SDTMIG.CG0296",
            "Version": "1",
            "Status": "Draft"
        },
        "Description": "Trigger error when ARM is populated and the timing and number of Visits for a trial does not depend on which ARM a subject is in",
        "Outcome": {
            "Message": null
        },
        "Rule_Type": "Record Data",
        "Sensitivity": "Dataset",
        "Authorities": [
            {
                "Organization": "CDISC",
                "Standards": [
                    {
                        "Name": "SDTMIG",
                        "Version": "3.4",
                        "References": [
                            {
                                "Origin": "SDTM and SDTMIG Conformance Rules",
                                "Rule_Identifier": {
                                    "Id": "CG0296",
                                    "Version": "1"
                                },
                                "Version": "2.0",
                                "Citations": [
                                    {
                                        "Cited_Guidance": "If the timing of Visits for a trial does not depend on which Arm a subject is in, then Arm should be left blank.",
                                        "Document": "IG v3.4",
                                        "Item": "Specification",
                                        "Section": "7.3.1"
                                    }
                                ]
                            }
                        ]
                    }
                ]
            }
        ],
        "Scope": {
            "Classes": {
                "Include": [
                    "TRIAL DESIGN"
                ]
            },
            "Domains": {
                "Include": [
                    "TV"
                ]
            }
        }
    }
}