{
    "id": "7088ccfe-0d4c-4419-baa6-7f5d35ae48ea",
    "changed": "2022-05-25T18:22:14Z",
    "content": "Check:\n  all:\n    - name: TIVERS\n      operator: not_exists\n    - name: IETESTCD\n      operator: is_not_unique_set\n      value: DOMAIN\nCore:\n  Id: CORE-000146\n  Version: '1'\n  Status: Published\nDescription: Trigger error when IETESTCD is not unique within dataset\nOutcome:\n  Message: IETESTCD is not unique\n  Output Variables:\n    - IETESTCD\nRule Type: Record Data\nSensitivity: Record\nAuthorities:\n  - Organization: CDISC\n    Standards:\n      - Name: SDTMIG\n        Version: '3.4'\n        References:\n          - Origin: SDTM and SDTMIG Conformance Rules\n            Rule Identifier:\n              Id: CG0256\n              Version: '1'\n            Version: '2.0'\n            Citations:\n              - Cited Guidance: The number of this version of the Inclusion/Exclusion\n                  criteria. May be omitted if there is only one version.\n                Document: IG v3.4\n                Item: Specification\n                Section: 7.4.1\n              - Cited Guidance: Individual criteria do not have versions. If a criterion\n                  changes, it should be treated as a new criterion, with a new value\n                  for IETESTCD.\n                Document: IG v3.4\n                Item: Assumption 3\n                Section: 7.4.1\nScope:\n  Classes:\n    Include:\n      - TRIAL DESIGN\n  Domains:\n    Include:\n      - TI\n",
    "created": "2021-10-17T04:54:12Z",
    "creator": {
        "id": "ff471ff8-f131-4cf5-9712-c79cce6301a1"
    },
    "json": {
        "Check": {
            "all": [
                {
                    "name": "TIVERS",
                    "operator": "not_exists"
                },
                {
                    "name": "IETESTCD",
                    "operator": "is_not_unique_set",
                    "value": "DOMAIN"
                }
            ]
        },
        "Core": {
            "Id": "CORE-000146",
            "Version": "1",
            "Status": "Published"
        },
        "Description": "Trigger error when IETESTCD is not unique within dataset",
        "Outcome": {
            "Message": "IETESTCD is not unique",
            "Output_Variables": [
                "IETESTCD"
            ]
        },
        "Rule_Type": "Record Data",
        "Sensitivity": "Record",
        "Authorities": [
            {
                "Organization": "CDISC",
                "Standards": [
                    {
                        "Name": "SDTMIG",
                        "Version": "3.4",
                        "References": [
                            {
                                "Origin": "SDTM and SDTMIG Conformance Rules",
                                "Rule_Identifier": {
                                    "Id": "CG0256",
                                    "Version": "1"
                                },
                                "Version": "2.0",
                                "Citations": [
                                    {
                                        "Cited_Guidance": "The number of this version of the Inclusion/Exclusion criteria. May be omitted if there is only one version.",
                                        "Document": "IG v3.4",
                                        "Item": "Specification",
                                        "Section": "7.4.1"
                                    },
                                    {
                                        "Cited_Guidance": "Individual criteria do not have versions. If a criterion changes, it should be treated as a new criterion, with a new value for IETESTCD.",
                                        "Document": "IG v3.4",
                                        "Item": "Assumption 3",
                                        "Section": "7.4.1"
                                    }
                                ]
                            }
                        ]
                    }
                ]
            }
        ],
        "Scope": {
            "Classes": {
                "Include": [
                    "TRIAL DESIGN"
                ]
            },
            "Domains": {
                "Include": [
                    "TI"
                ]
            }
        }
    }
}