{
    "id": "8773cfc2-1134-46fb-9c3a-797269ea640e",
    "changed": "2023-02-28T14:15:11.101Z",
    "content": "Check:\n  all:\n    - name: EPOCH\n      operator: exists\n    - name: SESTDTC\n      operator: date_less_than_or_equal_to\n      value: SVSTDTC\n    - name: SVSTDTC\n      operator: date_less_than_or_equal_to\n      value: SEENDTC\n    - name: EPOCH\n      operator: not_equal_to\n      value: SE.EPOCH\nMatch Datasets:\n  - Name: SE\n    Keys:\n      - USUBJID\n\nCore:\n  Id: CORE-000097\n  Version: '1'\n  Status: Published\nDescription: Raise an error when variable EPOCH values don't match between\n  Subject Visits (SV) and Subject Elements (SE) datasets.\n\nOutcome:\n  Message: EPOCH values don't match between Subject Visits (SV) and Subject\n    Elements (SE) datasets.\nRule Type: Record Data\nSensitivity: Record\nAuthorities:\n  - Organization: CDISC\n    Standards:\n      - Name: SDTMIG\n        Version: '3.4'\n        References:\n          - Origin: SDTM and SDTMIG Conformance Rules\n            Rule Identifier:\n              Id: CG0218\n              Version: '1'\n            Version: '2.0'\n            Citations:\n              - Cited Guidance: If TAETORD and/or EPOCH are added, then the values must be those\n                  at the start of the visit.\n                Document: IG v3.4\n                Item: Assumption 11\n                Section: '5.5'\nScope:\n  Classes:\n    Include:\n      - SPECIAL PURPOSE\n  Domains:\n    Include:\n      - SV\nExecutability: Fully Executable\n",
    "created": "2021-10-06T20:10:58Z",
    "creator": {
        "id": "76170e05-ed88-410d-8cad-ecd247a9050b"
    },
    "json": {
        "Check": {
            "all": [
                {
                    "name": "EPOCH",
                    "operator": "exists"
                },
                {
                    "name": "SESTDTC",
                    "operator": "date_less_than_or_equal_to",
                    "value": "SVSTDTC"
                },
                {
                    "name": "SVSTDTC",
                    "operator": "date_less_than_or_equal_to",
                    "value": "SEENDTC"
                },
                {
                    "name": "EPOCH",
                    "operator": "not_equal_to",
                    "value": "SE.EPOCH"
                }
            ]
        },
        "Core": {
            "Id": "CORE-000097",
            "Version": "1",
            "Status": "Published"
        },
        "Description": "Raise an error when variable EPOCH values don't match between Subject Visits (SV) and Subject Elements (SE) datasets.",
        "Outcome": {
            "Message": "EPOCH values don't match between Subject Visits (SV) and Subject Elements (SE) datasets."
        },
        "Sensitivity": "Record",
        "Authorities": [
            {
                "Organization": "CDISC",
                "Standards": [
                    {
                        "Name": "SDTMIG",
                        "Version": "3.4",
                        "References": [
                            {
                                "Origin": "SDTM and SDTMIG Conformance Rules",
                                "Version": "2.0",
                                "Citations": [
                                    {
                                        "Document": "IG v3.4",
                                        "Item": "Assumption 11",
                                        "Section": "5.5",
                                        "Cited_Guidance": "If TAETORD and/or EPOCH are added, then the values must be those at the start of the visit."
                                    }
                                ],
                                "Rule_Identifier": {
                                    "Id": "CG0218",
                                    "Version": "1"
                                }
                            }
                        ]
                    }
                ]
            }
        ],
        "Scope": {
            "Classes": {
                "Include": [
                    "SPECIAL PURPOSE"
                ]
            },
            "Domains": {
                "Include": [
                    "SV"
                ]
            }
        },
        "Executability": "Fully Executable",
        "Match_Datasets": [
            {
                "Name": "SE",
                "Keys": [
                    "USUBJID"
                ]
            }
        ],
        "Rule_Type": "Record Data"
    }
}