{
    "id": "36671f99-0761-48ce-93fe-32c7a0c4c399",
    "changed": "2022-02-15T21:27:22Z",
    "content": "Check:\n  all:\n    - name:\n      operator:\n    - name: TIVERS\n      operator: exists\nCore:\n  Id: CDISC.SDTMIG.CG0254\n  Version: '1'\n  Status: Draft\nDescription: Trigger error when TIVERS is not present in the data and there is more\n  than one version of the IE criteria\nOutcome:\n  Message: TIVERS is not present in the data when there is more than one version of\n    the IE criteria\nRule Type: Record Data\nSensitivity: Study\nAuthorities:\n  - Organization: CDISC\n    Standards:\n      - Name: SDTMIG\n        Version: '3.4'\n        References:\n          - Origin: SDTM and SDTMIG Conformance Rules\n            Rule Identifier:\n              Id: CG0254\n              Version: '1'\n            Version: '2.0'\n            Citations:\n              - Cited Guidance: The number of this version of the Inclusion/Exclusion\n                  criteria. May be omitted if there is only one version.\n                Document: IG v3.4\n                Item: Specification\n                Section: 7.4.1\nScope:\n  Classes:\n    Include:\n      - TRIAL DESIGN\n  Domains:\n    Include:\n      - TI\n",
    "created": "2021-10-30T10:42:13Z",
    "creator": {
        "id": "ff471ff8-f131-4cf5-9712-c79cce6301a1"
    },
    "json": {
        "Check": {
            "all": [
                {
                    "name": null,
                    "operator": null
                },
                {
                    "name": "TIVERS",
                    "operator": "exists"
                }
            ]
        },
        "Core": {
            "Id": "CDISC.SDTMIG.CG0254",
            "Version": "1",
            "Status": "Draft"
        },
        "Description": "Trigger error when TIVERS is not present in the data and there is more than one version of the IE criteria",
        "Outcome": {
            "Message": "TIVERS is not present in the data when there is more than one version of the IE criteria"
        },
        "Rule_Type": "Record Data",
        "Sensitivity": "Study",
        "Authorities": [
            {
                "Organization": "CDISC",
                "Standards": [
                    {
                        "Name": "SDTMIG",
                        "Version": "3.4",
                        "References": [
                            {
                                "Origin": "SDTM and SDTMIG Conformance Rules",
                                "Rule_Identifier": {
                                    "Id": "CG0254",
                                    "Version": "1"
                                },
                                "Version": "2.0",
                                "Citations": [
                                    {
                                        "Cited_Guidance": "The number of this version of the Inclusion/Exclusion criteria. May be omitted if there is only one version.",
                                        "Document": "IG v3.4",
                                        "Item": "Specification",
                                        "Section": "7.4.1"
                                    }
                                ]
                            }
                        ]
                    }
                ]
            }
        ],
        "Scope": {
            "Classes": {
                "Include": [
                    "TRIAL DESIGN"
                ]
            },
            "Domains": {
                "Include": [
                    "TI"
                ]
            }
        }
    }
}