{
    "id": "908f8089-6d1b-4962-a1b5-cfa072cbf91c",
    "changed": "2022-02-15T21:29:54Z",
    "content": "Check:\n  all:\n    - name:\n      operator:\n    - name: TABRANCH\n      operator: empty\nCore:\n  Id: CDISC.SDTMIG.CG0251\n  Version: '1'\n  Status: Draft\nDescription: Trigger error when trial design branches and TABRANCH is null\nOutcome:\n  Message: TABRANCH is null when trial design branches\nRule Type: Record Data\nSensitivity: Record\nAuthorities:\n  - Organization: CDISC\n    Standards:\n      - Name: SDTMIG\n        Version: '3.4'\n        References:\n          - Origin: SDTM and SDTMIG Conformance Rules\n            Rule Identifier:\n              Id: CG0251\n              Version: '1'\n            Version: '2.0'\n            Citations:\n              - Cited Guidance: TABRANCH describes the outcome of a branch decision\n                  point in the trial design for subjects in the Arm.\n                Document: IG v3.4\n                Item: Assumption 3\n                Section: 7.2.1\nScope:\n  Classes:\n    Include:\n      - TRIAL DESIGN\n  Domains:\n    Include:\n      - TA\n",
    "created": "2021-10-30T10:36:50Z",
    "creator": {
        "id": "ff471ff8-f131-4cf5-9712-c79cce6301a1"
    },
    "json": {
        "Check": {
            "all": [
                {
                    "name": null,
                    "operator": null
                },
                {
                    "name": "TABRANCH",
                    "operator": "empty"
                }
            ]
        },
        "Core": {
            "Id": "CDISC.SDTMIG.CG0251",
            "Version": "1",
            "Status": "Draft"
        },
        "Description": "Trigger error when trial design branches and TABRANCH is null",
        "Outcome": {
            "Message": "TABRANCH is null when trial design branches"
        },
        "Rule_Type": "Record Data",
        "Sensitivity": "Record",
        "Authorities": [
            {
                "Organization": "CDISC",
                "Standards": [
                    {
                        "Name": "SDTMIG",
                        "Version": "3.4",
                        "References": [
                            {
                                "Origin": "SDTM and SDTMIG Conformance Rules",
                                "Rule_Identifier": {
                                    "Id": "CG0251",
                                    "Version": "1"
                                },
                                "Version": "2.0",
                                "Citations": [
                                    {
                                        "Cited_Guidance": "TABRANCH describes the outcome of a branch decision point in the trial design for subjects in the Arm.",
                                        "Document": "IG v3.4",
                                        "Item": "Assumption 3",
                                        "Section": "7.2.1"
                                    }
                                ]
                            }
                        ]
                    }
                ]
            }
        ],
        "Scope": {
            "Classes": {
                "Include": [
                    "TRIAL DESIGN"
                ]
            },
            "Domains": {
                "Include": [
                    "TA"
                ]
            }
        }
    }
}