{
    "id": "f9b2e400-9c3f-4d28-9c37-78f23ec3f738",
    "changed": "2022-04-22T15:39:12Z",
    "content": "Check:\n  all:\n    - name: VISITNUM\n      operator: is_not_contained_by\n      value: $tv_visitnum\n    - name: VISITDY\n      operator: non_empty\nCore:\n  Id: CORE-000140\n  Version: '1'\n  Status: Published\nDescription: Trigger error if VISITYDY is populated when VISITNUM is not in TV.\nOperations:\n  - domain: TV\n    id: $tv_visitnum\n    name: VISITNUM\n    operator: distinct\nOutcome:\n  Message: VISITDY is not null when VISITNUM is not in TV.VISITNUM\n  Output Variables:\n    - VISITNUM\n    - VISITDY\nRule Type: Record Data\nSensitivity: Record\nAuthorities:\n  - Organization: CDISC\n    Standards:\n      - Name: SDTMIG\n        Version: '3.4'\n        References:\n          - Origin: SDTM and SDTMIG Conformance Rules\n            Rule Identifier:\n              Id: CG0225\n              Version: '1'\n            Version: '2.0'\n            Citations:\n              - Cited Guidance: VISITDY must not be populated for unplanned visits,\n                  since VISITDY is, by definition, the planned study day of visit,\n                  and since the actual study day of an unplanned visit belongs in\n                  a --DY variable.\n                Document: IG v3.4\n                Section: 4.4.5\nScope:\n  Classes:\n    Include:\n      - ALL\n  Domains:\n    Include:\n      - ALL\n",
    "created": "2021-10-16T11:19:49Z",
    "creator": {
        "id": "ff471ff8-f131-4cf5-9712-c79cce6301a1"
    },
    "json": {
        "Check": {
            "all": [
                {
                    "name": "VISITNUM",
                    "operator": "is_not_contained_by",
                    "value": "$tv_visitnum"
                },
                {
                    "name": "VISITDY",
                    "operator": "non_empty"
                }
            ]
        },
        "Core": {
            "Id": "CORE-000140",
            "Version": "1",
            "Status": "Published"
        },
        "Description": "Trigger error if VISITYDY is populated when VISITNUM is not in TV.",
        "Operations": [
            {
                "domain": "TV",
                "id": "$tv_visitnum",
                "name": "VISITNUM",
                "operator": "distinct"
            }
        ],
        "Outcome": {
            "Message": "VISITDY is not null when VISITNUM is not in TV.VISITNUM",
            "Output_Variables": [
                "VISITNUM",
                "VISITDY"
            ]
        },
        "Rule_Type": "Record Data",
        "Sensitivity": "Record",
        "Authorities": [
            {
                "Organization": "CDISC",
                "Standards": [
                    {
                        "Name": "SDTMIG",
                        "Version": "3.4",
                        "References": [
                            {
                                "Origin": "SDTM and SDTMIG Conformance Rules",
                                "Rule_Identifier": {
                                    "Id": "CG0225",
                                    "Version": "1"
                                },
                                "Version": "2.0",
                                "Citations": [
                                    {
                                        "Cited_Guidance": "VISITDY must not be populated for unplanned visits, since VISITDY is, by definition, the planned study day of visit, and since the actual study day of an unplanned visit belongs in a --DY variable.",
                                        "Document": "IG v3.4",
                                        "Section": "4.4.5"
                                    }
                                ]
                            }
                        ]
                    }
                ]
            }
        ],
        "Scope": {
            "Classes": {
                "Include": [
                    "ALL"
                ]
            },
            "Domains": {
                "Include": [
                    "ALL"
                ]
            }
        }
    }
}