{
    "id": "88a5f2ed-005c-4c3e-b8ea-5b3b3e2968c4",
    "changed": "2022-02-15T21:29:37Z",
    "content": "Check:\n  all:\n    - name:\n      operator:\nCore:\n  Id: CDISC.SDTMIG.CG0298\n  Version: '1'\n  Status: Draft\nDescription: Trigger error when a visit is not described in the protocol\nOutcome:\n  Message: VISIT is not described in the protocol\nRule Type: Record Data\nSensitivity: Record\nAuthorities:\n  - Organization: CDISC\n    Standards:\n      - Name: SDTMIG\n        Version: '3.4'\n        References:\n          - Origin: SDTM and SDTMIG Conformance Rules\n            Rule Identifier:\n              Id: CG0298\n              Version: '1'\n            Version: '2.0'\n            Citations:\n              - Cited Guidance: Protocol-defined description of clinical encounter.\n                Document: IG v3.4\n                Item: Specification\n                Section: 7.3.1\nScope:\n  Classes:\n    Include:\n      - TRIAL DESIGN\n  Domains:\n    Include:\n      - TV\n",
    "created": "2021-10-30T10:50:07Z",
    "creator": {
        "id": "ff471ff8-f131-4cf5-9712-c79cce6301a1"
    },
    "json": {
        "Check": {
            "all": [
                {
                    "name": null,
                    "operator": null
                }
            ]
        },
        "Core": {
            "Id": "CDISC.SDTMIG.CG0298",
            "Version": "1",
            "Status": "Draft"
        },
        "Description": "Trigger error when a visit is not described in the protocol",
        "Outcome": {
            "Message": "VISIT is not described in the protocol"
        },
        "Rule_Type": "Record Data",
        "Sensitivity": "Record",
        "Authorities": [
            {
                "Organization": "CDISC",
                "Standards": [
                    {
                        "Name": "SDTMIG",
                        "Version": "3.4",
                        "References": [
                            {
                                "Origin": "SDTM and SDTMIG Conformance Rules",
                                "Rule_Identifier": {
                                    "Id": "CG0298",
                                    "Version": "1"
                                },
                                "Version": "2.0",
                                "Citations": [
                                    {
                                        "Cited_Guidance": "Protocol-defined description of clinical encounter.",
                                        "Document": "IG v3.4",
                                        "Item": "Specification",
                                        "Section": "7.3.1"
                                    }
                                ]
                            }
                        ]
                    }
                ]
            }
        ],
        "Scope": {
            "Classes": {
                "Include": [
                    "TRIAL DESIGN"
                ]
            },
            "Domains": {
                "Include": [
                    "TV"
                ]
            }
        }
    }
}