{
    "id": "20fc5073-8c23-42aa-873f-1b22e2730378",
    "changed": "2022-02-15T21:26:58Z",
    "content": "Check:\n  all:\n    - name:\n      operator:\nCore:\n  Id: CDISC.SDTMIG.CG0250\n  Version: '1'\n  Status: Draft\nDescription: Trigger error when at least one EPOCH is associated with more than one\n  conceptual trial period\nOutcome:\n  Message: At least one EPOCH is associated with more than one conceptual trial period\nRule Type: Record Data\nSensitivity: Study\nAuthorities:\n  - Organization: CDISC\n    Standards:\n      - Name: SDTMIG\n        Version: '3.4'\n        References:\n          - Origin: SDTM and SDTMIG Conformance Rules\n            Rule Identifier:\n              Id: CG0250\n              Version: '1'\n            Version: '2.0'\n            Citations:\n              - Cited Guidance: 'EPOCH may be used as a timing variable in other datasets,\n                  such as EX and DS, and values of EPOCH must be different for different\n                  epochs. '\n                Document: IG v3.4\n                Item: Assumption 12\n                Section: 7.2.1\nScope:\n  Classes:\n    Include:\n      - TRIAL DESIGN\n  Domains:\n    Include:\n      - TA\n",
    "created": "2021-10-30T10:34:11Z",
    "creator": {
        "id": "ff471ff8-f131-4cf5-9712-c79cce6301a1"
    },
    "json": {
        "Check": {
            "all": [
                {
                    "name": null,
                    "operator": null
                }
            ]
        },
        "Core": {
            "Id": "CDISC.SDTMIG.CG0250",
            "Version": "1",
            "Status": "Draft"
        },
        "Description": "Trigger error when at least one EPOCH is associated with more than one conceptual trial period",
        "Outcome": {
            "Message": "At least one EPOCH is associated with more than one conceptual trial period"
        },
        "Rule_Type": "Record Data",
        "Sensitivity": "Study",
        "Authorities": [
            {
                "Organization": "CDISC",
                "Standards": [
                    {
                        "Name": "SDTMIG",
                        "Version": "3.4",
                        "References": [
                            {
                                "Origin": "SDTM and SDTMIG Conformance Rules",
                                "Rule_Identifier": {
                                    "Id": "CG0250",
                                    "Version": "1"
                                },
                                "Version": "2.0",
                                "Citations": [
                                    {
                                        "Cited_Guidance": "EPOCH may be used as a timing variable in other datasets, such as EX and DS, and values of EPOCH must be different for different epochs. ",
                                        "Document": "IG v3.4",
                                        "Item": "Assumption 12",
                                        "Section": "7.2.1"
                                    }
                                ]
                            }
                        ]
                    }
                ]
            }
        ],
        "Scope": {
            "Classes": {
                "Include": [
                    "TRIAL DESIGN"
                ]
            },
            "Domains": {
                "Include": [
                    "TA"
                ]
            }
        }
    }
}