{
    "id": "09604372-4390-4da3-84eb-b157ba1b279b",
    "changed": "2022-06-15T21:22:06Z",
    "content": "Check:\n  all:\n    - name: ARM\n      operator: non_empty\n    - name: ARM\n      operator: is_not_contained_by\n      value: $ta_arm\nCore:\n  Id: CORE-000156\n  Version: '1'\n  Status: Published\nDescription: Trigger error when ARM is populated and ARM is not in TA.ARM\nOperations:\n  - operator: distinct\n    domain: TA\n    name: ARM\n    id: $ta_arm\nOutcome:\n  Message: ARM is not in TA.ARM\nRule Type: Record Data\nSensitivity: Record\nAuthorities:\n  - Organization: CDISC\n    Standards:\n      - Name: SDTMIG\n        Version: '3.4'\n        References:\n          - Origin: SDTM and SDTMIG Conformance Rules\n            Rule Identifier:\n              Id: CG0294\n              Version: '1'\n            Version: '2.0'\n            Citations:\n              - Cited Guidance: 1. Name given to an Arm or Treatment Group. 2. If\n                  the timing of visits for a trial does not depend on which Arm a\n                  subject is in, then Arm should be left blank.\n                Document: IG v3.4\n                Item: Specification\n                Section: 7.3.1\nScope:\n  Classes:\n    Include:\n      - TRIAL DESIGN\n  Domains:\n    Include:\n      - TV\n",
    "created": "2021-10-17T05:44:37Z",
    "creator": {
        "id": "ff471ff8-f131-4cf5-9712-c79cce6301a1"
    },
    "json": {
        "Check": {
            "all": [
                {
                    "name": "ARM",
                    "operator": "non_empty"
                },
                {
                    "name": "ARM",
                    "operator": "is_not_contained_by",
                    "value": "$ta_arm"
                }
            ]
        },
        "Core": {
            "Id": "CORE-000156",
            "Version": "1",
            "Status": "Published"
        },
        "Description": "Trigger error when ARM is populated and ARM is not in TA.ARM",
        "Operations": [
            {
                "operator": "distinct",
                "domain": "TA",
                "name": "ARM",
                "id": "$ta_arm"
            }
        ],
        "Outcome": {
            "Message": "ARM is not in TA.ARM"
        },
        "Rule_Type": "Record Data",
        "Sensitivity": "Record",
        "Authorities": [
            {
                "Organization": "CDISC",
                "Standards": [
                    {
                        "Name": "SDTMIG",
                        "Version": "3.4",
                        "References": [
                            {
                                "Origin": "SDTM and SDTMIG Conformance Rules",
                                "Rule_Identifier": {
                                    "Id": "CG0294",
                                    "Version": "1"
                                },
                                "Version": "2.0",
                                "Citations": [
                                    {
                                        "Cited_Guidance": "1. Name given to an Arm or Treatment Group. 2. If the timing of visits for a trial does not depend on which Arm a subject is in, then Arm should be left blank.",
                                        "Document": "IG v3.4",
                                        "Item": "Specification",
                                        "Section": "7.3.1"
                                    }
                                ]
                            }
                        ]
                    }
                ]
            }
        ],
        "Scope": {
            "Classes": {
                "Include": [
                    "TRIAL DESIGN"
                ]
            },
            "Domains": {
                "Include": [
                    "TV"
                ]
            }
        }
    }
}