{
    "id": "5c68254d-aa3a-425d-9e16-be6c379b86a4",
    "changed": "2022-02-15T21:28:30Z",
    "content": "Check:\n  all:\n    - name: TSVCDREF\n      operator: is_contained_by\n      value:\n    - name: TSVCDVER\n      operator: is_empty\nCore:\n  Id: CDISC.SDTMIG.CG0267\n  Version: '1'\n  Status: Draft\nDescription: Trigger error when Reference Terminology is versioned and TSVCDVER is\n  null\nOutcome:\n  Message: TSVCDVER is null when Reference Terminology is versioned\nRule Type: Record Data\nSensitivity: Record\nAuthorities:\n  - Organization: CDISC\n    Standards:\n      - Name: SDTMIG\n        Version: '3.4'\n        References:\n          - Origin: SDTM and SDTMIG Conformance Rules\n            Rule Identifier:\n              Id: CG0267\n              Version: '1'\n            Version: '2.0'\n            Citations:\n              - Cited Guidance: The version number of the Reference Terminology, if\n                  applicable.\n                Document: IG v3.4\n                Item: Specification\n                Section: 7.4.2\nScope:\n  Classes:\n    Include:\n      - TRIAL DESIGN\n  Domains:\n    Include:\n      - TS\n",
    "created": "2021-10-30T10:45:08Z",
    "creator": {
        "id": "ff471ff8-f131-4cf5-9712-c79cce6301a1"
    },
    "json": {
        "Check": {
            "all": [
                {
                    "name": "TSVCDREF",
                    "operator": "is_contained_by",
                    "value": null
                },
                {
                    "name": "TSVCDVER",
                    "operator": "is_empty"
                }
            ]
        },
        "Core": {
            "Id": "CDISC.SDTMIG.CG0267",
            "Version": "1",
            "Status": "Draft"
        },
        "Description": "Trigger error when Reference Terminology is versioned and TSVCDVER is null",
        "Outcome": {
            "Message": "TSVCDVER is null when Reference Terminology is versioned"
        },
        "Rule_Type": "Record Data",
        "Sensitivity": "Record",
        "Authorities": [
            {
                "Organization": "CDISC",
                "Standards": [
                    {
                        "Name": "SDTMIG",
                        "Version": "3.4",
                        "References": [
                            {
                                "Origin": "SDTM and SDTMIG Conformance Rules",
                                "Rule_Identifier": {
                                    "Id": "CG0267",
                                    "Version": "1"
                                },
                                "Version": "2.0",
                                "Citations": [
                                    {
                                        "Cited_Guidance": "The version number of the Reference Terminology, if applicable.",
                                        "Document": "IG v3.4",
                                        "Item": "Specification",
                                        "Section": "7.4.2"
                                    }
                                ]
                            }
                        ]
                    }
                ]
            }
        ],
        "Scope": {
            "Classes": {
                "Include": [
                    "TRIAL DESIGN"
                ]
            },
            "Domains": {
                "Include": [
                    "TS"
                ]
            }
        }
    }
}