{
    "id": "cb636666-8724-4384-a4cd-c581a03b33a8",
    "changed": "2022-05-25T17:55:38Z",
    "content": "Check:\n  all:\n    - name: VISITNUM\n      operator: not_exists\n    - name: --TPTREF\n      operator: not_exists\n    - name: --TPT\n      operator: is_not_unique_relationship\n      value: --TPTNUM\nCore:\n  Id: CORE-000141\n  Version: '1'\n  Status: Published\nDescription: Trigger error when VISITNUM and --TPTREF are not present and --TPT and\n  --TPTNUM does not have a one-to-one relationship\nOutcome:\n  Message: --TPT and --TPTNUM do not have a one-to-one relationship\n  Output Variables:\n    - --TPT\n    - --TPTNUM\nRule Type: Record Data\nSensitivity: Record\nAuthorities:\n  - Organization: CDISC\n    Standards:\n      - Name: SDTMIG\n        Version: '3.4'\n        References:\n          - Origin: SDTM and SDTMIG Conformance Rules\n            Rule Identifier:\n              Id: CG0240\n              Version: '2'\n            Version: '2.0'\n            Citations:\n              - Cited Guidance: Within the context that defines uniqueness for a time\n                  point, which may include domain, visit, and reference time point,\n                  there must be a one-to-relationship between values of --TPT and\n                  --TPTNUM. in other words, if domain, visit, and reference time point\n                  uniquely identify subject data, then if two subjects have records\n                  with the same values of DOMAIN, VISITNUM, --TPTREF, and --TPTNUM,\n                  then these records may not have different time point descriptions\n                  in --TPT.\n                Document: IG v3.4\n                Section: 4.4.10\nScope:\n  Classes:\n    Include:\n      - ALL\n  Domains:\n    Include:\n      - ALL\n",
    "created": "2021-10-17T04:08:50Z",
    "creator": {
        "id": "ff471ff8-f131-4cf5-9712-c79cce6301a1"
    },
    "json": {
        "Check": {
            "all": [
                {
                    "name": "VISITNUM",
                    "operator": "not_exists"
                },
                {
                    "name": "--TPTREF",
                    "operator": "not_exists"
                },
                {
                    "name": "--TPT",
                    "operator": "is_not_unique_relationship",
                    "value": "--TPTNUM"
                }
            ]
        },
        "Core": {
            "Id": "CORE-000141",
            "Version": "1",
            "Status": "Published"
        },
        "Description": "Trigger error when VISITNUM and --TPTREF are not present and --TPT and --TPTNUM does not have a one-to-one relationship",
        "Outcome": {
            "Message": "--TPT and --TPTNUM do not have a one-to-one relationship",
            "Output_Variables": [
                "--TPT",
                "--TPTNUM"
            ]
        },
        "Rule_Type": "Record Data",
        "Sensitivity": "Record",
        "Authorities": [
            {
                "Organization": "CDISC",
                "Standards": [
                    {
                        "Name": "SDTMIG",
                        "Version": "3.4",
                        "References": [
                            {
                                "Origin": "SDTM and SDTMIG Conformance Rules",
                                "Rule_Identifier": {
                                    "Id": "CG0240",
                                    "Version": "2"
                                },
                                "Version": "2.0",
                                "Citations": [
                                    {
                                        "Cited_Guidance": "Within the context that defines uniqueness for a time point, which may include domain, visit, and reference time point, there must be a one-to-relationship between values of --TPT and --TPTNUM. in other words, if domain, visit, and reference time point uniquely identify subject data, then if two subjects have records with the same values of DOMAIN, VISITNUM, --TPTREF, and --TPTNUM, then these records may not have different time point descriptions in --TPT.",
                                        "Document": "IG v3.4",
                                        "Section": "4.4.10"
                                    }
                                ]
                            }
                        ]
                    }
                ]
            }
        ],
        "Scope": {
            "Classes": {
                "Include": [
                    "ALL"
                ]
            },
            "Domains": {
                "Include": [
                    "ALL"
                ]
            }
        }
    }
}