{
    "id": "8fc20b11-3c4f-4a7f-8dfc-23d031edb908",
    "changed": "2022-07-04T00:23:02Z",
    "content": "Check:\n  all:\n    - operator: additional_columns_empty\n      target: --VAL\nCore:\n  Id: CDISC.SDTMIG.CG0262\n  Version: '1'\n  Status: Draft\nDescription: Trigger error when TSVAL(n+1) ^= null and TSVALn = null\nOutcome:\n  Message: TSVALn is null when TSVAL(n+1) is populated.\nRule Type: Record Data\nSensitivity: Record\nAuthorities:\n  - Organization: CDISC\n    Standards:\n      - Name: SDTMIG\n        Version: '3.4'\n        References:\n          - Origin: SDTM and SDTMIG Conformance Rules\n            Rule Identifier:\n              Id: CG0262\n              Version: '1'\n            Version: '2.0'\n            Citations:\n              - Cited Guidance: Text over 200 characters can be added to additional\n                  columns TSVAL1-TSVALn.\n                Document: IG v3.4\n                Item: Specification\n                Section: 7.4.2\nScope:\n  Classes:\n    Include:\n      - TRIAL DESIGN\n  Domains:\n    Include:\n      - TS\n",
    "created": "2022-05-10T14:36:43Z",
    "creator": {
        "id": "ff471ff8-f131-4cf5-9712-c79cce6301a1"
    },
    "json": {
        "Check": {
            "all": [
                {
                    "operator": "additional_columns_empty",
                    "target": "--VAL"
                }
            ]
        },
        "Core": {
            "Id": "CDISC.SDTMIG.CG0262",
            "Version": "1",
            "Status": "Draft"
        },
        "Description": "Trigger error when TSVAL(n+1) ^= null and TSVALn = null",
        "Outcome": {
            "Message": "TSVALn is null when TSVAL(n+1) is populated."
        },
        "Rule_Type": "Record Data",
        "Sensitivity": "Record",
        "Authorities": [
            {
                "Organization": "CDISC",
                "Standards": [
                    {
                        "Name": "SDTMIG",
                        "Version": "3.4",
                        "References": [
                            {
                                "Origin": "SDTM and SDTMIG Conformance Rules",
                                "Rule_Identifier": {
                                    "Id": "CG0262",
                                    "Version": "1"
                                },
                                "Version": "2.0",
                                "Citations": [
                                    {
                                        "Cited_Guidance": "Text over 200 characters can be added to additional columns TSVAL1-TSVALn.",
                                        "Document": "IG v3.4",
                                        "Item": "Specification",
                                        "Section": "7.4.2"
                                    }
                                ]
                            }
                        ]
                    }
                ]
            }
        ],
        "Scope": {
            "Classes": {
                "Include": [
                    "TRIAL DESIGN"
                ]
            },
            "Domains": {
                "Include": [
                    "TS"
                ]
            }
        }
    }
}