{
    "id": "973fe890-9828-44e7-8006-1f959f69d2e6",
    "changed": "2022-04-22T09:36:27Z",
    "content": "Check:\n  all:\n    - name: IDVARVAL\n      operator: empty\n    - name: USUBJID\n      operator: empty\n    - name: IDVAR\n      operator: ends_with\n      value: SEQ\nCore:\n  Id: CORE-000136\n  Version: '1'\n  Status: Published\nDescription: Raise an error when IDVARVAL and USUBJID are empty and IDVAR = Sequence\n  Number.\nOutcome:\n  Message: IDVARVAL and USUBJID are not completed, but IDVAR equals Sequence Number.\n  Output Variables:\n    - RDOMAIN\n    - IDVAR\n    - IDVARVAL\n    - RELID\nRule Type: Record Data\nSensitivity: Record\nAuthorities:\n  - Organization: CDISC\n    Standards:\n      - Name: SDTMIG\n        Version: '3.4'\n        References:\n          - Origin: SDTM and SDTMIG Conformance Rules\n            Rule Identifier:\n              Id: CG0201\n              Version: '1'\n            Version: '2.0'\n            Citations:\n              - Cited Guidance: This example shows how to use the RELREC dataset to\n                  represent related information that is submitted as two datasets\n                  that have a one-to-many relationship. in the example below  all\n                  the records in one domain are being related to all of the records\n                  in the other, so both  USUBJID and IDVARVAL are null.... Since IDVAR\n                  identifies the keys that can be used to merge/join  records between\n                  the datasets, --SEQ cannot be used because --SEQ only has meaning\n                  within a subject within a dataset, not across datasets.\n                Document: IG v3.4\n                Section: 8.3.1 RELREC Dataset Relationship Example\nScope:\n  Classes:\n    Include:\n      - RELATIONSHIP\n  Domains:\n    Include:\n      - RELREC\n",
    "created": "2021-10-13T12:53:04Z",
    "creator": {
        "id": "02c3c969-4787-4d57-b164-e2851035c0e8"
    },
    "json": {
        "Check": {
            "all": [
                {
                    "name": "IDVARVAL",
                    "operator": "empty"
                },
                {
                    "name": "USUBJID",
                    "operator": "empty"
                },
                {
                    "name": "IDVAR",
                    "operator": "ends_with",
                    "value": "SEQ"
                }
            ]
        },
        "Core": {
            "Id": "CORE-000136",
            "Version": "1",
            "Status": "Published"
        },
        "Description": "Raise an error when IDVARVAL and USUBJID are empty and IDVAR = Sequence Number.",
        "Outcome": {
            "Message": "IDVARVAL and USUBJID are not completed, but IDVAR equals Sequence Number.",
            "Output_Variables": [
                "RDOMAIN",
                "IDVAR",
                "IDVARVAL",
                "RELID"
            ]
        },
        "Rule_Type": "Record Data",
        "Sensitivity": "Record",
        "Authorities": [
            {
                "Organization": "CDISC",
                "Standards": [
                    {
                        "Name": "SDTMIG",
                        "Version": "3.4",
                        "References": [
                            {
                                "Origin": "SDTM and SDTMIG Conformance Rules",
                                "Rule_Identifier": {
                                    "Id": "CG0201",
                                    "Version": "1"
                                },
                                "Version": "2.0",
                                "Citations": [
                                    {
                                        "Cited_Guidance": "This example shows how to use the RELREC dataset to represent related information that is submitted as two datasets that have a one-to-many relationship. in the example below  all the records in one domain are being related to all of the records in the other, so both  USUBJID and IDVARVAL are null.... Since IDVAR identifies the keys that can be used to merge/join  records between the datasets, --SEQ cannot be used because --SEQ only has meaning within a subject within a dataset, not across datasets.",
                                        "Document": "IG v3.4",
                                        "Section": "8.3.1 RELREC Dataset Relationship Example"
                                    }
                                ]
                            }
                        ]
                    }
                ]
            }
        ],
        "Scope": {
            "Classes": {
                "Include": [
                    "RELATIONSHIP"
                ]
            },
            "Domains": {
                "Include": [
                    "RELREC"
                ]
            }
        }
    }
}