{
    "id": "4256dbab-4ecc-4888-b3d1-25dd00e3ba8a",
    "changed": "2022-03-21T13:27:41Z",
    "content": "Check:\n  all:\n    - name: ETCD\n      operator: equal_to\n      value: UNPLAN\n    - name: TAETORD\n      operator: non_empty\nCore:\n  Id: CORE-000020\n  Version: '1'\n  Status: Published\nDescription: Raise an error when ETCD=\"UNPLAN\" and TAETORD is not null.\nOutcome:\n  Message: TAETORD should be null when ETCD = 'UNPLAN'.\n  Output Variables:\n    - ETCD\n    - TAETORD\nRule Type: Record Data\nSensitivity: Record\nAuthorities:\n  - Organization: CDISC\n    Standards:\n      - Name: SDTMIG\n        Version: '3.4'\n        References:\n          - Origin: SDTM and SDTMIG Conformance Rules\n            Rule Identifier:\n              Id: CG0206\n              Version: '1'\n            Version: '2.0'\n            Citations:\n              - Cited Guidance: TAETORD will not be populated for subject Elements\n                  that are not planned for the Arm to which the subject was assigned.\n                  Thus, TAETORD will not be populated for any Element with an ETCD\n                  value of UNPLAN.\n                Document: IG v3.4\n                Item: Assumption 6\n                Section: '5.3'\nScope:\n  Classes:\n    Include:\n      - SPECIAL-PURPOSE\n  Domains:\n    Include:\n      - SE\n",
    "created": "2021-09-29T09:36:28Z",
    "creator": {
        "id": "c2ea3586-26ef-4d9f-a8d5-a76a58005ea9"
    },
    "json": {
        "Check": {
            "all": [
                {
                    "name": "ETCD",
                    "operator": "equal_to",
                    "value": "UNPLAN"
                },
                {
                    "name": "TAETORD",
                    "operator": "non_empty"
                }
            ]
        },
        "Core": {
            "Id": "CORE-000020",
            "Version": "1",
            "Status": "Published"
        },
        "Description": "Raise an error when ETCD=\"UNPLAN\" and TAETORD is not null.",
        "Outcome": {
            "Message": "TAETORD should be null when ETCD = 'UNPLAN'.",
            "Output_Variables": [
                "ETCD",
                "TAETORD"
            ]
        },
        "Rule_Type": "Record Data",
        "Sensitivity": "Record",
        "Authorities": [
            {
                "Organization": "CDISC",
                "Standards": [
                    {
                        "Name": "SDTMIG",
                        "Version": "3.4",
                        "References": [
                            {
                                "Origin": "SDTM and SDTMIG Conformance Rules",
                                "Rule_Identifier": {
                                    "Id": "CG0206",
                                    "Version": "1"
                                },
                                "Version": "2.0",
                                "Citations": [
                                    {
                                        "Cited_Guidance": "TAETORD will not be populated for subject Elements that are not planned for the Arm to which the subject was assigned. Thus, TAETORD will not be populated for any Element with an ETCD value of UNPLAN.",
                                        "Document": "IG v3.4",
                                        "Item": "Assumption 6",
                                        "Section": "5.3"
                                    }
                                ]
                            }
                        ]
                    }
                ]
            }
        ],
        "Scope": {
            "Classes": {
                "Include": [
                    "SPECIAL-PURPOSE"
                ]
            },
            "Domains": {
                "Include": [
                    "SE"
                ]
            }
        }
    }
}