{
    "id": "f9dc74df-c2e5-45c5-85ae-28da3b6c9526",
    "changed": "2022-06-29T19:14:54Z",
    "content": "Check:\n  all:\n    - name: TSPARMCD\n      operator: is_not_unique_set\n      value:\n        - DOMAIN\n    - name: TSSEQ\n      operator: is_not_unique_set\n      value: TSPARMCD\nCore:\n  Id: CORE-000154\n  Version: '1'\n  Status: Published\nDescription: TSSEQ must be unique within TSPARMCD\nOutcome:\n  Message: TSSEQ is not unique within TSPARMCD\n  Output Variables:\n    - TSSEQ\n    - TSPARMCD\nRule Type: Record Data\nSensitivity: Record\nAuthorities:\n  - Organization: CDISC\n    Standards:\n      - Name: SDTMIG\n        Version: '3.4'\n        References:\n          - Origin: SDTM and SDTMIG Conformance Rules\n            Rule Identifier:\n              Id: CG0268\n              Version: '1'\n            Version: '2.0'\n            Citations:\n              - Cited Guidance: Sequence number given to ensure uniqueness within\n                  a dataset. Allows inclusion of multiple records for the same TSPARMCD.\n                Document: IG v3.4\n                Item: Specification\n                Section: 7.4.2\nScope:\n  Classes:\n    Include:\n      - TRIAL DESIGN\n  Domains:\n    Include:\n      - TS\n",
    "created": "2021-10-17T05:25:42Z",
    "creator": {
        "id": "ff471ff8-f131-4cf5-9712-c79cce6301a1"
    },
    "json": {
        "Check": {
            "all": [
                {
                    "name": "TSPARMCD",
                    "operator": "is_not_unique_set",
                    "value": [
                        "DOMAIN"
                    ]
                },
                {
                    "name": "TSSEQ",
                    "operator": "is_not_unique_set",
                    "value": "TSPARMCD"
                }
            ]
        },
        "Core": {
            "Id": "CORE-000154",
            "Version": "1",
            "Status": "Published"
        },
        "Description": "TSSEQ must be unique within TSPARMCD",
        "Outcome": {
            "Message": "TSSEQ is not unique within TSPARMCD",
            "Output_Variables": [
                "TSSEQ",
                "TSPARMCD"
            ]
        },
        "Rule_Type": "Record Data",
        "Sensitivity": "Record",
        "Authorities": [
            {
                "Organization": "CDISC",
                "Standards": [
                    {
                        "Name": "SDTMIG",
                        "Version": "3.4",
                        "References": [
                            {
                                "Origin": "SDTM and SDTMIG Conformance Rules",
                                "Rule_Identifier": {
                                    "Id": "CG0268",
                                    "Version": "1"
                                },
                                "Version": "2.0",
                                "Citations": [
                                    {
                                        "Cited_Guidance": "Sequence number given to ensure uniqueness within a dataset. Allows inclusion of multiple records for the same TSPARMCD.",
                                        "Document": "IG v3.4",
                                        "Item": "Specification",
                                        "Section": "7.4.2"
                                    }
                                ]
                            }
                        ]
                    }
                ]
            }
        ],
        "Scope": {
            "Classes": {
                "Include": [
                    "TRIAL DESIGN"
                ]
            },
            "Domains": {
                "Include": [
                    "TS"
                ]
            }
        }
    }
}