{
    "id": "131d7e58-949e-4195-9962-50d873668906",
    "changed": "2022-07-17T11:04:23Z",
    "content": "Check:\n  all:\n    - name: SEENDTC\n      operator: empty_within_except_last_row\n      value: USUBJID\nCore:\n  Id: CDISC.SDTMIG.CG0209\n  Version: '1'\n  Status: Draft\nDescription: Trigger error where element is not the last element and SEENDTC is null.\nOutcome:\n  Message: SEENDTC is null when element is not the last.\nRule Type: Record Data\nSensitivity: Record\nAuthorities:\n  - Organization: CDISC\n    Standards:\n      - Name: SDTMIG\n        Version: '3.4'\n        References:\n          - Origin: SDTM and SDTMIG Conformance Rules\n            Rule Identifier:\n              Id: CG0209\n              Version: '2'\n            Version: '2.0'\n            Citations:\n              - Cited Guidance: 'Since there are, by definition, no gaps between Elements,\n                  the value of SEENDTC for one Element will always be the same as\n                  the value of SESTDTC for the next Element. '\n                Document: IG v3.4\n                Item: Assumption 8\n                Section: '5.3'\n              - Cited Guidance: '\"Note that SESTDTC is required, although --STDTC\n                  is not required in any other subject-level dataset. The purpose\n                  of the dataset is to record the Elements a subject actually passed\n                  through. We assume that if it is known that a subject passed through\n                  a particular Element, then there must be some information on when\n                  it started, even if that information is imprecise. Thus, SESTDTC\n                  may not be null, although some records may not have all the components\n                  (e.g., year, month, day, hour, minute) of the date/time value collected.\"'\n                Document: IG v3.4\n                Item: Assumption 9\n                Section: '5.3'\nScope:\n  Classes:\n    Include:\n      - SPECIAL-PURPOSE\n  Domains:\n    Include:\n      - SE\n",
    "created": "2021-10-16T07:44:50Z",
    "creator": {
        "id": "ff471ff8-f131-4cf5-9712-c79cce6301a1"
    },
    "json": {
        "Check": {
            "all": [
                {
                    "name": "SEENDTC",
                    "operator": "empty_within_except_last_row",
                    "value": "USUBJID"
                }
            ]
        },
        "Core": {
            "Id": "CDISC.SDTMIG.CG0209",
            "Version": "1",
            "Status": "Draft"
        },
        "Description": "Trigger error where element is not the last element and SEENDTC is null.",
        "Outcome": {
            "Message": "SEENDTC is null when element is not the last."
        },
        "Rule_Type": "Record Data",
        "Sensitivity": "Record",
        "Authorities": [
            {
                "Organization": "CDISC",
                "Standards": [
                    {
                        "Name": "SDTMIG",
                        "Version": "3.4",
                        "References": [
                            {
                                "Origin": "SDTM and SDTMIG Conformance Rules",
                                "Rule_Identifier": {
                                    "Id": "CG0209",
                                    "Version": "2"
                                },
                                "Version": "2.0",
                                "Citations": [
                                    {
                                        "Cited_Guidance": "Since there are, by definition, no gaps between Elements, the value of SEENDTC for one Element will always be the same as the value of SESTDTC for the next Element. ",
                                        "Document": "IG v3.4",
                                        "Item": "Assumption 8",
                                        "Section": "5.3"
                                    },
                                    {
                                        "Cited_Guidance": "\"Note that SESTDTC is required, although --STDTC is not required in any other subject-level dataset. The purpose of the dataset is to record the Elements a subject actually passed through. We assume that if it is known that a subject passed through a particular Element, then there must be some information on when it started, even if that information is imprecise. Thus, SESTDTC may not be null, although some records may not have all the components (e.g., year, month, day, hour, minute) of the date/time value collected.\"",
                                        "Document": "IG v3.4",
                                        "Item": "Assumption 9",
                                        "Section": "5.3"
                                    }
                                ]
                            }
                        ]
                    }
                ]
            }
        ],
        "Scope": {
            "Classes": {
                "Include": [
                    "SPECIAL-PURPOSE"
                ]
            },
            "Domains": {
                "Include": [
                    "SE"
                ]
            }
        }
    }
}