{
    "id": "ec9b2df2-d7c2-47f1-891b-3f84f1e77182",
    "changed": "2022-07-30T11:17:29Z",
    "content": "Check:\n  all:\n    - name: TSPARMCD\n      operator: equal_to\n      value: AGEMAX\n    - name: TSVAL\n      operator: non_empty\n    - any:\n        - name: TSVAL\n          operator: not_matches_regex\n          value: ^P(?!$)(\\d+(?:\\.\\d+)?Y)?(\\d+(?:\\.\\d+)?M)?(\\d+(?:\\.\\d+)?W)?(\\d+(?:\\.\\d+)?D)?(T(?=\\d)(\\d+(?:\\.\\d+)?H)?(\\d+(?:\\.\\d+)?M)?(\\d+(?:\\.\\d+)?S)?)?$\nCore:\n  Id: CDISC.SDTMIG.CG0270\n  Version: '1'\n  Status: Draft\nDescription: Trigger error when TSPARMCD = 'AGEMAX' and TSVAL ^= null and TSVAL does\n  not conform to ISO 8601\nOutcome:\n  Message: TSVAL does not conform to ISO 8601\nRule Type: Record Data\nSensitivity: Record\nAuthorities:\n  - Organization: CDISC\n    Standards:\n      - Name: SDTMIG\n        Version: '3.4'\n        References:\n          - Origin: SDTM and SDTMIG Conformance Rules\n            Rule Identifier:\n              Id: CG0270\n              Version: '1'\n            Version: '2.0'\n            Citations:\n              - Cited Guidance: When the trial summary parameter is AGEMAX, then TSVAL\n                  should have a value expressed as an ISO8601 time duration (e.g.,\n                  P43Y for 43 years old or P6M for 6 months old).\n                Document: IG v3.4\n                Section: 7.4.2.1\nScope:\n  Classes:\n    Include:\n      - TRIAL DESIGN\n  Domains:\n    Include:\n      - TS\n",
    "created": "2021-10-17T05:28:10Z",
    "creator": {
        "id": "ff471ff8-f131-4cf5-9712-c79cce6301a1"
    },
    "json": {
        "Check": {
            "all": [
                {
                    "name": "TSPARMCD",
                    "operator": "equal_to",
                    "value": "AGEMAX"
                },
                {
                    "name": "TSVAL",
                    "operator": "non_empty"
                },
                {
                    "any": [
                        {
                            "name": "TSVAL",
                            "operator": "not_matches_regex",
                            "value": "^P(?!$)(\\d+(?:\\.\\d+)?Y)?(\\d+(?:\\.\\d+)?M)?(\\d+(?:\\.\\d+)?W)?(\\d+(?:\\.\\d+)?D)?(T(?=\\d)(\\d+(?:\\.\\d+)?H)?(\\d+(?:\\.\\d+)?M)?(\\d+(?:\\.\\d+)?S)?)?$"
                        }
                    ]
                }
            ]
        },
        "Core": {
            "Id": "CDISC.SDTMIG.CG0270",
            "Version": "1",
            "Status": "Draft"
        },
        "Description": "Trigger error when TSPARMCD = 'AGEMAX' and TSVAL ^= null and TSVAL does not conform to ISO 8601",
        "Outcome": {
            "Message": "TSVAL does not conform to ISO 8601"
        },
        "Rule_Type": "Record Data",
        "Sensitivity": "Record",
        "Authorities": [
            {
                "Organization": "CDISC",
                "Standards": [
                    {
                        "Name": "SDTMIG",
                        "Version": "3.4",
                        "References": [
                            {
                                "Origin": "SDTM and SDTMIG Conformance Rules",
                                "Rule_Identifier": {
                                    "Id": "CG0270",
                                    "Version": "1"
                                },
                                "Version": "2.0",
                                "Citations": [
                                    {
                                        "Cited_Guidance": "When the trial summary parameter is AGEMAX, then TSVAL should have a value expressed as an ISO8601 time duration (e.g., P43Y for 43 years old or P6M for 6 months old).",
                                        "Document": "IG v3.4",
                                        "Section": "7.4.2.1"
                                    }
                                ]
                            }
                        ]
                    }
                ]
            }
        ],
        "Scope": {
            "Classes": {
                "Include": [
                    "TRIAL DESIGN"
                ]
            },
            "Domains": {
                "Include": [
                    "TS"
                ]
            }
        }
    }
}