{
    "id": "3b0c313e-91cf-4edc-b2d6-2753f2eff627",
    "changed": "2023-02-07T15:48:58.427Z",
    "content": "Check:\n  all:\n    - name: SEENDTC\n      operator: has_next_corresponding_record\n      value: SESTDTC\n      within: USUBJID\n      ordering: SESEQ\nCore:\n  Id: CDISC.SDTMIG.CG0207\n  Version: '1'\n  Status: Draft\nDescription: Trigger error where SEENDTC is not equal to SESTDTC of the next element.\nOutcome:\n  Message: SEENDTC is not equal to SESTDTC of the next element.\nRule Type: Record Data\nSensitivity: Record\nAuthorities:\n  - Organization: CDISC\n    Standards:\n      - Name: SDTMIG\n        Version: '3.4'\n        References:\n          - Origin: SDTM and SDTMIG Conformance Rules\n            Rule Identifier:\n              Id: CG0207\n              Version: '1'\n            Version: '2.0'\n            Citations:\n              - Cited Guidance: Since there are, by definition, no gaps between Elements,\n                  the value of SEENDTC for one Element will always be the same as\n                  the value of SESTDTC for the next Element.\n                Document: IG v3.4\n                Item: Assumption 8\n                Section: '5.3'\nScope:\n  Classes:\n    Include:\n      - SPECIAL PURPOSE\n  Domains:\n    Include:\n      - SE\n",
    "created": "2021-10-16T07:36:59Z",
    "creator": {
        "id": "ff471ff8-f131-4cf5-9712-c79cce6301a1"
    },
    "json": {
        "Check": {
            "all": [
                {
                    "name": "SEENDTC",
                    "operator": "has_next_corresponding_record",
                    "value": "SESTDTC",
                    "within": "USUBJID",
                    "ordering": "SESEQ"
                }
            ]
        },
        "Core": {
            "Id": "CDISC.SDTMIG.CG0207",
            "Version": "1",
            "Status": "Draft"
        },
        "Description": "Trigger error where SEENDTC is not equal to SESTDTC of the next element.",
        "Outcome": {
            "Message": "SEENDTC is not equal to SESTDTC of the next element."
        },
        "Sensitivity": "Record",
        "Authorities": [
            {
                "Organization": "CDISC",
                "Standards": [
                    {
                        "Name": "SDTMIG",
                        "Version": "3.4",
                        "References": [
                            {
                                "Origin": "SDTM and SDTMIG Conformance Rules",
                                "Version": "2.0",
                                "Citations": [
                                    {
                                        "Document": "IG v3.4",
                                        "Item": "Assumption 8",
                                        "Section": "5.3",
                                        "Cited_Guidance": "Since there are, by definition, no gaps between Elements, the value of SEENDTC for one Element will always be the same as the value of SESTDTC for the next Element."
                                    }
                                ],
                                "Rule_Identifier": {
                                    "Id": "CG0207",
                                    "Version": "1"
                                }
                            }
                        ]
                    }
                ]
            }
        ],
        "Scope": {
            "Classes": {
                "Include": [
                    "SPECIAL PURPOSE"
                ]
            },
            "Domains": {
                "Include": [
                    "SE"
                ]
            }
        },
        "Rule_Type": "Record Data"
    }
}