{
    "id": "27b19da0-4601-490e-bbfe-a0d389d1c46a",
    "changed": "2022-10-04T14:25:22.691Z",
    "content": "Check:\n  all:\n    #Restrict check to records where --ENDTC has a complete date and RFSTDTC has a complete date\n    - name: --ENDTC\n      operator: is_complete_date\n    # - name: RFSTDTC\n    #  operator: is_complete_date\n    #Check --ENDY derivation\n    - name: --ENDY\n      operator: not_equal_to\n      value: $val_stdy\nOperations:\n  - name: RFSTDTC\n    operator: dy\n    domain: DM\n    id: $val_stdy\nCore:\n  Id: CDISC.SDTMIG.CG0222\n  Version: '1'\n  Status: Draft\nDescription: Study day must be calculated using the algorithm detailed in the SDTMIG.\nOutcome:\n  Message: --ENDY is not properly calculated per study day algorithm\nRule Type: Record Data\nSensitivity: Record\nAuthorities:\n  - Organization: CDISC\n    Standards:\n      - Name: SDTMIG\n        Version: '3.4'\n        References:\n          - Origin: SDTM and SDTMIG Conformance Rules\n            Rule Identifier:\n              Id: CG0222\n              Version: '1'\n            Version: '2.0'\n            Citations:\n              - Cited Guidance: The permissible Study Day variables (--DY, --STDY,\n                  and --ENDY) describe the relative day of the observation  starting\n                  with the reference date as Day 1. They are determined by comparing\n                  the date portion of the  respective date/time variables (--DTC,\n                  --STDTC, and --ENDTC) to the date portion of the Subject Reference  Start\n                  Date (RFSTDTC from the Demographics domain). All Study Day values\n                  are integers. Thus, to calculate Study Day,  --DY = (date portion\n                  of --DTC) - (date portion of RFSTDTC) + 1 if --DTC is on or after\n                  RFSTDTC,  --DY = (date portion of --DTC) - (date portion of RFSTDTC)\n                  if --DTC precedes RFSTDTC.  This algorithm should be used across\n                  all domains.\n                Document: IG v3.4\n                Section: 4.4.4\nScope:\n  Classes:\n    Include:\n      - ALL\n  Domains:\n    Exclude:\n      - DM\n",
    "created": "2021-10-16T11:08:21Z",
    "creator": {
        "id": "ff471ff8-f131-4cf5-9712-c79cce6301a1"
    },
    "json": {
        "Check": {
            "all": [
                {
                    "name": "--ENDTC",
                    "operator": "is_complete_date"
                },
                {
                    "name": "--ENDY",
                    "operator": "not_equal_to",
                    "value": "$val_stdy"
                }
            ]
        },
        "Operations": [
            {
                "name": "RFSTDTC",
                "operator": "dy",
                "domain": "DM",
                "id": "$val_stdy"
            }
        ],
        "Core": {
            "Id": "CDISC.SDTMIG.CG0222",
            "Version": "1",
            "Status": "Draft"
        },
        "Description": "Study day must be calculated using the algorithm detailed in the SDTMIG.",
        "Outcome": {
            "Message": "--ENDY is not properly calculated per study day algorithm"
        },
        "Rule_Type": "Record Data",
        "Sensitivity": "Record",
        "Authorities": [
            {
                "Organization": "CDISC",
                "Standards": [
                    {
                        "Name": "SDTMIG",
                        "Version": "3.4",
                        "References": [
                            {
                                "Origin": "SDTM and SDTMIG Conformance Rules",
                                "Rule_Identifier": {
                                    "Id": "CG0222",
                                    "Version": "1"
                                },
                                "Version": "2.0",
                                "Citations": [
                                    {
                                        "Cited_Guidance": "The permissible Study Day variables (--DY, --STDY, and --ENDY) describe the relative day of the observation  starting with the reference date as Day 1. They are determined by comparing the date portion of the  respective date/time variables (--DTC, --STDTC, and --ENDTC) to the date portion of the Subject Reference  Start Date (RFSTDTC from the Demographics domain). All Study Day values are integers. Thus, to calculate Study Day,  --DY = (date portion of --DTC) - (date portion of RFSTDTC) + 1 if --DTC is on or after RFSTDTC,  --DY = (date portion of --DTC) - (date portion of RFSTDTC) if --DTC precedes RFSTDTC.  This algorithm should be used across all domains.",
                                        "Document": "IG v3.4",
                                        "Section": "4.4.4"
                                    }
                                ]
                            }
                        ]
                    }
                ]
            }
        ],
        "Scope": {
            "Classes": {
                "Include": [
                    "ALL"
                ]
            },
            "Domains": {
                "Exclude": [
                    "DM"
                ]
            }
        }
    }
}