{
    "id": "d37ba86f-801a-4bfb-a3eb-853ab3501bce",
    "changed": "2022-05-25T18:14:08Z",
    "content": "Check:\n  all:\n    - name: TIVERS\n      operator: exists\n    - name: IETESTCD\n      operator: is_not_unique_set\n      value: TIVERS\nCore:\n  Id: CORE-000145\n  Version: '1'\n  Status: Published\nDescription: Trigger error when TIVERS is present and IETESTCD is not unique within\n  TIVERS\nOutcome:\n  Message: IETESTCD is not unique within TIVERS\n  Output Variables:\n    - IETESTCD\n    - TIVERS\nRule Type: Record Data\nSensitivity: Record\nAuthorities:\n  - Organization: CDISC\n    Standards:\n      - Name: SDTMIG\n        Version: '3.4'\n        References:\n          - Origin: SDTM and SDTMIG Conformance Rules\n            Rule Identifier:\n              Id: CG0255\n              Version: '1'\n            Version: '2.0'\n            Citations:\n              - Cited Guidance: If inclusion/exclusion criteria were amended during\n                  the trial, then each complete set of criteria must be included in\n                  the TI domain. TIVERS is used to distinguish between the versions.\n                Document: IG v3.4\n                Item: Assumption 1\n                Section: 7.4.1\nScope:\n  Classes:\n    Include:\n      - TRIAL DESIGN\n  Domains:\n    Include:\n      - TI\n",
    "created": "2021-10-17T04:49:02Z",
    "creator": {
        "id": "ff471ff8-f131-4cf5-9712-c79cce6301a1"
    },
    "json": {
        "Check": {
            "all": [
                {
                    "name": "TIVERS",
                    "operator": "exists"
                },
                {
                    "name": "IETESTCD",
                    "operator": "is_not_unique_set",
                    "value": "TIVERS"
                }
            ]
        },
        "Core": {
            "Id": "CORE-000145",
            "Version": "1",
            "Status": "Published"
        },
        "Description": "Trigger error when TIVERS is present and IETESTCD is not unique within TIVERS",
        "Outcome": {
            "Message": "IETESTCD is not unique within TIVERS",
            "Output_Variables": [
                "IETESTCD",
                "TIVERS"
            ]
        },
        "Rule_Type": "Record Data",
        "Sensitivity": "Record",
        "Authorities": [
            {
                "Organization": "CDISC",
                "Standards": [
                    {
                        "Name": "SDTMIG",
                        "Version": "3.4",
                        "References": [
                            {
                                "Origin": "SDTM and SDTMIG Conformance Rules",
                                "Rule_Identifier": {
                                    "Id": "CG0255",
                                    "Version": "1"
                                },
                                "Version": "2.0",
                                "Citations": [
                                    {
                                        "Cited_Guidance": "If inclusion/exclusion criteria were amended during the trial, then each complete set of criteria must be included in the TI domain. TIVERS is used to distinguish between the versions.",
                                        "Document": "IG v3.4",
                                        "Item": "Assumption 1",
                                        "Section": "7.4.1"
                                    }
                                ]
                            }
                        ]
                    }
                ]
            }
        ],
        "Scope": {
            "Classes": {
                "Include": [
                    "TRIAL DESIGN"
                ]
            },
            "Domains": {
                "Include": [
                    "TI"
                ]
            }
        }
    }
}