{
    "id": "98eda2c2-3ad1-4be7-8aab-817370c0e612",
    "changed": "2022-02-15T21:30:08Z",
    "content": "Check:\n  all:\n    - name:\n      operator:\n    - name: TATRANS\n      operator: empty\nCore:\n  Id: CDISC.SDTMIG.CG0252\n  Version: '1'\n  Status: Draft\nDescription: Trigger error when trial Design allows for a Subject to transition to\n  an Element other than the next Element in sequence, and TATRANS is null\nOutcome:\n  Message: TATRANS is null when trial Design allows for a Subject to transition to\n    an Element other than the next Element in sequence\nRule Type: Record Data\nSensitivity: Record\nAuthorities:\n  - Organization: CDISC\n    Standards:\n      - Name: SDTMIG\n        Version: '3.4'\n        References:\n          - Origin: SDTM and SDTMIG Conformance Rules\n            Rule Identifier:\n              Id: CG0252\n              Version: '1'\n            Version: '2.0'\n            Citations:\n              - Cited Guidance: If the trial design allows a subject to transition\n                  to an Element other than the next Element in sequence, then the\n                  conditions for transitioning to those other Elements, and the alternative\n                  Element sequences, are specified in this rule (e.g., Responders\n                  go to washout).\n                Document: IG v3.4\n                Item: Specification\n                Section: 7.2.1\nScope:\n  Classes:\n    Include:\n      - TRIAL DESIGN\n  Domains:\n    Include:\n      - TA\n",
    "created": "2021-10-30T10:38:58Z",
    "creator": {
        "id": "ff471ff8-f131-4cf5-9712-c79cce6301a1"
    },
    "json": {
        "Check": {
            "all": [
                {
                    "name": null,
                    "operator": null
                },
                {
                    "name": "TATRANS",
                    "operator": "empty"
                }
            ]
        },
        "Core": {
            "Id": "CDISC.SDTMIG.CG0252",
            "Version": "1",
            "Status": "Draft"
        },
        "Description": "Trigger error when trial Design allows for a Subject to transition to an Element other than the next Element in sequence, and TATRANS is null",
        "Outcome": {
            "Message": "TATRANS is null when trial Design allows for a Subject to transition to an Element other than the next Element in sequence"
        },
        "Rule_Type": "Record Data",
        "Sensitivity": "Record",
        "Authorities": [
            {
                "Organization": "CDISC",
                "Standards": [
                    {
                        "Name": "SDTMIG",
                        "Version": "3.4",
                        "References": [
                            {
                                "Origin": "SDTM and SDTMIG Conformance Rules",
                                "Rule_Identifier": {
                                    "Id": "CG0252",
                                    "Version": "1"
                                },
                                "Version": "2.0",
                                "Citations": [
                                    {
                                        "Cited_Guidance": "If the trial design allows a subject to transition to an Element other than the next Element in sequence, then the conditions for transitioning to those other Elements, and the alternative Element sequences, are specified in this rule (e.g., Responders go to washout).",
                                        "Document": "IG v3.4",
                                        "Item": "Specification",
                                        "Section": "7.2.1"
                                    }
                                ]
                            }
                        ]
                    }
                ]
            }
        ],
        "Scope": {
            "Classes": {
                "Include": [
                    "TRIAL DESIGN"
                ]
            },
            "Domains": {
                "Include": [
                    "TA"
                ]
            }
        }
    }
}