{
    "id": "ce041a2f-a518-4744-925d-47a497532e99",
    "changed": "2022-07-17T11:04:15Z",
    "content": "Check:\n  all:\n    - name: SESTDTC\n      operator: empty\nCore:\n  Id: CORE-000002\n  Version: '1'\n  Status: Published\nDescription: Raise an error when SESTDTC is null.\nOutcome:\n  Message: SESTDTC is required.\nRule Type: Record Data\nSensitivity: Record\nAuthorities:\n  - Organization: CDISC\n    Standards:\n      - Name: SDTMIG\n        Version: '3.4'\n        References:\n          - Origin: SDTM and SDTMIG Conformance Rules\n            Rule Identifier:\n              Id: CG0208\n              Version: '3'\n            Version: '2.0'\n            Citations:\n              - Cited Guidance: Note that SESTDTC is required, although --STDTC is\n                  not required in any other subject-level dataset. The purpose of\n                  the dataset is to record the Elements a subject actually passed\n                  through. We assume that if it is known that a subject passed through\n                  a particular Element, then there must be some information on when\n                  it started, even if that information is imprecise. Thus, SESTDTC\n                  may not be null, although some records may not have all the components\n                  (e.g., year, month, day, hour, minute) of the date/time value collected.\n                Document: SDTM v1.4\n                Section: '5.3'\nScope:\n  Classes:\n    Include:\n      - SPECIAL-PURPOSE\n  Domains:\n    Include:\n      - SE\n",
    "created": "2021-09-24T06:44:37Z",
    "creator": {
        "id": "ff471ff8-f131-4cf5-9712-c79cce6301a1"
    },
    "json": {
        "Check": {
            "all": [
                {
                    "name": "SESTDTC",
                    "operator": "empty"
                }
            ]
        },
        "Core": {
            "Id": "CORE-000002",
            "Version": "1",
            "Status": "Published"
        },
        "Description": "Raise an error when SESTDTC is null.",
        "Outcome": {
            "Message": "SESTDTC is required."
        },
        "Rule_Type": "Record Data",
        "Sensitivity": "Record",
        "Authorities": [
            {
                "Organization": "CDISC",
                "Standards": [
                    {
                        "Name": "SDTMIG",
                        "Version": "3.4",
                        "References": [
                            {
                                "Origin": "SDTM and SDTMIG Conformance Rules",
                                "Rule_Identifier": {
                                    "Id": "CG0208",
                                    "Version": "3"
                                },
                                "Version": "2.0",
                                "Citations": [
                                    {
                                        "Cited_Guidance": "Note that SESTDTC is required, although --STDTC is not required in any other subject-level dataset. The purpose of the dataset is to record the Elements a subject actually passed through. We assume that if it is known that a subject passed through a particular Element, then there must be some information on when it started, even if that information is imprecise. Thus, SESTDTC may not be null, although some records may not have all the components (e.g., year, month, day, hour, minute) of the date/time value collected.",
                                        "Document": "SDTM v1.4",
                                        "Section": "5.3"
                                    }
                                ]
                            }
                        ]
                    }
                ]
            }
        ],
        "Scope": {
            "Classes": {
                "Include": [
                    "SPECIAL-PURPOSE"
                ]
            },
            "Domains": {
                "Include": [
                    "SE"
                ]
            }
        }
    }
}