{
    "id": "de2e30fc-801b-49ce-b00a-0adfc5498a63",
    "changed": "2022-06-15T21:16:26Z",
    "content": "Check:\n  all:\n    - name: TSVAL1\n      operator: non_empty\n    - name: TSVAL\n      operator: empty\nCore:\n  Id: CORE-000151\n  Version: '1'\n  Status: Published\nDescription: Trigger error when TSVAL1 is populated and TSVAL is null\nOutcome:\n  Message: TSVAL is null when TSVAL1 is populated.\nRule Type: Record Data\nSensitivity: Record\nAuthorities:\n  - Organization: CDISC\n    Standards:\n      - Name: SDTMIG\n        Version: '3.4'\n        References:\n          - Origin: SDTM and SDTMIG Conformance Rules\n            Rule Identifier:\n              Id: CG0261\n              Version: '1'\n            Version: '2.0'\n            Citations:\n              - Cited Guidance: Text over 200 characters can be added to additional\n                  columns TSVAL1-TSVALn.\n                Document: IG v3.4\n                Item: Specification\n                Section: 7.4.2\nScope:\n  Classes:\n    Include:\n      - TRIAL DESIGN\n  Domains:\n    Include:\n      - TS\n",
    "created": "2021-10-17T05:09:50Z",
    "creator": {
        "id": "ff471ff8-f131-4cf5-9712-c79cce6301a1"
    },
    "json": {
        "Check": {
            "all": [
                {
                    "name": "TSVAL1",
                    "operator": "non_empty"
                },
                {
                    "name": "TSVAL",
                    "operator": "empty"
                }
            ]
        },
        "Core": {
            "Id": "CORE-000151",
            "Version": "1",
            "Status": "Published"
        },
        "Description": "Trigger error when TSVAL1 is populated and TSVAL is null",
        "Outcome": {
            "Message": "TSVAL is null when TSVAL1 is populated."
        },
        "Rule_Type": "Record Data",
        "Sensitivity": "Record",
        "Authorities": [
            {
                "Organization": "CDISC",
                "Standards": [
                    {
                        "Name": "SDTMIG",
                        "Version": "3.4",
                        "References": [
                            {
                                "Origin": "SDTM and SDTMIG Conformance Rules",
                                "Rule_Identifier": {
                                    "Id": "CG0261",
                                    "Version": "1"
                                },
                                "Version": "2.0",
                                "Citations": [
                                    {
                                        "Cited_Guidance": "Text over 200 characters can be added to additional columns TSVAL1-TSVALn.",
                                        "Document": "IG v3.4",
                                        "Item": "Specification",
                                        "Section": "7.4.2"
                                    }
                                ]
                            }
                        ]
                    }
                ]
            }
        ],
        "Scope": {
            "Classes": {
                "Include": [
                    "TRIAL DESIGN"
                ]
            },
            "Domains": {
                "Include": [
                    "TS"
                ]
            }
        }
    }
}