{
    "id": "c710c726-026c-4b8f-9210-200f769158e4",
    "changed": "2022-05-31T07:53:45Z",
    "content": "Check:\n  all:\n    - name: dataset_name\n      operator: longer_than\n      value: 8\nCore:\n  Id: CDISC.SDTMIG.CG0205\n  Version: '1'\n  Status: Draft\nDescription: Trigger error if length of dataset name is greater than 8\nOutcome:\n  Message: Length of dataset name of SUPP-- dataset is greater than 8.\nRule Type: Dataset Metadata Check\nSensitivity: Dataset\nAuthorities:\n  - Organization: CDISC\n    Standards:\n      - Name: SDTMIG\n        Version: '3.4'\n        References:\n          - Origin: SDTM and SDTMIG Conformance Rules\n            Rule Identifier:\n              Id: CG0205\n              Version: '1'\n            Version: '2.0'\n            Citations:\n              - Cited Guidance: \"\\\"When data have been split into multiple datasets\\\n                  \\ (see Section 4.1.7, Splitting Domains), longer names such as SUPPFAMH\\\n                  \\ may be needed. In cases where data about Associated Persons (see\\\n                  \\ Associated Persons Implementation Guide) have been collected,\\\n                  \\ Supplemental Qualifiers for Findings About events or interventions\\\n                  \\ for an associated person may need to be represented. A dataset\\\n                  \\ name with the SUPP fragment, e.g., SUPPAPFAMH, would be too long.\\\n                  \\ In this case only, the 'SUPP' portion should be shortened to 'SQ',\\\n                  \\ resulting in a dataset name such as SQAPFAMH.\\\"\"\n                Document: IG v3.4\n                Section: 8.4.2\nScope:\n  Classes:\n    Include:\n      - ALL\n  Domains:\n    Include:\n      - SUPP--\n",
    "created": "2021-10-16T07:30:45Z",
    "creator": {
        "id": "ff471ff8-f131-4cf5-9712-c79cce6301a1"
    },
    "json": {
        "Check": {
            "all": [
                {
                    "name": "dataset_name",
                    "operator": "longer_than",
                    "value": 8
                }
            ]
        },
        "Core": {
            "Id": "CDISC.SDTMIG.CG0205",
            "Version": "1",
            "Status": "Draft"
        },
        "Description": "Trigger error if length of dataset name is greater than 8",
        "Outcome": {
            "Message": "Length of dataset name of SUPP-- dataset is greater than 8."
        },
        "Rule_Type": "Dataset Metadata Check",
        "Sensitivity": "Dataset",
        "Authorities": [
            {
                "Organization": "CDISC",
                "Standards": [
                    {
                        "Name": "SDTMIG",
                        "Version": "3.4",
                        "References": [
                            {
                                "Origin": "SDTM and SDTMIG Conformance Rules",
                                "Rule_Identifier": {
                                    "Id": "CG0205",
                                    "Version": "1"
                                },
                                "Version": "2.0",
                                "Citations": [
                                    {
                                        "Cited_Guidance": "\"When data have been split into multiple datasets (see Section 4.1.7, Splitting Domains), longer names such as SUPPFAMH may be needed. In cases where data about Associated Persons (see Associated Persons Implementation Guide) have been collected, Supplemental Qualifiers for Findings About events or interventions for an associated person may need to be represented. A dataset name with the SUPP fragment, e.g., SUPPAPFAMH, would be too long. In this case only, the 'SUPP' portion should be shortened to 'SQ', resulting in a dataset name such as SQAPFAMH.\"",
                                        "Document": "IG v3.4",
                                        "Section": "8.4.2"
                                    }
                                ]
                            }
                        ]
                    }
                ]
            }
        ],
        "Scope": {
            "Classes": {
                "Include": [
                    "ALL"
                ]
            },
            "Domains": {
                "Include": [
                    "SUPP--"
                ]
            }
        }
    }
}