{
    "id": "84e521a6-3e85-4fbe-9a22-ab4b91b86f18",
    "changed": "2022-06-30T04:42:37Z",
    "content": "Check:\n  all:\n    - name: TSVALNF\n      operator: empty\n    - name: TSVAL\n      operator: prefix_matches_regex\n      value: (NI|OTH|NINF|PINF|UNK|ASKU|NAV|NASK|TRC|MSK|NA|QS)\nCore:\n  Id: CDISC.SDTMIG.CG0291\n  Version: '1'\n  Status: Draft\nDescription: When TSVALNF is null, TSVAL should not be populated with an ISO 21090\n  term or other null flavor.  This rule has been executed with the understanding that\n  non-ISO 21090 terms may not be flagged, and there may be exceptions where the term\n  has been used appropriately.\nOutcome:\n  Message: TSVAL is populated with an ISO 21090 or null flavor term\nRule Type: Record Data\nSensitivity: Record\nAuthorities:\n  - Organization: CDISC\n    Standards:\n      - Name: SDTMIG\n        Version: '3.4'\n        References:\n          - Origin: SDTM and SDTMIG Conformance Rules\n            Rule Identifier:\n              Id: CG0291\n              Version: '1'\n            Version: '2.0'\n            Citations:\n              - Cited Guidance: 'While it would be possible to allow a value such\n                  as NONE or UNBOUNDED to be entered in TSVAL, validation programs\n                  would then have to recognize this special term as an exception to\n                  the expected data format. Therefore, it was decided that a separate\n                  null flavor variable that uses the ISO 21090 null flavor terminology\n                  would be a better solution. '\n                Document: IG v3.4\n                Section: 7.4.2.1\nScope:\n  Classes:\n    Include:\n      - TRIAL DESIGN\n  Domains:\n    Include:\n      - TS\n",
    "created": "2021-10-17T05:40:37Z",
    "creator": {
        "id": "ff471ff8-f131-4cf5-9712-c79cce6301a1"
    },
    "json": {
        "Check": {
            "all": [
                {
                    "name": "TSVALNF",
                    "operator": "empty"
                },
                {
                    "name": "TSVAL",
                    "operator": "prefix_matches_regex",
                    "value": "(NI|OTH|NINF|PINF|UNK|ASKU|NAV|NASK|TRC|MSK|NA|QS)"
                }
            ]
        },
        "Core": {
            "Id": "CDISC.SDTMIG.CG0291",
            "Version": "1",
            "Status": "Draft"
        },
        "Description": "When TSVALNF is null, TSVAL should not be populated with an ISO 21090 term or other null flavor.  This rule has been executed with the understanding that non-ISO 21090 terms may not be flagged, and there may be exceptions where the term has been used appropriately.",
        "Outcome": {
            "Message": "TSVAL is populated with an ISO 21090 or null flavor term"
        },
        "Rule_Type": "Record Data",
        "Sensitivity": "Record",
        "Authorities": [
            {
                "Organization": "CDISC",
                "Standards": [
                    {
                        "Name": "SDTMIG",
                        "Version": "3.4",
                        "References": [
                            {
                                "Origin": "SDTM and SDTMIG Conformance Rules",
                                "Rule_Identifier": {
                                    "Id": "CG0291",
                                    "Version": "1"
                                },
                                "Version": "2.0",
                                "Citations": [
                                    {
                                        "Cited_Guidance": "While it would be possible to allow a value such as NONE or UNBOUNDED to be entered in TSVAL, validation programs would then have to recognize this special term as an exception to the expected data format. Therefore, it was decided that a separate null flavor variable that uses the ISO 21090 null flavor terminology would be a better solution. ",
                                        "Document": "IG v3.4",
                                        "Section": "7.4.2.1"
                                    }
                                ]
                            }
                        ]
                    }
                ]
            }
        ],
        "Scope": {
            "Classes": {
                "Include": [
                    "TRIAL DESIGN"
                ]
            },
            "Domains": {
                "Include": [
                    "TS"
                ]
            }
        }
    }
}