{
    "id": "a99e040e-1007-49bc-b503-b10fc6325e26",
    "changed": "2022-06-29T19:04:01Z",
    "content": "Check:\n  all:\n    - name: TSVAL\n      operator: non_empty\n    - name: TSVALCD\n      operator: non_empty\n    - name: TSVAL\n      operator: is_not_unique_relationship\n      value: TSVALCD\nCore:\n  Id: CORE-000152\n  Version: '1'\n  Status: Published\nDescription: When TSVAL and TSVALCD are populated, there must be a one-to-one relationship\n  between TSVALCD and TSVAL\nOutcome:\n  Message: There is not a one-to-one relationship between TSVAL and TSVALCD\n  Output Variables:\n    - TSVAL\n    - TSVALCD\nRule Type: Record Data\nSensitivity: Record\nAuthorities:\n  - Organization: CDISC\n    Standards:\n      - Name: SDTMIG\n        Version: '3.4'\n        References:\n          - Origin: SDTM and SDTMIG Conformance Rules\n            Rule Identifier:\n              Id: CG0265\n              Version: '1'\n            Version: '2.0'\n            Citations:\n              - Cited Guidance: This is the code of the term in TSVAL.\n                Document: IG v3.4\n                Item: Specification\n                Section: 7.4.2\nScope:\n  Classes:\n    Include:\n      - TRIAL DESIGN\n  Domains:\n    Include:\n      - TS\n",
    "created": "2021-10-17T05:20:16Z",
    "creator": {
        "id": "ff471ff8-f131-4cf5-9712-c79cce6301a1"
    },
    "json": {
        "Check": {
            "all": [
                {
                    "name": "TSVAL",
                    "operator": "non_empty"
                },
                {
                    "name": "TSVALCD",
                    "operator": "non_empty"
                },
                {
                    "name": "TSVAL",
                    "operator": "is_not_unique_relationship",
                    "value": "TSVALCD"
                }
            ]
        },
        "Core": {
            "Id": "CORE-000152",
            "Version": "1",
            "Status": "Published"
        },
        "Description": "When TSVAL and TSVALCD are populated, there must be a one-to-one relationship between TSVALCD and TSVAL",
        "Outcome": {
            "Message": "There is not a one-to-one relationship between TSVAL and TSVALCD",
            "Output_Variables": [
                "TSVAL",
                "TSVALCD"
            ]
        },
        "Rule_Type": "Record Data",
        "Sensitivity": "Record",
        "Authorities": [
            {
                "Organization": "CDISC",
                "Standards": [
                    {
                        "Name": "SDTMIG",
                        "Version": "3.4",
                        "References": [
                            {
                                "Origin": "SDTM and SDTMIG Conformance Rules",
                                "Rule_Identifier": {
                                    "Id": "CG0265",
                                    "Version": "1"
                                },
                                "Version": "2.0",
                                "Citations": [
                                    {
                                        "Cited_Guidance": "This is the code of the term in TSVAL.",
                                        "Document": "IG v3.4",
                                        "Item": "Specification",
                                        "Section": "7.4.2"
                                    }
                                ]
                            }
                        ]
                    }
                ]
            }
        ],
        "Scope": {
            "Classes": {
                "Include": [
                    "TRIAL DESIGN"
                ]
            },
            "Domains": {
                "Include": [
                    "TS"
                ]
            }
        }
    }
}