{
    "id": "4fea5cfe-5721-4d9e-9baa-b88ad14cf77b",
    "changed": "2022-05-25T18:59:53Z",
    "content": "Check:\n  all:\n    - name: TSVCDVER\n      operator: non_empty\n    - name: TSVCDREF\n      operator: empty\nCore:\n  Id: CORE-000153\n  Version: '1'\n  Status: Published\nDescription: Trigger error when TSVCDVER is populated and TSVCDREF is null\nOutcome:\n  Message: TSVCDREF is null when TSVCDVER is populated\n  Output Variables:\n    - TSVCDVER\n    - TSVCDREF\nRule Type: Record Data\nSensitivity: Record\nAuthorities:\n  - Organization: CDISC\n    Standards:\n      - Name: SDTMIG\n        Version: '3.4'\n        References:\n          - Origin: SDTM and SDTMIG Conformance Rules\n            Rule Identifier:\n              Id: CG0266\n              Version: '1'\n            Version: '2.0'\n            Citations:\n              - Cited Guidance: The version number of the Reference Terminology, if\n                  applicable.\n                Document: IG v3.4\n                Item: Specification\n                Section: 7.4.2\nScope:\n  Classes:\n    Include:\n      - TRIAL DESIGN\n  Domains:\n    Include:\n      - TS\n",
    "created": "2021-10-17T05:22:49Z",
    "creator": {
        "id": "ff471ff8-f131-4cf5-9712-c79cce6301a1"
    },
    "json": {
        "Check": {
            "all": [
                {
                    "name": "TSVCDVER",
                    "operator": "non_empty"
                },
                {
                    "name": "TSVCDREF",
                    "operator": "empty"
                }
            ]
        },
        "Core": {
            "Id": "CORE-000153",
            "Version": "1",
            "Status": "Published"
        },
        "Description": "Trigger error when TSVCDVER is populated and TSVCDREF is null",
        "Outcome": {
            "Message": "TSVCDREF is null when TSVCDVER is populated",
            "Output_Variables": [
                "TSVCDVER",
                "TSVCDREF"
            ]
        },
        "Rule_Type": "Record Data",
        "Sensitivity": "Record",
        "Authorities": [
            {
                "Organization": "CDISC",
                "Standards": [
                    {
                        "Name": "SDTMIG",
                        "Version": "3.4",
                        "References": [
                            {
                                "Origin": "SDTM and SDTMIG Conformance Rules",
                                "Rule_Identifier": {
                                    "Id": "CG0266",
                                    "Version": "1"
                                },
                                "Version": "2.0",
                                "Citations": [
                                    {
                                        "Cited_Guidance": "The version number of the Reference Terminology, if applicable.",
                                        "Document": "IG v3.4",
                                        "Item": "Specification",
                                        "Section": "7.4.2"
                                    }
                                ]
                            }
                        ]
                    }
                ]
            }
        ],
        "Scope": {
            "Classes": {
                "Include": [
                    "TRIAL DESIGN"
                ]
            },
            "Domains": {
                "Include": [
                    "TS"
                ]
            }
        }
    }
}