{
    "id": "175a9981-0d3f-43a5-a885-88854e081f25",
    "changed": "2023-03-02T16:39:49.661Z",
    "content": "Check:\n  all:\n    - name: SEUPDES\n      operator: empty\n    - name: ETCD\n      operator: equal_to\n      value: UNPLAN\nCore:\n  Id: CORE-000256\n  Version: '1'\n  Status: Published\nDescription: Raise an error when ETCD = 'UNPLAN', SEUPDES = null\nOutcome:\n  Message: Missing value for SEUPDES, when ETCD='UNPLAN'\nRule Type: Record Data\nSensitivity: Record\nExecutability: Fully Executable\nAuthorities:\n  - Organization: CDISC\n    Standards:\n      - Name: SDTMIG\n        Version: '3.4'\n        References:\n          - Origin: SDTM and SDTMIG Conformance Rules\n            Rule Identifier:\n              Id: CG0210\n              Version: '1'\n            Version: '2.0'\n            Citations:\n              - Cited Guidance: If the sponsor decides that the subject's experience for a\n                  particular\\ \\ period of time cannot be represented with one of\n                  the planned Elements, then\\ \\ that period of time should be\n                  represented as an unplanned Element. The value\\ \\ of ETCD for\n                  an unplanned Element is \"UNPLAN\" and SEUPDES should\\ \\ be\n                  populated with a description of the unplanned Element.\n                Document: IG v3.4\n                Item: Assumption 4\n                Section: '5.3'\nScope:\n  Classes:\n    Include:\n      - SPECIAL PURPOSE\n  Domains:\n    Include:\n      - SE\n",
    "created": "2021-10-06T19:11:35Z",
    "creator": {
        "id": "76170e05-ed88-410d-8cad-ecd247a9050b"
    },
    "json": {
        "Check": {
            "all": [
                {
                    "name": "SEUPDES",
                    "operator": "empty"
                },
                {
                    "name": "ETCD",
                    "operator": "equal_to",
                    "value": "UNPLAN"
                }
            ]
        },
        "Core": {
            "Id": "CORE-000256",
            "Version": "1",
            "Status": "Published"
        },
        "Description": "Raise an error when ETCD = 'UNPLAN', SEUPDES = null",
        "Outcome": {
            "Message": "Missing value for SEUPDES, when ETCD='UNPLAN'"
        },
        "Sensitivity": "Record",
        "Executability": "Fully Executable",
        "Authorities": [
            {
                "Organization": "CDISC",
                "Standards": [
                    {
                        "Name": "SDTMIG",
                        "Version": "3.4",
                        "References": [
                            {
                                "Origin": "SDTM and SDTMIG Conformance Rules",
                                "Version": "2.0",
                                "Citations": [
                                    {
                                        "Document": "IG v3.4",
                                        "Item": "Assumption 4",
                                        "Section": "5.3",
                                        "Cited_Guidance": "If the sponsor decides that the subject's experience for a particular\\ \\ period of time cannot be represented with one of the planned Elements, then\\ \\ that period of time should be represented as an unplanned Element. The value\\ \\ of ETCD for an unplanned Element is \"UNPLAN\" and SEUPDES should\\ \\ be populated with a description of the unplanned Element."
                                    }
                                ],
                                "Rule_Identifier": {
                                    "Id": "CG0210",
                                    "Version": "1"
                                }
                            }
                        ]
                    }
                ]
            }
        ],
        "Scope": {
            "Classes": {
                "Include": [
                    "SPECIAL PURPOSE"
                ]
            },
            "Domains": {
                "Include": [
                    "SE"
                ]
            }
        },
        "Rule_Type": "Record Data"
    }
}