{
    "id": "cd30ae89-5701-41c4-8e1d-21f1cbf68846",
    "changed": "2022-06-08T20:03:57Z",
    "content": "Check:\n  all:\n    - name: ARMCD\n      operator: non_empty\n    - name: ARMCD\n      operator: is_not_contained_by\n      value: $ta_armcd\nCore:\n  Id: CORE-000155\n  Version: '1'\n  Status: Published\nDescription: Trigger error when ARMCD is populated and ARMCD is not in TA.ARMCD\nOperations:\n  - operator: distinct\n    domain: TA\n    name: ARMCD\n    id: $ta_armcd\nOutcome:\n  Message: ARMCD is not in TA.ARMCD\n  Output Variables:\n    - ARMCD\nRule Type: Record Data\nSensitivity: Record\nAuthorities:\n  - Organization: CDISC\n    Standards:\n      - Name: SDTMIG\n        Version: '3.4'\n        References:\n          - Origin: SDTM and SDTMIG Conformance Rules\n            Rule Identifier:\n              Id: CG0293\n              Version: '1'\n            Version: '2.0'\n            Citations:\n              - Cited Guidance: 2. If the timing of Visits for a trial does not depend\n                  on which ARM a subject is in, then ARMCD should be null.\n                Document: IG v3.4\n                Item: Specification\n                Section: 7.3.1\nScope:\n  Classes:\n    Include:\n      - TRIAL DESIGN\n  Domains:\n    Include:\n      - TV\n",
    "created": "2021-10-17T05:42:59Z",
    "creator": {
        "id": "ff471ff8-f131-4cf5-9712-c79cce6301a1"
    },
    "json": {
        "Check": {
            "all": [
                {
                    "name": "ARMCD",
                    "operator": "non_empty"
                },
                {
                    "name": "ARMCD",
                    "operator": "is_not_contained_by",
                    "value": "$ta_armcd"
                }
            ]
        },
        "Core": {
            "Id": "CORE-000155",
            "Version": "1",
            "Status": "Published"
        },
        "Description": "Trigger error when ARMCD is populated and ARMCD is not in TA.ARMCD",
        "Operations": [
            {
                "operator": "distinct",
                "domain": "TA",
                "name": "ARMCD",
                "id": "$ta_armcd"
            }
        ],
        "Outcome": {
            "Message": "ARMCD is not in TA.ARMCD",
            "Output_Variables": [
                "ARMCD"
            ]
        },
        "Rule_Type": "Record Data",
        "Sensitivity": "Record",
        "Authorities": [
            {
                "Organization": "CDISC",
                "Standards": [
                    {
                        "Name": "SDTMIG",
                        "Version": "3.4",
                        "References": [
                            {
                                "Origin": "SDTM and SDTMIG Conformance Rules",
                                "Rule_Identifier": {
                                    "Id": "CG0293",
                                    "Version": "1"
                                },
                                "Version": "2.0",
                                "Citations": [
                                    {
                                        "Cited_Guidance": "2. If the timing of Visits for a trial does not depend on which ARM a subject is in, then ARMCD should be null.",
                                        "Document": "IG v3.4",
                                        "Item": "Specification",
                                        "Section": "7.3.1"
                                    }
                                ]
                            }
                        ]
                    }
                ]
            }
        ],
        "Scope": {
            "Classes": {
                "Include": [
                    "TRIAL DESIGN"
                ]
            },
            "Domains": {
                "Include": [
                    "TV"
                ]
            }
        }
    }
}