{
    "id": "b88194f7-4c36-421d-a325-d4f8e891eaba",
    "changed": "2022-07-29T08:54:44Z",
    "content": "Check:\n  all:\n    - operator: not_present_on_multiple_rows_within\n      target: RELID\n      within: USUBJID\nCore:\n  Id: CDISC.SDTMIG.CG0200\n  Version: '1'\n  Status: Draft\nDescription: Within a subject, each unique RELID should be present on multiple RELREC\n  records\nOutcome:\n  Message: Unique RELID is NOT present on multiple RELREC records within a subject.\nRule Type: Record Data\nSensitivity: Dataset\nAuthorities:\n  - Organization: CDISC\n    Standards:\n      - Name: SDTMIG\n        Version: '3.4'\n        References:\n          - Origin: SDTM and SDTMIG Conformance Rules\n            Rule Identifier:\n              Id: CG0200\n              Version: '1'\n            Version: '2.0'\n            Citations:\n              - Cited Guidance: All records for the same USUBJID that have the same\n                  RELID are considered \"related/associated.\"\n                Document: IG v3.4\n                Item: Specification\n                Section: 8.2.1\nScope:\n  Classes:\n    Include:\n      - SPECIAL-PURPOSE\n  Domains:\n    Include:\n      - RELREC\n",
    "created": "2021-10-16T07:18:46Z",
    "creator": {
        "id": "ff471ff8-f131-4cf5-9712-c79cce6301a1"
    },
    "json": {
        "Check": {
            "all": [
                {
                    "operator": "not_present_on_multiple_rows_within",
                    "target": "RELID",
                    "within": "USUBJID"
                }
            ]
        },
        "Core": {
            "Id": "CDISC.SDTMIG.CG0200",
            "Version": "1",
            "Status": "Draft"
        },
        "Description": "Within a subject, each unique RELID should be present on multiple RELREC records",
        "Outcome": {
            "Message": "Unique RELID is NOT present on multiple RELREC records within a subject."
        },
        "Rule_Type": "Record Data",
        "Sensitivity": "Dataset",
        "Authorities": [
            {
                "Organization": "CDISC",
                "Standards": [
                    {
                        "Name": "SDTMIG",
                        "Version": "3.4",
                        "References": [
                            {
                                "Origin": "SDTM and SDTMIG Conformance Rules",
                                "Rule_Identifier": {
                                    "Id": "CG0200",
                                    "Version": "1"
                                },
                                "Version": "2.0",
                                "Citations": [
                                    {
                                        "Cited_Guidance": "All records for the same USUBJID that have the same RELID are considered \"related/associated.\"",
                                        "Document": "IG v3.4",
                                        "Item": "Specification",
                                        "Section": "8.2.1"
                                    }
                                ]
                            }
                        ]
                    }
                ]
            }
        ],
        "Scope": {
            "Classes": {
                "Include": [
                    "SPECIAL-PURPOSE"
                ]
            },
            "Domains": {
                "Include": [
                    "RELREC"
                ]
            }
        }
    }
}