{
    "id": "c80fc57f-7eb8-4b0a-944a-afe3047952dc",
    "changed": "2022-05-25T18:04:47Z",
    "content": "Check:\n  all:\n    - name: TAETORD\n      operator: is_not_unique_set\n      value:\n        - ARM\nCore:\n  Id: CORE-000144\n  Version: '1'\n  Status: Published\nDescription: Trigger error when TAETORD is not unique within an ARM\nOutcome:\n  Message: TAETORD is not unique within ARM\n  Output Variables:\n    - TAETORD\n    - ARM\nRule Type: Record Data\nSensitivity: Record\nAuthorities:\n  - Organization: CDISC\n    Standards:\n      - Name: SDTMIG\n        Version: '3.4'\n        References:\n          - Origin: SDTM and SDTMIG Conformance Rules\n            Rule Identifier:\n              Id: CG0247\n              Version: '1'\n            Version: '2.0'\n            Citations:\n              - Cited Guidance: Number that gives the order of the Element within\n                  the Arm.\n                Document: IG v3.4\n                Item: Specification\n                Section: 7.2.1\nScope:\n  Classes:\n    Include:\n      - TRIAL DESIGN\n  Domains:\n    Include:\n      - TA\n",
    "created": "2021-10-17T04:34:32Z",
    "creator": {
        "id": "ff471ff8-f131-4cf5-9712-c79cce6301a1"
    },
    "json": {
        "Check": {
            "all": [
                {
                    "name": "TAETORD",
                    "operator": "is_not_unique_set",
                    "value": [
                        "ARM"
                    ]
                }
            ]
        },
        "Core": {
            "Id": "CORE-000144",
            "Version": "1",
            "Status": "Published"
        },
        "Description": "Trigger error when TAETORD is not unique within an ARM",
        "Outcome": {
            "Message": "TAETORD is not unique within ARM",
            "Output_Variables": [
                "TAETORD",
                "ARM"
            ]
        },
        "Rule_Type": "Record Data",
        "Sensitivity": "Record",
        "Authorities": [
            {
                "Organization": "CDISC",
                "Standards": [
                    {
                        "Name": "SDTMIG",
                        "Version": "3.4",
                        "References": [
                            {
                                "Origin": "SDTM and SDTMIG Conformance Rules",
                                "Rule_Identifier": {
                                    "Id": "CG0247",
                                    "Version": "1"
                                },
                                "Version": "2.0",
                                "Citations": [
                                    {
                                        "Cited_Guidance": "Number that gives the order of the Element within the Arm.",
                                        "Document": "IG v3.4",
                                        "Item": "Specification",
                                        "Section": "7.2.1"
                                    }
                                ]
                            }
                        ]
                    }
                ]
            }
        ],
        "Scope": {
            "Classes": {
                "Include": [
                    "TRIAL DESIGN"
                ]
            },
            "Domains": {
                "Include": [
                    "TA"
                ]
            }
        }
    }
}