{
    "id": "8b4b6d7e-14ff-47ff-b17d-be787ac0caa4",
    "changed": "2022-02-15T21:29:43Z",
    "content": "Check:\n  all:\n    - name: TDANCVAR\n      operator: is_not_contained_by\n      value: '[date variable name in ADSL]'\nCore:\n  Id: CDISC.SDTMIG.CG0375\n  Version: '1'\n  Status: Draft\nDescription: Trigger error when TDANCVAR is not a date variable name in ADSL\nOutcome:\n  Message: TDANCVAR is not valid\nRule Type: Record Data\nSensitivity: Record\nAuthorities:\n  - Organization: CDISC\n    Standards:\n      - Name: SDTMIG\n        Version: '3.4'\n        References:\n          - Origin: SDTM and SDTMIG Conformance Rules\n            Rule Identifier:\n              Id: CG0375\n              Version: '1'\n            Version: '2.0'\n            Citations:\n              - Cited Guidance: 'A reference to the date variable name that provides\n                  the start point from which the planned disease assessment schedule\n                  is measured. This must be referenced from the ADaM ADSL dataset\n                  e.g. ANCH1DT. Note: TDANCVAR is to contain the name of a reference\n                  date variable name.'\n                Document: IG v3.4\n                Item: Specification\n                Section: 7.3.2\nScope:\n  Classes:\n    Include:\n      - TRIAL DESIGN\n  Domains:\n    Include:\n      - TD\n",
    "created": "2021-11-06T09:40:09Z",
    "creator": {
        "id": "ff471ff8-f131-4cf5-9712-c79cce6301a1"
    },
    "json": {
        "Check": {
            "all": [
                {
                    "name": "TDANCVAR",
                    "operator": "is_not_contained_by",
                    "value": "[date variable name in ADSL]"
                }
            ]
        },
        "Core": {
            "Id": "CDISC.SDTMIG.CG0375",
            "Version": "1",
            "Status": "Draft"
        },
        "Description": "Trigger error when TDANCVAR is not a date variable name in ADSL",
        "Outcome": {
            "Message": "TDANCVAR is not valid"
        },
        "Rule_Type": "Record Data",
        "Sensitivity": "Record",
        "Authorities": [
            {
                "Organization": "CDISC",
                "Standards": [
                    {
                        "Name": "SDTMIG",
                        "Version": "3.4",
                        "References": [
                            {
                                "Origin": "SDTM and SDTMIG Conformance Rules",
                                "Rule_Identifier": {
                                    "Id": "CG0375",
                                    "Version": "1"
                                },
                                "Version": "2.0",
                                "Citations": [
                                    {
                                        "Cited_Guidance": "A reference to the date variable name that provides the start point from which the planned disease assessment schedule is measured. This must be referenced from the ADaM ADSL dataset e.g. ANCH1DT. Note: TDANCVAR is to contain the name of a reference date variable name.",
                                        "Document": "IG v3.4",
                                        "Item": "Specification",
                                        "Section": "7.3.2"
                                    }
                                ]
                            }
                        ]
                    }
                ]
            }
        ],
        "Scope": {
            "Classes": {
                "Include": [
                    "TRIAL DESIGN"
                ]
            },
            "Domains": {
                "Include": [
                    "TD"
                ]
            }
        }
    }
}