{
    "id": "83e3f823-3678-4ec0-9553-760ab4e3a195",
    "changed": "2022-12-01T15:40:49.022Z",
    "content": "Check:\n  all:\n    - name: RDEVID\n      operator: non_empty\n    - name: RSUBJID\n      operator: non_empty\nCore:\n  Id: CORE-000234\n  Version: '1'\n  Status: Published\nDescription: Verify that RSUBJID is empty when RDEVID is populated\nOutcome:\n  Message: RSUBJID must be missing when RDEVID is populated\n  Output Variables:\n    - RDEVID\n    - RSUBJID\nRule Type: Record Data\nSensitivity: Record\nAuthorities:\n  - Organization: CDISC\n    Standards:\n      - Name: SDTMIG\n        Version: '3.4'\n        References:\n          - Origin: SDTM and SDTMIG Conformance Rules\n            Rule Identifier:\n              Id: CG0366\n              Version: '1'\n            Version: '2.0'\n            Citations:\n              - Cited Guidance: Associated Persons (AP) are persons other than study\n                  subjects who can be associated with a study, a particular study\n                  subject, or a device used in the study.\n                Document: Model v2.0\n                Item: ' '\n                Section: Associated Persons\nScope:\n  Classes:\n    Include:\n      - ALL\n  Domains:\n    Include:\n      - AP--\n",
    "created": "2021-12-15T16:41:46Z",
    "creator": {
        "id": "57474fac-237e-4693-bb37-7826b02737da"
    },
    "json": {
        "Check": {
            "all": [
                {
                    "name": "RDEVID",
                    "operator": "non_empty"
                },
                {
                    "name": "RSUBJID",
                    "operator": "non_empty"
                }
            ]
        },
        "Core": {
            "Id": "CORE-000234",
            "Version": "1",
            "Status": "Published"
        },
        "Description": "Verify that RSUBJID is empty when RDEVID is populated",
        "Outcome": {
            "Message": "RSUBJID must be missing when RDEVID is populated",
            "Output_Variables": [
                "RDEVID",
                "RSUBJID"
            ]
        },
        "Rule_Type": "Record Data",
        "Sensitivity": "Record",
        "Authorities": [
            {
                "Organization": "CDISC",
                "Standards": [
                    {
                        "Name": "SDTMIG",
                        "Version": "3.4",
                        "References": [
                            {
                                "Origin": "SDTM and SDTMIG Conformance Rules",
                                "Rule_Identifier": {
                                    "Id": "CG0366",
                                    "Version": "1"
                                },
                                "Version": "2.0",
                                "Citations": [
                                    {
                                        "Cited_Guidance": "Associated Persons (AP) are persons other than study subjects who can be associated with a study, a particular study subject, or a device used in the study.",
                                        "Document": "Model v2.0",
                                        "Item": " ",
                                        "Section": "Associated Persons"
                                    }
                                ]
                            }
                        ]
                    }
                ]
            }
        ],
        "Scope": {
            "Classes": {
                "Include": [
                    "ALL"
                ]
            },
            "Domains": {
                "Include": [
                    "AP--"
                ]
            }
        }
    }
}