{
    "id": "3ae92f3e-5434-4fac-be65-6fd900218a90",
    "changed": "2022-03-05T07:25:37Z",
    "content": "Check:\n  all:\n    - name: TRDIR\n      operator: exists\nCore:\n  Id: CORE-000077\n  Version: '1'\n  Status: Published\nDescription: Raise an error when TRDIR is present.\nOutcome:\n  Message: TRDIR is present.\nRule Type: Record Data\nSensitivity: Dataset\nAuthorities:\n  - Organization: CDISC\n    Standards:\n      - Name: SDTMIG\n        Version: '3.4'\n        References:\n          - Origin: SDTM and SDTMIG Conformance Rules\n            Rule Identifier:\n              Id: CG0301\n              Version: '1'\n            Version: '2.0'\n            Citations:\n              - Cited Guidance: The TR domain does not include anatomical location\n                  information on each measurement/assessment record, because this\n                  would be a duplication of information already represented in TU.\n                  The multi-domain approach to representing oncology assessment data\n                  was developed largely to reduce duplication of stored information.\n                Document: SDTMIG v3.4\n                Section: 6.3.12.2\nScope:\n  Classes:\n    Include:\n      - FINDINGS\n  Domains:\n    Include:\n      - TR\n",
    "created": "2021-10-04T05:33:10Z",
    "creator": {
        "id": "ff471ff8-f131-4cf5-9712-c79cce6301a1"
    },
    "json": {
        "Check": {
            "all": [
                {
                    "name": "TRDIR",
                    "operator": "exists"
                }
            ]
        },
        "Core": {
            "Id": "CORE-000077",
            "Version": "1",
            "Status": "Published"
        },
        "Description": "Raise an error when TRDIR is present.",
        "Outcome": {
            "Message": "TRDIR is present."
        },
        "Rule_Type": "Record Data",
        "Sensitivity": "Dataset",
        "Authorities": [
            {
                "Organization": "CDISC",
                "Standards": [
                    {
                        "Name": "SDTMIG",
                        "Version": "3.4",
                        "References": [
                            {
                                "Origin": "SDTM and SDTMIG Conformance Rules",
                                "Rule_Identifier": {
                                    "Id": "CG0301",
                                    "Version": "1"
                                },
                                "Version": "2.0",
                                "Citations": [
                                    {
                                        "Cited_Guidance": "The TR domain does not include anatomical location information on each measurement/assessment record, because this would be a duplication of information already represented in TU. The multi-domain approach to representing oncology assessment data was developed largely to reduce duplication of stored information.",
                                        "Document": "SDTMIG v3.4",
                                        "Section": "6.3.12.2"
                                    }
                                ]
                            }
                        ]
                    }
                ]
            }
        ],
        "Scope": {
            "Classes": {
                "Include": [
                    "FINDINGS"
                ]
            },
            "Domains": {
                "Include": [
                    "TR"
                ]
            }
        }
    }
}