{
    "id": "6385802f-3a8c-4aae-aad6-d0022d66ccc8",
    "changed": "2022-10-12T20:52:03.713Z",
    "content": "Check:\n  all:\n    - name: $valid_hierarchy\n      operator: equal_to\n      value: true\nOperations:\n  - id: $valid_hierarchy\n    operator: valid_meddra_code_references\nCore:\n  Id: QC.CDISC.SDTMIG.CG0377\n  Version: '1'\n  Status: Draft\nDescription: Trigger error when --LLT  is not a valid MedDRA lowest level TERM\nOutcome:\n  Message: --LLT is not a valid MedDRA lowest level TERM\nRule Type: Record Data\nSensitivity: Record\nAuthorities:\n  - Organization: CDISC\n    Standards:\n      - Name: SDTMIG\n        Version: '3.4'\n        References:\n          - Origin: SDTM and SDTMIG Conformance Rules\n            Rule Identifier:\n              Id: CG0377\n              Version: '1'\n            Version: '2.0'\n            Citations:\n              - Cited Guidance: The lowest-level term assigned to the event from MedDRA.\n                Document: Model v2.0\n                Item: --LLT\n                Section: Events\nScope:\n  Classes:\n    Include:\n      - EVENTS\n  Domains:\n    Include:\n      - AE\n      - MH\n      - CE\n",
    "created": "2021-09-29T11:07:43Z",
    "creator": {
        "id": "b5bc818b-4ec4-4952-951f-0fbca010be52"
    },
    "json": {
        "Check": {
            "all": [
                {
                    "name": "$valid_hierarchy",
                    "operator": "equal_to",
                    "value": true
                }
            ]
        },
        "Operations": [
            {
                "id": "$valid_hierarchy",
                "operator": "valid_meddra_code_references"
            }
        ],
        "Core": {
            "Id": "QC.CDISC.SDTMIG.CG0377",
            "Version": "1",
            "Status": "Draft"
        },
        "Description": "Trigger error when --LLT  is not a valid MedDRA lowest level TERM",
        "Outcome": {
            "Message": "--LLT is not a valid MedDRA lowest level TERM"
        },
        "Rule_Type": "Record Data",
        "Sensitivity": "Record",
        "Authorities": [
            {
                "Organization": "CDISC",
                "Standards": [
                    {
                        "Name": "SDTMIG",
                        "Version": "3.4",
                        "References": [
                            {
                                "Origin": "SDTM and SDTMIG Conformance Rules",
                                "Rule_Identifier": {
                                    "Id": "CG0377",
                                    "Version": "1"
                                },
                                "Version": "2.0",
                                "Citations": [
                                    {
                                        "Cited_Guidance": "The lowest-level term assigned to the event from MedDRA.",
                                        "Document": "Model v2.0",
                                        "Item": "--LLT",
                                        "Section": "Events"
                                    }
                                ]
                            }
                        ]
                    }
                ]
            }
        ],
        "Scope": {
            "Classes": {
                "Include": [
                    "EVENTS"
                ]
            },
            "Domains": {
                "Include": [
                    "AE",
                    "MH",
                    "CE"
                ]
            }
        }
    }
}