{
    "id": "3d4f0870-46fc-4aec-ab5f-11d1986cfb39",
    "changed": "2022-02-15T21:27:33Z",
    "content": "Check:\n  all:\n    - name: --BODSYS\n      operator: is_contained_by\n      value:\n        - MedDRA system organ class\nCore:\n  Id: CDISC.SDTMIG.CG0385\n  Version: '1'\n  Status: Draft\nDescription: Trigger error when --BODSYS  is not a valid MedDRA system organ class\nOutcome:\n  Message: --BODSYS  is not a valid MedDRA system organ class\nRule Type: Record Data\nSensitivity: Record\nAuthorities:\n  - Organization: CDISC\n    Standards:\n      - Name: SDTMIG\n        Version: '3.4'\n        References:\n          - Origin: SDTM and SDTMIG Conformance Rules\n            Rule Identifier:\n              Id: CG0385\n              Version: '1'\n            Version: '2.0'\n            Citations:\n              - Cited Guidance: A standardized or dictionary derived name for the\n                  body system or organ class. Body system or system organ class assigned\n                  for analysis from a standard hierarchy (e.g., MedDRA) associated\n                  with an event.\n                Document: Model v2.0\n                Item: --BODSYS\n                Section: Events\nScope:\n  Classes:\n    Include:\n      - EVENTS\n  Domains:\n    Include:\n      - AE\n      - MH\n      - CE\n",
    "created": "2021-11-06T09:24:32Z",
    "creator": {
        "id": "ff471ff8-f131-4cf5-9712-c79cce6301a1"
    },
    "json": {
        "Check": {
            "all": [
                {
                    "name": "--BODSYS",
                    "operator": "is_contained_by",
                    "value": [
                        "MedDRA system organ class"
                    ]
                }
            ]
        },
        "Core": {
            "Id": "CDISC.SDTMIG.CG0385",
            "Version": "1",
            "Status": "Draft"
        },
        "Description": "Trigger error when --BODSYS  is not a valid MedDRA system organ class",
        "Outcome": {
            "Message": "--BODSYS  is not a valid MedDRA system organ class"
        },
        "Rule_Type": "Record Data",
        "Sensitivity": "Record",
        "Authorities": [
            {
                "Organization": "CDISC",
                "Standards": [
                    {
                        "Name": "SDTMIG",
                        "Version": "3.4",
                        "References": [
                            {
                                "Origin": "SDTM and SDTMIG Conformance Rules",
                                "Rule_Identifier": {
                                    "Id": "CG0385",
                                    "Version": "1"
                                },
                                "Version": "2.0",
                                "Citations": [
                                    {
                                        "Cited_Guidance": "A standardized or dictionary derived name for the body system or organ class. Body system or system organ class assigned for analysis from a standard hierarchy (e.g., MedDRA) associated with an event.",
                                        "Document": "Model v2.0",
                                        "Item": "--BODSYS",
                                        "Section": "Events"
                                    }
                                ]
                            }
                        ]
                    }
                ]
            }
        ],
        "Scope": {
            "Classes": {
                "Include": [
                    "EVENTS"
                ]
            },
            "Domains": {
                "Include": [
                    "AE",
                    "MH",
                    "CE"
                ]
            }
        }
    }
}