{
    "id": "3e3580bc-e5ea-4ce5-a969-1e4218c10a1d",
    "changed": "2022-02-15T21:27:35Z",
    "content": "Check:\n  all:\n    - name:\n      operator:\n    - name: QNAM\n      operator: is_contained_by\n      value:\n        - Model List of Allowed Variables for Observation Class\nCore:\n  Id: CDISC.SDTMIG.CG0351\n  Version: '1'\n  Status: Draft\nDescription: Trigger error when a variable in Model List of Allowed Variables for\n  Observation Class is in SUPPQUAL\nOutcome:\n  Message: Variable within SUPPQUAL is in Model List of Allowed Variables for Observation\n    Class\nRule Type: Record Data\nSensitivity: Value\nAuthorities:\n  - Organization: CDISC\n    Standards:\n      - Name: SDTMIG\n        Version: '3.4'\n        References:\n          - Origin: SDTM and SDTMIG Conformance Rules\n            Rule Identifier:\n              Id: CG0351\n              Version: '1'\n            Version: '2.0'\n            Citations:\n              - Cited Guidance: Using SDTM-specified standard variable names\n                Document: IG v3.2\n                Item:\n                Section: 3.2.2\nScope:\n  Classes:\n    Include:\n      - ALL\n  Domains:\n    Include:\n      - ALL\n",
    "created": "2021-11-06T08:52:39Z",
    "creator": {
        "id": "ff471ff8-f131-4cf5-9712-c79cce6301a1"
    },
    "json": {
        "Check": {
            "all": [
                {
                    "name": null,
                    "operator": null
                },
                {
                    "name": "QNAM",
                    "operator": "is_contained_by",
                    "value": [
                        "Model List of Allowed Variables for Observation Class"
                    ]
                }
            ]
        },
        "Core": {
            "Id": "CDISC.SDTMIG.CG0351",
            "Version": "1",
            "Status": "Draft"
        },
        "Description": "Trigger error when a variable in Model List of Allowed Variables for Observation Class is in SUPPQUAL",
        "Outcome": {
            "Message": "Variable within SUPPQUAL is in Model List of Allowed Variables for Observation Class"
        },
        "Rule_Type": "Record Data",
        "Sensitivity": "Value",
        "Authorities": [
            {
                "Organization": "CDISC",
                "Standards": [
                    {
                        "Name": "SDTMIG",
                        "Version": "3.4",
                        "References": [
                            {
                                "Origin": "SDTM and SDTMIG Conformance Rules",
                                "Rule_Identifier": {
                                    "Id": "CG0351",
                                    "Version": "1"
                                },
                                "Version": "2.0",
                                "Citations": [
                                    {
                                        "Cited_Guidance": "Using SDTM-specified standard variable names",
                                        "Document": "IG v3.2",
                                        "Item": null,
                                        "Section": "3.2.2"
                                    }
                                ]
                            }
                        ]
                    }
                ]
            }
        ],
        "Scope": {
            "Classes": {
                "Include": [
                    "ALL"
                ]
            },
            "Domains": {
                "Include": [
                    "ALL"
                ]
            }
        }
    }
}