{
    "id": "f28250d5-a762-4dc5-ad29-21b6eba0df9e",
    "changed": "2022-09-29T08:52:50.217Z",
    "content": "Check:\n  all:\n    - name: IDVAR\n      operator: is_valid_reference\n      context: RDOMAIN\nCore:\n  Id: CDISC.SDTMIG.CG0370\n  Version: '1'\n  Status: Draft\nDescription: When IDVAR is populated, IDVAR must be a valid variable in the domain\n  referenced by RDOMAIN.\nOutcome:\n  Message: IDVAR does not represent a variable present in the dataset identified in\n    RDOMAIN\n  Output Variables:\n    - RDOMAIN\n    - USUBJID\n    - IDVAR\nRule Type: Record Data\nSensitivity: Record\nAuthorities:\n  - Organization: CDISC\n    Standards:\n      - Name: SDTMIG\n        Version: '3.4'\n        References:\n          - Origin: SDTM and SDTMIG Conformance Rules\n            Rule Identifier:\n              Id: CG0370\n              Version: '1'\n            Version: '2.0'\n            Citations:\n              - Cited Guidance: Identifying variable in the parent dataset that identifies\n                  the record(s) to which the comment applies.\n                Document: Model v2.0\n                Item: IDVAR\n                Section: Comments\n              - Cited Guidance: Name of the identifying variable in the general-observation-class\n                  dataset that identifies the related record(s).\n                Document: Model v2.0\n                Item: IDVAR\n                Section: Supplemental Qualifiers\n              - Cited Guidance: Name of the  identifying variable in the general-observation-class\n                  dataset that identifies the related record(s).\n                Document: Model v2.0\n                Item: IDVAR\n                Section: Related Records\nScope:\n  Classes:\n    Include:\n      - SPECIAL-PURPOSE\n  Domains:\n    Include:\n      - CO\n      - SUPP--\n      - RELREC\n",
    "created": "2021-11-06T09:49:24Z",
    "creator": {
        "id": "ff471ff8-f131-4cf5-9712-c79cce6301a1"
    },
    "json": {
        "Check": {
            "all": [
                {
                    "name": "IDVAR",
                    "operator": "is_valid_reference",
                    "context": "RDOMAIN"
                }
            ]
        },
        "Core": {
            "Id": "CDISC.SDTMIG.CG0370",
            "Version": "1",
            "Status": "Draft"
        },
        "Description": "When IDVAR is populated, IDVAR must be a valid variable in the domain referenced by RDOMAIN.",
        "Outcome": {
            "Message": "IDVAR does not represent a variable present in the dataset identified in RDOMAIN",
            "Output_Variables": [
                "RDOMAIN",
                "USUBJID",
                "IDVAR"
            ]
        },
        "Rule_Type": "Record Data",
        "Sensitivity": "Record",
        "Authorities": [
            {
                "Organization": "CDISC",
                "Standards": [
                    {
                        "Name": "SDTMIG",
                        "Version": "3.4",
                        "References": [
                            {
                                "Origin": "SDTM and SDTMIG Conformance Rules",
                                "Rule_Identifier": {
                                    "Id": "CG0370",
                                    "Version": "1"
                                },
                                "Version": "2.0",
                                "Citations": [
                                    {
                                        "Cited_Guidance": "Identifying variable in the parent dataset that identifies the record(s) to which the comment applies.",
                                        "Document": "Model v2.0",
                                        "Item": "IDVAR",
                                        "Section": "Comments"
                                    },
                                    {
                                        "Cited_Guidance": "Name of the identifying variable in the general-observation-class dataset that identifies the related record(s).",
                                        "Document": "Model v2.0",
                                        "Item": "IDVAR",
                                        "Section": "Supplemental Qualifiers"
                                    },
                                    {
                                        "Cited_Guidance": "Name of the  identifying variable in the general-observation-class dataset that identifies the related record(s).",
                                        "Document": "Model v2.0",
                                        "Item": "IDVAR",
                                        "Section": "Related Records"
                                    }
                                ]
                            }
                        ]
                    }
                ]
            }
        ],
        "Scope": {
            "Classes": {
                "Include": [
                    "SPECIAL-PURPOSE"
                ]
            },
            "Domains": {
                "Include": [
                    "CO",
                    "SUPP--",
                    "RELREC"
                ]
            }
        }
    }
}