{
    "id": "88b13865-3b8a-41ba-abc5-85d7db72dd5c",
    "changed": "2022-03-24T08:40:00Z",
    "content": "Check:\n  all:\n    - name: AESMIE\n      operator: non_empty\n    - name: AESMIE\n      operator: is_not_contained_by\n      value:\n        - Y\n        - N\nCore:\n  Id: CORE-000130\n  Version: '1'\n  Status: Published\nDescription: Raise an error when AESMIE is completed and value is not 'Y' or 'N'\nOutcome:\n  Message: AESMIE is completed, but not equal to \"N\" or \"Y\"\n  Output Variables:\n    - AESMIE\nRule Type: Record Data\nSensitivity: Record\nAuthorities:\n  - Organization: CDISC\n    Standards:\n      - Name: SDTMIG\n        Version: '3.4'\n        References:\n          - Origin: SDTM and SDTMIG Conformance Rules\n            Rule Identifier:\n              Id: CG0395\n              Version: '1'\n            Version: '2.0'\n            Citations:\n              - Cited Guidance: Valid values are \"Y\" and \"N\" and null.\n                Document: Model v2.0\n                Item: --SMIE\n                Section: Events\nScope:\n  Classes:\n    Include:\n      - EVENTS\n  Domains:\n    Include:\n      - AE\n",
    "created": "2021-10-12T10:10:26Z",
    "creator": {
        "id": "ae6dbbf3-4c9a-4149-b596-8183766167d4"
    },
    "json": {
        "Check": {
            "all": [
                {
                    "name": "AESMIE",
                    "operator": "non_empty"
                },
                {
                    "name": "AESMIE",
                    "operator": "is_not_contained_by",
                    "value": [
                        "Y",
                        "N"
                    ]
                }
            ]
        },
        "Core": {
            "Id": "CORE-000130",
            "Version": "1",
            "Status": "Published"
        },
        "Description": "Raise an error when AESMIE is completed and value is not 'Y' or 'N'",
        "Outcome": {
            "Message": "AESMIE is completed, but not equal to \"N\" or \"Y\"",
            "Output_Variables": [
                "AESMIE"
            ]
        },
        "Rule_Type": "Record Data",
        "Sensitivity": "Record",
        "Authorities": [
            {
                "Organization": "CDISC",
                "Standards": [
                    {
                        "Name": "SDTMIG",
                        "Version": "3.4",
                        "References": [
                            {
                                "Origin": "SDTM and SDTMIG Conformance Rules",
                                "Rule_Identifier": {
                                    "Id": "CG0395",
                                    "Version": "1"
                                },
                                "Version": "2.0",
                                "Citations": [
                                    {
                                        "Cited_Guidance": "Valid values are \"Y\" and \"N\" and null.",
                                        "Document": "Model v2.0",
                                        "Item": "--SMIE",
                                        "Section": "Events"
                                    }
                                ]
                            }
                        ]
                    }
                ]
            }
        ],
        "Scope": {
            "Classes": {
                "Include": [
                    "EVENTS"
                ]
            },
            "Domains": {
                "Include": [
                    "AE"
                ]
            }
        }
    }
}