{
    "id": "919a2f2e-ab2c-477a-aa46-e43d816970de",
    "changed": "2022-04-04T13:16:27Z",
    "content": "Check:\n  all:\n    - any:\n        - name: --ORRES\n          operator: non_empty\n        - name: --DRVFL\n          operator: equal_to\n          value: Y\n    - all:\n        - name: --STRESC\n          operator: empty\nCore:\n  Id: CORE-000021\n  Version: '1'\n  Status: Published\nDescription: Raise an error when the value for --STRESC is null.\nOutcome:\n  Message: --STRESC should not be blank when either --ORRES is provided or --DRVFL\n    = 'Y' .\n  Output Variables:\n    - --ORRES\n    - --DRVFL\n    - --STRESC\nRule Type: Record Data\nSensitivity: Record\nAuthorities:\n  - Organization: CDISC\n    Standards:\n      - Name: SDTMIG\n        Version: '3.4'\n        References:\n          - Origin: SDTM and SDTMIG Conformance Rules\n            Rule Identifier:\n              Id: CG0397\n              Version: '1'\n            Version: '2.0'\n            Citations:\n              - Cited Guidance: Model v2.0[Findings][The standardized result of the\n                  measurement, test, or examination in character format. --STRESC\n                  should store all results or findings in character format; if results\n                  are numeric, they should also be stored in numeric format in --STRESN.\n                  If various tests have results \"NONE\", \"NEG\", and \"NEGATIVE\" in --ORRES\n                  and these results effectively have the same meaning, they could\n                  be represented in standard format in --STRESC as \"NEGATIVE\".]|IG\n                  v3.4[6.3.5.3][Contains the result value for all findings, copied\n                  or derived from LBORRES in a standard format or standard units.]\n                Document: Model v2.0|IG v3.4\n                Section: Findings|6.3.5.3\n                Item: Specification\nScope:\n  Classes:\n    Include:\n      - FINDINGS\n  Domains:\n    Include:\n      - ALL\n",
    "created": "2021-09-29T10:35:56Z",
    "creator": {
        "id": "c2ea3586-26ef-4d9f-a8d5-a76a58005ea9"
    },
    "json": {
        "Check": {
            "all": [
                {
                    "any": [
                        {
                            "name": "--ORRES",
                            "operator": "non_empty"
                        },
                        {
                            "name": "--DRVFL",
                            "operator": "equal_to",
                            "value": "Y"
                        }
                    ]
                },
                {
                    "all": [
                        {
                            "name": "--STRESC",
                            "operator": "empty"
                        }
                    ]
                }
            ]
        },
        "Core": {
            "Id": "CORE-000021",
            "Version": "1",
            "Status": "Published"
        },
        "Description": "Raise an error when the value for --STRESC is null.",
        "Outcome": {
            "Message": "--STRESC should not be blank when either --ORRES is provided or --DRVFL = 'Y' .",
            "Output_Variables": [
                "--ORRES",
                "--DRVFL",
                "--STRESC"
            ]
        },
        "Rule_Type": "Record Data",
        "Sensitivity": "Record",
        "Authorities": [
            {
                "Organization": "CDISC",
                "Standards": [
                    {
                        "Name": "SDTMIG",
                        "Version": "3.4",
                        "References": [
                            {
                                "Origin": "SDTM and SDTMIG Conformance Rules",
                                "Rule_Identifier": {
                                    "Id": "CG0397",
                                    "Version": "1"
                                },
                                "Version": "2.0",
                                "Citations": [
                                    {
                                        "Cited_Guidance": "Model v2.0[Findings][The standardized result of the measurement, test, or examination in character format. --STRESC should store all results or findings in character format; if results are numeric, they should also be stored in numeric format in --STRESN. If various tests have results \"NONE\", \"NEG\", and \"NEGATIVE\" in --ORRES and these results effectively have the same meaning, they could be represented in standard format in --STRESC as \"NEGATIVE\".]|IG v3.4[6.3.5.3][Contains the result value for all findings, copied or derived from LBORRES in a standard format or standard units.]",
                                        "Document": "Model v2.0|IG v3.4",
                                        "Section": "Findings|6.3.5.3",
                                        "Item": "Specification"
                                    }
                                ]
                            }
                        ]
                    }
                ]
            }
        ],
        "Scope": {
            "Classes": {
                "Include": [
                    "FINDINGS"
                ]
            },
            "Domains": {
                "Include": [
                    "ALL"
                ]
            }
        }
    }
}