{
    "id": "2f48d438-b498-4ef7-8093-7e9f75d44564",
    "changed": "2022-04-04T13:13:56Z",
    "content": "Check:\n  all:\n    - any:\n        - name: --STAT\n          operator: empty\n        - name: --DRVFL\n          operator: not_equal_to\n          value: Y\n    - all:\n        - name: --ORRES\n          operator: empty\nCore:\n  Id: CORE-000200\n  Version: '1'\n  Status: Published\nDescription: Verify that --ORRES is not missing when either --STAT is null or --DRVFL\n  not equal to 'Y'\nOutcome:\n  Message: --ORRES cannot be null when --STAT is null or --DRVFL not equal to 'Y'\n  Output Variables:\n    - --STAT\n    - --DRVFL\n    - --ORRES\nRule Type: Record Data\nSensitivity: Value\nAuthorities:\n  - Organization: CDISC\n    Standards:\n      - Name: SDTMIG\n        Version: '3.4'\n        References:\n          - Origin: SDTM and SDTMIG Conformance Rules\n            Rule Identifier:\n              Id: CG0348\n              Version: '1'\n            Version: '2.0'\n            Citations:\n              - Cited Guidance: \"--ORRES variable contains the result of the measurement\\\n                  \\ or finding as originally received or collected.  --ORRES is an\\\n                  \\ expected variable and should always be populated, with two exceptions':'\\\n                  \\ When --STAT = \\\"NOT DONE\\\" since there is no result for such a\\\n                  \\ record When --DRVFL = \\\"Y\\\" since the distinction between an original\\\n                  \\ result and a standard result is not applicable for records for\\\n                  \\ which --DRVFL = \\\"Y\\\" \"\n                Document: IG v3.4\n                Item: '    '\n                Section: 4.5.1.1\nScope:\n  Classes:\n    Include:\n      - FINDINGS\n  Domains:\n    Include:\n      - ALL\n",
    "created": "2021-11-05T14:30:35Z",
    "creator": {
        "id": "57474fac-237e-4693-bb37-7826b02737da"
    },
    "json": {
        "Check": {
            "all": [
                {
                    "any": [
                        {
                            "name": "--STAT",
                            "operator": "empty"
                        },
                        {
                            "name": "--DRVFL",
                            "operator": "not_equal_to",
                            "value": "Y"
                        }
                    ]
                },
                {
                    "all": [
                        {
                            "name": "--ORRES",
                            "operator": "empty"
                        }
                    ]
                }
            ]
        },
        "Core": {
            "Id": "CORE-000200",
            "Version": "1",
            "Status": "Published"
        },
        "Description": "Verify that --ORRES is not missing when either --STAT is null or --DRVFL not equal to 'Y'",
        "Outcome": {
            "Message": "--ORRES cannot be null when --STAT is null or --DRVFL not equal to 'Y'",
            "Output_Variables": [
                "--STAT",
                "--DRVFL",
                "--ORRES"
            ]
        },
        "Rule_Type": "Record Data",
        "Sensitivity": "Value",
        "Authorities": [
            {
                "Organization": "CDISC",
                "Standards": [
                    {
                        "Name": "SDTMIG",
                        "Version": "3.4",
                        "References": [
                            {
                                "Origin": "SDTM and SDTMIG Conformance Rules",
                                "Rule_Identifier": {
                                    "Id": "CG0348",
                                    "Version": "1"
                                },
                                "Version": "2.0",
                                "Citations": [
                                    {
                                        "Cited_Guidance": "--ORRES variable contains the result of the measurement or finding as originally received or collected.  --ORRES is an expected variable and should always be populated, with two exceptions':' When --STAT = \"NOT DONE\" since there is no result for such a record When --DRVFL = \"Y\" since the distinction between an original result and a standard result is not applicable for records for which --DRVFL = \"Y\" ",
                                        "Document": "IG v3.4",
                                        "Item": "    ",
                                        "Section": "4.5.1.1"
                                    }
                                ]
                            }
                        ]
                    }
                ]
            }
        ],
        "Scope": {
            "Classes": {
                "Include": [
                    "FINDINGS"
                ]
            },
            "Domains": {
                "Include": [
                    "ALL"
                ]
            }
        }
    }
}