{
    "id": "a71094a1-cd41-40d2-ab2d-db392ece4c15",
    "changed": "2022-03-14T20:05:29Z",
    "content": "Check:\n  all:\n    - name: TEENRL\n      operator: empty\n    - name: TEDUR\n      operator: empty\nCore:\n  Id: CORE-000194\n  Version: '1'\n  Status: Published\nDescription: Raise an error if TEDUR is null when TEENRL is null\nOutcome:\n  Message: TEDUR cannot be null when TEENRL is null\n  Output Variables:\n    - TEENRL\n    - TEDUR\nRule Type: Record Data\nSensitivity: Record\nAuthorities:\n  - Organization: CDISC\n    Standards:\n      - Name: SDTMIG\n        Version: '3.4'\n        References:\n          - Origin: SDTM and SDTMIG Conformance Rules\n            Rule Identifier:\n              Id: CG0329\n              Version: '1'\n            Version: '2.0'\n            Citations:\n              - Cited Guidance: Either TEENRL or TEDUR must be populated for each\n                  Element.\n                Document: IG v3.4\n                Item: Specification\n                Section: 7.2.2\n              - Cited Guidance: At least one of TEENRL and TEDUR must be populated.\n                  Both may be populated.\n                Document: IG v3.4\n                Item: Assumption 12\n                Section: 7.2.2\nScope:\n  Classes:\n    Include:\n      - TRIAL DESIGN\n  Domains:\n    Include:\n      - TE\n",
    "created": "2021-11-03T17:20:49Z",
    "creator": {
        "id": "57474fac-237e-4693-bb37-7826b02737da"
    },
    "json": {
        "Check": {
            "all": [
                {
                    "name": "TEENRL",
                    "operator": "empty"
                },
                {
                    "name": "TEDUR",
                    "operator": "empty"
                }
            ]
        },
        "Core": {
            "Id": "CORE-000194",
            "Version": "1",
            "Status": "Published"
        },
        "Description": "Raise an error if TEDUR is null when TEENRL is null",
        "Outcome": {
            "Message": "TEDUR cannot be null when TEENRL is null",
            "Output_Variables": [
                "TEENRL",
                "TEDUR"
            ]
        },
        "Rule_Type": "Record Data",
        "Sensitivity": "Record",
        "Authorities": [
            {
                "Organization": "CDISC",
                "Standards": [
                    {
                        "Name": "SDTMIG",
                        "Version": "3.4",
                        "References": [
                            {
                                "Origin": "SDTM and SDTMIG Conformance Rules",
                                "Rule_Identifier": {
                                    "Id": "CG0329",
                                    "Version": "1"
                                },
                                "Version": "2.0",
                                "Citations": [
                                    {
                                        "Cited_Guidance": "Either TEENRL or TEDUR must be populated for each Element.",
                                        "Document": "IG v3.4",
                                        "Item": "Specification",
                                        "Section": "7.2.2"
                                    },
                                    {
                                        "Cited_Guidance": "At least one of TEENRL and TEDUR must be populated. Both may be populated.",
                                        "Document": "IG v3.4",
                                        "Item": "Assumption 12",
                                        "Section": "7.2.2"
                                    }
                                ]
                            }
                        ]
                    }
                ]
            }
        ],
        "Scope": {
            "Classes": {
                "Include": [
                    "TRIAL DESIGN"
                ]
            },
            "Domains": {
                "Include": [
                    "TE"
                ]
            }
        }
    }
}