{
    "id": "60ed12e8-a863-4ba9-8404-47f5d7b5168e",
    "changed": "2022-03-16T13:30:46Z",
    "content": "Check:\n  all:\n    - name: variable_name\n      operator: longer_than\n      value: 8\nCore:\n  Id: CORE-000182\n  Version: '1'\n  Status: Published\nDescription: Raise an error when variable name length is greater than 8.\nOutcome:\n  Message: Variable name length is greater than 8.\nRule Type: Variable Metadata Check\nSensitivity: Variable\nAuthorities:\n  - Organization: CDISC\n    Standards:\n      - Name: SDTMIG\n        Version: '3.4'\n        References:\n          - Origin: SDTM and SDTMIG Conformance Rules\n            Rule Identifier:\n              Id: CG0310\n              Version: '1'\n            Version: '2.0'\n            Citations:\n              - Cited Guidance: In some cases, the standard variable name will be\n                  shortened to meet the 8-character variable name requirement...\n                Document: IG v3.4\n                Section: 4.2.8.3\nScope:\n  Classes:\n    Include:\n      - ALL\n  Domains:\n    Include:\n      - ALL\n",
    "created": "2021-10-28T14:30:47Z",
    "creator": {
        "id": "76170e05-ed88-410d-8cad-ecd247a9050b"
    },
    "json": {
        "Check": {
            "all": [
                {
                    "name": "variable_name",
                    "operator": "longer_than",
                    "value": 8
                }
            ]
        },
        "Core": {
            "Id": "CORE-000182",
            "Version": "1",
            "Status": "Published"
        },
        "Description": "Raise an error when variable name length is greater than 8.",
        "Outcome": {
            "Message": "Variable name length is greater than 8."
        },
        "Rule_Type": "Variable Metadata Check",
        "Sensitivity": "Variable",
        "Authorities": [
            {
                "Organization": "CDISC",
                "Standards": [
                    {
                        "Name": "SDTMIG",
                        "Version": "3.4",
                        "References": [
                            {
                                "Origin": "SDTM and SDTMIG Conformance Rules",
                                "Rule_Identifier": {
                                    "Id": "CG0310",
                                    "Version": "1"
                                },
                                "Version": "2.0",
                                "Citations": [
                                    {
                                        "Cited_Guidance": "In some cases, the standard variable name will be shortened to meet the 8-character variable name requirement...",
                                        "Document": "IG v3.4",
                                        "Section": "4.2.8.3"
                                    }
                                ]
                            }
                        ]
                    }
                ]
            }
        ],
        "Scope": {
            "Classes": {
                "Include": [
                    "ALL"
                ]
            },
            "Domains": {
                "Include": [
                    "ALL"
                ]
            }
        }
    }
}