{
    "id": "897681c6-b14e-416d-85b5-93c4ba806c94",
    "changed": "2022-03-21T12:33:15Z",
    "content": "Check:\n  all:\n    - name: DOMAIN\n      operator: starts_with\n      value: AP\n    - name: DOMAIN\n      operator: has_not_equal_length\n      value: 4\nCore:\n  Id: CORE-000181\n  Version: '1'\n  Status: Published\nDescription: Raise an error when AP-- domain value length is not equal to 4.\nOutcome:\n  Message: AP-- Domain value length is not equal to 4.\nRule Type: Record Data\nSensitivity: Domain\nAuthorities:\n  - Organization: CDISC\n    Standards:\n      - Name: SDTMIG\n        Version: '3.4'\n        References:\n          - Origin: SDTM and SDTMIG Conformance Rules\n            Rule Identifier:\n              Id: CG0309\n              Version: '1'\n            Version: '2.0'\n            Citations:\n              - Cited Guidance: Each domain dataset is distinguished by a unique,\n                  two-character code\n                Document: IG v3.4\n                Section: '2.2'\nScope:\n  Classes:\n    Include:\n      - ALL\n  Domains:\n    Include:\n      - ALL\n",
    "created": "2021-10-28T14:30:15Z",
    "creator": {
        "id": "76170e05-ed88-410d-8cad-ecd247a9050b"
    },
    "json": {
        "Check": {
            "all": [
                {
                    "name": "DOMAIN",
                    "operator": "starts_with",
                    "value": "AP"
                },
                {
                    "name": "DOMAIN",
                    "operator": "has_not_equal_length",
                    "value": 4
                }
            ]
        },
        "Core": {
            "Id": "CORE-000181",
            "Version": "1",
            "Status": "Published"
        },
        "Description": "Raise an error when AP-- domain value length is not equal to 4.",
        "Outcome": {
            "Message": "AP-- Domain value length is not equal to 4."
        },
        "Rule_Type": "Record Data",
        "Sensitivity": "Domain",
        "Authorities": [
            {
                "Organization": "CDISC",
                "Standards": [
                    {
                        "Name": "SDTMIG",
                        "Version": "3.4",
                        "References": [
                            {
                                "Origin": "SDTM and SDTMIG Conformance Rules",
                                "Rule_Identifier": {
                                    "Id": "CG0309",
                                    "Version": "1"
                                },
                                "Version": "2.0",
                                "Citations": [
                                    {
                                        "Cited_Guidance": "Each domain dataset is distinguished by a unique, two-character code",
                                        "Document": "IG v3.4",
                                        "Section": "2.2"
                                    }
                                ]
                            }
                        ]
                    }
                ]
            }
        ],
        "Scope": {
            "Classes": {
                "Include": [
                    "ALL"
                ]
            },
            "Domains": {
                "Include": [
                    "ALL"
                ]
            }
        }
    }
}