{
    "id": "fede1129-7fb4-4635-aeac-f6d387816d30",
    "changed": "2022-03-16T13:10:45Z",
    "content": "Check:\n  all:\n    - name: DOMAIN\n      operator: longer_than\n      value: 2\nCore:\n  Id: CORE-000180\n  Version: '1'\n  Status: Published\nDescription: Raise an error when DOMAIN value length is not equal 2.\nOutcome:\n  Message: Domain value length is not equal 2.\nRule Type: Record Data\nSensitivity: Domain\nAuthorities:\n  - Organization: CDISC\n    Standards:\n      - Name: SDTMIG\n        Version: '3.4'\n        References:\n          - Origin: SDTM and SDTMIG Conformance Rules\n            Rule Identifier:\n              Id: CG0308\n              Version: '1'\n            Version: '2.0'\n            Citations:\n              - Cited Guidance: Each domain dataset is distinguished by a unique,\n                  two-character code\n                Document: IG v3.4\n                Section: '2.2'\nScope:\n  Classes:\n    Exclude:\n      - RELATIONSHIP\n  Domains:\n    Exclude:\n      - AP--\n",
    "created": "2021-10-28T14:29:37Z",
    "creator": {
        "id": "76170e05-ed88-410d-8cad-ecd247a9050b"
    },
    "json": {
        "Check": {
            "all": [
                {
                    "name": "DOMAIN",
                    "operator": "longer_than",
                    "value": 2
                }
            ]
        },
        "Core": {
            "Id": "CORE-000180",
            "Version": "1",
            "Status": "Published"
        },
        "Description": "Raise an error when DOMAIN value length is not equal 2.",
        "Outcome": {
            "Message": "Domain value length is not equal 2."
        },
        "Rule_Type": "Record Data",
        "Sensitivity": "Domain",
        "Authorities": [
            {
                "Organization": "CDISC",
                "Standards": [
                    {
                        "Name": "SDTMIG",
                        "Version": "3.4",
                        "References": [
                            {
                                "Origin": "SDTM and SDTMIG Conformance Rules",
                                "Rule_Identifier": {
                                    "Id": "CG0308",
                                    "Version": "1"
                                },
                                "Version": "2.0",
                                "Citations": [
                                    {
                                        "Cited_Guidance": "Each domain dataset is distinguished by a unique, two-character code",
                                        "Document": "IG v3.4",
                                        "Section": "2.2"
                                    }
                                ]
                            }
                        ]
                    }
                ]
            }
        ],
        "Scope": {
            "Classes": {
                "Exclude": [
                    "RELATIONSHIP"
                ]
            },
            "Domains": {
                "Exclude": [
                    "AP--"
                ]
            }
        }
    }
}