{
    "id": "1dc09aea-64bb-4d1e-958c-a16ff2d40a70",
    "changed": "2022-07-30T10:33:26Z",
    "content": "Check:\n  all:\n    - any:\n        - name: TEDUR\n          operator: empty\n        - name: TEDUR\n          operator: not_exists\n    - any:\n        - name: TEENRL\n          operator: empty\n        - name: TEENRL\n          operator: not_exists\nCore:\n  Id: CORE-000027\n  Version: '1'\n  Status: Published\nDescription: Either TEENRL or TEDUR must be present for each Element.\nOutcome:\n  Message: At least one of TEENRL and TEDUR must be populated.\n  Output Variables:\n    - ETCD\n    - TEDUR\n    - TEENRL\nRule Type: Record Data\nSensitivity: Record\nAuthorities:\n  - Organization: CDISC\n    Standards:\n      - Name: SDTMIG\n        Version: '3.4'\n        References:\n          - Origin: SDTM and SDTMIG Conformance Rules\n            Rule Identifier:\n              Id: CG0328\n              Version: '1'\n            Version: '2.0'\n            Citations:\n              - Cited Guidance: Either TEENRL or TEDUR must be present for each Element.\n                Document: SDTMIG v3.4\n                Item: Specification\n                Section: 7.2.2\n              - Cited Guidance: At least one of TEENRL and TEDUR must be populated.\n                  Both may be populated.\n                Document: SDTMIG v3.4\n                Item: Assumption 12\n                Section: 7.2.2\nScope:\n  Classes:\n    Include:\n      - TRIAL DESIGN\n  Domains:\n    Include:\n      - TE\n",
    "created": "2021-09-29T22:00:52Z",
    "creator": {
        "id": "b36967c1-e7ba-40d7-b1fd-9ffb956b3d9f"
    },
    "json": {
        "Check": {
            "all": [
                {
                    "any": [
                        {
                            "name": "TEDUR",
                            "operator": "empty"
                        },
                        {
                            "name": "TEDUR",
                            "operator": "not_exists"
                        }
                    ]
                },
                {
                    "any": [
                        {
                            "name": "TEENRL",
                            "operator": "empty"
                        },
                        {
                            "name": "TEENRL",
                            "operator": "not_exists"
                        }
                    ]
                }
            ]
        },
        "Core": {
            "Id": "CORE-000027",
            "Version": "1",
            "Status": "Published"
        },
        "Description": "Either TEENRL or TEDUR must be present for each Element.",
        "Outcome": {
            "Message": "At least one of TEENRL and TEDUR must be populated.",
            "Output_Variables": [
                "ETCD",
                "TEDUR",
                "TEENRL"
            ]
        },
        "Rule_Type": "Record Data",
        "Sensitivity": "Record",
        "Authorities": [
            {
                "Organization": "CDISC",
                "Standards": [
                    {
                        "Name": "SDTMIG",
                        "Version": "3.4",
                        "References": [
                            {
                                "Origin": "SDTM and SDTMIG Conformance Rules",
                                "Rule_Identifier": {
                                    "Id": "CG0328",
                                    "Version": "1"
                                },
                                "Version": "2.0",
                                "Citations": [
                                    {
                                        "Cited_Guidance": "Either TEENRL or TEDUR must be present for each Element.",
                                        "Document": "SDTMIG v3.4",
                                        "Item": "Specification",
                                        "Section": "7.2.2"
                                    },
                                    {
                                        "Cited_Guidance": "At least one of TEENRL and TEDUR must be populated. Both may be populated.",
                                        "Document": "SDTMIG v3.4",
                                        "Item": "Assumption 12",
                                        "Section": "7.2.2"
                                    }
                                ]
                            }
                        ]
                    }
                ]
            }
        ],
        "Scope": {
            "Classes": {
                "Include": [
                    "TRIAL DESIGN"
                ]
            },
            "Domains": {
                "Include": [
                    "TE"
                ]
            }
        }
    }
}