{
    "id": "703fe66a-7616-4241-9ec4-a28b897f25a1",
    "changed": "2022-03-04T14:10:28Z",
    "content": "Check:\n  all:\n    - name: dataset_name\n      operator: matches_regex\n      value: ^[A-Z][a-z0-9]{3,4}\n    - name: dataset_name\n      operator: not_prefix_matches_regex\n      prefix: 2\n      value: (ap|AP|fa|Fa)\n    - name: dataset_name\n      operator: is_not_contained_by\n      value: <Needs to be a dynamic list of two-letter domains for respective study>\nCore:\n  Id: CDISC.SDTMIG.CG0332\n  Version: '1'\n  Status: Draft\nDescription: Verifying that split domains (i.e three/four-letter domain name) have\n  a two-letter parent domain present in the study\nOutcome:\n  Message: Two-Letter parent domain must be present when spilt datasets are present\n    in the study.\nRule Type: Domain Presence Check\nSensitivity: Domain\n\nAuthorities:\n  - Organization: CDISC\n    Standards:\n      - Name: SDTMIG\n        Version: '3.4'\n        References:\n          - Origin: SDTM and SDTMIG Conformance Rules\n            Rule Identifier:\n              Id: CG0332\n              Version: '1'\n            Version: '2.0'\n            Citations:\n              - Cited Guidance: 'For domains with two-letter domain codes (i.e., other\n                  than SUPPxx and RELREC), split dataset names can be up to four characters\n                  in length. For example, if splitting by --CAT, then dataset names\n                  would be the domain name plus up to two additional characters (e.g.,\n                  QS36 for SF-36). If splitting Findings About by parent domain, then\n                  the dataset name would be the domain code, \"FA\", plus the two-character\n                  domain code for parent domain code (e.g., \"FACM\"). The four-character\n                  dataset-name limitation allows the use of a Supplemental Qualifier\n                  dataset associated with the split dataset. '\n                Document: IG v3.4\n                Item: '6'\n                Section: 4.1.7\nScope:\n  Classes:\n    Include:\n      - ALL\n  Domains:\n    Exclude:\n      - RELREC\n      - RELSUB\n      - SUPP\n",
    "created": "2021-11-04T13:19:04Z",
    "creator": {
        "id": "57474fac-237e-4693-bb37-7826b02737da"
    },
    "json": {
        "Check": {
            "all": [
                {
                    "name": "dataset_name",
                    "operator": "matches_regex",
                    "value": "^[A-Z][a-z0-9]{3,4}"
                },
                {
                    "name": "dataset_name",
                    "operator": "not_prefix_matches_regex",
                    "prefix": 2,
                    "value": "(ap|AP|fa|Fa)"
                },
                {
                    "name": "dataset_name",
                    "operator": "is_not_contained_by",
                    "value": "<Needs to be a dynamic list of two-letter domains for respective study>"
                }
            ]
        },
        "Core": {
            "Id": "CDISC.SDTMIG.CG0332",
            "Version": "1",
            "Status": "Draft"
        },
        "Description": "Verifying that split domains (i.e three/four-letter domain name) have a two-letter parent domain present in the study",
        "Outcome": {
            "Message": "Two-Letter parent domain must be present when spilt datasets are present in the study."
        },
        "Rule_Type": "Domain Presence Check",
        "Sensitivity": "Domain",
        "Authorities": [
            {
                "Organization": "CDISC",
                "Standards": [
                    {
                        "Name": "SDTMIG",
                        "Version": "3.4",
                        "References": [
                            {
                                "Origin": "SDTM and SDTMIG Conformance Rules",
                                "Rule_Identifier": {
                                    "Id": "CG0332",
                                    "Version": "1"
                                },
                                "Version": "2.0",
                                "Citations": [
                                    {
                                        "Cited_Guidance": "For domains with two-letter domain codes (i.e., other than SUPPxx and RELREC), split dataset names can be up to four characters in length. For example, if splitting by --CAT, then dataset names would be the domain name plus up to two additional characters (e.g., QS36 for SF-36). If splitting Findings About by parent domain, then the dataset name would be the domain code, \"FA\", plus the two-character domain code for parent domain code (e.g., \"FACM\"). The four-character dataset-name limitation allows the use of a Supplemental Qualifier dataset associated with the split dataset. ",
                                        "Document": "IG v3.4",
                                        "Item": "6",
                                        "Section": "4.1.7"
                                    }
                                ]
                            }
                        ]
                    }
                ]
            }
        ],
        "Scope": {
            "Classes": {
                "Include": [
                    "ALL"
                ]
            },
            "Domains": {
                "Exclude": [
                    "RELREC",
                    "RELSUB",
                    "SUPP"
                ]
            }
        }
    }
}