{
    "id": "8f052d44-280c-4f7c-b745-76a0cb0f1838",
    "changed": "2022-02-15T21:29:51Z",
    "content": "Check:\n  all:\n    - name: dataset_name\n      operator: is_not_contained_by\n      value:\n        - Domain CT\n    - name:\n      operator:\nCore:\n  Id: CDISC.SDTMIG.CG0321\n  Version: '1'\n  Status: Draft\nDescription: Trigger error when a custom domain is present and is not based on of\n  the observation classes\nOutcome:\n  Message: Custom domain is not based on one of the observation classes\nRule Type: Domain Existence Check\nSensitivity: Domain\nAuthorities:\n  - Organization: CDISC\n    Standards:\n      - Name: SDTMIG\n        Version: '3.4'\n        References:\n          - Origin: SDTM and SDTMIG Conformance Rules\n            Rule Identifier:\n              Id: CG0321\n              Version: '1'\n            Version: '2.0'\n            Citations:\n              - Cited Guidance: This section describes the overall process for creating\n                  a custom domain, which must be based on one of the three SDTM general\n                  observation classes.\n                Document: IG v3.4\n                Section: '2.6'\nScope:\n  Classes:\n    Include:\n      - ALL\n  Domains:\n    Include:\n      - ALL\n",
    "created": "2021-11-06T08:16:43Z",
    "creator": {
        "id": "ff471ff8-f131-4cf5-9712-c79cce6301a1"
    },
    "json": {
        "Check": {
            "all": [
                {
                    "name": "dataset_name",
                    "operator": "is_not_contained_by",
                    "value": [
                        "Domain CT"
                    ]
                },
                {
                    "name": null,
                    "operator": null
                }
            ]
        },
        "Core": {
            "Id": "CDISC.SDTMIG.CG0321",
            "Version": "1",
            "Status": "Draft"
        },
        "Description": "Trigger error when a custom domain is present and is not based on of the observation classes",
        "Outcome": {
            "Message": "Custom domain is not based on one of the observation classes"
        },
        "Rule_Type": "Domain Existence Check",
        "Sensitivity": "Domain",
        "Authorities": [
            {
                "Organization": "CDISC",
                "Standards": [
                    {
                        "Name": "SDTMIG",
                        "Version": "3.4",
                        "References": [
                            {
                                "Origin": "SDTM and SDTMIG Conformance Rules",
                                "Rule_Identifier": {
                                    "Id": "CG0321",
                                    "Version": "1"
                                },
                                "Version": "2.0",
                                "Citations": [
                                    {
                                        "Cited_Guidance": "This section describes the overall process for creating a custom domain, which must be based on one of the three SDTM general observation classes.",
                                        "Document": "IG v3.4",
                                        "Section": "2.6"
                                    }
                                ]
                            }
                        ]
                    }
                ]
            }
        ],
        "Scope": {
            "Classes": {
                "Include": [
                    "ALL"
                ]
            },
            "Domains": {
                "Include": [
                    "ALL"
                ]
            }
        }
    }
}