{
    "id": "e4fda321-9f95-4fa2-9f29-0985016eaadd",
    "changed": "2022-02-15T21:31:50Z",
    "content": "Check:\n  all:\n    - name: --BDSYCD\n      operator: is_contained_by\n      value:\n        - MedDRA system organ class code\nCore:\n  Id: CDISC.SDTMIG.CG0386\n  Version: '1'\n  Status: Draft\nDescription: Trigger error when --BDSYCD is not a valid MedDRA system organ class\n  code\nOutcome:\n  Message: --BDSYCD is not a valid MedDRA system organ class code\nRule Type: Record Data\nSensitivity: Record\nAuthorities:\n  - Organization: CDISC\n    Standards:\n      - Name: SDTMIG\n        Version: '3.4'\n        References:\n          - Origin: SDTM and SDTMIG Conformance Rules\n            Rule Identifier:\n              Id: CG0386\n              Version: '1'\n            Version: '2.0'\n            Citations:\n              - Cited Guidance: A standardized or dictionary derived short sequence\n                  of characters used to represent the body system or organ class.\u00a0MedDRA\n                  System Organ Class code corresponding to --BODSYS assigned for analysis.\n                Document: Model v2.0\n                Item: --BDSYCD\n                Section: Events\nScope:\n  Classes:\n    Include:\n      - EVENTS\n  Domains:\n    Include:\n      - AE\n      - MH\n      - CE\n",
    "created": "2021-11-06T09:24:15Z",
    "creator": {
        "id": "ff471ff8-f131-4cf5-9712-c79cce6301a1"
    },
    "json": {
        "Check": {
            "all": [
                {
                    "name": "--BDSYCD",
                    "operator": "is_contained_by",
                    "value": [
                        "MedDRA system organ class code"
                    ]
                }
            ]
        },
        "Core": {
            "Id": "CDISC.SDTMIG.CG0386",
            "Version": "1",
            "Status": "Draft"
        },
        "Description": "Trigger error when --BDSYCD is not a valid MedDRA system organ class code",
        "Outcome": {
            "Message": "--BDSYCD is not a valid MedDRA system organ class code"
        },
        "Rule_Type": "Record Data",
        "Sensitivity": "Record",
        "Authorities": [
            {
                "Organization": "CDISC",
                "Standards": [
                    {
                        "Name": "SDTMIG",
                        "Version": "3.4",
                        "References": [
                            {
                                "Origin": "SDTM and SDTMIG Conformance Rules",
                                "Rule_Identifier": {
                                    "Id": "CG0386",
                                    "Version": "1"
                                },
                                "Version": "2.0",
                                "Citations": [
                                    {
                                        "Cited_Guidance": "A standardized or dictionary derived short sequence of characters used to represent the body system or organ class.\u00a0MedDRA System Organ Class code corresponding to --BODSYS assigned for analysis.",
                                        "Document": "Model v2.0",
                                        "Item": "--BDSYCD",
                                        "Section": "Events"
                                    }
                                ]
                            }
                        ]
                    }
                ]
            }
        ],
        "Scope": {
            "Classes": {
                "Include": [
                    "EVENTS"
                ]
            },
            "Domains": {
                "Include": [
                    "AE",
                    "MH",
                    "CE"
                ]
            }
        }
    }
}