{
    "id": "0b350343-b02f-4575-9a2e-4ed30741c0e1",
    "changed": "2022-02-15T21:11:48Z",
    "content": "Check:\n  all:\n    - name: --HLTCD\n      operator: is_contained_by\n      value:\n        - MedDRA high level TERM code\nCore:\n  Id: CDISC.SDTMIG.CG0382\n  Version: '1'\n  Status: Draft\nDescription: Trigger error when --HLTCD  is not a valid MedDRA high level TERM code\nOutcome:\n  Message: --HLTCD  is not a valid MedDRA high level TERM code\nRule Type: Record Data\nSensitivity: Record\nAuthorities:\n  - Organization: CDISC\n    Standards:\n      - Name: SDTMIG\n        Version: '3.4'\n        References:\n          - Origin: SDTM and SDTMIG Conformance Rules\n            Rule Identifier:\n              Id: CG0382\n              Version: '1'\n            Version: '2.0'\n            Citations:\n              - Cited Guidance: The high-level term code from the primary hierarchy\n                  assigned to the event from MedDRA.\n                Document: Model v2.0\n                Item: --HLTCD\n                Section: Events\nScope:\n  Classes:\n    Include:\n      - EVENTS\n  Domains:\n    Include:\n      - AE\n      - MH\n      - CE\n",
    "created": "2021-11-06T09:29:47Z",
    "creator": {
        "id": "ff471ff8-f131-4cf5-9712-c79cce6301a1"
    },
    "json": {
        "Check": {
            "all": [
                {
                    "name": "--HLTCD",
                    "operator": "is_contained_by",
                    "value": [
                        "MedDRA high level TERM code"
                    ]
                }
            ]
        },
        "Core": {
            "Id": "CDISC.SDTMIG.CG0382",
            "Version": "1",
            "Status": "Draft"
        },
        "Description": "Trigger error when --HLTCD  is not a valid MedDRA high level TERM code",
        "Outcome": {
            "Message": "--HLTCD  is not a valid MedDRA high level TERM code"
        },
        "Rule_Type": "Record Data",
        "Sensitivity": "Record",
        "Authorities": [
            {
                "Organization": "CDISC",
                "Standards": [
                    {
                        "Name": "SDTMIG",
                        "Version": "3.4",
                        "References": [
                            {
                                "Origin": "SDTM and SDTMIG Conformance Rules",
                                "Rule_Identifier": {
                                    "Id": "CG0382",
                                    "Version": "1"
                                },
                                "Version": "2.0",
                                "Citations": [
                                    {
                                        "Cited_Guidance": "The high-level term code from the primary hierarchy assigned to the event from MedDRA.",
                                        "Document": "Model v2.0",
                                        "Item": "--HLTCD",
                                        "Section": "Events"
                                    }
                                ]
                            }
                        ]
                    }
                ]
            }
        ],
        "Scope": {
            "Classes": {
                "Include": [
                    "EVENTS"
                ]
            },
            "Domains": {
                "Include": [
                    "AE",
                    "MH",
                    "CE"
                ]
            }
        }
    }
}