{
    "id": "6566949b-f40d-4ca0-a50e-d244c7f65964",
    "changed": "2022-02-15T21:28:42Z",
    "content": "Check:\n  all:\n    - name: --DECOD\n      operator: non_empty\n    - name: --DECOD\n      operator: is_contained_by\n      value:\n        - MedDRA preferred TERM\nCore:\n  Id: CDISC.SDTMIG.CG0379\n  Version: '1'\n  Status: Draft\nDescription: Trigger error when --DECOD  is not a valid MedDRA preferred TERM\nOutcome:\n  Message: --DECOD  is not a valid MedDRA preferred TERM\nRule Type: Record Data\nSensitivity: Record\nAuthorities:\n  - Organization: CDISC\n    Standards:\n      - Name: SDTMIG\n        Version: '3.4'\n        References:\n          - Origin: SDTM and SDTMIG Conformance Rules\n            Rule Identifier:\n              Id: CG0379\n              Version: '1'\n            Version: '2.0'\n            Citations:\n              - Cited Guidance: Equivalent to the Preferred Term (PT in MedDRA).\n                Document: Model v2.0\n                Item: --DECOD\n                Section: Events\nScope:\n  Classes:\n    Include:\n      - EVENTS\n  Domains:\n    Include:\n      - AE\n",
    "created": "2021-11-06T09:33:06Z",
    "creator": {
        "id": "ff471ff8-f131-4cf5-9712-c79cce6301a1"
    },
    "json": {
        "Check": {
            "all": [
                {
                    "name": "--DECOD",
                    "operator": "non_empty"
                },
                {
                    "name": "--DECOD",
                    "operator": "is_contained_by",
                    "value": [
                        "MedDRA preferred TERM"
                    ]
                }
            ]
        },
        "Core": {
            "Id": "CDISC.SDTMIG.CG0379",
            "Version": "1",
            "Status": "Draft"
        },
        "Description": "Trigger error when --DECOD  is not a valid MedDRA preferred TERM",
        "Outcome": {
            "Message": "--DECOD  is not a valid MedDRA preferred TERM"
        },
        "Rule_Type": "Record Data",
        "Sensitivity": "Record",
        "Authorities": [
            {
                "Organization": "CDISC",
                "Standards": [
                    {
                        "Name": "SDTMIG",
                        "Version": "3.4",
                        "References": [
                            {
                                "Origin": "SDTM and SDTMIG Conformance Rules",
                                "Rule_Identifier": {
                                    "Id": "CG0379",
                                    "Version": "1"
                                },
                                "Version": "2.0",
                                "Citations": [
                                    {
                                        "Cited_Guidance": "Equivalent to the Preferred Term (PT in MedDRA).",
                                        "Document": "Model v2.0",
                                        "Item": "--DECOD",
                                        "Section": "Events"
                                    }
                                ]
                            }
                        ]
                    }
                ]
            }
        ],
        "Scope": {
            "Classes": {
                "Include": [
                    "EVENTS"
                ]
            },
            "Domains": {
                "Include": [
                    "AE"
                ]
            }
        }
    }
}