{
    "id": "d19cbbb2-d45c-4018-90a8-e40971c0a280",
    "changed": "2022-06-30T17:32:31Z",
    "content": "Check:\n  all:\n    - name: PP\n      operator: exists\n    - name: PC\n      operator: not_exists\nCore:\n  Id: CORE-000183\n  Version: '1'\n  Status: Published\nDescription: Raise an error when a PP dataset is present in study, but a PC dataset\n  is not present in study.\nOutcome:\n  Message: PP dataset is present in  study, but PC dataset is not present in study.\nRule Type: Domain Presence Check\nSensitivity: Dataset\nAuthorities:\n  - Organization: CDISC\n    Standards:\n      - Name: SDTMIG\n        Version: '3.4'\n        References:\n          - Origin: SDTM and SDTMIG Conformance Rules\n            Rule Identifier:\n              Id: CG0318\n              Version: '1'\n            Version: '2.0'\n            Citations:\n              - Cited Guidance: Note, domain pairs have been modeled for microbiology\n                  data (MB/MS domains) and PK data (PC/PP domains) to enable dataset-level\n                  relationships to be described using RELREC.\n                Document: IG v3.4\n                Item: '1'\n                Section: '2.6'\n              - Cited Guidance: A findings domain that contains pharmacokinetic parameters\n                  derived from pharmacokinetic concentration-time (PC) data.\n                Document: IG v3.4\n                Item: PP - Description/Overview\n                Section: 6.3.5.6.2\nScope:\n  Classes:\n    Include:\n      - FINDINGS\n  Domains:\n    Include:\n      - PC\n      - PP\n",
    "created": "2021-10-28T14:33:18Z",
    "creator": {
        "id": "76170e05-ed88-410d-8cad-ecd247a9050b"
    },
    "json": {
        "Check": {
            "all": [
                {
                    "name": "PP",
                    "operator": "exists"
                },
                {
                    "name": "PC",
                    "operator": "not_exists"
                }
            ]
        },
        "Core": {
            "Id": "CORE-000183",
            "Version": "1",
            "Status": "Published"
        },
        "Description": "Raise an error when a PP dataset is present in study, but a PC dataset is not present in study.",
        "Outcome": {
            "Message": "PP dataset is present in  study, but PC dataset is not present in study."
        },
        "Rule_Type": "Domain Presence Check",
        "Sensitivity": "Dataset",
        "Authorities": [
            {
                "Organization": "CDISC",
                "Standards": [
                    {
                        "Name": "SDTMIG",
                        "Version": "3.4",
                        "References": [
                            {
                                "Origin": "SDTM and SDTMIG Conformance Rules",
                                "Rule_Identifier": {
                                    "Id": "CG0318",
                                    "Version": "1"
                                },
                                "Version": "2.0",
                                "Citations": [
                                    {
                                        "Cited_Guidance": "Note, domain pairs have been modeled for microbiology data (MB/MS domains) and PK data (PC/PP domains) to enable dataset-level relationships to be described using RELREC.",
                                        "Document": "IG v3.4",
                                        "Item": "1",
                                        "Section": "2.6"
                                    },
                                    {
                                        "Cited_Guidance": "A findings domain that contains pharmacokinetic parameters derived from pharmacokinetic concentration-time (PC) data.",
                                        "Document": "IG v3.4",
                                        "Item": "PP - Description/Overview",
                                        "Section": "6.3.5.6.2"
                                    }
                                ]
                            }
                        ]
                    }
                ]
            }
        ],
        "Scope": {
            "Classes": {
                "Include": [
                    "FINDINGS"
                ]
            },
            "Domains": {
                "Include": [
                    "PC",
                    "PP"
                ]
            }
        }
    }
}