{
    "id": "fe9ea11f-3d2d-41ba-8b98-cb07be6943e6",
    "changed": "2022-03-03T08:27:48Z",
    "content": "Check:\n  all:\n    - name: --TESTCD\n      operator: equal_to\n      value: MULTIPLE\nCore:\n  Id: CORE-000162\n  Version: '1'\n  Status: Published\nDescription: Raise an error when --TESTCD = 'MULTIPLE'\nOutcome:\n  Message: --TESTCD is equal to 'MULTIPLE'\n  Output Variables:\n    - --TESTCD\nRule Type: Record Data\nSensitivity: Record\nAuthorities:\n  - Organization: CDISC\n    Standards:\n      - Name: SDTMIG\n        Version: '3.4'\n        References:\n          - Origin: SDTM and SDTMIG Conformance Rules\n            Rule Identifier:\n              Id: CG0344\n              Version: '1'\n            Version: '2.0'\n            Citations:\n              - Cited Guidance: If multiple result values (--ORRES) are reported for\n                  a test in a Findings class dataset, multiple records should be submitted\n                  for that --TESTCD.\n                Document: IG v3.4\n                Section: 4.2.8.2\nScope:\n  Classes:\n    Include:\n      - FINDINGS\n  Domains:\n    Include:\n      - ALL\n",
    "created": "2021-10-19T08:49:32Z",
    "creator": {
        "id": "ae6dbbf3-4c9a-4149-b596-8183766167d4"
    },
    "json": {
        "Check": {
            "all": [
                {
                    "name": "--TESTCD",
                    "operator": "equal_to",
                    "value": "MULTIPLE"
                }
            ]
        },
        "Core": {
            "Id": "CORE-000162",
            "Version": "1",
            "Status": "Published"
        },
        "Description": "Raise an error when --TESTCD = 'MULTIPLE'",
        "Outcome": {
            "Message": "--TESTCD is equal to 'MULTIPLE'",
            "Output_Variables": [
                "--TESTCD"
            ]
        },
        "Rule_Type": "Record Data",
        "Sensitivity": "Record",
        "Authorities": [
            {
                "Organization": "CDISC",
                "Standards": [
                    {
                        "Name": "SDTMIG",
                        "Version": "3.4",
                        "References": [
                            {
                                "Origin": "SDTM and SDTMIG Conformance Rules",
                                "Rule_Identifier": {
                                    "Id": "CG0344",
                                    "Version": "1"
                                },
                                "Version": "2.0",
                                "Citations": [
                                    {
                                        "Cited_Guidance": "If multiple result values (--ORRES) are reported for a test in a Findings class dataset, multiple records should be submitted for that --TESTCD.",
                                        "Document": "IG v3.4",
                                        "Section": "4.2.8.2"
                                    }
                                ]
                            }
                        ]
                    }
                ]
            }
        ],
        "Scope": {
            "Classes": {
                "Include": [
                    "FINDINGS"
                ]
            },
            "Domains": {
                "Include": [
                    "ALL"
                ]
            }
        }
    }
}