{
    "id": "daac7711-1749-4c58-8c1e-249c68c4f380",
    "changed": "2022-03-14T20:03:55Z",
    "content": "Check:\n  all:\n    - name: USUBJID\n      operator: non_empty\n    - name: POOLID\n      operator: non_empty\nCore:\n  Id: CORE-000229\n  Version: '1'\n  Status: Published\nDescription: Verify that When USUBJID is populated, POOLID is not populated\nOutcome:\n  Message: POOLID must be null when USUBJID is populated\n  Output Variables:\n    - USUBJID\n    - POOLID\nRule Type: Record Data\nSensitivity: Value\nAuthorities:\n  - Organization: CDISC\n    Standards:\n      - Name: SDTMIG\n        Version: '3.4'\n        References:\n          - Origin: SDTM and SDTMIG Conformance Rules\n            Rule Identifier:\n              Id: CG0361\n              Version: '1'\n            Version: '2.0'\n            Citations:\n              - Cited Guidance: '\"USUBJID: Either USUBJID or POOILD must be populated.\"'\n                Document: Model v2.0\n                Item: USUBJID\n                Section: RELSUB\n              - Cited Guidance: '\"POOILD: Either USUBJID or POOILD must be populated.\"        '\n                Document: Model v2.0\n                Item: POOLID\n                Section: RELSUB\nScope:\n  Classes:\n    Include:\n      - SPECIAL-PURPOSE\n  Domains:\n    Include:\n      - RELSUB\n",
    "created": "2021-12-09T17:32:27Z",
    "creator": {
        "id": "57474fac-237e-4693-bb37-7826b02737da"
    },
    "json": {
        "Check": {
            "all": [
                {
                    "name": "USUBJID",
                    "operator": "non_empty"
                },
                {
                    "name": "POOLID",
                    "operator": "non_empty"
                }
            ]
        },
        "Core": {
            "Id": "CORE-000229",
            "Version": "1",
            "Status": "Published"
        },
        "Description": "Verify that When USUBJID is populated, POOLID is not populated",
        "Outcome": {
            "Message": "POOLID must be null when USUBJID is populated",
            "Output_Variables": [
                "USUBJID",
                "POOLID"
            ]
        },
        "Rule_Type": "Record Data",
        "Sensitivity": "Value",
        "Authorities": [
            {
                "Organization": "CDISC",
                "Standards": [
                    {
                        "Name": "SDTMIG",
                        "Version": "3.4",
                        "References": [
                            {
                                "Origin": "SDTM and SDTMIG Conformance Rules",
                                "Rule_Identifier": {
                                    "Id": "CG0361",
                                    "Version": "1"
                                },
                                "Version": "2.0",
                                "Citations": [
                                    {
                                        "Cited_Guidance": "\"USUBJID: Either USUBJID or POOILD must be populated.\"",
                                        "Document": "Model v2.0",
                                        "Item": "USUBJID",
                                        "Section": "RELSUB"
                                    },
                                    {
                                        "Cited_Guidance": "\"POOILD: Either USUBJID or POOILD must be populated.\"        ",
                                        "Document": "Model v2.0",
                                        "Item": "POOLID",
                                        "Section": "RELSUB"
                                    }
                                ]
                            }
                        ]
                    }
                ]
            }
        ],
        "Scope": {
            "Classes": {
                "Include": [
                    "SPECIAL-PURPOSE"
                ]
            },
            "Domains": {
                "Include": [
                    "RELSUB"
                ]
            }
        }
    }
}