{
    "id": "2f067a90-c6c8-4e77-8d62-f26f7a64c81d",
    "changed": "2022-03-17T10:16:21Z",
    "content": "Check:\n  all:\n    - name: --REASEX\n      operator: exists\nCore:\n  Id: CORE-000243\n  Version: '1'\n  Status: Published\nDescription: Raise an error when --REASEX is present in dataset.\nOutcome:\n  Message: --REASEX must never be used in SDTM-based human trials\n  Output Variables:\n    - --REASEX\nRule Type: Record Data\nSensitivity: Variable\nAuthorities:\n  - Organization: CDISC\n    Standards:\n      - Name: SDTMIG\n        Version: '3.4'\n        References:\n          - Origin: SDTM and SDTMIG Conformance Rules\n            Rule Identifier:\n              Id: CG0354\n              Version: '1'\n            Version: '2.0'\n            Citations:\n              - Cited Guidance: 'The following SDTM variables, defined for use in\n                  non-clinical studies (SEND), must  NEVER be used in the submission\n                  of SDTM-based data for human clinical trials: --DTHREL (Findings)\n                  --EXCLFL (Findings) --REASEX (Findings) --DETECT (Findings)'\n                Document: IG v3.4\n                Section: '2.7'\nScope:\n  Classes:\n    Include:\n      - ALL\n  Domains:\n    Include:\n      - ALL\n",
    "created": "2022-02-05T12:39:26Z",
    "creator": {
        "id": "ff471ff8-f131-4cf5-9712-c79cce6301a1"
    },
    "json": {
        "Check": {
            "all": [
                {
                    "name": "--REASEX",
                    "operator": "exists"
                }
            ]
        },
        "Core": {
            "Id": "CORE-000243",
            "Version": "1",
            "Status": "Published"
        },
        "Description": "Raise an error when --REASEX is present in dataset.",
        "Outcome": {
            "Message": "--REASEX must never be used in SDTM-based human trials",
            "Output_Variables": [
                "--REASEX"
            ]
        },
        "Rule_Type": "Record Data",
        "Sensitivity": "Variable",
        "Authorities": [
            {
                "Organization": "CDISC",
                "Standards": [
                    {
                        "Name": "SDTMIG",
                        "Version": "3.4",
                        "References": [
                            {
                                "Origin": "SDTM and SDTMIG Conformance Rules",
                                "Rule_Identifier": {
                                    "Id": "CG0354",
                                    "Version": "1"
                                },
                                "Version": "2.0",
                                "Citations": [
                                    {
                                        "Cited_Guidance": "The following SDTM variables, defined for use in non-clinical studies (SEND), must  NEVER be used in the submission of SDTM-based data for human clinical trials: --DTHREL (Findings) --EXCLFL (Findings) --REASEX (Findings) --DETECT (Findings)",
                                        "Document": "IG v3.4",
                                        "Section": "2.7"
                                    }
                                ]
                            }
                        ]
                    }
                ]
            }
        ],
        "Scope": {
            "Classes": {
                "Include": [
                    "ALL"
                ]
            },
            "Domains": {
                "Include": [
                    "ALL"
                ]
            }
        }
    }
}