{
    "id": "ee3cdf7a-50b0-4a3f-a821-e85ce30af503",
    "changed": "2022-02-15T21:32:10Z",
    "content": "Check:\n  all:\n    - name: QNAM\n      operator: non_empty\n    - context: RDOMAIN\n      name: QNAM\n      operator: exists\n      value: variable_name\nCore:\n  Id: CDISC.SDTMIG.CG0314\n  Version: '1'\n  Status: Draft\nDescription: Raise an error when SUPP--.QNAM presents in dataset, but value of SUPP--.QNAM\n  ^= any variable name defined in the corresponding SDTM version.\nOutcome:\n  Message: SUPP--.QNAM presents in dataset, but value of SUPP--.QNAM ^= any variable\n    name defined in the corresponding SDTM version.\nRule Type: Record Data\nSensitivity: Variable\nAuthorities:\n  - Organization: CDISC\n    Standards:\n      - Name: SDTMIG\n        Version: '3.4'\n        References:\n          - Origin: SDTM and SDTMIG Conformance Rules\n            Rule Identifier:\n              Id: CG0314\n              Version: '1'\n            Version: '2.0'\n            Citations:\n              - Cited Guidance: The SDTM allows for the inclusion of a sponsor's non-SDTM\n                  variables using the Supplemental Qualifiers special-purpose dataset\n                  structure\n                Document: IG v3.4\n                Item: NA\n                Section: '2.5'\nScope:\n  Classes:\n    Include:\n      - ALL\n  Domains:\n    Include:\n      - ALL\n",
    "created": "2021-10-28T14:31:47Z",
    "creator": {
        "id": "76170e05-ed88-410d-8cad-ecd247a9050b"
    },
    "json": {
        "Check": {
            "all": [
                {
                    "name": "QNAM",
                    "operator": "non_empty"
                },
                {
                    "context": "RDOMAIN",
                    "name": "QNAM",
                    "operator": "exists",
                    "value": "variable_name"
                }
            ]
        },
        "Core": {
            "Id": "CDISC.SDTMIG.CG0314",
            "Version": "1",
            "Status": "Draft"
        },
        "Description": "Raise an error when SUPP--.QNAM presents in dataset, but value of SUPP--.QNAM ^= any variable name defined in the corresponding SDTM version.",
        "Outcome": {
            "Message": "SUPP--.QNAM presents in dataset, but value of SUPP--.QNAM ^= any variable name defined in the corresponding SDTM version."
        },
        "Rule_Type": "Record Data",
        "Sensitivity": "Variable",
        "Authorities": [
            {
                "Organization": "CDISC",
                "Standards": [
                    {
                        "Name": "SDTMIG",
                        "Version": "3.4",
                        "References": [
                            {
                                "Origin": "SDTM and SDTMIG Conformance Rules",
                                "Rule_Identifier": {
                                    "Id": "CG0314",
                                    "Version": "1"
                                },
                                "Version": "2.0",
                                "Citations": [
                                    {
                                        "Cited_Guidance": "The SDTM allows for the inclusion of a sponsor's non-SDTM variables using the Supplemental Qualifiers special-purpose dataset structure",
                                        "Document": "IG v3.4",
                                        "Item": "NA",
                                        "Section": "2.5"
                                    }
                                ]
                            }
                        ]
                    }
                ]
            }
        ],
        "Scope": {
            "Classes": {
                "Include": [
                    "ALL"
                ]
            },
            "Domains": {
                "Include": [
                    "ALL"
                ]
            }
        }
    }
}