{
    "id": "8aee07d9-cfb6-4d46-b4df-c52f249cf36c",
    "changed": "2022-07-14T03:49:24Z",
    "content": "Check:\n  all:\n    - name: --TESTCD\n      operator: not_exists\nCore:\n  Id: CDISC.SDTMIG.CG0320\n  Version: '1'\n  Status: Draft\nDescription: Raise an error when variable --TESTCD is missing for custom finding domains\nOutcome:\n  Message: --TESTCD does not exist in Findings domain.\nRule Type: Record Data\nSensitivity: Variable\nAuthorities:\n  - Organization: CDISC\n    Standards:\n      - Name: SDTMIG\n        Version: '3.4'\n        References:\n          - Origin: SDTM and SDTMIG Conformance Rules\n            Rule Identifier:\n              Id: CG0320\n              Version: '2'\n            Version: '2.0'\n            Citations:\n              - Cited Guidance: Include the topic variable from the identified general\n                  observation class (e.g., --TESTCD for Findings) in the SDTM.\n                Document: IG v3.4\n                Item: Item 3.b.\n                Section: '2.6'\n              - Cited Guidance: For a Findings domain, the topic variable, --TESTCD,\n                  should use Controlled Terminology (e.g., \"SYSBP\" for Systolic Blood\n                  Pressure)\n                Document: IG v3.4\n                Section: 4.3.6\nScope:\n  Classes:\n    Include:\n      - FINDINGS\n  Domains:\n    Exclude:\n      - BS\n      - CP\n      - CV\n      - DA\n      - DD\n      - EG\n      - FT\n      - GF\n      - IE\n      - IS\n      - LB\n      - MB\n      - MI\n      - MK\n      - MS\n      - NV\n      - OE\n      - PC\n      - PE\n      - PP\n      - QS\n      - RE\n      - RP\n      - RS\n      - SC\n      - SS\n      - TR\n      - TU\n      - UR\n      - VS\n",
    "created": "2021-10-28T14:33:48Z",
    "creator": {
        "id": "76170e05-ed88-410d-8cad-ecd247a9050b"
    },
    "json": {
        "Check": {
            "all": [
                {
                    "name": "--TESTCD",
                    "operator": "not_exists"
                }
            ]
        },
        "Core": {
            "Id": "CDISC.SDTMIG.CG0320",
            "Version": "1",
            "Status": "Draft"
        },
        "Description": "Raise an error when variable --TESTCD is missing for custom finding domains",
        "Outcome": {
            "Message": "--TESTCD does not exist in Findings domain."
        },
        "Rule_Type": "Record Data",
        "Sensitivity": "Variable",
        "Authorities": [
            {
                "Organization": "CDISC",
                "Standards": [
                    {
                        "Name": "SDTMIG",
                        "Version": "3.4",
                        "References": [
                            {
                                "Origin": "SDTM and SDTMIG Conformance Rules",
                                "Rule_Identifier": {
                                    "Id": "CG0320",
                                    "Version": "2"
                                },
                                "Version": "2.0",
                                "Citations": [
                                    {
                                        "Cited_Guidance": "Include the topic variable from the identified general observation class (e.g., --TESTCD for Findings) in the SDTM.",
                                        "Document": "IG v3.4",
                                        "Item": "Item 3.b.",
                                        "Section": "2.6"
                                    },
                                    {
                                        "Cited_Guidance": "For a Findings domain, the topic variable, --TESTCD, should use Controlled Terminology (e.g., \"SYSBP\" for Systolic Blood Pressure)",
                                        "Document": "IG v3.4",
                                        "Section": "4.3.6"
                                    }
                                ]
                            }
                        ]
                    }
                ]
            }
        ],
        "Scope": {
            "Classes": {
                "Include": [
                    "FINDINGS"
                ]
            },
            "Domains": {
                "Exclude": [
                    "BS",
                    "CP",
                    "CV",
                    "DA",
                    "DD",
                    "EG",
                    "FT",
                    "GF",
                    "IE",
                    "IS",
                    "LB",
                    "MB",
                    "MI",
                    "MK",
                    "MS",
                    "NV",
                    "OE",
                    "PC",
                    "PE",
                    "PP",
                    "QS",
                    "RE",
                    "RP",
                    "RS",
                    "SC",
                    "SS",
                    "TR",
                    "TU",
                    "UR",
                    "VS"
                ]
            }
        }
    }
}