{
    "id": "e54b123a-90d7-408c-9c1a-adbb664f4925",
    "changed": "2022-03-03T08:29:38Z",
    "content": "Check:\n  all:\n    - name: --TERM\n      operator: equal_to\n      value: MULTIPLE\nCore:\n  Id: CORE-000164\n  Version: '1'\n  Status: Published\nDescription: Raise an error when --TERM = 'MULTIPLE'\nOutcome:\n  Message: --TERM is equal to 'MULTIPLE'\n  Output Variables:\n    - --TERM\nRule Type: Record Data\nSensitivity: Record\nAuthorities:\n  - Organization: CDISC\n    Standards:\n      - Name: SDTMIG\n        Version: '3.4'\n        References:\n          - Origin: SDTM and SDTMIG Conformance Rules\n            Rule Identifier:\n              Id: CG0346\n              Version: '1'\n            Version: '2.0'\n            Citations:\n              - Cited Guidance: If multiple values are reported for a topic variable\n                  (i.e., --TRT in an Interventions general-observation-class dataset\n                  or --TERM in an Events general-observation-class dataset), it is\n                  expected that the sponsor will split the values into multiple records\n                  or otherwise resolve the multiplicity per the sponsor's data management\n                  standard operating procedures.\n                Document: IG v3.4\n                Section: 4.2.8.1\nScope:\n  Classes:\n    Include:\n      - EVENTS\n  Domains:\n    Include:\n      - ALL\n",
    "created": "2021-10-19T09:12:28Z",
    "creator": {
        "id": "ae6dbbf3-4c9a-4149-b596-8183766167d4"
    },
    "json": {
        "Check": {
            "all": [
                {
                    "name": "--TERM",
                    "operator": "equal_to",
                    "value": "MULTIPLE"
                }
            ]
        },
        "Core": {
            "Id": "CORE-000164",
            "Version": "1",
            "Status": "Published"
        },
        "Description": "Raise an error when --TERM = 'MULTIPLE'",
        "Outcome": {
            "Message": "--TERM is equal to 'MULTIPLE'",
            "Output_Variables": [
                "--TERM"
            ]
        },
        "Rule_Type": "Record Data",
        "Sensitivity": "Record",
        "Authorities": [
            {
                "Organization": "CDISC",
                "Standards": [
                    {
                        "Name": "SDTMIG",
                        "Version": "3.4",
                        "References": [
                            {
                                "Origin": "SDTM and SDTMIG Conformance Rules",
                                "Rule_Identifier": {
                                    "Id": "CG0346",
                                    "Version": "1"
                                },
                                "Version": "2.0",
                                "Citations": [
                                    {
                                        "Cited_Guidance": "If multiple values are reported for a topic variable (i.e., --TRT in an Interventions general-observation-class dataset or --TERM in an Events general-observation-class dataset), it is expected that the sponsor will split the values into multiple records or otherwise resolve the multiplicity per the sponsor's data management standard operating procedures.",
                                        "Document": "IG v3.4",
                                        "Section": "4.2.8.1"
                                    }
                                ]
                            }
                        ]
                    }
                ]
            }
        ],
        "Scope": {
            "Classes": {
                "Include": [
                    "EVENTS"
                ]
            },
            "Domains": {
                "Include": [
                    "ALL"
                ]
            }
        }
    }
}