{
    "id": "e420f81d-6035-4fcf-8da6-2a228090364b",
    "changed": "2022-06-29T11:37:59Z",
    "content": "Check:\n  all:\n    - name: TEENRL\n      operator: contains\n      value: $ta_arm\nCore:\n  Id: CDISC.SDTMIG.CG0324\n  Version: '1'\n  Status: Draft\nDescription: TEENRL should not reference a specific ARM.  This rule has only been\n  partially executed to identify explicit references to ARM.\nOperations:\n  - domain: TA\n    id: $ta_arm\n    name: ARM\n    operator: distinct\nOutcome:\n  Message: TEENRL refers to a specific ARM\nRule Type: Record Data\nSensitivity: Record\nAuthorities:\n  - Organization: CDISC\n    Standards:\n      - Name: SDTMIG\n        Version: '3.4'\n        References:\n          - Origin: SDTM and SDTMIG Conformance Rules\n            Rule Identifier:\n              Id: CG0324\n              Version: '1'\n            Version: '2.0'\n            Citations:\n              - Cited Guidance: The Trial Arms dataset, not the Trial Elements dataset,\n                  describes where the subject moves next, so TEENRL must be expressed\n                  without referring to Arm.\n                Document: IG v3.4\n                Item: Assumption 13\n                Section: 7.2.2\nScope:\n  Classes:\n    Include:\n      - STUDY REFERENCE\n  Domains:\n    Include:\n      - TE\n",
    "created": "2021-11-06T08:23:23Z",
    "creator": {
        "id": "ff471ff8-f131-4cf5-9712-c79cce6301a1"
    },
    "json": {
        "Check": {
            "all": [
                {
                    "name": "TEENRL",
                    "operator": "contains",
                    "value": "$ta_arm"
                }
            ]
        },
        "Core": {
            "Id": "CDISC.SDTMIG.CG0324",
            "Version": "1",
            "Status": "Draft"
        },
        "Description": "TEENRL should not reference a specific ARM.  This rule has only been partially executed to identify explicit references to ARM.",
        "Operations": [
            {
                "domain": "TA",
                "id": "$ta_arm",
                "name": "ARM",
                "operator": "distinct"
            }
        ],
        "Outcome": {
            "Message": "TEENRL refers to a specific ARM"
        },
        "Rule_Type": "Record Data",
        "Sensitivity": "Record",
        "Authorities": [
            {
                "Organization": "CDISC",
                "Standards": [
                    {
                        "Name": "SDTMIG",
                        "Version": "3.4",
                        "References": [
                            {
                                "Origin": "SDTM and SDTMIG Conformance Rules",
                                "Rule_Identifier": {
                                    "Id": "CG0324",
                                    "Version": "1"
                                },
                                "Version": "2.0",
                                "Citations": [
                                    {
                                        "Cited_Guidance": "The Trial Arms dataset, not the Trial Elements dataset, describes where the subject moves next, so TEENRL must be expressed without referring to Arm.",
                                        "Document": "IG v3.4",
                                        "Item": "Assumption 13",
                                        "Section": "7.2.2"
                                    }
                                ]
                            }
                        ]
                    }
                ]
            }
        ],
        "Scope": {
            "Classes": {
                "Include": [
                    "STUDY REFERENCE"
                ]
            },
            "Domains": {
                "Include": [
                    "TE"
                ]
            }
        }
    }
}