{
    "id": "32a1907b-fe88-470b-8505-b110c7a1393f",
    "changed": "2022-03-07T22:24:41Z",
    "content": "Check:\n  all:\n    - name: SPECIES\n      operator: exists\nCore:\n  Id: CORE-000174\n  Version: '1'\n  Status: Published\nDescription: Verify variable SPECIES does not exist in DM dataset\nOutcome:\n  Message: SPECIES is present in DM dataset.\n  Output Variables:\n    - SPECIES\nRule Type: Record Data\nSensitivity: Dataset\nAuthorities:\n  - Organization: CDISC\n    Standards:\n      - Name: SDTMIG\n        Version: '3.4'\n        References:\n          - Origin: SDTM and SDTMIG Conformance Rules\n            Rule Identifier:\n              Id: CG0356\n              Version: '1'\n            Version: '2.0'\n            Citations:\n              - Cited Guidance: \"The following variables can be used for non-clinical\\\n                  \\ studies (SEND) but must NEVER be used in the Demographics domain\\\n                  \\ for human clinical trials. However, the use of these variables\\\n                  \\ is currently  being evaluated in Findings general observation\\\n                  \\ class domains being developed for use in the  tabulations of virology\\\n                  \\ data:\\n  SPECIES (Demographics)\\n  STRAIN (Demographics)\\n  SBSTRAIN\\\n                  \\ (Demographics)\"\n                Document: IG 3.4\n                Section: '2.7'\nScope:\n  Classes:\n    Include:\n      - SPECIAL-PURPOSE\n  Domains:\n    Include:\n      - DM\n",
    "created": "2021-10-27T22:50:21Z",
    "creator": {
        "id": "f9333394-14e8-48f3-9a3a-62f1e3cf098c"
    },
    "json": {
        "Check": {
            "all": [
                {
                    "name": "SPECIES",
                    "operator": "exists"
                }
            ]
        },
        "Core": {
            "Id": "CORE-000174",
            "Version": "1",
            "Status": "Published"
        },
        "Description": "Verify variable SPECIES does not exist in DM dataset",
        "Outcome": {
            "Message": "SPECIES is present in DM dataset.",
            "Output_Variables": [
                "SPECIES"
            ]
        },
        "Rule_Type": "Record Data",
        "Sensitivity": "Dataset",
        "Authorities": [
            {
                "Organization": "CDISC",
                "Standards": [
                    {
                        "Name": "SDTMIG",
                        "Version": "3.4",
                        "References": [
                            {
                                "Origin": "SDTM and SDTMIG Conformance Rules",
                                "Rule_Identifier": {
                                    "Id": "CG0356",
                                    "Version": "1"
                                },
                                "Version": "2.0",
                                "Citations": [
                                    {
                                        "Cited_Guidance": "The following variables can be used for non-clinical studies (SEND) but must NEVER be used in the Demographics domain for human clinical trials. However, the use of these variables is currently  being evaluated in Findings general observation class domains being developed for use in the  tabulations of virology data:\n  SPECIES (Demographics)\n  STRAIN (Demographics)\n  SBSTRAIN (Demographics)",
                                        "Document": "IG 3.4",
                                        "Section": "2.7"
                                    }
                                ]
                            }
                        ]
                    }
                ]
            }
        ],
        "Scope": {
            "Classes": {
                "Include": [
                    "SPECIAL-PURPOSE"
                ]
            },
            "Domains": {
                "Include": [
                    "DM"
                ]
            }
        }
    }
}