{
    "id": "23baabfe-1c3b-4f4f-aaaf-a72a3418e143",
    "changed": "2022-07-30T10:05:36Z",
    "content": "Check:\n  all:\n    - context: DOMAIN\n      name: RDOMAIN\n      operator: is_not_valid_reference\nCore:\n  Id: CDISC.SDTMIG.CG0374\n  Version: '1'\n  Status: Draft\nDescription: RELREC.RDOMAIN must represent a dataset that is present in the study.\n  in the study\nOutcome:\n  Message: RELREC.RDOMAIN does not represent a dataset present in the study\nRule Type: Record Data\nSensitivity: Study\nAuthorities:\n  - Organization: CDISC\n    Standards:\n      - Name: SDTMIG\n        Version: '3.4'\n        References:\n          - Origin: SDTM and SDTMIG Conformance Rules\n            Rule Identifier:\n              Id: CG0374\n              Version: '1'\n            Version: '2.0'\n            Citations:\n              - Cited Guidance: 'Two-character abbreviation for the domain of the\n                  parent record(s). '\n                Document: Model v2.0\n                Item: RDOMAIN\n                Section: Related Records\nScope:\n  Classes:\n    Include:\n      - ALL\n  Domains:\n    Include:\n      - RELREC\n",
    "created": "2021-11-06T09:42:46Z",
    "creator": {
        "id": "ff471ff8-f131-4cf5-9712-c79cce6301a1"
    },
    "json": {
        "Check": {
            "all": [
                {
                    "context": "DOMAIN",
                    "name": "RDOMAIN",
                    "operator": "is_not_valid_reference"
                }
            ]
        },
        "Core": {
            "Id": "CDISC.SDTMIG.CG0374",
            "Version": "1",
            "Status": "Draft"
        },
        "Description": "RELREC.RDOMAIN must represent a dataset that is present in the study. in the study",
        "Outcome": {
            "Message": "RELREC.RDOMAIN does not represent a dataset present in the study"
        },
        "Rule_Type": "Record Data",
        "Sensitivity": "Study",
        "Authorities": [
            {
                "Organization": "CDISC",
                "Standards": [
                    {
                        "Name": "SDTMIG",
                        "Version": "3.4",
                        "References": [
                            {
                                "Origin": "SDTM and SDTMIG Conformance Rules",
                                "Rule_Identifier": {
                                    "Id": "CG0374",
                                    "Version": "1"
                                },
                                "Version": "2.0",
                                "Citations": [
                                    {
                                        "Cited_Guidance": "Two-character abbreviation for the domain of the parent record(s). ",
                                        "Document": "Model v2.0",
                                        "Item": "RDOMAIN",
                                        "Section": "Related Records"
                                    }
                                ]
                            }
                        ]
                    }
                ]
            }
        ],
        "Scope": {
            "Classes": {
                "Include": [
                    "ALL"
                ]
            },
            "Domains": {
                "Include": [
                    "RELREC"
                ]
            }
        }
    }
}