{
    "id": "2c4c70bd-fcdb-4d48-b2eb-9f4f2ef79e1f",
    "changed": "2022-03-03T09:20:59Z",
    "content": "Check:\n  all:\n    - name: --TESTCD\n      operator: equal_to\n      value: OTHER\nCore:\n  Id: CORE-000159\n  Version: '1'\n  Status: Published\nDescription: Raise an error when --TESTCD = 'OTHER'\nOutcome:\n  Message: --TESTCD is equal to 'OTHER'\n  Output Variables:\n    - --TESTCD\nRule Type: Record Data\nSensitivity: Record\nAuthorities:\n  - Organization: CDISC\n    Standards:\n      - Name: SDTMIG\n        Version: '3.4'\n        References:\n          - Origin: SDTM and SDTMIG Conformance Rules\n            Rule Identifier:\n              Id: CG0341\n              Version: '1'\n            Version: '2.0'\n            Citations:\n              - Cited Guidance: 'Findings: \"Other, Specify\" for tests may be handled\n                  similarly to Interventions. --TESTCD and --TEST should be populated\n                  with the code and description of the test found in the specified\n                  text. If specific tests are not prespecified on the CRF and the\n                  investigator has the option of writing in tests, then the name of\n                  the test would have to be coded to ensure that all --TESTCD and\n                  --TEST values are consistent with the test controlled terminology.'\n                Document: IG v3.4\n                Section: 4.2.7.3\nScope:\n  Classes:\n    Include:\n      - FINDINGS\n  Domains:\n    Include:\n      - ALL\n",
    "created": "2021-10-19T08:38:52Z",
    "creator": {
        "id": "ae6dbbf3-4c9a-4149-b596-8183766167d4"
    },
    "json": {
        "Check": {
            "all": [
                {
                    "name": "--TESTCD",
                    "operator": "equal_to",
                    "value": "OTHER"
                }
            ]
        },
        "Core": {
            "Id": "CORE-000159",
            "Version": "1",
            "Status": "Published"
        },
        "Description": "Raise an error when --TESTCD = 'OTHER'",
        "Outcome": {
            "Message": "--TESTCD is equal to 'OTHER'",
            "Output_Variables": [
                "--TESTCD"
            ]
        },
        "Rule_Type": "Record Data",
        "Sensitivity": "Record",
        "Authorities": [
            {
                "Organization": "CDISC",
                "Standards": [
                    {
                        "Name": "SDTMIG",
                        "Version": "3.4",
                        "References": [
                            {
                                "Origin": "SDTM and SDTMIG Conformance Rules",
                                "Rule_Identifier": {
                                    "Id": "CG0341",
                                    "Version": "1"
                                },
                                "Version": "2.0",
                                "Citations": [
                                    {
                                        "Cited_Guidance": "Findings: \"Other, Specify\" for tests may be handled similarly to Interventions. --TESTCD and --TEST should be populated with the code and description of the test found in the specified text. If specific tests are not prespecified on the CRF and the investigator has the option of writing in tests, then the name of the test would have to be coded to ensure that all --TESTCD and --TEST values are consistent with the test controlled terminology.",
                                        "Document": "IG v3.4",
                                        "Section": "4.2.7.3"
                                    }
                                ]
                            }
                        ]
                    }
                ]
            }
        ],
        "Scope": {
            "Classes": {
                "Include": [
                    "FINDINGS"
                ]
            },
            "Domains": {
                "Include": [
                    "ALL"
                ]
            }
        }
    }
}