{
    "id": "43e71764-280d-4ccb-91cb-63278db6bc3b",
    "changed": "2022-03-14T20:04:05Z",
    "content": "Check:\n  all:\n    - name: POOLID\n      operator: non_empty\n    - name: USUBJID\n      operator: non_empty\nCore:\n  Id: CORE-000230\n  Version: '1'\n  Status: Published\nDescription: Verify that when POOLID is populated, USUBJID is not populated\nOutcome:\n  Message: USUBJID must be null when POOLID is populated\n  Output Variables:\n    - POOLID\n    - USUBJID\nRule Type: Record Data\nSensitivity: Variable\nAuthorities:\n  - Organization: CDISC\n    Standards:\n      - Name: SDTMIG\n        Version: '3.4'\n        References:\n          - Origin: SDTM and SDTMIG Conformance Rules\n            Rule Identifier:\n              Id: CG0362\n              Version: '1'\n            Version: '2.0'\n            Citations:\n              - Cited Guidance: Either USUBJID or POOILD must be populated.\n                Document: Model v2.0\n                Item: USUBJID\n                Section: RELSUB\n              - Cited Guidance: Either USUBJID or POOILD must be populated.\n                Document: Model v2.0\n                Item: POOLID\n                Section: RELSUB\nScope:\n  Classes:\n    Include:\n      - SPECIAL-PURPOSE\n  Domains:\n    Include:\n      - RELSUB\n",
    "created": "2021-12-15T12:40:31Z",
    "creator": {
        "id": "57474fac-237e-4693-bb37-7826b02737da"
    },
    "json": {
        "Check": {
            "all": [
                {
                    "name": "POOLID",
                    "operator": "non_empty"
                },
                {
                    "name": "USUBJID",
                    "operator": "non_empty"
                }
            ]
        },
        "Core": {
            "Id": "CORE-000230",
            "Version": "1",
            "Status": "Published"
        },
        "Description": "Verify that when POOLID is populated, USUBJID is not populated",
        "Outcome": {
            "Message": "USUBJID must be null when POOLID is populated",
            "Output_Variables": [
                "POOLID",
                "USUBJID"
            ]
        },
        "Rule_Type": "Record Data",
        "Sensitivity": "Variable",
        "Authorities": [
            {
                "Organization": "CDISC",
                "Standards": [
                    {
                        "Name": "SDTMIG",
                        "Version": "3.4",
                        "References": [
                            {
                                "Origin": "SDTM and SDTMIG Conformance Rules",
                                "Rule_Identifier": {
                                    "Id": "CG0362",
                                    "Version": "1"
                                },
                                "Version": "2.0",
                                "Citations": [
                                    {
                                        "Cited_Guidance": "Either USUBJID or POOILD must be populated.",
                                        "Document": "Model v2.0",
                                        "Item": "USUBJID",
                                        "Section": "RELSUB"
                                    },
                                    {
                                        "Cited_Guidance": "Either USUBJID or POOILD must be populated.",
                                        "Document": "Model v2.0",
                                        "Item": "POOLID",
                                        "Section": "RELSUB"
                                    }
                                ]
                            }
                        ]
                    }
                ]
            }
        ],
        "Scope": {
            "Classes": {
                "Include": [
                    "SPECIAL-PURPOSE"
                ]
            },
            "Domains": {
                "Include": [
                    "RELSUB"
                ]
            }
        }
    }
}