{
    "id": "4da8ea6a-6139-4dfe-8605-e055068f1355",
    "changed": "2022-12-01T10:53:55.623Z",
    "content": "Check:\n  all:\n    - name: RSUBJID\n      operator: non_empty\n    - name: RSUBJID\n      operator: equal_to\n      value: POOLID\nCore:\n  Id: CORE-000232\n  Version: '1'\n  Status: Published\nDescription: Verify when RSUBJID is populated it does not equal POOLID\nOutcome:\n  Message: When RSUBJID is populated, RUSBJID cannot equal POOLID\n  Output Variables:\n    - RSUBJID\n    - POOLID\nRule Type: Record Data\nSensitivity: Record\nAuthorities:\n  - Organization: CDISC\n    Standards:\n      - Name: SDTMIG\n        Version: '3.4'\n        References:\n          - Origin: SDTM and SDTMIG Conformance Rules\n            Rule Identifier:\n              Id: CG0364\n              Version: '1'\n            Version: '2.0'\n            Citations:\n              - Cited Guidance: Identifier used to identify a related subject or pool\n                  of subjects. RSUBJID will be populated with either the  USUBJID\n                  of the related subject or the POOLID of the related pool.\n                Document: Model v2.0\n                Item: RSUBJID\n                Section: RELSUB\nScope:\n  Classes:\n    Include:\n      - RELATIONSHIP\n  Domains:\n    Include:\n      - RELSUB\n",
    "created": "2021-12-15T15:40:16Z",
    "creator": {
        "id": "57474fac-237e-4693-bb37-7826b02737da"
    },
    "json": {
        "Check": {
            "all": [
                {
                    "name": "RSUBJID",
                    "operator": "non_empty"
                },
                {
                    "name": "RSUBJID",
                    "operator": "equal_to",
                    "value": "POOLID"
                }
            ]
        },
        "Core": {
            "Id": "CORE-000232",
            "Version": "1",
            "Status": "Published"
        },
        "Description": "Verify when RSUBJID is populated it does not equal POOLID",
        "Outcome": {
            "Message": "When RSUBJID is populated, RUSBJID cannot equal POOLID",
            "Output_Variables": [
                "RSUBJID",
                "POOLID"
            ]
        },
        "Rule_Type": "Record Data",
        "Sensitivity": "Record",
        "Authorities": [
            {
                "Organization": "CDISC",
                "Standards": [
                    {
                        "Name": "SDTMIG",
                        "Version": "3.4",
                        "References": [
                            {
                                "Origin": "SDTM and SDTMIG Conformance Rules",
                                "Rule_Identifier": {
                                    "Id": "CG0364",
                                    "Version": "1"
                                },
                                "Version": "2.0",
                                "Citations": [
                                    {
                                        "Cited_Guidance": "Identifier used to identify a related subject or pool of subjects. RSUBJID will be populated with either the  USUBJID of the related subject or the POOLID of the related pool.",
                                        "Document": "Model v2.0",
                                        "Item": "RSUBJID",
                                        "Section": "RELSUB"
                                    }
                                ]
                            }
                        ]
                    }
                ]
            }
        ],
        "Scope": {
            "Classes": {
                "Include": [
                    "RELATIONSHIP"
                ]
            },
            "Domains": {
                "Include": [
                    "RELSUB"
                ]
            }
        }
    }
}