{
    "id": "e1e459ba-9c8c-403f-9993-e081478a227a",
    "changed": "2022-07-30T10:24:03Z",
    "content": "Check:\n  all:\n    - name: variable_label\n      operator: not_matches_regex\n      value: ^\\s*[A-Z]\\S*\\s*((a|an|the|and|but|or|for|in|of|on|with|([A-Z]\\S*))\\s*)*$\nCore:\n  Id: CDISC.SDTMIG.CG0359\n  Version: '1'\n  Status: Draft\nDescription: Title case should be used for all labels, where the first letter of every\n  word is capitalized except for articles, prepositions, and conjunctions\nOutcome:\n  Message: Variable label is not in title case (title case means to capitalize the\n    first letter of every word except for articles, prepositions, and conjunctions)\nRule Type: Variable Metadata Check\nSensitivity: Variable\nAuthorities:\n  - Organization: CDISC\n    Standards:\n      - Name: SDTMIG\n        Version: '3.4'\n        References:\n          - Origin: SDTM and SDTMIG Conformance Rules\n            Rule Identifier:\n              Id: CG0359\n              Version: '1'\n            Version: '2.0'\n            Citations:\n              - Cited Guidance: Use title case for all labels (title case means to\n                  capitalize the first letter of every word except for articles, prepositions,\n                  and conjunctions).\n                Document: IG v3.4\n                Item: 3h\n                Section: '2.6'\nScope:\n  Classes:\n    Include:\n      - ALL\n  Domains:\n    Include:\n      - ALL\n",
    "created": "2021-11-06T08:58:06Z",
    "creator": {
        "id": "ff471ff8-f131-4cf5-9712-c79cce6301a1"
    },
    "json": {
        "Check": {
            "all": [
                {
                    "name": "variable_label",
                    "operator": "not_matches_regex",
                    "value": "^\\s*[A-Z]\\S*\\s*((a|an|the|and|but|or|for|in|of|on|with|([A-Z]\\S*))\\s*)*$"
                }
            ]
        },
        "Core": {
            "Id": "CDISC.SDTMIG.CG0359",
            "Version": "1",
            "Status": "Draft"
        },
        "Description": "Title case should be used for all labels, where the first letter of every word is capitalized except for articles, prepositions, and conjunctions",
        "Outcome": {
            "Message": "Variable label is not in title case (title case means to capitalize the first letter of every word except for articles, prepositions, and conjunctions)"
        },
        "Rule_Type": "Variable Metadata Check",
        "Sensitivity": "Variable",
        "Authorities": [
            {
                "Organization": "CDISC",
                "Standards": [
                    {
                        "Name": "SDTMIG",
                        "Version": "3.4",
                        "References": [
                            {
                                "Origin": "SDTM and SDTMIG Conformance Rules",
                                "Rule_Identifier": {
                                    "Id": "CG0359",
                                    "Version": "1"
                                },
                                "Version": "2.0",
                                "Citations": [
                                    {
                                        "Cited_Guidance": "Use title case for all labels (title case means to capitalize the first letter of every word except for articles, prepositions, and conjunctions).",
                                        "Document": "IG v3.4",
                                        "Item": "3h",
                                        "Section": "2.6"
                                    }
                                ]
                            }
                        ]
                    }
                ]
            }
        ],
        "Scope": {
            "Classes": {
                "Include": [
                    "ALL"
                ]
            },
            "Domains": {
                "Include": [
                    "ALL"
                ]
            }
        }
    }
}