{
    "id": "79f70b85-8305-4d66-bbb2-ffe7bf07aff6",
    "changed": "2022-07-14T15:19:46Z",
    "content": "Check:\n  all:\n    - name: TSPARM\n      operator: is_not_unique_relationship\n      value: TSPARMCD\nCore:\n  Id: CORE-000179\n  Version: '1'\n  Status: Published\nDescription: Raise an error when TSPARM and TSPARMCD don't have a one-to-one relationship.\nOutcome:\n  Message: TSPARM and TSPARMCD don't have a one-to-one relationship.\n  Output Variables:\n    - TSPARM\n    - TSPARMCD\nRule Type: Record Data\nSensitivity: Record\nAuthorities:\n  - Organization: CDISC\n    Standards:\n      - Name: SDTMIG\n        Version: '3.4'\n        References:\n          - Origin: SDTM and SDTMIG Conformance Rules\n            Rule Identifier:\n              Id: CG0307\n              Version: '1'\n            Version: '2.0'\n            Citations:\n              - Cited Guidance: \"'TSPARMCD (the companion to TSPARM)'\"\n                Document: IG v3.4\n                Item: Specification\n                Section: 7.4.2\nScope:\n  Classes:\n    Include:\n      - TRIAL DESIGN\n  Domains:\n    Include:\n      - TS\n",
    "created": "2021-10-28T14:26:15Z",
    "creator": {
        "id": "76170e05-ed88-410d-8cad-ecd247a9050b"
    },
    "json": {
        "Check": {
            "all": [
                {
                    "name": "TSPARM",
                    "operator": "is_not_unique_relationship",
                    "value": "TSPARMCD"
                }
            ]
        },
        "Core": {
            "Id": "CORE-000179",
            "Version": "1",
            "Status": "Published"
        },
        "Description": "Raise an error when TSPARM and TSPARMCD don't have a one-to-one relationship.",
        "Outcome": {
            "Message": "TSPARM and TSPARMCD don't have a one-to-one relationship.",
            "Output_Variables": [
                "TSPARM",
                "TSPARMCD"
            ]
        },
        "Rule_Type": "Record Data",
        "Sensitivity": "Record",
        "Authorities": [
            {
                "Organization": "CDISC",
                "Standards": [
                    {
                        "Name": "SDTMIG",
                        "Version": "3.4",
                        "References": [
                            {
                                "Origin": "SDTM and SDTMIG Conformance Rules",
                                "Rule_Identifier": {
                                    "Id": "CG0307",
                                    "Version": "1"
                                },
                                "Version": "2.0",
                                "Citations": [
                                    {
                                        "Cited_Guidance": "'TSPARMCD (the companion to TSPARM)'",
                                        "Document": "IG v3.4",
                                        "Item": "Specification",
                                        "Section": "7.4.2"
                                    }
                                ]
                            }
                        ]
                    }
                ]
            }
        ],
        "Scope": {
            "Classes": {
                "Include": [
                    "TRIAL DESIGN"
                ]
            },
            "Domains": {
                "Include": [
                    "TS"
                ]
            }
        }
    }
}