{
    "id": "aa1215bd-ec8c-4353-b4fe-71fcdb87b237",
    "changed": "2022-03-14T20:03:33Z",
    "content": "Check:\n  all:\n    - name: RSUBJID\n      operator: non_empty\n    - name: RSUBJID\n      operator: equal_to\n      value: USUBJID\nCore:\n  Id: CORE-000231\n  Version: '1'\n  Status: Published\nDescription: Verify that when RSUBJID populated , RSUBJID does not equal USUBJID\nOutcome:\n  Message: RSUBJID when populated cannot equal USUBJID\n  Output Variables:\n    - RSUBJID\n    - USUBJID\nRule Type: Record Data\nSensitivity: Value\nAuthorities:\n  - Organization: CDISC\n    Standards:\n      - Name: SDTMIG\n        Version: '3.4'\n        References:\n          - Origin: SDTM and SDTMIG Conformance Rules\n            Rule Identifier:\n              Id: CG0363\n              Version: '1'\n            Version: '2.0'\n            Citations:\n              - Cited Guidance: Identifier used to identify a related subject or pool\n                  of subjects. RSUBJID will be populated with either the USUBJID of\n                  the related subject or the POOLID of the related pool.\n                Document: Model v2.0\n                Item: RSUBJID\n                Section: RELSUB\nScope:\n  Classes:\n    Include:\n      - RELATIONSHIP\n  Domains:\n    Include:\n      - RELSUB\n",
    "created": "2021-12-15T12:56:07Z",
    "creator": {
        "id": "57474fac-237e-4693-bb37-7826b02737da"
    },
    "json": {
        "Check": {
            "all": [
                {
                    "name": "RSUBJID",
                    "operator": "non_empty"
                },
                {
                    "name": "RSUBJID",
                    "operator": "equal_to",
                    "value": "USUBJID"
                }
            ]
        },
        "Core": {
            "Id": "CORE-000231",
            "Version": "1",
            "Status": "Published"
        },
        "Description": "Verify that when RSUBJID populated , RSUBJID does not equal USUBJID",
        "Outcome": {
            "Message": "RSUBJID when populated cannot equal USUBJID",
            "Output_Variables": [
                "RSUBJID",
                "USUBJID"
            ]
        },
        "Rule_Type": "Record Data",
        "Sensitivity": "Value",
        "Authorities": [
            {
                "Organization": "CDISC",
                "Standards": [
                    {
                        "Name": "SDTMIG",
                        "Version": "3.4",
                        "References": [
                            {
                                "Origin": "SDTM and SDTMIG Conformance Rules",
                                "Rule_Identifier": {
                                    "Id": "CG0363",
                                    "Version": "1"
                                },
                                "Version": "2.0",
                                "Citations": [
                                    {
                                        "Cited_Guidance": "Identifier used to identify a related subject or pool of subjects. RSUBJID will be populated with either the USUBJID of the related subject or the POOLID of the related pool.",
                                        "Document": "Model v2.0",
                                        "Item": "RSUBJID",
                                        "Section": "RELSUB"
                                    }
                                ]
                            }
                        ]
                    }
                ]
            }
        ],
        "Scope": {
            "Classes": {
                "Include": [
                    "RELATIONSHIP"
                ]
            },
            "Domains": {
                "Include": [
                    "RELSUB"
                ]
            }
        }
    }
}