{
    "id": "c234c795-56d2-432c-b98b-2e6f045e7e29",
    "changed": "2022-03-14T20:04:55Z",
    "content": "Check:\n  all:\n    - name: --DTHREL\n      operator: exists\nCore:\n  Id: CORE-000226\n  Version: '1'\n  Status: Published\nDescription: Verifying presence of SEND variable --DTHREL\nOutcome:\n  Message: --DTHREL must never be used in SDTM-based data for human clinical trials\n  Output Variables:\n    - --DTHREL\nRule Type: Record Data\nSensitivity: Variable\nAuthorities:\n  - Organization: CDISC\n    Standards:\n      - Name: SDTMIG\n        Version: '3.4'\n        References:\n          - Origin: SDTM and SDTMIG Conformance Rules\n            Rule Identifier:\n              Id: CG0352\n              Version: '1'\n            Version: '2.0'\n            Citations:\n              - Cited Guidance: 'The following SDTM variables, defined for use in\n                  non-clinical studies (SEND), must  NEVER be used in the submission\n                  of SDTM-based data for human clinical trials: --DTHREL (Findings)\n                  --EXCLFL (Findings) --REASEX (Findings) --DETECT (Findings)'\n                Document: Model v1.4\n                Item: '   '\n                Section: '2.7'\nScope:\n  Classes:\n    Include:\n      - ALL\n  Domains:\n    Include:\n      - ALL\n",
    "created": "2021-12-09T14:36:20Z",
    "creator": {
        "id": "57474fac-237e-4693-bb37-7826b02737da"
    },
    "json": {
        "Check": {
            "all": [
                {
                    "name": "--DTHREL",
                    "operator": "exists"
                }
            ]
        },
        "Core": {
            "Id": "CORE-000226",
            "Version": "1",
            "Status": "Published"
        },
        "Description": "Verifying presence of SEND variable --DTHREL",
        "Outcome": {
            "Message": "--DTHREL must never be used in SDTM-based data for human clinical trials",
            "Output_Variables": [
                "--DTHREL"
            ]
        },
        "Rule_Type": "Record Data",
        "Sensitivity": "Variable",
        "Authorities": [
            {
                "Organization": "CDISC",
                "Standards": [
                    {
                        "Name": "SDTMIG",
                        "Version": "3.4",
                        "References": [
                            {
                                "Origin": "SDTM and SDTMIG Conformance Rules",
                                "Rule_Identifier": {
                                    "Id": "CG0352",
                                    "Version": "1"
                                },
                                "Version": "2.0",
                                "Citations": [
                                    {
                                        "Cited_Guidance": "The following SDTM variables, defined for use in non-clinical studies (SEND), must  NEVER be used in the submission of SDTM-based data for human clinical trials: --DTHREL (Findings) --EXCLFL (Findings) --REASEX (Findings) --DETECT (Findings)",
                                        "Document": "Model v1.4",
                                        "Item": "   ",
                                        "Section": "2.7"
                                    }
                                ]
                            }
                        ]
                    }
                ]
            }
        ],
        "Scope": {
            "Classes": {
                "Include": [
                    "ALL"
                ]
            },
            "Domains": {
                "Include": [
                    "ALL"
                ]
            }
        }
    }
}