{
    "id": "9b7ea83b-6765-41a8-acca-500a44eefa84",
    "changed": "2022-02-15T21:30:12Z",
    "content": "Check:\n  all:\n    - name: --ORRES\n      operator: not_contained_by\n      value:\n        - Questionnaire CT\n    - name: --ORRES\n      operator: equals\n      value: MULTIPLE\nCore:\n  Id: CDISC.SDTMIG.CG0347\n  Version: '1'\n  Status: Draft\nDescription: Trigger error when --ORRES is equal to MULTIPLE when it is not a valid\n  response in the context of the finding (e.g., Questionnaire CT)\nOutcome:\n  Message: --ORRES is equal to MULTIPLE when it is not a valid response in the context\n    of the finding (e.g., Questionnaire CT)\nRule Type: Record Data\nSensitivity: Record\nAuthorities:\n  - Organization: CDISC\n    Standards:\n      - Name: SDTMIG\n        Version: '3.4'\n        References:\n          - Origin: SDTM and SDTMIG Conformance Rules\n            Rule Identifier:\n              Id: CG0347\n              Version: '1'\n            Version: '2.0'\n            Citations:\n              - Cited Guidance: If multiple result values (--ORRES) are reported for\n                  a test in a Findings class dataset, multiple records should be submitted\n                  for that --TESTCD. When a finding can have multiple results, the\n                  key structure for the findings dataset must be adequate to distinguish\n                  between the multiple results.  See Section 4.1.9 Assigning Natural\n                  Keys in the Metadata.\n                Document: IG v3.4\n                Section: 4.2.8.2\nScope:\n  Classes:\n    Include:\n      - FINDINGS\n  Domains:\n    Include:\n      - ALL\n",
    "created": "2021-11-06T08:38:13Z",
    "creator": {
        "id": "ff471ff8-f131-4cf5-9712-c79cce6301a1"
    },
    "json": {
        "Check": {
            "all": [
                {
                    "name": "--ORRES",
                    "operator": "not_contained_by",
                    "value": [
                        "Questionnaire CT"
                    ]
                },
                {
                    "name": "--ORRES",
                    "operator": "equals",
                    "value": "MULTIPLE"
                }
            ]
        },
        "Core": {
            "Id": "CDISC.SDTMIG.CG0347",
            "Version": "1",
            "Status": "Draft"
        },
        "Description": "Trigger error when --ORRES is equal to MULTIPLE when it is not a valid response in the context of the finding (e.g., Questionnaire CT)",
        "Outcome": {
            "Message": "--ORRES is equal to MULTIPLE when it is not a valid response in the context of the finding (e.g., Questionnaire CT)"
        },
        "Rule_Type": "Record Data",
        "Sensitivity": "Record",
        "Authorities": [
            {
                "Organization": "CDISC",
                "Standards": [
                    {
                        "Name": "SDTMIG",
                        "Version": "3.4",
                        "References": [
                            {
                                "Origin": "SDTM and SDTMIG Conformance Rules",
                                "Rule_Identifier": {
                                    "Id": "CG0347",
                                    "Version": "1"
                                },
                                "Version": "2.0",
                                "Citations": [
                                    {
                                        "Cited_Guidance": "If multiple result values (--ORRES) are reported for a test in a Findings class dataset, multiple records should be submitted for that --TESTCD. When a finding can have multiple results, the key structure for the findings dataset must be adequate to distinguish between the multiple results.  See Section 4.1.9 Assigning Natural Keys in the Metadata.",
                                        "Document": "IG v3.4",
                                        "Section": "4.2.8.2"
                                    }
                                ]
                            }
                        ]
                    }
                ]
            }
        ],
        "Scope": {
            "Classes": {
                "Include": [
                    "FINDINGS"
                ]
            },
            "Domains": {
                "Include": [
                    "ALL"
                ]
            }
        }
    }
}