{
    "id": "4d578463-8af4-4c54-917e-058771de2ccf",
    "changed": "2022-07-03T14:26:52Z",
    "content": "Check:\n  all:\n    - name: TDSTOFF\n      operator: not_equal_to\n      value: 0\n    - name: TDSTOFF\n      operator: not_matches_regex\n      value: ^P(([0-9]+Y)?([0-9]+M)?([0-9]+W)?([0-9]+D)?(T([0-9]+H)?([0-9]+M)?([0-9]+(\\.?[0-9]+)?S)?))?$\nCore:\n  Id: CDISC.SDTMIG.CG0376\n  Version: '1'\n  Status: Draft\nDescription: TDSTOFF must be equal to 0 or a positive value in ISO 8601 Duration format\nOutcome:\n  Message: TDSTOFF is not equal to zero or a positive value in ISO 8601 Duration format\nRule Type: Record Data\nSensitivity: Record\nAuthorities:\n  - Organization: CDISC\n    Standards:\n      - Name: SDTMIG\n        Version: '3.4'\n        References:\n          - Origin: SDTM and SDTMIG Conformance Rules\n            Rule Identifier:\n              Id: CG0376\n              Version: '1'\n            Version: '2.0'\n            Citations:\n              - Cited Guidance: 'A fixed offset from the date provided by the variable\n                  referenced in TDANCVAR. This is used when the timing of planned\n                  cycles does not start on the exact day referenced in the variable\n                  indicated in TDANCVAR. The value of this variable will be either\n                  zero or a positive value and will be represented in ISO 8601 character\n                  format.  '\n                Document: IG v3.4\n                Item: Specification\n                Section: 7.3.2\nScope:\n  Classes:\n    Include:\n      - TRIAL DESIGN\n  Domains:\n    Include:\n      - TD\n",
    "created": "2021-11-06T09:37:51Z",
    "creator": {
        "id": "ff471ff8-f131-4cf5-9712-c79cce6301a1"
    },
    "json": {
        "Check": {
            "all": [
                {
                    "name": "TDSTOFF",
                    "operator": "not_equal_to",
                    "value": 0
                },
                {
                    "name": "TDSTOFF",
                    "operator": "not_matches_regex",
                    "value": "^P(([0-9]+Y)?([0-9]+M)?([0-9]+W)?([0-9]+D)?(T([0-9]+H)?([0-9]+M)?([0-9]+(\\.?[0-9]+)?S)?))?$"
                }
            ]
        },
        "Core": {
            "Id": "CDISC.SDTMIG.CG0376",
            "Version": "1",
            "Status": "Draft"
        },
        "Description": "TDSTOFF must be equal to 0 or a positive value in ISO 8601 Duration format",
        "Outcome": {
            "Message": "TDSTOFF is not equal to zero or a positive value in ISO 8601 Duration format"
        },
        "Rule_Type": "Record Data",
        "Sensitivity": "Record",
        "Authorities": [
            {
                "Organization": "CDISC",
                "Standards": [
                    {
                        "Name": "SDTMIG",
                        "Version": "3.4",
                        "References": [
                            {
                                "Origin": "SDTM and SDTMIG Conformance Rules",
                                "Rule_Identifier": {
                                    "Id": "CG0376",
                                    "Version": "1"
                                },
                                "Version": "2.0",
                                "Citations": [
                                    {
                                        "Cited_Guidance": "A fixed offset from the date provided by the variable referenced in TDANCVAR. This is used when the timing of planned cycles does not start on the exact day referenced in the variable indicated in TDANCVAR. The value of this variable will be either zero or a positive value and will be represented in ISO 8601 character format.  ",
                                        "Document": "IG v3.4",
                                        "Item": "Specification",
                                        "Section": "7.3.2"
                                    }
                                ]
                            }
                        ]
                    }
                ]
            }
        ],
        "Scope": {
            "Classes": {
                "Include": [
                    "TRIAL DESIGN"
                ]
            },
            "Domains": {
                "Include": [
                    "TD"
                ]
            }
        }
    }
}