{
    "id": "5c47f917-50d8-45b2-aee2-80fef82c309b",
    "changed": "2022-07-29T09:04:02Z",
    "content": "Check:\n  all:\n    - name: RDOMAIN\n      operator: is_not_valid_reference\n      context: dataset_name\nCore:\n  Id: CDISC.SDTMIG.CG0369\n  Version: '1'\n  Status: Draft\nDescription: When RDOMAIN is populated the referenced RDOMAIN must exist as a DOMAIN\n  in the present study\nOutcome:\n  Message: RDOMAIN does not represent a dataset present in the study\n  Output Variables:\n    - RDOMAIN\n    - USUBJID\nRule Type: Record Data\nSensitivity: Record\nAuthorities:\n  - Organization: CDISC\n    Standards:\n      - Name: SDTMIG\n        Version: '3.4'\n        References:\n          - Origin: SDTM and SDTMIG Conformance Rules\n            Rule Identifier:\n              Id: CG0369\n              Version: '1'\n            Version: '2.0'\n            Citations:\n              - Cited Guidance: Each study must include 1 standardized set of observations\n                  in a specific structure; this is the Demographics domain described\n                  here.\n                Document: Model v2.0\n                Item: RDOMAIN\n                Section: Comments\n              - Cited Guidance: Each study must include 1 standardized set of observations\n                  in a specific structure; this is the Demographics domain described\n                  here.\n                Document: Model v2.0\n                Item: RDOMAIN\n                Section: Supplemental Qualifiers\n              - Cited Guidance: Each study must incude 1 standardized set of observations\n                  in a specific structure; this is the Demographics domain described\n                  here.\n                Document: Model v2.0\n                Item: RDOMAIN\n                Section: Related Records\nScope:\n  Classes:\n    Include:\n      - SPECIAL-PURPOSE\n  Domains:\n    Include:\n      - CO\n      - RELREC\n      - SUPP--\n",
    "created": "2021-11-06T09:56:03Z",
    "creator": {
        "id": "ff471ff8-f131-4cf5-9712-c79cce6301a1"
    },
    "json": {
        "Check": {
            "all": [
                {
                    "name": "RDOMAIN",
                    "operator": "is_not_valid_reference",
                    "context": "dataset_name"
                }
            ]
        },
        "Core": {
            "Id": "CDISC.SDTMIG.CG0369",
            "Version": "1",
            "Status": "Draft"
        },
        "Description": "When RDOMAIN is populated the referenced RDOMAIN must exist as a DOMAIN in the present study",
        "Outcome": {
            "Message": "RDOMAIN does not represent a dataset present in the study",
            "Output_Variables": [
                "RDOMAIN",
                "USUBJID"
            ]
        },
        "Rule_Type": "Record Data",
        "Sensitivity": "Record",
        "Authorities": [
            {
                "Organization": "CDISC",
                "Standards": [
                    {
                        "Name": "SDTMIG",
                        "Version": "3.4",
                        "References": [
                            {
                                "Origin": "SDTM and SDTMIG Conformance Rules",
                                "Rule_Identifier": {
                                    "Id": "CG0369",
                                    "Version": "1"
                                },
                                "Version": "2.0",
                                "Citations": [
                                    {
                                        "Cited_Guidance": "Each study must include 1 standardized set of observations in a specific structure; this is the Demographics domain described here.",
                                        "Document": "Model v2.0",
                                        "Item": "RDOMAIN",
                                        "Section": "Comments"
                                    },
                                    {
                                        "Cited_Guidance": "Each study must include 1 standardized set of observations in a specific structure; this is the Demographics domain described here.",
                                        "Document": "Model v2.0",
                                        "Item": "RDOMAIN",
                                        "Section": "Supplemental Qualifiers"
                                    },
                                    {
                                        "Cited_Guidance": "Each study must incude 1 standardized set of observations in a specific structure; this is the Demographics domain described here.",
                                        "Document": "Model v2.0",
                                        "Item": "RDOMAIN",
                                        "Section": "Related Records"
                                    }
                                ]
                            }
                        ]
                    }
                ]
            }
        ],
        "Scope": {
            "Classes": {
                "Include": [
                    "SPECIAL-PURPOSE"
                ]
            },
            "Domains": {
                "Include": [
                    "CO",
                    "RELREC",
                    "SUPP--"
                ]
            }
        }
    }
}