{
    "id": "513d1590-579f-4909-be51-745a306657af",
    "changed": "2023-02-21T15:38:22.242Z",
    "content": "Check:\n  any:\n    # - all:\n    #     - name: ETCD\n    #       operator: is_not_unique_set\n    #       value:\n    #         - ELEMENT\n    #         - TESTRL\n    #         - TEENRL\n    #     - name: TEDUR\n    #       operator: not_exists\n    # - all:\n    #     - name: ETCD\n    #       operator: is_not_unique_set\n    #       value:\n    #         - ELEMENT\n    #         - TESTRL\n    #         - TEDUR\n    #     - name: TEENRL\n    #       operator: not_exists\n    - name: ETCD\n      operator: is_not_unique_set\n      value:\n        - ELEMENT\n        - TESTRL\n        - TEENRL\n        - TEDUR\nCore:\n  Id: CDISC.SDTMIG.CG0325\n  Version: '1'\n  Status: Draft\nDescription: The combination of ELEMENT, TESTRL, TEENRL, and TEDUR must be unique\n  for each ETCD.\nOutcome:\n  Message: The combination of ELEMENT, TESTRL, TEENRL, and TEDUR is not unique for\n    each ETCD\n  Output Variables:\n    - ETCD\n    - ELEMENT\n    - TESTRL\n    - TEENRL\n    - TEDUR\nRule Type: Record Data\nSensitivity: Dataset\nAuthorities:\n  - Organization: CDISC\n    Standards:\n      - Name: SDTMIG\n        Version: '3.4'\n        References:\n          - Origin: SDTM and SDTMIG Conformance Rules\n            Rule Identifier:\n              Id: CG0325\n              Version: '2'\n            Version: '2.0'\n            Citations:\n              - Cited Guidance: Note that Elements that have different start and end\n                  rules are different Elements and must have different values of ELEMENT\n                  and ETCD.\n                Document: IG v3.4\n                Item: Assumption 13\n                Section: 7.2.2\nScope:\n  Classes:\n    Include:\n      - TRIAL DESIGN\n  Domains:\n    Include:\n      - TE\n",
    "created": "2021-11-06T08:25:01Z",
    "creator": {
        "id": "ff471ff8-f131-4cf5-9712-c79cce6301a1"
    },
    "json": {
        "Check": {
            "any": [
                {
                    "name": "ETCD",
                    "operator": "is_not_unique_set",
                    "value": [
                        "ELEMENT",
                        "TESTRL",
                        "TEENRL",
                        "TEDUR"
                    ]
                }
            ]
        },
        "Core": {
            "Id": "CDISC.SDTMIG.CG0325",
            "Version": "1",
            "Status": "Draft"
        },
        "Description": "The combination of ELEMENT, TESTRL, TEENRL, and TEDUR must be unique for each ETCD.",
        "Outcome": {
            "Message": "The combination of ELEMENT, TESTRL, TEENRL, and TEDUR is not unique for each ETCD",
            "Output_Variables": [
                "ETCD",
                "ELEMENT",
                "TESTRL",
                "TEENRL",
                "TEDUR"
            ]
        },
        "Sensitivity": "Dataset",
        "Authorities": [
            {
                "Organization": "CDISC",
                "Standards": [
                    {
                        "Name": "SDTMIG",
                        "Version": "3.4",
                        "References": [
                            {
                                "Origin": "SDTM and SDTMIG Conformance Rules",
                                "Version": "2.0",
                                "Citations": [
                                    {
                                        "Document": "IG v3.4",
                                        "Item": "Assumption 13",
                                        "Section": "7.2.2",
                                        "Cited_Guidance": "Note that Elements that have different start and end rules are different Elements and must have different values of ELEMENT and ETCD."
                                    }
                                ],
                                "Rule_Identifier": {
                                    "Id": "CG0325",
                                    "Version": "2"
                                }
                            }
                        ]
                    }
                ]
            }
        ],
        "Scope": {
            "Classes": {
                "Include": [
                    "TRIAL DESIGN"
                ]
            },
            "Domains": {
                "Include": [
                    "TE"
                ]
            }
        },
        "Rule_Type": "Record Data"
    }
}