{
    "id": "c8e99eb4-4e2f-4fa0-b318-1efc93dc9d79",
    "changed": "2022-03-17T11:52:27Z",
    "content": "Check:\n  all:\n    - name: --ORRES\n      operator: non_empty\n    - name: --STAT\n      operator: non_empty\nCore:\n  Id: CORE-000099\n  Version: '1'\n  Status: Published\nDescription: Raise an error when both --ORRES and --STAT values are populated\nOutcome:\n  Message: Value for --STAT is populated, when --ORRES is populated\n  Output Variables:\n    - --ORRES\n    - --STAT\nRule Type: Record Data\nSensitivity: Dataset\nAuthorities:\n  - Organization: CDISC\n    Standards:\n      - Name: SDTMIG\n        Version: '3.4'\n        References:\n          - Origin: SDTM and SDTMIG Conformance Rules\n            Rule Identifier:\n              Id: CG0422\n              Version: '1'\n            Version: '2.0'\n            Citations:\n              - Cited Guidance: The --ORRES variable contains the result of the measurement\n                  or finding as originally received or collected. --ORRES is an expected\n                  variable and should always be populated, except (1) when --STAT\n                  = \"NOT DONE\" (because there is no result for such a record) or (2)\n                  for derived records.\n                Document: IG v3.4\n                Item: --STAT\n                Section: 4.5.1.1\n              - Cited Guidance: Should be null or have a value of \"NOT DONE\".\n                Document: Model v2.0\n                Item: --STAT\n                Section: Findings\nScope:\n  Classes:\n    Include:\n      - FINDINGS\n  Domains:\n    Include:\n      - ALL\n",
    "created": "2021-10-06T20:55:34Z",
    "creator": {
        "id": "d0881041-369e-4940-b721-5b456d12101b"
    },
    "json": {
        "Check": {
            "all": [
                {
                    "name": "--ORRES",
                    "operator": "non_empty"
                },
                {
                    "name": "--STAT",
                    "operator": "non_empty"
                }
            ]
        },
        "Core": {
            "Id": "CORE-000099",
            "Version": "1",
            "Status": "Published"
        },
        "Description": "Raise an error when both --ORRES and --STAT values are populated",
        "Outcome": {
            "Message": "Value for --STAT is populated, when --ORRES is populated",
            "Output_Variables": [
                "--ORRES",
                "--STAT"
            ]
        },
        "Rule_Type": "Record Data",
        "Sensitivity": "Dataset",
        "Authorities": [
            {
                "Organization": "CDISC",
                "Standards": [
                    {
                        "Name": "SDTMIG",
                        "Version": "3.4",
                        "References": [
                            {
                                "Origin": "SDTM and SDTMIG Conformance Rules",
                                "Rule_Identifier": {
                                    "Id": "CG0422",
                                    "Version": "1"
                                },
                                "Version": "2.0",
                                "Citations": [
                                    {
                                        "Cited_Guidance": "The --ORRES variable contains the result of the measurement or finding as originally received or collected. --ORRES is an expected variable and should always be populated, except (1) when --STAT = \"NOT DONE\" (because there is no result for such a record) or (2) for derived records.",
                                        "Document": "IG v3.4",
                                        "Item": "--STAT",
                                        "Section": "4.5.1.1"
                                    },
                                    {
                                        "Cited_Guidance": "Should be null or have a value of \"NOT DONE\".",
                                        "Document": "Model v2.0",
                                        "Item": "--STAT",
                                        "Section": "Findings"
                                    }
                                ]
                            }
                        ]
                    }
                ]
            }
        ],
        "Scope": {
            "Classes": {
                "Include": [
                    "FINDINGS"
                ]
            },
            "Domains": {
                "Include": [
                    "ALL"
                ]
            }
        }
    }
}