{
    "id": "bf2ec34a-82a9-4dbb-a7f3-0071a8ba29fc",
    "changed": "2022-03-24T10:01:13Z",
    "content": "Check:\n  all:\n    - name: ETCD\n      operator: not_equal_to\n      value: UNPLAN\n    - name: ETCD\n      operator: is_not_contained_by\n      value: $te_etcd\nCore:\n  Id: CORE-000173\n  Version: '1'\n  Status: Published\nDescription: Raise an error when ETCD is not equal to 'UNPLAN' and not equal to TE.ETCD\nOperations:\n  - domain: TE\n    id: $te_etcd\n    name: ETCD\n    operator: distinct\nOutcome:\n  Message: ETCD is not equal to 'UNPLAN' and not equal to TE.ETCD\n  Output Variables:\n    - ETCD\nRule Type: Record Data\nSensitivity: Record\nAuthorities:\n  - Organization: CDISC\n    Standards:\n      - Name: SDTMIG\n        Version: '3.4'\n        References:\n          - Origin: SDTM and SDTMIG Conformance Rules\n            Rule Identifier:\n              Id: CG0414\n              Version: '1'\n            Version: '2.0'\n            Citations:\n              - Cited Guidance: The Subject Elements domain allows the submission\n                  of data on the timing of the trial Elements a subject actually passed\n                  through in their participation in the trial. Read Section 7.2.2,\n                  Trial Elements, on the Trial Elements (TE) dataset and Section 7.2.1,\n                  Trial Arms, on the Trial Arms (TA) dataset, as these datasets define\n                  a trial's planned Elements and describe the planned sequences of\n                  Elements for the Arms of the trial.\n                Document: SDTMIG V3.4\n                Item: Assumptions\n                Section: '5.3'\nScope:\n  Classes:\n    Include:\n      - SPECIAL-PURPOSE\n      - TRIAL DESIGN\n  Domains:\n    Include:\n      - SE\n      - TA\n",
    "created": "2021-10-26T09:45:20Z",
    "creator": {
        "id": "ae6dbbf3-4c9a-4149-b596-8183766167d4"
    },
    "json": {
        "Check": {
            "all": [
                {
                    "name": "ETCD",
                    "operator": "not_equal_to",
                    "value": "UNPLAN"
                },
                {
                    "name": "ETCD",
                    "operator": "is_not_contained_by",
                    "value": "$te_etcd"
                }
            ]
        },
        "Core": {
            "Id": "CORE-000173",
            "Version": "1",
            "Status": "Published"
        },
        "Description": "Raise an error when ETCD is not equal to 'UNPLAN' and not equal to TE.ETCD",
        "Operations": [
            {
                "domain": "TE",
                "id": "$te_etcd",
                "name": "ETCD",
                "operator": "distinct"
            }
        ],
        "Outcome": {
            "Message": "ETCD is not equal to 'UNPLAN' and not equal to TE.ETCD",
            "Output_Variables": [
                "ETCD"
            ]
        },
        "Rule_Type": "Record Data",
        "Sensitivity": "Record",
        "Authorities": [
            {
                "Organization": "CDISC",
                "Standards": [
                    {
                        "Name": "SDTMIG",
                        "Version": "3.4",
                        "References": [
                            {
                                "Origin": "SDTM and SDTMIG Conformance Rules",
                                "Rule_Identifier": {
                                    "Id": "CG0414",
                                    "Version": "1"
                                },
                                "Version": "2.0",
                                "Citations": [
                                    {
                                        "Cited_Guidance": "The Subject Elements domain allows the submission of data on the timing of the trial Elements a subject actually passed through in their participation in the trial. Read Section 7.2.2, Trial Elements, on the Trial Elements (TE) dataset and Section 7.2.1, Trial Arms, on the Trial Arms (TA) dataset, as these datasets define a trial's planned Elements and describe the planned sequences of Elements for the Arms of the trial.",
                                        "Document": "SDTMIG V3.4",
                                        "Item": "Assumptions",
                                        "Section": "5.3"
                                    }
                                ]
                            }
                        ]
                    }
                ]
            }
        ],
        "Scope": {
            "Classes": {
                "Include": [
                    "SPECIAL-PURPOSE",
                    "TRIAL DESIGN"
                ]
            },
            "Domains": {
                "Include": [
                    "SE",
                    "TA"
                ]
            }
        }
    }
}