{
    "id": "f655c5b2-f6d6-4938-8a0e-d7f14bad956e",
    "changed": "2022-08-04T15:35:24Z",
    "content": "Check:\n  all:\n    - name: VISITNUM\n      operator: is_contained_by\n      value: $tv_visitnum\n    - name: VISITNUM\n      operator: is_not_unique_set\n      value: USUBJID\nCore:\n  Id: CORE-000204\n  Version: '1'\n  Status: Published\nDescription: When VISITNUM is present in TV.VISITNUM, SV.VISITNUM must be unique within\n  subject\nOperations:\n  - domain: TV\n    id: $tv_visitnum\n    name: VISITNUM\n    operator: distinct\nOutcome:\n  Message: Scheduled or Contingent visit is not unique within subject\n  Output Variables:\n    - USUBJID\n    - VISITNUM\nRule Type: Record Data\nSensitivity: Record\nAuthorities:\n  - Organization: CDISC\n    Standards:\n      - Name: SDTMIG\n        Version: '3.4'\n        References:\n          - Origin: SDTM and SDTMIG Conformance Rules\n            Rule Identifier:\n              Id: CG0410\n              Version: '2'\n            Version: '2.0'\n            Citations:\n              - Cited Guidance: One record per subject per actual visit.\n                Document: IG v3.4\n                Item: 7.3.1.1 TV\n                Section: '5.5'\n              - Cited Guidance: Some data collection is contingent on the occurrence\n                  of a \"trigger\" event, or disease milestone (see the Trial Disease\n                  Milestones (TM) dataset under Section 7.3, Schedule for Assessments\n                  (TV, TD, and TM)). When such planned data collection involves an\n                  additional clinic visit, a \"contingent\" Visit may be included in\n                  the trial visits table, with start a rule that describes the circumstances\n                  under which it will take place. Since values of VISITNUM must be\n                  assigned to all records in the Trial Visits dataset, a contingent\n                  Visit included in the Trial Visits dataset must have a VISITNUM,\n                  but the VISITNUM value may not be a \"chronological\" value, due to\n                  the uncertain timing of a contingent Visit. If contingent visits\n                  are not included in the TV dataset, then they would be treated as\n                  unplanned visits in the Subject Visits (SV) domain.\n                Document: IG v3.4\n                Item: TV Issues 4\n                Section: 7.3.1.1\nScope:\n  Classes:\n    Include:\n      - SPECIAL-PURPOSE\n  Domains:\n    Include:\n      - SV\n",
    "created": "2021-11-06T09:16:04Z",
    "creator": {
        "id": "ff471ff8-f131-4cf5-9712-c79cce6301a1"
    },
    "json": {
        "Check": {
            "all": [
                {
                    "name": "VISITNUM",
                    "operator": "is_contained_by",
                    "value": "$tv_visitnum"
                },
                {
                    "name": "VISITNUM",
                    "operator": "is_not_unique_set",
                    "value": "USUBJID"
                }
            ]
        },
        "Core": {
            "Id": "CORE-000204",
            "Version": "1",
            "Status": "Published"
        },
        "Description": "When VISITNUM is present in TV.VISITNUM, SV.VISITNUM must be unique within subject",
        "Operations": [
            {
                "domain": "TV",
                "id": "$tv_visitnum",
                "name": "VISITNUM",
                "operator": "distinct"
            }
        ],
        "Outcome": {
            "Message": "Scheduled or Contingent visit is not unique within subject",
            "Output_Variables": [
                "USUBJID",
                "VISITNUM"
            ]
        },
        "Rule_Type": "Record Data",
        "Sensitivity": "Record",
        "Authorities": [
            {
                "Organization": "CDISC",
                "Standards": [
                    {
                        "Name": "SDTMIG",
                        "Version": "3.4",
                        "References": [
                            {
                                "Origin": "SDTM and SDTMIG Conformance Rules",
                                "Rule_Identifier": {
                                    "Id": "CG0410",
                                    "Version": "2"
                                },
                                "Version": "2.0",
                                "Citations": [
                                    {
                                        "Cited_Guidance": "One record per subject per actual visit.",
                                        "Document": "IG v3.4",
                                        "Item": "7.3.1.1 TV",
                                        "Section": "5.5"
                                    },
                                    {
                                        "Cited_Guidance": "Some data collection is contingent on the occurrence of a \"trigger\" event, or disease milestone (see the Trial Disease Milestones (TM) dataset under Section 7.3, Schedule for Assessments (TV, TD, and TM)). When such planned data collection involves an additional clinic visit, a \"contingent\" Visit may be included in the trial visits table, with start a rule that describes the circumstances under which it will take place. Since values of VISITNUM must be assigned to all records in the Trial Visits dataset, a contingent Visit included in the Trial Visits dataset must have a VISITNUM, but the VISITNUM value may not be a \"chronological\" value, due to the uncertain timing of a contingent Visit. If contingent visits are not included in the TV dataset, then they would be treated as unplanned visits in the Subject Visits (SV) domain.",
                                        "Document": "IG v3.4",
                                        "Item": "TV Issues 4",
                                        "Section": "7.3.1.1"
                                    }
                                ]
                            }
                        ]
                    }
                ]
            }
        ],
        "Scope": {
            "Classes": {
                "Include": [
                    "SPECIAL-PURPOSE"
                ]
            },
            "Domains": {
                "Include": [
                    "SV"
                ]
            }
        }
    }
}