{
    "id": "95d6d681-6916-4258-add5-8a759c916ea0",
    "changed": "2022-10-11T12:23:55.258Z",
    "content": "Check:\n  any:\n    - all:\n        - name: RDOMAIN\n          operator: equal_to\n          value: DM\n          value_is_literal: true\n        - name: USUBJID\n          operator: is_not_unique_set\n          value:\n            - QNAM\n    - all:\n        - name: RDOMAIN\n          operator: not_equal_to\n          value: DM\n          value_is_literal: true\n        - name: USUBJID\n          operator: is_not_unique_set\n          value:\n            - IDVAR\n            - IDVARVAL\n            - QNAM\nCore:\n  Id: CORE-000203\n  Version: '1'\n  Status: Published\nDescription: Trigger error when the combination of IDVAR, IDVARVAL, and QNAM is not\n  unique per parent subject record\nOutcome:\n  Message: The combination of IDVAR, IDVARVAL, and QNAM is not unique per parent subject\n    record\n  Output Variables:\n    - USUBJID\n    - IDVAR\n    - IDVARVAL\n    - QNAM\nRule Type: Record Data\nSensitivity: Record\nAuthorities:\n  - Organization: CDISC\n    Standards:\n      - Name: SDTMIG\n        Version: '3.4'\n        References:\n          - Origin: SDTM and SDTMIG Conformance Rules\n            Rule Identifier:\n              Id: CG0411\n              Version: '1'\n            Version: '2.0'\n            Citations:\n              - Cited Guidance: The combined set of values for the first six columns\n                  (STUDYID\u2026QNAM) should be unique for every record. That is, there\n                  should not be multiple records in a SUPP-- dataset for the same\n                  QNAM value, as it relates to IDVAR/IDVARVAL for a USUBJID in a domain.\n                Document: IG v3.4\n                Section: '8.4'\nScope:\n  Classes:\n    Include:\n      - ALL\n  Domains:\n    Include:\n      - SUPP--\n",
    "created": "2021-11-06T09:12:55Z",
    "creator": {
        "id": "ff471ff8-f131-4cf5-9712-c79cce6301a1"
    },
    "json": {
        "Check": {
            "any": [
                {
                    "all": [
                        {
                            "name": "RDOMAIN",
                            "operator": "equal_to",
                            "value": "DM",
                            "value_is_literal": true
                        },
                        {
                            "name": "USUBJID",
                            "operator": "is_not_unique_set",
                            "value": [
                                "QNAM"
                            ]
                        }
                    ]
                },
                {
                    "all": [
                        {
                            "name": "RDOMAIN",
                            "operator": "not_equal_to",
                            "value": "DM",
                            "value_is_literal": true
                        },
                        {
                            "name": "USUBJID",
                            "operator": "is_not_unique_set",
                            "value": [
                                "IDVAR",
                                "IDVARVAL",
                                "QNAM"
                            ]
                        }
                    ]
                }
            ]
        },
        "Core": {
            "Id": "CORE-000203",
            "Version": "1",
            "Status": "Published"
        },
        "Description": "Trigger error when the combination of IDVAR, IDVARVAL, and QNAM is not unique per parent subject record",
        "Outcome": {
            "Message": "The combination of IDVAR, IDVARVAL, and QNAM is not unique per parent subject record",
            "Output_Variables": [
                "USUBJID",
                "IDVAR",
                "IDVARVAL",
                "QNAM"
            ]
        },
        "Rule_Type": "Record Data",
        "Sensitivity": "Record",
        "Authorities": [
            {
                "Organization": "CDISC",
                "Standards": [
                    {
                        "Name": "SDTMIG",
                        "Version": "3.4",
                        "References": [
                            {
                                "Origin": "SDTM and SDTMIG Conformance Rules",
                                "Rule_Identifier": {
                                    "Id": "CG0411",
                                    "Version": "1"
                                },
                                "Version": "2.0",
                                "Citations": [
                                    {
                                        "Cited_Guidance": "The combined set of values for the first six columns (STUDYID\u2026QNAM) should be unique for every record. That is, there should not be multiple records in a SUPP-- dataset for the same QNAM value, as it relates to IDVAR/IDVARVAL for a USUBJID in a domain.",
                                        "Document": "IG v3.4",
                                        "Section": "8.4"
                                    }
                                ]
                            }
                        ]
                    }
                ]
            }
        ],
        "Scope": {
            "Classes": {
                "Include": [
                    "ALL"
                ]
            },
            "Domains": {
                "Include": [
                    "SUPP--"
                ]
            }
        }
    }
}