{
    "id": "0dcf27ff-4e9e-42bc-aa40-6d49526ffaa1",
    "changed": "2022-07-17T04:49:42Z",
    "content": "Check:\n  all:\n    - name: ARMCD\n      operator: longer_than_or_equal_to\n      value: 21\nCore:\n  Id: CDISC.SDTMIG.CG0415\n  Version: '1'\n  Status: Draft\nDescription: Verify that ARMCD in TA domain is valid planned arm code\nOutcome:\n  Message: Length of ARMCD must be less than or equal to 20 characters\nRule Type: Record Data\nSensitivity: Value\nAuthorities:\n  - Organization: CDISC\n    Standards:\n      - Name: SDTMIG\n        Version: '3.4'\n        References:\n          - Origin: SDTM and SDTMIG Conformance Rules\n            Rule Identifier:\n              Id: CG0415\n              Version: '1'\n            Version: '2.0'\n            Citations:\n              - Cited Guidance: A trial design domain that contains each planned arm\n                  in the trial.\n                Document: IG 3.4\n                Item: ''\n                Section: 7.2.1 TA\nScope:\n  Classes:\n    Include:\n      - TRIAL DESIGN\n  Domains:\n    Include:\n      - TA\n",
    "created": "2021-12-16T13:54:35Z",
    "creator": {
        "id": "57474fac-237e-4693-bb37-7826b02737da"
    },
    "json": {
        "Check": {
            "all": [
                {
                    "name": "ARMCD",
                    "operator": "longer_than_or_equal_to",
                    "value": 21
                }
            ]
        },
        "Core": {
            "Id": "CDISC.SDTMIG.CG0415",
            "Version": "1",
            "Status": "Draft"
        },
        "Description": "Verify that ARMCD in TA domain is valid planned arm code",
        "Outcome": {
            "Message": "Length of ARMCD must be less than or equal to 20 characters"
        },
        "Rule_Type": "Record Data",
        "Sensitivity": "Value",
        "Authorities": [
            {
                "Organization": "CDISC",
                "Standards": [
                    {
                        "Name": "SDTMIG",
                        "Version": "3.4",
                        "References": [
                            {
                                "Origin": "SDTM and SDTMIG Conformance Rules",
                                "Rule_Identifier": {
                                    "Id": "CG0415",
                                    "Version": "1"
                                },
                                "Version": "2.0",
                                "Citations": [
                                    {
                                        "Cited_Guidance": "A trial design domain that contains each planned arm in the trial.",
                                        "Document": "IG 3.4",
                                        "Item": "",
                                        "Section": "7.2.1 TA"
                                    }
                                ]
                            }
                        ]
                    }
                ]
            }
        ],
        "Scope": {
            "Classes": {
                "Include": [
                    "TRIAL DESIGN"
                ]
            },
            "Domains": {
                "Include": [
                    "TA"
                ]
            }
        }
    }
}