{
    "id": "921ca633-d781-4eb4-b112-1bbe382db122",
    "changed": "2022-10-11T12:54:03.709Z",
    "content": "Check:\n  all:\n    - name: --TPT\n      operator: exists\n    - name: --TPTNUM\n      operator: not_exists\nCore:\n  Id: CORE-000026\n  Version: '1'\n  Status: Published\nDescription: When --TPT is present in a dataset, --TPTNUM must also be present.\nOutcome:\n  Message: The --TPTNUM variable does not exist when --TPT does exist.\nRule Type: Record Data\nSensitivity: Dataset\nAuthorities:\n  - Organization: CDISC\n    Standards:\n      - Name: SDTMIG\n        Version: '3.4'\n        References:\n          - Origin: SDTM and SDTMIG Conformance Rules\n            Rule Identifier:\n              Id: CG0468\n              Version: '1'\n            Version: '2.0'\n            Citations:\n              - Cited Guidance: When time points are represented in SDTMIG domains,\n                  both --TPT and --TPTNUM must be used.\n                Document: IG v3.3\n                Section: 4.4.10 Timing Variables for All Classes\nScope:\n  Classes:\n    Include:\n      - ALL\n  Domains:\n    Include:\n      - ALL\n",
    "created": "2021-09-29T21:09:47Z",
    "creator": {
        "id": "bd422eaf-bc35-4410-a098-59b9fe63965e"
    },
    "json": {
        "Check": {
            "all": [
                {
                    "name": "--TPT",
                    "operator": "exists"
                },
                {
                    "name": "--TPTNUM",
                    "operator": "not_exists"
                }
            ]
        },
        "Core": {
            "Id": "CORE-000026",
            "Version": "1",
            "Status": "Published"
        },
        "Description": "When --TPT is present in a dataset, --TPTNUM must also be present.",
        "Outcome": {
            "Message": "The --TPTNUM variable does not exist when --TPT does exist."
        },
        "Rule_Type": "Record Data",
        "Sensitivity": "Dataset",
        "Authorities": [
            {
                "Organization": "CDISC",
                "Standards": [
                    {
                        "Name": "SDTMIG",
                        "Version": "3.4",
                        "References": [
                            {
                                "Origin": "SDTM and SDTMIG Conformance Rules",
                                "Rule_Identifier": {
                                    "Id": "CG0468",
                                    "Version": "1"
                                },
                                "Version": "2.0",
                                "Citations": [
                                    {
                                        "Cited_Guidance": "When time points are represented in SDTMIG domains, both --TPT and --TPTNUM must be used.",
                                        "Document": "IG v3.3",
                                        "Section": "4.4.10 Timing Variables for All Classes"
                                    }
                                ]
                            }
                        ]
                    }
                ]
            }
        ],
        "Scope": {
            "Classes": {
                "Include": [
                    "ALL"
                ]
            },
            "Domains": {
                "Include": [
                    "ALL"
                ]
            }
        }
    }
}