{
    "id": "21aeed8b-25e0-4072-975b-96fb23ecb2a7",
    "changed": "2022-02-15T21:26:59Z",
    "content": "Check:\n  all:\n    - name: --STRESC\n      operator: not_empty\n    - name:\n      operator:\n    - name: --STRESU\n      operator: empty\nCore:\n  Id: CDISC.SDTMIG.CG0425\n  Version: '1'\n  Status: Draft\nDescription: Trigger error if --STRESU is null when --STRESC ^= null and units are\n  applicable for the result\nOutcome:\n  Message: --STRESU is null when --STRESC ^= null and units are applicable for the\n    result\nRule Type: Record Data\nSensitivity: Record\nAuthorities:\n  - Organization: CDISC\n    Standards:\n      - Name: SDTMIG\n        Version: '3.4'\n        References:\n          - Origin: SDTM and SDTMIG Conformance Rules\n            Rule Identifier:\n              Id: CG0425\n              Version: '1'\n            Version: '2.0'\n            Citations:\n              - Cited Guidance: 'The unit of measure for the standardized result of\n                  the measurement, test, or examination.  Variable(s) Qualified: --STRESC\n                  and --STRESN and --STNRLO and --STNRHI and --STREFC and --STREFN\n                  and --LLOQ and --ULOQ.'\n                Document: Model v2.0\n                Item: --STRESU\n                Section: Findings\nScope:\n  Classes:\n    Include:\n      - FINDINGS\n  Domains:\n    Include:\n      - ALL\n",
    "created": "2021-11-06T09:04:46Z",
    "creator": {
        "id": "ff471ff8-f131-4cf5-9712-c79cce6301a1"
    },
    "json": {
        "Check": {
            "all": [
                {
                    "name": "--STRESC",
                    "operator": "not_empty"
                },
                {
                    "name": null,
                    "operator": null
                },
                {
                    "name": "--STRESU",
                    "operator": "empty"
                }
            ]
        },
        "Core": {
            "Id": "CDISC.SDTMIG.CG0425",
            "Version": "1",
            "Status": "Draft"
        },
        "Description": "Trigger error if --STRESU is null when --STRESC ^= null and units are applicable for the result",
        "Outcome": {
            "Message": "--STRESU is null when --STRESC ^= null and units are applicable for the result"
        },
        "Rule_Type": "Record Data",
        "Sensitivity": "Record",
        "Authorities": [
            {
                "Organization": "CDISC",
                "Standards": [
                    {
                        "Name": "SDTMIG",
                        "Version": "3.4",
                        "References": [
                            {
                                "Origin": "SDTM and SDTMIG Conformance Rules",
                                "Rule_Identifier": {
                                    "Id": "CG0425",
                                    "Version": "1"
                                },
                                "Version": "2.0",
                                "Citations": [
                                    {
                                        "Cited_Guidance": "The unit of measure for the standardized result of the measurement, test, or examination.  Variable(s) Qualified: --STRESC and --STRESN and --STNRLO and --STNRHI and --STREFC and --STREFN and --LLOQ and --ULOQ.",
                                        "Document": "Model v2.0",
                                        "Item": "--STRESU",
                                        "Section": "Findings"
                                    }
                                ]
                            }
                        ]
                    }
                ]
            }
        ],
        "Scope": {
            "Classes": {
                "Include": [
                    "FINDINGS"
                ]
            },
            "Domains": {
                "Include": [
                    "ALL"
                ]
            }
        }
    }
}