{
    "id": "4df36a40-f05f-4e15-ad75-83708bccfce7",
    "changed": "2022-10-11T13:50:06.940Z",
    "content": "Check:\n  all:\n    - name: --STRESU\n      operator: non_empty\n    - name: --STRESC\n      operator: empty\nCore:\n  Id: CORE-000133\n  Version: '1'\n  Status: Published\nDescription: When --STRESU is populated, --STRESC must also be populated. Please note\n  that this rule, as executed, cannot check if --STRESC is populated with the standardized\n  unit.\nOutcome:\n  Message: Missing value for --STRESC, when --STRESU is provided\nRule Type: Record Data\nSensitivity: Record\nAuthorities:\n  - Organization: CDISC\n    Standards:\n      - Name: SDTMIG\n        Version: '3.4'\n        References:\n          - Origin: SDTM and SDTMIG Conformance Rules\n            Rule Identifier:\n              Id: CG0426\n              Version: '1'\n            Version: '2.0'\n            Citations:\n              - Cited Guidance: The unit of measure for the standardized result of\n                  the measurement, test, or examination.  Variable(s) Qualified, --STRESC\n                  and --STRESN and --STNRLO and --STNRHI and --STREFC and --STREFN\n                  and --LLOQ and --ULOQ.\n                Document: Model v2.0\n                Section: Findings\nScope:\n  Classes:\n    Include:\n      - FINDINGS\n  Domains:\n    Include:\n      - ALL\n",
    "created": "2021-10-13T09:41:54Z",
    "creator": {
        "id": "deb2bb4c-9e4c-4fad-a4b2-1c8487962681"
    },
    "json": {
        "Check": {
            "all": [
                {
                    "name": "--STRESU",
                    "operator": "non_empty"
                },
                {
                    "name": "--STRESC",
                    "operator": "empty"
                }
            ]
        },
        "Core": {
            "Id": "CORE-000133",
            "Version": "1",
            "Status": "Published"
        },
        "Description": "When --STRESU is populated, --STRESC must also be populated. Please note that this rule, as executed, cannot check if --STRESC is populated with the standardized unit.",
        "Outcome": {
            "Message": "Missing value for --STRESC, when --STRESU is provided"
        },
        "Rule_Type": "Record Data",
        "Sensitivity": "Record",
        "Authorities": [
            {
                "Organization": "CDISC",
                "Standards": [
                    {
                        "Name": "SDTMIG",
                        "Version": "3.4",
                        "References": [
                            {
                                "Origin": "SDTM and SDTMIG Conformance Rules",
                                "Rule_Identifier": {
                                    "Id": "CG0426",
                                    "Version": "1"
                                },
                                "Version": "2.0",
                                "Citations": [
                                    {
                                        "Cited_Guidance": "The unit of measure for the standardized result of the measurement, test, or examination.  Variable(s) Qualified, --STRESC and --STRESN and --STNRLO and --STNRHI and --STREFC and --STREFN and --LLOQ and --ULOQ.",
                                        "Document": "Model v2.0",
                                        "Section": "Findings"
                                    }
                                ]
                            }
                        ]
                    }
                ]
            }
        ],
        "Scope": {
            "Classes": {
                "Include": [
                    "FINDINGS"
                ]
            },
            "Domains": {
                "Include": [
                    "ALL"
                ]
            }
        }
    }
}