{
    "id": "813e488e-b41e-4266-bebb-b70342955bf9",
    "changed": "2022-07-27T19:34:19Z",
    "content": "Check:\n  all:\n    - name: IDVAR\n      operator: suffix_matches_regex\n      suffix: 3\n      value: SEQ\n    - name: RELTYPE\n      operator: non_empty\nCore:\n  Id: CORE-000202\n  Version: '1'\n  Status: Published\nDescription: When IDVAR is populated with a --SEQ value, RELTYPE must be null.\nOutcome:\n  Message: RELTYPE is populated when IDVAR is populated with a --SEQ value.\n  Output Variables:\n    - IDVAR\n    - RELTYPE\nRule Type: Record Data\nSensitivity: Record\nAuthorities:\n  - Organization: CDISC\n    Standards:\n      - Name: SDTMIG\n        Version: '3.4'\n        References:\n          - Origin: SDTM and SDTMIG Conformance Rules\n            Rule Identifier:\n              Id: CG0419\n              Version: '1'\n            Version: '2.0'\n            Citations:\n              - Cited Guidance: Identifies the hierarchical level of the records in\n                  the relationship. Values should be either ONE or MANY. Used only\n                  when identifying a relationship between datasets (as described in\n                  Section 8.3, Relating Datasets).\n                Document: IG 3.4\n                Section: 8.2.1\n              - Cited Guidance: Since IDVAR identifies the keys that can be used to\n                  merge/join records between the datasets, --SEQ cannot be used because\n                  --SEQ only has meaning within a subject within a dataset, not across\n                  datasets.\n                Document: IG 3.4\n                Section: 8.3.1\nScope:\n  Classes:\n    Include:\n      - SPECIAL-PURPOSE\n  Domains:\n    Include:\n      - RELREC\n",
    "created": "2021-11-06T09:07:22Z",
    "creator": {
        "id": "ff471ff8-f131-4cf5-9712-c79cce6301a1"
    },
    "json": {
        "Check": {
            "all": [
                {
                    "name": "IDVAR",
                    "operator": "suffix_matches_regex",
                    "suffix": 3,
                    "value": "SEQ"
                },
                {
                    "name": "RELTYPE",
                    "operator": "non_empty"
                }
            ]
        },
        "Core": {
            "Id": "CORE-000202",
            "Version": "1",
            "Status": "Published"
        },
        "Description": "When IDVAR is populated with a --SEQ value, RELTYPE must be null.",
        "Outcome": {
            "Message": "RELTYPE is populated when IDVAR is populated with a --SEQ value.",
            "Output_Variables": [
                "IDVAR",
                "RELTYPE"
            ]
        },
        "Rule_Type": "Record Data",
        "Sensitivity": "Record",
        "Authorities": [
            {
                "Organization": "CDISC",
                "Standards": [
                    {
                        "Name": "SDTMIG",
                        "Version": "3.4",
                        "References": [
                            {
                                "Origin": "SDTM and SDTMIG Conformance Rules",
                                "Rule_Identifier": {
                                    "Id": "CG0419",
                                    "Version": "1"
                                },
                                "Version": "2.0",
                                "Citations": [
                                    {
                                        "Cited_Guidance": "Identifies the hierarchical level of the records in the relationship. Values should be either ONE or MANY. Used only when identifying a relationship between datasets (as described in Section 8.3, Relating Datasets).",
                                        "Document": "IG 3.4",
                                        "Section": "8.2.1"
                                    },
                                    {
                                        "Cited_Guidance": "Since IDVAR identifies the keys that can be used to merge/join records between the datasets, --SEQ cannot be used because --SEQ only has meaning within a subject within a dataset, not across datasets.",
                                        "Document": "IG 3.4",
                                        "Section": "8.3.1"
                                    }
                                ]
                            }
                        ]
                    }
                ]
            }
        ],
        "Scope": {
            "Classes": {
                "Include": [
                    "SPECIAL-PURPOSE"
                ]
            },
            "Domains": {
                "Include": [
                    "RELREC"
                ]
            }
        }
    }
}