{
    "id": "e088472d-0625-45b3-b803-415d9aed65d1",
    "changed": "2022-07-15T12:25:34Z",
    "content": "Check:\n  all:\n    - name: --OCCUR\n      operator: equal_to\n      value: N\n    - name: --ENRF\n      operator: non_empty\nCore:\n  Id: CORE-000241\n  Version: '1'\n  Status: Published\nDescription: When --OCCUR = 'N', --ENRF must not be populated\nOutcome:\n  Message: --ENRF is populated when --OCCUR = \"N\"\n  Output Variables:\n    - --ENRF\nRule Type: Record Data\nSensitivity: Record\nAuthorities:\n  - Organization: CDISC\n    Standards:\n      - Name: SDTMIG\n        Version: '3.4'\n        References:\n          - Origin: SDTM and SDTMIG Conformance Rules\n            Rule Identifier:\n              Id: CG0421\n              Version: '1'\n            Version: '2.0'\n            Citations:\n              - Cited Guidance: The characterization of the end of an observation\n                  relative to the study reference period. The sponsor-defined reference\n                  period is a continuous period of time defined by a discrete starting\n                  point and a discrete ending point represented by RFSTDTC and RFENDTC\n                  in Demographics.\n                Document: Model v2.0\n                Item: --ENRF\n                Section: Timing\nScope:\n  Classes:\n    Include:\n      - INTERVENTIONS\n      - EVENTS\n  Domains:\n    Include:\n      - ALL\n",
    "created": "2022-02-05T06:27:49Z",
    "creator": {
        "id": "ff471ff8-f131-4cf5-9712-c79cce6301a1"
    },
    "json": {
        "Check": {
            "all": [
                {
                    "name": "--OCCUR",
                    "operator": "equal_to",
                    "value": "N"
                },
                {
                    "name": "--ENRF",
                    "operator": "non_empty"
                }
            ]
        },
        "Core": {
            "Id": "CORE-000241",
            "Version": "1",
            "Status": "Published"
        },
        "Description": "When --OCCUR = 'N', --ENRF must not be populated",
        "Outcome": {
            "Message": "--ENRF is populated when --OCCUR = \"N\"",
            "Output_Variables": [
                "--ENRF"
            ]
        },
        "Rule_Type": "Record Data",
        "Sensitivity": "Record",
        "Authorities": [
            {
                "Organization": "CDISC",
                "Standards": [
                    {
                        "Name": "SDTMIG",
                        "Version": "3.4",
                        "References": [
                            {
                                "Origin": "SDTM and SDTMIG Conformance Rules",
                                "Rule_Identifier": {
                                    "Id": "CG0421",
                                    "Version": "1"
                                },
                                "Version": "2.0",
                                "Citations": [
                                    {
                                        "Cited_Guidance": "The characterization of the end of an observation relative to the study reference period. The sponsor-defined reference period is a continuous period of time defined by a discrete starting point and a discrete ending point represented by RFSTDTC and RFENDTC in Demographics.",
                                        "Document": "Model v2.0",
                                        "Item": "--ENRF",
                                        "Section": "Timing"
                                    }
                                ]
                            }
                        ]
                    }
                ]
            }
        ],
        "Scope": {
            "Classes": {
                "Include": [
                    "INTERVENTIONS",
                    "EVENTS"
                ]
            },
            "Domains": {
                "Include": [
                    "ALL"
                ]
            }
        }
    }
}