{
    "id": "ecd4d80a-f5fa-4f9e-abad-31403dcbffb6",
    "changed": "2022-03-10T12:55:29Z",
    "content": "Check:\n  all:\n    - name: --TEST\n      operator: longer_than\n      value: 40\nCore:\n  Id: CORE-000199\n  Version: '1'\n  Status: Published\nDescription: Raise an error when length of --TEST > 40.\nOutcome:\n  Message: Value length of --TEST > 40.\n  Output Variables:\n    - --TEST\nRule Type: Record Data\nSensitivity: Record\nAuthorities:\n  - Organization: CDISC\n    Standards:\n      - Name: SDTMIG\n        Version: '3.4'\n        References:\n          - Origin: SDTM and SDTMIG Conformance Rules\n            Rule Identifier:\n              Id: CG0406\n              Version: '1'\n            Version: '2.0'\n            Citations:\n              - Cited Guidance: Since the --TEST variable is meant to serve as a label\n                  for a --TESTCD when a Findings dataset is transposed to a more horizontal\n                  format, the length of --TEST is limited to 40 characters (except\n                  as noted below) to conform to the limitations of the SAS v5 Transport\n                  format currently used for submission datasets.... IETEST values\n                  in IE and TI are exceptions to the above 40-character rule and are\n                  limited to 200 characters, since they are not expected to be transformed\n                  to column labels.\n                Document: IG v3.4\n                Section: 4.5.3.1\nScope:\n  Classes:\n    Include:\n      - FINDINGS\n  Domains:\n    Exclude:\n      - IE\n",
    "created": "2021-11-04T10:11:16Z",
    "creator": {
        "id": "02c3c969-4787-4d57-b164-e2851035c0e8"
    },
    "json": {
        "Check": {
            "all": [
                {
                    "name": "--TEST",
                    "operator": "longer_than",
                    "value": 40
                }
            ]
        },
        "Core": {
            "Id": "CORE-000199",
            "Version": "1",
            "Status": "Published"
        },
        "Description": "Raise an error when length of --TEST > 40.",
        "Outcome": {
            "Message": "Value length of --TEST > 40.",
            "Output_Variables": [
                "--TEST"
            ]
        },
        "Rule_Type": "Record Data",
        "Sensitivity": "Record",
        "Authorities": [
            {
                "Organization": "CDISC",
                "Standards": [
                    {
                        "Name": "SDTMIG",
                        "Version": "3.4",
                        "References": [
                            {
                                "Origin": "SDTM and SDTMIG Conformance Rules",
                                "Rule_Identifier": {
                                    "Id": "CG0406",
                                    "Version": "1"
                                },
                                "Version": "2.0",
                                "Citations": [
                                    {
                                        "Cited_Guidance": "Since the --TEST variable is meant to serve as a label for a --TESTCD when a Findings dataset is transposed to a more horizontal format, the length of --TEST is limited to 40 characters (except as noted below) to conform to the limitations of the SAS v5 Transport format currently used for submission datasets.... IETEST values in IE and TI are exceptions to the above 40-character rule and are limited to 200 characters, since they are not expected to be transformed to column labels.",
                                        "Document": "IG v3.4",
                                        "Section": "4.5.3.1"
                                    }
                                ]
                            }
                        ]
                    }
                ]
            }
        ],
        "Scope": {
            "Classes": {
                "Include": [
                    "FINDINGS"
                ]
            },
            "Domains": {
                "Exclude": [
                    "IE"
                ]
            }
        }
    }
}