{
    "id": "817c188f-269a-4521-89e0-6d73695928d6",
    "changed": "2022-03-17T13:30:56Z",
    "content": "Check:\n  all:\n    - name: AGEU\n      operator: non_empty\n    - name: AGE\n      operator: empty\n    - name: AGETXT\n      operator: empty\nCore:\n  Id: CORE-000122\n  Version: '1'\n  Status: Published\nDescription: Raise an error when both AGETXT and AGE are empty, but AGEU is populated.\nOutcome:\n  Message: AGEU not empty, but AGE empty and AGETXT empty\n  Output Variables:\n    - AGE\n    - AGEU\n    - AGETXT\nRule Type: Record Data\nSensitivity: Record\nAuthorities:\n  - Organization: CDISC\n    Standards:\n      - Name: SDTMIG\n        Version: '3.4'\n        References:\n          - Origin: SDTM and SDTMIG Conformance Rules\n            Rule Identifier:\n              Id: CG0434\n              Version: '1'\n            Version: '2.0'\n            Citations:\n              - Cited Guidance: Variable Qualifier of AGE or AGETXT.\n                Document: Model v2.0\n                Item: AGEU\n                Section: Demographics\nScope:\n  Classes:\n    Include:\n      - SPECIAL-PURPOSE\n  Domains:\n    Include:\n      - DM\n",
    "created": "2021-10-12T02:45:08Z",
    "creator": {
        "id": "d0881041-369e-4940-b721-5b456d12101b"
    },
    "json": {
        "Check": {
            "all": [
                {
                    "name": "AGEU",
                    "operator": "non_empty"
                },
                {
                    "name": "AGE",
                    "operator": "empty"
                },
                {
                    "name": "AGETXT",
                    "operator": "empty"
                }
            ]
        },
        "Core": {
            "Id": "CORE-000122",
            "Version": "1",
            "Status": "Published"
        },
        "Description": "Raise an error when both AGETXT and AGE are empty, but AGEU is populated.",
        "Outcome": {
            "Message": "AGEU not empty, but AGE empty and AGETXT empty",
            "Output_Variables": [
                "AGE",
                "AGEU",
                "AGETXT"
            ]
        },
        "Rule_Type": "Record Data",
        "Sensitivity": "Record",
        "Authorities": [
            {
                "Organization": "CDISC",
                "Standards": [
                    {
                        "Name": "SDTMIG",
                        "Version": "3.4",
                        "References": [
                            {
                                "Origin": "SDTM and SDTMIG Conformance Rules",
                                "Rule_Identifier": {
                                    "Id": "CG0434",
                                    "Version": "1"
                                },
                                "Version": "2.0",
                                "Citations": [
                                    {
                                        "Cited_Guidance": "Variable Qualifier of AGE or AGETXT.",
                                        "Document": "Model v2.0",
                                        "Item": "AGEU",
                                        "Section": "Demographics"
                                    }
                                ]
                            }
                        ]
                    }
                ]
            }
        ],
        "Scope": {
            "Classes": {
                "Include": [
                    "SPECIAL-PURPOSE"
                ]
            },
            "Domains": {
                "Include": [
                    "DM"
                ]
            }
        }
    }
}