{
    "id": "b5bbd00f-d4b3-4a00-9fbb-f426c4141de1",
    "changed": "2022-05-11T13:30:10Z",
    "content": "Check:\n  all:\n    #Condition: Variable Core Status = Expected and data collected\r\n    - name: define_variable_role\n      operator: equal_to\n      value: Expected\n    #Rule: Variable is not present\r\n    - name: variable_name\n      operator: empty\n\nCore:\n  Id: CDISC.SDTMIG.CG0431\n  Version: '1'\n  Status: Draft\nDescription: Raise an error when variable Core Status = Expected and data is collected,\n  but variable is not present\nOutcome:\n  Message: Variable is empty, where variable core status is expected and data is collected.\nRule Type: Record Data\nSensitivity: Value\nAuthorities:\n  - Organization: CDISC\n    Standards:\n      - Name: SDTMIG\n        Version: '3.4'\n        References:\n          - Origin: SDTM and SDTMIG Conformance Rules\n            Rule Identifier:\n              Id: CG0431\n              Version: '1'\n            Version: '2.0'\n            Citations:\n              - Cited Guidance: When the study does not include the data item for\n                  an expected variable, however, a null column must still be included\n                  in the dataset, and a comment must be included in the Define-XML\n                  document to state that the study does not include the data item.\n                Document: IG v3.4\n                Section: 4.1.5\nScope:\n  Classes:\n    Include:\n      - ALL\n  Domains:\n    Include:\n      - ALL\n",
    "created": "2022-02-05T06:30:47Z",
    "creator": {
        "id": "ff471ff8-f131-4cf5-9712-c79cce6301a1"
    },
    "json": {
        "Check": {
            "all": [
                {
                    "name": "define_variable_role",
                    "operator": "equal_to",
                    "value": "Expected"
                },
                {
                    "name": "variable_name",
                    "operator": "empty"
                }
            ]
        },
        "Core": {
            "Id": "CDISC.SDTMIG.CG0431",
            "Version": "1",
            "Status": "Draft"
        },
        "Description": "Raise an error when variable Core Status = Expected and data is collected, but variable is not present",
        "Outcome": {
            "Message": "Variable is empty, where variable core status is expected and data is collected."
        },
        "Rule_Type": "Record Data",
        "Sensitivity": "Value",
        "Authorities": [
            {
                "Organization": "CDISC",
                "Standards": [
                    {
                        "Name": "SDTMIG",
                        "Version": "3.4",
                        "References": [
                            {
                                "Origin": "SDTM and SDTMIG Conformance Rules",
                                "Rule_Identifier": {
                                    "Id": "CG0431",
                                    "Version": "1"
                                },
                                "Version": "2.0",
                                "Citations": [
                                    {
                                        "Cited_Guidance": "When the study does not include the data item for an expected variable, however, a null column must still be included in the dataset, and a comment must be included in the Define-XML document to state that the study does not include the data item.",
                                        "Document": "IG v3.4",
                                        "Section": "4.1.5"
                                    }
                                ]
                            }
                        ]
                    }
                ]
            }
        ],
        "Scope": {
            "Classes": {
                "Include": [
                    "ALL"
                ]
            },
            "Domains": {
                "Include": [
                    "ALL"
                ]
            }
        }
    }
}