{
    "id": "3a6201d0-2183-4a96-af42-8e854299dfa3",
    "changed": "2022-07-17T11:07:08Z",
    "content": "Check:\n  all:\n    - name:\n      operator: is_not_contained_by\n      prefix: 2\n      value:\n    - name: --TERM\n      operator: exists\nCore:\n  Id: CDISC.SDTMIG.CG0464\n  Version: '1'\n  Status: Draft\nDescription: Trigger error when --TERM is not present in custom events dataset\nOutcome:\n  Message: --TERM is not present in custom events dataset\nRule Type: Record Data\nSensitivity: Dataset\nAuthorities:\n  - Organization: CDISC\n    Standards:\n      - Name: SDTMIG\n        Version: '3.4'\n        References:\n          - Origin: SDTM and SDTMIG Conformance Rules\n            Rule Identifier:\n              Id: CG0464\n              Version: '2'\n            Version: '2.0'\n            Citations:\n              - Cited Guidance: Include the Topic variable from the identified general\n                  observation class (e.g., --TESTCD for Findings) in the SDTM\n                Document: IG v3.4\n                Item: Assumption 3b\n                Section: '2.6'\nScope:\n  Classes:\n    Include:\n      - EVENTS\n  Domains:\n    Include:\n      - ALL\n",
    "created": "2021-11-08T10:23:58Z",
    "creator": {
        "id": "ff471ff8-f131-4cf5-9712-c79cce6301a1"
    },
    "json": {
        "Check": {
            "all": [
                {
                    "name": null,
                    "operator": "is_not_contained_by",
                    "prefix": 2,
                    "value": null
                },
                {
                    "name": "--TERM",
                    "operator": "exists"
                }
            ]
        },
        "Core": {
            "Id": "CDISC.SDTMIG.CG0464",
            "Version": "1",
            "Status": "Draft"
        },
        "Description": "Trigger error when --TERM is not present in custom events dataset",
        "Outcome": {
            "Message": "--TERM is not present in custom events dataset"
        },
        "Rule_Type": "Record Data",
        "Sensitivity": "Dataset",
        "Authorities": [
            {
                "Organization": "CDISC",
                "Standards": [
                    {
                        "Name": "SDTMIG",
                        "Version": "3.4",
                        "References": [
                            {
                                "Origin": "SDTM and SDTMIG Conformance Rules",
                                "Rule_Identifier": {
                                    "Id": "CG0464",
                                    "Version": "2"
                                },
                                "Version": "2.0",
                                "Citations": [
                                    {
                                        "Cited_Guidance": "Include the Topic variable from the identified general observation class (e.g., --TESTCD for Findings) in the SDTM",
                                        "Document": "IG v3.4",
                                        "Item": "Assumption 3b",
                                        "Section": "2.6"
                                    }
                                ]
                            }
                        ]
                    }
                ]
            }
        ],
        "Scope": {
            "Classes": {
                "Include": [
                    "EVENTS"
                ]
            },
            "Domains": {
                "Include": [
                    "ALL"
                ]
            }
        }
    }
}