{
    "id": "1dcc7ab8-1ecc-4602-967c-ad21f1cb5e5c",
    "changed": "2022-03-17T11:43:06Z",
    "content": "Check:\n  all:\n    - name: QNAM\n      operator: not_matches_regex\n      value: ^[A-Z_][A-Z0-9_]{0,7}$\nCore:\n  Id: CORE-000221\n  Version: '1'\n  Status: Published\nDescription: Raise an error when QNAM > 8 chars or contains more than only letters\n  in uppercase, numbers and underscores, or starts with a number.\nOutcome:\n  Message: QNAM > 8 chars or contains letters that are in not in uppercase, more than\n    only letters, numbers, underscores, or starts with a number.\n  Output Variables:\n    - IDVAR\n    - IDVARVAL\n    - QNAM\nRule Type: Record Data\nSensitivity: Record\nAuthorities:\n  - Organization: CDISC\n    Standards:\n      - Name: SDTMIG\n        Version: '3.4'\n        References:\n          - Origin: SDTM and SDTMIG Conformance Rules\n            Rule Identifier:\n              Id: CG0417\n              Version: '1'\n            Version: '2.0'\n            Citations:\n              - Cited Guidance: The value in QNAM cannot be longer than 8 characters;\n                  nor can it start with a  number (e.g., '1TEST'). QNAM cannot contain\n                  characters other than letters; numbers; or underscores.\n                Document: Model v2.0\n                Item: QNAM\n                Section: Supplemental Qualifiers\nScope:\n  Classes:\n    Include:\n      - RELATIONSHIP\n  Domains:\n    Include:\n      - SUPP--\n",
    "created": "2021-11-17T19:51:42Z",
    "creator": {
        "id": "02c3c969-4787-4d57-b164-e2851035c0e8"
    },
    "json": {
        "Check": {
            "all": [
                {
                    "name": "QNAM",
                    "operator": "not_matches_regex",
                    "value": "^[A-Z_][A-Z0-9_]{0,7}$"
                }
            ]
        },
        "Core": {
            "Id": "CORE-000221",
            "Version": "1",
            "Status": "Published"
        },
        "Description": "Raise an error when QNAM > 8 chars or contains more than only letters in uppercase, numbers and underscores, or starts with a number.",
        "Outcome": {
            "Message": "QNAM > 8 chars or contains letters that are in not in uppercase, more than only letters, numbers, underscores, or starts with a number.",
            "Output_Variables": [
                "IDVAR",
                "IDVARVAL",
                "QNAM"
            ]
        },
        "Rule_Type": "Record Data",
        "Sensitivity": "Record",
        "Authorities": [
            {
                "Organization": "CDISC",
                "Standards": [
                    {
                        "Name": "SDTMIG",
                        "Version": "3.4",
                        "References": [
                            {
                                "Origin": "SDTM and SDTMIG Conformance Rules",
                                "Rule_Identifier": {
                                    "Id": "CG0417",
                                    "Version": "1"
                                },
                                "Version": "2.0",
                                "Citations": [
                                    {
                                        "Cited_Guidance": "The value in QNAM cannot be longer than 8 characters; nor can it start with a  number (e.g., '1TEST'). QNAM cannot contain characters other than letters; numbers; or underscores.",
                                        "Document": "Model v2.0",
                                        "Item": "QNAM",
                                        "Section": "Supplemental Qualifiers"
                                    }
                                ]
                            }
                        ]
                    }
                ]
            }
        ],
        "Scope": {
            "Classes": {
                "Include": [
                    "RELATIONSHIP"
                ]
            },
            "Domains": {
                "Include": [
                    "SUPP--"
                ]
            }
        }
    }
}