{
    "id": "8bb7df23-9f6d-41f7-9ae0-a58f24bc9740",
    "changed": "2022-07-29T08:04:24Z",
    "content": "Check:\n  all:\n    - name: dataset_name\n      operator: prefix_not_equal_to\n      prefix: 2\n      value: DOMAIN\nCore:\n  Id: CDISC.SDTMIG.CG0413\n  Version: '1'\n  Status: Draft\nDescription: The dataset name must begin with the DOMAIN value.\nOutcome:\n  Message: Dataset name does not begin with DOMAIN value\nRule Type: Dataset Metadata Check\nSensitivity: Dataset\nAuthorities:\n  - Organization: CDISC\n    Standards:\n      - Name: SDTMIG\n        Version: '3.4'\n        References:\n          - Origin: SDTM and SDTMIG Conformance Rules\n            Rule Identifier:\n              Id: CG0413\n              Version: '1'\n            Version: '2.0'\n            Citations:\n              - Cited Guidance: Each study subject domain dataset is distinguished\n                  by a unique, 2-character code that should be used consistently throughout\n                  the submission. This code, which is stored in the SDTM variable\n                  named DOMAIN, is used in the dataset name, as the value of the DOMAIN\n                  variable in that dataset, and as a prefix for most variable names\n                  in that dataset.\n                Document: Model v2.0\n                Section: Study Subject Data\nScope:\n  Classes:\n    Include:\n      - ALL\n  Domains:\n    Include:\n      - ALL\n",
    "created": "2021-11-06T09:11:03Z",
    "creator": {
        "id": "ff471ff8-f131-4cf5-9712-c79cce6301a1"
    },
    "json": {
        "Check": {
            "all": [
                {
                    "name": "dataset_name",
                    "operator": "prefix_not_equal_to",
                    "prefix": 2,
                    "value": "DOMAIN"
                }
            ]
        },
        "Core": {
            "Id": "CDISC.SDTMIG.CG0413",
            "Version": "1",
            "Status": "Draft"
        },
        "Description": "The dataset name must begin with the DOMAIN value.",
        "Outcome": {
            "Message": "Dataset name does not begin with DOMAIN value"
        },
        "Rule_Type": "Dataset Metadata Check",
        "Sensitivity": "Dataset",
        "Authorities": [
            {
                "Organization": "CDISC",
                "Standards": [
                    {
                        "Name": "SDTMIG",
                        "Version": "3.4",
                        "References": [
                            {
                                "Origin": "SDTM and SDTMIG Conformance Rules",
                                "Rule_Identifier": {
                                    "Id": "CG0413",
                                    "Version": "1"
                                },
                                "Version": "2.0",
                                "Citations": [
                                    {
                                        "Cited_Guidance": "Each study subject domain dataset is distinguished by a unique, 2-character code that should be used consistently throughout the submission. This code, which is stored in the SDTM variable named DOMAIN, is used in the dataset name, as the value of the DOMAIN variable in that dataset, and as a prefix for most variable names in that dataset.",
                                        "Document": "Model v2.0",
                                        "Section": "Study Subject Data"
                                    }
                                ]
                            }
                        ]
                    }
                ]
            }
        ],
        "Scope": {
            "Classes": {
                "Include": [
                    "ALL"
                ]
            },
            "Domains": {
                "Include": [
                    "ALL"
                ]
            }
        }
    }
}