{
    "id": "63c003fb-7f67-462b-aed0-03f2ea7c9593",
    "changed": "2022-03-17T11:54:12Z",
    "content": "Check:\n  all:\n    - name: --VAMT\n      operator: non_empty\n    - name: --TRTV\n      operator: empty\nCore:\n  Id: CORE-000100\n  Version: '1'\n  Status: Published\nDescription: Raise an error when --VAMT is not empty, but --TRTV is empty.\nOutcome:\n  Message: Missing --TRTV value, when --VAMT value is populated.\n  Output Variables:\n    - --TRTV\n    - --VAMT\nRule Type: Record Data\nSensitivity: Record\nAuthorities:\n  - Organization: CDISC\n    Standards:\n      - Name: SDTMIG\n        Version: '3.4'\n        References:\n          - Origin: SDTM and SDTMIG Conformance Rules\n            Rule Identifier:\n              Id: CG0423\n              Version: '1'\n            Version: '2.0'\n            Citations:\n              - Cited Guidance: A carrier or inert medium in which a medicinally active\n                  agent is administered.\n                Document: Model v2.0\n                Item: --TRTV\n                Section: Interventions\n              - Cited Guidance: Amount of the prepared product (treatment plus vehicle)\n                  administered.\n                Document: Model v2.0\n                Item: --VAMT\n                Section: Interventions\nScope:\n  Classes:\n    Include:\n      - INTERVENTIONS\n  Domains:\n    Include:\n      - ALL\n",
    "created": "2021-10-06T21:06:57Z",
    "creator": {
        "id": "d0881041-369e-4940-b721-5b456d12101b"
    },
    "json": {
        "Check": {
            "all": [
                {
                    "name": "--VAMT",
                    "operator": "non_empty"
                },
                {
                    "name": "--TRTV",
                    "operator": "empty"
                }
            ]
        },
        "Core": {
            "Id": "CORE-000100",
            "Version": "1",
            "Status": "Published"
        },
        "Description": "Raise an error when --VAMT is not empty, but --TRTV is empty.",
        "Outcome": {
            "Message": "Missing --TRTV value, when --VAMT value is populated.",
            "Output_Variables": [
                "--TRTV",
                "--VAMT"
            ]
        },
        "Rule_Type": "Record Data",
        "Sensitivity": "Record",
        "Authorities": [
            {
                "Organization": "CDISC",
                "Standards": [
                    {
                        "Name": "SDTMIG",
                        "Version": "3.4",
                        "References": [
                            {
                                "Origin": "SDTM and SDTMIG Conformance Rules",
                                "Rule_Identifier": {
                                    "Id": "CG0423",
                                    "Version": "1"
                                },
                                "Version": "2.0",
                                "Citations": [
                                    {
                                        "Cited_Guidance": "A carrier or inert medium in which a medicinally active agent is administered.",
                                        "Document": "Model v2.0",
                                        "Item": "--TRTV",
                                        "Section": "Interventions"
                                    },
                                    {
                                        "Cited_Guidance": "Amount of the prepared product (treatment plus vehicle) administered.",
                                        "Document": "Model v2.0",
                                        "Item": "--VAMT",
                                        "Section": "Interventions"
                                    }
                                ]
                            }
                        ]
                    }
                ]
            }
        ],
        "Scope": {
            "Classes": {
                "Include": [
                    "INTERVENTIONS"
                ]
            },
            "Domains": {
                "Include": [
                    "ALL"
                ]
            }
        }
    }
}