{
    "id": "f16b9a0b-3644-402e-b984-96cb1aecb138",
    "changed": "2022-03-14T20:02:16Z",
    "content": "Check:\n  all:\n    - name: STUDYID\n      operator: is_not_contained_by\n      value: $dm_studyid\nCore:\n  Id: CORE-000172\n  Version: '1'\n  Status: Published\nDescription: Raise an error when STUDYID is not equal to DM.STUDYID\nOperations:\n  - domain: DM\n    id: $dm_studyid\n    name: STUDYID\n    operator: distinct\nOutcome:\n  Message: STUDYID is not equal to DM.STUDYID\n  Output Variables:\n    - STUDYID\nRule Type: Record Data\nSensitivity: Record\nAuthorities:\n  - Organization: CDISC\n    Standards:\n      - Name: SDTMIG\n        Version: '3.4'\n        References:\n          - Origin: SDTM and SDTMIG Conformance Rules\n            Rule Identifier:\n              Id: CG0409\n              Version: '1'\n            Version: '2.0'\n            Citations:\n              - Cited Guidance: All records with the same STUDYID value are a group\n                  of records that describe that study.\n                Document: SDTMIG v3.4\n                Item: 2.B.1\n                Section: 4.2.6\nScope:\n  Classes:\n    Include:\n      - ALL\n  Domains:\n    Include:\n      - ALL\n",
    "created": "2021-10-26T09:30:18Z",
    "creator": {
        "id": "ae6dbbf3-4c9a-4149-b596-8183766167d4"
    },
    "json": {
        "Check": {
            "all": [
                {
                    "name": "STUDYID",
                    "operator": "is_not_contained_by",
                    "value": "$dm_studyid"
                }
            ]
        },
        "Core": {
            "Id": "CORE-000172",
            "Version": "1",
            "Status": "Published"
        },
        "Description": "Raise an error when STUDYID is not equal to DM.STUDYID",
        "Operations": [
            {
                "domain": "DM",
                "id": "$dm_studyid",
                "name": "STUDYID",
                "operator": "distinct"
            }
        ],
        "Outcome": {
            "Message": "STUDYID is not equal to DM.STUDYID",
            "Output_Variables": [
                "STUDYID"
            ]
        },
        "Rule_Type": "Record Data",
        "Sensitivity": "Record",
        "Authorities": [
            {
                "Organization": "CDISC",
                "Standards": [
                    {
                        "Name": "SDTMIG",
                        "Version": "3.4",
                        "References": [
                            {
                                "Origin": "SDTM and SDTMIG Conformance Rules",
                                "Rule_Identifier": {
                                    "Id": "CG0409",
                                    "Version": "1"
                                },
                                "Version": "2.0",
                                "Citations": [
                                    {
                                        "Cited_Guidance": "All records with the same STUDYID value are a group of records that describe that study.",
                                        "Document": "SDTMIG v3.4",
                                        "Item": "2.B.1",
                                        "Section": "4.2.6"
                                    }
                                ]
                            }
                        ]
                    }
                ]
            }
        ],
        "Scope": {
            "Classes": {
                "Include": [
                    "ALL"
                ]
            },
            "Domains": {
                "Include": [
                    "ALL"
                ]
            }
        }
    }
}