{
    "id": "0fa1bdb2-6fc0-4011-bf9e-42873ecefd84",
    "changed": "2022-04-04T13:45:09Z",
    "content": "Check:\n  all:\n    - name: --RESCAT\n      operator: non_empty\n    - name: --STRESC\n      operator: empty\nCore:\n  Id: CORE-000101\n  Version: '1'\n  Status: Published\nDescription: Raise an error when --RESCAT is not empty, but --STRESC is empty\nOutcome:\n  Message: Missing --STRESC value, when --RESCAT value is populated.\n  Output Variables:\n    - --RESCAT\n    - --STRESC\nRule Type: Record Data\nSensitivity: Record\nAuthorities:\n  - Organization: CDISC\n    Standards:\n      - Name: SDTMIG\n        Version: '3.4'\n        References:\n          - Origin: SDTM and SDTMIG Conformance Rules\n            Rule Identifier:\n              Id: CG0427\n              Version: '1'\n            Version: '2.0'\n            Citations:\n              - Cited Guidance: A grouping or classification of the results of an\n                  assessment. The result is in --STRESC.\n                Document: Model v2.0\n                Item: --RESCAT\n                Section: Findings\nScope:\n  Classes:\n    Include:\n      - FINDINGS\n  Domains:\n    Include:\n      - ALL\n",
    "created": "2021-10-06T21:13:50Z",
    "creator": {
        "id": "d0881041-369e-4940-b721-5b456d12101b"
    },
    "json": {
        "Check": {
            "all": [
                {
                    "name": "--RESCAT",
                    "operator": "non_empty"
                },
                {
                    "name": "--STRESC",
                    "operator": "empty"
                }
            ]
        },
        "Core": {
            "Id": "CORE-000101",
            "Version": "1",
            "Status": "Published"
        },
        "Description": "Raise an error when --RESCAT is not empty, but --STRESC is empty",
        "Outcome": {
            "Message": "Missing --STRESC value, when --RESCAT value is populated.",
            "Output_Variables": [
                "--RESCAT",
                "--STRESC"
            ]
        },
        "Rule_Type": "Record Data",
        "Sensitivity": "Record",
        "Authorities": [
            {
                "Organization": "CDISC",
                "Standards": [
                    {
                        "Name": "SDTMIG",
                        "Version": "3.4",
                        "References": [
                            {
                                "Origin": "SDTM and SDTMIG Conformance Rules",
                                "Rule_Identifier": {
                                    "Id": "CG0427",
                                    "Version": "1"
                                },
                                "Version": "2.0",
                                "Citations": [
                                    {
                                        "Cited_Guidance": "A grouping or classification of the results of an assessment. The result is in --STRESC.",
                                        "Document": "Model v2.0",
                                        "Item": "--RESCAT",
                                        "Section": "Findings"
                                    }
                                ]
                            }
                        ]
                    }
                ]
            }
        ],
        "Scope": {
            "Classes": {
                "Include": [
                    "FINDINGS"
                ]
            },
            "Domains": {
                "Include": [
                    "ALL"
                ]
            }
        }
    }
}