{
    "id": "31ac8cf6-a86d-43ac-bb2f-c44d3a7a9224",
    "changed": "2022-02-15T21:27:15Z",
    "content": "Check:\n  all:\n    - name:\n      operator:\n    - name: EX\n      operator: not_exists\nCore:\n  Id: CDISC.SDTMIG.CG0407\n  Version: '1'\n  Status: Draft\nDescription: Trigger error when study includes protocol-specified study treatment\n  and EX is not present\nOutcome:\n  Message: EX is not present in study when study includes protocol-specified study\n    treatment\nRule Type: Domain Existence Check\nSensitivity: Study\nAuthorities:\n  - Organization: CDISC\n    Standards:\n      - Name: SDTMIG\n        Version: '3.4'\n        References:\n          - Origin: SDTM and SDTMIG Conformance Rules\n            Rule Identifier:\n              Id: CG0407\n              Version: '1'\n            Version: '2.0'\n            Citations:\n              - Cited Guidance: The EX domain is required for all studies that include\n                  protocol-specified study treatment.\n                Document: IG v3.4\n                Item: Assumption 1c\n                Section: 6.1.3.1\nScope:\n  Classes:\n    Include:\n      - INTERVENTIONS\n  Domains:\n    Include:\n      - EX\n",
    "created": "2021-11-06T09:19:17Z",
    "creator": {
        "id": "ff471ff8-f131-4cf5-9712-c79cce6301a1"
    },
    "json": {
        "Check": {
            "all": [
                {
                    "name": null,
                    "operator": null
                },
                {
                    "name": "EX",
                    "operator": "not_exists"
                }
            ]
        },
        "Core": {
            "Id": "CDISC.SDTMIG.CG0407",
            "Version": "1",
            "Status": "Draft"
        },
        "Description": "Trigger error when study includes protocol-specified study treatment and EX is not present",
        "Outcome": {
            "Message": "EX is not present in study when study includes protocol-specified study treatment"
        },
        "Rule_Type": "Domain Existence Check",
        "Sensitivity": "Study",
        "Authorities": [
            {
                "Organization": "CDISC",
                "Standards": [
                    {
                        "Name": "SDTMIG",
                        "Version": "3.4",
                        "References": [
                            {
                                "Origin": "SDTM and SDTMIG Conformance Rules",
                                "Rule_Identifier": {
                                    "Id": "CG0407",
                                    "Version": "1"
                                },
                                "Version": "2.0",
                                "Citations": [
                                    {
                                        "Cited_Guidance": "The EX domain is required for all studies that include protocol-specified study treatment.",
                                        "Document": "IG v3.4",
                                        "Item": "Assumption 1c",
                                        "Section": "6.1.3.1"
                                    }
                                ]
                            }
                        ]
                    }
                ]
            }
        ],
        "Scope": {
            "Classes": {
                "Include": [
                    "INTERVENTIONS"
                ]
            },
            "Domains": {
                "Include": [
                    "EX"
                ]
            }
        }
    }
}