{
    "id": "8721feff-a658-4afc-b0ac-85b6637997a9",
    "changed": "2022-02-24T16:31:08Z",
    "content": "Check:\n  all:\n    - name: DTHDTC\n      operator: non_empty\n    - name: DTHFL\n      operator: not_equal_to\n      value: Y\nCore:\n  Id: CORE-000007\n  Version: '1'\n  Status: Published\nDescription: Raise an error when DTHDTC is not empty and DTHFL not equal to \"Y\"\nOutcome:\n  Message: DTHFL is not \"Y\", when DTHDTC is populated\n  Output Variables:\n    - DTHDTC\n    - DTHFL\nRule Type: Record Data\nSensitivity: Record\nAuthorities:\n  - Organization: CDISC\n    Standards:\n      - Name: SDTMIG\n        Version: '3.4'\n        References:\n          - Origin: SDTM and SDTMIG Conformance Rules\n            Rule Identifier:\n              Id: CG0435\n              Version: '1'\n            Version: '2.0'\n            Citations:\n              - Cited Guidance: DTHDTC[The date or date and time of death, represented\n                  in a standardized character format.] DTHFL[An indication that the\n                  subject died.]\n                Document: Model v2.0\n                Item: DTHDTC|DTHFL\n                Section: Demographics\nScope:\n  Classes:\n    Include:\n      - SPECIAL-PURPOSE\n  Domains:\n    Include:\n      - DM\n",
    "created": "2021-09-26T21:26:22Z",
    "creator": {
        "id": "d0881041-369e-4940-b721-5b456d12101b"
    },
    "json": {
        "Check": {
            "all": [
                {
                    "name": "DTHDTC",
                    "operator": "non_empty"
                },
                {
                    "name": "DTHFL",
                    "operator": "not_equal_to",
                    "value": "Y"
                }
            ]
        },
        "Core": {
            "Id": "CORE-000007",
            "Version": "1",
            "Status": "Published"
        },
        "Description": "Raise an error when DTHDTC is not empty and DTHFL not equal to \"Y\"",
        "Outcome": {
            "Message": "DTHFL is not \"Y\", when DTHDTC is populated",
            "Output_Variables": [
                "DTHDTC",
                "DTHFL"
            ]
        },
        "Rule_Type": "Record Data",
        "Sensitivity": "Record",
        "Authorities": [
            {
                "Organization": "CDISC",
                "Standards": [
                    {
                        "Name": "SDTMIG",
                        "Version": "3.4",
                        "References": [
                            {
                                "Origin": "SDTM and SDTMIG Conformance Rules",
                                "Rule_Identifier": {
                                    "Id": "CG0435",
                                    "Version": "1"
                                },
                                "Version": "2.0",
                                "Citations": [
                                    {
                                        "Cited_Guidance": "DTHDTC[The date or date and time of death, represented in a standardized character format.] DTHFL[An indication that the subject died.]",
                                        "Document": "Model v2.0",
                                        "Item": "DTHDTC|DTHFL",
                                        "Section": "Demographics"
                                    }
                                ]
                            }
                        ]
                    }
                ]
            }
        ],
        "Scope": {
            "Classes": {
                "Include": [
                    "SPECIAL-PURPOSE"
                ]
            },
            "Domains": {
                "Include": [
                    "DM"
                ]
            }
        }
    }
}