{
    "id": "21d1e2a9-d3d1-43d2-b4b2-113551c31651",
    "changed": "2022-03-14T20:01:21Z",
    "content": "Check:\n  all:\n    - name: QLABEL\n      operator: longer_than\n      value: 40\nCore:\n  Id: CORE-000222\n  Version: '1'\n  Status: Published\nDescription: Raise an error when QLABEL > 40 chars.\nOutcome:\n  Message: QLABEL > 40 chars.\n  Output Variables:\n    - IDVAR\n    - IDVARVAL\n    - QLABEL\nRule Type: Record Data\nSensitivity: Record\nAuthorities:\n  - Organization: CDISC\n    Standards:\n      - Name: SDTMIG\n        Version: '3.4'\n        References:\n          - Origin: SDTM and SDTMIG Conformance Rules\n            Rule Identifier:\n              Id: CG0416\n              Version: '1'\n            Version: '2.0'\n            Citations:\n              - Cited Guidance: This is the long name or label associated with QNAM.\n                  The value in QLABEL cannot be longer than 40 characters. This will\n                  often be the column label in the sponsor's original dataset.\n                Document: Model v2.0\n                Item: QLABEL\n                Section: Supplemental Qualifiers\nScope:\n  Classes:\n    Include:\n      - SPECIAL-PURPOSE\n  Domains:\n    Include:\n      - SUPP--\n",
    "created": "2021-11-17T20:10:03Z",
    "creator": {
        "id": "02c3c969-4787-4d57-b164-e2851035c0e8"
    },
    "json": {
        "Check": {
            "all": [
                {
                    "name": "QLABEL",
                    "operator": "longer_than",
                    "value": 40
                }
            ]
        },
        "Core": {
            "Id": "CORE-000222",
            "Version": "1",
            "Status": "Published"
        },
        "Description": "Raise an error when QLABEL > 40 chars.",
        "Outcome": {
            "Message": "QLABEL > 40 chars.",
            "Output_Variables": [
                "IDVAR",
                "IDVARVAL",
                "QLABEL"
            ]
        },
        "Rule_Type": "Record Data",
        "Sensitivity": "Record",
        "Authorities": [
            {
                "Organization": "CDISC",
                "Standards": [
                    {
                        "Name": "SDTMIG",
                        "Version": "3.4",
                        "References": [
                            {
                                "Origin": "SDTM and SDTMIG Conformance Rules",
                                "Rule_Identifier": {
                                    "Id": "CG0416",
                                    "Version": "1"
                                },
                                "Version": "2.0",
                                "Citations": [
                                    {
                                        "Cited_Guidance": "This is the long name or label associated with QNAM. The value in QLABEL cannot be longer than 40 characters. This will often be the column label in the sponsor's original dataset.",
                                        "Document": "Model v2.0",
                                        "Item": "QLABEL",
                                        "Section": "Supplemental Qualifiers"
                                    }
                                ]
                            }
                        ]
                    }
                ]
            }
        ],
        "Scope": {
            "Classes": {
                "Include": [
                    "SPECIAL-PURPOSE"
                ]
            },
            "Domains": {
                "Include": [
                    "SUPP--"
                ]
            }
        }
    }
}