{
    "id": "6bd776a6-f7dc-4e57-9c3b-23628389b370",
    "changed": "2022-02-15T21:28:49Z",
    "content": "Check:\n  all:\n    - name: --LOINC\n      operator: is_not_contained_by\n      value:\n        - LOINC codes contained in the version of the LOINC dictionary specified in\n          define.xml\nCore:\n  Id: CDISC.SDTMIG.CG0400\n  Version: '1'\n  Status: Draft\nDescription: Trigger error when --LOINC is not a valid code in the version of the\n  LOINC dictionary specified in define.xml\nOutcome:\n  Message: --LOINC is not a valid code in the version of the LOINC dictionary specified\n    in define.xml\nRule Type: Record Data\nSensitivity: Record\nAuthorities:\n  - Organization: CDISC\n    Standards:\n      - Name: SDTMIG\n        Version: '3.4'\n        References:\n          - Origin: SDTM and SDTMIG Conformance Rules\n            Rule Identifier:\n              Id: CG0400\n              Version: '1'\n            Version: '2.0'\n            Citations:\n              - Cited Guidance: A short sequence of characters used to represent laboratory\n                  and clinical tests within the Logical Observation Identifiers Names\n                  and Codes (LOINC) database.\n                Document: Model v2.0\n                Item: --LOINC\n                Section: Findings\nScope:\n  Classes:\n    Include:\n      - FINDINGS\n  Domains:\n    Include:\n      - ALL\n",
    "created": "2021-11-06T09:21:06Z",
    "creator": {
        "id": "ff471ff8-f131-4cf5-9712-c79cce6301a1"
    },
    "json": {
        "Check": {
            "all": [
                {
                    "name": "--LOINC",
                    "operator": "is_not_contained_by",
                    "value": [
                        "LOINC codes contained in the version of the LOINC dictionary specified in define.xml"
                    ]
                }
            ]
        },
        "Core": {
            "Id": "CDISC.SDTMIG.CG0400",
            "Version": "1",
            "Status": "Draft"
        },
        "Description": "Trigger error when --LOINC is not a valid code in the version of the LOINC dictionary specified in define.xml",
        "Outcome": {
            "Message": "--LOINC is not a valid code in the version of the LOINC dictionary specified in define.xml"
        },
        "Rule_Type": "Record Data",
        "Sensitivity": "Record",
        "Authorities": [
            {
                "Organization": "CDISC",
                "Standards": [
                    {
                        "Name": "SDTMIG",
                        "Version": "3.4",
                        "References": [
                            {
                                "Origin": "SDTM and SDTMIG Conformance Rules",
                                "Rule_Identifier": {
                                    "Id": "CG0400",
                                    "Version": "1"
                                },
                                "Version": "2.0",
                                "Citations": [
                                    {
                                        "Cited_Guidance": "A short sequence of characters used to represent laboratory and clinical tests within the Logical Observation Identifiers Names and Codes (LOINC) database.",
                                        "Document": "Model v2.0",
                                        "Item": "--LOINC",
                                        "Section": "Findings"
                                    }
                                ]
                            }
                        ]
                    }
                ]
            }
        ],
        "Scope": {
            "Classes": {
                "Include": [
                    "FINDINGS"
                ]
            },
            "Domains": {
                "Include": [
                    "ALL"
                ]
            }
        }
    }
}