{
    "id": "63b54fc9-a285-48a4-ae6b-2a03b509b9a0",
    "changed": "2022-03-08T01:33:47Z",
    "content": "Check:\n  all:\n    - name: --SCAT\n      operator: exists\n    - name: --CAT\n      operator: not_exists\nCore:\n  Id: CORE-000104\n  Version: '1'\n  Status: Published\nDescription: Raise an error when --SCAT exists in a dataset, but --CAT does not exist.\nOutcome:\n  Message: --SCAT exists in a dataset, but --CAT does not exist.\n  Output Variables:\n    - --CAT\n    - --SCAT\n\nRule Type: Record Data\nSensitivity: Dataset\nAuthorities:\n  - Organization: CDISC\n    Standards:\n      - Name: SDTMIG\n        Version: '3.4'\n        References:\n          - Origin: SDTM and SDTMIG Conformance Rules\n            Rule Identifier:\n              Id: CG0430\n              Version: '1'\n            Version: '2.0'\n            Citations:\n              - Cited Guidance: A further grouping or classification of the category\n                  for the topic of the finding, event, or intervention. The category\n                  is in --CAT.\n                Document: Model v2.0\n                Item: --SCAT\n                Section: Interventions\n              - Cited Guidance: A further grouping or classification of the category\n                  for the topic of the finding, event, or intervention. The category\n                  is in --CAT.\n                Document: Model v2.0\n                Item: --SCAT\n                Section: Events\n              - Cited Guidance: A further grouping or classification of the category\n                  for the topic of the finding, event, or intervention. The category\n                  is in --CAT.\n                Document: Model v2.0\n                Item: --SCAT\n                Section: Findings\nScope:\n  Classes:\n    Include:\n      - ALL\n  Domains:\n    Include:\n      - ALL\n",
    "created": "2021-10-06T21:55:39Z",
    "creator": {
        "id": "d0881041-369e-4940-b721-5b456d12101b"
    },
    "json": {
        "Check": {
            "all": [
                {
                    "name": "--SCAT",
                    "operator": "exists"
                },
                {
                    "name": "--CAT",
                    "operator": "not_exists"
                }
            ]
        },
        "Core": {
            "Id": "CORE-000104",
            "Version": "1",
            "Status": "Published"
        },
        "Description": "Raise an error when --SCAT exists in a dataset, but --CAT does not exist.",
        "Outcome": {
            "Message": "--SCAT exists in a dataset, but --CAT does not exist.",
            "Output_Variables": [
                "--CAT",
                "--SCAT"
            ]
        },
        "Rule_Type": "Record Data",
        "Sensitivity": "Dataset",
        "Authorities": [
            {
                "Organization": "CDISC",
                "Standards": [
                    {
                        "Name": "SDTMIG",
                        "Version": "3.4",
                        "References": [
                            {
                                "Origin": "SDTM and SDTMIG Conformance Rules",
                                "Rule_Identifier": {
                                    "Id": "CG0430",
                                    "Version": "1"
                                },
                                "Version": "2.0",
                                "Citations": [
                                    {
                                        "Cited_Guidance": "A further grouping or classification of the category for the topic of the finding, event, or intervention. The category is in --CAT.",
                                        "Document": "Model v2.0",
                                        "Item": "--SCAT",
                                        "Section": "Interventions"
                                    },
                                    {
                                        "Cited_Guidance": "A further grouping or classification of the category for the topic of the finding, event, or intervention. The category is in --CAT.",
                                        "Document": "Model v2.0",
                                        "Item": "--SCAT",
                                        "Section": "Events"
                                    },
                                    {
                                        "Cited_Guidance": "A further grouping or classification of the category for the topic of the finding, event, or intervention. The category is in --CAT.",
                                        "Document": "Model v2.0",
                                        "Item": "--SCAT",
                                        "Section": "Findings"
                                    }
                                ]
                            }
                        ]
                    }
                ]
            }
        ],
        "Scope": {
            "Classes": {
                "Include": [
                    "ALL"
                ]
            },
            "Domains": {
                "Include": [
                    "ALL"
                ]
            }
        }
    }
}