{
    "id": "9c5eb2d0-24f5-424e-af74-79d3869e3ea1",
    "changed": "2022-03-17T13:13:46Z",
    "content": "Check:\n  all:\n    - name: --TOX\n      operator: non_empty\n    - name: --TOXGR\n      operator: empty\nCore:\n  Id: CORE-000102\n  Version: '1'\n  Status: Published\nDescription: Raise an error when --TOX is not empty, but --TOXGR is empty.\nOutcome:\n  Message: --TOXGR should not be null when --TOX is populated.\n  Output Variables:\n    - --TOX\n    - --TOXGR\nRule Type: Record Data\nSensitivity: Record\nAuthorities:\n  - Organization: CDISC\n    Standards:\n      - Name: SDTMIG\n        Version: '3.4'\n        References:\n          - Origin: SDTM and SDTMIG Conformance Rules\n            Rule Identifier:\n              Id: CG0428\n              Version: '1'\n            Version: '2.0'\n            Citations:\n              - Cited Guidance: Variable Qualifier of --TOXGR\n                Document: Model v2.0\n                Item: --TOX\n                Section: Events|Findings\nScope:\n  Classes:\n    Include:\n      - EVENTS\n      - FINDINGS\n  Domains:\n    Include:\n      - AE\n      - MH\n      - CE\n      - EG\n      - LB\n      - PC\n      - PP\n",
    "created": "2021-10-06T21:35:18Z",
    "creator": {
        "id": "d0881041-369e-4940-b721-5b456d12101b"
    },
    "json": {
        "Check": {
            "all": [
                {
                    "name": "--TOX",
                    "operator": "non_empty"
                },
                {
                    "name": "--TOXGR",
                    "operator": "empty"
                }
            ]
        },
        "Core": {
            "Id": "CORE-000102",
            "Version": "1",
            "Status": "Published"
        },
        "Description": "Raise an error when --TOX is not empty, but --TOXGR is empty.",
        "Outcome": {
            "Message": "--TOXGR should not be null when --TOX is populated.",
            "Output_Variables": [
                "--TOX",
                "--TOXGR"
            ]
        },
        "Rule_Type": "Record Data",
        "Sensitivity": "Record",
        "Authorities": [
            {
                "Organization": "CDISC",
                "Standards": [
                    {
                        "Name": "SDTMIG",
                        "Version": "3.4",
                        "References": [
                            {
                                "Origin": "SDTM and SDTMIG Conformance Rules",
                                "Rule_Identifier": {
                                    "Id": "CG0428",
                                    "Version": "1"
                                },
                                "Version": "2.0",
                                "Citations": [
                                    {
                                        "Cited_Guidance": "Variable Qualifier of --TOXGR",
                                        "Document": "Model v2.0",
                                        "Item": "--TOX",
                                        "Section": "Events|Findings"
                                    }
                                ]
                            }
                        ]
                    }
                ]
            }
        ],
        "Scope": {
            "Classes": {
                "Include": [
                    "EVENTS",
                    "FINDINGS"
                ]
            },
            "Domains": {
                "Include": [
                    "AE",
                    "MH",
                    "CE",
                    "EG",
                    "LB",
                    "PC",
                    "PP"
                ]
            }
        }
    }
}