{
    "id": "5710b7b0-8096-4a49-acb5-e630519eb3ac",
    "changed": "2022-10-11T12:17:31.883Z",
    "content": "Check:\n  all:\n    - name: ACTARMCD\n      operator: non_empty\n    - name: ACTARMCD\n      operator: is_not_contained_by\n      value: $ta_armcd\nCore:\n  Id: CORE-000208\n  Version: '1'\n  Status: Published\nDescription: Trigger error when study does not use multi-stage arm assignments and\n  ACTARMCD ^= null, and ACTARMCD is not in TA.ARMCD\nOperations:\n  - domain: TA\n    id: $ta_armcd\n    name: ARMCD\n    operator: distinct\nOutcome:\n  Message: ACTARMCD is not in in TA.ARMCD\n  Output Variables:\n    - ACTARMCD\nRule Type: Record Data\nSensitivity: Record\nAuthorities:\n  - Organization: CDISC\n    Standards:\n      - Name: SDTMIG\n        Version: '3.4'\n        References:\n          - Origin: SDTM and SDTMIG Conformance Rules\n            Rule Identifier:\n              Id: CG0512\n              Version: '1'\n            Version: '2.0'\n            Citations:\n              - Cited Guidance: With the exception of studies which use multi-stage\n                  Arm assignments, must be a value of ARMCD in the Trial Arms Dataset.\n                  If the subject was not assigned to an Arm or followed a course not\n                  described by any planned Arm, ACTARMCD is null and ARMNRS is populated.\n                Document: IG v3.4\n                Item: Specification\n                Section: '5.2'\nScope:\n  Classes:\n    Include:\n      - SPECIAL-PURPOSE\n  Domains:\n    Include:\n      - DM\n",
    "created": "2021-11-08T10:24:31Z",
    "creator": {
        "id": "ff471ff8-f131-4cf5-9712-c79cce6301a1"
    },
    "json": {
        "Check": {
            "all": [
                {
                    "name": "ACTARMCD",
                    "operator": "non_empty"
                },
                {
                    "name": "ACTARMCD",
                    "operator": "is_not_contained_by",
                    "value": "$ta_armcd"
                }
            ]
        },
        "Core": {
            "Id": "CORE-000208",
            "Version": "1",
            "Status": "Published"
        },
        "Description": "Trigger error when study does not use multi-stage arm assignments and ACTARMCD ^= null, and ACTARMCD is not in TA.ARMCD",
        "Operations": [
            {
                "domain": "TA",
                "id": "$ta_armcd",
                "name": "ARMCD",
                "operator": "distinct"
            }
        ],
        "Outcome": {
            "Message": "ACTARMCD is not in in TA.ARMCD",
            "Output_Variables": [
                "ACTARMCD"
            ]
        },
        "Rule_Type": "Record Data",
        "Sensitivity": "Record",
        "Authorities": [
            {
                "Organization": "CDISC",
                "Standards": [
                    {
                        "Name": "SDTMIG",
                        "Version": "3.4",
                        "References": [
                            {
                                "Origin": "SDTM and SDTMIG Conformance Rules",
                                "Rule_Identifier": {
                                    "Id": "CG0512",
                                    "Version": "1"
                                },
                                "Version": "2.0",
                                "Citations": [
                                    {
                                        "Cited_Guidance": "With the exception of studies which use multi-stage Arm assignments, must be a value of ARMCD in the Trial Arms Dataset. If the subject was not assigned to an Arm or followed a course not described by any planned Arm, ACTARMCD is null and ARMNRS is populated.",
                                        "Document": "IG v3.4",
                                        "Item": "Specification",
                                        "Section": "5.2"
                                    }
                                ]
                            }
                        ]
                    }
                ]
            }
        ],
        "Scope": {
            "Classes": {
                "Include": [
                    "SPECIAL-PURPOSE"
                ]
            },
            "Domains": {
                "Include": [
                    "DM"
                ]
            }
        }
    }
}