{
    "id": "ed510be1-988b-4031-b490-2398318036b0",
    "changed": "2022-06-30T23:24:16Z",
    "content": "Check:\n  all:\n    - name: ACTARM\n      operator: non_empty\n    - name: ARM\n      operator: non_empty\n    - name: ARM\n      operator: is_not_contained_by\n      value: $ta_arm\nOperations:\n  - operator: distinct\n    domain: TA\n    name: ARM\n    id: $ta_arm\nCore:\n  Id: CORE-000047\n  Version: '1'\n  Status: Published\nDescription: When study does not use multi-stage arm assignments and ARM is populated,\n  ARM must be present in TA.ARM. This rule has been executed to identify all cases\n  when ARM is not present in TA.ARM and therefore acknowledges that false positives\n  may be recorded when multi-stage arm assignments are in use.\nOutcome:\n  Message: ARM value in DM dataset is not among the values of ARM variable in TA dataset.\n    This is allowed only in a multistage study with incomplete ARM assignment. Please\n    confirm if your study is a multistage assignment study\n  Output Variables:\n    - ARM\nRule Type: Record Data\nSensitivity: Record\nAuthorities:\n  - Organization: CDISC\n    Standards:\n      - Name: SDTMIG\n        Version: '3.4'\n        References:\n          - Origin: SDTM and SDTMIG Conformance Rules\n            Rule Identifier:\n              Id: CG0518\n              Version: '1'\n            Version: '2.0'\n            Citations:\n              - Cited Guidance: With the exception of studies which use multistage\n                  Arm assignments, must be a value of ARM in the Trial Arms Dataset.\n                  If the subject was not assigned to an Arm or followed a course not\n                  described by any planned arm, ARM is null and ARMNRS is populated.\"\n                Document: SDTMIG v3.4\n                Item: Specification and ACTARM CDISC Notes\n                Section: '5.2'\nScope:\n  Classes:\n    Include:\n      - SPECIAL-PURPOSE\n  Domains:\n    Include:\n      - DM\n",
    "created": "2021-10-04T02:04:39Z",
    "creator": {
        "id": "24709aaa-3e57-4ee4-a635-6006b165bb1b"
    },
    "json": {
        "Check": {
            "all": [
                {
                    "name": "ACTARM",
                    "operator": "non_empty"
                },
                {
                    "name": "ARM",
                    "operator": "non_empty"
                },
                {
                    "name": "ARM",
                    "operator": "is_not_contained_by",
                    "value": "$ta_arm"
                }
            ]
        },
        "Operations": [
            {
                "operator": "distinct",
                "domain": "TA",
                "name": "ARM",
                "id": "$ta_arm"
            }
        ],
        "Core": {
            "Id": "CORE-000047",
            "Version": "1",
            "Status": "Published"
        },
        "Description": "When study does not use multi-stage arm assignments and ARM is populated, ARM must be present in TA.ARM. This rule has been executed to identify all cases when ARM is not present in TA.ARM and therefore acknowledges that false positives may be recorded when multi-stage arm assignments are in use.",
        "Outcome": {
            "Message": "ARM value in DM dataset is not among the values of ARM variable in TA dataset. This is allowed only in a multistage study with incomplete ARM assignment. Please confirm if your study is a multistage assignment study",
            "Output_Variables": [
                "ARM"
            ]
        },
        "Rule_Type": "Record Data",
        "Sensitivity": "Record",
        "Authorities": [
            {
                "Organization": "CDISC",
                "Standards": [
                    {
                        "Name": "SDTMIG",
                        "Version": "3.4",
                        "References": [
                            {
                                "Origin": "SDTM and SDTMIG Conformance Rules",
                                "Rule_Identifier": {
                                    "Id": "CG0518",
                                    "Version": "1"
                                },
                                "Version": "2.0",
                                "Citations": [
                                    {
                                        "Cited_Guidance": "With the exception of studies which use multistage Arm assignments, must be a value of ARM in the Trial Arms Dataset. If the subject was not assigned to an Arm or followed a course not described by any planned arm, ARM is null and ARMNRS is populated.\"",
                                        "Document": "SDTMIG v3.4",
                                        "Item": "Specification and ACTARM CDISC Notes",
                                        "Section": "5.2"
                                    }
                                ]
                            }
                        ]
                    }
                ]
            }
        ],
        "Scope": {
            "Classes": {
                "Include": [
                    "SPECIAL-PURPOSE"
                ]
            },
            "Domains": {
                "Include": [
                    "DM"
                ]
            }
        }
    }
}