{
    "id": "85d9ee8d-fc0e-41fe-9579-3cfa54db6320",
    "changed": "2022-03-17T14:48:25Z",
    "content": "Check:\n  all:\n    - name: ACTARMCD\n      operator: empty\n    - name: ACTARM\n      operator: non_empty\nCore:\n  Id: CORE-000120\n  Version: '1'\n  Status: Published\nDescription: Raise an error when ACTARM is not empty, but ACTARMCD is empty\nOutcome:\n  Message: ACTARM is populated, when ACTARMCD is NULL\n  Output Variables:\n    - ACTARMCD\n    - ACTARM\nRule Type: Record Data\nSensitivity: Record\nAuthorities:\n  - Organization: CDISC\n    Standards:\n      - Name: SDTMIG\n        Version: '3.4'\n        References:\n          - Origin: SDTM and SDTMIG Conformance Rules\n            Rule Identifier:\n              Id: CG0522\n              Version: '1'\n            Version: '2.0'\n            Citations:\n              - Cited Guidance: \"\\\"If ACTARMCD is null, then ACTARM must be null and\\\n                  \\ ARMNRS must  be populated with the reason ACTARMCD is null.\\n\\\n                  \\ Both ARMCD and ACTARMCD will be null for subjects who were not\\\n                  \\ assigned to treatment. \\n The same reason  will provide the reason\\\n                  \\ that both are null.\\\"\"\n                Document: IG v3.4\n                Item: Assumption 4\n                Section: '5.2'\nScope:\n  Classes:\n    Include:\n      - SPECIAL-PURPOSE\n  Domains:\n    Include:\n      - DM\n",
    "created": "2021-10-12T02:20:05Z",
    "creator": {
        "id": "d0881041-369e-4940-b721-5b456d12101b"
    },
    "json": {
        "Check": {
            "all": [
                {
                    "name": "ACTARMCD",
                    "operator": "empty"
                },
                {
                    "name": "ACTARM",
                    "operator": "non_empty"
                }
            ]
        },
        "Core": {
            "Id": "CORE-000120",
            "Version": "1",
            "Status": "Published"
        },
        "Description": "Raise an error when ACTARM is not empty, but ACTARMCD is empty",
        "Outcome": {
            "Message": "ACTARM is populated, when ACTARMCD is NULL",
            "Output_Variables": [
                "ACTARMCD",
                "ACTARM"
            ]
        },
        "Rule_Type": "Record Data",
        "Sensitivity": "Record",
        "Authorities": [
            {
                "Organization": "CDISC",
                "Standards": [
                    {
                        "Name": "SDTMIG",
                        "Version": "3.4",
                        "References": [
                            {
                                "Origin": "SDTM and SDTMIG Conformance Rules",
                                "Rule_Identifier": {
                                    "Id": "CG0522",
                                    "Version": "1"
                                },
                                "Version": "2.0",
                                "Citations": [
                                    {
                                        "Cited_Guidance": "\"If ACTARMCD is null, then ACTARM must be null and ARMNRS must  be populated with the reason ACTARMCD is null.\n Both ARMCD and ACTARMCD will be null for subjects who were not assigned to treatment. \n The same reason  will provide the reason that both are null.\"",
                                        "Document": "IG v3.4",
                                        "Item": "Assumption 4",
                                        "Section": "5.2"
                                    }
                                ]
                            }
                        ]
                    }
                ]
            }
        ],
        "Scope": {
            "Classes": {
                "Include": [
                    "SPECIAL-PURPOSE"
                ]
            },
            "Domains": {
                "Include": [
                    "DM"
                ]
            }
        }
    }
}