{
    "id": "bbe42844-04fa-4e99-87ba-7c8bdced0c6a",
    "changed": "2022-07-07T15:20:09Z",
    "content": "Check:\n  all:\n    - name: --USCHFL\n      operator: exists\nCore:\n  Id: CORE-000049\n  Version: '1'\n  Status: Published\nDescription: Raise an error when --USCHFL is present.\nOutcome:\n  Message: --USCHFL is present.\nRule Type: Record Data\nSensitivity: Dataset\nAuthorities:\n  - Organization: CDISC\n    Standards:\n      - Name: SDTMIG\n        Version: '3.4'\n        References:\n          - Origin: SDTM and SDTMIG Conformance Rules\n            Rule Identifier:\n              Id: CG0507\n              Version: '1'\n            Version: '2.0'\n            Citations:\n              Cited Guidance: The following SDTM variables, defined for use in non-clinical\n                studies (SEND), must NEVER be used in the submission of SDTM-based\n                data for human clinical trials, --USCHFL (Interventions, Events, Findings),\n                --DTHREL (Findings), --EXCLFL (Findings), --REASEX (Findings), --IMPLBL\n                (Findings), FETUSID (Identifiers), --DETECT (Timing Variables), --NOMDY\n                (Timing Variables), --NOMLBL (Timing Variables)\n              Document: IG v3.4\n              Item: SDTM Variables Not Allowed in SDTMIG\n              Section: '2.7'\n      - Name: SDTMIG\n        Version: '3.4'\n        References:\n          - Origin: SDTM and SDTMIG Conformance Rules\n            Rule Identifier:\n              Id: CG0622\n              Version: '1'\n            Version: '2.0'\n            Citations:\n              Cited Guidance: Not in human clinical trials.\n              Document: Model v2.0\n              Section: Interventions|Events|Findings\n              Item: --USCHFL\nScope:\n  Classes:\n    Include:\n      - ALL\n  Domains:\n    Include:\n      - ALL\n",
    "created": "2021-10-04T04:44:29Z",
    "creator": {
        "id": "ff471ff8-f131-4cf5-9712-c79cce6301a1"
    },
    "json": {
        "Check": {
            "all": [
                {
                    "name": "--USCHFL",
                    "operator": "exists"
                }
            ]
        },
        "Core": {
            "Id": "CORE-000049",
            "Version": "1",
            "Status": "Published"
        },
        "Description": "Raise an error when --USCHFL is present.",
        "Outcome": {
            "Message": "--USCHFL is present."
        },
        "Rule_Type": "Record Data",
        "Sensitivity": "Dataset",
        "Authorities": [
            {
                "Organization": "CDISC",
                "Standards": [
                    {
                        "Name": "SDTMIG",
                        "Version": "3.4",
                        "References": [
                            {
                                "Origin": "SDTM and SDTMIG Conformance Rules",
                                "Rule_Identifier": {
                                    "Id": "CG0507",
                                    "Version": "1"
                                },
                                "Version": "2.0",
                                "Citations": {
                                    "Cited_Guidance": "The following SDTM variables, defined for use in non-clinical studies (SEND), must NEVER be used in the submission of SDTM-based data for human clinical trials, --USCHFL (Interventions, Events, Findings), --DTHREL (Findings), --EXCLFL (Findings), --REASEX (Findings), --IMPLBL (Findings), FETUSID (Identifiers), --DETECT (Timing Variables), --NOMDY (Timing Variables), --NOMLBL (Timing Variables)",
                                    "Document": "IG v3.4",
                                    "Item": "SDTM Variables Not Allowed in SDTMIG",
                                    "Section": "2.7"
                                }
                            }
                        ]
                    },
                    {
                        "Name": "SDTMIG",
                        "Version": "3.4",
                        "References": [
                            {
                                "Origin": "SDTM and SDTMIG Conformance Rules",
                                "Rule_Identifier": {
                                    "Id": "CG0622",
                                    "Version": "1"
                                },
                                "Version": "2.0",
                                "Citations": {
                                    "Cited_Guidance": "Not in human clinical trials.",
                                    "Document": "Model v2.0",
                                    "Section": "Interventions|Events|Findings",
                                    "Item": "--USCHFL"
                                }
                            }
                        ]
                    }
                ]
            }
        ],
        "Scope": {
            "Classes": {
                "Include": [
                    "ALL"
                ]
            },
            "Domains": {
                "Include": [
                    "ALL"
                ]
            }
        }
    }
}