{
    "id": "2092eed4-3bb9-4556-8462-2d79c494da01",
    "changed": "2022-03-22T12:33:48Z",
    "content": "Check:\n  all:\n    - name: --AGENT\n      operator: exists\nCore:\n  Id: CORE-000111\n  Version: '1'\n  Status: Published\nDescription: Raise an error when --AGENT is present in a dataset other than MS.\nOutcome:\n  Message: --AGENT is present in a dataset other than MS.\n  Output Variables:\n    - --AGENT\nRule Type: Record Data\nSensitivity: Dataset\nAuthorities:\n  - Organization: CDISC\n    Standards:\n      - Name: SDTMIG\n        Version: '3.4'\n        References:\n          - Origin: SDTM and SDTMIG Conformance Rules\n            Rule Identifier:\n              Id: CG0564\n              Version: '1'\n            Version: '2.0'\n            Citations:\n              - Cited Guidance: MS Domain only\n                Document: Model v2.0\n                Item: --AGENT\n                Section: Findings\nScope:\n  Classes:\n    Include:\n      - FINDINGS\n  Domains:\n    Exclude:\n      - MS\n",
    "created": "2021-10-08T12:04:10Z",
    "creator": {
        "id": "ff471ff8-f131-4cf5-9712-c79cce6301a1"
    },
    "json": {
        "Check": {
            "all": [
                {
                    "name": "--AGENT",
                    "operator": "exists"
                }
            ]
        },
        "Core": {
            "Id": "CORE-000111",
            "Version": "1",
            "Status": "Published"
        },
        "Description": "Raise an error when --AGENT is present in a dataset other than MS.",
        "Outcome": {
            "Message": "--AGENT is present in a dataset other than MS.",
            "Output_Variables": [
                "--AGENT"
            ]
        },
        "Rule_Type": "Record Data",
        "Sensitivity": "Dataset",
        "Authorities": [
            {
                "Organization": "CDISC",
                "Standards": [
                    {
                        "Name": "SDTMIG",
                        "Version": "3.4",
                        "References": [
                            {
                                "Origin": "SDTM and SDTMIG Conformance Rules",
                                "Rule_Identifier": {
                                    "Id": "CG0564",
                                    "Version": "1"
                                },
                                "Version": "2.0",
                                "Citations": [
                                    {
                                        "Cited_Guidance": "MS Domain only",
                                        "Document": "Model v2.0",
                                        "Item": "--AGENT",
                                        "Section": "Findings"
                                    }
                                ]
                            }
                        ]
                    }
                ]
            }
        ],
        "Scope": {
            "Classes": {
                "Include": [
                    "FINDINGS"
                ]
            },
            "Domains": {
                "Exclude": [
                    "MS"
                ]
            }
        }
    }
}