{
    "id": "2052cfb7-741b-4b87-ab8d-4c8e0c57a40e",
    "changed": "2022-02-15T21:26:55Z",
    "content": "Check:\n  all:\n    - name: --ORREF\n      operator:\nCore:\n  Id: CDISC.SDTMIG.CG0548\n  Version: '1'\n  Status: Draft\nDescription: Trigger error when --ORREF is not in the same units as --ORRES\nOutcome:\n  Message: --ORREF is not in the same units as --ORRES\nRule Type: Record Data\nSensitivity: Record\nAuthorities:\n  - Organization: CDISC\n    Standards:\n      - Name: SDTMIG\n        Version: '3.4'\n        References:\n          - Origin: SDTM and SDTMIG Conformance Rules\n            Rule Identifier:\n              Id: CG0548\n              Version: '1'\n            Version: '2.0'\n            Citations:\n              - Cited Guidance: --ORREF uses the same units as --ORRES, if applicable.\n                Document: Model v2.0\n                Item: --ORREF\n                Section: Findings\nScope:\n  Classes:\n    Include:\n      - FINDINGS\n  Domains:\n    Include:\n      - ALL\n",
    "created": "2021-11-08T10:27:24Z",
    "creator": {
        "id": "ff471ff8-f131-4cf5-9712-c79cce6301a1"
    },
    "json": {
        "Check": {
            "all": [
                {
                    "name": "--ORREF",
                    "operator": null
                }
            ]
        },
        "Core": {
            "Id": "CDISC.SDTMIG.CG0548",
            "Version": "1",
            "Status": "Draft"
        },
        "Description": "Trigger error when --ORREF is not in the same units as --ORRES",
        "Outcome": {
            "Message": "--ORREF is not in the same units as --ORRES"
        },
        "Rule_Type": "Record Data",
        "Sensitivity": "Record",
        "Authorities": [
            {
                "Organization": "CDISC",
                "Standards": [
                    {
                        "Name": "SDTMIG",
                        "Version": "3.4",
                        "References": [
                            {
                                "Origin": "SDTM and SDTMIG Conformance Rules",
                                "Rule_Identifier": {
                                    "Id": "CG0548",
                                    "Version": "1"
                                },
                                "Version": "2.0",
                                "Citations": [
                                    {
                                        "Cited_Guidance": "--ORREF uses the same units as --ORRES, if applicable.",
                                        "Document": "Model v2.0",
                                        "Item": "--ORREF",
                                        "Section": "Findings"
                                    }
                                ]
                            }
                        ]
                    }
                ]
            }
        ],
        "Scope": {
            "Classes": {
                "Include": [
                    "FINDINGS"
                ]
            },
            "Domains": {
                "Include": [
                    "ALL"
                ]
            }
        }
    }
}