{
    "id": "24f0c4bc-70a5-4827-a16e-ac1b415b0ab4",
    "changed": "2022-03-09T01:55:08Z",
    "content": "Check:\n  all:\n    - name: ARMCD\n      operator: non_empty\n    - name: ACTARMCD\n      operator: non_empty\n    - name: ARMNRS\n      operator: non_empty\nCore:\n  Id: CORE-000121\n  Version: '1'\n  Status: Published\nDescription: Verify the value for ARMNRS, when both ARMCD and ACTARMCD values are\n  populated\nOutcome:\n  Message: Value for ARMNRS is populated, when both ARMCD and ACTARMCD values are\n    populated\n  Output Variables:\n    - ARMCD\n    - ACTARMCD\n    - ARMNRS\nRule Type: Record Data\nSensitivity: Record\nAuthorities:\n  - Organization: CDISC\n    Standards:\n      - Name: SDTMIG\n        Version: '3.4'\n        References:\n          - Origin: SDTM and SDTMIG Conformance Rules\n            Rule Identifier:\n              Id: CG0520\n              Version: '1'\n            Version: '2.0'\n            Citations:\n              - Cited Guidance: \"\\\"Specification [A coded reason that arm variables\\\n                  \\ (ARM and ARMCD) and/or actual arm variables (ACTARM and ACTARMCD)\\\n                  \\ are null.]\\n Assumption  4[ARMNRS may not be populated if both\\\n                  \\ ARMCD and ACTARMCD are populated]\\\"\"\n                Document: IG v3.4\n                Item: Specification|Assumption 4\n                Section: '5.2'\nScope:\n  Classes:\n    Include:\n      - SPECIAL-PURPOSE\n  Domains:\n    Include:\n      - DM\n",
    "created": "2021-10-12T02:26:44Z",
    "creator": {
        "id": "d0881041-369e-4940-b721-5b456d12101b"
    },
    "json": {
        "Check": {
            "all": [
                {
                    "name": "ARMCD",
                    "operator": "non_empty"
                },
                {
                    "name": "ACTARMCD",
                    "operator": "non_empty"
                },
                {
                    "name": "ARMNRS",
                    "operator": "non_empty"
                }
            ]
        },
        "Core": {
            "Id": "CORE-000121",
            "Version": "1",
            "Status": "Published"
        },
        "Description": "Verify the value for ARMNRS, when both ARMCD and ACTARMCD values are populated",
        "Outcome": {
            "Message": "Value for ARMNRS is populated, when both ARMCD and ACTARMCD values are populated",
            "Output_Variables": [
                "ARMCD",
                "ACTARMCD",
                "ARMNRS"
            ]
        },
        "Rule_Type": "Record Data",
        "Sensitivity": "Record",
        "Authorities": [
            {
                "Organization": "CDISC",
                "Standards": [
                    {
                        "Name": "SDTMIG",
                        "Version": "3.4",
                        "References": [
                            {
                                "Origin": "SDTM and SDTMIG Conformance Rules",
                                "Rule_Identifier": {
                                    "Id": "CG0520",
                                    "Version": "1"
                                },
                                "Version": "2.0",
                                "Citations": [
                                    {
                                        "Cited_Guidance": "\"Specification [A coded reason that arm variables (ARM and ARMCD) and/or actual arm variables (ACTARM and ACTARMCD) are null.]\n Assumption  4[ARMNRS may not be populated if both ARMCD and ACTARMCD are populated]\"",
                                        "Document": "IG v3.4",
                                        "Item": "Specification|Assumption 4",
                                        "Section": "5.2"
                                    }
                                ]
                            }
                        ]
                    }
                ]
            }
        ],
        "Scope": {
            "Classes": {
                "Include": [
                    "SPECIAL-PURPOSE"
                ]
            },
            "Domains": {
                "Include": [
                    "DM"
                ]
            }
        }
    }
}