{
    "id": "df063396-1015-4516-a660-914f15e1d577",
    "changed": "2022-02-15T21:31:38Z",
    "content": "Check:\n  all:\n    - name:\n      operator:\n    - name: RACE\n      operator: not_equal_to\n      value: UNKNOWN\nCore:\n  Id: CDISC.SDTMIG.CG0526\n  Version: '1'\n  Status: Draft\nDescription: Trigger error when subject does not specify race and RACE is not equal\n  to \"UNKNOWN\"\nOutcome:\n  Message: RACE is not equal to \"UNKNOWN\" when subject did not specify race\nRule Type: Record Data\nSensitivity: Record\nAuthorities:\n  - Organization: CDISC\n    Standards:\n      - Name: SDTMIG\n        Version: '3.4'\n        References:\n          - Origin: SDTM and SDTMIG Conformance Rules\n            Rule Identifier:\n              Id: CG0526\n              Version: '1'\n            Version: '2.0'\n            Citations:\n              - Cited Guidance: 'If a subject refuses to provide or does not know\n                  their race information, the value of RACE could be \u201cUNKNOWN\u201d. '\n                Document: IG v3.4\n                Item: Assumption 6\n                Section: '5.2'\nScope:\n  Classes:\n    Include:\n      - SPECIAL-PURPOSE\n  Domains:\n    Include:\n      - DM\n",
    "created": "2021-11-08T10:25:34Z",
    "creator": {
        "id": "ff471ff8-f131-4cf5-9712-c79cce6301a1"
    },
    "json": {
        "Check": {
            "all": [
                {
                    "name": null,
                    "operator": null
                },
                {
                    "name": "RACE",
                    "operator": "not_equal_to",
                    "value": "UNKNOWN"
                }
            ]
        },
        "Core": {
            "Id": "CDISC.SDTMIG.CG0526",
            "Version": "1",
            "Status": "Draft"
        },
        "Description": "Trigger error when subject does not specify race and RACE is not equal to \"UNKNOWN\"",
        "Outcome": {
            "Message": "RACE is not equal to \"UNKNOWN\" when subject did not specify race"
        },
        "Rule_Type": "Record Data",
        "Sensitivity": "Record",
        "Authorities": [
            {
                "Organization": "CDISC",
                "Standards": [
                    {
                        "Name": "SDTMIG",
                        "Version": "3.4",
                        "References": [
                            {
                                "Origin": "SDTM and SDTMIG Conformance Rules",
                                "Rule_Identifier": {
                                    "Id": "CG0526",
                                    "Version": "1"
                                },
                                "Version": "2.0",
                                "Citations": [
                                    {
                                        "Cited_Guidance": "If a subject refuses to provide or does not know their race information, the value of RACE could be \u201cUNKNOWN\u201d. ",
                                        "Document": "IG v3.4",
                                        "Item": "Assumption 6",
                                        "Section": "5.2"
                                    }
                                ]
                            }
                        ]
                    }
                ]
            }
        ],
        "Scope": {
            "Classes": {
                "Include": [
                    "SPECIAL-PURPOSE"
                ]
            },
            "Domains": {
                "Include": [
                    "DM"
                ]
            }
        }
    }
}