{
    "id": "88c6a709-f8e8-4039-8593-7896c973e1fc",
    "changed": "2022-03-22T12:34:31Z",
    "content": "Check:\n  all:\n    - name: --CONC\n      operator: exists\nCore:\n  Id: CORE-000112\n  Version: '1'\n  Status: Published\nDescription: Raise an error when --CONC is present in a dataset other than MS.\nOutcome:\n  Message: --CONC is present in a dataset other than MS.\n  Output Variables:\n    - --CONC\nRule Type: Record Data\nSensitivity: Dataset\nAuthorities:\n  - Organization: CDISC\n    Standards:\n      - Name: SDTMIG\n        Version: '3.4'\n        References:\n          - Origin: SDTM and SDTMIG Conformance Rules\n            Rule Identifier:\n              Id: CG0565\n              Version: '1'\n            Version: '2.0'\n            Citations:\n              - Cited Guidance: MS Domain only\n                Document: Model v2.0\n                Item: --CONC\n                Section: Findings\nScope:\n  Classes:\n    Include:\n      - FINDINGS\n  Domains:\n    Exclude:\n      - MS\n",
    "created": "2021-10-08T12:04:57Z",
    "creator": {
        "id": "ff471ff8-f131-4cf5-9712-c79cce6301a1"
    },
    "json": {
        "Check": {
            "all": [
                {
                    "name": "--CONC",
                    "operator": "exists"
                }
            ]
        },
        "Core": {
            "Id": "CORE-000112",
            "Version": "1",
            "Status": "Published"
        },
        "Description": "Raise an error when --CONC is present in a dataset other than MS.",
        "Outcome": {
            "Message": "--CONC is present in a dataset other than MS.",
            "Output_Variables": [
                "--CONC"
            ]
        },
        "Rule_Type": "Record Data",
        "Sensitivity": "Dataset",
        "Authorities": [
            {
                "Organization": "CDISC",
                "Standards": [
                    {
                        "Name": "SDTMIG",
                        "Version": "3.4",
                        "References": [
                            {
                                "Origin": "SDTM and SDTMIG Conformance Rules",
                                "Rule_Identifier": {
                                    "Id": "CG0565",
                                    "Version": "1"
                                },
                                "Version": "2.0",
                                "Citations": [
                                    {
                                        "Cited_Guidance": "MS Domain only",
                                        "Document": "Model v2.0",
                                        "Item": "--CONC",
                                        "Section": "Findings"
                                    }
                                ]
                            }
                        ]
                    }
                ]
            }
        ],
        "Scope": {
            "Classes": {
                "Include": [
                    "FINDINGS"
                ]
            },
            "Domains": {
                "Exclude": [
                    "MS"
                ]
            }
        }
    }
}