{
    "id": "779c203c-123d-45dc-aefb-ddc108cb6186",
    "changed": "2022-03-19T10:25:53Z",
    "content": "Check:\n  all:\n    - name: --RESLOC\n      operator: exists\nCore:\n  Id: CORE-000247\n  Version: '1'\n  Status: Published\nDescription: Raise an error when --RESLOC is present.\nOutcome:\n  Message: --RESLOC is present.\nRule Type: Record Data\nSensitivity: Dataset\nAuthorities:\n  - Organization: CDISC\n    Standards:\n      - Name: SDTMIG\n        Version: '3.4'\n        References:\n          - Origin: SDTM and SDTMIG Conformance Rules\n            Rule Identifier:\n              Id: CG0552\n              Version: '1'\n            Version: '2.0'\n            Citations:\n              - Cited Guidance: --RESLOC is not be used in human clinical trials.\n                Document: Model v2.0\n                Section: Findings\nScope:\n  Classes:\n    Include:\n      - FINDINGS\n  Domains:\n    Include:\n      - ALL\n",
    "created": "2022-02-05T12:52:57Z",
    "creator": {
        "id": "ff471ff8-f131-4cf5-9712-c79cce6301a1"
    },
    "json": {
        "Check": {
            "all": [
                {
                    "name": "--RESLOC",
                    "operator": "exists"
                }
            ]
        },
        "Core": {
            "Id": "CORE-000247",
            "Version": "1",
            "Status": "Published"
        },
        "Description": "Raise an error when --RESLOC is present.",
        "Outcome": {
            "Message": "--RESLOC is present."
        },
        "Rule_Type": "Record Data",
        "Sensitivity": "Dataset",
        "Authorities": [
            {
                "Organization": "CDISC",
                "Standards": [
                    {
                        "Name": "SDTMIG",
                        "Version": "3.4",
                        "References": [
                            {
                                "Origin": "SDTM and SDTMIG Conformance Rules",
                                "Rule_Identifier": {
                                    "Id": "CG0552",
                                    "Version": "1"
                                },
                                "Version": "2.0",
                                "Citations": [
                                    {
                                        "Cited_Guidance": "--RESLOC is not be used in human clinical trials.",
                                        "Document": "Model v2.0",
                                        "Section": "Findings"
                                    }
                                ]
                            }
                        ]
                    }
                ]
            }
        ],
        "Scope": {
            "Classes": {
                "Include": [
                    "FINDINGS"
                ]
            },
            "Domains": {
                "Include": [
                    "ALL"
                ]
            }
        }
    }
}