{
    "id": "f5223c92-3cc6-4022-ac8a-138f2123a194",
    "changed": "2022-03-14T20:10:51Z",
    "content": "Check:\n  all:\n    - name: PEORRES\n      operator: empty\n    - name: PESTRESC\n      operator: non_empty\nCore:\n  Id: CORE-000082\n  Version: '1'\n  Status: Published\nDescription: Verify that PESTRESC is null when PEORRES is null\nOutcome:\n  Message: PESTRESC value is not missing when PEORRES value is missing\n  Output Variables:\n    - PEORRES\n    - PESTRESC\nRule Type: Record Data\nSensitivity: Record\nAuthorities:\n  - Organization: CDISC\n    Standards:\n      - Name: SDTMIG\n        Version: '3.4'\n        References:\n          - Origin: SDTM and SDTMIG Conformance Rules\n            Rule Identifier:\n              Id: CG0561\n              Version: '1'\n            Version: '2.0'\n            Citations:\n              - Cited Guidance: If PEORRES is null, PESTRESC must be null.\n                Document: IG v3.4\n                Item: Specification\n                Section: 6.3.8\nScope:\n  Classes:\n    Include:\n      - FINDINGS\n  Domains:\n    Include:\n      - PE\n",
    "created": "2021-10-04T14:26:43Z",
    "creator": {
        "id": "24709aaa-3e57-4ee4-a635-6006b165bb1b"
    },
    "json": {
        "Check": {
            "all": [
                {
                    "name": "PEORRES",
                    "operator": "empty"
                },
                {
                    "name": "PESTRESC",
                    "operator": "non_empty"
                }
            ]
        },
        "Core": {
            "Id": "CORE-000082",
            "Version": "1",
            "Status": "Published"
        },
        "Description": "Verify that PESTRESC is null when PEORRES is null",
        "Outcome": {
            "Message": "PESTRESC value is not missing when PEORRES value is missing",
            "Output_Variables": [
                "PEORRES",
                "PESTRESC"
            ]
        },
        "Rule_Type": "Record Data",
        "Sensitivity": "Record",
        "Authorities": [
            {
                "Organization": "CDISC",
                "Standards": [
                    {
                        "Name": "SDTMIG",
                        "Version": "3.4",
                        "References": [
                            {
                                "Origin": "SDTM and SDTMIG Conformance Rules",
                                "Rule_Identifier": {
                                    "Id": "CG0561",
                                    "Version": "1"
                                },
                                "Version": "2.0",
                                "Citations": [
                                    {
                                        "Cited_Guidance": "If PEORRES is null, PESTRESC must be null.",
                                        "Document": "IG v3.4",
                                        "Item": "Specification",
                                        "Section": "6.3.8"
                                    }
                                ]
                            }
                        ]
                    }
                ]
            }
        ],
        "Scope": {
            "Classes": {
                "Include": [
                    "FINDINGS"
                ]
            },
            "Domains": {
                "Include": [
                    "PE"
                ]
            }
        }
    }
}