{
    "id": "014ec862-deb7-4b40-9987-af238a7542a3",
    "changed": "2022-02-15T21:03:23Z",
    "content": "Check:\n  all:\n    - name:\n      operator:\n    - name: RSDRVFL\n      operator: not_equal_to\n      value: Y\nCore:\n  Id: CDISC.SDTMIG.CG0563\n  Version: '1'\n  Status: Draft\nDescription: Raise an error when record is derived in a data collection tool and RSDRVFL\n  is not equal to \"Y\"\nOutcome:\n  Message: Record is derived in a data collection tool and RSDRVFL is not equal to\n    \"Y\"\nRule Type: Record Data\nSensitivity: Record\nAuthorities:\n  - Organization: CDISC\n    Standards:\n      - Name: SDTMIG\n        Version: '3.4'\n        References:\n          - Origin: SDTM and SDTMIG Conformance Rules\n            Rule Identifier:\n              Id: CG0563\n              Version: '1'\n            Version: '2.0'\n            Citations:\n              - Cited Guidance: Used to indicate a derived record (e.g., a record\n                  that represents the average of other records such as a computed\n                  baseline). Should be \"Y\" or null.\n                Document: SDTMIG v3.4\n                Section: Section 6.3.9.3\nScope:\n  Classes:\n    Include:\n      - FINDINGS\n  Domains:\n    Include:\n      - RS\n",
    "created": "2021-10-08T12:27:38Z",
    "creator": {
        "id": "ff471ff8-f131-4cf5-9712-c79cce6301a1"
    },
    "json": {
        "Check": {
            "all": [
                {
                    "name": null,
                    "operator": null
                },
                {
                    "name": "RSDRVFL",
                    "operator": "not_equal_to",
                    "value": "Y"
                }
            ]
        },
        "Core": {
            "Id": "CDISC.SDTMIG.CG0563",
            "Version": "1",
            "Status": "Draft"
        },
        "Description": "Raise an error when record is derived in a data collection tool and RSDRVFL is not equal to \"Y\"",
        "Outcome": {
            "Message": "Record is derived in a data collection tool and RSDRVFL is not equal to \"Y\""
        },
        "Rule_Type": "Record Data",
        "Sensitivity": "Record",
        "Authorities": [
            {
                "Organization": "CDISC",
                "Standards": [
                    {
                        "Name": "SDTMIG",
                        "Version": "3.4",
                        "References": [
                            {
                                "Origin": "SDTM and SDTMIG Conformance Rules",
                                "Rule_Identifier": {
                                    "Id": "CG0563",
                                    "Version": "1"
                                },
                                "Version": "2.0",
                                "Citations": [
                                    {
                                        "Cited_Guidance": "Used to indicate a derived record (e.g., a record that represents the average of other records such as a computed baseline). Should be \"Y\" or null.",
                                        "Document": "SDTMIG v3.4",
                                        "Section": "Section 6.3.9.3"
                                    }
                                ]
                            }
                        ]
                    }
                ]
            }
        ],
        "Scope": {
            "Classes": {
                "Include": [
                    "FINDINGS"
                ]
            },
            "Domains": {
                "Include": [
                    "RS"
                ]
            }
        }
    }
}