{
    "id": "3d9e11b2-0ba6-4086-9d17-fce61f47062c",
    "changed": "2022-10-11T12:16:03.467Z",
    "content": "Check:\n  all:\n    - name: DSCAT\n      operator: equal_to\n      value: DISPOSITION EVENT\n      value_is_literal: true\n    - name: DSSCAT\n      operator: exists\n    - name: EPOCH\n      operator: is_not_unique_set\n      value: DSSCAT\nCore:\n  Id: CORE-000213\n  Version: '1'\n  Status: Published\nDescription: Trigger error when there is more than one record per subject per DSSCAT\n  per EPOCH\nOutcome:\n  Message: More than one record per subject per DSSCAT per EPOCH\n  Output Variables:\n    - DSSCAT\n    - EPOCH\nRule Type: Record Data\nSensitivity: Record\nAuthorities:\n  - Organization: CDISC\n    Standards:\n      - Name: SDTMIG\n        Version: '3.4'\n        References:\n          - Origin: SDTM and SDTMIG Conformance Rules\n            Rule Identifier:\n              Id: CG0536\n              Version: '1'\n            Version: '2.0'\n            Citations:\n              - Cited Guidance: If disposition events for both study participation\n                  and study treatment(s) are to be represented, then DSSCAT provides\n                  this distinction.\n                Document: IG v3.4\n                Item: Assumption 2.b\n                Section: 6.2.3\n              - Cited Guidance: \"ICH E3: Section 10.1 indicates that 'the specific\\\n                  \\ reason for discontinuation' should be presented, and that summaries\\\n                  \\ should be 'grouped by treatment and by major reason.' The CDISC\\\n                  \\ SDS Team interprets this guidance as requiring one standardized\\\n                  \\ disposition term (DSDECOD) per disposition event. If multiple\\\n                  \\ reasons are reported, the sponsor should identify a primary reason\\\n                  \\ and use that to populate DSTERM and DSDECOD. Additional reasons\\\n                  \\ should be submitted in SUPPDS.\"\n                Document: IG v3.4\n                Item: Assumption 5\n                Section: 6.2.3\nScope:\n  Classes:\n    Include:\n      - EVENTS\n  Domains:\n    Include:\n      - DS\n",
    "created": "2021-11-08T10:26:13Z",
    "creator": {
        "id": "ff471ff8-f131-4cf5-9712-c79cce6301a1"
    },
    "json": {
        "Check": {
            "all": [
                {
                    "name": "DSCAT",
                    "operator": "equal_to",
                    "value": "DISPOSITION EVENT",
                    "value_is_literal": true
                },
                {
                    "name": "DSSCAT",
                    "operator": "exists"
                },
                {
                    "name": "EPOCH",
                    "operator": "is_not_unique_set",
                    "value": "DSSCAT"
                }
            ]
        },
        "Core": {
            "Id": "CORE-000213",
            "Version": "1",
            "Status": "Published"
        },
        "Description": "Trigger error when there is more than one record per subject per DSSCAT per EPOCH",
        "Outcome": {
            "Message": "More than one record per subject per DSSCAT per EPOCH",
            "Output_Variables": [
                "DSSCAT",
                "EPOCH"
            ]
        },
        "Rule_Type": "Record Data",
        "Sensitivity": "Record",
        "Authorities": [
            {
                "Organization": "CDISC",
                "Standards": [
                    {
                        "Name": "SDTMIG",
                        "Version": "3.4",
                        "References": [
                            {
                                "Origin": "SDTM and SDTMIG Conformance Rules",
                                "Rule_Identifier": {
                                    "Id": "CG0536",
                                    "Version": "1"
                                },
                                "Version": "2.0",
                                "Citations": [
                                    {
                                        "Cited_Guidance": "If disposition events for both study participation and study treatment(s) are to be represented, then DSSCAT provides this distinction.",
                                        "Document": "IG v3.4",
                                        "Item": "Assumption 2.b",
                                        "Section": "6.2.3"
                                    },
                                    {
                                        "Cited_Guidance": "ICH E3: Section 10.1 indicates that 'the specific reason for discontinuation' should be presented, and that summaries should be 'grouped by treatment and by major reason.' The CDISC SDS Team interprets this guidance as requiring one standardized disposition term (DSDECOD) per disposition event. If multiple reasons are reported, the sponsor should identify a primary reason and use that to populate DSTERM and DSDECOD. Additional reasons should be submitted in SUPPDS.",
                                        "Document": "IG v3.4",
                                        "Item": "Assumption 5",
                                        "Section": "6.2.3"
                                    }
                                ]
                            }
                        ]
                    }
                ]
            }
        ],
        "Scope": {
            "Classes": {
                "Include": [
                    "EVENTS"
                ]
            },
            "Domains": {
                "Include": [
                    "DS"
                ]
            }
        }
    }
}