{
    "id": "83e0b657-a3ac-4b1e-9d98-51e0f02da435",
    "changed": "2022-02-15T21:29:26Z",
    "content": "Check:\n  all:\n    - name:\n      operator:\n    - name: ACTARMCD\n      operator: non_empty\nCore:\n  Id: CDISC.SDTMIG.CG0524\n  Version: '1'\n  Status: Draft\nDescription: Trigger error when ACTARMCD is populated for a subject who was not assigned\n  to treatment\nOutcome:\n  Message: ACTARMCD is populated for a subject who was not assigned to treatment\nRule Type: Record Data\nSensitivity: Record\nAuthorities:\n  - Organization: CDISC\n    Standards:\n      - Name: SDTMIG\n        Version: '3.4'\n        References:\n          - Origin: SDTM and SDTMIG Conformance Rules\n            Rule Identifier:\n              Id: CG0524\n              Version: '1'\n            Version: '2.0'\n            Citations:\n              - Cited Guidance: Both ARMCD and ACTARMCD will be null for subjects\n                  who were not assigned to treatment.  The same reason will provide\n                  the reason that both are null.\n                Document: IG v3.4\n                Item: Assumption 4\n                Section: '5.2'\nScope:\n  Classes:\n    Include:\n      - SPECIAL-PURPOSE\n  Domains:\n    Include:\n      - DM\n",
    "created": "2021-11-08T10:25:17Z",
    "creator": {
        "id": "ff471ff8-f131-4cf5-9712-c79cce6301a1"
    },
    "json": {
        "Check": {
            "all": [
                {
                    "name": null,
                    "operator": null
                },
                {
                    "name": "ACTARMCD",
                    "operator": "non_empty"
                }
            ]
        },
        "Core": {
            "Id": "CDISC.SDTMIG.CG0524",
            "Version": "1",
            "Status": "Draft"
        },
        "Description": "Trigger error when ACTARMCD is populated for a subject who was not assigned to treatment",
        "Outcome": {
            "Message": "ACTARMCD is populated for a subject who was not assigned to treatment"
        },
        "Rule_Type": "Record Data",
        "Sensitivity": "Record",
        "Authorities": [
            {
                "Organization": "CDISC",
                "Standards": [
                    {
                        "Name": "SDTMIG",
                        "Version": "3.4",
                        "References": [
                            {
                                "Origin": "SDTM and SDTMIG Conformance Rules",
                                "Rule_Identifier": {
                                    "Id": "CG0524",
                                    "Version": "1"
                                },
                                "Version": "2.0",
                                "Citations": [
                                    {
                                        "Cited_Guidance": "Both ARMCD and ACTARMCD will be null for subjects who were not assigned to treatment.  The same reason will provide the reason that both are null.",
                                        "Document": "IG v3.4",
                                        "Item": "Assumption 4",
                                        "Section": "5.2"
                                    }
                                ]
                            }
                        ]
                    }
                ]
            }
        ],
        "Scope": {
            "Classes": {
                "Include": [
                    "SPECIAL-PURPOSE"
                ]
            },
            "Domains": {
                "Include": [
                    "DM"
                ]
            }
        }
    }
}