{
    "id": "2584d6ab-1f4b-4bc2-bfd3-cb931e6d6a75",
    "changed": "2022-07-17T11:07:42Z",
    "content": "Check:\n  all:\n    - name: $MIDS_EXISTS\n      operator: equal_to\n      value: true\n    - name: TM\n      operator: not_exists\nOperations:\n  - id: $MIDS_EXISTS\n    name: MIDS\n    operator: variable_exists\nCore:\n  Id: CDISC.SDTMIG.CG0501\n  Version: '1'\n  Status: Draft\nDescription: Raise an error when variable MIDS is present in any of the dataset and\n  TM dataset is missing.\nOutcome:\n  Message: TM dataset is missing when MIDS variable is present in one of the dataset.\nRule Type: Domain Presence Check\nSensitivity: Dataset\nAuthorities:\n  - Organization: CDISC\n    Standards:\n      - Name: SDTMIG\n        Version: '3.4'\n        References:\n          - Origin: SDTM and SDTMIG Conformance Rules\n            Rule Identifier:\n              Id: CG0501\n              Version: '2'\n            Version: '2.0'\n            Citations:\n              - Cited Guidance: The name of a specific instance of a Disease Milestone\n                  Type (MIDSTYPE) described in the Trial Disease Milestones dataset\n                  (see Section 5.1.4.3, Trial Disease Milestones). This should be\n                  unique within a subject. Used only in conjunction with RELMIDS and\n                  MIDSDTC.\n                Document: Model v2.0\n                Item: MIDS\n                Section: Timing\nScope:\n  Classes:\n    Include:\n      - ALL\n  Domains:\n    Include:\n      - ALL\n",
    "created": "2021-11-03T11:50:58Z",
    "creator": {
        "id": "fac95de6-5815-411a-a579-ddbc7ee4b97a"
    },
    "json": {
        "Check": {
            "all": [
                {
                    "name": "$MIDS_EXISTS",
                    "operator": "equal_to",
                    "value": true
                },
                {
                    "name": "TM",
                    "operator": "not_exists"
                }
            ]
        },
        "Operations": [
            {
                "id": "$MIDS_EXISTS",
                "name": "MIDS",
                "operator": "variable_exists"
            }
        ],
        "Core": {
            "Id": "CDISC.SDTMIG.CG0501",
            "Version": "1",
            "Status": "Draft"
        },
        "Description": "Raise an error when variable MIDS is present in any of the dataset and TM dataset is missing.",
        "Outcome": {
            "Message": "TM dataset is missing when MIDS variable is present in one of the dataset."
        },
        "Rule_Type": "Domain Presence Check",
        "Sensitivity": "Dataset",
        "Authorities": [
            {
                "Organization": "CDISC",
                "Standards": [
                    {
                        "Name": "SDTMIG",
                        "Version": "3.4",
                        "References": [
                            {
                                "Origin": "SDTM and SDTMIG Conformance Rules",
                                "Rule_Identifier": {
                                    "Id": "CG0501",
                                    "Version": "2"
                                },
                                "Version": "2.0",
                                "Citations": [
                                    {
                                        "Cited_Guidance": "The name of a specific instance of a Disease Milestone Type (MIDSTYPE) described in the Trial Disease Milestones dataset (see Section 5.1.4.3, Trial Disease Milestones). This should be unique within a subject. Used only in conjunction with RELMIDS and MIDSDTC.",
                                        "Document": "Model v2.0",
                                        "Item": "MIDS",
                                        "Section": "Timing"
                                    }
                                ]
                            }
                        ]
                    }
                ]
            }
        ],
        "Scope": {
            "Classes": {
                "Include": [
                    "ALL"
                ]
            },
            "Domains": {
                "Include": [
                    "ALL"
                ]
            }
        }
    }
}