{
    "id": "506e4fdb-9a8a-49f5-b917-e58dbf0394f2",
    "changed": "2022-07-17T11:07:50Z",
    "content": "Check:\n  all:\n    - name: $RELMIDS_EXISTS\n      operator: equal_to\n      value: true\n    - name: TM\n      operator: not_exists\nOperations:\n  - id: $RELMIDS_EXISTS\n    name: RELMIDS\n    operator: variable_exists\nCore:\n  Id: CDISC.SDTMIG.CG0502\n  Version: '1'\n  Status: Draft\nDescription: Raise an error when variable RELMIDS is present in any of the dataset\n  and TM dataset is missing in a study.\nOutcome:\n  Message: TM dataset is missing when RELMIDS variable is present in any of the dataset.\nRule Type: Domain Presence Check\nSensitivity: Dataset\nAuthorities:\n  - Organization: CDISC\n    Standards:\n      - Name: SDTMIG\n        Version: '3.4'\n        References:\n          - Origin: SDTM and SDTMIG Conformance Rules\n            Rule Identifier:\n              Id: CG0502\n              Version: '2'\n            Version: '2.0'\n            Citations:\n              - Cited Guidance: The temporal relationship of the observation to the\n                  Disease Milestone Instance Name in MIDS.\n                Document: Model v2.0\n                Item: RELMIDS\n                Section: Timing\nScope:\n  Classes:\n    Include:\n      - ALL\n  Domains:\n    Include:\n      - ALL\n",
    "created": "2021-11-03T11:56:09Z",
    "creator": {
        "id": "fac95de6-5815-411a-a579-ddbc7ee4b97a"
    },
    "json": {
        "Check": {
            "all": [
                {
                    "name": "$RELMIDS_EXISTS",
                    "operator": "equal_to",
                    "value": true
                },
                {
                    "name": "TM",
                    "operator": "not_exists"
                }
            ]
        },
        "Operations": [
            {
                "id": "$RELMIDS_EXISTS",
                "name": "RELMIDS",
                "operator": "variable_exists"
            }
        ],
        "Core": {
            "Id": "CDISC.SDTMIG.CG0502",
            "Version": "1",
            "Status": "Draft"
        },
        "Description": "Raise an error when variable RELMIDS is present in any of the dataset and TM dataset is missing in a study.",
        "Outcome": {
            "Message": "TM dataset is missing when RELMIDS variable is present in any of the dataset."
        },
        "Rule_Type": "Domain Presence Check",
        "Sensitivity": "Dataset",
        "Authorities": [
            {
                "Organization": "CDISC",
                "Standards": [
                    {
                        "Name": "SDTMIG",
                        "Version": "3.4",
                        "References": [
                            {
                                "Origin": "SDTM and SDTMIG Conformance Rules",
                                "Rule_Identifier": {
                                    "Id": "CG0502",
                                    "Version": "2"
                                },
                                "Version": "2.0",
                                "Citations": [
                                    {
                                        "Cited_Guidance": "The temporal relationship of the observation to the Disease Milestone Instance Name in MIDS.",
                                        "Document": "Model v2.0",
                                        "Item": "RELMIDS",
                                        "Section": "Timing"
                                    }
                                ]
                            }
                        ]
                    }
                ]
            }
        ],
        "Scope": {
            "Classes": {
                "Include": [
                    "ALL"
                ]
            },
            "Domains": {
                "Include": [
                    "ALL"
                ]
            }
        }
    }
}