{
    "id": "9468d363-8a7a-47c2-9ff3-53080832352b",
    "changed": "2022-10-11T12:15:21.130Z",
    "content": "Check:\n  all:\n    - name: DSCAT\n      operator: equal_to\n      value: DISPOSITION EVENT\n      value_is_literal: true\n    - name: DSSCAT\n      operator: equal_to\n      value: STUDY TREATMENT\n    - name: DSSCAT\n      operator: is_not_unique_set\n      value: USUBJID\nCore:\n  Id: CORE-000215\n  Version: '1'\n  Status: Published\nDescription: Trigger error when there is more than 1 record per subject has DSSCAT\n  = 'STUDY TREATMENT'\nOutcome:\n  Message: There is more than 1 record per subject has DSSCAT = 'STUDY TREATMENT'\n  Output Variables:\n    - USUBJID\n    - DSCAT\n    - DSSCAT\nRule Type: Record Data\nSensitivity: Record\nAuthorities:\n  - Organization: CDISC\n    Standards:\n      - Name: SDTMIG\n        Version: '3.4'\n        References:\n          - Origin: SDTM and SDTMIG Conformance Rules\n            Rule Identifier:\n              Id: CG0539\n              Version: '1'\n            Version: '2.0'\n            Citations:\n              - Cited Guidance: DSSCAT = 'STUDY TREATMENT' can be used as a generic\n                  identifier when a study has only a single treatment.\n                Document: IG v3.4\n                Item: Assumption 2.b.2\n                Section: 6.2.3\n              - Cited Guidance: If a study has multiple treatments, then DSSCAT should\n                  name the individual treatment.\n                Document: IG v3.4\n                Item: Assumption 2.b.3\n                Section: 6.2.3\nScope:\n  Classes:\n    Include:\n      - EVENTS\n  Domains:\n    Include:\n      - DS\n",
    "created": "2021-11-08T10:26:45Z",
    "creator": {
        "id": "ff471ff8-f131-4cf5-9712-c79cce6301a1"
    },
    "json": {
        "Check": {
            "all": [
                {
                    "name": "DSCAT",
                    "operator": "equal_to",
                    "value": "DISPOSITION EVENT",
                    "value_is_literal": true
                },
                {
                    "name": "DSSCAT",
                    "operator": "equal_to",
                    "value": "STUDY TREATMENT"
                },
                {
                    "name": "DSSCAT",
                    "operator": "is_not_unique_set",
                    "value": "USUBJID"
                }
            ]
        },
        "Core": {
            "Id": "CORE-000215",
            "Version": "1",
            "Status": "Published"
        },
        "Description": "Trigger error when there is more than 1 record per subject has DSSCAT = 'STUDY TREATMENT'",
        "Outcome": {
            "Message": "There is more than 1 record per subject has DSSCAT = 'STUDY TREATMENT'",
            "Output_Variables": [
                "USUBJID",
                "DSCAT",
                "DSSCAT"
            ]
        },
        "Rule_Type": "Record Data",
        "Sensitivity": "Record",
        "Authorities": [
            {
                "Organization": "CDISC",
                "Standards": [
                    {
                        "Name": "SDTMIG",
                        "Version": "3.4",
                        "References": [
                            {
                                "Origin": "SDTM and SDTMIG Conformance Rules",
                                "Rule_Identifier": {
                                    "Id": "CG0539",
                                    "Version": "1"
                                },
                                "Version": "2.0",
                                "Citations": [
                                    {
                                        "Cited_Guidance": "DSSCAT = 'STUDY TREATMENT' can be used as a generic identifier when a study has only a single treatment.",
                                        "Document": "IG v3.4",
                                        "Item": "Assumption 2.b.2",
                                        "Section": "6.2.3"
                                    },
                                    {
                                        "Cited_Guidance": "If a study has multiple treatments, then DSSCAT should name the individual treatment.",
                                        "Document": "IG v3.4",
                                        "Item": "Assumption 2.b.3",
                                        "Section": "6.2.3"
                                    }
                                ]
                            }
                        ]
                    }
                ]
            }
        ],
        "Scope": {
            "Classes": {
                "Include": [
                    "EVENTS"
                ]
            },
            "Domains": {
                "Include": [
                    "DS"
                ]
            }
        }
    }
}