{
    "id": "9b0b0834-9c7d-4217-84d3-34ec2ceec994",
    "changed": "2022-03-09T01:56:29Z",
    "content": "Check:\n  all:\n    - name: ARMCD\n      operator: empty\n    - name: ARM\n      operator: non_empty\nCore:\n  Id: CORE-000119\n  Version: '1'\n  Status: Published\nDescription: Raise an error when ARM is not empty, but ARMCD is empty\nOutcome:\n  Message: ARM is populated, when ARMCD is NULL\n  Output Variables:\n    - ARMCD\n    - ARM\nRule Type: Record Data\nSensitivity: Record\nAuthorities:\n  - Organization: CDISC\n    Standards:\n      - Name: SDTMIG\n        Version: '3.4'\n        References:\n          - Origin: SDTM and SDTMIG Conformance Rules\n            Rule Identifier:\n              Id: CG0521\n              Version: '1'\n            Version: '2.0'\n            Citations:\n              - Cited Guidance: If ARMCD is null, then ARM must be null and ARMNRS\n                  must be populated with the reason ARMCD is null.\n                Document: IG v3.4\n                Item: Assumption 4\n                Section: '5.2'\nScope:\n  Classes:\n    Include:\n      - SPECIAL-PURPOSE\n  Domains:\n    Include:\n      - DM\n",
    "created": "2021-10-12T02:16:21Z",
    "creator": {
        "id": "d0881041-369e-4940-b721-5b456d12101b"
    },
    "json": {
        "Check": {
            "all": [
                {
                    "name": "ARMCD",
                    "operator": "empty"
                },
                {
                    "name": "ARM",
                    "operator": "non_empty"
                }
            ]
        },
        "Core": {
            "Id": "CORE-000119",
            "Version": "1",
            "Status": "Published"
        },
        "Description": "Raise an error when ARM is not empty, but ARMCD is empty",
        "Outcome": {
            "Message": "ARM is populated, when ARMCD is NULL",
            "Output_Variables": [
                "ARMCD",
                "ARM"
            ]
        },
        "Rule_Type": "Record Data",
        "Sensitivity": "Record",
        "Authorities": [
            {
                "Organization": "CDISC",
                "Standards": [
                    {
                        "Name": "SDTMIG",
                        "Version": "3.4",
                        "References": [
                            {
                                "Origin": "SDTM and SDTMIG Conformance Rules",
                                "Rule_Identifier": {
                                    "Id": "CG0521",
                                    "Version": "1"
                                },
                                "Version": "2.0",
                                "Citations": [
                                    {
                                        "Cited_Guidance": "If ARMCD is null, then ARM must be null and ARMNRS must be populated with the reason ARMCD is null.",
                                        "Document": "IG v3.4",
                                        "Item": "Assumption 4",
                                        "Section": "5.2"
                                    }
                                ]
                            }
                        ]
                    }
                ]
            }
        ],
        "Scope": {
            "Classes": {
                "Include": [
                    "SPECIAL-PURPOSE"
                ]
            },
            "Domains": {
                "Include": [
                    "DM"
                ]
            }
        }
    }
}