{
    "id": "c8ed4f77-2943-4612-a2e0-b125ce11288f",
    "changed": "2022-10-11T12:49:34.404Z",
    "content": "Check:\n  any:\n    - all:\n        - name: DOMAIN\n          operator: prefix_matches_regex\n          prefix: 2\n          value: (AP|ap)\n        - name: APID\n          operator: not_exists\n    - all:\n        - name: DOMAIN\n          operator: not_prefix_matches_regex\n          prefix: 2\n          value: (AP|ap)\n        - name: STUDYID\n          operator: exists\n        - name: --SEQ\n          operator: exists\n        - name: USUBJID\n          operator: not_exists\n        - name: SPDEVID\n          operator: not_exists\n        - name: POOLID\n          operator: not_exists\nCore:\n  Id: CORE-000107\n  Version: '1'\n  Status: Published\nDescription: APID is required in all Associated Persons Data. In addition to STUDYID,\n  DOMAIN, and --SEQ being required for all domains based on one of the 3 general observation\n  classes, one of USUBJID, APID, SPDEVID, or POOLID must also be present.\nOutcome:\n  Message: An appropriate subject identifier is not present.  APID is required in\n    all Associated Persons Data. In addition to STUDYID, DOMAIN, and --SEQ being required\n    for all domains based on one of the 3 general observation classes, one of USUBJID,\n    APID, SPDEVID, or POOLID must also be present.\nRule Type: Record Data\nSensitivity: Dataset\nAuthorities:\n  - Organization: CDISC\n    Standards:\n      - Name: SDTMIG\n        Version: '3.4'\n        References:\n          - Origin: SDTM and SDTMIG Conformance Rules\n            Rule Identifier:\n              Id: CG0554\n              Version: '1'\n            Version: '2.0'\n            Citations:\n              - Cited Guidance: STUDYID, DOMAIN, and --SEQ are required in all domains\n                  based on one of the 3 general observation classes. Each general\n                  class domain must also include at least one of the following subject\n                  identifiers USUBJID, SPDEVID, or POOLID.\n                Document: Model v2.0\n                Section: Identifiers\n              - Cited Guidance: The Associated Persons Identifier (APID) will be required\n                  in all AP datasets, and will identify records as AP data.'\n                Document: Model v2.0\n                Section: Associated Persons Data\nScope:\n  Classes:\n    Include:\n      - ALL\n  Domains:\n    Include:\n      - ALL\n",
    "created": "2021-10-07T12:53:22Z",
    "creator": {
        "id": "87137f01-406d-495e-9cad-f73dc359c273"
    },
    "json": {
        "Check": {
            "any": [
                {
                    "all": [
                        {
                            "name": "DOMAIN",
                            "operator": "prefix_matches_regex",
                            "prefix": 2,
                            "value": "(AP|ap)"
                        },
                        {
                            "name": "APID",
                            "operator": "not_exists"
                        }
                    ]
                },
                {
                    "all": [
                        {
                            "name": "DOMAIN",
                            "operator": "not_prefix_matches_regex",
                            "prefix": 2,
                            "value": "(AP|ap)"
                        },
                        {
                            "name": "STUDYID",
                            "operator": "exists"
                        },
                        {
                            "name": "--SEQ",
                            "operator": "exists"
                        },
                        {
                            "name": "USUBJID",
                            "operator": "not_exists"
                        },
                        {
                            "name": "SPDEVID",
                            "operator": "not_exists"
                        },
                        {
                            "name": "POOLID",
                            "operator": "not_exists"
                        }
                    ]
                }
            ]
        },
        "Core": {
            "Id": "CORE-000107",
            "Version": "1",
            "Status": "Published"
        },
        "Description": "APID is required in all Associated Persons Data. In addition to STUDYID, DOMAIN, and --SEQ being required for all domains based on one of the 3 general observation classes, one of USUBJID, APID, SPDEVID, or POOLID must also be present.",
        "Outcome": {
            "Message": "An appropriate subject identifier is not present.  APID is required in all Associated Persons Data. In addition to STUDYID, DOMAIN, and --SEQ being required for all domains based on one of the 3 general observation classes, one of USUBJID, APID, SPDEVID, or POOLID must also be present."
        },
        "Rule_Type": "Record Data",
        "Sensitivity": "Dataset",
        "Authorities": [
            {
                "Organization": "CDISC",
                "Standards": [
                    {
                        "Name": "SDTMIG",
                        "Version": "3.4",
                        "References": [
                            {
                                "Origin": "SDTM and SDTMIG Conformance Rules",
                                "Rule_Identifier": {
                                    "Id": "CG0554",
                                    "Version": "1"
                                },
                                "Version": "2.0",
                                "Citations": [
                                    {
                                        "Cited_Guidance": "STUDYID, DOMAIN, and --SEQ are required in all domains based on one of the 3 general observation classes. Each general class domain must also include at least one of the following subject identifiers USUBJID, SPDEVID, or POOLID.",
                                        "Document": "Model v2.0",
                                        "Section": "Identifiers"
                                    },
                                    {
                                        "Cited_Guidance": "The Associated Persons Identifier (APID) will be required in all AP datasets, and will identify records as AP data.'",
                                        "Document": "Model v2.0",
                                        "Section": "Associated Persons Data"
                                    }
                                ]
                            }
                        ]
                    }
                ]
            }
        ],
        "Scope": {
            "Classes": {
                "Include": [
                    "ALL"
                ]
            },
            "Domains": {
                "Include": [
                    "ALL"
                ]
            }
        }
    }
}