{
    "id": "03d46573-5ef7-45d4-b610-c6d6e7cebe98",
    "changed": "2022-03-09T19:53:47Z",
    "content": "Check:\n  all:\n    - name: --LOBXFL\n      operator: equal_to\n      value: Y\n    - name: --STRESC\n      operator: empty\nCore:\n  Id: CORE-000105\n  Version: '1'\n  Status: Published\nDescription: Raise an error when --LOBXFL = 'Y' and --STRESC is empty.\nOutcome:\n  Message: --LOBXFL = 'Y', but --STRESC is empty.\n  Output Variables:\n    - --TESTCD\n    - --CAT\nRule Type: Record Data\nSensitivity: Record\nAuthorities:\n  - Organization: CDISC\n    Standards:\n      - Name: SDTMIG\n        Version: '3.4'\n        References:\n          - Origin: SDTM and SDTMIG Conformance Rules\n            Rule Identifier:\n              Id: CG0569\n              Version: '1'\n            Version: '2.0'\n            Citations:\n              - Cited Guidance: Operationally-derived indicator used to identify the\n                  last non-missing value prior to RFXSTDTC. Result value is in --STRESC.\n                Document: Model 2.0\n                Item: --STRESC\n                Section: Findings\nScope:\n  Classes:\n    Include:\n      - FINDINGS\n  Domains:\n    Include:\n      - ALL\n",
    "created": "2021-10-07T08:56:01Z",
    "creator": {
        "id": "02c3c969-4787-4d57-b164-e2851035c0e8"
    },
    "json": {
        "Check": {
            "all": [
                {
                    "name": "--LOBXFL",
                    "operator": "equal_to",
                    "value": "Y"
                },
                {
                    "name": "--STRESC",
                    "operator": "empty"
                }
            ]
        },
        "Core": {
            "Id": "CORE-000105",
            "Version": "1",
            "Status": "Published"
        },
        "Description": "Raise an error when --LOBXFL = 'Y' and --STRESC is empty.",
        "Outcome": {
            "Message": "--LOBXFL = 'Y', but --STRESC is empty.",
            "Output_Variables": [
                "--TESTCD",
                "--CAT"
            ]
        },
        "Rule_Type": "Record Data",
        "Sensitivity": "Record",
        "Authorities": [
            {
                "Organization": "CDISC",
                "Standards": [
                    {
                        "Name": "SDTMIG",
                        "Version": "3.4",
                        "References": [
                            {
                                "Origin": "SDTM and SDTMIG Conformance Rules",
                                "Rule_Identifier": {
                                    "Id": "CG0569",
                                    "Version": "1"
                                },
                                "Version": "2.0",
                                "Citations": [
                                    {
                                        "Cited_Guidance": "Operationally-derived indicator used to identify the last non-missing value prior to RFXSTDTC. Result value is in --STRESC.",
                                        "Document": "Model 2.0",
                                        "Item": "--STRESC",
                                        "Section": "Findings"
                                    }
                                ]
                            }
                        ]
                    }
                ]
            }
        ],
        "Scope": {
            "Classes": {
                "Include": [
                    "FINDINGS"
                ]
            },
            "Domains": {
                "Include": [
                    "ALL"
                ]
            }
        }
    }
}