{
    "id": "c12b7782-c0a0-4e39-9399-fc57fd833146",
    "changed": "2022-07-17T04:51:09Z",
    "content": "Check:\n  all:\n    - name:\n      operator:\n    - name: RACE\n      operator: not_equal_to\n      value: MULTIPLE\nCore:\n  Id: CDISC.SDTMIG.CG0527\n  Version: '1'\n  Status: Draft\nDescription: Trigger error when RACE does not equal \"MULTIPLE\" when multiple races\n  collected and primary race not specified\nOutcome:\n  Message: RACE does not equal \"MULTIPLE\" when multiple races collected and primary\n    race not specified\nRule Type: Record Data\nSensitivity: Record\nAuthorities:\n  - Organization: CDISC\n    Standards:\n      - Name: SDTMIG\n        Version: '3.4'\n        References:\n          - Origin: SDTM and SDTMIG Conformance Rules\n            Rule Identifier:\n              Id: CG0527\n              Version: '1'\n            Version: '2.0'\n            Citations:\n              - Cited Guidance: If multiple races are collected, then the value of\n                  RACE should be \u201cMULTIPLE\u201d and the additional information will be\n                  included in the Supplemental Qualifiers dataset.\n                Document: IG v3.4\n                Item: Assumption 6\n                Section: '5.2'\nScope:\n  Classes:\n    Include:\n      - SPECIAL-PURPOSE\n  Domains:\n    Include:\n      - DM\n",
    "created": "2021-11-08T10:25:45Z",
    "creator": {
        "id": "ff471ff8-f131-4cf5-9712-c79cce6301a1"
    },
    "json": {
        "Check": {
            "all": [
                {
                    "name": null,
                    "operator": null
                },
                {
                    "name": "RACE",
                    "operator": "not_equal_to",
                    "value": "MULTIPLE"
                }
            ]
        },
        "Core": {
            "Id": "CDISC.SDTMIG.CG0527",
            "Version": "1",
            "Status": "Draft"
        },
        "Description": "Trigger error when RACE does not equal \"MULTIPLE\" when multiple races collected and primary race not specified",
        "Outcome": {
            "Message": "RACE does not equal \"MULTIPLE\" when multiple races collected and primary race not specified"
        },
        "Rule_Type": "Record Data",
        "Sensitivity": "Record",
        "Authorities": [
            {
                "Organization": "CDISC",
                "Standards": [
                    {
                        "Name": "SDTMIG",
                        "Version": "3.4",
                        "References": [
                            {
                                "Origin": "SDTM and SDTMIG Conformance Rules",
                                "Rule_Identifier": {
                                    "Id": "CG0527",
                                    "Version": "1"
                                },
                                "Version": "2.0",
                                "Citations": [
                                    {
                                        "Cited_Guidance": "If multiple races are collected, then the value of RACE should be \u201cMULTIPLE\u201d and the additional information will be included in the Supplemental Qualifiers dataset.",
                                        "Document": "IG v3.4",
                                        "Item": "Assumption 6",
                                        "Section": "5.2"
                                    }
                                ]
                            }
                        ]
                    }
                ]
            }
        ],
        "Scope": {
            "Classes": {
                "Include": [
                    "SPECIAL-PURPOSE"
                ]
            },
            "Domains": {
                "Include": [
                    "DM"
                ]
            }
        }
    }
}