{
    "id": "86704bbf-9dae-4254-a8bc-7d105db32459",
    "changed": "2022-05-17T18:21:21Z",
    "content": "Check:\n  all:\n    - name: ARM\n      operator: is_contained_by_case_insensitive\n      value:\n        - Screen Failure\n        - Not Assigned\n        - Not Treated\n        - Unplanned Treatment\nCore:\n  Id: CORE-000115\n  Version: '1'\n  Status: Published\nDescription: Raise an error when ARM is 'Screen Failure', 'Not Assigned', 'Unplanned\n  Treatment', 'Not Treated'\nOutcome:\n  Message: ARM cannot be equal to 'Screen Failure', 'Not Assigned', 'Unplanned Treatment'\n    or 'Not Treated'.\nRule Type: Record Data\nSensitivity: Record\nAuthorities:\n  - Organization: CDISC\n    Standards:\n      - Name: SDTMIG\n        Version: '3.4'\n        References:\n          - Origin: SDTM and SDTMIG Conformance Rules\n            Rule Identifier:\n              Id: CG0570\n              Version: '1'\n            Version: '2.0'\n            Citations:\n              - Cited Guidance: The trial arms table describes each planned arm in\n                  the trial.\n                Document: SDTMIG v3.4\n                Section: '7.2'\n              - Cited Guidance: The trial arms table describes each planned arm in\n                  the trial.\n                Document: SDTMIG v3.4\n                Section: 7.3.1\n              - Cited Guidance: The trial arms table describes each planned arm in\n                  the trial.\n                Document: SDTMIG v3.4\n                Section: '5.2'\nScope:\n  Classes:\n    Include:\n      - TRIAL DESIGN\n      - SPECIAL-PURPOSE\n  Domains:\n    Include:\n      - DM\n      - TA\n      - TV\n",
    "created": "2021-10-08T12:32:43Z",
    "creator": {
        "id": "ff471ff8-f131-4cf5-9712-c79cce6301a1"
    },
    "json": {
        "Check": {
            "all": [
                {
                    "name": "ARM",
                    "operator": "is_contained_by_case_insensitive",
                    "value": [
                        "Screen Failure",
                        "Not Assigned",
                        "Not Treated",
                        "Unplanned Treatment"
                    ]
                }
            ]
        },
        "Core": {
            "Id": "CORE-000115",
            "Version": "1",
            "Status": "Published"
        },
        "Description": "Raise an error when ARM is 'Screen Failure', 'Not Assigned', 'Unplanned Treatment', 'Not Treated'",
        "Outcome": {
            "Message": "ARM cannot be equal to 'Screen Failure', 'Not Assigned', 'Unplanned Treatment' or 'Not Treated'."
        },
        "Rule_Type": "Record Data",
        "Sensitivity": "Record",
        "Authorities": [
            {
                "Organization": "CDISC",
                "Standards": [
                    {
                        "Name": "SDTMIG",
                        "Version": "3.4",
                        "References": [
                            {
                                "Origin": "SDTM and SDTMIG Conformance Rules",
                                "Rule_Identifier": {
                                    "Id": "CG0570",
                                    "Version": "1"
                                },
                                "Version": "2.0",
                                "Citations": [
                                    {
                                        "Cited_Guidance": "The trial arms table describes each planned arm in the trial.",
                                        "Document": "SDTMIG v3.4",
                                        "Section": "7.2"
                                    },
                                    {
                                        "Cited_Guidance": "The trial arms table describes each planned arm in the trial.",
                                        "Document": "SDTMIG v3.4",
                                        "Section": "7.3.1"
                                    },
                                    {
                                        "Cited_Guidance": "The trial arms table describes each planned arm in the trial.",
                                        "Document": "SDTMIG v3.4",
                                        "Section": "5.2"
                                    }
                                ]
                            }
                        ]
                    }
                ]
            }
        ],
        "Scope": {
            "Classes": {
                "Include": [
                    "TRIAL DESIGN",
                    "SPECIAL-PURPOSE"
                ]
            },
            "Domains": {
                "Include": [
                    "DM",
                    "TA",
                    "TV"
                ]
            }
        }
    }
}