{
    "id": "12e9b275-a577-4302-b99f-2094cc069e9e",
    "changed": "2022-02-23T06:52:19Z",
    "content": "Check:\n  all:\n    - name: MIDSDTC\n      operator: exists\n    - name: MIDS\n      operator: not_exists\nCore:\n  Id: CORE-000193\n  Version: '1'\n  Status: Published\nDescription: Raise an error when variable MIDSDTC is present and MIDS variable is\n  missing.\nOutcome:\n  Message: MIDS variable is missing when MIDSDTC variable is present in a dataset.\n  Output Variables:\n    - MIDSDTC\n    - MIDS\nRule Type: Record Data\nSensitivity: Dataset\nAuthorities:\n  - Organization: CDISC\n    Standards:\n      - Name: SDTMIG\n        Version: '3.4'\n        References:\n          - Origin: SDTM and SDTMIG Conformance Rules\n            Rule Identifier:\n              Id: CG0503\n              Version: '1'\n            Version: '2.0'\n            Citations:\n              - Cited Guidance: The start date/time of the Disease Milestone Instance\n                  Name in MIDS.\n                Document: Model v2.0\n                Item: MIDSDTC\n                Section: Timing\nScope:\n  Classes:\n    Include:\n      - ALL\n  Domains:\n    Include:\n      - ALL\n",
    "created": "2021-11-03T11:59:19Z",
    "creator": {
        "id": "fac95de6-5815-411a-a579-ddbc7ee4b97a"
    },
    "json": {
        "Check": {
            "all": [
                {
                    "name": "MIDSDTC",
                    "operator": "exists"
                },
                {
                    "name": "MIDS",
                    "operator": "not_exists"
                }
            ]
        },
        "Core": {
            "Id": "CORE-000193",
            "Version": "1",
            "Status": "Published"
        },
        "Description": "Raise an error when variable MIDSDTC is present and MIDS variable is missing.",
        "Outcome": {
            "Message": "MIDS variable is missing when MIDSDTC variable is present in a dataset.",
            "Output_Variables": [
                "MIDSDTC",
                "MIDS"
            ]
        },
        "Rule_Type": "Record Data",
        "Sensitivity": "Dataset",
        "Authorities": [
            {
                "Organization": "CDISC",
                "Standards": [
                    {
                        "Name": "SDTMIG",
                        "Version": "3.4",
                        "References": [
                            {
                                "Origin": "SDTM and SDTMIG Conformance Rules",
                                "Rule_Identifier": {
                                    "Id": "CG0503",
                                    "Version": "1"
                                },
                                "Version": "2.0",
                                "Citations": [
                                    {
                                        "Cited_Guidance": "The start date/time of the Disease Milestone Instance Name in MIDS.",
                                        "Document": "Model v2.0",
                                        "Item": "MIDSDTC",
                                        "Section": "Timing"
                                    }
                                ]
                            }
                        ]
                    }
                ]
            }
        ],
        "Scope": {
            "Classes": {
                "Include": [
                    "ALL"
                ]
            },
            "Domains": {
                "Include": [
                    "ALL"
                ]
            }
        }
    }
}