{
    "id": "e2319650-f0f6-4d82-a7c1-c9fc81776e98",
    "changed": "2022-04-14T00:26:38Z",
    "content": "Check:\n  all:\n    - any:\n        - name: --ORREF\n          operator: non_empty\n        - name: --DRVFL\n          operator: equal_to\n          value: Y\n    - name: --STREFC\n      operator: empty\nCore:\n  Id: CORE-000110\n  Version: '1'\n  Status: Published\nDescription: Raise an error when (--ORREF ^= null or --DRVFL='Y') and --STREFC is\n  null.\nOutcome:\n  Message: --STREFC is null when --ORREF is non-empty or --DRVFL is equal to 'Y'\n  Output Variables:\n    - --ORREF\n    - --DRVFL\n    - --STREFC\nRule Type: Record Data\nSensitivity: Record\nAuthorities:\n  - Organization: CDISC\n    Standards:\n      - Name: SDTMIG\n        Version: '3.4'\n        References:\n          - Origin: SDTM and SDTMIG Conformance Rules\n            Rule Identifier:\n              Id: CG0549\n              Version: '1'\n            Version: '2.0'\n            Citations:\n              - Cited Guidance: Reference value for the result or finding copied or\n                  derived from --ORREF in a standard format.\n                Document: SDTM v2.0\n                Item: --STREFC\n                Section: Findings\nScope:\n  Classes:\n    Include:\n      - FINDINGS\n  Domains:\n    Include:\n      - ALL\n",
    "created": "2021-10-08T11:57:55Z",
    "creator": {
        "id": "ff471ff8-f131-4cf5-9712-c79cce6301a1"
    },
    "json": {
        "Check": {
            "all": [
                {
                    "any": [
                        {
                            "name": "--ORREF",
                            "operator": "non_empty"
                        },
                        {
                            "name": "--DRVFL",
                            "operator": "equal_to",
                            "value": "Y"
                        }
                    ]
                },
                {
                    "name": "--STREFC",
                    "operator": "empty"
                }
            ]
        },
        "Core": {
            "Id": "CORE-000110",
            "Version": "1",
            "Status": "Published"
        },
        "Description": "Raise an error when (--ORREF ^= null or --DRVFL='Y') and --STREFC is null.",
        "Outcome": {
            "Message": "--STREFC is null when --ORREF is non-empty or --DRVFL is equal to 'Y'",
            "Output_Variables": [
                "--ORREF",
                "--DRVFL",
                "--STREFC"
            ]
        },
        "Rule_Type": "Record Data",
        "Sensitivity": "Record",
        "Authorities": [
            {
                "Organization": "CDISC",
                "Standards": [
                    {
                        "Name": "SDTMIG",
                        "Version": "3.4",
                        "References": [
                            {
                                "Origin": "SDTM and SDTMIG Conformance Rules",
                                "Rule_Identifier": {
                                    "Id": "CG0549",
                                    "Version": "1"
                                },
                                "Version": "2.0",
                                "Citations": [
                                    {
                                        "Cited_Guidance": "Reference value for the result or finding copied or derived from --ORREF in a standard format.",
                                        "Document": "SDTM v2.0",
                                        "Item": "--STREFC",
                                        "Section": "Findings"
                                    }
                                ]
                            }
                        ]
                    }
                ]
            }
        ],
        "Scope": {
            "Classes": {
                "Include": [
                    "FINDINGS"
                ]
            },
            "Domains": {
                "Include": [
                    "ALL"
                ]
            }
        }
    }
}