{
    "id": "bf0d6683-901e-4022-ac40-ca48b1f66acf",
    "changed": "2022-03-17T14:32:06Z",
    "content": "Check:\n  all:\n    - name: --IMPLBL\n      operator: exists\nCore:\n  Id: CORE-000074\n  Version: '1'\n  Status: Published\nDescription: Raise an error when --IMPLBL is present.\nOutcome:\n  Message: --IMPLBL is present.\n  Output Variables:\n    - --IMPLBL\nRule Type: Record Data\nSensitivity: Dataset\nAuthorities:\n  - Organization: CDISC\n    Standards:\n      - Name: SDTMIG\n        Version: '3.4'\n        References:\n          - Origin: SDTM and SDTMIG Conformance Rules\n            Rule Identifier:\n              Id: CG0508\n              Version: '1'\n            Version: '2.0'\n            Citations:\n              - Cited Guidance: The following SDTM variables, defined for use in non-clinical\n                  studies (SEND), must NEVER be used in the submission of SDTM-based\n                  data for human clinical trials, --USCHFL (Interventions, Events,\n                  Findings), --DTHREL (Findings), --EXCLFL (Findings), --REASEX (Findings),\n                  --IMPLBL (Findings), FETUSID (Identifiers), --DETECT (Timing Variables),\n                  --NOMDY (Timing Variables), --NOMLBL (Timing Variables)\n                Document: IG v3.4\n                Item: SDTM Variables Not Allowed in SDTMIG\n                Section: '2.7'\nScope:\n  Classes:\n    Include:\n      - ALL\n  Domains:\n    Include:\n      - ALL\n",
    "created": "2021-10-04T05:28:51Z",
    "creator": {
        "id": "ff471ff8-f131-4cf5-9712-c79cce6301a1"
    },
    "json": {
        "Check": {
            "all": [
                {
                    "name": "--IMPLBL",
                    "operator": "exists"
                }
            ]
        },
        "Core": {
            "Id": "CORE-000074",
            "Version": "1",
            "Status": "Published"
        },
        "Description": "Raise an error when --IMPLBL is present.",
        "Outcome": {
            "Message": "--IMPLBL is present.",
            "Output_Variables": [
                "--IMPLBL"
            ]
        },
        "Rule_Type": "Record Data",
        "Sensitivity": "Dataset",
        "Authorities": [
            {
                "Organization": "CDISC",
                "Standards": [
                    {
                        "Name": "SDTMIG",
                        "Version": "3.4",
                        "References": [
                            {
                                "Origin": "SDTM and SDTMIG Conformance Rules",
                                "Rule_Identifier": {
                                    "Id": "CG0508",
                                    "Version": "1"
                                },
                                "Version": "2.0",
                                "Citations": [
                                    {
                                        "Cited_Guidance": "The following SDTM variables, defined for use in non-clinical studies (SEND), must NEVER be used in the submission of SDTM-based data for human clinical trials, --USCHFL (Interventions, Events, Findings), --DTHREL (Findings), --EXCLFL (Findings), --REASEX (Findings), --IMPLBL (Findings), FETUSID (Identifiers), --DETECT (Timing Variables), --NOMDY (Timing Variables), --NOMLBL (Timing Variables)",
                                        "Document": "IG v3.4",
                                        "Item": "SDTM Variables Not Allowed in SDTMIG",
                                        "Section": "2.7"
                                    }
                                ]
                            }
                        ]
                    }
                ]
            }
        ],
        "Scope": {
            "Classes": {
                "Include": [
                    "ALL"
                ]
            },
            "Domains": {
                "Include": [
                    "ALL"
                ]
            }
        }
    }
}