{
    "id": "1e95bf13-9d51-460c-9fe7-20a6c3c47916",
    "changed": "2022-10-11T12:16:50.710Z",
    "content": "Check:\n  all:\n    - name: ARMCD\n      operator: non_empty\n    - name: ARMCD\n      operator: is_not_contained_by\n      value: $ta_armcd\nOperations:\n  - domain: TA\n    id: $ta_armcd\n    name: ARMCD\n    operator: distinct\nCore:\n  Id: CORE-000210\n  Version: '1'\n  Status: Published\nDescription: When study does not use multi-stage arm assignments and ARMCD is populated,\n  ARMCD must be present in TA.ARMCD. This rule has been executed to identify all cases\n  when ARMCD is not present in TA.ARMCD and therefore acknowledges that false positives\n  may be recorded when multi-stage arm assignments are in use.\nOutcome:\n  Message: ARMCD is not present in TA.ARMCD\nRule Type: Record Data\nSensitivity: Record\nAuthorities:\n  - Organization: CDISC\n    Standards:\n      - Name: SDTMIG\n        Version: '3.4'\n        References:\n          - Origin: SDTM and SDTMIG Conformance Rules\n            Rule Identifier:\n              Id: CG0516\n              Version: '1'\n            Version: '2.0'\n            Citations:\n              - Cited Guidance: With the exception of studies which use multi-stage\n                  Arm assignments, must be a value of ARMCD in the Trial Arms Dataset.  If\n                  the subject was not assigned to an Arm, ARMCD is null and ARMNRS\n                  is populated\n                Document: IG v3.4\n                Item: Specification\n                Section: '5.2'\nScope:\n  Classes:\n    Include:\n      - SPECIAL-PURPOSE\n  Domains:\n    Include:\n      - DM\n",
    "created": "2021-11-08T10:24:58Z",
    "creator": {
        "id": "ff471ff8-f131-4cf5-9712-c79cce6301a1"
    },
    "json": {
        "Check": {
            "all": [
                {
                    "name": "ARMCD",
                    "operator": "non_empty"
                },
                {
                    "name": "ARMCD",
                    "operator": "is_not_contained_by",
                    "value": "$ta_armcd"
                }
            ]
        },
        "Operations": [
            {
                "domain": "TA",
                "id": "$ta_armcd",
                "name": "ARMCD",
                "operator": "distinct"
            }
        ],
        "Core": {
            "Id": "CORE-000210",
            "Version": "1",
            "Status": "Published"
        },
        "Description": "When study does not use multi-stage arm assignments and ARMCD is populated, ARMCD must be present in TA.ARMCD. This rule has been executed to identify all cases when ARMCD is not present in TA.ARMCD and therefore acknowledges that false positives may be recorded when multi-stage arm assignments are in use.",
        "Outcome": {
            "Message": "ARMCD is not present in TA.ARMCD"
        },
        "Rule_Type": "Record Data",
        "Sensitivity": "Record",
        "Authorities": [
            {
                "Organization": "CDISC",
                "Standards": [
                    {
                        "Name": "SDTMIG",
                        "Version": "3.4",
                        "References": [
                            {
                                "Origin": "SDTM and SDTMIG Conformance Rules",
                                "Rule_Identifier": {
                                    "Id": "CG0516",
                                    "Version": "1"
                                },
                                "Version": "2.0",
                                "Citations": [
                                    {
                                        "Cited_Guidance": "With the exception of studies which use multi-stage Arm assignments, must be a value of ARMCD in the Trial Arms Dataset.  If the subject was not assigned to an Arm, ARMCD is null and ARMNRS is populated",
                                        "Document": "IG v3.4",
                                        "Item": "Specification",
                                        "Section": "5.2"
                                    }
                                ]
                            }
                        ]
                    }
                ]
            }
        ],
        "Scope": {
            "Classes": {
                "Include": [
                    "SPECIAL-PURPOSE"
                ]
            },
            "Domains": {
                "Include": [
                    "DM"
                ]
            }
        }
    }
}