{
    "id": "5c8efb13-a1b4-4079-9fee-130d1bf29914",
    "changed": "2022-03-10T13:11:04Z",
    "content": "Check:\n  all:\n    - name: ARM\n      operator: non_empty\n    - name: RFENDTC\n      operator: empty\nCore:\n  Id: CORE-000191\n  Version: '1'\n  Status: Published\nDescription: Raise an error when ARM is not empty and RFENDTC is empty.\nOutcome:\n  Message: RFENDTC is missing when ARM is provided.\n  Output Variables:\n    - ARM\n    - RFENDTC\nRule Type: Record Data\nSensitivity: Record\nAuthorities:\n  - Organization: CDISC\n    Standards:\n      - Name: SDTMIG\n        Version: '3.4'\n        References:\n          - Origin: SDTM and SDTMIG Conformance Rules\n            Rule Identifier:\n              Id: CG0529\n              Version: '1'\n            Version: '2.0'\n            Citations:\n              - Cited Guidance: Required for all randomized subjects; null for screen\n                  failures or unassigned subjects.\n                Document: IG v3.4\n                Item: Specification\n                Section: '5.2'\nScope:\n  Classes:\n    Include:\n      - SPECIAL-PURPOSE\n  Domains:\n    Include:\n      - DM\n",
    "created": "2021-11-03T11:13:31Z",
    "creator": {
        "id": "fac95de6-5815-411a-a579-ddbc7ee4b97a"
    },
    "json": {
        "Check": {
            "all": [
                {
                    "name": "ARM",
                    "operator": "non_empty"
                },
                {
                    "name": "RFENDTC",
                    "operator": "empty"
                }
            ]
        },
        "Core": {
            "Id": "CORE-000191",
            "Version": "1",
            "Status": "Published"
        },
        "Description": "Raise an error when ARM is not empty and RFENDTC is empty.",
        "Outcome": {
            "Message": "RFENDTC is missing when ARM is provided.",
            "Output_Variables": [
                "ARM",
                "RFENDTC"
            ]
        },
        "Rule_Type": "Record Data",
        "Sensitivity": "Record",
        "Authorities": [
            {
                "Organization": "CDISC",
                "Standards": [
                    {
                        "Name": "SDTMIG",
                        "Version": "3.4",
                        "References": [
                            {
                                "Origin": "SDTM and SDTMIG Conformance Rules",
                                "Rule_Identifier": {
                                    "Id": "CG0529",
                                    "Version": "1"
                                },
                                "Version": "2.0",
                                "Citations": [
                                    {
                                        "Cited_Guidance": "Required for all randomized subjects; null for screen failures or unassigned subjects.",
                                        "Document": "IG v3.4",
                                        "Item": "Specification",
                                        "Section": "5.2"
                                    }
                                ]
                            }
                        ]
                    }
                ]
            }
        ],
        "Scope": {
            "Classes": {
                "Include": [
                    "SPECIAL-PURPOSE"
                ]
            },
            "Domains": {
                "Include": [
                    "DM"
                ]
            }
        }
    }
}