{
    "id": "54b0fac0-9c4b-47bd-9a0f-84c15a1bdeeb",
    "changed": "2022-11-29T16:03:08.787Z",
    "content": "Check:\n  all:\n    - name: RPATHCD\n      operator: exists\nCore:\n  Id: CORE-000073\n  Version: '1'\n  Status: Published\nDescription: Raise an error when RPATHCD is present.\nOutcome:\n  Message: RPATHCD is present.\n  Output Variables:\n    - RPATHCD\nRule Type: Record Data\nSensitivity: Dataset\nAuthorities:\n  - Organization: CDISC\n    Standards:\n      - Name: SDTMIG\n        Version: '3.4'\n        References:\n          - Origin: SDTM and SDTMIG Conformance Rules\n            Rule Identifier:\n              Id: CG0533\n              Version: '1'\n            Version: '2.0'\n            Citations:\n              - Cited Guidance: RPATHCD is not to be used in human clinical trials.\n                Document: SDTM v2.0\n                Section: Demographics\nScope:\n  Classes:\n    Include:\n      - SPECIAL-PURPOSE\n  Domains:\n    Include:\n      - DM\n",
    "created": "2021-10-04T05:25:52Z",
    "creator": {
        "id": "ff471ff8-f131-4cf5-9712-c79cce6301a1"
    },
    "json": {
        "Check": {
            "all": [
                {
                    "name": "RPATHCD",
                    "operator": "exists"
                }
            ]
        },
        "Core": {
            "Id": "CORE-000073",
            "Version": "1",
            "Status": "Published"
        },
        "Description": "Raise an error when RPATHCD is present.",
        "Outcome": {
            "Message": "RPATHCD is present.",
            "Output_Variables": [
                "RPATHCD"
            ]
        },
        "Rule_Type": "Record Data",
        "Sensitivity": "Dataset",
        "Authorities": [
            {
                "Organization": "CDISC",
                "Standards": [
                    {
                        "Name": "SDTMIG",
                        "Version": "3.4",
                        "References": [
                            {
                                "Origin": "SDTM and SDTMIG Conformance Rules",
                                "Rule_Identifier": {
                                    "Id": "CG0533",
                                    "Version": "1"
                                },
                                "Version": "2.0",
                                "Citations": [
                                    {
                                        "Cited_Guidance": "RPATHCD is not to be used in human clinical trials.",
                                        "Document": "SDTM v2.0",
                                        "Section": "Demographics"
                                    }
                                ]
                            }
                        ]
                    }
                ]
            }
        ],
        "Scope": {
            "Classes": {
                "Include": [
                    "SPECIAL-PURPOSE"
                ]
            },
            "Domains": {
                "Include": [
                    "DM"
                ]
            }
        }
    }
}