{
    "id": "51868eb6-d402-4259-8734-807c0e56dddf",
    "changed": "2022-05-11T12:07:08Z",
    "content": "Check:\n  all:\n    - name: TMRPT\n      operator: equal_to\n      value: Y\n    - name: MIDS\n      operator: #not suffixed with a sequence number in consistent chronological order\r\nMatch Datasets:\n  - Name: TM\n    Keys:\n      - MIDSTYPE\nCore:\n  Id: CDISC.SDTMIG.CG0546\n  Version: '1'\n  Status: Draft\nDescription: Trigger error when MIDSTYPE=TM.MIDSTYPE and TM.TMRPT=Y and MIDS is not\n  suffixed with a sequence number in consistent chronological order\nOutcome:\n  Message: MIDS is not suffixed with a sequence number in consistent chronological\n    order\nRule Type: Record Data\nSensitivity: Dataset\nAuthorities:\n  - Organization: CDISC\n    Standards:\n      - Name: SDTMIG\n        Version: '3.4'\n        References:\n          - Origin: SDTM and SDTMIG Conformance Rules\n            Rule Identifier:\n              Id: CG0546\n              Version: '1'\n            Version: '2.0'\n            Citations:\n              - Cited Guidance: For types of Disease Milestones that can occur multiple\n                  times, MIDS will usually be an abbreviated version of MIDSTYPE and\n                  will always end with a sequence number. Sequence numbers should\n                  start with one and indicate the chronological order of the instances\n                  of this type of Disease Milestone.\n                Document: IG v3.4\n                Item: Assumption 2.b\n                Section: '5.4'\nScope:\n  Classes:\n    Include:\n      - SPECIAL-PURPOSE\n  Domains:\n    Include:\n      - SM\n",
    "created": "2021-11-08T10:27:16Z",
    "creator": {
        "id": "ff471ff8-f131-4cf5-9712-c79cce6301a1"
    },
    "json": {
        "Check": {
            "all": [
                {
                    "name": "TMRPT",
                    "operator": "equal_to",
                    "value": "Y"
                },
                {
                    "name": "MIDS",
                    "operator": null
                }
            ]
        },
        "Match_Datasets": [
            {
                "Name": "TM",
                "Keys": [
                    "MIDSTYPE"
                ]
            }
        ],
        "Core": {
            "Id": "CDISC.SDTMIG.CG0546",
            "Version": "1",
            "Status": "Draft"
        },
        "Description": "Trigger error when MIDSTYPE=TM.MIDSTYPE and TM.TMRPT=Y and MIDS is not suffixed with a sequence number in consistent chronological order",
        "Outcome": {
            "Message": "MIDS is not suffixed with a sequence number in consistent chronological order"
        },
        "Rule_Type": "Record Data",
        "Sensitivity": "Dataset",
        "Authorities": [
            {
                "Organization": "CDISC",
                "Standards": [
                    {
                        "Name": "SDTMIG",
                        "Version": "3.4",
                        "References": [
                            {
                                "Origin": "SDTM and SDTMIG Conformance Rules",
                                "Rule_Identifier": {
                                    "Id": "CG0546",
                                    "Version": "1"
                                },
                                "Version": "2.0",
                                "Citations": [
                                    {
                                        "Cited_Guidance": "For types of Disease Milestones that can occur multiple times, MIDS will usually be an abbreviated version of MIDSTYPE and will always end with a sequence number. Sequence numbers should start with one and indicate the chronological order of the instances of this type of Disease Milestone.",
                                        "Document": "IG v3.4",
                                        "Item": "Assumption 2.b",
                                        "Section": "5.4"
                                    }
                                ]
                            }
                        ]
                    }
                ]
            }
        ],
        "Scope": {
            "Classes": {
                "Include": [
                    "SPECIAL-PURPOSE"
                ]
            },
            "Domains": {
                "Include": [
                    "SM"
                ]
            }
        }
    }
}