{
    "id": "c60254d5-857e-41a2-991d-69cf0d845cf1",
    "changed": "2022-10-11T12:16:43.550Z",
    "content": "Check:\n  all:\n    - name: RDOMAIN\n      operator: equal_to_case_insensitive\n      value: DM\n    - name: QNAM\n      operator: matches_regex\n      value: (ENRFL|SAFFL|EFFFL|ITTFL|PPROTFL|COMPLFL|COMPLT|FULLSET|ITT|PPROT|SAFETY)\nCore:\n  Id: CORE-000211\n  Version: '1'\n  Status: Published\nDescription: SUPPDM must not include population flags.\nOutcome:\n  Message: Population flag is present in SUPPDM\n  Output Variables:\n    - QNAM\nRule Type: Record Data\nSensitivity: Record\nAuthorities:\n  - Organization: CDISC\n    Standards:\n      - Name: SDTMIG\n        Version: '3.4'\n        References:\n          - Origin: SDTM and SDTMIG Conformance Rules\n            Rule Identifier:\n              Id: CG0528\n              Version: '1'\n            Version: '2.0'\n            Citations:\n              - Cited Guidance: The standard Supplemental Qualifiers included in previous\n                  versions of the SDTMIG (COMPLT, FULLSET, ITT, PPROT, and SAFETY)\n                  should not be used. Note that the ADaM subject-level analysis dataset\n                  (ADSL) specifies standard variable names for the most common populations\n                  and requires the inclusion of these flags when necessary for analysis;\n                  consult the ADaM Implementation Guide for more information about\n                  these variables.\n                Document: IG v3.4\n                Item: Assumption 5\n                Section: '5.2'\nScope:\n  Classes:\n    Include:\n      - SPECIAL-PURPOSE\n  Domains:\n    Include:\n      - SUPP--\n",
    "created": "2021-11-08T10:25:53Z",
    "creator": {
        "id": "ff471ff8-f131-4cf5-9712-c79cce6301a1"
    },
    "json": {
        "Check": {
            "all": [
                {
                    "name": "RDOMAIN",
                    "operator": "equal_to_case_insensitive",
                    "value": "DM"
                },
                {
                    "name": "QNAM",
                    "operator": "matches_regex",
                    "value": "(ENRFL|SAFFL|EFFFL|ITTFL|PPROTFL|COMPLFL|COMPLT|FULLSET|ITT|PPROT|SAFETY)"
                }
            ]
        },
        "Core": {
            "Id": "CORE-000211",
            "Version": "1",
            "Status": "Published"
        },
        "Description": "SUPPDM must not include population flags.",
        "Outcome": {
            "Message": "Population flag is present in SUPPDM",
            "Output_Variables": [
                "QNAM"
            ]
        },
        "Rule_Type": "Record Data",
        "Sensitivity": "Record",
        "Authorities": [
            {
                "Organization": "CDISC",
                "Standards": [
                    {
                        "Name": "SDTMIG",
                        "Version": "3.4",
                        "References": [
                            {
                                "Origin": "SDTM and SDTMIG Conformance Rules",
                                "Rule_Identifier": {
                                    "Id": "CG0528",
                                    "Version": "1"
                                },
                                "Version": "2.0",
                                "Citations": [
                                    {
                                        "Cited_Guidance": "The standard Supplemental Qualifiers included in previous versions of the SDTMIG (COMPLT, FULLSET, ITT, PPROT, and SAFETY) should not be used. Note that the ADaM subject-level analysis dataset (ADSL) specifies standard variable names for the most common populations and requires the inclusion of these flags when necessary for analysis; consult the ADaM Implementation Guide for more information about these variables.",
                                        "Document": "IG v3.4",
                                        "Item": "Assumption 5",
                                        "Section": "5.2"
                                    }
                                ]
                            }
                        ]
                    }
                ]
            }
        ],
        "Scope": {
            "Classes": {
                "Include": [
                    "SPECIAL-PURPOSE"
                ]
            },
            "Domains": {
                "Include": [
                    "SUPP--"
                ]
            }
        }
    }
}