{
    "id": "4e42738d-ddc8-4ed6-8ab7-ec127631b03d",
    "changed": "2022-02-15T21:28:02Z",
    "content": "Check:\n  all:\n    - name: --STREFN\n      operator:\nCore:\n  Id: CDISC.SDTMIG.CG0551\n  Version: '1'\n  Status: Draft\nDescription: Trigger error when --STREFN is not in the same units as --STRESN\nOutcome:\n  Message: --STREFN is not in the same units as --STRESN\nRule Type: Record Data\nSensitivity: Record\nAuthorities:\n  - Organization: CDISC\n    Standards:\n      - Name: SDTMIG\n        Version: '3.4'\n        References:\n          - Origin: SDTM and SDTMIG Conformance Rules\n            Rule Identifier:\n              Id: CG0551\n              Version: '1'\n            Version: '2.0'\n            Citations:\n              - Cited Guidance: Reference value for continuous or numeric results\n                  or findings in standard format or in standard units. --STREFN uses\n                  the same units as --STRESN, if applicable.\n                Document: Model v2.0\n                Item: --STREFN\n                Section: Findings\nScope:\n  Classes:\n    Include:\n      - FINDINGS\n  Domains:\n    Include:\n      - ALL\n",
    "created": "2021-11-08T10:27:36Z",
    "creator": {
        "id": "ff471ff8-f131-4cf5-9712-c79cce6301a1"
    },
    "json": {
        "Check": {
            "all": [
                {
                    "name": "--STREFN",
                    "operator": null
                }
            ]
        },
        "Core": {
            "Id": "CDISC.SDTMIG.CG0551",
            "Version": "1",
            "Status": "Draft"
        },
        "Description": "Trigger error when --STREFN is not in the same units as --STRESN",
        "Outcome": {
            "Message": "--STREFN is not in the same units as --STRESN"
        },
        "Rule_Type": "Record Data",
        "Sensitivity": "Record",
        "Authorities": [
            {
                "Organization": "CDISC",
                "Standards": [
                    {
                        "Name": "SDTMIG",
                        "Version": "3.4",
                        "References": [
                            {
                                "Origin": "SDTM and SDTMIG Conformance Rules",
                                "Rule_Identifier": {
                                    "Id": "CG0551",
                                    "Version": "1"
                                },
                                "Version": "2.0",
                                "Citations": [
                                    {
                                        "Cited_Guidance": "Reference value for continuous or numeric results or findings in standard format or in standard units. --STREFN uses the same units as --STRESN, if applicable.",
                                        "Document": "Model v2.0",
                                        "Item": "--STREFN",
                                        "Section": "Findings"
                                    }
                                ]
                            }
                        ]
                    }
                ]
            }
        ],
        "Scope": {
            "Classes": {
                "Include": [
                    "FINDINGS"
                ]
            },
            "Domains": {
                "Include": [
                    "ALL"
                ]
            }
        }
    }
}