{
    "id": "e3fce13f-9a74-445a-9f7c-e3182fff82b0",
    "changed": "2022-10-06T15:14:49.488Z",
    "content": "Check:\n  all:\n    - name: ACTARM\n      operator: non_empty\n    - name: ACTARM\n      operator: is_not_contained_by\n      value: $ta_arm\nOperations:\n  - operator: distinct\n    domain: TA\n    name: ARM\n    id: $ta_arm\nCore:\n  Id: CORE-000209\n  Version: '1'\n  Status: Published\nDescription: When study does not use multi-stage arm assignments and ACTARM is populated,\n  ACTARM must be present in TA.ARM. This rule has been executed to identify all cases\n  when ACTARM is not present in TA.ARM and therefore acknowledges that false positives\n  may be recorded when multi-stage arm assignments are in use.\nOutcome:\n  Message: ACTARM value in DM dataset is not among the values of ARM variable in the\n    TA dataset. This is allowed only in a multistage study with incomplete ARM assignment.\n    Please confirm if your study is a multistage assignment study.\n  Output Variables:\n    - ACTARM\nRule Type: Record Data\nSensitivity: Record\nAuthorities:\n  - Organization: CDISC\n    Standards:\n      - Name: SDTMIG\n        Version: '3.4'\n        References:\n          - Origin: SDTM and SDTMIG Conformance Rules\n            Rule Identifier:\n              Id: CG0514\n              Version: '1'\n            Version: '2.0'\n            Citations:\n              - Cited Guidance: With the exception of studies which use multi-stage\n                  Arm assignments, must be a value of ARM in the Trial Arms Dataset.\n                  If the subject was not assigned to an Arm or followed a course not\n                  described by any planned Arm, ACTARM is null and ARMNRS is populated.\n                Document: IG v3.4\n                Item: Specification\n                Section: '5.2'\nScope:\n  Classes:\n    Include:\n      - SPECIAL-PURPOSE\n  Domains:\n    Include:\n      - DM\n",
    "created": "2021-11-08T10:24:47Z",
    "creator": {
        "id": "ff471ff8-f131-4cf5-9712-c79cce6301a1"
    },
    "json": {
        "Check": {
            "all": [
                {
                    "name": "ACTARM",
                    "operator": "non_empty"
                },
                {
                    "name": "ACTARM",
                    "operator": "is_not_contained_by",
                    "value": "$ta_arm"
                }
            ]
        },
        "Operations": [
            {
                "operator": "distinct",
                "domain": "TA",
                "name": "ARM",
                "id": "$ta_arm"
            }
        ],
        "Core": {
            "Id": "CORE-000209",
            "Version": "1",
            "Status": "Published"
        },
        "Description": "When study does not use multi-stage arm assignments and ACTARM is populated, ACTARM must be present in TA.ARM. This rule has been executed to identify all cases when ACTARM is not present in TA.ARM and therefore acknowledges that false positives may be recorded when multi-stage arm assignments are in use.",
        "Outcome": {
            "Message": "ACTARM value in DM dataset is not among the values of ARM variable in the TA dataset. This is allowed only in a multistage study with incomplete ARM assignment. Please confirm if your study is a multistage assignment study.",
            "Output_Variables": [
                "ACTARM"
            ]
        },
        "Rule_Type": "Record Data",
        "Sensitivity": "Record",
        "Authorities": [
            {
                "Organization": "CDISC",
                "Standards": [
                    {
                        "Name": "SDTMIG",
                        "Version": "3.4",
                        "References": [
                            {
                                "Origin": "SDTM and SDTMIG Conformance Rules",
                                "Rule_Identifier": {
                                    "Id": "CG0514",
                                    "Version": "1"
                                },
                                "Version": "2.0",
                                "Citations": [
                                    {
                                        "Cited_Guidance": "With the exception of studies which use multi-stage Arm assignments, must be a value of ARM in the Trial Arms Dataset. If the subject was not assigned to an Arm or followed a course not described by any planned Arm, ACTARM is null and ARMNRS is populated.",
                                        "Document": "IG v3.4",
                                        "Item": "Specification",
                                        "Section": "5.2"
                                    }
                                ]
                            }
                        ]
                    }
                ]
            }
        ],
        "Scope": {
            "Classes": {
                "Include": [
                    "SPECIAL-PURPOSE"
                ]
            },
            "Domains": {
                "Include": [
                    "DM"
                ]
            }
        }
    }
}