{
    "id": "6890afb0-ab19-4ba3-8243-47b7c607db45",
    "changed": "2022-03-17T14:40:56Z",
    "content": "Check:\n  all:\n    - name: ARM\n      operator: empty\n    - name: ARMNRS\n      operator: empty\nCore:\n  Id: CORE-000046\n  Version: '1'\n  Status: Published\nDescription: Verify ARMNRS is not null when ARM is null\nOutcome:\n  Message: ARMNRS is missing when ARM value is missing\n  Output Variables:\n    - ARM\n    - ARMNRS\nRule Type: Record Data\nSensitivity: Record\nAuthorities:\n  - Organization: CDISC\n    Standards:\n      - Name: SDTMIG\n        Version: '3.4'\n        References:\n          - Origin: SDTM and SDTMIG Conformance Rules\n            Rule Identifier:\n              Id: CG0519\n              Version: '1'\n            Version: '2.0'\n            Citations:\n              - Cited Guidance: With the exception of studies which use multi-stage\n                  Arm assignments, must be a value of ARM in the Trial Arms Dataset.\n                  If the subject was not assigned to an Arm, ARM is null and ARMNRS\n                  is populated.\n                Document: IG v3.4\n                Item: Specification\n                Section: '5.2'\nScope:\n  Classes:\n    Include:\n      - SPECIAL-PURPOSE\n  Domains:\n    Include:\n      - DM\n",
    "created": "2021-10-04T01:29:06Z",
    "creator": {
        "id": "24709aaa-3e57-4ee4-a635-6006b165bb1b"
    },
    "json": {
        "Check": {
            "all": [
                {
                    "name": "ARM",
                    "operator": "empty"
                },
                {
                    "name": "ARMNRS",
                    "operator": "empty"
                }
            ]
        },
        "Core": {
            "Id": "CORE-000046",
            "Version": "1",
            "Status": "Published"
        },
        "Description": "Verify ARMNRS is not null when ARM is null",
        "Outcome": {
            "Message": "ARMNRS is missing when ARM value is missing",
            "Output_Variables": [
                "ARM",
                "ARMNRS"
            ]
        },
        "Rule_Type": "Record Data",
        "Sensitivity": "Record",
        "Authorities": [
            {
                "Organization": "CDISC",
                "Standards": [
                    {
                        "Name": "SDTMIG",
                        "Version": "3.4",
                        "References": [
                            {
                                "Origin": "SDTM and SDTMIG Conformance Rules",
                                "Rule_Identifier": {
                                    "Id": "CG0519",
                                    "Version": "1"
                                },
                                "Version": "2.0",
                                "Citations": [
                                    {
                                        "Cited_Guidance": "With the exception of studies which use multi-stage Arm assignments, must be a value of ARM in the Trial Arms Dataset. If the subject was not assigned to an Arm, ARM is null and ARMNRS is populated.",
                                        "Document": "IG v3.4",
                                        "Item": "Specification",
                                        "Section": "5.2"
                                    }
                                ]
                            }
                        ]
                    }
                ]
            }
        ],
        "Scope": {
            "Classes": {
                "Include": [
                    "SPECIAL-PURPOSE"
                ]
            },
            "Domains": {
                "Include": [
                    "DM"
                ]
            }
        }
    }
}