{
    "id": "b36d2ff4-0dcf-46a0-bcb3-97e4a43e79f5",
    "changed": "2022-03-10T13:42:27Z",
    "content": "Check:\n  all:\n    - name: --LOBXFL\n      operator: not_equal_to\n      value: Y\n    - name: --LOBXFL\n      operator: non_empty\nCore:\n  Id: CORE-000170\n  Version: '1'\n  Status: Published\nDescription: Raise an error when --LOBXFL is not 'Y' or null\nOutcome:\n  Message: Value of --LOBXFL must be 'Y' or null\n  Output Variables:\n    - --CAT\n    - --TEST\n    - --TESTCD\n    - --LOBXFL\nRule Type: Record Data\nSensitivity: Record\nAuthorities:\n  - Organization: CDISC\n    Standards:\n      - Name: SDTMIG\n        Version: '3.4'\n        References:\n          - Origin: SDTM and SDTMIG Conformance Rules\n            Rule Identifier:\n              Id: CG0541\n              Version: '1.0'\n            Version: '2.0'\n            Citations:\n              - Cited Guidance: The value should be \"Y\" or null.\n                Document: IG v3.4\n                Item: Specification\n                Section: Various Findings Domains\nScope:\n  Classes:\n    Include:\n      - FINDINGS\n  Domains:\n    Include:\n      - ALL\n",
    "created": "2021-10-21T14:40:58Z",
    "creator": {
        "id": "58534b88-88e7-41a5-be67-a4d0742ed999"
    },
    "json": {
        "Check": {
            "all": [
                {
                    "name": "--LOBXFL",
                    "operator": "not_equal_to",
                    "value": "Y"
                },
                {
                    "name": "--LOBXFL",
                    "operator": "non_empty"
                }
            ]
        },
        "Core": {
            "Id": "CORE-000170",
            "Version": "1",
            "Status": "Published"
        },
        "Description": "Raise an error when --LOBXFL is not 'Y' or null",
        "Outcome": {
            "Message": "Value of --LOBXFL must be 'Y' or null",
            "Output_Variables": [
                "--CAT",
                "--TEST",
                "--TESTCD",
                "--LOBXFL"
            ]
        },
        "Rule_Type": "Record Data",
        "Sensitivity": "Record",
        "Authorities": [
            {
                "Organization": "CDISC",
                "Standards": [
                    {
                        "Name": "SDTMIG",
                        "Version": "3.4",
                        "References": [
                            {
                                "Origin": "SDTM and SDTMIG Conformance Rules",
                                "Rule_Identifier": {
                                    "Id": "CG0541",
                                    "Version": "1.0"
                                },
                                "Version": "2.0",
                                "Citations": [
                                    {
                                        "Cited_Guidance": "The value should be \"Y\" or null.",
                                        "Document": "IG v3.4",
                                        "Item": "Specification",
                                        "Section": "Various Findings Domains"
                                    }
                                ]
                            }
                        ]
                    }
                ]
            }
        ],
        "Scope": {
            "Classes": {
                "Include": [
                    "FINDINGS"
                ]
            },
            "Domains": {
                "Include": [
                    "ALL"
                ]
            }
        }
    }
}