{
    "id": "d7575d10-caf5-4189-953b-510cd8b3bbfb",
    "changed": "2022-10-11T12:15:37.478Z",
    "content": "Check:\n  all:\n    - name: DSSCAT\n      operator: equal_to\n      value: STUDY PARTICIPATION\n      value_is_literal: true\n    - name: DSSCAT\n      operator: is_not_unique_set\n      value: USUBJID\nCore:\n  Id: CORE-000214\n  Version: '1'\n  Status: Published\nDescription: Trigger error when more than 1 record per subject has DSSCAT = 'STUDY\n  PARTICIPATION'\nOutcome:\n  Message: There is more than 1 record per subject has DSSCAT = 'STUDY PARTICIPATION'\n  Output Variables:\n    - DSSCAT\n    - USUBJID\nRule Type: Record Data\nSensitivity: Record\nAuthorities:\n  - Organization: CDISC\n    Standards:\n      - Name: SDTMIG\n        Version: '3.4'\n        References:\n          - Origin: SDTM and SDTMIG Conformance Rules\n            Rule Identifier:\n              Id: CG0538\n              Version: '1'\n            Version: '2.0'\n            Citations:\n              - Cited Guidance: DSSCAT = \"STUDY PARTICIPATION\" is used to represent\n                  disposition of study participation\n                Document: IG v3.4\n                Item: Assumption 2.b.1\n                Section: 6.2.3\nScope:\n  Classes:\n    Include:\n      - EVENTS\n  Domains:\n    Include:\n      - DS\n",
    "created": "2021-11-08T10:26:37Z",
    "creator": {
        "id": "ff471ff8-f131-4cf5-9712-c79cce6301a1"
    },
    "json": {
        "Check": {
            "all": [
                {
                    "name": "DSSCAT",
                    "operator": "equal_to",
                    "value": "STUDY PARTICIPATION",
                    "value_is_literal": true
                },
                {
                    "name": "DSSCAT",
                    "operator": "is_not_unique_set",
                    "value": "USUBJID"
                }
            ]
        },
        "Core": {
            "Id": "CORE-000214",
            "Version": "1",
            "Status": "Published"
        },
        "Description": "Trigger error when more than 1 record per subject has DSSCAT = 'STUDY PARTICIPATION'",
        "Outcome": {
            "Message": "There is more than 1 record per subject has DSSCAT = 'STUDY PARTICIPATION'",
            "Output_Variables": [
                "DSSCAT",
                "USUBJID"
            ]
        },
        "Rule_Type": "Record Data",
        "Sensitivity": "Record",
        "Authorities": [
            {
                "Organization": "CDISC",
                "Standards": [
                    {
                        "Name": "SDTMIG",
                        "Version": "3.4",
                        "References": [
                            {
                                "Origin": "SDTM and SDTMIG Conformance Rules",
                                "Rule_Identifier": {
                                    "Id": "CG0538",
                                    "Version": "1"
                                },
                                "Version": "2.0",
                                "Citations": [
                                    {
                                        "Cited_Guidance": "DSSCAT = \"STUDY PARTICIPATION\" is used to represent disposition of study participation",
                                        "Document": "IG v3.4",
                                        "Item": "Assumption 2.b.1",
                                        "Section": "6.2.3"
                                    }
                                ]
                            }
                        ]
                    }
                ]
            }
        ],
        "Scope": {
            "Classes": {
                "Include": [
                    "EVENTS"
                ]
            },
            "Domains": {
                "Include": [
                    "DS"
                ]
            }
        }
    }
}