{
    "id": "54ce26c6-1c7e-4bbf-ba68-c4aea2326b56",
    "changed": "2022-07-27T19:43:01Z",
    "content": "Check:\n  all:\n    - name: FETUSID\n      operator: exists\nCore:\n  Id: CORE-000057\n  Version: '1'\n  Status: Published\nDescription: FETUSID must not be present in SDTM domains.\nOutcome:\n  Message: FETUSID is present.\nRule Type: Record Data\nSensitivity: Dataset\nAuthorities:\n  - Organization: CDISC\n    Standards:\n      - Name: SDTMIG\n        Version: '3.4'\n        References:\n          - Origin: SDTM and SDTMIG Conformance Rules\n            Rule Identifier:\n              Id: CG0509\n              Version: '1'\n            Version: '2.0'\n            Citations:\n              Cited Guidance: FETUSID is not be used in human clinical trials.\n              Document: SDTM v2.0\n              Section: Identifiers\n      - Name: SDTMIG\n        Version: '3.4'\n        References:\n          - Origin: SDTM and SDTMIG Conformance Rules\n            Rule Identifier:\n              Id: CG0630\n              Version: '1'\n            Version: '2.0'\n            Citations:\n              Cited Guidance: The following SDTM variables, defined for use in non-clinical\n                studies (SEND), must NEVER be used in the submission of SDTM-based\n                data for human clinical trials --USCHFL (Interventions, Events, Findings)\n                --DTHREL (Findings) --EXCLFL (Findings) --REASEX (Findings) --IMPLBL\n                (Findings) FETUSID (Identifiers) --DETECT (Timing Variables) --NOMDY\n                (Timing Variables) --NOMLBL (Timing Variables)\n              Document: IG v3.4\n              Item: SDTM Variables Not Allowed in SDTMIG\n              Section: '2.7'\nScope:\n  Classes:\n    Include:\n      - ALL\n  Domains:\n    Include:\n      - ALL\n",
    "created": "2021-10-04T04:51:29Z",
    "creator": {
        "id": "ff471ff8-f131-4cf5-9712-c79cce6301a1"
    },
    "json": {
        "Check": {
            "all": [
                {
                    "name": "FETUSID",
                    "operator": "exists"
                }
            ]
        },
        "Core": {
            "Id": "CORE-000057",
            "Version": "1",
            "Status": "Published"
        },
        "Description": "FETUSID must not be present in SDTM domains.",
        "Outcome": {
            "Message": "FETUSID is present."
        },
        "Rule_Type": "Record Data",
        "Sensitivity": "Dataset",
        "Authorities": [
            {
                "Organization": "CDISC",
                "Standards": [
                    {
                        "Name": "SDTMIG",
                        "Version": "3.4",
                        "References": [
                            {
                                "Origin": "SDTM and SDTMIG Conformance Rules",
                                "Rule_Identifier": {
                                    "Id": "CG0509",
                                    "Version": "1"
                                },
                                "Version": "2.0",
                                "Citations": {
                                    "Cited_Guidance": "FETUSID is not be used in human clinical trials.",
                                    "Document": "SDTM v2.0",
                                    "Section": "Identifiers"
                                }
                            }
                        ]
                    },
                    {
                        "Name": "SDTMIG",
                        "Version": "3.4",
                        "References": [
                            {
                                "Origin": "SDTM and SDTMIG Conformance Rules",
                                "Rule_Identifier": {
                                    "Id": "CG0630",
                                    "Version": "1"
                                },
                                "Version": "2.0",
                                "Citations": {
                                    "Cited_Guidance": "The following SDTM variables, defined for use in non-clinical studies (SEND), must NEVER be used in the submission of SDTM-based data for human clinical trials --USCHFL (Interventions, Events, Findings) --DTHREL (Findings) --EXCLFL (Findings) --REASEX (Findings) --IMPLBL (Findings) FETUSID (Identifiers) --DETECT (Timing Variables) --NOMDY (Timing Variables) --NOMLBL (Timing Variables)",
                                    "Document": "IG v3.4",
                                    "Item": "SDTM Variables Not Allowed in SDTMIG",
                                    "Section": "2.7"
                                }
                            }
                        ]
                    }
                ]
            }
        ],
        "Scope": {
            "Classes": {
                "Include": [
                    "ALL"
                ]
            },
            "Domains": {
                "Include": [
                    "ALL"
                ]
            }
        }
    }
}