{
    "id": "61a78fe5-14e8-45ec-aa57-c4541e0c6de3",
    "changed": "2022-06-22T23:48:01Z",
    "content": "Check:\n  all:\n    - name: --REPNUM\n      operator: exists\n    - name: --REPNUM\n      operator: is_not_unique_set\n      value:\n        - USUBJID\n        - --TESTCD\n        - VISITNUM\n        - --VISIT\n        - VISITDY\n        - TAETORD\n        - EPOCH\n        - --DTC\n        - --STDTC\n        - --ENDTC\n        - --DY\n        - --STDY\n        - --ENDY\n        - --XDY\n        - --XSTDY\n        - --XENDY\n        - --CHDY\n        - --CHSTDY\n        - --CHENDY\n        - --DUR\n        - --TPT\n        - --TPTNUM\n        - --ELTM\n        - --TPTREF\n        - --RFTDTC\n        - --STRF\n        - --ENRF\n        - --EVLINT\n        - --EVINTX\n        - --STRTPT\n        - --STTPT\n        - --ENRTPT\n        - --ENTPT\n        - MIDS\n        - RELMIDS\n        - MIDSDTC\n        - --STINT\n        - --ENINT\n        - --PTFL\n        - --PDUR\nCore:\n  Id: CDISC.SDTMIG.CG0562\n  Version: '1'\n  Status: Draft\nDescription: Raise an error when REPNUM is in the dataset and there are multiple records\n  for a subject for a test within the timeframe identified by the timing variables\n  on the record, and --REPNUM is null or not unique per subject per test per timing\n  variables.\nOutcome:\n  Message: --REPNUM is null or is not unique per subject per test per timing variables.\nRule Type: Record Data\nSensitivity: Record\nAuthorities:\n  - Organization: CDISC\n    Standards:\n      - Name: SDTMIG\n        Version: '3.4'\n        References:\n          - Origin: SDTM and SDTMIG Conformance Rules\n            Rule Identifier:\n              Id: CG0562\n              Version: '1'\n            Version: '2.0'\n            Citations:\n              - Cited Guidance: The instance number of a test that is repeated within\n                  a given timeframe for the same test. The level of granularity can\n                  vary (e.g., within a time point or within a visit).\n                Document: SDTM v2.0\n                Item: --REPNUM\n                Section: Findings\nScope:\n  Classes:\n    Include:\n      - FINDINGS\n  Domains:\n    Include:\n      - ALL\n",
    "created": "2021-10-08T12:17:50Z",
    "creator": {
        "id": "ff471ff8-f131-4cf5-9712-c79cce6301a1"
    },
    "json": {
        "Check": {
            "all": [
                {
                    "name": "--REPNUM",
                    "operator": "exists"
                },
                {
                    "name": "--REPNUM",
                    "operator": "is_not_unique_set",
                    "value": [
                        "USUBJID",
                        "--TESTCD",
                        "VISITNUM",
                        "--VISIT",
                        "VISITDY",
                        "TAETORD",
                        "EPOCH",
                        "--DTC",
                        "--STDTC",
                        "--ENDTC",
                        "--DY",
                        "--STDY",
                        "--ENDY",
                        "--XDY",
                        "--XSTDY",
                        "--XENDY",
                        "--CHDY",
                        "--CHSTDY",
                        "--CHENDY",
                        "--DUR",
                        "--TPT",
                        "--TPTNUM",
                        "--ELTM",
                        "--TPTREF",
                        "--RFTDTC",
                        "--STRF",
                        "--ENRF",
                        "--EVLINT",
                        "--EVINTX",
                        "--STRTPT",
                        "--STTPT",
                        "--ENRTPT",
                        "--ENTPT",
                        "MIDS",
                        "RELMIDS",
                        "MIDSDTC",
                        "--STINT",
                        "--ENINT",
                        "--PTFL",
                        "--PDUR"
                    ]
                }
            ]
        },
        "Core": {
            "Id": "CDISC.SDTMIG.CG0562",
            "Version": "1",
            "Status": "Draft"
        },
        "Description": "Raise an error when REPNUM is in the dataset and there are multiple records for a subject for a test within the timeframe identified by the timing variables on the record, and --REPNUM is null or not unique per subject per test per timing variables.",
        "Outcome": {
            "Message": "--REPNUM is null or is not unique per subject per test per timing variables."
        },
        "Rule_Type": "Record Data",
        "Sensitivity": "Record",
        "Authorities": [
            {
                "Organization": "CDISC",
                "Standards": [
                    {
                        "Name": "SDTMIG",
                        "Version": "3.4",
                        "References": [
                            {
                                "Origin": "SDTM and SDTMIG Conformance Rules",
                                "Rule_Identifier": {
                                    "Id": "CG0562",
                                    "Version": "1"
                                },
                                "Version": "2.0",
                                "Citations": [
                                    {
                                        "Cited_Guidance": "The instance number of a test that is repeated within a given timeframe for the same test. The level of granularity can vary (e.g., within a time point or within a visit).",
                                        "Document": "SDTM v2.0",
                                        "Item": "--REPNUM",
                                        "Section": "Findings"
                                    }
                                ]
                            }
                        ]
                    }
                ]
            }
        ],
        "Scope": {
            "Classes": {
                "Include": [
                    "FINDINGS"
                ]
            },
            "Domains": {
                "Include": [
                    "ALL"
                ]
            }
        }
    }
}