{
    "id": "7f5503b3-098a-4bbb-a579-075a5671b403",
    "changed": "2022-04-13T23:53:32Z",
    "content": "Check:\n  all:\n    - name: SMSTDTC\n      operator: empty\nCore:\n  Id: CORE-000109\n  Version: '1'\n  Status: Published\nDescription: Raise an error when SMSTDTC is null.\nOutcome:\n  Message: SMSTDTC is null.\nRule Type: Record Data\nSensitivity: Record\nAuthorities:\n  - Organization: CDISC\n    Standards:\n      - Name: SDTMIG\n        Version: '3.4'\n        References:\n          - Origin: SDTM and SDTMIG Conformance Rules\n            Rule Identifier:\n              Id: CG0547\n              Version: '1'\n            Version: '2.0'\n            Citations:\n              - Cited Guidance: The start date/time of the Disease Milestone is the\n                  critical date/time, and must be populated. If the Disease Milestone\n                  is an event, then the meaning of \u201cstart date\u201d for the event may\n                  need to be defined.\n                Document: SDTMIG v3.4\n                Section: '5.4'\nScope:\n  Classes:\n    Include:\n      - SPECIAL-PURPOSE\n  Domains:\n    Include:\n      - SM\n",
    "created": "2021-10-08T11:49:26Z",
    "creator": {
        "id": "ff471ff8-f131-4cf5-9712-c79cce6301a1"
    },
    "json": {
        "Check": {
            "all": [
                {
                    "name": "SMSTDTC",
                    "operator": "empty"
                }
            ]
        },
        "Core": {
            "Id": "CORE-000109",
            "Version": "1",
            "Status": "Published"
        },
        "Description": "Raise an error when SMSTDTC is null.",
        "Outcome": {
            "Message": "SMSTDTC is null."
        },
        "Rule_Type": "Record Data",
        "Sensitivity": "Record",
        "Authorities": [
            {
                "Organization": "CDISC",
                "Standards": [
                    {
                        "Name": "SDTMIG",
                        "Version": "3.4",
                        "References": [
                            {
                                "Origin": "SDTM and SDTMIG Conformance Rules",
                                "Rule_Identifier": {
                                    "Id": "CG0547",
                                    "Version": "1"
                                },
                                "Version": "2.0",
                                "Citations": [
                                    {
                                        "Cited_Guidance": "The start date/time of the Disease Milestone is the critical date/time, and must be populated. If the Disease Milestone is an event, then the meaning of \u201cstart date\u201d for the event may need to be defined.",
                                        "Document": "SDTMIG v3.4",
                                        "Section": "5.4"
                                    }
                                ]
                            }
                        ]
                    }
                ]
            }
        ],
        "Scope": {
            "Classes": {
                "Include": [
                    "SPECIAL-PURPOSE"
                ]
            },
            "Domains": {
                "Include": [
                    "SM"
                ]
            }
        }
    }
}