{
    "id": "c3dc6682-414f-456f-8b68-3bb18a920da4",
    "changed": "2022-07-17T11:08:37Z",
    "content": "Check:\n  all:\n    - name: AGE\n      operator: non_empty\n    - name: AGEU\n      operator: empty\nCore:\n  Id: CORE-000189\n  Version: '1'\n  Status: Published\nDescription: Raise an error when AGE is not blank and AGEU is blank.\nOutcome:\n  Message: AGEU is missing when AGE is provided.\n  Output Variables:\n    - AGE\n    - AGEU\nRule Type: Record Data\nSensitivity: Record\nAuthorities:\n  - Organization: CDISC\n    Standards:\n      - Name: SDTMIG\n        Version: '3.4'\n        References:\n          - Origin: SDTM and SDTMIG Conformance Rules\n            Rule Identifier:\n              Id: CG0665\n              Version: '2'\n            Version: '2.0'\n            Citations:\n              - Cited Guidance: '[AGEU]Variable Qualifier of AGE or AGETXT.|[AGETXT]Not\n                  in human clinical trials.'\n                Document: Model v2.0\n                Item: AGEU|AGETXT\n                Section: Demographics\nScope:\n  Classes:\n    Include:\n      - SPECIAL-PURPOSE\n  Domains:\n    Include:\n      - DM\n",
    "created": "2021-11-03T10:48:47Z",
    "creator": {
        "id": "fac95de6-5815-411a-a579-ddbc7ee4b97a"
    },
    "json": {
        "Check": {
            "all": [
                {
                    "name": "AGE",
                    "operator": "non_empty"
                },
                {
                    "name": "AGEU",
                    "operator": "empty"
                }
            ]
        },
        "Core": {
            "Id": "CORE-000189",
            "Version": "1",
            "Status": "Published"
        },
        "Description": "Raise an error when AGE is not blank and AGEU is blank.",
        "Outcome": {
            "Message": "AGEU is missing when AGE is provided.",
            "Output_Variables": [
                "AGE",
                "AGEU"
            ]
        },
        "Rule_Type": "Record Data",
        "Sensitivity": "Record",
        "Authorities": [
            {
                "Organization": "CDISC",
                "Standards": [
                    {
                        "Name": "SDTMIG",
                        "Version": "3.4",
                        "References": [
                            {
                                "Origin": "SDTM and SDTMIG Conformance Rules",
                                "Rule_Identifier": {
                                    "Id": "CG0665",
                                    "Version": "2"
                                },
                                "Version": "2.0",
                                "Citations": [
                                    {
                                        "Cited_Guidance": "[AGEU]Variable Qualifier of AGE or AGETXT.|[AGETXT]Not in human clinical trials.",
                                        "Document": "Model v2.0",
                                        "Item": "AGEU|AGETXT",
                                        "Section": "Demographics"
                                    }
                                ]
                            }
                        ]
                    }
                ]
            }
        ],
        "Scope": {
            "Classes": {
                "Include": [
                    "SPECIAL-PURPOSE"
                ]
            },
            "Domains": {
                "Include": [
                    "DM"
                ]
            }
        }
    }
}