{
    "id": "990a26a7-1762-4fcb-b7e3-18c91625f599",
    "changed": "2022-04-04T14:17:06Z",
    "content": "Check:\n  all:\n    - name: SBSTRAIN\n      operator: exists\nCore:\n  Id: CORE-000071\n  Version: '1'\n  Status: Published\nDescription: Raise an error when SBSTRAIN is present.\nOutcome:\n  Message: SBSTRAIN is present.\nRule Type: Record Data\nSensitivity: Dataset\nAuthorities:\n  - Organization: CDISC\n    Standards:\n      - Name: SDTMIG\n        Version: '3.4'\n        References:\n          - Origin: SDTM and SDTMIG Conformance Rules\n            Rule Identifier:\n              Id: CG0644\n              Version: '1'\n            Version: '2.0'\n            Citations:\n              - Cited Guidance: SBSTRAIN is not be used in human clinical trials.\n                Document: SDTM v2.0\n                Section: Demographics\nScope:\n  Classes:\n    Include:\n      - SPECIAL-PURPOSE\n  Domains:\n    Include:\n      - DM\n",
    "created": "2021-10-04T05:03:34Z",
    "creator": {
        "id": "ff471ff8-f131-4cf5-9712-c79cce6301a1"
    },
    "json": {
        "Check": {
            "all": [
                {
                    "name": "SBSTRAIN",
                    "operator": "exists"
                }
            ]
        },
        "Core": {
            "Id": "CORE-000071",
            "Version": "1",
            "Status": "Published"
        },
        "Description": "Raise an error when SBSTRAIN is present.",
        "Outcome": {
            "Message": "SBSTRAIN is present."
        },
        "Rule_Type": "Record Data",
        "Sensitivity": "Dataset",
        "Authorities": [
            {
                "Organization": "CDISC",
                "Standards": [
                    {
                        "Name": "SDTMIG",
                        "Version": "3.4",
                        "References": [
                            {
                                "Origin": "SDTM and SDTMIG Conformance Rules",
                                "Rule_Identifier": {
                                    "Id": "CG0644",
                                    "Version": "1"
                                },
                                "Version": "2.0",
                                "Citations": [
                                    {
                                        "Cited_Guidance": "SBSTRAIN is not be used in human clinical trials.",
                                        "Document": "SDTM v2.0",
                                        "Section": "Demographics"
                                    }
                                ]
                            }
                        ]
                    }
                ]
            }
        ],
        "Scope": {
            "Classes": {
                "Include": [
                    "SPECIAL-PURPOSE"
                ]
            },
            "Domains": {
                "Include": [
                    "DM"
                ]
            }
        }
    }
}