{
    "id": "d365c60e-0c08-47a4-90e7-b6d3aec4b6d4",
    "changed": "2022-04-04T14:16:00Z",
    "content": "Check:\n  all:\n    - name: --DETECT\n      operator: exists\nCore:\n  Id: CORE-000067\n  Version: '1'\n  Status: Published\nDescription: Raise an error when --DETECT is present.\nOutcome:\n  Message: --DETECT is present.\nRule Type: Record Data\nSensitivity: Dataset\nAuthorities:\n  - Organization: CDISC\n    Standards:\n      - Name: SDTMIG\n        Version: '3.4'\n        References:\n          - Origin: SDTM and SDTMIG Conformance Rules\n            Rule Identifier:\n              Id: CG0640\n              Version: '1'\n            Version: '2.0'\n            Citations:\n              - Cited Guidance: --DETECT is not be used in human clinical trials.\n                Document: SDTM v2.0\n                Section: Timing\nScope:\n  Classes:\n    Include:\n      - ALL\n  Domains:\n    Include:\n      - ALL\n",
    "created": "2021-10-04T05:00:58Z",
    "creator": {
        "id": "ff471ff8-f131-4cf5-9712-c79cce6301a1"
    },
    "json": {
        "Check": {
            "all": [
                {
                    "name": "--DETECT",
                    "operator": "exists"
                }
            ]
        },
        "Core": {
            "Id": "CORE-000067",
            "Version": "1",
            "Status": "Published"
        },
        "Description": "Raise an error when --DETECT is present.",
        "Outcome": {
            "Message": "--DETECT is present."
        },
        "Rule_Type": "Record Data",
        "Sensitivity": "Dataset",
        "Authorities": [
            {
                "Organization": "CDISC",
                "Standards": [
                    {
                        "Name": "SDTMIG",
                        "Version": "3.4",
                        "References": [
                            {
                                "Origin": "SDTM and SDTMIG Conformance Rules",
                                "Rule_Identifier": {
                                    "Id": "CG0640",
                                    "Version": "1"
                                },
                                "Version": "2.0",
                                "Citations": [
                                    {
                                        "Cited_Guidance": "--DETECT is not be used in human clinical trials.",
                                        "Document": "SDTM v2.0",
                                        "Section": "Timing"
                                    }
                                ]
                            }
                        ]
                    }
                ]
            }
        ],
        "Scope": {
            "Classes": {
                "Include": [
                    "ALL"
                ]
            },
            "Domains": {
                "Include": [
                    "ALL"
                ]
            }
        }
    }
}