{
    "id": "aeb1bf5f-d6a6-4255-9cc0-b61afbe35c2b",
    "changed": "2022-04-14T00:55:02Z",
    "content": "Check:\n  any:\n    - name: SJ\n      operator: exists\nCore:\n  Id: CORE-000044\n  Version: '1'\n  Status: Published\nDescription: Raise an error when SJ dataset is present.\nOutcome:\n  Message: SJ dataset is present.\nRule Type: Domain Presence Check\nSensitivity: Study\nAuthorities:\n  - Organization: CDISC\n    Standards:\n      - Name: SDTMIG\n        Version: '3.4'\n        References:\n          - Origin: SDTM and SDTMIG Conformance Rules\n            Rule Identifier:\n              Id: CG0646\n              Version: '1'\n            Version: '2.0'\n            Citations:\n              - Cited Guidance: The SJ dataset must not be used in human clinical\n                  trials.\n                Document: SDTM v2.0\n                Section: Subject Repro Stages\nScope:\n  Classes:\n    Include:\n      - ALL\n  Domains:\n    Include:\n      - SJ\n",
    "created": "2021-10-03T10:41:21Z",
    "creator": {
        "id": "ff471ff8-f131-4cf5-9712-c79cce6301a1"
    },
    "json": {
        "Check": {
            "any": [
                {
                    "name": "SJ",
                    "operator": "exists"
                }
            ]
        },
        "Core": {
            "Id": "CORE-000044",
            "Version": "1",
            "Status": "Published"
        },
        "Description": "Raise an error when SJ dataset is present.",
        "Outcome": {
            "Message": "SJ dataset is present."
        },
        "Rule_Type": "Domain Presence Check",
        "Sensitivity": "Study",
        "Authorities": [
            {
                "Organization": "CDISC",
                "Standards": [
                    {
                        "Name": "SDTMIG",
                        "Version": "3.4",
                        "References": [
                            {
                                "Origin": "SDTM and SDTMIG Conformance Rules",
                                "Rule_Identifier": {
                                    "Id": "CG0646",
                                    "Version": "1"
                                },
                                "Version": "2.0",
                                "Citations": [
                                    {
                                        "Cited_Guidance": "The SJ dataset must not be used in human clinical trials.",
                                        "Document": "SDTM v2.0",
                                        "Section": "Subject Repro Stages"
                                    }
                                ]
                            }
                        ]
                    }
                ]
            }
        ],
        "Scope": {
            "Classes": {
                "Include": [
                    "ALL"
                ]
            },
            "Domains": {
                "Include": [
                    "SJ"
                ]
            }
        }
    }
}