{
    "id": "a74ce2d2-afba-4be0-a621-fbc9b7ecd4b1",
    "changed": "2022-07-29T08:36:49Z",
    "content": "Check:\n  any:\n    - name: dataset_name\n      operator: longer_than\n      value: 6\n    - name: dataset_name\n      operator: shorter_than\n      value: 4\nCore:\n  Id: CDISC.SDTMIG.CG0650\n  Version: '1'\n  Status: Draft\nDescription: When an Associated Persons non-supplemental qualifier dataset is associated\n  with a split dataset, the dataset name length must be greater than 4 and less than,\n  or equal to, 6.\nOutcome:\n  Message: Associated Persons non-supplemental qualifier dataset associated with a\n    split dataset does not have a dataset name with a length greater than 4 and less\n    than, or equal to, 6.\nRule Type: Dataset Metadata Check\nSensitivity: Dataset\nAuthorities:\n  - Organization: CDISC\n    Standards:\n      - Name: SDTMIG\n        Version: '3.4'\n        References:\n          - Origin: SDTM and SDTMIG Conformance Rules\n            Rule Identifier:\n              Id: CG0650\n              Version: '1'\n            Version: '2.0'\n            Citations:\n              - Cited Guidance: Supplemental Qualifier datasets for split domains\n                  would also be split. The nomenclature would include the additional\n                  one-to-two characters used to identify the split dataset.\n                Document: IG v3.4\n                Item: '7'\n                Section: 4.1.7\nScope:\n  Classes:\n    Include:\n      - ALL\n  Domains:\n    include_split_datasets: true\n    Include:\n      - AP--\n",
    "created": "2022-06-29T15:36:18Z",
    "creator": {
        "id": "ff471ff8-f131-4cf5-9712-c79cce6301a1"
    },
    "json": {
        "Check": {
            "any": [
                {
                    "name": "dataset_name",
                    "operator": "longer_than",
                    "value": 6
                },
                {
                    "name": "dataset_name",
                    "operator": "shorter_than",
                    "value": 4
                }
            ]
        },
        "Core": {
            "Id": "CDISC.SDTMIG.CG0650",
            "Version": "1",
            "Status": "Draft"
        },
        "Description": "When an Associated Persons non-supplemental qualifier dataset is associated with a split dataset, the dataset name length must be greater than 4 and less than, or equal to, 6.",
        "Outcome": {
            "Message": "Associated Persons non-supplemental qualifier dataset associated with a split dataset does not have a dataset name with a length greater than 4 and less than, or equal to, 6."
        },
        "Rule_Type": "Dataset Metadata Check",
        "Sensitivity": "Dataset",
        "Authorities": [
            {
                "Organization": "CDISC",
                "Standards": [
                    {
                        "Name": "SDTMIG",
                        "Version": "3.4",
                        "References": [
                            {
                                "Origin": "SDTM and SDTMIG Conformance Rules",
                                "Rule_Identifier": {
                                    "Id": "CG0650",
                                    "Version": "1"
                                },
                                "Version": "2.0",
                                "Citations": [
                                    {
                                        "Cited_Guidance": "Supplemental Qualifier datasets for split domains would also be split. The nomenclature would include the additional one-to-two characters used to identify the split dataset.",
                                        "Document": "IG v3.4",
                                        "Item": "7",
                                        "Section": "4.1.7"
                                    }
                                ]
                            }
                        ]
                    }
                ]
            }
        ],
        "Scope": {
            "Classes": {
                "Include": [
                    "ALL"
                ]
            },
            "Domains": {
                "include_split_datasets": true,
                "Include": [
                    "AP--"
                ]
            }
        }
    }
}