{
    "id": "7c738e68-dd2b-47c5-88aa-06b50ba2fb76",
    "changed": "2022-05-18T20:28:59Z",
    "content": "Check:\n  all:\n    - name: SVPRESP\n      operator: equal_to\n      value: Y\n    - name: VISIT\n      operator: is_not_contained_by\n      value: $tv_visit\nCore:\n  Id: CORE-000036\n  Version: '1'\n  Status: Published\nDescription: Raise an error when SVPRESP is \"Y\" and VISIT is not present in TV.VISIT.\nOperations:\n  - domain: TV\n    id: $tv_visit\n    name: VISIT\n    operator: distinct\nOutcome:\n  Message: Planned visit is not found in TV.\nRule Type: Record Data\nSensitivity: Record\nAuthorities:\n  - Organization: CDISC\n    Standards:\n      - Name: SDTMIG\n        Version: '3.4'\n        References:\n          - Origin: SDTM and SDTMIG Conformance Rules\n            Rule Identifier:\n              Id: CG0657\n              Version: '1'\n            Version: '2.0'\n            Citations:\n              - Cited Guidance: Value is \"Y\" for planned visits, null for unplanned\n                  visits.\n                Document: SDTMIG v3.4\n                Item: SVPRESP\n                Section: '5.5'\n              - Cited Guidance: The values of VISITNUM in the TV dataset are the valid\n                  values of VISITNUM for planned Visits.  Any values of VISITNUM that\n                  appear in subject-level datasets that are not in the TV dataset\n                  are assumed to correspond to unplanned Visits....  If a subject-level\n                  dataset includes both VISITNUM and VISIT, then records that include\n                  values of VISITNUM that appear in the TV dataset should also include\n                  the corresponding values of VISIT from the TV dataset.\n                Document: SDTMIG v3.4\n                Item: Assumption 6\n                Section: 7.3.1\nScope:\n  Classes:\n    Include:\n      - SPECIAL-PURPOSE\n  Domains:\n    Include:\n      - SV\n",
    "created": "2021-10-03T09:08:58Z",
    "creator": {
        "id": "ff471ff8-f131-4cf5-9712-c79cce6301a1"
    },
    "json": {
        "Check": {
            "all": [
                {
                    "name": "SVPRESP",
                    "operator": "equal_to",
                    "value": "Y"
                },
                {
                    "name": "VISIT",
                    "operator": "is_not_contained_by",
                    "value": "$tv_visit"
                }
            ]
        },
        "Core": {
            "Id": "CORE-000036",
            "Version": "1",
            "Status": "Published"
        },
        "Description": "Raise an error when SVPRESP is \"Y\" and VISIT is not present in TV.VISIT.",
        "Operations": [
            {
                "domain": "TV",
                "id": "$tv_visit",
                "name": "VISIT",
                "operator": "distinct"
            }
        ],
        "Outcome": {
            "Message": "Planned visit is not found in TV."
        },
        "Rule_Type": "Record Data",
        "Sensitivity": "Record",
        "Authorities": [
            {
                "Organization": "CDISC",
                "Standards": [
                    {
                        "Name": "SDTMIG",
                        "Version": "3.4",
                        "References": [
                            {
                                "Origin": "SDTM and SDTMIG Conformance Rules",
                                "Rule_Identifier": {
                                    "Id": "CG0657",
                                    "Version": "1"
                                },
                                "Version": "2.0",
                                "Citations": [
                                    {
                                        "Cited_Guidance": "Value is \"Y\" for planned visits, null for unplanned visits.",
                                        "Document": "SDTMIG v3.4",
                                        "Item": "SVPRESP",
                                        "Section": "5.5"
                                    },
                                    {
                                        "Cited_Guidance": "The values of VISITNUM in the TV dataset are the valid values of VISITNUM for planned Visits.  Any values of VISITNUM that appear in subject-level datasets that are not in the TV dataset are assumed to correspond to unplanned Visits....  If a subject-level dataset includes both VISITNUM and VISIT, then records that include values of VISITNUM that appear in the TV dataset should also include the corresponding values of VISIT from the TV dataset.",
                                        "Document": "SDTMIG v3.4",
                                        "Item": "Assumption 6",
                                        "Section": "7.3.1"
                                    }
                                ]
                            }
                        ]
                    }
                ]
            }
        ],
        "Scope": {
            "Classes": {
                "Include": [
                    "SPECIAL-PURPOSE"
                ]
            },
            "Domains": {
                "Include": [
                    "SV"
                ]
            }
        }
    }
}