{
    "id": "9f44af9b-17d1-42b9-ba95-802336002f04",
    "changed": "2022-03-17T19:42:11Z",
    "content": "Check:\n  all:\n    - name: --RSTMOD\n      operator: exists\nCore:\n  Id: CORE-000051\n  Version: '1'\n  Status: Published\nDescription: Raise an error when --RSTMOD is present.\nOutcome:\n  Message: --RSTMOD is present.\nRule Type: Record Data\nSensitivity: Dataset\nAuthorities:\n  - Organization: CDISC\n    Standards:\n      - Name: SDTMIG\n        Version: '3.4'\n        References:\n          - Origin: SDTM and SDTMIG Conformance Rules\n            Rule Identifier:\n              Id: CG0624\n              Version: '1'\n            Version: '2.0'\n            Citations:\n              - Cited Guidance: Not in human clinical trials.\n                Document: Model v2.0\n                Section: Interventions|Findings\n                Item: --RSTMOD\nScope:\n  Classes:\n    Include:\n      - INTERVENTIONS\n      - FINDINGS\n  Domains:\n    Include:\n      - ALL\n",
    "created": "2021-10-04T04:46:55Z",
    "creator": {
        "id": "ff471ff8-f131-4cf5-9712-c79cce6301a1"
    },
    "json": {
        "Check": {
            "all": [
                {
                    "name": "--RSTMOD",
                    "operator": "exists"
                }
            ]
        },
        "Core": {
            "Id": "CORE-000051",
            "Version": "1",
            "Status": "Published"
        },
        "Description": "Raise an error when --RSTMOD is present.",
        "Outcome": {
            "Message": "--RSTMOD is present."
        },
        "Rule_Type": "Record Data",
        "Sensitivity": "Dataset",
        "Authorities": [
            {
                "Organization": "CDISC",
                "Standards": [
                    {
                        "Name": "SDTMIG",
                        "Version": "3.4",
                        "References": [
                            {
                                "Origin": "SDTM and SDTMIG Conformance Rules",
                                "Rule_Identifier": {
                                    "Id": "CG0624",
                                    "Version": "1"
                                },
                                "Version": "2.0",
                                "Citations": [
                                    {
                                        "Cited_Guidance": "Not in human clinical trials.",
                                        "Document": "Model v2.0",
                                        "Section": "Interventions|Findings",
                                        "Item": "--RSTMOD"
                                    }
                                ]
                            }
                        ]
                    }
                ]
            }
        ],
        "Scope": {
            "Classes": {
                "Include": [
                    "INTERVENTIONS",
                    "FINDINGS"
                ]
            },
            "Domains": {
                "Include": [
                    "ALL"
                ]
            }
        }
    }
}