{
    "id": "60a9ce11-2d6a-4708-ae19-7bc8bf288126",
    "changed": "2022-05-13T04:43:26Z",
    "content": "Check:\n  any:\n    # Fire query if domain name does not start with APFA and does not have the format \"AP\" followed by an alpha character, then an alphanum character\r\n    - all:\n        - name: DOMAIN\n          operator: not_prefix_matches_regex\n          prefix: 4\n          value: ^APFA$\n        - name: DOMAIN\n          operator: not_matches_regex\n          value: ^AP[A-Z][A-Z0-9]$\n    # Fire query if domain name starts with APFA and is not followed by an alpha character, then an alphanum character\r\n    - all:\n        - name: DOMAIN\n          operator: prefix_matches_regex\n          prefix: 4\n          value: ^APFA$\n        - name: DOMAIN\n          operator: not_suffix_matches_regex\n          suffix: 2\n          value: '[A-Z0-9][A-Z0-9]$'\n    # Fire query if characters 3/4 refers to invalid SDTM domain\r\n    - name: DOMAIN\n      operator: matches_regex\n      value: ^AP(AD|AX|AP|SQ|SA)$\n    # Fire query if characters 5/6 refers to invalid SDTM domain (for APFA domains)\r\n    - name: DOMAIN\n      operator: matches_regex\n      value: ^APFA(AD|AX|AP|SQ|SA)$\nCore:\n  Id: CDISC.SDTMIG.CG0663\n  Version: '1'\n  Status: Draft\nDescription: Raise an error when an AP Core Domain does not have a value length of\n  4 characters beginning with 'AP' and ending with 2 character SDTM domain\nOutcome:\n  Message: AP Core Domain does not have a value length of 4 characters beginning with\n    'AP' and ending with 2 character SDTM domain\nRule Type: Record Data\nSensitivity: Variable\nAuthorities:\n  - Organization: CDISC\n    Standards:\n      - Name: SDTMIG\n        Version: '3.4'\n        References:\n          - Origin: SDTM and SDTMIG Conformance Rules\n            Rule Identifier:\n              Id: CG0663\n              Version: '1'\n            Version: '2.0'\n            Citations:\n              - Cited Guidance: Associated Persons datasets are given a prefix of\n                  AP-- to identify the data as AP data to and distinguish them from\n                  study subject data. Associated Persons domain codes in the DOMAIN\n                  column of every record are also given a prefix of AP-- to identify\n                  the domains as AP domains and to distinguish them from study subject\n                  domains. AP domain codes are therefore four characters long.\n                Document: AP Guide v1.0\n                Section: Section 2\nScope:\n  Classes:\n    Include:\n      - ALL\n  Domains:\n    Include:\n      - AP--\n    Exclude:\n      - APRELSUB\n      - SUPP--\n      - POOLDEF\n",
    "created": "2022-05-11T10:32:58Z",
    "creator": {
        "id": "ff471ff8-f131-4cf5-9712-c79cce6301a1"
    },
    "json": {
        "Check": {
            "any": [
                {
                    "all": [
                        {
                            "name": "DOMAIN",
                            "operator": "not_prefix_matches_regex",
                            "prefix": 4,
                            "value": "^APFA$"
                        },
                        {
                            "name": "DOMAIN",
                            "operator": "not_matches_regex",
                            "value": "^AP[A-Z][A-Z0-9]$"
                        }
                    ]
                },
                {
                    "all": [
                        {
                            "name": "DOMAIN",
                            "operator": "prefix_matches_regex",
                            "prefix": 4,
                            "value": "^APFA$"
                        },
                        {
                            "name": "DOMAIN",
                            "operator": "not_suffix_matches_regex",
                            "suffix": 2,
                            "value": "[A-Z0-9][A-Z0-9]$"
                        }
                    ]
                },
                {
                    "name": "DOMAIN",
                    "operator": "matches_regex",
                    "value": "^AP(AD|AX|AP|SQ|SA)$"
                },
                {
                    "name": "DOMAIN",
                    "operator": "matches_regex",
                    "value": "^APFA(AD|AX|AP|SQ|SA)$"
                }
            ]
        },
        "Core": {
            "Id": "CDISC.SDTMIG.CG0663",
            "Version": "1",
            "Status": "Draft"
        },
        "Description": "Raise an error when an AP Core Domain does not have a value length of 4 characters beginning with 'AP' and ending with 2 character SDTM domain",
        "Outcome": {
            "Message": "AP Core Domain does not have a value length of 4 characters beginning with 'AP' and ending with 2 character SDTM domain"
        },
        "Rule_Type": "Record Data",
        "Sensitivity": "Variable",
        "Authorities": [
            {
                "Organization": "CDISC",
                "Standards": [
                    {
                        "Name": "SDTMIG",
                        "Version": "3.4",
                        "References": [
                            {
                                "Origin": "SDTM and SDTMIG Conformance Rules",
                                "Rule_Identifier": {
                                    "Id": "CG0663",
                                    "Version": "1"
                                },
                                "Version": "2.0",
                                "Citations": [
                                    {
                                        "Cited_Guidance": "Associated Persons datasets are given a prefix of AP-- to identify the data as AP data to and distinguish them from study subject data. Associated Persons domain codes in the DOMAIN column of every record are also given a prefix of AP-- to identify the domains as AP domains and to distinguish them from study subject domains. AP domain codes are therefore four characters long.",
                                        "Document": "AP Guide v1.0",
                                        "Section": "Section 2"
                                    }
                                ]
                            }
                        ]
                    }
                ]
            }
        ],
        "Scope": {
            "Classes": {
                "Include": [
                    "ALL"
                ]
            },
            "Domains": {
                "Include": [
                    "AP--"
                ],
                "Exclude": [
                    "APRELSUB",
                    "SUPP--",
                    "POOLDEF"
                ]
            }
        }
    }
}