{
    "id": "3016e56e-e70f-4feb-aa62-b445e6db1cba",
    "changed": "2022-04-14T02:12:09Z",
    "content": "Check:\n  all:\n    - name: SVPRESP\n      operator: not_equal_to\n      value: Y\n    - name: SVPRESP\n      operator: non_empty\nCore:\n  Id: CORE-000037\n  Version: '1'\n  Status: Published\nDescription: Raise an error when SVPRESP not \"Y\" or null.\nOutcome:\n  Message: SVPRESP is not null and not equal to \"Y\". Values should be \"Y\" or null.\nRule Type: Record Data\nSensitivity: Record\nAuthorities:\n  - Organization: CDISC\n    Standards:\n      - Name: SDTMIG\n        Version: '3.4'\n        References:\n          - Origin: SDTM and SDTMIG Conformance Rules\n            Rule Identifier:\n              Id: CG0653\n              Version: '1'\n            Version: '2.0'\n            Citations:\n              - Cited Guidance: Values should be \"Y\" or null.\n                Document: SDTM v2.0\n                Section: Subject Visits\nScope:\n  Classes:\n    Include:\n      - SPECIAL-PURPOSE\n  Domains:\n    Include:\n      - SV\n",
    "created": "2021-10-03T09:18:30Z",
    "creator": {
        "id": "ff471ff8-f131-4cf5-9712-c79cce6301a1"
    },
    "json": {
        "Check": {
            "all": [
                {
                    "name": "SVPRESP",
                    "operator": "not_equal_to",
                    "value": "Y"
                },
                {
                    "name": "SVPRESP",
                    "operator": "non_empty"
                }
            ]
        },
        "Core": {
            "Id": "CORE-000037",
            "Version": "1",
            "Status": "Published"
        },
        "Description": "Raise an error when SVPRESP not \"Y\" or null.",
        "Outcome": {
            "Message": "SVPRESP is not null and not equal to \"Y\". Values should be \"Y\" or null."
        },
        "Rule_Type": "Record Data",
        "Sensitivity": "Record",
        "Authorities": [
            {
                "Organization": "CDISC",
                "Standards": [
                    {
                        "Name": "SDTMIG",
                        "Version": "3.4",
                        "References": [
                            {
                                "Origin": "SDTM and SDTMIG Conformance Rules",
                                "Rule_Identifier": {
                                    "Id": "CG0653",
                                    "Version": "1"
                                },
                                "Version": "2.0",
                                "Citations": [
                                    {
                                        "Cited_Guidance": "Values should be \"Y\" or null.",
                                        "Document": "SDTM v2.0",
                                        "Section": "Subject Visits"
                                    }
                                ]
                            }
                        ]
                    }
                ]
            }
        ],
        "Scope": {
            "Classes": {
                "Include": [
                    "SPECIAL-PURPOSE"
                ]
            },
            "Domains": {
                "Include": [
                    "SV"
                ]
            }
        }
    }
}