{
    "id": "388226fc-2ad2-48b4-bf1e-79369a5b11e9",
    "changed": "2022-04-14T01:54:51Z",
    "content": "Check:\n  all:\n    - name: TP\n      operator: exists\nCore:\n  Id: CORE-000043\n  Version: '1'\n  Status: Published\nDescription: Raise an error when TP dataset is present.\nOutcome:\n  Message: TP dataset is present.\nRule Type: Domain Presence Check\nSensitivity: Study\nAuthorities:\n  - Organization: CDISC\n    Standards:\n      - Name: SDTMIG\n        Version: '3.4'\n        References:\n          - Origin: SDTM and SDTMIG Conformance Rules\n            Rule Identifier:\n              Id: CG0648\n              Version: '1'\n            Version: '2.0'\n            Citations:\n              - Cited Guidance: The TP dataset must not be used in human clinical\n                  trials.\n                Document: SDTM v2.0\n                Section: Trial Repro Paths\nScope:\n  Classes:\n    Include:\n      - ALL\n  Domains:\n    Include:\n      - TP\n",
    "created": "2021-10-03T10:39:47Z",
    "creator": {
        "id": "ff471ff8-f131-4cf5-9712-c79cce6301a1"
    },
    "json": {
        "Check": {
            "all": [
                {
                    "name": "TP",
                    "operator": "exists"
                }
            ]
        },
        "Core": {
            "Id": "CORE-000043",
            "Version": "1",
            "Status": "Published"
        },
        "Description": "Raise an error when TP dataset is present.",
        "Outcome": {
            "Message": "TP dataset is present."
        },
        "Rule_Type": "Domain Presence Check",
        "Sensitivity": "Study",
        "Authorities": [
            {
                "Organization": "CDISC",
                "Standards": [
                    {
                        "Name": "SDTMIG",
                        "Version": "3.4",
                        "References": [
                            {
                                "Origin": "SDTM and SDTMIG Conformance Rules",
                                "Rule_Identifier": {
                                    "Id": "CG0648",
                                    "Version": "1"
                                },
                                "Version": "2.0",
                                "Citations": [
                                    {
                                        "Cited_Guidance": "The TP dataset must not be used in human clinical trials.",
                                        "Document": "SDTM v2.0",
                                        "Section": "Trial Repro Paths"
                                    }
                                ]
                            }
                        ]
                    }
                ]
            }
        ],
        "Scope": {
            "Classes": {
                "Include": [
                    "ALL"
                ]
            },
            "Domains": {
                "Include": [
                    "TP"
                ]
            }
        }
    }
}