{
    "id": "b376f7e6-0bfb-4eac-b790-6a5a3431b723",
    "changed": "2022-08-04T15:51:07Z",
    "content": "Check:\n  all:\n    - name: TSVAL\n      operator: non_empty\n    - name: TSVAL\n      operator: is_not_contained_by_case_insensitive\n      value:\n        - NI\n        - INV\n        - DER\n        - OTH\n        - NINF\n        - PINF\n        - UNC\n        - MSK\n        - NA\n        - UNK\n        - ASKU\n        - NAV\n        - NASK\n        - NAVU\n        - NAV\n        - QS\n        - TRC\n        - NP\n    - name: TSVALNF\n      operator: non_empty\nCore:\n  Id: CORE-000041\n  Version: '1'\n  Status: Published\nDescription: When TSVAL is not populated with values or synonyms of values in the\n  ISO 21090 null flavor codelist (or other terms that can be represented as null flavors),\n  unless the term is included in published terminology, TSVALNF should be null.\nOutcome:\n  Message: TSVALNF is populated when TSVAL is populated with a value that is not in\n    the ISO 21090 null flavor codelist.\nRule Type: Record Data\nSensitivity: Record\nAuthorities:\n  - Organization: CDISC\n    Standards:\n      - Name: SDTMIG\n        Version: '3.4'\n        References:\n          - Origin: SDTM and SDTMIG Conformance Rules\n            Rule Identifier:\n              Id: CG0649\n              Version: '1'\n            Version: '2.0'\n            Citations:\n              - Cited Guidance: Some codelists used for TSVAL include terms which\n                  are also null flavors. For example, the Pharmaceutical Dosage Form\n                  codelist includes the values 'UNKNOWN' and 'NOT APPLICABLE. In such\n                  cases, TSVAL should have the term from the codelist and TSVALNF\n                  should be null.\n                Document: SDTMIG v3.4\n                Item: Assumption 11\n                Section: 7.4.2\n              - Cited Guidance: While it would be possible to allow a value such as\n                  NONE or UNBOUNDED to be entered in TSVAL,  validation programs would\n                  then have to recognize this special term as an exception to the\n                  expected data format. Therefore, it was decided that a separate\n                  null flavor variable that uses the ISO 21090 null flavor terminology\n                  would be a better solution.\n                Document: SDTMIG v3.4\n                Section: 7.4.2.1\nScope:\n  Classes:\n    Include:\n      - TRIAL DESIGN\n  Domains:\n    Include:\n      - TS\n",
    "created": "2021-10-03T10:17:20Z",
    "creator": {
        "id": "ff471ff8-f131-4cf5-9712-c79cce6301a1"
    },
    "json": {
        "Check": {
            "all": [
                {
                    "name": "TSVAL",
                    "operator": "non_empty"
                },
                {
                    "name": "TSVAL",
                    "operator": "is_not_contained_by_case_insensitive",
                    "value": [
                        "NI",
                        "INV",
                        "DER",
                        "OTH",
                        "NINF",
                        "PINF",
                        "UNC",
                        "MSK",
                        "NA",
                        "UNK",
                        "ASKU",
                        "NAV",
                        "NASK",
                        "NAVU",
                        "NAV",
                        "QS",
                        "TRC",
                        "NP"
                    ]
                },
                {
                    "name": "TSVALNF",
                    "operator": "non_empty"
                }
            ]
        },
        "Core": {
            "Id": "CORE-000041",
            "Version": "1",
            "Status": "Published"
        },
        "Description": "When TSVAL is not populated with values or synonyms of values in the ISO 21090 null flavor codelist (or other terms that can be represented as null flavors), unless the term is included in published terminology, TSVALNF should be null.",
        "Outcome": {
            "Message": "TSVALNF is populated when TSVAL is populated with a value that is not in the ISO 21090 null flavor codelist."
        },
        "Rule_Type": "Record Data",
        "Sensitivity": "Record",
        "Authorities": [
            {
                "Organization": "CDISC",
                "Standards": [
                    {
                        "Name": "SDTMIG",
                        "Version": "3.4",
                        "References": [
                            {
                                "Origin": "SDTM and SDTMIG Conformance Rules",
                                "Rule_Identifier": {
                                    "Id": "CG0649",
                                    "Version": "1"
                                },
                                "Version": "2.0",
                                "Citations": [
                                    {
                                        "Cited_Guidance": "Some codelists used for TSVAL include terms which are also null flavors. For example, the Pharmaceutical Dosage Form codelist includes the values 'UNKNOWN' and 'NOT APPLICABLE. In such cases, TSVAL should have the term from the codelist and TSVALNF should be null.",
                                        "Document": "SDTMIG v3.4",
                                        "Item": "Assumption 11",
                                        "Section": "7.4.2"
                                    },
                                    {
                                        "Cited_Guidance": "While it would be possible to allow a value such as NONE or UNBOUNDED to be entered in TSVAL,  validation programs would then have to recognize this special term as an exception to the expected data format. Therefore, it was decided that a separate null flavor variable that uses the ISO 21090 null flavor terminology would be a better solution.",
                                        "Document": "SDTMIG v3.4",
                                        "Section": "7.4.2.1"
                                    }
                                ]
                            }
                        ]
                    }
                ]
            }
        ],
        "Scope": {
            "Classes": {
                "Include": [
                    "TRIAL DESIGN"
                ]
            },
            "Domains": {
                "Include": [
                    "TS"
                ]
            }
        }
    }
}