{
    "id": "af0689f6-9ad7-4373-81da-1a0fa80e5f97",
    "changed": "2022-03-17T23:12:12Z",
    "content": "Check:\n  all:\n    - name: --NOMDY\n      operator: exists\nCore:\n  Id: CORE-000062\n  Version: '1'\n  Status: Published\nDescription: Raise an error when --NOMDY is present.\nOutcome:\n  Message: --NOMDY is present.\nRule Type: Record Data\nSensitivity: Dataset\nAuthorities:\n  - Organization: CDISC\n    Standards:\n      - Name: SDTMIG\n        Version: '3.4'\n        References:\n          - Origin: SDTM and SDTMIG Conformance Rules\n            Rule Identifier:\n              Id: CG0635\n              Version: '1'\n            Version: '2.0'\n            Citations:\n              - Cited Guidance: --NOMDY is not be used in human clinical trials.\n                Document: SDTM v2.0\n                Section: Timing\nScope:\n  Classes:\n    Include:\n      - ALL\n  Domains:\n    Include:\n      - ALL\n",
    "created": "2021-10-04T04:57:30Z",
    "creator": {
        "id": "ff471ff8-f131-4cf5-9712-c79cce6301a1"
    },
    "json": {
        "Check": {
            "all": [
                {
                    "name": "--NOMDY",
                    "operator": "exists"
                }
            ]
        },
        "Core": {
            "Id": "CORE-000062",
            "Version": "1",
            "Status": "Published"
        },
        "Description": "Raise an error when --NOMDY is present.",
        "Outcome": {
            "Message": "--NOMDY is present."
        },
        "Rule_Type": "Record Data",
        "Sensitivity": "Dataset",
        "Authorities": [
            {
                "Organization": "CDISC",
                "Standards": [
                    {
                        "Name": "SDTMIG",
                        "Version": "3.4",
                        "References": [
                            {
                                "Origin": "SDTM and SDTMIG Conformance Rules",
                                "Rule_Identifier": {
                                    "Id": "CG0635",
                                    "Version": "1"
                                },
                                "Version": "2.0",
                                "Citations": [
                                    {
                                        "Cited_Guidance": "--NOMDY is not be used in human clinical trials.",
                                        "Document": "SDTM v2.0",
                                        "Section": "Timing"
                                    }
                                ]
                            }
                        ]
                    }
                ]
            }
        ],
        "Scope": {
            "Classes": {
                "Include": [
                    "ALL"
                ]
            },
            "Domains": {
                "Include": [
                    "ALL"
                ]
            }
        }
    }
}