{
    "id": "fbfa116e-6417-4dba-932f-4fd609197aef",
    "changed": "2022-02-15T21:32:30Z",
    "content": "Check:\n  all:\n    - name: MBTEST\n      operator: not_equal_to\n      value:\nCore:\n  Id: CDISC.SDTMIG.CG0607\n  Version: '1'\n  Status: Draft\nDescription: Verify MBTEST equals the name of the organism/antigen targeted by the\n  identification assay.\nOutcome:\n  Message: Test targets an organism, group of organisms, or antigen, but MBTEST is\n    not the name of the  organism/antigen.\nRule Type: Range and limit\nSensitivity: Record\nAuthorities:\n  - Organization: CDISC\n    Standards:\n      - Name: SDTMIG\n        Version: '3.4'\n        References:\n          - Origin: SDTM and SDTMIG Conformance Rules\n            Rule Identifier:\n              Id: CG0607\n              Version: '1'\n            Version: '2.0'\n            Citations:\n              - Cited Guidance: In cases of tests that target an organism, group of\n                  organisms, or antigen for  identification, MBTEST equals the name\n                  of the organism/antigen targeted  by the identification assay.\n                Document: SDTMIG v3.4\n                Item: Assumption 1\n                Section: 6.3.5.7.1\nScope:\n  Classes:\n    Include:\n      - FINDINGS\n  Domains:\n    Include:\n      - MB\n",
    "created": "2021-11-10T22:44:25Z",
    "creator": {
        "id": "f9333394-14e8-48f3-9a3a-62f1e3cf098c"
    },
    "json": {
        "Check": {
            "all": [
                {
                    "name": "MBTEST",
                    "operator": "not_equal_to",
                    "value": null
                }
            ]
        },
        "Core": {
            "Id": "CDISC.SDTMIG.CG0607",
            "Version": "1",
            "Status": "Draft"
        },
        "Description": "Verify MBTEST equals the name of the organism/antigen targeted by the identification assay.",
        "Outcome": {
            "Message": "Test targets an organism, group of organisms, or antigen, but MBTEST is not the name of the  organism/antigen."
        },
        "Rule_Type": "Range and limit",
        "Sensitivity": "Record",
        "Authorities": [
            {
                "Organization": "CDISC",
                "Standards": [
                    {
                        "Name": "SDTMIG",
                        "Version": "3.4",
                        "References": [
                            {
                                "Origin": "SDTM and SDTMIG Conformance Rules",
                                "Rule_Identifier": {
                                    "Id": "CG0607",
                                    "Version": "1"
                                },
                                "Version": "2.0",
                                "Citations": [
                                    {
                                        "Cited_Guidance": "In cases of tests that target an organism, group of organisms, or antigen for  identification, MBTEST equals the name of the organism/antigen targeted  by the identification assay.",
                                        "Document": "SDTMIG v3.4",
                                        "Item": "Assumption 1",
                                        "Section": "6.3.5.7.1"
                                    }
                                ]
                            }
                        ]
                    }
                ]
            }
        ],
        "Scope": {
            "Classes": {
                "Include": [
                    "FINDINGS"
                ]
            },
            "Domains": {
                "Include": [
                    "MB"
                ]
            }
        }
    }
}