{
    "id": "e536b883-15df-42fa-a455-8328dcffbda1",
    "changed": "2022-02-15T21:31:51Z",
    "content": "Check:\n  all:\n    - name: --DECOD\n      operator: empty\n    - name:\n      operator:\n    - name:\n      operator:\nCore:\n  Id: CDISC.SDTMIG.CG0601\n  Version: '1'\n  Status: Draft\nDescription: Verify that for finding collected in a \\\"Other, specify\\\" CRF field a\n  related parent record exist\nOutcome:\n  Message:\nRule Type: Record Data\nSensitivity: Record\nAuthorities:\n  - Organization: CDISC\n    Standards:\n      - Name: SDTMIG\n        Version: '3.4'\n        References:\n          - Origin: SDTM and SDTMIG Conformance Rules\n            Rule Identifier:\n              Id: CG0601\n              Version: '1'\n            Version: '2.0'\n            Citations:\n              - Cited Guidance: When findings are collected about an event or intervention,\n                  and the name of the event or intervention is collected in an\u00a0\\\"Other,\n                  specify\\\" CRF field, the value in --OBJ variable depends on whether\n                  the FA record has a parent\u00a0record and whether the \\\"Other, specify\\\"\n                  value was coded.\n                Document: IG v3.4\n                Section: 4.2.7.4\nScope:\n  Classes:\n    Include:\n      - FINDINGS ABOUT\n  Domains:\n    Include:\n      - ALL\n",
    "created": "2022-01-06T12:52:23Z",
    "creator": {
        "id": "fd0c5f6f-7bc8-40a2-a9f9-9bbcf77833b9"
    },
    "json": {
        "Check": {
            "all": [
                {
                    "name": "--DECOD",
                    "operator": "empty"
                },
                {
                    "name": null,
                    "operator": null
                },
                {
                    "name": null,
                    "operator": null
                }
            ]
        },
        "Core": {
            "Id": "CDISC.SDTMIG.CG0601",
            "Version": "1",
            "Status": "Draft"
        },
        "Description": "Verify that for finding collected in a \\\"Other, specify\\\" CRF field a related parent record exist",
        "Outcome": {
            "Message": null
        },
        "Rule_Type": "Record Data",
        "Sensitivity": "Record",
        "Authorities": [
            {
                "Organization": "CDISC",
                "Standards": [
                    {
                        "Name": "SDTMIG",
                        "Version": "3.4",
                        "References": [
                            {
                                "Origin": "SDTM and SDTMIG Conformance Rules",
                                "Rule_Identifier": {
                                    "Id": "CG0601",
                                    "Version": "1"
                                },
                                "Version": "2.0",
                                "Citations": [
                                    {
                                        "Cited_Guidance": "When findings are collected about an event or intervention, and the name of the event or intervention is collected in an\u00a0\\\"Other, specify\\\" CRF field, the value in --OBJ variable depends on whether the FA record has a parent\u00a0record and whether the \\\"Other, specify\\\" value was coded.",
                                        "Document": "IG v3.4",
                                        "Section": "4.2.7.4"
                                    }
                                ]
                            }
                        ]
                    }
                ]
            }
        ],
        "Scope": {
            "Classes": {
                "Include": [
                    "FINDINGS ABOUT"
                ]
            },
            "Domains": {
                "Include": [
                    "ALL"
                ]
            }
        }
    }
}