{
    "id": "ae3f2478-f1b0-4900-9f4c-e8be091ea022",
    "changed": "2022-05-18T20:37:05Z",
    "content": "Check:\n  all:\n    - name: SVPRESP\n      operator: empty\n    - name: VISITDY\n      operator: non_empty\nCore:\n  Id: CORE-000035\n  Version: '1'\n  Status: Published\nDescription: Raise an error when SVPRESP is null and VISITDY is not null.\nOutcome:\n  Message: VISITDY is populated when SVPRESP is null.  VISITDY is the Planned Study\n    Day of a visit. It should not be populated for unplanned visits.\nRule Type: Record Data\nSensitivity: Record\nAuthorities:\n  - Organization: CDISC\n    Standards:\n      - Name: SDTMIG\n        Version: '3.4'\n        References:\n          - Origin: SDTM and SDTMIG Conformance Rules\n            Rule Identifier:\n              Id: CG0658\n              Version: '1'\n            Version: '2.0'\n            Citations:\n              - Cited Guidance: VISITDY is the Planned Study Day of a visit. It should\n                  not be populated for unplanned visits.\n                Document: SDTMIG v3.4\n                Section: '5.5'\nScope:\n  Classes:\n    Include:\n      - SPECIAL-PURPOSE\n  Domains:\n    Include:\n      - SV\n",
    "created": "2021-10-03T08:53:52Z",
    "creator": {
        "id": "ff471ff8-f131-4cf5-9712-c79cce6301a1"
    },
    "json": {
        "Check": {
            "all": [
                {
                    "name": "SVPRESP",
                    "operator": "empty"
                },
                {
                    "name": "VISITDY",
                    "operator": "non_empty"
                }
            ]
        },
        "Core": {
            "Id": "CORE-000035",
            "Version": "1",
            "Status": "Published"
        },
        "Description": "Raise an error when SVPRESP is null and VISITDY is not null.",
        "Outcome": {
            "Message": "VISITDY is populated when SVPRESP is null.  VISITDY is the Planned Study Day of a visit. It should not be populated for unplanned visits."
        },
        "Rule_Type": "Record Data",
        "Sensitivity": "Record",
        "Authorities": [
            {
                "Organization": "CDISC",
                "Standards": [
                    {
                        "Name": "SDTMIG",
                        "Version": "3.4",
                        "References": [
                            {
                                "Origin": "SDTM and SDTMIG Conformance Rules",
                                "Rule_Identifier": {
                                    "Id": "CG0658",
                                    "Version": "1"
                                },
                                "Version": "2.0",
                                "Citations": [
                                    {
                                        "Cited_Guidance": "VISITDY is the Planned Study Day of a visit. It should not be populated for unplanned visits.",
                                        "Document": "SDTMIG v3.4",
                                        "Section": "5.5"
                                    }
                                ]
                            }
                        ]
                    }
                ]
            }
        ],
        "Scope": {
            "Classes": {
                "Include": [
                    "SPECIAL-PURPOSE"
                ]
            },
            "Domains": {
                "Include": [
                    "SV"
                ]
            }
        }
    }
}