{
    "id": "07ab7953-20b0-449e-9c71-ed422dde7a95",
    "changed": "2023-02-09T16:58:26.315Z",
    "content": "Check:\n  all:\n    - name: --ENTPT\n      operator: non_empty\n    - name: --ENRTPT\n      operator: empty\nCore:\n  Id: DEF\n  Version: '1'\n  Status: Draft\nDescription: Raise an error when --ENTPT is completed and --ENRTPT is not completed.\nOutcome:\n  Message: --ENTPT is completed, but --ENRTPT is not completed.\nRule Type: Record Data\nSensitivity: Record\nAuthorities:\n  - Organization: CDISC\n    Standards:\n      - Name: SDTMIG\n        Version: '3.4'\n        References:\n          - Origin: SDTM and SDTMIG Conformance Rules\n            Rule Identifier:\n              Id: Demo\n              Version: '1.0'\n            Version: '2.0'\n            Citations:\n              - Cited Guidance: --> The description or date and/or time of a time point that\n                  acts as a fixed reference for characterizing the end of an\n                  observation. This is the sponsor-defined reference point\n                  referred to by --ENRTPT.\n                Document: Model v2.0\n                Item: --ENTPT\n                Section: Timing\nScope:\n  Classes:\n    Include:\n      - ALL\n  Domains:\n    Include:\n      - ALL\n",
    "created": "2022-01-10T14:37:24Z",
    "creator": {
        "id": "e4113eae-4854-4831-a2f1-a0f1639da65a"
    },
    "json": {
        "Check": {
            "all": [
                {
                    "name": "--ENTPT",
                    "operator": "non_empty"
                },
                {
                    "name": "--ENRTPT",
                    "operator": "empty"
                }
            ]
        },
        "Core": {
            "Id": "DEF",
            "Version": "1",
            "Status": "Draft"
        },
        "Description": "Raise an error when --ENTPT is completed and --ENRTPT is not completed.",
        "Outcome": {
            "Message": "--ENTPT is completed, but --ENRTPT is not completed."
        },
        "Sensitivity": "Record",
        "Authorities": [
            {
                "Organization": "CDISC",
                "Standards": [
                    {
                        "Name": "SDTMIG",
                        "Version": "3.4",
                        "References": [
                            {
                                "Origin": "SDTM and SDTMIG Conformance Rules",
                                "Version": "2.0",
                                "Citations": [
                                    {
                                        "Document": "Model v2.0",
                                        "Item": "--ENTPT",
                                        "Section": "Timing",
                                        "Cited_Guidance": "--> The description or date and/or time of a time point that acts as a fixed reference for characterizing the end of an observation. This is the sponsor-defined reference point referred to by --ENRTPT."
                                    }
                                ],
                                "Rule_Identifier": {
                                    "Id": "Demo",
                                    "Version": "1.0"
                                }
                            }
                        ]
                    }
                ]
            }
        ],
        "Scope": {
            "Classes": {
                "Include": [
                    "ALL"
                ]
            },
            "Domains": {
                "Include": [
                    "ALL"
                ]
            }
        },
        "Rule_Type": "Record Data"
    }
}