{
    "id": "413b4e4d-73c2-4613-bb6c-1421207030d7",
    "changed": "2022-02-15T21:27:41Z",
    "content": "Check:\n  all:\n    - name: --DOSE\n      operator: non_empty\n    - name: --DOSE\n      operator: greater_than_or_equal_to\n      value: 0\nCore:\n  Id: FDA.VALIDATOR.SD0014\n  Version: '1'\n  Status: Draft\nDescription: Raise an error when --DOSE is a negative value\nOutcome:\n  Message: Negative value for --DOSE\nRule Type: Record Data\nSensitivity: Record\nAuthorities:\n  - Organization: FDA\n    Standards:\n      - Name: SDTMIG\n        Version: '3.4'\n        References:\n          - Origin: FDA Validator Rules\n            Rule Identifier:\n              Id: SD0014, Publisher ID FDAB040\n              Version: '1'\n            Version: '1.5'\n            Citations:\n              - Cited Guidance: Non-missing Dose (--DOSE) value must be greater than\n                  or equal to 0.\n                Document: FDA Validator Rules v1.5\n                Section: N/A\nScope:\n  Classes:\n    Include:\n      - INTERVENTIONS\n  Domains:\n    Include:\n      - ALL\n",
    "created": "2021-11-11T23:14:35Z",
    "creator": {
        "id": "ff471ff8-f131-4cf5-9712-c79cce6301a1"
    },
    "json": {
        "Check": {
            "all": [
                {
                    "name": "--DOSE",
                    "operator": "non_empty"
                },
                {
                    "name": "--DOSE",
                    "operator": "greater_than_or_equal_to",
                    "value": 0
                }
            ]
        },
        "Core": {
            "Id": "FDA.VALIDATOR.SD0014",
            "Version": "1",
            "Status": "Draft"
        },
        "Description": "Raise an error when --DOSE is a negative value",
        "Outcome": {
            "Message": "Negative value for --DOSE"
        },
        "Rule_Type": "Record Data",
        "Sensitivity": "Record",
        "Authorities": [
            {
                "Organization": "FDA",
                "Standards": [
                    {
                        "Name": "SDTMIG",
                        "Version": "3.4",
                        "References": [
                            {
                                "Origin": "FDA Validator Rules",
                                "Rule_Identifier": {
                                    "Id": "SD0014, Publisher ID FDAB040",
                                    "Version": "1"
                                },
                                "Version": "1.5",
                                "Citations": [
                                    {
                                        "Cited_Guidance": "Non-missing Dose (--DOSE) value must be greater than or equal to 0.",
                                        "Document": "FDA Validator Rules v1.5",
                                        "Section": "N/A"
                                    }
                                ]
                            }
                        ]
                    }
                ]
            }
        ],
        "Scope": {
            "Classes": {
                "Include": [
                    "INTERVENTIONS"
                ]
            },
            "Domains": {
                "Include": [
                    "ALL"
                ]
            }
        }
    }
}