{
    "id": "9223a799-3676-4702-890a-a2344c3ef0e9",
    "changed": "2022-09-07T13:24:44Z",
    "content": "Check:\n  all:\n    - name: SSSTRESC\n      operator: does_not_use_valid_codelist_terms\n      value: DEAD\n      value_is_literal: true\n    - name: $ds_dsdecod\n      operator: does_not_contain\n      value: DEATH\n      value_is_literal: true\nOperations:\n  - operator: distinct\n    domain: DS\n    name: DSDECOD\n    id: $ds_dsdecod\n    group:\n      - USUBJID\nCore:\n  Id: FDA.SDTMIG.CT2001\n  Version: '1'\n  Status: Draft\nDescription: Variable must be populated with terms from its CDISC controlled terminology\n  codelist. New terms cannot be added into non-extensible codelists.\nOutcome:\n  Message: Variable value not found in non-extensible codelist.\n  Output Variables:\n    - \nRule Type: Record Data\nSensitivity: Record\nAuthorities:\n  - Organization: FDA\n    Standards:\n      - Name: SDTMIG\n        Version: '3.2 '\n        References:\n          - Origin: FDA Business Rules\n            Rule Identifier:\n              Id: FDAB017\n              Version: '1'\n            Version: '1.5'\nScope:\n  Classes:\n    Include:\n      - ALL\n  Domains:\n    Include:\n      - ALL\n",
    "created": "2022-08-19T12:52:51Z",
    "creator": {
        "id": "e44cc128-d0f9-4dda-bec2-453ea0478695"
    },
    "json": {
        "Check": {
            "all": [
                {
                    "name": "SSSTRESC",
                    "operator": "does_not_use_valid_codelist_terms",
                    "value": "DEAD",
                    "value_is_literal": true
                },
                {
                    "name": "$ds_dsdecod",
                    "operator": "does_not_contain",
                    "value": "DEATH",
                    "value_is_literal": true
                }
            ]
        },
        "Operations": [
            {
                "operator": "distinct",
                "domain": "DS",
                "name": "DSDECOD",
                "id": "$ds_dsdecod",
                "group": [
                    "USUBJID"
                ]
            }
        ],
        "Core": {
            "Id": "FDA.SDTMIG.CT2001",
            "Version": "1",
            "Status": "Draft"
        },
        "Description": "Variable must be populated with terms from its CDISC controlled terminology codelist. New terms cannot be added into non-extensible codelists.",
        "Outcome": {
            "Message": "Variable value not found in non-extensible codelist.",
            "Output_Variables": [
                null
            ]
        },
        "Rule_Type": "Record Data",
        "Sensitivity": "Record",
        "Authorities": [
            {
                "Organization": "FDA",
                "Standards": [
                    {
                        "Name": "SDTMIG",
                        "Version": "3.2 ",
                        "References": [
                            {
                                "Origin": "FDA Business Rules",
                                "Rule_Identifier": {
                                    "Id": "FDAB017",
                                    "Version": "1"
                                },
                                "Version": "1.5"
                            }
                        ]
                    }
                ]
            }
        ],
        "Scope": {
            "Classes": {
                "Include": [
                    "ALL"
                ]
            },
            "Domains": {
                "Include": [
                    "ALL"
                ]
            }
        }
    }
}