{
    "id": "935342b7-f8fc-496e-90a3-6f2ff936fdd2",
    "changed": "2022-02-15T21:29:59Z",
    "content": "Check:\n  all:\n    - name: --STDTC\n      operator: non_empty\n    - name: --ENDTC\n      operator: non_empty\n    - name: --STDTC\n      operator: date_greater_than\n      value: --ENDTC\nCore:\n  Id: FDA.VALIDATOR.SD0013\n  Version: '1'\n  Status: Draft\nDescription: Raise an error when --STDTC is after --ENDTC\nOutcome:\n  Message: --STDTC is after --ENDTC\nRule Type: Record Data\nSensitivity: Record\nAuthorities:\n  - Organization: FDA\n    Standards:\n      - Name: SDTMIG\n        Version: '3.4'\n        References:\n          - Origin: FDA Validator Rules\n            Rule Identifier:\n              Id: SD0013, Publisher ID FDAB034\n              Version: '1'\n            Version: '1.5'\n            Citations:\n              - Cited Guidance: Start Date/Time of Event, Exposure or Observation\n                  (--STDTC) must be less or equal to End Date/Time of Event, Exposure\n                  or Observation (--ENDTC).\n                Document: FDA Validator Rules v1.5\n                Section: N/A\nScope:\n  Classes:\n    Include:\n      - INTERVENTIONS\n      - EVENTS\n      - SPECIAL-PURPOSE\n  Domains:\n    Exclude:\n      - CO\n      - DM\n",
    "created": "2021-11-11T23:12:48Z",
    "creator": {
        "id": "ff471ff8-f131-4cf5-9712-c79cce6301a1"
    },
    "json": {
        "Check": {
            "all": [
                {
                    "name": "--STDTC",
                    "operator": "non_empty"
                },
                {
                    "name": "--ENDTC",
                    "operator": "non_empty"
                },
                {
                    "name": "--STDTC",
                    "operator": "date_greater_than",
                    "value": "--ENDTC"
                }
            ]
        },
        "Core": {
            "Id": "FDA.VALIDATOR.SD0013",
            "Version": "1",
            "Status": "Draft"
        },
        "Description": "Raise an error when --STDTC is after --ENDTC",
        "Outcome": {
            "Message": "--STDTC is after --ENDTC"
        },
        "Rule_Type": "Record Data",
        "Sensitivity": "Record",
        "Authorities": [
            {
                "Organization": "FDA",
                "Standards": [
                    {
                        "Name": "SDTMIG",
                        "Version": "3.4",
                        "References": [
                            {
                                "Origin": "FDA Validator Rules",
                                "Rule_Identifier": {
                                    "Id": "SD0013, Publisher ID FDAB034",
                                    "Version": "1"
                                },
                                "Version": "1.5",
                                "Citations": [
                                    {
                                        "Cited_Guidance": "Start Date/Time of Event, Exposure or Observation (--STDTC) must be less or equal to End Date/Time of Event, Exposure or Observation (--ENDTC).",
                                        "Document": "FDA Validator Rules v1.5",
                                        "Section": "N/A"
                                    }
                                ]
                            }
                        ]
                    }
                ]
            }
        ],
        "Scope": {
            "Classes": {
                "Include": [
                    "INTERVENTIONS",
                    "EVENTS",
                    "SPECIAL-PURPOSE"
                ]
            },
            "Domains": {
                "Exclude": [
                    "CO",
                    "DM"
                ]
            }
        }
    }
}