{
    "id": "b0ffaebd-8544-48d7-91e9-13dcad421cdc",
    "changed": "2022-02-15T21:30:34Z",
    "content": "Check:\n  all:\n    - name: --DTC\n      operator: non_empty\n    - name: --ENDTC\n      operator: non_empty\n    - name: --DTC\n      operator: date_greater_than\n      value: --ENDTC\nCore:\n  Id: FDA.VALIDATOR.SD0025\n  Version: '1'\n  Status: Draft\nDescription: Raise an error when --DTC is after --ENDTC\nOutcome:\n  Message: --DTC is after --ENDTC\nRule Type: Record Data\nSensitivity: Record\nAuthorities:\n  - Organization: FDA\n    Standards:\n      - Name: SDTMIG\n        Version: '3.4'\n        References:\n          - Origin: FDA Validator Rules\n            Rule Identifier:\n              Id: SD0025, Publisher ID FDAB034\n              Version: '1'\n            Version: '1.5'\n            Citations:\n              - Cited Guidance: Date/Time of Specimen Collection (--DTC) must be less\n                  or equal to End Date/Time of Specimen Collection (--ENDTC).\n                Document: FDA Validator Rules v1.5\nScope:\n  Classes:\n    Include:\n      - FINDINGS\n      - FINDINGS ABOUT\n  Domains:\n    Include:\n      - ALL\n",
    "created": "2021-11-11T23:18:35Z",
    "creator": {
        "id": "ff471ff8-f131-4cf5-9712-c79cce6301a1"
    },
    "json": {
        "Check": {
            "all": [
                {
                    "name": "--DTC",
                    "operator": "non_empty"
                },
                {
                    "name": "--ENDTC",
                    "operator": "non_empty"
                },
                {
                    "name": "--DTC",
                    "operator": "date_greater_than",
                    "value": "--ENDTC"
                }
            ]
        },
        "Core": {
            "Id": "FDA.VALIDATOR.SD0025",
            "Version": "1",
            "Status": "Draft"
        },
        "Description": "Raise an error when --DTC is after --ENDTC",
        "Outcome": {
            "Message": "--DTC is after --ENDTC"
        },
        "Rule_Type": "Record Data",
        "Sensitivity": "Record",
        "Authorities": [
            {
                "Organization": "FDA",
                "Standards": [
                    {
                        "Name": "SDTMIG",
                        "Version": "3.4",
                        "References": [
                            {
                                "Origin": "FDA Validator Rules",
                                "Rule_Identifier": {
                                    "Id": "SD0025, Publisher ID FDAB034",
                                    "Version": "1"
                                },
                                "Version": "1.5",
                                "Citations": [
                                    {
                                        "Cited_Guidance": "Date/Time of Specimen Collection (--DTC) must be less or equal to End Date/Time of Specimen Collection (--ENDTC).",
                                        "Document": "FDA Validator Rules v1.5"
                                    }
                                ]
                            }
                        ]
                    }
                ]
            }
        ],
        "Scope": {
            "Classes": {
                "Include": [
                    "FINDINGS",
                    "FINDINGS ABOUT"
                ]
            },
            "Domains": {
                "Include": [
                    "ALL"
                ]
            }
        }
    }
}