{
    "id": "0ab2f337-93e1-4bcc-902e-f24394b4fe82",
    "changed": "2022-02-15T21:11:46Z",
    "content": "Check:\n  all:\n    - name: --DUR\n      operator: non_empty\n    - name: --DUR\n      operator: greater_than_or_equal_to\n      value: 0\nCore:\n  Id: FDA.VALIDATOR.SD0015\n  Version: '1'\n  Status: Draft\nDescription: Raise an error when --DUR is a negative value\nOutcome:\n  Message: Negative value for --DUR\nRule Type: Record Data\nSensitivity: Record\nAuthorities:\n  - Organization: FDA\n    Standards:\n      - Name: SDTMIG\n        Version: '3.4'\n        References:\n          - Origin: FDA Validator Rules\n            Rule Identifier:\n              Id: SD0015,Publisher ID FDAB040\n              Version: '1'\n            Version: '1.5'\n            Citations:\n              - Cited Guidance: Non-missing Duration of Event, Exposure or Observation\n                  (--DUR) value must be greater than or equal to 0.\n                Document: FDA Validator Rules v1.5\n                Section: N/A\nScope:\n  Classes:\n    Include:\n      - INTERVENTIONS\n      - EVENTS\n      - FINDINGS\n      - FINDINGS ABOUT\n      - TRIAL DESIGN\n      - SPECIAL-PURPOSE\n  Domains:\n    Exclude:\n      - CO\n      - DM\n      - TS\n      - TD\n      - TM\n      - TI\n      - TV\n",
    "created": "2021-11-11T23:16:59Z",
    "creator": {
        "id": "ff471ff8-f131-4cf5-9712-c79cce6301a1"
    },
    "json": {
        "Check": {
            "all": [
                {
                    "name": "--DUR",
                    "operator": "non_empty"
                },
                {
                    "name": "--DUR",
                    "operator": "greater_than_or_equal_to",
                    "value": 0
                }
            ]
        },
        "Core": {
            "Id": "FDA.VALIDATOR.SD0015",
            "Version": "1",
            "Status": "Draft"
        },
        "Description": "Raise an error when --DUR is a negative value",
        "Outcome": {
            "Message": "Negative value for --DUR"
        },
        "Rule_Type": "Record Data",
        "Sensitivity": "Record",
        "Authorities": [
            {
                "Organization": "FDA",
                "Standards": [
                    {
                        "Name": "SDTMIG",
                        "Version": "3.4",
                        "References": [
                            {
                                "Origin": "FDA Validator Rules",
                                "Rule_Identifier": {
                                    "Id": "SD0015,Publisher ID FDAB040",
                                    "Version": "1"
                                },
                                "Version": "1.5",
                                "Citations": [
                                    {
                                        "Cited_Guidance": "Non-missing Duration of Event, Exposure or Observation (--DUR) value must be greater than or equal to 0.",
                                        "Document": "FDA Validator Rules v1.5",
                                        "Section": "N/A"
                                    }
                                ]
                            }
                        ]
                    }
                ]
            }
        ],
        "Scope": {
            "Classes": {
                "Include": [
                    "INTERVENTIONS",
                    "EVENTS",
                    "FINDINGS",
                    "FINDINGS ABOUT",
                    "TRIAL DESIGN",
                    "SPECIAL-PURPOSE"
                ]
            },
            "Domains": {
                "Exclude": [
                    "CO",
                    "DM",
                    "TS",
                    "TD",
                    "TM",
                    "TI",
                    "TV"
                ]
            }
        }
    }
}