{
    "id": "e7539c87-c5b5-493c-97c9-adae559787d6",
    "changed": "2022-02-15T21:31:58Z",
    "content": "Check:\n  all:\n    - name: --DTC\n      operator: empty\n    - name: --ENDTC\n      operator: non_empty\nCore:\n  Id: FDA.VALIDATOR.SD0024\n  Version: '1'\n  Status: Draft\nDescription: Raise an error when --ENDTC is provided and --DTC is missing\nOutcome:\n  Message: Missing value for --DTC, when --ENDTC is provided\nRule Type: Record Data\nSensitivity: Record\nAuthorities:\n  - Organization: FDA\n    Standards:\n      - Name: SDTMIG\n        Version: '3.4'\n        References:\n          - Origin: FDA Validator Rules\n            Rule Identifier:\n              Id: SD0024, Publisher ID FDAB043\n              Version: '1'\n            Version: '1.5'\n            Citations:\n              - Cited Guidance: Date/Time of Collection (--DTC) should not be NULL,\n                  when End Date/Time of Observation (--ENDTC) is not NULL.\n                Document: FDA Validator Rules v1.5\n                Section: Validator Rules\nScope:\n  Classes:\n    Include:\n      - FINDINGS\n      - FINDINGS ABOUT\n  Domains:\n    Include:\n      - ALL\n",
    "created": "2021-11-11T23:20:00Z",
    "creator": {
        "id": "ff471ff8-f131-4cf5-9712-c79cce6301a1"
    },
    "json": {
        "Check": {
            "all": [
                {
                    "name": "--DTC",
                    "operator": "empty"
                },
                {
                    "name": "--ENDTC",
                    "operator": "non_empty"
                }
            ]
        },
        "Core": {
            "Id": "FDA.VALIDATOR.SD0024",
            "Version": "1",
            "Status": "Draft"
        },
        "Description": "Raise an error when --ENDTC is provided and --DTC is missing",
        "Outcome": {
            "Message": "Missing value for --DTC, when --ENDTC is provided"
        },
        "Rule_Type": "Record Data",
        "Sensitivity": "Record",
        "Authorities": [
            {
                "Organization": "FDA",
                "Standards": [
                    {
                        "Name": "SDTMIG",
                        "Version": "3.4",
                        "References": [
                            {
                                "Origin": "FDA Validator Rules",
                                "Rule_Identifier": {
                                    "Id": "SD0024, Publisher ID FDAB043",
                                    "Version": "1"
                                },
                                "Version": "1.5",
                                "Citations": [
                                    {
                                        "Cited_Guidance": "Date/Time of Collection (--DTC) should not be NULL, when End Date/Time of Observation (--ENDTC) is not NULL.",
                                        "Document": "FDA Validator Rules v1.5",
                                        "Section": "Validator Rules"
                                    }
                                ]
                            }
                        ]
                    }
                ]
            }
        ],
        "Scope": {
            "Classes": {
                "Include": [
                    "FINDINGS",
                    "FINDINGS ABOUT"
                ]
            },
            "Domains": {
                "Include": [
                    "ALL"
                ]
            }
        }
    }
}