{
    "id": "13282606-6208-431f-a03b-18701472b50c",
    "changed": "2023-02-06T20:21:06.472Z",
    "content": "Check:\r\n  all:\r\n    - name: SSSTRESC\r\n      operator: equal_to\r\n      value: DEAD\r\n      value_is_literal: true\r\n    - name: $ds_dsdecod\r\n      operator: does_not_contain\r\n      value: DEATH\r\n      value_is_literal: true\r\nOperations:\r\n  - operator: distinct\r\n    domain: DS\r\n    name: DSDECOD\r\n    id: $ds_dsdecod\r\n    group:\r\n      - USUBJID\r\nCore:\r\n  Id: NA\r\n  Version: '1'\r\n  Status: Draft\r\nDescription: Raise an error when SS.SSSTRESC = \"DEAD\" and DSDECOD ^= \"DEATH\".\r\nOutcome:\r\n  Message: DSDECOD is not \"DEATH\", When SS.SSSTRESC = \"DEAD\".\r\n  Output Variables:\r\n    - SSSTRESC\r\nRule Type: Record Data\r\nSensitivity: Record\r\nAuthorities:\r\n  - Organization: CDISC - something new\r\n    Standards:\r\n      - Name: SDTMIG\r\n        Version: '3.4'\r\n        References:\r\n          - Origin: SDTM and SDTMIG Conformance Rules\r\n            Rule Identifier:\r\n              Id: CG0067\r\n              Version: '1'\r\n            Version: '2.0'\r\n            Citations:\r\n              - Cited Guidance: For example, if a subject's survival status is \"DEAD\", the date\r\n                  of death must be stored in DM and within a final disposition\r\n                  record in DS.\r\n                Document: IG v3.4\r\n                Item: Assumption 1\r\n                Section: 6.3.11\r\nScope:\r\n  Classes:\r\n    Include:\r\n      - FINDINGS\r\n  Domains:\r\n    Include:\r\n      - SS\r\n",
    "created": "2022-03-10T16:55:51Z",
    "creator": {
        "id": "e4113eae-4854-4831-a2f1-a0f1639da65a"
    },
    "json": {
        "Check": {
            "all": [
                {
                    "name": "SSSTRESC",
                    "operator": "equal_to",
                    "value": "DEAD",
                    "value_is_literal": true
                },
                {
                    "name": "$ds_dsdecod",
                    "operator": "does_not_contain",
                    "value": "DEATH",
                    "value_is_literal": true
                }
            ]
        },
        "Operations": [
            {
                "operator": "distinct",
                "domain": "DS",
                "name": "DSDECOD",
                "id": "$ds_dsdecod",
                "group": [
                    "USUBJID"
                ]
            }
        ],
        "Core": {
            "Id": "NA",
            "Version": "1",
            "Status": "Draft"
        },
        "Description": "Raise an error when SS.SSSTRESC = \"DEAD\" and DSDECOD ^= \"DEATH\".",
        "Outcome": {
            "Message": "DSDECOD is not \"DEATH\", When SS.SSSTRESC = \"DEAD\".",
            "Output_Variables": [
                "SSSTRESC"
            ]
        },
        "Sensitivity": "Record",
        "Authorities": [
            {
                "Organization": "CDISC - something new",
                "Standards": [
                    {
                        "Name": "SDTMIG",
                        "Version": "3.4",
                        "References": [
                            {
                                "Origin": "SDTM and SDTMIG Conformance Rules",
                                "Version": "2.0",
                                "Citations": [
                                    {
                                        "Document": "IG v3.4",
                                        "Item": "Assumption 1",
                                        "Section": "6.3.11",
                                        "Cited_Guidance": "For example, if a subject's survival status is \"DEAD\", the date of death must be stored in DM and within a final disposition record in DS."
                                    }
                                ],
                                "Rule_Identifier": {
                                    "Id": "CG0067",
                                    "Version": "1"
                                }
                            }
                        ]
                    }
                ]
            }
        ],
        "Scope": {
            "Classes": {
                "Include": [
                    "FINDINGS"
                ]
            },
            "Domains": {
                "Include": [
                    "SS"
                ]
            }
        },
        "Rule_Type": "Record Data"
    }
}