{
    "id": "02b0e7e7-9acc-402f-a270-173669ec415d",
    "changed": "2023-01-12T16:46:49.865Z",
    "content": "Check:\n  all:\n    - name: --SEQ\n      operator: greater_than\n      value: 0\nCore:\n  Id: QC.shorter_than_or_equal_to\n  Version: '1'\n  Status: Draft\nDescription: Nil\nOutcome:\n  Message: Nil\nRule Type: Record Data\nSensitivity: Record\nAuthorities:\n  - Organization: CDISC\n    Standards:\n      - Name: SDTMIG\n        Version: '3.4'\n        References:\n          - Origin: SDTM and SDTMIG Conformance Rules\n            Rule Identifier:\n              Id: Nil\n              Version: Nil\n            Version: 1\n            Citations:\n              - Cited Guidance: Nil\n                Document: Nil\n                Item: Nil\n                Section: Nil\nScope:\n  Classes:\n    Include:\n      - ALL\n  Domains:\n    Include:\n      - ALL\n",
    "created": "2021-09-23T15:30:01Z",
    "creator": {
        "id": "b5bc818b-4ec4-4952-951f-0fbca010be52"
    },
    "json": {
        "Check": {
            "all": [
                {
                    "name": "--SEQ",
                    "operator": "greater_than",
                    "value": 0
                }
            ]
        },
        "Core": {
            "Id": "QC.shorter_than_or_equal_to",
            "Version": "1",
            "Status": "Draft"
        },
        "Description": "Nil",
        "Outcome": {
            "Message": "Nil"
        },
        "Rule_Type": "Record Data",
        "Sensitivity": "Record",
        "Authorities": [
            {
                "Organization": "CDISC",
                "Standards": [
                    {
                        "Name": "SDTMIG",
                        "Version": "3.4",
                        "References": [
                            {
                                "Origin": "SDTM and SDTMIG Conformance Rules",
                                "Rule_Identifier": {
                                    "Id": "Nil",
                                    "Version": "Nil"
                                },
                                "Version": 1,
                                "Citations": [
                                    {
                                        "Cited_Guidance": "Nil",
                                        "Document": "Nil",
                                        "Item": "Nil",
                                        "Section": "Nil"
                                    }
                                ]
                            }
                        ]
                    }
                ]
            }
        ],
        "Scope": {
            "Classes": {
                "Include": [
                    "ALL"
                ]
            },
            "Domains": {
                "Include": [
                    "ALL"
                ]
            }
        }
    }
}