{
    "id": "6566949b-f40d-4ca0-a50e-d244c7f65964",
    "created": "2021-11-06T09:33:06Z",
    "changed": "2023-03-17T15:41:53Z",
    "creator": {
        "id": "dd0f9aa3-68f9-4825-84a4-86c8303daaff"
    },
    "content": "changed: '2023-03-17T15:41:53Z'\ncontent: null\ncreated: '2021-11-06T09:33:06Z'\ncreator:\n  id: dd0f9aa3-68f9-4825-84a4-86c8303daaff\nid: 6566949b-f40d-4ca0-a50e-d244c7f65964\njson:\n  Authorities:\n  - Organization: CDISC\n    Standards:\n    - Name: SDTMIG\n      References:\n      - Citations:\n        - Cited_Guidance: Dictionary or sponsor-defined derived text description of\n            the topic variable; --TERM; or the modified topic variable (--MODIFY);\n            if applicable. Equivalent to the Preferred Term (PT in MedDRA).\n          Document: Model v1.4\n          Item: ''\n          Section: 2.2.1\n        Origin: SDTM and SDTMIG Conformance Rules\n        Rule_Identifier:\n          Id: CG0379\n          Version: '1'\n        Version: '2.0'\n      Version: '3.2'\n    - Name: SDTMIG\n      References:\n      - Citations:\n        - Cited_Guidance: Dictionary or sponsor-defined derived text description of\n            the topic variable; --TERM; or the modified topic variable (--MODIFY);\n            if applicable. Equivalent to the Preferred Term (PT in MedDRA).\n          Document: Model v1.7\n          Item: ''\n          Section: 2.2.2\n        Origin: SDTM and SDTMIG Conformance Rules\n        Rule_Identifier:\n          Id: CG0379\n          Version: '1'\n        Version: '2.0'\n      Version: '3.3'\n    - Name: SDTMIG\n      References:\n      - Citations:\n        - Cited_Guidance: Equivalent to the Preferred Term (PT in MedDRA).\n          Document: Model v2.0\n          Item: --DECOD\n          Section: Events\n        Origin: SDTM and SDTMIG Conformance Rules\n        Rule_Identifier:\n          Id: CG0379\n          Version: '1'\n        Version: '2.0'\n      Version: '3.4'\n  Check:\n    Check: null\n  Core:\n    Id: CDISC.SDTMIG.CG0379\n    Status: Draft\n    Version: '1'\n  Description: Trigger error when --DECOD not equal to MedDRA preferred TERM\n  Executability: null\n  Outcome:\n    Message: --DECOD not equal to MedDRA preferred TERM\n  Rule_Type: Record Data\n  Scope:\n    Classes:\n      Include:\n      - EVT\n    Domains:\n      Include:\n      - AE\n  Sensitivity: Record\n",
    "json": {
        "Core": {
            "Id": "CDISC.SDTMIG.CG0379",
            "Version": "1",
            "Status": "Draft"
        },
        "Description": "Trigger error when --DECOD not equal to MedDRA preferred TERM",
        "Outcome": {
            "Message": "--DECOD not equal to MedDRA preferred TERM"
        },
        "Rule_Type": "Record Data",
        "Sensitivity": "Record",
        "Authorities": [
            {
                "Organization": "CDISC",
                "Standards": [
                    {
                        "Name": "SDTMIG",
                        "Version": "3.2",
                        "References": [
                            {
                                "Origin": "SDTM and SDTMIG Conformance Rules",
                                "Rule_Identifier": {
                                    "Id": "CG0379",
                                    "Version": "1"
                                },
                                "Version": "2.0",
                                "Citations": [
                                    {
                                        "Cited_Guidance": "Dictionary or sponsor-defined derived text description of the topic variable; --TERM; or the modified topic variable (--MODIFY); if applicable. Equivalent to the Preferred Term (PT in MedDRA).",
                                        "Document": "Model v1.4",
                                        "Item": "",
                                        "Section": "2.2.1"
                                    }
                                ]
                            }
                        ]
                    },
                    {
                        "Name": "SDTMIG",
                        "Version": "3.3",
                        "References": [
                            {
                                "Origin": "SDTM and SDTMIG Conformance Rules",
                                "Rule_Identifier": {
                                    "Id": "CG0379",
                                    "Version": "1"
                                },
                                "Version": "2.0",
                                "Citations": [
                                    {
                                        "Cited_Guidance": "Dictionary or sponsor-defined derived text description of the topic variable; --TERM; or the modified topic variable (--MODIFY); if applicable. Equivalent to the Preferred Term (PT in MedDRA).",
                                        "Document": "Model v1.7",
                                        "Item": "",
                                        "Section": "2.2.2"
                                    }
                                ]
                            }
                        ]
                    },
                    {
                        "Name": "SDTMIG",
                        "Version": "3.4",
                        "References": [
                            {
                                "Origin": "SDTM and SDTMIG Conformance Rules",
                                "Rule_Identifier": {
                                    "Id": "CG0379",
                                    "Version": "1"
                                },
                                "Version": "2.0",
                                "Citations": [
                                    {
                                        "Cited_Guidance": "Equivalent to the Preferred Term (PT in MedDRA).",
                                        "Document": "Model v2.0",
                                        "Item": "--DECOD",
                                        "Section": "Events"
                                    }
                                ]
                            }
                        ]
                    }
                ]
            }
        ],
        "Scope": {
            "Classes": {
                "Include": [
                    "EVT"
                ]
            },
            "Domains": {
                "Include": [
                    "AE"
                ]
            }
        },
        "Executability": null,
        "Check": {
            "Check": null
        }
    }
}