{
    "id": "abcffc09-b50f-46a2-bea0-0baba8d3e3c1",
    "created": "2021-11-06T09:44:41Z",
    "changed": "2023-03-15T16:53:41Z",
    "creator": {
        "id": "dd0f9aa3-68f9-4825-84a4-86c8303daaff"
    },
    "content": "changed: '2023-03-15T16:53:41Z'\ncontent: null\ncreated: '2021-11-06T09:44:41Z'\ncreator:\n  id: dd0f9aa3-68f9-4825-84a4-86c8303daaff\nid: abcffc09-b50f-46a2-bea0-0baba8d3e3c1\njson:\n  Authorities:\n  - Organization: CDISC\n    Standards:\n    - Name: SDTMIG\n      References:\n      - Citations:\n        - Cited_Guidance: There is a one-to-one correspondence between a domain dataset\n            and it's Supplemental Qualifier dataset by creating one SUPPQUAL for each\n            domain dataset. The single SUPPQUAL dataset option that was introduced\n            in SDTMIG v3.1.1 is now deprecated. The set of Supplemental Qualifiers\n            for each domain is included in a separate dataset with the name SUPP--\n            where '--' denotes the source domain which the supplemental Qualifiers\n            relate back to.\n          Document: IG v3.2\n          Item: ''\n          Section: 8.4.2\n        Origin: SDTM and SDTMIG Conformance Rules\n        Rule_Identifier:\n          Id: CG0373\n          Version: '1'\n        Version: '2.0'\n      Version: '3.2'\n    - Name: SDTMIG\n      References:\n      - Citations:\n        - Cited_Guidance: There is a one-to-one correspondence between a domain dataset\n            and its Supplemental Qualifier dataset. The single SUPPQUAL dataset option\n            that was introduced in SDTMIG v3.1 was deprecated. The set of Supplemental\n            Qualifiers for each domain is included in a separate dataset with the\n            name SUPP-- where \"--\" denotes the source domain which the Supplemental\n            Qualifiers relate back to.\n          Document: IG v3.3\n          Item: ''\n          Section: 8.4.2\n        Origin: SDTM and SDTMIG Conformance Rules\n        Rule_Identifier:\n          Id: CG0373\n          Version: '1'\n        Version: '2.0'\n      Version: '3.3'\n    - Name: SDTMIG\n      References:\n      - Citations:\n        - Cited_Guidance: \"There is a one-to-one correspondence between a domain dataset\\\n            \\ and it's Supplemental Qualifier dataset by creating one SUPPQUAL for\\\n            \\ each domain dataset. The single SUPPQUAL dataset option that was introduced\\\n            \\ in SDTMIG v3.1.1 is now deprecated.  The set of Supplemental Qualifiers\\\n            \\ for each domain is included in a separate dataset with the name SUPP--\\\n            \\ where \\u201C--\\u201C denotes the source domain which the supplemental\\\n            \\ Qualifiers relate back to.\"\n          Document: IG v3.2\n          Item: ''\n          Section: 8.4.2\n        Origin: SDTM and SDTMIG Conformance Rules\n        Rule_Identifier:\n          Id: CG0373\n          Version: '1'\n        Version: '2.0'\n      Version: '3.4'\n  Check:\n    Check: null\n  Core:\n    Id: CDISC.SDTMIG.CG0373\n    Status: Draft\n    Version: '1'\n  Description: Trigger error when Dataset present in study with DOMAIN not equal to\n    SUPP--.RDOMAIN\n  Executability: null\n  Outcome:\n    Message: Dataset present in study with DOMAIN not equal to SUPP--.RDOMAIN\n  Rule_Type: Record Data\n  Scope:\n    Classes:\n      Include:\n      - ALL\n    Domains:\n      Include:\n      - ALL\n  Sensitivity: Record\n",
    "json": {
        "Check": {
            "Check": null
        },
        "Core": {
            "Id": "CDISC.SDTMIG.CG0373",
            "Version": "1",
            "Status": "Draft"
        },
        "Description": "Trigger error when Dataset present in study with DOMAIN not equal to SUPP--.RDOMAIN",
        "Outcome": {
            "Message": "Dataset present in study with DOMAIN not equal to SUPP--.RDOMAIN"
        },
        "Rule_Type": "Record Data",
        "Sensitivity": "Record",
        "Authorities": [
            {
                "Organization": "CDISC",
                "Standards": [
                    {
                        "Name": "SDTMIG",
                        "Version": "3.2",
                        "References": [
                            {
                                "Origin": "SDTM and SDTMIG Conformance Rules",
                                "Rule_Identifier": {
                                    "Id": "CG0373",
                                    "Version": "1"
                                },
                                "Version": "2.0",
                                "Citations": [
                                    {
                                        "Cited_Guidance": "There is a one-to-one correspondence between a domain dataset and it's Supplemental Qualifier dataset by creating one SUPPQUAL for each domain dataset. The single SUPPQUAL dataset option that was introduced in SDTMIG v3.1.1 is now deprecated. The set of Supplemental Qualifiers for each domain is included in a separate dataset with the name SUPP-- where '--' denotes the source domain which the supplemental Qualifiers relate back to.",
                                        "Document": "IG v3.2",
                                        "Item": "",
                                        "Section": "8.4.2"
                                    }
                                ]
                            }
                        ]
                    },
                    {
                        "Name": "SDTMIG",
                        "Version": "3.3",
                        "References": [
                            {
                                "Origin": "SDTM and SDTMIG Conformance Rules",
                                "Rule_Identifier": {
                                    "Id": "CG0373",
                                    "Version": "1"
                                },
                                "Version": "2.0",
                                "Citations": [
                                    {
                                        "Cited_Guidance": "There is a one-to-one correspondence between a domain dataset and its Supplemental Qualifier dataset. The single SUPPQUAL dataset option that was introduced in SDTMIG v3.1 was deprecated. The set of Supplemental Qualifiers for each domain is included in a separate dataset with the name SUPP-- where \"--\" denotes the source domain which the Supplemental Qualifiers relate back to.",
                                        "Document": "IG v3.3",
                                        "Item": "",
                                        "Section": "8.4.2"
                                    }
                                ]
                            }
                        ]
                    },
                    {
                        "Name": "SDTMIG",
                        "Version": "3.4",
                        "References": [
                            {
                                "Origin": "SDTM and SDTMIG Conformance Rules",
                                "Rule_Identifier": {
                                    "Id": "CG0373",
                                    "Version": "1"
                                },
                                "Version": "2.0",
                                "Citations": [
                                    {
                                        "Cited_Guidance": "There is a one-to-one correspondence between a domain dataset and it's Supplemental Qualifier dataset by creating one SUPPQUAL for each domain dataset. The single SUPPQUAL dataset option that was introduced in SDTMIG v3.1.1 is now deprecated.  The set of Supplemental Qualifiers for each domain is included in a separate dataset with the name SUPP-- where \u201c--\u201c denotes the source domain which the supplemental Qualifiers relate back to.",
                                        "Document": "IG v3.2",
                                        "Item": "",
                                        "Section": "8.4.2"
                                    }
                                ]
                            }
                        ]
                    }
                ]
            }
        ],
        "Scope": {
            "Classes": {
                "Include": [
                    "ALL"
                ]
            },
            "Domains": {
                "Include": [
                    "ALL"
                ]
            }
        },
        "Executability": null
    }
}